Workbook

Sheet Revenue Drivers
A1: Revenue Drivers
A2: Source operating drivers. Model Inputs links to these rows.
C4: Stub | D4: Q1 | E4: Q2 | F4: Q3 | G4: Q4 | H4: Q5 | I4: Q6 | J4: Q7 | K4: Q8 | L4: Q9 | M4: Q10 | N4: Q11 | O4: Q12 | P4: Q13 | Q4: Q14 | R4: Q15 | S4: Q16 | T4: Q17 | U4: Q18 | V4: Q19 | W4: Q20 | X4: Y1 | Y4: Y2 | Z4: Y3 | AA4: Y4 | AB4: Y5
C5: 46162 | D5: 46295 | E5: 46387 | F5: 46477 | G5: 46568 | H5: 46660 | I5: 46752 | J5: 46843 | K5: 46934 | L5: 47026 | M5: 47118 | N5: 47208 | O5: 47299 | P5: 47391 | Q5: 47483 | R5: 47573 | S5: 47664 | T5: 47756 | U5: 47848 | V5: 47938 | W5: 48029 | X5: Annual | Y5: Annual | Z5: Annual | AA5: Annual | AB5: Annual
A6: Revenue Driver Source Rows
A7: Primary line of business / Completed repair order
A8: Primary line of business / Completed repair order - Capacity | B8: Source driver | C8: 1495 | D8: 2000 | E8: 2000 | F8: 2000 | G8: 2000 | H8: 2000 | I8: 2000 | J8: 2000 | K8: 2000 | L8: 2000 | M8: 2000 | N8: 2000 | O8: 2000 | P8: 2000 | Q8: 2000 | R8: 2000 | S8: 2000 | T8: 2000 | U8: 2000 | V8: 2000 | W8: 2000
A9: Primary line of business / Completed repair order - Unit Price | B9: Source driver | C9: 625 | D9: 625 | E9: 627.5 | F9: 630 | G9: 632.5 | H9: 635 | I9: 637.5 | J9: 640 | K9: 642.5 | L9: 645 | M9: 647.5 | N9: 650 | O9: 652.77778 | P9: 655.55556 | Q9: 658.33333 | R9: 661.11111 | S9: 663.88889 | T9: 666.66667 | U9: 669.44444 | V9: 672.22222 | W9: 675
A10: Primary line of business / Completed repair order - Utilization | B10: Source driver | C10: 0.82 | D10: 0.82 | E10: 0.822 | F10: 0.824 | G10: 0.826 | H10: 0.828 | I10: 0.83 | J10: 0.832 | K10: 0.834 | L10: 0.836 | M10: 0.838 | N10: 0.84 | O10: 0.84 | P10: 0.84 | Q10: 0.84 | R10: 0.84 | S10: 0.84 | T10: 0.84 | U10: 0.84 | V10: 0.84 | W10: 0.84
A11: Primary line of business / Completed repair order - Revenue | B11: Capacity x Unit Price x Utilization | C11: =C8*C9*C10 | D11: =D8*D9*D10 | E11: =E8*E9*E10 | F11: =F8*F9*F10 | G11: =G8*G9*G10 | H11: =H8*H9*H10 | I11: =I8*I9*I10 | J11: =J8*J9*J10 | ... W11: =W8*W9*W10 | X11: =SUM(D11:G11) | Y11: =SUM(H11:K11) | Z11: =SUM(L11:O11) | AA11: =SUM(P11:S11) | AB11: =SUM(T11:W11)
A13: Total Capacity Units | B13: All revenue driver capacity units | C13: =SUM(C8) | D13: =SUM(D8) | E13: =SUM(E8) | F13: =SUM(F8) | G13: =SUM(G8) | H13: =SUM(H8) | I13: =SUM(I8) | J13: =SUM(J8) | ... W13: =SUM(W8) | X13: =SUM(D13:G13) | Y13: =SUM(H13:K13) | Z13: =SUM(L13:O13) | AA13: =SUM(P13:S13) | AB13: =SUM(T13:W13)
A14: Total Revenue | B14: All revenue products | C14: =SUM(C11) | D14: =SUM(D11) | E14: =SUM(E11) | F14: =SUM(F11) | G14: =SUM(G11) | H14: =SUM(H11) | I14: =SUM(I11) | J14: =SUM(J11) | ... W14: =SUM(W11) | X14: =SUM(D14:G14) | Y14: =SUM(H14:K14) | Z14: =SUM(L14:O14) | AA14: =SUM(P14:S14) | AB14: =SUM(T14:W14)
A16: Stage Ramp Contract
A17: Actual Revenue QoQ Growth | B17: Total revenue growth from modeled revenue drivers | C17: =0 | D17: =IFERROR(D14/C14-1,0) | E17: =IFERROR(E14/D14-1,0) | F17: =IFERROR(F14/E14-1,0) | G17: =IFERROR(G14/F14-1,0) | H17: =IFERROR(H14/G14-1,0) | I17: =IFERROR(I14/H14-1,0) | J17: =IFERROR(J14/I14-1,0) | K17: =IFERROR(K14/J14-1,0) | ... W17: =IFERROR(W14/V14-1,0) | X17: =AVERAGE(D17:G17) | Y17: =AVERAGE(H17:K17) | Z17: =AVERAGE(L17:O17) | AA17: =AVERAGE(P17:S17) | AB17: =AVERAGE(T17:W17)
A18: Stage Ramp Revenue QoQ Target | B18: GPT-selected stage ramp contract | C18: 0 | D18: 0.02 | E18: 0.02 | F18: 0.02 | G18: 0.02 | H18: 0.02 | I18: 0.02 | J18: 0.02 | K18: 0.02 | L18: 0.02 | M18: 0.02 | N18: 0.02 | O18: 0.02 | P18: 0.02 | Q18: 0.02 | R18: 0.02 | S18: 0.02 | T18: 0.02 | U18: 0.02 | V18: 0.02 | W18: 0.02 | X18: =AVERAGE(D18:G18) | Y18: =AVERAGE(H18:K18) | Z18: =AVERAGE(L18:O18) | AA18: =AVERAGE(P18:S18) | AB18: =AVERAGE(T18:W18)
A19: Stage Ramp Revenue QoQ Max | B19: GPT-selected stage ramp contract | C19: 0 | D19: 0.07 | E19: 0.07 | F19: 0.07 | G19: 0.07 | H19: 0.07 | I19: 0.07 | J19: 0.07 | K19: 0.07 | L19: 0.07 | M19: 0.07 | N19: 0.07 | O19: 0.07 | P19: 0.07 | Q19: 0.07 | R19: 0.07 | S19: 0.07 | T19: 0.07 | U19: 0.07 | V19: 0.07 | W19: 0.07 | X19: =AVERAGE(D19:G19) | Y19: =AVERAGE(H19:K19) | Z19: =AVERAGE(L19:O19) | AA19: =AVERAGE(P19:S19) | AB19: =AVERAGE(T19:W19)
A20: Stage Ramp Revenue QoQ Spike Max | B20: GPT-selected stage ramp contract | C20: 0 | D20: 0.07 | E20: 0.07 | F20: 0.07 | G20: 0.07 | H20: 0.07 | I20: 0.07 | J20: 0.07 | K20: 0.07 | L20: 0.07 | M20: 0.07 | N20: 0.07 | O20: 0.07 | P20: 0.07 | Q20: 0.07 | R20: 0.07 | S20: 0.07 | T20: 0.07 | U20: 0.07 | V20: 0.07 | W20: 0.07 | X20: =AVERAGE(D20:G20) | Y20: =AVERAGE(H20:K20) | Z20: =AVERAGE(L20:O20) | AA20: =AVERAGE(P20:S20) | AB20: =AVERAGE(T20:W20)
A21: Stage Ramp Utilization Cap | B21: GPT-selected stage ramp contract | C21: 0 | D21: 0.65 | E21: 0.67 | F21: 0.69 | G21: 0.71 | H21: 0.73 | I21: 0.75 | J21: 0.77 | K21: 0.79 | L21: 0.81 | M21: 0.83 | N21: 0.85 | O21: 0.85 | P21: 0.85 | Q21: 0.85 | R21: 0.85 | S21: 0.85 | T21: 0.85 | U21: 0.85 | V21: 0.85 | W21: 0.85 | X21: =AVERAGE(D21:G21) | Y21: =AVERAGE(H21:K21) | Z21: =AVERAGE(L21:O21) | AA21: =AVERAGE(P21:S21) | AB21: =AVERAGE(T21:W21)
A22: Stage Ramp COGS % Revenue Target | B22: GPT-selected stage ramp contract | C22: 0 | D22: 0.69 | E22: 0.69 | F22: 0.69 | G22: 0.69 | H22: 0.69 | I22: 0.69 | J22: 0.69 | K22: 0.69 | L22: 0.69 | M22: 0.69 | N22: 0.69 | O22: 0.69 | P22: 0.69 | Q22: 0.69 | R22: 0.69 | S22: 0.69 | T22: 0.69 | U22: 0.69 | V22: 0.69 | W22: 0.69 | X22: =AVERAGE(D22:G22) | Y22: =AVERAGE(H22:K22) | Z22: =AVERAGE(L22:O22) | AA22: =AVERAGE(P22:S22) | AB22: =AVERAGE(T22:W22)
A23: Stage Ramp COGS % Revenue Max | B23: GPT-selected stage ramp contract | C23: 0 | D23: 0.9 | E23: 0.9 | F23: 0.9 | G23: 0.9 | H23: 0.9 | I23: 0.9 | J23: 0.9 | K23: 0.9 | L23: 0.9 | M23: 0.9 | N23: 0.9 | O23: 0.9 | P23: 0.9 | Q23: 0.9 | R23: 0.9 | S23: 0.9 | T23: 0.9 | U23: 0.9 | V23: 0.9 | W23: 0.9 | X23: =AVERAGE(D23:G23) | Y23: =AVERAGE(H23:K23) | Z23: =AVERAGE(L23:O23) | AA23: =AVERAGE(P23:S23) | AB23: =AVERAGE(T23:W23)
A24: Stage Ramp Marketing % Revenue Max | B24: GPT-selected stage ramp contract | C24: 0 | D24: 0.4 | E24: 0.4 | F24: 0.4 | G24: 0.4 | H24: 0.4 | I24: 0.4 | J24: 0.4 | K24: 0.4 | L24: 0.4 | M24: 0.4 | N24: 0.4 | O24: 0.4 | P24: 0.4 | Q24: 0.4 | R24: 0.4 | S24: 0.4 | T24: 0.4 | U24: 0.4 | V24: 0.4 | W24: 0.4 | X24: =AVERAGE(D24:G24) | Y24: =AVERAGE(H24:K24) | Z24: =AVERAGE(L24:O24) | AA24: =AVERAGE(P24:S24) | AB24: =AVERAGE(T24:W24)
A25: Stage Ramp R&D % Revenue Max | B25: GPT-selected stage ramp contract | C25: 0 | D25: 0.29 | E25: 0.29 | F25: 0.29 | G25: 0.29 | H25: 0.29 | I25: 0.29 | J25: 0.29 | K25: 0.29 | L25: 0.29 | M25: 0.29 | N25: 0.29 | O25: 0.29 | P25: 0.29 | Q25: 0.29 | R25: 0.29 | S25: 0.29 | T25: 0.29 | U25: 0.29 | V25: 0.29 | W25: 0.29 | X25: =AVERAGE(D25:G25) | Y25: =AVERAGE(H25:K25) | Z25: =AVERAGE(L25:O25) | AA25: =AVERAGE(P25:S25) | AB25: =AVERAGE(T25:W25)
A26: Stage Ramp G&A % Revenue Max | B26: GPT-selected stage ramp contract | C26: 0 | D26: 0.6 | E26: 0.6 | F26: 0.6 | G26: 0.6 | H26: 0.6 | I26: 0.6 | J26: 0.6 | K26: 0.6 | L26: 0.6 | M26: 0.6 | N26: 0.6 | O26: 0.6 | P26: 0.6 | Q26: 0.6 | R26: 0.6 | S26: 0.6 | T26: 0.6 | U26: 0.6 | V26: 0.6 | W26: 0.6 | X26: =AVERAGE(D26:G26) | Y26: =AVERAGE(H26:K26) | Z26: =AVERAGE(L26:O26) | AA26: =AVERAGE(P26:S26) | AB26: =AVERAGE(T26:W26)
A27: Stage Ramp Lease % Revenue Max | B27: GPT-selected stage ramp contract | C27: 0 | D27: 0.3 | E27: 0.3 | F27: 0.3 | G27: 0.3 | H27: 0.3 | I27: 0.3 | J27: 0.3 | K27: 0.3 | L27: 0.3 | M27: 0.3 | N27: 0.3 | O27: 0.3 | P27: 0.3 | Q27: 0.3 | R27: 0.3 | S27: 0.3 | T27: 0.3 | U27: 0.3 | V27: 0.3 | W27: 0.3 | X27: =AVERAGE(D27:G27) | Y27: =AVERAGE(H27:K27) | Z27: =AVERAGE(L27:O27) | AA27: =AVERAGE(P27:S27) | AB27: =AVERAGE(T27:W27)
A28: Stage Ramp Net Income Margin Floor | B28: GPT-selected stage ramp contract | C28: 0 | D28: 0 | E28: 0 | F28: 0 | G28: 0 | H28: 0.05 | I28: 0.05 | J28: 0.05 | K28: 0.05 | L28: 0.05 | M28: 0.05 | N28: 0.07 | O28: 0.07 | P28: 0.07 | Q28: 0.07 | R28: 0.07 | S28: 0.07 | T28: 0.07 | U28: 0.07 | V28: 0.07 | W28: 0.07 | X28: =AVERAGE(D28:G28) | Y28: =AVERAGE(H28:K28) | Z28: =AVERAGE(L28:O28) | AA28: =AVERAGE(P28:S28) | AB28: =AVERAGE(T28:W28)

Sheet Payroll Schedule
A1: Payroll Schedule
A2: OEWS-title, capacity/utilization-driven payroll source. Model Inputs links to Total Payroll.
C4: Stub | D4: Q1 | E4: Q2 | F4: Q3 | G4: Q4 | H4: Q5 | I4: Q6 | J4: Q7 | K4: Q8 | L4: Q9 | M4: Q10 | N4: Q11 | O4: Q12 | P4: Q13 | Q4: Q14 | R4: Q15 | S4: Q16 | T4: Q17 | U4: Q18 | V4: Q19 | W4: Q20 | X4: Y1 | Y4: Y2 | Z4: Y3 | AA4: Y4 | AB4: Y5
C5: 46162 | D5: 46295 | E5: 46387 | F5: 46477 | G5: 46568 | H5: 46660 | I5: 46752 | J5: 46843 | K5: 46934 | L5: 47026 | M5: 47118 | N5: 47208 | O5: 47299 | P5: 47391 | Q5: 47483 | R5: 47573 | S5: 47664 | T5: 47756 | U5: 47848 | V5: 47938 | W5: 48029 | X5: Annual | Y5: Annual | Z5: Annual | AA5: Annual | AB5: Annual
A6: Payroll Assumptions
A7: Capacity Labor Model | B7: labor_driven
A8: Labor Intensity Class | B8: high
A9: Wage Positioning Tier | B9: market
A10: Wage Positioning Multiplier | B10: 1.25
A11: Capacity Units per Supporting FTE | B11: 250
A12: Target Payroll % of Revenue | B12: 0.22
A14: Quarter Summary
A15: Total Ending FTE | B15: Formula output from payroll detail | C15: =SUMIFS($G$27:$G$86,$A$27:$A$86,0) | D15: =SUMIFS($G$27:$G$86,$A$27:$A$86,1) | E15: =SUMIFS($G$27:$G$86,$A$27:$A$86,2) | F15: =SUMIFS($G$27:$G$86,$A$27:$A$86,3) | G15: =SUMIFS($G$27:$G$86,$A$27:$A$86,4) | H15: =SUMIFS($G$27:$G$86,$A$27:$A$86,5) | I15: =SUMIFS($G$27:$G$86,$A$27:$A$86,6) | J15: =SUMIFS($G$27:$G$86,$A$27:$A$86,7) | K15: =SUMIFS($G$27:$G$86,$A$27:$A$86,8) | L15: =SUMIFS($G$27:$G$86,$A$27:$A$86,9) | M15: =SUMIFS($G$27:$G$86,$A$27:$A$86,10) | N15: =SUMIFS($G$27:$G$86,$A$27:$A$86,11) | O15: =SUMIFS($G$27:$G$86,$A$27:$A$86,12) | P15: =SUMIFS($G$27:$G$86,$A$27:$A$86,13) | Q15: =SUMIFS($G$27:$G$86,$A$27:$A$86,14) | R15: =SUMIFS($G$27:$G$86,$A$27:$A$86,15) | S15: =SUMIFS($G$27:$G$86,$A$27:$A$86,16) | T15: =SUMIFS($G$27:$G$86,$A$27:$A$86,17) | U15: =SUMIFS($G$27:$G$86,$A$27:$A$86,18) | V15: =SUMIFS($G$27:$G$86,$A$27:$A$86,19) | W15: =SUMIFS($G$27:$G$86,$A$27:$A$86,20) | X15: =G15 | Y15: =K15 | Z15: =O15 | AA15: =S15 | AB15: =W15
A16: Total Average FTE | B16: Formula output from payroll detail | C16: =SUMIFS($H$27:$H$86,$A$27:$A$86,0) | D16: =SUMIFS($H$27:$H$86,$A$27:$A$86,1) | E16: =SUMIFS($H$27:$H$86,$A$27:$A$86,2) | F16: =SUMIFS($H$27:$H$86,$A$27:$A$86,3) | G16: =SUMIFS($H$27:$H$86,$A$27:$A$86,4) | H16: =SUMIFS($H$27:$H$86,$A$27:$A$86,5) | I16: =SUMIFS($H$27:$H$86,$A$27:$A$86,6) | J16: =SUMIFS($H$27:$H$86,$A$27:$A$86,7) | K16: =SUMIFS($H$27:$H$86,$A$27:$A$86,8) | L16: =SUMIFS($H$27:$H$86,$A$27:$A$86,9) | M16: =SUMIFS($H$27:$H$86,$A$27:$A$86,10) | N16: =SUMIFS($H$27:$H$86,$A$27:$A$86,11) | O16: =SUMIFS($H$27:$H$86,$A$27:$A$86,12) | P16: =SUMIFS($H$27:$H$86,$A$27:$A$86,13) | Q16: =SUMIFS($H$27:$H$86,$A$27:$A$86,14) | R16: =SUMIFS($H$27:$H$86,$A$27:$A$86,15) | S16: =SUMIFS($H$27:$H$86,$A$27:$A$86,16) | T16: =SUMIFS($H$27:$H$86,$A$27:$A$86,17) | U16: =SUMIFS($H$27:$H$86,$A$27:$A$86,18) | V16: =SUMIFS($H$27:$H$86,$A$27:$A$86,19) | W16: =SUMIFS($H$27:$H$86,$A$27:$A$86,20) | X16: =AVERAGE(D16:G16) | Y16: =AVERAGE(H16:K16) | Z16: =AVERAGE(L16:O16) | AA16: =AVERAGE(P16:S16) | AB16: =AVERAGE(T16:W16)
A17: Total Payroll | B17: Formula output from payroll detail | C17: =SUMIFS($M$27:$M$86,$A$27:$A$86,0) | D17: =SUMIFS($M$27:$M$86,$A$27:$A$86,1) | E17: =SUMIFS($M$27:$M$86,$A$27:$A$86,2) | F17: =SUMIFS($M$27:$M$86,$A$27:$A$86,3) | G17: =SUMIFS($M$27:$M$86,$A$27:$A$86,4) | H17: =SUMIFS($M$27:$M$86,$A$27:$A$86,5) | I17: =SUMIFS($M$27:$M$86,$A$27:$A$86,6) | J17: =SUMIFS($M$27:$M$86,$A$27:$A$86,7) | K17: =SUMIFS($M$27:$M$86,$A$27:$A$86,8) | L17: =SUMIFS($M$27:$M$86,$A$27:$A$86,9) | M17: =SUMIFS($M$27:$M$86,$A$27:$A$86,10) | N17: =SUMIFS($M$27:$M$86,$A$27:$A$86,11) | O17: =SUMIFS($M$27:$M$86,$A$27:$A$86,12) | P17: =SUMIFS($M$27:$M$86,$A$27:$A$86,13) | Q17: =SUMIFS($M$27:$M$86,$A$27:$A$86,14) | R17: =SUMIFS($M$27:$M$86,$A$27:$A$86,15) | S17: =SUMIFS($M$27:$M$86,$A$27:$A$86,16) | T17: =SUMIFS($M$27:$M$86,$A$27:$A$86,17) | U17: =SUMIFS($M$27:$M$86,$A$27:$A$86,18) | V17: =SUMIFS($M$27:$M$86,$A$27:$A$86,19) | W17: =SUMIFS($M$27:$M$86,$A$27:$A$86,20) | X17: =SUM(D17:G17) | Y17: =SUM(H17:K17) | Z17: =SUM(L17:O17) | AA17: =SUM(P17:S17) | AB17: =SUM(T17:W17)
A18: Total Revenue | B18: Linked from Revenue Drivers | C18: ='Revenue Drivers'!C14 | D18: ='Revenue Drivers'!D14 | E18: ='Revenue Drivers'!E14 | F18: ='Revenue Drivers'!F14 | G18: ='Revenue Drivers'!G14 | H18: ='Revenue Drivers'!H14 | I18: ='Revenue Drivers'!I14 | J18: ='Revenue Drivers'!J14 | ... W18: ='Revenue Drivers'!W14 | X18: =SUM(D18:G18) | Y18: =SUM(H18:K18) | Z18: =SUM(L18:O18) | AA18: =SUM(P18:S18) | AB18: =SUM(T18:W18)
A19: Total Capacity Units | B19: Linked from Revenue Drivers | C19: ='Revenue Drivers'!C13 | D19: ='Revenue Drivers'!D13 | E19: ='Revenue Drivers'!E13 | F19: ='Revenue Drivers'!F13 | G19: ='Revenue Drivers'!G13 | H19: ='Revenue Drivers'!H13 | I19: ='Revenue Drivers'!I13 | J19: ='Revenue Drivers'!J13 | ... W19: ='Revenue Drivers'!W13 | X19: =SUM(D19:G19) | Y19: =SUM(H19:K19) | Z19: =SUM(L19:O19) | AA19: =SUM(P19:S19) | AB19: =SUM(T19:W19)
A20: Revenue per Employee | B20: Python-built productivity formula | C20: =IFERROR(C18/C16,0) | D20: =IFERROR(D18/D16,0) | E20: =IFERROR(E18/E16,0) | F20: =IFERROR(F18/F16,0) | G20: =IFERROR(G18/G16,0) | H20: =IFERROR(H18/H16,0) | I20: =IFERROR(I18/I16,0) | J20: =IFERROR(J18/J16,0) | ... AB20: =IFERROR(AB18/AB16,0)
A21: Units per Employee | B21: Python-built productivity formula | C21: =IFERROR(C19/C16,0) | D21: =IFERROR(D19/D16,0) | E21: =IFERROR(E19/E16,0) | F21: =IFERROR(F19/F16,0) | G21: =IFERROR(G19/G16,0) | H21: =IFERROR(H19/H16,0) | I21: =IFERROR(I19/I16,0) | J21: =IFERROR(J19/J16,0) | ... AB21: =IFERROR(AB19/AB16,0)
A22: Payroll % of Revenue | B22: Python-built productivity formula | C22: =IFERROR(C17/C18,0) | D22: =IFERROR(D17/D18,0) | E22: =IFERROR(E17/E18,0) | F22: =IFERROR(F17/F18,0) | G22: =IFERROR(G17/G18,0) | H22: =IFERROR(H17/H18,0) | I22: =IFERROR(I17/I18,0) | J22: =IFERROR(J17/J18,0) | ... AB22: =IFERROR(AB17/AB18,0)
A25: Payroll Detail
A26: Quarter | B26: Staffing Class | C26: Title / Person | D26: OEWS Title | E26: Starting FTE | F26: Hires | G26: Ending FTE | H26: Average FTE | I26: Annual Wage | J26: Benefits % | K26: Wage Cost | L26: Taxes & Benefits | M26: Total Payroll | N26: Wage Source
A27: 1 | B27: key_person | C27: Owner & General Manager | E27: 1 | F27: 0 | G27: =E27+F27 | H27: =(E27+G27)/2 | I27: 78840 | J27: 0.22 | K27: =H27*I27/4 | L27: =K27*J27 | M27: =K27+L27 | N27: oews_median
A28: 2 | B28: key_person | C28: Owner & General Manager | E28: 1 | F28: 0 | G28: =E28+F28 | H28: =(E28+G28)/2 | I28: 78840 | J28: 0.22 | K28: =H28*I28/4 | L28: =K28*J28 | M28: =K28+L28 | N28: oews_median
A29: 3 | B29: key_person | C29: Owner & General Manager | E29: 1 | F29: 0 | G29: =E29+F29 | H29: =(E29+G29)/2 | I29: 78840 | J29: 0.22 | K29: =H29*I29/4 | L29: =K29*J29 | M29: =K29+L29 | N29: oews_median
A30: 4 | B30: key_person | C30: Owner & General Manager | E30: 1 | F30: 0 | G30: =E30+F30 | H30: =(E30+G30)/2 | I30: 78840 | J30: 0.22 | K30: =H30*I30/4 | L30: =K30*J30 | M30: =K30+L30 | N30: oews_median
A31: 5 | B31: key_person | C31: Owner & General Manager | E31: 1 | F31: 0 | G31: =E31+F31 | H31: =(E31+G31)/2 | I31: 81205 | J31: 0.22 | K31: =H31*I31/4 | L31: =K31*J31 | M31: =K31+L31 | N31: oews_median
A32: 6 | B32: key_person | C32: Owner & General Manager | E32: 1 | F32: 0 | G32: =E32+F32 | H32: =(E32+G32)/2 | I32: 81205 | J32: 0.22 | K32: =H32*I32/4 | L32: =K32*J32 | M32: =K32+L32 | N32: oews_median
A33: 7 | B33: key_person | C33: Owner & General Manager | E33: 1 | F33: 0 | G33: =E33+F33 | H33: =(E33+G33)/2 | I33: 81205 | J33: 0.22 | K33: =H33*I33/4 | L33: =K33*J33 | M33: =K33+L33 | N33: oews_median
A34: 8 | B34: key_person | C34: Owner & General Manager | E34: 1 | F34: 0 | G34: =E34+F34 | H34: =(E34+G34)/2 | I34: 81205 | J34: 0.22 | K34: =H34*I34/4 | L34: =K34*J34 | M34: =K34+L34 | N34: oews_median
A35: 9 | B35: key_person | C35: Owner & General Manager | E35: 1 | F35: 0 | G35: =E35+F35 | H35: =(E35+G35)/2 | I35: 83641 | J35: 0.22 | K35: =H35*I35/4 | L35: =K35*J35 | M35: =K35+L35 | N35: oews_median
A36: 10 | B36: key_person | C36: Owner & General Manager | E36: 1 | F36: 0 | G36: =E36+F36 | H36: =(E36+G36)/2 | I36: 83641 | J36: 0.22 | K36: =H36*I36/4 | L36: =K36*J36 | M36: =K36+L36 | N36: oews_median
A37: 11 | B37: key_person | C37: Owner & General Manager | E37: 1 | F37: 0 | G37: =E37+F37 | H37: =(E37+G37)/2 | I37: 83641 | J37: 0.22 | K37: =H37*I37/4 | L37: =K37*J37 | M37: =K37+L37 | N37: oews_median
A38: 12 | B38: key_person | C38: Owner & General Manager | E38: 1 | F38: 0 | G38: =E38+F38 | H38: =(E38+G38)/2 | I38: 83641 | J38: 0.22 | K38: =H38*I38/4 | L38: =K38*J38 | M38: =K38+L38 | N38: oews_median
... A66: 20 | B66: key_person | C66: Service Manager | E66: 1 | F66: 0 | G66: =E66+F66 | H66: =(E66+G66)/2 | I66: 73147 | J66: 0.22 | K66: =H66*I66/4 | L66: =K66*J66 | M66: =K66+L66 | N66: oews_median
A67: 1 | B67: supporting_staff | C67: Automotive Service Technicians and Mechanics | D67: Automotive Service Technicians and Mechanics | E67: 6 | F67: 0 | G67: =E67+F67 | H67: =(E67+G67)/2 | I67: 60400 | J67: 0.22 | K67: =H67*I67/4 | L67: =K67*J67 | M67: =K67+L67 | N67: oews_title_catalog:oews_median
A68: 2 | B68: supporting_staff | C68: Automotive Service Technicians and Mechanics | D68: Automotive Service Technicians and Mechanics | E68: 6 | F68: 0 | G68: =E68+F68 | H68: =(E68+G68)/2 | I68: 60400 | J68: 0.22 | K68: =H68*I68/4 | L68: =K68*J68 | M68: =K68+L68 | N68: oews_title_catalog:oews_median
A69: 3 | B69: supporting_staff | C69: Automotive Service Technicians and Mechanics | D69: Automotive Service Technicians and Mechanics | E69: 6 | F69: 0 | G69: =E69+F69 | H69: =(E69+G69)/2 | I69: 60400 | J69: 0.22 | K69: =H69*I69/4 | L69: =K69*J69 | M69: =K69+L69 | N69: oews_title_catalog:oews_median
A70: 4 | B70: supporting_staff | C70: Automotive Service Technicians and Mechanics | D70: Automotive Service Technicians and Mechanics | E70: 6 | F70: 0 | G70: =E70+F70 | H70: =(E70+G70)/2 | I70: 60400 | J70: 0.22 | K70: =H70*I70/4 | L70: =K70*J70 | M70: =K70+L70 | N70: oews_title_catalog:oews_median
A71: 5 | B71: supporting_staff | C71: Automotive Service Technicians and Mechanics | D71: Automotive Service Technicians and Mechanics | E71: 6 | F71: 0 | G71: =E71+F71 | H71: =(E71+G71)/2 | I71: 62212 | J71: 0.22 | K71: =H71*I71/4 | L71: =K71*J71 | M71: =K71+L71 | N71: oews_title_catalog:oews_median
A72: 6 | B72: supporting_staff | C72: Automotive Service Technicians and Mechanics | D72: Automotive Service Technicians and Mechanics | E72: 6 | F72: 0 | G72: =E72+F72 | H72: =(E72+G72)/2 | I72: 62212 | J72: 0.22 | K72: =H72*I72/4 | L72: =K72*J72 | M72: =K72+L72 | N72: oews_title_catalog:oews_median
A73: 7 | B73: supporting_staff | C73: Automotive Service Technicians and Mechanics | D73: Automotive Service Technicians and Mechanics | E73: 6 | F73: 0 | G73: =E73+F73 | H73: =(E73+G73)/2 | I73: 62212 | J73: 0.22 | K73: =H73*I73/4 | L73: =K73*J73 | M73: =K73+L73 | N73: oews_title_catalog:oews_median
A74: 8 | B74: supporting_staff | C74: Automotive Service Technicians and Mechanics | D74: Automotive Service Technicians and Mechanics | E74: 6 | F74: 0 | G74: =E74+F74 | H74: =(E74+G74)/2 | I74: 62212 | J74: 0.22 | K74: =H74*I74/4 | L74: =K74*J74 | M74: =K74+L74 | N74: oews_title_catalog:oews_median
A75: 9 | B75: supporting_staff | C75: Automotive Service Technicians and Mechanics | D75: Automotive Service Technicians and Mechanics | E75: 6 | F75: 0 | G75: =E75+F75 | H75: =(E75+G75)/2 | I75: 64078 | J75: 0.22 | K75: =H75*I75/4 | L75: =K75*J75 | M75: =K75+L75 | N75: oews_title_catalog:oews_median
A76: 10 | B76: supporting_staff | C76: Automotive Service Technicians and Mechanics | D76: Automotive Service Technicians and Mechanics | E76: 6 | F76: 0 | G76: =E76+F76 | H76: =(E76+G76)/2 | I76: 64078 | J76: 0.22 | K76: =H76*I76/4 | L76: =K76*J76 | M76: =K76+L76 | N76: oews_title_catalog:oews_median
A77: 11 | B77: supporting_staff | C77: Automotive Service Technicians and Mechanics | D77: Automotive Service Technicians and Mechanics | E77: 6 | F77: 0 | G77: =E77+F77 | H77: =(E77+G77)/2 | I77: 64078 | J77: 0.22 | K77: =H77*I77/4 | L77: =K77*J77 | M77: =K77+L77 | N77: oews_title_catalog:oews_median
A78: 12 | B78: supporting_staff | C78: Automotive Service Technicians and Mechanics | D78: Automotive Service Technicians and Mechanics | E78: 6 | F78: 0 | G78: =E78+F78 | H78: =(E78+G78)/2 | I78: 64078 | J78: 0.22 | K78: =H78*I78/4 | L78: =K78*J78 | M78: =K78+L78 | N78: oews_title_catalog:oews_median
... A86: 20 | B86: supporting_staff | C86: Automotive Service Technicians and Mechanics | D86: Automotive Service Technicians and Mechanics | E86: 6 | F86: 0 | G86: =E86+F86 | H86: =(E86+G86)/2 | I86: 67981 | J86: 0.22 | K86: =H86*I86/4 | L86: =K86*J86 | M86: =K86+L86 | N86: oews_title_catalog:oews_median

Sheet Debt Schedule
A1: Debt Schedule
A2: Debt, interest, and capital lease mechanics. Model Inputs links to calculated outputs.
C4: Stub | D4: Q1 | E4: Q2 | F4: Q3 | G4: Q4 | H4: Q5 | I4: Q6 | J4: Q7 | K4: Q8 | L4: Q9 | M4: Q10 | N4: Q11 | O4: Q12 | P4: Q13 | Q4: Q14 | R4: Q15 | S4: Q16 | T4: Q17 | U4: Q18 | V4: Q19 | W4: Q20 | X4: Y1 | Y4: Y2 | Z4: Y3 | AA4: Y4 | AB4: Y5
C5: 46162 | D5: 46295 | E5: 46387 | F5: 46477 | G5: 46568 | H5: 46660 | I5: 46752 | J5: 46843 | K5: 46934 | L5: 47026 | M5: 47118 | N5: 47208 | O5: 47299 | P5: 47391 | Q5: 47483 | R5: 47573 | S5: 47664 | T5: 47756 | U5: 47848 | V5: 47938 | W5: 48029 | X5: Annual | Y5: Annual | Z5: Annual | AA5: Annual | AB5: Annual
A6: Debt Amortization
A7: Opening Debt | B7: Calculated | C7: 450000 | D7: =C11 | E7: =D11 | F7: =E11 | G7: =F11 | H7: =G11 | I7: =H11 | J7: =I11 | K7: =J11 | ... W7: =V11 | X7: =G7 | Y7: =K7 | Z7: =O7 | AA7: =S7 | AB7: =W7
A8: Debt Issuance | B8: Source borrowing | C8: 0 | D8: 0 | E8: 0 | F8: 0 | G8: 0 | H8: 0 | I8: 0 | J8: 0 | K8: 0 | L8: 0 | M8: 0 | N8: 0 | O8: 0 | P8: 0 | Q8: 0 | R8: 0 | S8: 0 | T8: 0 | U8: 0 | V8: 0 | W8: 0 | X8: =SUM(D8:G8) | Y8: =SUM(H8:K8) | Z8: =SUM(L8:O8) | AA8: =SUM(P8:S8) | AB8: =SUM(T8:W8)
A9: Requested Debt Repayment | B9: Source scheduled repayment | C9: 0 | D9: 22500 | E9: 22500 | F9: 22500 | G9: 22500 | H9: 22500 | I9: 22500 | J9: 22500 | K9: 22500 | L9: 22500 | M9: 22500 | N9: 37380 | O9: 63635 | P9: 65328 | Q9: 58657 | R9: 22500 | S9: 22500 | T9: 22500 | U9: 22500 | V9: 22500 | W9: 22500 | X9: =SUM(D9:G9) | Y9: =SUM(H9:K9) | Z9: =SUM(L9:O9) | AA9: =SUM(P9:S9) | AB9: =SUM(T9:W9)
A10: Actual Debt Repayment | B10: MIN(requested repayment, opening debt + issuance) | C10: =MIN(C9,C7+C8) | D10: =MIN(D9,D7+D8) | E10: =MIN(E9,E7+E8) | F10: =MIN(F9,F7+F8) | G10: =MIN(G9,G7+G8) | H10: =MIN(H9,H7+H8) | I10: =MIN(I9,I7+I8) | J10: =MIN(J9,J7+J8) | ... W10: =MIN(W9,W7+W8) | X10: =SUM(D10:G10) | Y10: =SUM(H10:K10) | Z10: =SUM(L10:O10) | AA10: =SUM(P10:S10) | AB10: =SUM(T10:W10)
A11: Closing Debt | B11: Calculated | C11: =MAX(0,C7+C8-C10) | D11: =MAX(0,D7+D8-D10) | E11: =MAX(0,E7+E8-E10) | F11: =MAX(0,F7+F8-F10) | G11: =MAX(0,G7+G8-G10) | H11: =MAX(0,H7+H8-H10) | I11: =MAX(0,I7+I8-I10) | J11: =MAX(0,J7+J8-J10) | ... W11: =MAX(0,W7+W8-W10) | X11: =G11 | Y11: =K11 | Z11: =O11 | AA11: =S11 | AB11: =W11
A12: Interest Rate | B12: Source rate | C12: 0.017778 | D12: 0.023125 | E12: 0.023125 | F12: 0.023125 | G12: 0.023125 | H12: 0.023125 | I12: 0.023125 | J12: 0.023125 | K12: 0.023125 | L12: 0.023125 | M12: 0.023125 | N12: 0.023125 | O12: 0.023125 | P12: 0.023125 | Q12: 0.023125 | R12: 0.023125 | S12: 0.023125 | T12: 0.023125 | U12: 0.023125 | V12: 0.023125 | W12: 0.023125 | X12: =SUM(D12:G12) | Y12: =SUM(H12:K12) | Z12: =SUM(L12:O12) | AA12: =SUM(P12:S12) | AB12: =SUM(T12:W12)
A13: Interest Expense | B13: Average debt balance x rate | C13: =((C7+C11)/2)*C12 | D13: =((D7+D11)/2)*D12 | E13: =((E7+E11)/2)*E12 | F13: =((F7+F11)/2)*F12 | G13: =((G7+G11)/2)*G12 | H13: =((H7+H11)/2)*H12 | I13: =((I7+I11)/2)*I12 | J13: =((J7+J11)/2)*J12 | ... W13: =((W7+W11)/2)*W12 | X13: =SUM(D13:G13) | Y13: =SUM(H13:K13) | Z13: =SUM(L13:O13) | AA13: =SUM(P13:S13) | AB13: =SUM(T13:W13)
A14: Total Debt Service | B14: Interest + actual repayment | C14: =C13+C10 | D14: =D13+D10 | E14: =E13+E10 | F14: =F13+F10 | G14: =G13+G10 | H14: =H13+H10 | I14: =I13+I10 | J14: =J13+J10 | ... W14: =W13+W10 | X14: =SUM(D14:G14) | Y14: =SUM(H14:K14) | Z14: =SUM(L14:O14) | AA14: =SUM(P14:S14) | AB14: =SUM(T14:W14)
A17: Capital Lease Schedule
A18: Lease Opening Balance | B18: Capital leases | C18: 54000 | D18: =C23 | E18: =D23 | F18: =E23 | G18: =F23 | H18: =G23 | I18: =H23 | J18: =I23 | K18: =J23 | ... W18: =V23 | X18: =G18 | Y18: =K18 | Z18: =O18 | AA18: =S18 | AB18: =W18
A19: Requested Lease Principal Repayments | B19: Capital leases | C19: 0 | D19: 17500 | E19: 17500 | F19: 17500 | G19: 17500 | H19: 17500 | I19: 17500 | J19: 17500 | K19: 17500 | L19: 17500 | M19: 17500 | N19: 17500 | O19: 17500 | P19: 17500 | Q19: 17500 | R19: 17500 | S19: 17500 | T19: 17500 | U19: 17500 | V19: 17500 | W19: 17500 | X19: =SUM(D19:G19) | Y19: =SUM(H19:K19) | Z19: =SUM(L19:O19) | AA19: =SUM(P19:S19) | AB19: =SUM(T19:W19)
A20: Lease Principal Repayments | B20: Capital leases | C20: =MIN(C19,C18+C21) | D20: =MIN(D19,D18+D21) | E20: =MIN(E19,E18+E21) | F20: =MIN(F19,F18+F21) | G20: =MIN(G19,G18+G21) | H20: =MIN(H19,H18+H21) | I20: =MIN(I19,I18+I21) | J20: =MIN(J19,J18+J21) | ... W20: =MIN(W19,W18+W21) | X20: =SUM(D20:G20) | Y20: =SUM(H20:K20) | Z20: =SUM(L20:O20) | AA20: =SUM(P20:S20) | AB20: =SUM(T20:W20)
A21: Lease Net Additions | B21: Capital leases | C21: 0 | D21: 0 | E21: 0 | F21: 0 | G21: 0 | H21: 0 | I21: 0 | J21: 0 | K21: 0 | L21: 0 | M21: 0 | N21: 0 | O21: 0 | P21: 0 | Q21: 0 | R21: 0 | S21: 0 | T21: 0 | U21: 0 | V21: 0 | W21: 0 | X21: =SUM(D21:G21) | Y21: =SUM(H21:K21) | Z21: =SUM(L21:O21) | AA21: =SUM(P21:S21) | AB21: =SUM(T21:W21)
A22: Lease Interest Expense | B22: Capital leases | C22: 0 | D22: =D18*D12 | E22: =E18*E12 | F22: =F18*F12 | G22: =G18*G12 | H22: =H18*H12 | I22: =I18*I12 | J22: =J18*J12 | K22: =K18*K12 | ... W22: =W18*W12 | X22: =SUM(D22:G22) | Y22: =SUM(H22:K22) | Z22: =SUM(L22:O22) | AA22: =SUM(P22:S22) | AB22: =SUM(T22:W22)
A23: Lease Closing Balance | B23: Capital leases | C23: =MAX(0,C18+C21-C20) | D23: =MAX(0,D18+D21-D20) | E23: =MAX(0,E18+E21-E20) | F23: =MAX(0,F18+F21-F20) | G23: =MAX(0,G18+G21-G20) | H23: =MAX(0,H18+H21-H20) | I23: =MAX(0,I18+I21-I20) | J23: =MAX(0,J18+J21-J20) | ... W23: =MAX(0,W18+W21-W20) | X23: =G23 | Y23: =K23 | Z23: =O23 | AA23: =S23 | AB23: =W23
A24: Right-of-Use Asset Opening | B24: Capital leases | C24: 54000 | D24: =C26 | E24: =D26 | F24: =E26 | G24: =F26 | H24: =G26 | I24: =H26 | J24: =I26 | K24: =J26 | ... W24: =V26 | X24: =G24 | Y24: =K24 | Z24: =O24 | AA24: =S24 | AB24: =W24
A25: Lease Asset Depreciation | B25: Capital leases | C25: 0 | D25: =MIN((C18/20),D24) | E25: =MIN((C18/20),E24) | F25: =MIN((C18/20),F24) | G25: =MIN((C18/20),G24) | H25: =MIN((C18/20),H24) | I25: =MIN((C18/20),I24) | J25: =MIN((C18/20),J24) | K25: =MIN((C18/20),K24) | L25: =MIN((C18/20),L24) | M25: =MIN((C18/20),M24) | N25: =MIN((C18/20),N24) | O25: =MIN((C18/20),O24) | P25: =MIN((C18/20),P24) | Q25: =MIN((C18/20),Q24) | R25: =MIN((C18/20),R24) | S25: =MIN((C18/20),S24) | T25: =MIN((C18/20),T24) | U25: =MIN((C18/20),U24) | V25: =MIN((C18/20),V24) | W25: =MIN((C18/20),W24) | X25: =SUM(D25:G25) | Y25: =SUM(H25:K25) | Z25: =SUM(L25:O25) | AA25: =SUM(P25:S25) | AB25: =SUM(T25:W25)
A26: Right-of-Use Asset Closing | B26: Capital leases | C26: =MAX(0,C24-C25) | D26: =MAX(0,D24-D25) | E26: =MAX(0,E24-E25) | F26: =MAX(0,F24-F25) | G26: =MAX(0,G24-G25) | H26: =MAX(0,H24-H25) | I26: =MAX(0,I24-I25) | J26: =MAX(0,J24-J25) | ... W26: =MAX(0,W24-W25) | X26: =G26 | Y26: =K26 | Z26: =O26 | AA26: =S26 | AB26: =W26

Sheet CapEx Depreciation
A1: CapEx & Depreciation Schedule
A2: Capital expenditure and depreciation mechanics. Model Inputs links to calculated outputs.
C4: Stub | D4: Q1 | E4: Q2 | F4: Q3 | G4: Q4 | H4: Q5 | I4: Q6 | J4: Q7 | K4: Q8 | L4: Q9 | M4: Q10 | N4: Q11 | O4: Q12 | P4: Q13 | Q4: Q14 | R4: Q15 | S4: Q16 | T4: Q17 | U4: Q18 | V4: Q19 | W4: Q20 | X4: Y1 | Y4: Y2 | Z4: Y3 | AA4: Y4 | AB4: Y5
C5: 46162 | D5: 46295 | E5: 46387 | F5: 46477 | G5: 46568 | H5: 46660 | I5: 46752 | J5: 46843 | K5: 46934 | L5: 47026 | M5: 47118 | N5: 47208 | O5: 47299 | P5: 47391 | Q5: 47483 | R5: 47573 | S5: 47664 | T5: 47756 | U5: 47848 | V5: 47938 | W5: 48029 | X5: Annual | Y5: Annual | Z5: Annual | AA5: Annual | AB5: Annual
A6: PPE and Depreciation
A7: Opening PPE | B7: Calculated | C7: 1200000 | D7: =C12 | E7: =D12 | F7: =E12 | G7: =F12 | H7: =G12 | I7: =H12 | J7: =I12 | K7: =J12 | ... W7: =V12 | X7: =G7 | Y7: =K7 | Z7: =O7 | AA7: =S7 | AB7: =W7
A8: Capital Expenditures | B8: Schedule source | C8: 0 | D8: 8396.4 | E8: 8452.2109 | F8: 8505.4598 | G8: 8556.1013 | H8: 8604.101 | I8: 8649.4274 | J8: 8692.0518 | K8: 8731.931 | L8: 8769.0329 | M8: 8803.3286 | N8: 8834.7829 | O8: 8863.3634 | P8: 8889.0495 | Q8: 8911.8054 | R8: 8931.5985 | S8: 8948.4078 | T8: 8962.2063 | U8: 8972.9609 | V8: 8980.6507 | W8: 8985.2578 | X8: =SUM(D8:G8) | Y8: =SUM(H8:K8) | Z8: =SUM(L8:O8) | AA8: =SUM(P8:S8) | AB8: =SUM(T8:W8)
A9: Lease Additions | B9: Schedule source | C9: 0 | D9: ='Debt Schedule'!D21 | E9: ='Debt Schedule'!E21 | F9: ='Debt Schedule'!F21 | G9: ='Debt Schedule'!G21 | H9: ='Debt Schedule'!H21 | I9: ='Debt Schedule'!I21 | J9: ='Debt Schedule'!J21 | K9: ='Debt Schedule'!K21 | ... W9: ='Debt Schedule'!W21 | X9: =SUM(D9:G9) | Y9: =SUM(H9:K9) | Z9: =SUM(L9:O9) | AA9: =SUM(P9:S9) | AB9: =SUM(T9:W9)
A10: Depreciation Rate | B10: Schedule source | C10: 0 | D10: 0.00035 | E10: 0.000697 | F10: 0.001043 | G10: 0.001387 | H10: 0.001729 | I10: 0.002069 | J10: 0.002409 | K10: 0.002748 | L10: 0.003086 | M10: 0.003424 | N10: 0.003762 | O10: 0.004099 | P10: 0.004437 | Q10: 0.004776 | R10: 0.005115 | S10: 0.005455 | T10: 0.005797 | U10: 0.00614 | V10: 0.006484 | W10: 0.006831 | X10: =SUM(D10:G10) | Y10: =SUM(H10:K10) | Z10: =SUM(L10:O10) | AA10: =SUM(P10:S10) | AB10: =SUM(T10:W10)
A11: Depreciation Expense | B11: Calculated | C11: =MIN(C7*C10,C7) | D11: =MIN(D7*D10,D7) | E11: =MIN(E7*E10,E7) | F11: =MIN(F7*F10,F7) | G11: =MIN(G7*G10,G7) | H11: =MIN(H7*H10,H7) | I11: =MIN(I7*I10,I7) | J11: =MIN(J7*J10,J7) | ... W11: =MIN(W7*W10,W7) | X11: =SUM(D11:G11) | Y11: =SUM(H11:K11) | Z11: =SUM(L11:O11) | AA11: =SUM(P11:S11) | AB11: =SUM(T11:W11)
A12: Closing PPE | B12: Calculated | C12: =MAX(0,C7+C8+C9-C11) | D12: =MAX(0,D7+D8+D9-D11) | E12: =MAX(0,E7+E8+E9-E11) | F12: =MAX(0,F7+F8+F9-F11) | G12: =MAX(0,G7+G8+G9-G11) | H12: =MAX(0,H7+H8+H9-H11) | I12: =MAX(0,I7+I8+I9-I11) | J12: =MAX(0,J7+J8+J9-J11) | ... W12: =MAX(0,W7+W8+W9-W11) | X12: =G12 | Y12: =K12 | Z12: =O12 | AA12: =S12 | AB12: =W12
A13: Opening Accumulated Depreciation | B13: Calculated | C13: 0 | D13: =C14 | E13: =D14 | F13: =E14 | G13: =F14 | H13: =G14 | I13: =H14 | J13: =I14 | K13: =J14 | ... W13: =V14 | X13: =G13 | Y13: =K13 | Z13: =O13 | AA13: =S13 | AB13: =W13
A14: Accumulated Depreciation | B14: Calculated | C14: =C13-C11 | D14: =D13-D11 | E14: =E13-E11 | F14: =F13-F11 | G14: =G13-G11 | H14: =H13-H11 | I14: =I13-I11 | J14: =J13-J11 | ... W14: =W13-W11 | X14: =G14 | Y14: =K14 | Z14: =O14 | AA14: =S14 | AB14: =W14

Sheet Working Capital
A1: Working Capital Schedule
A2: Working-capital drivers. Model Inputs links to these source rows.
C4: Stub | D4: Q1 | E4: Q2 | F4: Q3 | G4: Q4 | H4: Q5 | I4: Q6 | J4: Q7 | K4: Q8 | L4: Q9 | M4: Q10 | N4: Q11 | O4: Q12 | P4: Q13 | Q4: Q14 | R4: Q15 | S4: Q16 | T4: Q17 | U4: Q18 | V4: Q19 | W4: Q20 | X4: Y1 | Y4: Y2 | Z4: Y3 | AA4: Y4 | AB4: Y5
C5: 46162 | D5: 46295 | E5: 46387 | F5: 46477 | G5: 46568 | H5: 46660 | I5: 46752 | J5: 46843 | K5: 46934 | L5: 47026 | M5: 47118 | N5: 47208 | O5: 47299 | P5: 47391 | Q5: 47483 | R5: 47573 | S5: 47664 | T5: 47756 | U5: 47848 | V5: 47938 | W5: 48029 | X5: Annual | Y5: Annual | Z5: Annual | AA5: Annual | AB5: Annual
A6: Working Capital Drivers
A7: Accounts Receivable Days | B7: Working capital driver | C7: 0 | D7: 15 | E7: 15 | F7: 15 | G7: 15 | H7: 15 | I7: 15 | J7: 15 | K7: 15 | L7: 15 | M7: 15 | N7: 15 | O7: 15 | P7: 15 | Q7: 15 | R7: 15 | S7: 15 | T7: 15 | U7: 15 | V7: 15 | W7: 15
A8: Inventory Days | B8: Working capital driver | C8: 0 | D8: 20 | E8: 20 | F8: 20 | G8: 20 | H8: 20 | I8: 20 | J8: 20 | K8: 20 | L8: 20 | M8: 20 | N8: 20 | O8: 20 | P8: 20 | Q8: 20 | R8: 20 | S8: 20 | T8: 20 | U8: 20 | V8: 20 | W8: 20
A9: Accounts Payable Days | B9: Working capital driver | C9: 0 | D9: 30 | E9: 30 | F9: 30 | G9: 30 | H9: 30 | I9: 30 | J9: 30 | K9: 30 | L9: 30 | M9: 30 | N9: 30 | O9: 30 | P9: 30 | Q9: 30 | R9: 30 | S9: 30 | T9: 30 | U9: 30 | V9: 30 | W9: 30
A10: Prepaid Expenses (% of Revenue) | B10: Working capital driver | C10: 0 | D10: 0 | E10: 0 | F10: 0 | G10: 0 | H10: 0 | I10: 0 | J10: 0 | K10: 0 | L10: 0 | M10: 0 | N10: 0 | O10: 0 | P10: 0 | Q10: 0 | R10: 0 | S10: 0 | T10: 0 | U10: 0 | V10: 0 | W10: 0
A11: Deferred Revenue (% of Revenue) | B11: Working capital driver | C11: 0 | D11: 0 | E11: 0 | F11: 0 | G11: 0 | H11: 0 | I11: 0 | J11: 0 | K11: 0 | L11: 0 | M11: 0 | N11: 0 | O11: 0 | P11: 0 | Q11: 0 | R11: 0 | S11: 0 | T11: 0 | U11: 0 | V11: 0 | W11: 0
A12: Short Term Debt (% of LTD) | B12: Working capital driver | C12: 0 | D12: 0 | E12: 0 | F12: 0 | G12: 0 | H12: 0 | I12: 0 | J12: 0 | K12: 0 | L12: 0 | M12: 0 | N12: 0 | O12: 0 | P12: 0 | Q12: 0 | R12: 0 | S12: 0 | T12: 0 | U12: 0 | V12: 0 | W12: 0
A14: Opening Working Capital Seeds
A15: Cash Opening Balance | B15: Opening balance seed | C15: 180000 | D15: 0 | E15: 0 | F15: 0 | G15: 0 | H15: 0 | I15: 0 | J15: 0 | K15: 0 | L15: 0 | M15: 0 | N15: 0 | O15: 0 | P15: 0 | Q15: 0 | R15: 0 | S15: 0 | T15: 0 | U15: 0 | V15: 0 | W15: 0
A16: Accounts Receivable Opening Balance | B16: Opening balance seed | C16: 35000 | D16: 0 | E16: 0 | F16: 0 | G16: 0 | H16: 0 | I16: 0 | J16: 0 | K16: 0 | L16: 0 | M16: 0 | N16: 0 | O16: 0 | P16: 0 | Q16: 0 | R16: 0 | S16: 0 | T16: 0 | U16: 0 | V16: 0 | W16: 0
A17: Inventory Opening Balance | B17: Opening balance seed | C17: 85000 | D17: 0 | E17: 0 | F17: 0 | G17: 0 | H17: 0 | I17: 0 | J17: 0 | K17: 0 | L17: 0 | M17: 0 | N17: 0 | O17: 0 | P17: 0 | Q17: 0 | R17: 0 | S17: 0 | T17: 0 | U17: 0 | V17: 0 | W17: 0
A18: Accounts Payable Opening Balance | B18: Opening balance seed | C18: 70000 | D18: 0 | E18: 0 | F18: 0 | G18: 0 | H18: 0 | I18: 0 | J18: 0 | K18: 0 | L18: 0 | M18: 0 | N18: 0 | O18: 0 | P18: 0 | Q18: 0 | R18: 0 | S18: 0 | T18: 0 | U18: 0 | V18: 0 | W18: 0
A19: Short Term Debt Opening Balance | B19: Opening balance seed | C19: 0 | D19: 0 | E19: 0 | F19: 0 | G19: 0 | H19: 0 | I19: 0 | J19: 0 | K19: 0 | L19: 0 | M19: 0 | N19: 0 | O19: 0 | P19: 0 | Q19: 0 | R19: 0 | S19: 0 | T19: 0 | U19: 0 | V19: 0 | W19: 0

Sheet Cash Equity Schedule
A1: Cash & Equity Schedule
A2: Equity, distributions, lease/rent, and opening cash seeds. Model Inputs links to these rows.
C4: Stub | D4: Q1 | E4: Q2 | F4: Q3 | G4: Q4 | H4: Q5 | I4: Q6 | J4: Q7 | K4: Q8 | L4: Q9 | M4: Q10 | N4: Q11 | O4: Q12 | P4: Q13 | Q4: Q14 | R4: Q15 | S4: Q16 | T4: Q17 | U4: Q18 | V4: Q19 | W4: Q20 | X4: Y1 | Y4: Y2 | Z4: Y3 | AA4: Y4 | AB4: Y5
C5: 46162 | D5: 46295 | E5: 46387 | F5: 46477 | G5: 46568 | H5: 46660 | I5: 46752 | J5: 46843 | K5: 46934 | L5: 47026 | M5: 47118 | N5: 47208 | O5: 47299 | P5: 47391 | Q5: 47483 | R5: 47573 | S5: 47664 | T5: 47756 | U5: 47848 | V5: 47938 | W5: 48029 | X5: Annual | Y5: Annual | Z5: Annual | AA5: Annual | AB5: Annual
A6: Equity and Distributions
A7: Owner's Capital | B7: Equity / distribution input | C7: 650000 | D7: 1181676 | E7: 1301272 | F7: 1398809 | G7: 1454018 | H7: 1489178 | I7: 1503569 | J7: 1503569 | K7: 1503569 | L7: 1503569 | M7: 1503569 | N7: 1503569 | O7: 1503569 | P7: 1503569 | Q7: 1503569 | R7: 1503569 | S7: 1503569 | T7: 1503569 | U7: 1503569 | V7: 1503569 | W7: 1503569
A8: Other Equity | B8: Equity / distribution input | C8: 0 | D8: 0 | E8: 0 | F8: 0 | G8: 0 | H8: 0 | I8: 0 | J8: 0 | K8: 0 | L8: 0 | M8: 0 | N8: 0 | O8: 0 | P8: 0 | Q8: 0 | R8: 0 | S8: 0 | T8: 0 | U8: 0 | V8: 0 | W8: 0
A9: Distributions | B9: Equity / distribution input | C9: 0 | D9: 0 | E9: 0 | F9: 0 | G9: 0 | H9: 0 | I9: 0 | J9: 0 | K9: 0 | L9: 0 | M9: 0 | N9: 14883 | O9: 41137 | P9: 42830 | Q9: 58499 | R9: 122522 | S9: 134394 | T9: 136755 | U9: 144900 | V9: 149825 | W9: 162176
A11: Operating Fixed Cash Items
A12: Lease | B12: Operating lease/rent input | C12: 72000 | D12: 54000 | E12: 54000 | F12: 54000 | G12: 54000 | H12: 54000 | I12: 54000 | J12: 54000 | K12: 54000 | L12: 54000 | M12: 54000 | N12: 54000 | O12: 54000 | P12: 54000 | Q12: 54000 | R12: 54000 | S12: 54000 | T12: 54000 | U12: 54000 | V12: 54000 | W12: 54000

Sheet Model Inputs
A1: Model Inputs
A2: Formula-driven bridge from schedules into FINMO. FINMO references this sheet only.
C4: Stub | D4: Q1 | E4: Q2 | F4: Q3 | G4: Q4 | H4: Q5 | I4: Q6 | J4: Q7 | K4: Q8 | L4: Q9 | M4: Q10 | N4: Q11 | O4: Q12 | P4: Q13 | Q4: Q14 | R4: Q15 | S4: Q16 | T4: Q17 | U4: Q18 | V4: Q19 | W4: Q20 | X4: Y1 | Y4: Y2 | Z4: Y3 | AA4: Y4 | AB4: Y5
C5: 46162 | D5: 46295 | E5: 46387 | F5: 46477 | G5: 46568 | H5: 46660 | I5: 46752 | J5: 46843 | K5: 46934 | L5: 47026 | M5: 47118 | N5: 47208 | O5: 47299 | P5: 47391 | Q5: 47483 | R5: 47573 | S5: 47664 | T5: 47756 | U5: 47848 | V5: 47938 | W5: 48029 | X5: Annual | Y5: Annual | Z5: Annual | AA5: Annual | AB5: Annual
A6: Income Statement Inputs
A7: Primary line of business / Completed repair order - Capacity | B7: Revenue Drivers schedule | C7: ='Revenue Drivers'!C8 | D7: ='Revenue Drivers'!D8 | E7: ='Revenue Drivers'!E8 | F7: ='Revenue Drivers'!F8 | G7: ='Revenue Drivers'!G8 | H7: ='Revenue Drivers'!H8 | I7: ='Revenue Drivers'!I8 | J7: ='Revenue Drivers'!J8 | ... W7: ='Revenue Drivers'!W8 | X7: =SUM(D7:G7) | Y7: =SUM(H7:K7) | Z7: =SUM(L7:O7) | AA7: =SUM(P7:S7) | AB7: =SUM(T7:W7)
A8: Primary line of business / Completed repair order - Unit Price | B8: Revenue Drivers schedule | C8: ='Revenue Drivers'!C9 | D8: ='Revenue Drivers'!D9 | E8: ='Revenue Drivers'!E9 | F8: ='Revenue Drivers'!F9 | G8: ='Revenue Drivers'!G9 | H8: ='Revenue Drivers'!H9 | I8: ='Revenue Drivers'!I9 | J8: ='Revenue Drivers'!J9 | ... W8: ='Revenue Drivers'!W9 | X8: =SUM(D8:G8) | Y8: =SUM(H8:K8) | Z8: =SUM(L8:O8) | AA8: =SUM(P8:S8) | AB8: =SUM(T8:W8)
A9: Primary line of business / Completed repair order - Utilization | B9: Revenue Drivers schedule | C9: ='Revenue Drivers'!C10 | D9: ='Revenue Drivers'!D10 | E9: ='Revenue Drivers'!E10 | F9: ='Revenue Drivers'!F10 | G9: ='Revenue Drivers'!G10 | H9: ='Revenue Drivers'!H10 | I9: ='Revenue Drivers'!I10 | J9: ='Revenue Drivers'!J10 | ... W9: ='Revenue Drivers'!W10 | X9: =SUM(D9:G9) | Y9: =SUM(H9:K9) | Z9: =SUM(L9:O9) | AA9: =SUM(P9:S9) | AB9: =SUM(T9:W9)
A10: Primary line of business / Completed repair order - Revenue | B10: Revenue Drivers schedule | C10: ='Revenue Drivers'!C11 | D10: ='Revenue Drivers'!D11 | E10: ='Revenue Drivers'!E11 | F10: ='Revenue Drivers'!F11 | G10: ='Revenue Drivers'!G11 | H10: ='Revenue Drivers'!H11 | I10: ='Revenue Drivers'!I11 | J10: ='Revenue Drivers'!J11 | ... W10: ='Revenue Drivers'!W11 | X10: =SUM(D10:G10) | Y10: =SUM(H10:K10) | Z10: =SUM(L10:O10) | AA10: =SUM(P10:S10) | AB10: =SUM(T10:W10)
A11: Revenue | B11: Revenue Drivers schedule | C11: ='Revenue Drivers'!C14 | D11: ='Revenue Drivers'!D14 | E11: ='Revenue Drivers'!E14 | F11: ='Revenue Drivers'!F14 | G11: ='Revenue Drivers'!G14 | H11: ='Revenue Drivers'!H14 | I11: ='Revenue Drivers'!I14 | J11: ='Revenue Drivers'!J14 | ... W11: ='Revenue Drivers'!W14 | X11: =SUM(D11:G11) | Y11: =SUM(H11:K11) | Z11: =SUM(L11:O11) | AA11: =SUM(P11:S11) | AB11: =SUM(T11:W11)
A12: Cost of Goods Sold | B12: Direct model driver | C12: 0.34 | D12: 0.46 | E12: 0.456 | F12: 0.452 | G12: 0.448 | H12: 0.444 | I12: 0.44 | J12: 0.436 | K12: 0.432 | L12: 0.428 | M12: 0.424 | N12: 0.42 | O12: 0.41777778 | P12: 0.41555556 | Q12: 0.41333333 | R12: 0.41111111 | S12: 0.40888889 | T12: 0.40666667 | U12: 0.40444444 | V12: 0.40222222 | W12: 0.4 | X12: =SUM(D12:G12) | Y12: =SUM(H12:K12) | Z12: =SUM(L12:O12) | AA12: =SUM(P12:S12) | AB12: =SUM(T12:W12)
A13: Marketing | B13: Direct model driver | C13: 0.072 | D13: 0.21 | E13: 0.199 | F13: 0.188 | G13: 0.177 | H13: 0.166 | I13: 0.155 | J13: 0.144 | K13: 0.133 | L13: 0.122 | M13: 0.111 | N13: 0.1 | O13: 0.097777778 | P13: 0.095555556 | Q13: 0.093333333 | R13: 0.091111111 | S13: 0.088888889 | T13: 0.086666667 | U13: 0.084444444 | V13: 0.082222222 | W13: 0.08 | X13: =SUM(D13:G13) | Y13: =SUM(H13:K13) | Z13: =SUM(L13:O13) | AA13: =SUM(P13:S13) | AB13: =SUM(T13:W13)
A14: Research & Development | B14: Direct model driver | C14: 0 | D14: 0 | E14: 0 | F14: 0 | G14: 0 | H14: 0 | I14: 0 | J14: 0 | K14: 0 | L14: 0 | M14: 0 | N14: 0 | O14: 0 | P14: 0 | Q14: 0 | R14: 0 | S14: 0 | T14: 0 | U14: 0 | V14: 0 | W14: 0 | X14: =SUM(D14:G14) | Y14: =SUM(H14:K14) | Z14: =SUM(L14:O14) | AA14: =SUM(P14:S14) | AB14: =SUM(T14:W14)
A15: Lease | B15: Cash Equity Schedule output | C15: ='Cash Equity Schedule'!C12 | D15: ='Cash Equity Schedule'!D12 | E15: ='Cash Equity Schedule'!E12 | F15: ='Cash Equity Schedule'!F12 | G15: ='Cash Equity Schedule'!G12 | H15: ='Cash Equity Schedule'!H12 | I15: ='Cash Equity Schedule'!I12 | J15: ='Cash Equity Schedule'!J12 | ... W15: ='Cash Equity Schedule'!W12 | X15: =SUM(D15:G15) | Y15: =SUM(H15:K15) | Z15: =SUM(L15:O15) | AA15: =SUM(P15:S15) | AB15: =SUM(T15:W15)
A16: Payroll | B16: Payroll Schedule output | C16: 212500 | D16: ='Payroll Schedule'!D17 | E16: ='Payroll Schedule'!E17 | F16: ='Payroll Schedule'!F17 | G16: ='Payroll Schedule'!G17 | H16: ='Payroll Schedule'!H17 | I16: ='Payroll Schedule'!I17 | J16: ='Payroll Schedule'!J17 | K16: ='Payroll Schedule'!K17 | ... W16: ='Payroll Schedule'!W17 | X16: =SUM(D16:G16) | Y16: =SUM(H16:K16) | Z16: =SUM(L16:O16) | AA16: =SUM(P16:S16) | AB16: =SUM(T16:W16)
A17: General & Administrative | B17: Direct model driver | C17: 0.00507 | D17: 0.21 | E17: 0.204 | F17: 0.198 | G17: 0.192 | H17: 0.186 | I17: 0.18 | J17: 0.174 | K17: 0.168 | L17: 0.162 | M17: 0.156 | N17: 0.15 | O17: 0.14666667 | P17: 0.14333333 | Q17: 0.14 | R17: 0.13666667 | S17: 0.13333333 | T17: 0.13 | U17: 0.12666667 | V17: 0.12333333 | W17: 0.12 | X17: =SUM(D17:G17) | Y17: =SUM(H17:K17) | Z17: =SUM(L17:O17) | AA17: =SUM(P17:S17) | AB17: =SUM(T17:W17)
A18: Interest Rate | B18: Debt Schedule output | C18: ='Debt Schedule'!C12 | D18: ='Debt Schedule'!D12 | E18: ='Debt Schedule'!E12 | F18: ='Debt Schedule'!F12 | G18: ='Debt Schedule'!G12 | H18: ='Debt Schedule'!H12 | I18: ='Debt Schedule'!I12 | J18: ='Debt Schedule'!J12 | ... W18: ='Debt Schedule'!W12 | X18: =SUM(D18:G18) | Y18: =SUM(H18:K18) | Z18: =SUM(L18:O18) | AA18: =SUM(P18:S18) | AB18: =SUM(T18:W18)
A19: Interest Expense | B19: Debt Schedule output | C19: 0 | D19: ='Debt Schedule'!D13 | E19: ='Debt Schedule'!E13 | F19: ='Debt Schedule'!F13 | G19: ='Debt Schedule'!G13 | H19: ='Debt Schedule'!H13 | I19: ='Debt Schedule'!I13 | J19: ='Debt Schedule'!J13 | K19: ='Debt Schedule'!K13 | ... W19: ='Debt Schedule'!W13 | X19: =SUM(D19:G19) | Y19: =SUM(H19:K19) | Z19: =SUM(L19:O19) | AA19: =SUM(P19:S19) | AB19: =SUM(T19:W19)
A20: Depreciation | B20: CapEx Depreciation output | C20: ='CapEx Depreciation'!C10 | D20: ='CapEx Depreciation'!D10 | E20: ='CapEx Depreciation'!E10 | F20: ='CapEx Depreciation'!F10 | G20: ='CapEx Depreciation'!G10 | H20: ='CapEx Depreciation'!H10 | I20: ='CapEx Depreciation'!I10 | J20: ='CapEx Depreciation'!J10 | ... W20: ='CapEx Depreciation'!W10 | X20: =SUM(D20:G20) | Y20: =SUM(H20:K20) | Z20: =SUM(L20:O20) | AA20: =SUM(P20:S20) | AB20: =SUM(T20:W20)
A21: Depreciation Expense | B21: CapEx Depreciation output | C21: ='CapEx Depreciation'!C11 | D21: ='CapEx Depreciation'!D11 | E21: ='CapEx Depreciation'!E11 | F21: ='CapEx Depreciation'!F11 | G21: ='CapEx Depreciation'!G11 | H21: ='CapEx Depreciation'!H11 | I21: ='CapEx Depreciation'!I11 | J21: ='CapEx Depreciation'!J11 | ... W21: ='CapEx Depreciation'!W11 | X21: =SUM(D21:G21) | Y21: =SUM(H21:K21) | Z21: =SUM(L21:O21) | AA21: =SUM(P21:S21) | AB21: =SUM(T21:W21)
A22: Taxes | B22: Direct model driver | C22: 0.269425 | D22: 0.269425 | E22: 0.269425 | F22: 0.269425 | G22: 0.269425 | H22: 0.269425 | I22: 0.269425 | J22: 0.269425 | K22: 0.269425 | L22: 0.269425 | M22: 0.269425 | N22: 0.269425 | O22: 0.269425 | P22: 0.269425 | Q22: 0.269425 | R22: 0.269425 | S22: 0.269425 | T22: 0.269425 | U22: 0.269425 | V22: 0.269425 | W22: 0.269425 | X22: =SUM(D22:G22) | Y22: =SUM(H22:K22) | Z22: =SUM(L22:O22) | AA22: =SUM(P22:S22) | AB22: =SUM(T22:W22)
A24: Balance Sheet Inputs
A25: Accounts Receivable Days | B25: Working Capital schedule | C25: ='Working Capital'!C7 | D25: ='Working Capital'!D7 | E25: ='Working Capital'!E7 | F25: ='Working Capital'!F7 | G25: ='Working Capital'!G7 | H25: ='Working Capital'!H7 | I25: ='Working Capital'!I7 | J25: ='Working Capital'!J7 | ... W25: ='Working Capital'!W7 | X25: =SUM(D25:G25) | Y25: =SUM(H25:K25) | Z25: =SUM(L25:O25) | AA25: =SUM(P25:S25) | AB25: =SUM(T25:W25)
A26: Inventory Days | B26: Working Capital schedule | C26: ='Working Capital'!C8 | D26: ='Working Capital'!D8 | E26: ='Working Capital'!E8 | F26: ='Working Capital'!F8 | G26: ='Working Capital'!G8 | H26: ='Working Capital'!H8 | I26: ='Working Capital'!I8 | J26: ='Working Capital'!J8 | ... W26: ='Working Capital'!W8 | X26: =SUM(D26:G26) | Y26: =SUM(H26:K26) | Z26: =SUM(L26:O26) | AA26: =SUM(P26:S26) | AB26: =SUM(T26:W26)
A27: Accounts Payable Days | B27: Working Capital schedule | C27: ='Working Capital'!C9 | D27: ='Working Capital'!D9 | E27: ='Working Capital'!E9 | F27: ='Working Capital'!F9 | G27: ='Working Capital'!G9 | H27: ='Working Capital'!H9 | I27: ='Working Capital'!I9 | J27: ='Working Capital'!J9 | ... W27: ='Working Capital'!W9 | X27: =SUM(D27:G27) | Y27: =SUM(H27:K27) | Z27: =SUM(L27:O27) | AA27: =SUM(P27:S27) | AB27: =SUM(T27:W27)
A28: Prepaid Expenses (% of Revenue) | B28: Working Capital schedule | C28: ='Working Capital'!C10 | D28: ='Working Capital'!D10 | E28: ='Working Capital'!E10 | F28: ='Working Capital'!F10 | G28: ='Working Capital'!G10 | H28: ='Working Capital'!H10 | I28: ='Working Capital'!I10 | J28: ='Working Capital'!J10 | ... W28: ='Working Capital'!W10 | X28: =SUM(D28:G28) | Y28: =SUM(H28:K28) | Z28: =SUM(L28:O28) | AA28: =SUM(P28:S28) | AB28: =SUM(T28:W28)
A29: Deferred Revenue (% of Revenue) | B29: Working Capital schedule | C29: ='Working Capital'!C11 | D29: ='Working Capital'!D11 | E29: ='Working Capital'!E11 | F29: ='Working Capital'!F11 | G29: ='Working Capital'!G11 | H29: ='Working Capital'!H11 | I29: ='Working Capital'!I11 | J29: ='Working Capital'!J11 | ... W29: ='Working Capital'!W11 | X29: =SUM(D29:G29) | Y29: =SUM(H29:K29) | Z29: =SUM(L29:O29) | AA29: =SUM(P29:S29) | AB29: =SUM(T29:W29)
A30: Short Term Debt (% of LTD) | B30: Working Capital schedule | C30: ='Working Capital'!C12 | D30: ='Working Capital'!D12 | E30: ='Working Capital'!E12 | F30: ='Working Capital'!F12 | G30: ='Working Capital'!G12 | H30: ='Working Capital'!H12 | I30: ='Working Capital'!I12 | J30: ='Working Capital'!J12 | ... W30: ='Working Capital'!W12 | X30: =SUM(D30:G30) | Y30: =SUM(H30:K30) | Z30: =SUM(L30:O30) | AA30: =SUM(P30:S30) | AB30: =SUM(T30:W30)
A31: Owner's Capital | B31: Cash Equity Schedule schedule | C31: ='Cash Equity Schedule'!C7 | D31: ='Cash Equity Schedule'!D7 | E31: ='Cash Equity Schedule'!E7 | F31: ='Cash Equity Schedule'!F7 | G31: ='Cash Equity Schedule'!G7 | H31: ='Cash Equity Schedule'!H7 | I31: ='Cash Equity Schedule'!I7 | J31: ='Cash Equity Schedule'!J7 | ... W31: ='Cash Equity Schedule'!W7 | X31: =G31 | Y31: =K31 | Z31: =O31 | AA31: =S31 | AB31: =W31
A32: Other Equity | B32: Cash Equity Schedule schedule | C32: ='Cash Equity Schedule'!C8 | D32: ='Cash Equity Schedule'!D8 | E32: ='Cash Equity Schedule'!E8 | F32: ='Cash Equity Schedule'!F8 | G32: ='Cash Equity Schedule'!G8 | H32: ='Cash Equity Schedule'!H8 | I32: ='Cash Equity Schedule'!I8 | J32: ='Cash Equity Schedule'!J8 | ... W32: ='Cash Equity Schedule'!W8 | X32: =G32 | Y32: =K32 | Z32: =O32 | AA32: =S32 | AB32: =W32
A33: Distributions | B33: Cash Equity Schedule schedule | C33: ='Cash Equity Schedule'!C9 | D33: ='Cash Equity Schedule'!D9 | E33: ='Cash Equity Schedule'!E9 | F33: ='Cash Equity Schedule'!F9 | G33: ='Cash Equity Schedule'!G9 | H33: ='Cash Equity Schedule'!H9 | I33: ='Cash Equity Schedule'!I9 | J33: ='Cash Equity Schedule'!J9 | ... W33: ='Cash Equity Schedule'!W9 | X33: =G33 | Y33: =K33 | Z33: =O33 | AA33: =S33 | AB33: =W33
A35: Cash Flow and Schedule Inputs
A36: Cash Opening Balance | B36: Working Capital schedule | C36: ='Working Capital'!C15 | D36: ='Working Capital'!D15 | E36: ='Working Capital'!E15 | F36: ='Working Capital'!F15 | G36: ='Working Capital'!G15 | H36: ='Working Capital'!H15 | I36: ='Working Capital'!I15 | J36: ='Working Capital'!J15 | ... W36: ='Working Capital'!W15 | X36: =G36 | Y36: =K36 | Z36: =O36 | AA36: =S36 | AB36: =W36
A37: Accounts Receivable Opening Balance | B37: Working Capital schedule | C37: ='Working Capital'!C16 | D37: ='Working Capital'!D16 | E37: ='Working Capital'!E16 | F37: ='Working Capital'!F16 | G37: ='Working Capital'!G16 | H37: ='Working Capital'!H16 | I37: ='Working Capital'!I16 | J37: ='Working Capital'!J16 | ... W37: ='Working Capital'!W16 | X37: =G37 | Y37: =K37 | Z37: =O37 | AA37: =S37 | AB37: =W37
A38: Inventory Opening Balance | B38: Working Capital schedule | C38: ='Working Capital'!C17 | D38: ='Working Capital'!D17 | E38: ='Working Capital'!E17 | F38: ='Working Capital'!F17 | G38: ='Working Capital'!G17 | H38: ='Working Capital'!H17 | I38: ='Working Capital'!I17 | J38: ='Working Capital'!J17 | ... W38: ='Working Capital'!W17 | X38: =G38 | Y38: =K38 | Z38: =O38 | AA38: =S38 | AB38: =W38
A39: Accounts Payable Opening Balance | B39: Working Capital schedule | C39: ='Working Capital'!C18 | D39: ='Working Capital'!D18 | E39: ='Working Capital'!E18 | F39: ='Working Capital'!F18 | G39: ='Working Capital'!G18 | H39: ='Working Capital'!H18 | I39: ='Working Capital'!I18 | J39: ='Working Capital'!J18 | ... W39: ='Working Capital'!W18 | X39: =G39 | Y39: =K39 | Z39: =O39 | AA39: =S39 | AB39: =W39
A40: Short Term Debt Opening Balance | B40: Working Capital schedule | C40: ='Working Capital'!C19 | D40: ='Working Capital'!D19 | E40: ='Working Capital'!E19 | F40: ='Working Capital'!F19 | G40: ='Working Capital'!G19 | H40: ='Working Capital'!H19 | I40: ='Working Capital'!I19 | J40: ='Working Capital'!J19 | ... W40: ='Working Capital'!W19 | X40: =G40 | Y40: =K40 | Z40: =O40 | AA40: =S40 | AB40: =W40
A41: Debt Opening Balance | B41: Debt Schedule schedule | C41: ='Debt Schedule'!C7 | D41: ='Debt Schedule'!D7 | E41: ='Debt Schedule'!E7 | F41: ='Debt Schedule'!F7 | G41: ='Debt Schedule'!G7 | H41: ='Debt Schedule'!H7 | I41: ='Debt Schedule'!I7 | J41: ='Debt Schedule'!J7 | ... W41: ='Debt Schedule'!W7 | X41: =G41 | Y41: =K41 | Z41: =O41 | AA41: =S41 | AB41: =W41
A42: Debt Issuance | B42: Debt Schedule schedule | C42: ='Debt Schedule'!C8 | D42: ='Debt Schedule'!D8 | E42: ='Debt Schedule'!E8 | F42: ='Debt Schedule'!F8 | G42: ='Debt Schedule'!G8 | H42: ='Debt Schedule'!H8 | I42: ='Debt Schedule'!I8 | J42: ='Debt Schedule'!J8 | ... W42: ='Debt Schedule'!W8 | X42: =SUM(D42:G42) | Y42: =SUM(H42:K42) | Z42: =SUM(L42:O42) | AA42: =SUM(P42:S42) | AB42: =SUM(T42:W42)
A43: Debt Repayment | B43: Debt Schedule schedule | C43: ='Debt Schedule'!C10 | D43: ='Debt Schedule'!D10 | E43: ='Debt Schedule'!E10 | F43: ='Debt Schedule'!F10 | G43: ='Debt Schedule'!G10 | H43: ='Debt Schedule'!H10 | I43: ='Debt Schedule'!I10 | J43: ='Debt Schedule'!J10 | ... W43: ='Debt Schedule'!W10 | X43: =SUM(D43:G43) | Y43: =SUM(H43:K43) | Z43: =SUM(L43:O43) | AA43: =SUM(P43:S43) | AB43: =SUM(T43:W43)
A44: Debt Closing Balance | B44: Debt Schedule schedule | C44: ='Debt Schedule'!C11 | D44: ='Debt Schedule'!D11 | E44: ='Debt Schedule'!E11 | F44: ='Debt Schedule'!F11 | G44: ='Debt Schedule'!G11 | H44: ='Debt Schedule'!H11 | I44: ='Debt Schedule'!I11 | J44: ='Debt Schedule'!J11 | ... W44: ='Debt Schedule'!W11 | X44: =G44 | Y44: =K44 | Z44: =O44 | AA44: =S44 | AB44: =W44
A45: Lease Opening Balance | B45: Debt Schedule schedule | C45: ='Debt Schedule'!C18 | D45: ='Debt Schedule'!D18 | E45: ='Debt Schedule'!E18 | F45: ='Debt Schedule'!F18 | G45: ='Debt Schedule'!G18 | H45: ='Debt Schedule'!H18 | I45: ='Debt Schedule'!I18 | J45: ='Debt Schedule'!J18 | ... W45: ='Debt Schedule'!W18 | X45: =G45 | Y45: =K45 | Z45: =O45 | AA45: =S45 | AB45: =W45
A46: Lease Principal Repayments | B46: Debt Schedule schedule | C46: ='Debt Schedule'!C20 | D46: ='Debt Schedule'!D20 | E46: ='Debt Schedule'!E20 | F46: ='Debt Schedule'!F20 | G46: ='Debt Schedule'!G20 | H46: ='Debt Schedule'!H20 | I46: ='Debt Schedule'!I20 | J46: ='Debt Schedule'!J20 | ... W46: ='Debt Schedule'!W20 | X46: =SUM(D46:G46) | Y46: =SUM(H46:K46) | Z46: =SUM(L46:O46) | AA46: =SUM(P46:S46) | AB46: =SUM(T46:W46)
A47: Lease Net Additions | B47: Debt Schedule schedule | C47: ='Debt Schedule'!C21 | D47: ='Debt Schedule'!D21 | E47: ='Debt Schedule'!E21 | F47: ='Debt Schedule'!F21 | G47: ='Debt Schedule'!G21 | H47: ='Debt Schedule'!H21 | I47: ='Debt Schedule'!I21 | J47: ='Debt Schedule'!J21 | ... W47: ='Debt Schedule'!W21 | X47: =SUM(D47:G47) | Y47: =SUM(H47:K47) | Z47: =SUM(L47:O47) | AA47: =SUM(P47:S47) | AB47: =SUM(T47:W47)
A48: Lease Interest Expense | B48: Debt Schedule schedule | C48: ='Debt Schedule'!C22 | D48: ='Debt Schedule'!D22 | E48: ='Debt Schedule'!E22 | F48: ='Debt Schedule'!F22 | G48: ='Debt Schedule'!G22 | H48: ='Debt Schedule'!H22 | I48: ='Debt Schedule'!I22 | J48: ='Debt Schedule'!J22 | ... W48: ='Debt Schedule'!W22 | X48: =SUM(D48:G48) | Y48: =SUM(H48:K48) | Z48: =SUM(L48:O48) | AA48: =SUM(P48:S48) | AB48: =SUM(T48:W48)
A49: Lease Closing Balance | B49: Debt Schedule schedule | C49: ='Debt Schedule'!C23 | D49: ='Debt Schedule'!D23 | E49: ='Debt Schedule'!E23 | F49: ='Debt Schedule'!F23 | G49: ='Debt Schedule'!G23 | H49: ='Debt Schedule'!H23 | I49: ='Debt Schedule'!I23 | J49: ='Debt Schedule'!J23 | ... W49: ='Debt Schedule'!W23 | X49: =G49 | Y49: =K49 | Z49: =O49 | AA49: =S49 | AB49: =W49
A50: Right-of-Use Asset | B50: Debt Schedule schedule | C50: ='Debt Schedule'!C26 | D50: ='Debt Schedule'!D26 | E50: ='Debt Schedule'!E26 | F50: ='Debt Schedule'!F26 | G50: ='Debt Schedule'!G26 | H50: ='Debt Schedule'!H26 | I50: ='Debt Schedule'!I26 | J50: ='Debt Schedule'!J26 | ... W50: ='Debt Schedule'!W26 | X50: =G50 | Y50: =K50 | Z50: =O50 | AA50: =S50 | AB50: =W50
A51: Lease Asset Depreciation | B51: Debt Schedule schedule | C51: ='Debt Schedule'!C25 | D51: ='Debt Schedule'!D25 | E51: ='Debt Schedule'!E25 | F51: ='Debt Schedule'!F25 | G51: ='Debt Schedule'!G25 | H51: ='Debt Schedule'!H25 | I51: ='Debt Schedule'!I25 | J51: ='Debt Schedule'!J25 | ... W51: ='Debt Schedule'!W25 | X51: =SUM(D51:G51) | Y51: =SUM(H51:K51) | Z51: =SUM(L51:O51) | AA51: =SUM(P51:S51) | AB51: =SUM(T51:W51)
A52: Capital Expenditures | B52: CapEx Depreciation schedule | C52: ='CapEx Depreciation'!C8 | D52: ='CapEx Depreciation'!D8 | E52: ='CapEx Depreciation'!E8 | F52: ='CapEx Depreciation'!F8 | G52: ='CapEx Depreciation'!G8 | H52: ='CapEx Depreciation'!H8 | I52: ='CapEx Depreciation'!I8 | J52: ='CapEx Depreciation'!J8 | ... W52: ='CapEx Depreciation'!W8 | X52: =SUM(D52:G52) | Y52: =SUM(H52:K52) | Z52: =SUM(L52:O52) | AA52: =SUM(P52:S52) | AB52: =SUM(T52:W52)
A53: PPE Closing Balance | B53: CapEx Depreciation schedule | C53: ='CapEx Depreciation'!C12 | D53: ='CapEx Depreciation'!D12 | E53: ='CapEx Depreciation'!E12 | F53: ='CapEx Depreciation'!F12 | G53: ='CapEx Depreciation'!G12 | H53: ='CapEx Depreciation'!H12 | I53: ='CapEx Depreciation'!I12 | J53: ='CapEx Depreciation'!J12 | ... W53: ='CapEx Depreciation'!W12 | X53: =G53 | Y53: =K53 | Z53: =O53 | AA53: =S53 | AB53: =W53
A54: Accumulated Depreciation | B54: CapEx Depreciation schedule | C54: ='CapEx Depreciation'!C14 | D54: ='CapEx Depreciation'!D14 | E54: ='CapEx Depreciation'!E14 | F54: ='CapEx Depreciation'!F14 | G54: ='CapEx Depreciation'!G14 | H54: ='CapEx Depreciation'!H14 | I54: ='CapEx Depreciation'!I14 | J54: ='CapEx Depreciation'!J14 | ... W54: ='CapEx Depreciation'!W14 | X54: =G54 | Y54: =K54 | Z54: =O54 | AA54: =S54 | AB54: =W54

Sheet FINMO
A1: FINMO
A2: Three-statement financial model. All formulas reference Model Inputs and in-sheet statement rows.
C4: Stub | D4: Q1 | E4: Q2 | F4: Q3 | G4: Q4 | H4: Q5 | I4: Q6 | J4: Q7 | K4: Q8 | L4: Q9 | M4: Q10 | N4: Q11 | O4: Q12 | P4: Q13 | Q4: Q14 | R4: Q15 | S4: Q16 | T4: Q17 | U4: Q18 | V4: Q19 | W4: Q20 | X4: Y1 | Y4: Y2 | Z4: Y3 | AA4: Y4 | AB4: Y5
C5: 46162 | D5: 46295 | E5: 46387 | F5: 46477 | G5: 46568 | H5: 46660 | I5: 46752 | J5: 46843 | K5: 46934 | L5: 47026 | M5: 47118 | N5: 47208 | O5: 47299 | P5: 47391 | Q5: 47483 | R5: 47573 | S5: 47664 | T5: 47756 | U5: 47848 | V5: 47938 | W5: 48029 | X5: Annual | Y5: Annual | Z5: Annual | AA5: Annual | AB5: Annual
A6: Days in Quarter | C6: 0 | D6: 92 | E6: 92 | F6: 90 | G6: 91 | H6: 92 | I6: 92 | J6: 91 | K6: 91 | L6: 92 | M6: 92 | N6: 90 | O6: 91 | P6: 92 | Q6: 92 | R6: 90 | S6: 91 | T6: 92 | U6: 92 | V6: 90 | W6: 91
A7: Income Statement
A8: Revenue | B8: Formula | C8: ='Model Inputs'!C11 | D8: ='Model Inputs'!D11 | E8: ='Model Inputs'!E11 | F8: ='Model Inputs'!F11 | G8: ='Model Inputs'!G11 | H8: ='Model Inputs'!H11 | I8: ='Model Inputs'!I11 | J8: ='Model Inputs'!J11 | ... W8: ='Model Inputs'!W11 | X8: =SUM(D8:G8) | Y8: =SUM(H8:K8) | Z8: =SUM(L8:O8) | AA8: =SUM(P8:S8) | AB8: =SUM(T8:W8)
A9: Cost of Goods Sold | B9: Formula | C9: =C8*'Model Inputs'!C12 | D9: =D8*'Model Inputs'!D12 | E9: =E8*'Model Inputs'!E12 | F9: =F8*'Model Inputs'!F12 | G9: =G8*'Model Inputs'!G12 | H9: =H8*'Model Inputs'!H12 | I9: =I8*'Model Inputs'!I12 | J9: =J8*'Model Inputs'!J12 | ... W9: =W8*'Model Inputs'!W12 | X9: =SUM(D9:G9) | Y9: =SUM(H9:K9) | Z9: =SUM(L9:O9) | AA9: =SUM(P9:S9) | AB9: =SUM(T9:W9)
A10: Gross Profit | B10: Formula | C10: =C8-C9 | D10: =D8-D9 | E10: =E8-E9 | F10: =F8-F9 | G10: =G8-G9 | H10: =H8-H9 | I10: =I8-I9 | J10: =J8-J9 | ... W10: =W8-W9 | X10: =SUM(D10:G10) | Y10: =SUM(H10:K10) | Z10: =SUM(L10:O10) | AA10: =SUM(P10:S10) | AB10: =SUM(T10:W10)
A11: Marketing | B11: Formula | C11: =C8*'Model Inputs'!C13 | D11: =D8*'Model Inputs'!D13 | E11: =E8*'Model Inputs'!E13 | F11: =F8*'Model Inputs'!F13 | G11: =G8*'Model Inputs'!G13 | H11: =H8*'Model Inputs'!H13 | I11: =I8*'Model Inputs'!I13 | J11: =J8*'Model Inputs'!J13 | ... W11: =W8*'Model Inputs'!W13 | X11: =SUM(D11:G11) | Y11: =SUM(H11:K11) | Z11: =SUM(L11:O11) | AA11: =SUM(P11:S11) | AB11: =SUM(T11:W11)
A12: Research & Development | B12: Formula | C12: =C8*'Model Inputs'!C14 | D12: =D8*'Model Inputs'!D14 | E12: =E8*'Model Inputs'!E14 | F12: =F8*'Model Inputs'!F14 | G12: =G8*'Model Inputs'!G14 | H12: =H8*'Model Inputs'!H14 | I12: =I8*'Model Inputs'!I14 | J12: =J8*'Model Inputs'!J14 | ... W12: =W8*'Model Inputs'!W14 | X12: =SUM(D12:G12) | Y12: =SUM(H12:K12) | Z12: =SUM(L12:O12) | AA12: =SUM(P12:S12) | AB12: =SUM(T12:W12)
A13: Lease/Rent | B13: Formula | C13: ='Model Inputs'!C15 | D13: ='Model Inputs'!D15 | E13: ='Model Inputs'!E15 | F13: ='Model Inputs'!F15 | G13: ='Model Inputs'!G15 | H13: ='Model Inputs'!H15 | I13: ='Model Inputs'!I15 | J13: ='Model Inputs'!J15 | ... W13: ='Model Inputs'!W15 | X13: =SUM(D13:G13) | Y13: =SUM(H13:K13) | Z13: =SUM(L13:O13) | AA13: =SUM(P13:S13) | AB13: =SUM(T13:W13)
A14: Payroll | B14: Formula | C14: ='Model Inputs'!C16 | D14: ='Model Inputs'!D16 | E14: ='Model Inputs'!E16 | F14: ='Model Inputs'!F16 | G14: ='Model Inputs'!G16 | H14: ='Model Inputs'!H16 | I14: ='Model Inputs'!I16 | J14: ='Model Inputs'!J16 | ... W14: ='Model Inputs'!W16 | X14: =SUM(D14:G14) | Y14: =SUM(H14:K14) | Z14: =SUM(L14:O14) | AA14: =SUM(P14:S14) | AB14: =SUM(T14:W14)
A15: General & Administrative | B15: Formula | C15: =C8*'Model Inputs'!C17 | D15: =D8*'Model Inputs'!D17 | E15: =E8*'Model Inputs'!E17 | F15: =F8*'Model Inputs'!F17 | G15: =G8*'Model Inputs'!G17 | H15: =H8*'Model Inputs'!H17 | I15: =I8*'Model Inputs'!I17 | J15: =J8*'Model Inputs'!J17 | ... W15: =W8*'Model Inputs'!W17 | X15: =SUM(D15:G15) | Y15: =SUM(H15:K15) | Z15: =SUM(L15:O15) | AA15: =SUM(P15:S15) | AB15: =SUM(T15:W15)
A16: EBITDA | B16: Formula | C16: =C10-SUM(C11:C15) | D16: =D10-SUM(D11:D15) | E16: =E10-SUM(E11:E15) | F16: =F10-SUM(F11:F15) | G16: =G10-SUM(G11:G15) | H16: =H10-SUM(H11:H15) | I16: =I10-SUM(I11:I15) | J16: =J10-SUM(J11:J15) | ... W16: =W10-SUM(W11:W15) | X16: =SUM(D16:G16) | Y16: =SUM(H16:K16) | Z16: =SUM(L16:O16) | AA16: =SUM(P16:S16) | AB16: =SUM(T16:W16)
A17: Interest | B17: Formula | C17: ='Model Inputs'!C19+'Model Inputs'!C48 | D17: ='Model Inputs'!D19+'Model Inputs'!D48 | E17: ='Model Inputs'!E19+'Model Inputs'!E48 | F17: ='Model Inputs'!F19+'Model Inputs'!F48 | G17: ='Model Inputs'!G19+'Model Inputs'!G48 | H17: ='Model Inputs'!H19+'Model Inputs'!H48 | I17: ='Model Inputs'!I19+'Model Inputs'!I48 | J17: ='Model Inputs'!J19+'Model Inputs'!J48 | ... W17: ='Model Inputs'!W19+'Model Inputs'!W48 | X17: =SUM(D17:G17) | Y17: =SUM(H17:K17) | Z17: =SUM(L17:O17) | AA17: =SUM(P17:S17) | AB17: =SUM(T17:W17)
A18: Depreciation | B18: Formula | C18: ='Model Inputs'!C21+'Model Inputs'!C51 | D18: ='Model Inputs'!D21+'Model Inputs'!D51 | E18: ='Model Inputs'!E21+'Model Inputs'!E51 | F18: ='Model Inputs'!F21+'Model Inputs'!F51 | G18: ='Model Inputs'!G21+'Model Inputs'!G51 | H18: ='Model Inputs'!H21+'Model Inputs'!H51 | I18: ='Model Inputs'!I21+'Model Inputs'!I51 | J18: ='Model Inputs'!J21+'Model Inputs'!J51 | ... W18: ='Model Inputs'!W21+'Model Inputs'!W51 | X18: =SUM(D18:G18) | Y18: =SUM(H18:K18) | Z18: =SUM(L18:O18) | AA18: =SUM(P18:S18) | AB18: =SUM(T18:W18)
A19: Taxes | B19: Formula | C19: =MAX(0,C16-C17-C18)*'Model Inputs'!C22 | D19: =MAX(0,D16-D17-D18)*'Model Inputs'!D22 | E19: =MAX(0,E16-E17-E18)*'Model Inputs'!E22 | F19: =MAX(0,F16-F17-F18)*'Model Inputs'!F22 | G19: =MAX(0,G16-G17-G18)*'Model Inputs'!G22 | H19: =MAX(0,H16-H17-H18)*'Model Inputs'!H22 | I19: =MAX(0,I16-I17-I18)*'Model Inputs'!I22 | J19: =MAX(0,J16-J17-J18)*'Model Inputs'!J22 | ... W19: =MAX(0,W16-W17-W18)*'Model Inputs'!W22 | X19: =SUM(D19:G19) | Y19: =SUM(H19:K19) | Z19: =SUM(L19:O19) | AA19: =SUM(P19:S19) | AB19: =SUM(T19:W19)
A20: Net Income | B20: Formula | C20: =C16-SUM(C17:C19) | D20: =D16-SUM(D17:D19) | E20: =E16-SUM(E17:E19) | F20: =F16-SUM(F17:F19) | G20: =G16-SUM(G17:G19) | H20: =H16-SUM(H17:H19) | I20: =I16-SUM(I17:I19) | J20: =J16-SUM(J17:J19) | ... W20: =W16-SUM(W17:W19) | X20: =SUM(D20:G20) | Y20: =SUM(H20:K20) | Z20: =SUM(L20:O20) | AA20: =SUM(P20:S20) | AB20: =SUM(T20:W20)
A22: Balance Sheet
A23: Cash | B23: Formula | C23: =C61 | D23: =D61 | E23: =E61 | F23: =F61 | G23: =G61 | H23: =H61 | I23: =I61 | J23: =J61 | ... W23: =W61 | X23: =G23 | Y23: =K23 | Z23: =O23 | AA23: =S23 | AB23: =W23
A24: Accounts Receivable | B24: Formula | C24: ='Model Inputs'!C37 | D24: =('Model Inputs'!D25/D6)*D8 | E24: =('Model Inputs'!E25/E6)*E8 | F24: =('Model Inputs'!F25/F6)*F8 | G24: =('Model Inputs'!G25/G6)*G8 | H24: =('Model Inputs'!H25/H6)*H8 | I24: =('Model Inputs'!I25/I6)*I8 | J24: =('Model Inputs'!J25/J6)*J8 | K24: =('Model Inputs'!K25/K6)*K8 | ... W24: =('Model Inputs'!W25/W6)*W8 | X24: =G24 | Y24: =K24 | Z24: =O24 | AA24: =S24 | AB24: =W24
A25: Inventory | B25: Formula | C25: ='Model Inputs'!C38 | D25: =('Model Inputs'!D26/D6)*D9 | E25: =('Model Inputs'!E26/E6)*E9 | F25: =('Model Inputs'!F26/F6)*F9 | G25: =('Model Inputs'!G26/G6)*G9 | H25: =('Model Inputs'!H26/H6)*H9 | I25: =('Model Inputs'!I26/I6)*I9 | J25: =('Model Inputs'!J26/J6)*J9 | K25: =('Model Inputs'!K26/K6)*K9 | ... W25: =('Model Inputs'!W26/W6)*W9 | X25: =G25 | Y25: =K25 | Z25: =O25 | AA25: =S25 | AB25: =W25
A26: Prepaid Expenses | B26: Formula | C26: =0 | D26: =D8*'Model Inputs'!D28 | E26: =E8*'Model Inputs'!E28 | F26: =F8*'Model Inputs'!F28 | G26: =G8*'Model Inputs'!G28 | H26: =H8*'Model Inputs'!H28 | I26: =I8*'Model Inputs'!I28 | J26: =J8*'Model Inputs'!J28 | K26: =K8*'Model Inputs'!K28 | ... W26: =W8*'Model Inputs'!W28 | X26: =G26 | Y26: =K26 | Z26: =O26 | AA26: =S26 | AB26: =W26
A27: Current Assets | B27: Formula | C27: =SUM(C23:C26) | D27: =SUM(D23:D26) | E27: =SUM(E23:E26) | F27: =SUM(F23:F26) | G27: =SUM(G23:G26) | H27: =SUM(H23:H26) | I27: =SUM(I23:I26) | J27: =SUM(J23:J26) | ... W27: =SUM(W23:W26) | X27: =G27 | Y27: =K27 | Z27: =O27 | AA27: =S27 | AB27: =W27
A28: PPE | B28: Formula | C28: ='Model Inputs'!C53 | D28: ='Model Inputs'!D53 | E28: ='Model Inputs'!E53 | F28: ='Model Inputs'!F53 | G28: ='Model Inputs'!G53 | H28: ='Model Inputs'!H53 | I28: ='Model Inputs'!I53 | J28: ='Model Inputs'!J53 | ... W28: ='Model Inputs'!W53 | X28: =G28 | Y28: =K28 | Z28: =O28 | AA28: =S28 | AB28: =W28
A29: Right-of-Use Asset (Capital Lease) | B29: Formula | C29: ='Model Inputs'!C50 | D29: ='Model Inputs'!D50 | E29: ='Model Inputs'!E50 | F29: ='Model Inputs'!F50 | G29: ='Model Inputs'!G50 | H29: ='Model Inputs'!H50 | I29: ='Model Inputs'!I50 | J29: ='Model Inputs'!J50 | ... W29: ='Model Inputs'!W50 | X29: =G29 | Y29: =K29 | Z29: =O29 | AA29: =S29 | AB29: =W29
A30: Accumulated Depreciation | B30: Formula | C30: ='Model Inputs'!C54 | D30: ='Model Inputs'!D54 | E30: ='Model Inputs'!E54 | F30: ='Model Inputs'!F54 | G30: ='Model Inputs'!G54 | H30: ='Model Inputs'!H54 | I30: ='Model Inputs'!I54 | J30: ='Model Inputs'!J54 | ... W30: ='Model Inputs'!W54 | X30: =G30 | Y30: =K30 | Z30: =O30 | AA30: =S30 | AB30: =W30
A31: Total Assets | B31: Formula | C31: =C27+C28+C29 | D31: =D27+D28+D29 | E31: =E27+E28+E29 | F31: =F27+F28+F29 | G31: =G27+G28+G29 | H31: =H27+H28+H29 | I31: =I27+I28+I29 | J31: =J27+J28+J29 | ... W31: =W27+W28+W29 | X31: =G31 | Y31: =K31 | Z31: =O31 | AA31: =S31 | AB31: =W31
A32: Accounts Payable | B32: Formula | C32: ='Model Inputs'!C39 | D32: =('Model Inputs'!D27/D6)*SUM(D11:D15) | E32: =('Model Inputs'!E27/E6)*SUM(E11:E15) | F32: =('Model Inputs'!F27/F6)*SUM(F11:F15) | G32: =('Model Inputs'!G27/G6)*SUM(G11:G15) | H32: =('Model Inputs'!H27/H6)*SUM(H11:H15) | I32: =('Model Inputs'!I27/I6)*SUM(I11:I15) | J32: =('Model Inputs'!J27/J6)*SUM(J11:J15) | K32: =('Model Inputs'!K27/K6)*SUM(K11:K15) | ... W32: =('Model Inputs'!W27/W6)*SUM(W11:W15) | X32: =G32 | Y32: =K32 | Z32: =O32 | AA32: =S32 | AB32: =W32
A33: Short Term Debt | B33: Formula | C33: ='Model Inputs'!C40 | D33: =SUM('Debt Schedule'!E10:H10) | E33: =SUM('Debt Schedule'!F10:I10) | F33: =SUM('Debt Schedule'!G10:J10) | G33: =SUM('Debt Schedule'!H10:K10) | H33: =SUM('Debt Schedule'!I10:L10) | I33: =SUM('Debt Schedule'!J10:M10) | J33: =SUM('Debt Schedule'!K10:N10) | K33: =SUM('Debt Schedule'!L10:O10) | ... S33: =SUM('Debt Schedule'!T10:W10) | T33: =SUM('Debt Schedule'!U10:W10) | U33: =SUM('Debt Schedule'!V10:W10) | V33: =SUM('Debt Schedule'!W10:W10) | W33: =0 | X33: =G33 | Y33: =K33 | Z33: =O33 | AA33: =S33 | AB33: =W33
A34: Deferred Revenue | B34: Formula | C34: =0 | D34: ='Model Inputs'!D29*D8 | E34: ='Model Inputs'!E29*E8 | F34: ='Model Inputs'!F29*F8 | G34: ='Model Inputs'!G29*G8 | H34: ='Model Inputs'!H29*H8 | I34: ='Model Inputs'!I29*I8 | J34: ='Model Inputs'!J29*J8 | K34: ='Model Inputs'!K29*K8 | ... W34: ='Model Inputs'!W29*W8 | X34: =G34 | Y34: =K34 | Z34: =O34 | AA34: =S34 | AB34: =W34
A35: Current Liabilities | B35: Formula | C35: =SUM(C32:C34) | D35: =SUM(D32:D34) | E35: =SUM(E32:E34) | F35: =SUM(F32:F34) | G35: =SUM(G32:G34) | H35: =SUM(H32:H34) | I35: =SUM(I32:I34) | J35: =SUM(J32:J34) | ... W35: =SUM(W32:W34) | X35: =G35 | Y35: =K35 | Z35: =O35 | AA35: =S35 | AB35: =W35
A36: Long Term Debt | B36: Formula | C36: =MAX(0,'Model Inputs'!C41-C33) | D36: =MAX(0,'Model Inputs'!D44-D33) | E36: =MAX(0,'Model Inputs'!E44-E33) | F36: =MAX(0,'Model Inputs'!F44-F33) | G36: =MAX(0,'Model Inputs'!G44-G33) | H36: =MAX(0,'Model Inputs'!H44-H33) | I36: =MAX(0,'Model Inputs'!I44-I33) | J36: =MAX(0,'Model Inputs'!J44-J33) | K36: =MAX(0,'Model Inputs'!K44-K33) | ... W36: =MAX(0,'Model Inputs'!W44-W33) | X36: =G36 | Y36: =K36 | Z36: =O36 | AA36: =S36 | AB36: =W36
A37: Capital Lease Obligation | B37: Formula | C37: ='Model Inputs'!C49 | D37: ='Model Inputs'!D49 | E37: ='Model Inputs'!E49 | F37: ='Model Inputs'!F49 | G37: ='Model Inputs'!G49 | H37: ='Model Inputs'!H49 | I37: ='Model Inputs'!I49 | J37: ='Model Inputs'!J49 | ... W37: ='Model Inputs'!W49 | X37: =G37 | Y37: =K37 | Z37: =O37 | AA37: =S37 | AB37: =W37
A38: Total Liabilities | B38: Formula | C38: =C35+C36+C37 | D38: =D35+D36+D37 | E38: =E35+E36+E37 | F38: =F35+F36+F37 | G38: =G35+G36+G37 | H38: =H35+H36+H37 | I38: =I35+I36+I37 | J38: =J35+J36+J37 | ... W38: =W35+W36+W37 | X38: =G38 | Y38: =K38 | Z38: =O38 | AA38: =S38 | AB38: =W38
A39: Owner's Capital | B39: Formula | C39: ='Model Inputs'!C31 | D39: ='Model Inputs'!D31 | E39: ='Model Inputs'!E31 | F39: ='Model Inputs'!F31 | G39: ='Model Inputs'!G31 | H39: ='Model Inputs'!H31 | I39: ='Model Inputs'!I31 | J39: ='Model Inputs'!J31 | ... W39: ='Model Inputs'!W31 | X39: =G39 | Y39: =K39 | Z39: =O39 | AA39: =S39 | AB39: =W39
A40: Retained Earnings | B40: Formula | C40: =C31-C38-C39-C41 | D40: =C40+D20-'Model Inputs'!D33 | E40: =D40+E20-'Model Inputs'!E33 | F40: =E40+F20-'Model Inputs'!F33 | G40: =F40+G20-'Model Inputs'!G33 | H40: =G40+H20-'Model Inputs'!H33 | I40: =H40+I20-'Model Inputs'!I33 | J40: =I40+J20-'Model Inputs'!J33 | K40: =J40+K20-'Model Inputs'!K33 | ... W40: =V40+W20-'Model Inputs'!W33 | X40: =G40 | Y40: =K40 | Z40: =O40 | AA40: =S40 | AB40: =W40
A41: Other Equity | B41: Formula | C41: ='Model Inputs'!C32 | D41: ='Model Inputs'!D32 | E41: ='Model Inputs'!E32 | F41: ='Model Inputs'!F32 | G41: ='Model Inputs'!G32 | H41: ='Model Inputs'!H32 | I41: ='Model Inputs'!I32 | J41: ='Model Inputs'!J32 | ... W41: ='Model Inputs'!W32 | X41: =G41 | Y41: =K41 | Z41: =O41 | AA41: =S41 | AB41: =W41
A42: Total Equity | B42: Formula | C42: =C39+C40+C41 | D42: =D39+D40+D41 | E42: =E39+E40+E41 | F42: =F39+F40+F41 | G42: =G39+G40+G41 | H42: =H39+H40+H41 | I42: =I39+I40+I41 | J42: =J39+J40+J41 | ... W42: =W39+W40+W41 | X42: =G42 | Y42: =K42 | Z42: =O42 | AA42: =S42 | AB42: =W42
A43: Total Liabilities & Equity | B43: Formula | C43: =C38+C42 | D43: =D38+D42 | E43: =E38+E42 | F43: =F38+F42 | G43: =G38+G42 | H43: =H38+H42 | I43: =I38+I42 | J43: =J38+J42 | ... W43: =W38+W42 | X43: =G43 | Y43: =K43 | Z43: =O43 | AA43: =S43 | AB43: =W43
A45: Cash Flow
A46: Beginning Cash | B46: Formula | C46: ='Model Inputs'!C36 | D46: =C61 | E46: =D61 | F46: =E61 | G46: =F61 | H46: =G61 | I46: =H61 | J46: =I61 | K46: =J61 | ... W46: =V61 | X46: =SUM(D46:G46) | Y46: =SUM(H46:K46) | Z46: =SUM(L46:O46) | AA46: =SUM(P46:S46) | AB46: =SUM(T46:W46)
A47: Net Income | B47: Formula | C47: =0 | D47: =D20 | E47: =E20 | F47: =F20 | G47: =G20 | H47: =H20 | I47: =I20 | J47: =J20 | K47: =K20 | ... W47: =W20 | X47: =SUM(D47:G47) | Y47: =SUM(H47:K47) | Z47: =SUM(L47:O47) | AA47: =SUM(P47:S47) | AB47: =SUM(T47:W47)
A48: Depreciation | B48: Formula | C48: =0 | D48: =D18 | E48: =E18 | F48: =F18 | G48: =G18 | H48: =H18 | I48: =I18 | J48: =J18 | K48: =K18 | ... W48: =W18 | X48: =SUM(D48:G48) | Y48: =SUM(H48:K48) | Z48: =SUM(L48:O48) | AA48: =SUM(P48:S48) | AB48: =SUM(T48:W48)
A49: Changes in Current Assets | B49: Formula | C49: =0 | D49: =-((D24+D25+D26)-(C24+C25+C26)) | E49: =-((E24+E25+E26)-(D24+D25+D26)) | F49: =-((F24+F25+F26)-(E24+E25+E26)) | G49: =-((G24+G25+G26)-(F24+F25+F26)) | H49: =-((H24+H25+H26)-(G24+G25+G26)) | I49: =-((I24+I25+I26)-(H24+H25+H26)) | J49: =-((J24+J25+J26)-(I24+I25+I26)) | K49: =-((K24+K25+K26)-(J24+J25+J26)) | ... W49: =-((W24+W25+W26)-(V24+V25+V26)) | X49: =SUM(D49:G49) | Y49: =SUM(H49:K49) | Z49: =SUM(L49:O49) | AA49: =SUM(P49:S49) | AB49: =SUM(T49:W49)
A50: Changes in Current Liabilities | B50: Formula | C50: =0 | D50: =(D32+D34)-(C32+C34) | E50: =(E32+E34)-(D32+D34) | F50: =(F32+F34)-(E32+E34) | G50: =(G32+G34)-(F32+F34) | H50: =(H32+H34)-(G32+G34) | I50: =(I32+I34)-(H32+H34) | J50: =(J32+J34)-(I32+I34) | K50: =(K32+K34)-(J32+J34) | ... W50: =(W32+W34)-(V32+V34) | X50: =SUM(D50:G50) | Y50: =SUM(H50:K50) | Z50: =SUM(L50:O50) | AA50: =SUM(P50:S50) | AB50: =SUM(T50:W50)
A51: Operating Cash Flow | B51: Formula | C51: =0 | D51: =SUM(D47:D50) | E51: =SUM(E47:E50) | F51: =SUM(F47:F50) | G51: =SUM(G47:G50) | H51: =SUM(H47:H50) | I51: =SUM(I47:I50) | J51: =SUM(J47:J50) | K51: =SUM(K47:K50) | ... W51: =SUM(W47:W50) | X51: =SUM(D51:G51) | Y51: =SUM(H51:K51) | Z51: =SUM(L51:O51) | AA51: =SUM(P51:S51) | AB51: =SUM(T51:W51)
A52: Capital Expenditures | B52: Formula | C52: ='Model Inputs'!C52 | D52: ='Model Inputs'!D52 | E52: ='Model Inputs'!E52 | F52: ='Model Inputs'!F52 | G52: ='Model Inputs'!G52 | H52: ='Model Inputs'!H52 | I52: ='Model Inputs'!I52 | J52: ='Model Inputs'!J52 | ... W52: ='Model Inputs'!W52 | X52: =SUM(D52:G52) | Y52: =SUM(H52:K52) | Z52: =SUM(L52:O52) | AA52: =SUM(P52:S52) | AB52: =SUM(T52:W52)
A53: Investing Cash Flow | B53: Formula | C53: =0 | D53: =-D52 | E53: =-E52 | F53: =-F52 | G53: =-G52 | H53: =-H52 | I53: =-I52 | J53: =-J52 | K53: =-K52 | ... W53: =-W52 | X53: =SUM(D53:G53) | Y53: =SUM(H53:K53) | Z53: =SUM(L53:O53) | AA53: =SUM(P53:S53) | AB53: =SUM(T53:W53)
A54: Debt Issuance (New Borrowing) | B54: Formula | C54: ='Model Inputs'!C42 | D54: ='Model Inputs'!D42 | E54: ='Model Inputs'!E42 | F54: ='Model Inputs'!F42 | G54: ='Model Inputs'!G42 | H54: ='Model Inputs'!H42 | I54: ='Model Inputs'!I42 | J54: ='Model Inputs'!J42 | ... W54: ='Model Inputs'!W42 | X54: =SUM(D54:G54) | Y54: =SUM(H54:K54) | Z54: =SUM(L54:O54) | AA54: =SUM(P54:S54) | AB54: =SUM(T54:W54)
A55: Debt Repayment | B55: Formula | C55: ='Model Inputs'!C43 | D55: ='Model Inputs'!D43 | E55: ='Model Inputs'!E43 | F55: ='Model Inputs'!F43 | G55: ='Model Inputs'!G43 | H55: ='Model Inputs'!H43 | I55: ='Model Inputs'!I43 | J55: ='Model Inputs'!J43 | ... W55: ='Model Inputs'!W43 | X55: =SUM(D55:G55) | Y55: =SUM(H55:K55) | Z55: =SUM(L55:O55) | AA55: =SUM(P55:S55) | AB55: =SUM(T55:W55)
A56: Equity | B56: Formula | C56: =0 | D56: =(D39-C39)+(D41-C41) | E56: =(E39-D39)+(E41-D41) | F56: =(F39-E39)+(F41-E41) | G56: =(G39-F39)+(G41-F41) | H56: =(H39-G39)+(H41-G41) | I56: =(I39-H39)+(I41-H41) | J56: =(J39-I39)+(J41-I41) | K56: =(K39-J39)+(K41-J41) | ... W56: =(W39-V39)+(W41-V41) | X56: =SUM(D56:G56) | Y56: =SUM(H56:K56) | Z56: =SUM(L56:O56) | AA56: =SUM(P56:S56) | AB56: =SUM(T56:W56)
A57: Distributions | B57: Formula | C57: ='Model Inputs'!C33 | D57: ='Model Inputs'!D33 | E57: ='Model Inputs'!E33 | F57: ='Model Inputs'!F33 | G57: ='Model Inputs'!G33 | H57: ='Model Inputs'!H33 | I57: ='Model Inputs'!I33 | J57: ='Model Inputs'!J33 | ... W57: ='Model Inputs'!W33 | X57: =SUM(D57:G57) | Y57: =SUM(H57:K57) | Z57: =SUM(L57:O57) | AA57: =SUM(P57:S57) | AB57: =SUM(T57:W57)
A58: Capital Lease Principal Payments | B58: Formula | C58: ='Model Inputs'!C46 | D58: ='Model Inputs'!D46 | E58: ='Model Inputs'!E46 | F58: ='Model Inputs'!F46 | G58: ='Model Inputs'!G46 | H58: ='Model Inputs'!H46 | I58: ='Model Inputs'!I46 | J58: ='Model Inputs'!J46 | ... W58: ='Model Inputs'!W46 | X58: =SUM(D58:G58) | Y58: =SUM(H58:K58) | Z58: =SUM(L58:O58) | AA58: =SUM(P58:S58) | AB58: =SUM(T58:W58)
A59: Financing Cash Flow | B59: Formula | C59: =0 | D59: =D54-D55+D56-D57-D58 | E59: =E54-E55+E56-E57-E58 | F59: =F54-F55+F56-F57-F58 | G59: =G54-G55+G56-G57-G58 | H59: =H54-H55+H56-H57-H58 | I59: =I54-I55+I56-I57-I58 | J59: =J54-J55+J56-J57-J58 | K59: =K54-K55+K56-K57-K58 | ... W59: =W54-W55+W56-W57-W58 | X59: =SUM(D59:G59) | Y59: =SUM(H59:K59) | Z59: =SUM(L59:O59) | AA59: =SUM(P59:S59) | AB59: =SUM(T59:W59)
A60: Net Cash Flow | B60: Formula | C60: =0 | D60: =D51+D53+D59 | E60: =E51+E53+E59 | F60: =F51+F53+F59 | G60: =G51+G53+G59 | H60: =H51+H53+H59 | I60: =I51+I53+I59 | J60: =J51+J53+J59 | K60: =K51+K53+K59 | ... W60: =W51+W53+W59 | X60: =SUM(D60:G60) | Y60: =SUM(H60:K60) | Z60: =SUM(L60:O60) | AA60: =SUM(P60:S60) | AB60: =SUM(T60:W60)
A61: Ending Cash | B61: Formula | C61: =C46+C60 | D61: =D46+D60 | E61: =E46+E60 | F61: =F46+F60 | G61: =G46+G60 | H61: =H46+H60 | I61: =I46+I60 | J61: =J46+J60 | ... W61: =W46+W60 | X61: =SUM(D61:G61) | Y61: =SUM(H61:K61) | Z61: =SUM(L61:O61) | AA61: =SUM(P61:S61) | AB61: =SUM(T61:W61)

Sheet Audit Source
A1: Audit Source
A2: Persisted system outputs used only for checks and audit tie-outs.
C4: Stub | D4: Q1 | E4: Q2 | F4: Q3 | G4: Q4 | H4: Q5 | I4: Q6 | J4: Q7 | K4: Q8 | L4: Q9 | M4: Q10 | N4: Q11 | O4: Q12 | P4: Q13 | Q4: Q14 | R4: Q15 | S4: Q16 | T4: Q17 | U4: Q18 | V4: Q19 | W4: Q20 | X4: Y1 | Y4: Y2 | Z4: Y3 | AA4: Y4 | AB4: Y5
C5: 46162 | D5: 46295 | E5: 46387 | F5: 46477 | G5: 46568 | H5: 46660 | I5: 46752 | J5: 46843 | K5: 46934 | L5: 47026 | M5: 47118 | N5: 47208 | O5: 47299 | P5: 47391 | Q5: 47483 | R5: 47573 | S5: 47664 | T5: 47756 | U5: 47848 | V5: 47938 | W5: 48029 | X5: Annual | Y5: Annual | Z5: Annual | AA5: Annual | AB5: Annual
A6: Income Statement
A7: Revenue | B7: Persisted FINMO | C7: 766187.5 | D7: 1025000 | E7: 1031610 | F7: 1038240 | G7: 1044890 | H7: 1051560 | I7: 1058250 | J7: 1064960 | K7: 1071690 | L7: 1078440 | M7: 1085210 | N7: 1092000 | O7: 1096666.7 | P7: 1101333.3 | Q7: 1106000 | R7: 1110666.7 | S7: 1115333.3 | T7: 1120000 | U7: 1124666.7 | V7: 1129333.3 | W7: 1134000
A8: Cost of Goods Sold | B8: Persisted FINMO | C8: 260503.75 | D8: 471500 | E8: 470414.16 | F8: 469284.48 | G8: 468110.72 | H8: 466892.64 | I8: 465630 | J8: 464322.56 | K8: 462970.08 | L8: 461572.32 | M8: 460129.04 | N8: 458640 | O8: 458162.96 | P8: 457665.19 | Q8: 457146.67 | R8: 456607.41 | S8: 456047.41 | T8: 455466.67 | U8: 454865.18 | V8: 454242.96 | W8: 453600
A9: Gross Profit | B9: Persisted FINMO | C9: 505683.75 | D9: 553500 | E9: 561195.84 | F9: 568955.52 | G9: 576779.28 | H9: 584667.36 | I9: 592620 | J9: 600637.44 | K9: 608719.92 | L9: 616867.68 | M9: 625080.96 | N9: 633360 | O9: 638503.7 | P9: 643668.15 | Q9: 648853.33 | R9: 654059.26 | S9: 659285.93 | T9: 664533.33 | U9: 669801.48 | V9: 675090.37 | W9: 680400
A10: Marketing | B10: Persisted FINMO | C10: 55165.5 | D10: 215250 | E10: 205290.39 | F10: 195189.12 | G10: 184945.53 | H10: 174558.96 | I10: 164028.75 | J10: 153354.24 | K10: 142534.77 | L10: 131569.68 | M10: 120458.31 | N10: 109200 | O10: 107229.63 | P10: 105238.52 | Q10: 103226.67 | R10: 101194.07 | S10: 99140.741 | T10: 97066.667 | U10: 94971.852 | V10: 92856.296 | W10: 90720
A11: Research & Development | B11: Persisted FINMO | C11: 0 | D11: 0 | E11: 0 | F11: 0 | G11: 0 | H11: 0 | I11: 0 | J11: 0 | K11: 0 | L11: 0 | M11: 0 | N11: 0 | O11: 0 | P11: 0 | Q11: 0 | R11: 0 | S11: 0 | T11: 0 | U11: 0 | V11: 0 | W11: 0
A12: Lease/Rent | B12: Persisted FINMO | C12: 72000 | D12: 54000 | E12: 54000 | F12: 54000 | G12: 54000 | H12: 54000 | I12: 54000 | J12: 54000 | K12: 54000 | L12: 54000 | M12: 54000 | N12: 54000 | O12: 54000 | P12: 54000 | Q12: 54000 | R12: 54000 | S12: 54000 | T12: 54000 | U12: 54000 | V12: 54000 | W12: 54000
A13: Payroll | B13: Persisted FINMO | C13: 212500 | D13: 154401 | E13: 154401 | F13: 154401 | G13: 154401 | H13: 159032 | I13: 159032 | J13: 159032 | K13: 159032 | L13: 163802 | M13: 163802 | N13: 163802 | O13: 163802 | P13: 168718 | Q13: 168718 | R13: 168718 | S13: 168718 | T13: 173780 | U13: 173780 | V13: 173780 | W13: 173780
A14: General & Administrative | B14: Persisted FINMO | C14: 3884.5706 | D14: 215250 | E14: 210448.44 | F14: 205571.52 | G14: 200618.88 | H14: 195590.16 | I14: 190485 | J14: 185303.04 | K14: 180043.92 | L14: 174707.28 | M14: 169292.76 | N14: 163800 | O14: 160844.44 | P14: 157857.78 | Q14: 154840 | R14: 151791.11 | S14: 148711.11 | T14: 145600 | U14: 142457.78 | V14: 139284.44 | W14: 136080
A15: EBITDA | B15: Persisted FINMO | C15: 162133.68 | D15: -85401 | E15: -62943.99 | F15: -40206.12 | G15: -17186.13 | H15: 1486.24 | I15: 25074.25 | J15: 48948.16 | K15: 73109.23 | L15: 92788.72 | M15: 117527.89 | N15: 142558 | O15: 152627.63 | P15: 157853.85 | Q15: 168068.67 | R15: 178356.07 | S15: 188716.07 | T15: 194086.67 | U15: 204591.85 | V15: 215169.63 | W15: 225820
A16: Interest | B16: Persisted FINMO | C16: 8000.1 | D16: 11394.844 | E16: 10469.844 | F16: 9544.8438 | G16: 8619.8438 | H16: 8064.8438 | I16: 7544.5312 | J16: 7024.2188 | K16: 6503.9062 | L16: 5983.5938 | M16: 5463.2812 | N16: 4770.9187 | O16: 3602.9328 | P16: 2111.7981 | Q16: 678.22156 | R16: 0 | S16: 0 | T16: 0 | U16: 0 | V16: 0 | W16: 0
A17: Depreciation | B17: Persisted FINMO | C17: 0 | D17: 3120 | E17: 3541.9596 | F17: 3967.8569 | G17: 4396.0572 | H17: 4826.1242 | I17: 5257.6197 | J17: 5692.5901 | K17: 6129.3763 | L17: 6567.5483 | M17: 7007.9316 | N17: 7450.1005 | O17: 7892.3577 | P17: 8336.8033 | Q17: 8783.0045 | R17: 9229.2449 | S17: 9676.3562 | T17: 10125.169 | U17: 10573.943 | V17: 11022.215 | W17: 11472.087
A18: Taxes | B18: Persisted FINMO | C18: 41527.44 | D18: 0 | E18: 0 | F18: 0 | G18: 0 | H18: 0 | I18: 3306.4103 | J18: 9761.6318 | K18: 16293.732 | L18: 21618.009 | M18: 28304.895 | N18: 35116.041 | O18: 38024.581 | P18: 39714.66 | Q18: 42732.81 | R18: 45566.996 | S18: 48237.776 | T18: 49563.826 | U18: 52273.275 | V18: 55002.417 | W18: 57750.686
A19: Net Income | B19: Persisted FINMO | C19: 112606.14 | D19: -99915.844 | E19: -76955.793 | F19: -53718.821 | G19: -30202.031 | H19: -11404.728 | I19: 8965.6887 | J19: 26469.719 | K19: 44182.215 | L19: 58619.568 | M19: 76751.782 | N19: 95220.94 | O19: 103107.76 | P19: 107690.59 | Q19: 115874.63 | R19: 123559.83 | S19: 130801.94 | T19: 134397.67 | U19: 141744.63 | V19: 149145 | W19: 156597.23
A22: Balance Sheet
A23: Cash | B23: Persisted FINMO | C23: 180000 | D23: 555201.47 | E23: 547276.34 | F23: 539222.73 | G23: 531037.89 | H23: 525037.86 | I23: 516587.98 | J23: 510537.46 | K23: 523504.4 | L23: 553972.29 | M23: 600249.75 | N23: 632961.7 | O23: 629360.32 | P23: 628986.19 | Q23: 625287.77 | R23: 621539.75 | S23: 617743.9 | T23: 617276.3 | U23: 613384.07 | V23: 609441.95 | W23: 605454.35
A24: Accounts Receivable | B24: Persisted FINMO | C24: 35000 | D24: 167119.57 | E24: 168197.28 | F24: 173040 | G24: 172234.62 | H24: 171450 | I24: 172540.76 | J24: 175542.86 | K24: 176652.2 | L24: 175832.61 | M24: 176936.41 | N24: 182000 | O24: 180769.23 | P24: 179565.22 | Q24: 180326.09 | R24: 185111.11 | S24: 183846.15 | T24: 182608.7 | U24: 183369.57 | V24: 188222.22 | W24: 186923.08
A25: Inventory | B25: Persisted FINMO | C25: 85000 | D25: 102500 | E25: 102263.95 | F25: 104285.44 | G25: 102881.48 | H25: 101498.4 | I25: 101223.91 | J25: 102048.91 | K25: 101751.67 | L25: 100341.81 | M25: 100028.05 | N25: 101920 | O25: 100695.16 | P25: 99492.432 | Q25: 99379.71 | R25: 101468.31 | S25: 100230.2 | T25: 99014.493 | U25: 98883.736 | V25: 100942.88 | W25: 99692.308
A26: Current Assets | B26: Persisted FINMO | C26: 300000 | D26: 824821.04 | E26: 817737.57 | F26: 816548.17 | G26: 806153.99 | H26: 797986.26 | I26: 790352.66 | J26: 788129.23 | K26: 801908.26 | L26: 830146.7 | M26: 877214.21 | N26: 916881.7 | O26: 910824.71 | P26: 908043.84 | Q26: 904993.57 | R26: 908119.17 | S26: 901820.25 | T26: 898899.49 | U26: 895637.37 | V26: 898607.06 | W26: 892069.74
A27: PPE | B27: Persisted FINMO | C27: 1200000 | D27: 1207976.4 | E27: 1215586.7 | F27: 1222824.3 | G27: 1229684.3 | H27: 1236162.3 | I27: 1242254.1 | J27: 1247953.5 | K27: 1253256.1 | L27: 1258157.6 | M27: 1262653 | N27: 1266737.7 | O27: 1270408.7 | P27: 1273660.9 | Q27: 1276489.7 | R27: 1278892.1 | S27: 1280864.1 | T27: 1282401.2 | U27: 1283500.2 | V27: 1284158.6 | W27: 1284371.8
A28: Accumulated Depreciation | B28: Persisted FINMO | C28: 0 | D28: -420 | E28: -1261.9596 | F28: -2529.8164 | G28: -4225.8737 | H28: -6351.9978 | I28: -8909.6176 | J28: -11902.208 | K28: -15331.584 | L28: -19199.132 | M28: -23507.064 | N28: -28257.164 | O28: -33449.522 | P28: -39086.325 | Q28: -45169.33 | R28: -51698.575 | S28: -58674.931 | T28: -66100.1 | U28: -73974.043 | V28: -82296.259 | W28: -91068.346
A29: Total Assets | B29: Persisted FINMO | C29: 1554000 | D29: 2084097.4 | E29: 2081924.2 | F29: 2085272.4 | G29: 2079038.3 | H29: 2074648.5 | I29: 2070406.7 | J29: 2071182.8 | K29: 2087564.4 | L29: 2118004.3 | M29: 2166867.2 | N29: 2207919.4 | O29: 2202833.4 | P29: 2200604.8 | Q29: 2197683.3 | R29: 2200511.2 | S29: 2193484.4 | T29: 2189400.6 | U29: 2184537.5 | V29: 2185465.7 | W29: 2176441.5
A30: Accounts Payable | B30: Persisted FINMO | C30: 70000 | D30: 208337.28 | E30: 203523.86 | F30: 203053.88 | G30: 195812.77 | H30: 190167.76 | I30: 185069.27 | J30: 181875.59 | K30: 176574.95 | L30: 170895.31 | M30: 165506.44 | N30: 163600.67 | O30: 160178.93 | P30: 158417.71 | Q30: 156777.61 | R30: 158567.73 | S30: 155132.92 | T30: 153406.52 | U30: 151698.79 | V30: 153306.91 | W30: 149861.54
A31: Prepaid Expenses (% of Revenue) | B31: Persisted FINMO | C31: 0 | D31: 0 | E31: 0 | F31: 0 | G31: 0 | H31: 0 | I31: 0 | J31: 0 | K31: 0 | L31: 0 | M31: 0 | N31: 0 | O31: 0 | P31: 0 | Q31: 0 | R31: 0 | S31: 0 | T31: 0 | U31: 0 | V31: 0 | W31: 0
A32: Short Term Debt | B32: Persisted FINMO | C32: 0 | D32: 90000 | E32: 90000 | F32: 90000 | G32: 90000 | H32: 90000 | I32: 90000 | J32: 104880 | K32: 146015 | L32: 188843 | M32: 225000 | N32: 187620 | O32: 123985 | P32: 58657 | Q32: 0 | R32: 0 | S32: 0 | T32: 0 | U32: 0 | V32: 0 | W32: 0
A33: Deferred Revenue (% of Revenue) | B33: Persisted FINMO | C33: 0 | D33: 0 | E33: 0 | F33: 0 | G33: 0 | H33: 0 | I33: 0 | J33: 0 | K33: 0 | L33: 0 | M33: 0 | N33: 0 | O33: 0 | P33: 0 | Q33: 0 | R33: 0 | S33: 0 | T33: 0 | U33: 0 | V33: 0 | W33: 0
A34: Current Liabilites | B34: Persisted FINMO | C34: 70000 | D34: 298337.28 | E34: 293523.86 | F34: 293053.88 | G34: 285812.77 | H34: 280167.76 | I34: 275069.27 | J34: 286755.59 | K34: 322589.95 | L34: 359738.31 | M34: 390506.44 | N34: 351220.67 | O34: 284163.93 | P34: 217074.71 | Q34: 156777.61 | R34: 158567.73 | S34: 155132.92 | T34: 153406.52 | U34: 151698.79 | V34: 153306.91 | W34: 149861.54
... A41: Total Liabilities & Equity | B41: Persisted FINMO | C41: 1554000 | D41: 2084097.4 | E41: 2081924.2 | F41: 2085272.4 | G41: 2079038.3 | H41: 2074648.5 | I41: 2070406.7 | J41: 2071182.8 | K41: 2087564.4 | L41: 2118004.3 | M41: 2166867.2 | N41: 2207919.4 | O41: 2202833.4 | P41: 2200604.8 | Q41: 2197683.3 | R41: 2200511.2 | S41: 2193484.4 | T41: 2189400.6 | U41: 2184537.5 | V41: 2185465.7 | W41: 2176441.5
A44: Cash Flow
A45: Beginning Cash | B45: Persisted FINMO | C45: 180000 | D45: 180000 | E45: 555201.47 | F45: 547276.34 | G45: 539222.73 | H45: 531037.89 | I45: 525037.86 | J45: 516587.98 | K45: 510537.46 | L45: 523504.4 | M45: 553972.29 | N45: 600249.75 | O45: 632961.7 | P45: 629360.32 | Q45: 628986.19 | R45: 625287.77 | S45: 621539.75 | T45: 617743.9 | U45: 617276.3 | V45: 613384.07 | W45: 609441.95
A46: Net Income | B46: Persisted FINMO | C46: 112606.14 | D46: -99915.844 | E46: -76955.793 | F46: -53718.821 | G46: -30202.031 | H46: -11404.728 | I46: 8965.6887 | J46: 26469.719 | K46: 44182.215 | L46: 58619.568 | M46: 76751.782 | N46: 95220.94 | O46: 103107.76 | P46: 107690.59 | Q46: 115874.63 | R46: 123559.83 | S46: 130801.94 | T46: 134397.67 | U46: 141744.63 | V46: 149145 | W46: 156597.23
A47: Depreciatoin | B47: Persisted FINMO | C47: 0 | D47: 3120 | E47: 3541.9596 | F47: 3967.8569 | G47: 4396.0572 | H47: 4826.1242 | I47: 5257.6197 | J47: 5692.5901 | K47: 6129.3763 | L47: 6567.5483 | M47: 7007.9316 | N47: 7450.1005 | O47: 7892.3577 | P47: 8336.8033 | Q47: 8783.0045 | R47: 9229.2449 | S47: 9676.3562 | T47: 10125.169 | U47: 10573.943 | V47: 11022.215 | W47: 11472.087
A48: Changes in Current Assets | B48: Persisted FINMO | C48: 0 | D48: -149619.57 | E48: -841.66522 | F48: -6864.2096 | G48: 2209.3477 | H48: 2167.6923 | I48: -816.27391 | J48: -3827.0975 | K48: -812.09231 | L48: 2229.4463 | M48: -790.04783 | N48: -6955.5348 | O48: 2455.6124 | P48: 2406.7384 | Q48: -648.14782 | R48: -6873.6269 | S48: 2503.0705 | T48: 2453.1648 | U48: -630.11239 | V48: -6911.8018 | W48: 2549.7182
A49: Changes in Current Liabilites | B49: Persisted FINMO | C49: 0 | D49: 138337.28 | E49: -4813.425 | F49: -469.97761 | G49: -7241.1075 | H49: -5645.016 | I49: -5098.4902 | J49: -3193.6795 | K49: -5300.6341 | L49: -5679.6397 | M49: -5388.8772 | N49: -1905.7692 | O49: -3421.7411 | P49: -1761.2202 | Q49: -1640.0967 | R49: 1790.1197 | S49: -3434.8102 | T49: -1726.3964 | U49: -1707.7296 | V49: 1608.1213 | W49: -3445.3751
A50: Operating Cash Flow | B50: Persisted FINMO | C50: 0 | D50: -108078.13 | E50: -79068.924 | F50: -57085.151 | G50: -30837.734 | H50: -10055.927 | I50: 8308.5443 | J50: 25141.532 | K50: 44198.865 | L50: 61736.923 | M50: 77580.788 | N50: 93809.736 | O50: 110033.99 | P50: 116672.91 | Q50: 122369.39 | R50: 127705.57 | S50: 139546.56 | T50: 145249.61 | U50: 149980.73 | V50: 154863.53 | W50: 167173.66
A51: Capital Expenditures | B51: Persisted FINMO | C51: 0 | D51: 8396.4 | E51: 8452.2109 | F51: 8505.4598 | G51: 8556.1013 | H51: 8604.101 | I51: 8649.4274 | J51: 8692.0518 | K51: 8731.931 | L51: 8769.0329 | M51: 8803.3286 | N51: 8834.7829 | O51: 8863.3634 | P51: 8889.0495 | Q51: 8911.8054 | R51: 8931.5985 | S51: 8948.4078 | T51: 8962.2063 | U51: 8972.9609 | V51: 8980.6507 | W51: 8985.2578
A52: Investing Cash Flow | B52: Persisted FINMO | C52: 0 | D52: -8396.4 | E52: -8452.2109 | F52: -8505.4598 | G52: -8556.1013 | H52: -8604.101 | I52: -8649.4274 | J52: -8692.0518 | K52: -8731.931 | L52: -8769.0329 | M52: -8803.3286 | N52: -8834.7829 | O52: -8863.3634 | P52: -8889.0495 | Q52: -8911.8054 | R52: -8931.5985 | S52: -8948.4078 | T52: -8962.2063 | U52: -8972.9609 | V52: -8980.6507 | W52: -8985.2578
A53: Debt Issuance (New Borrowing) | B53: Persisted FINMO | C53: 0 | D53: 0 | E53: 0 | F53: 0 | G53: 0 | H53: 0 | I53: 0 | J53: 0 | K53: 0 | L53: 0 | M53: 0 | N53: 0 | O53: 0 | P53: 0 | Q53: 0 | R53: 0 | S53: 0 | T53: 0 | U53: 0 | V53: 0 | W53: 0
A54: Debt Repayment | B54: Persisted FINMO | C54: 0 | D54: -22500 | E54: -22500 | F54: -22500 | G54: -22500 | H54: -22500 | I54: -22500 | J54: -22500 | K54: -22500 | L54: -22500 | M54: -22500 | N54: -37380 | O54: -63635 | P54: -65328 | Q54: -58657 | R54: 0 | S54: 0 | T54: 0 | U54: 0 | V54: 0 | W54: 0
A55: Equity | B55: Persisted FINMO | C55: 0 | D55: 531676 | E55: 119596 | F55: 97537 | G55: 55209 | H55: 35160 | I55: 14391 | J55: 0 | K55: 0 | L55: 0 | M55: 0 | N55: 0 | O55: 0 | P55: 0 | Q55: 0 | R55: 0 | S55: 0 | T55: 0 | U55: 0 | V55: 0 | W55: 0
A56: Distributions | B56: Persisted FINMO | C56: 0 | D56: 0 | E56: 0 | F56: 0 | G56: 0 | H56: 0 | I56: 0 | J56: 0 | K56: 0 | L56: 0 | M56: 0 | N56: 14883 | O56: 41137 | P56: 42830 | Q56: 58499 | R56: 122522 | S56: 134394 | T56: 136755 | U56: 144900 | V56: 149825 | W56: 162176
... A59: Ending Cash | B59: Persisted FINMO | C59: 180000 | D59: 555201.47 | E59: 547276.34 | F59: 539222.73 | G59: 531037.89 | H59: 525037.86 | I59: 516587.98 | J59: 510537.46 | K59: 523504.4 | L59: 553972.29 | M59: 600249.75 | N59: 632961.7 | O59: 629360.32 | P59: 628986.19 | Q59: 625287.77 | R59: 621539.75 | S59: 617743.9 | T59: 617276.3 | U59: 613384.07 | V59: 609441.95 | W59: 605454.35

Sheet Checks
A1: Checks
A2: Model Status | B2: =IF(COUNTIF(I7:I172,"FAIL")=0,"OK","FAIL")
A3: Rule | B3: Only real formula/coherence failures return FAIL. Baseline scenario changes show CHANGED.
A5: Category | B5: Line Item | C5: Sheet | D5: Range / Cell | E5: Actual | F5: Expected | G5: Difference | H5: Tolerance | I5: Status | J5: Notes
A6: Model Coherence Checks
A7: Statement Coherence | B7: Balance Sheet balances Q1 | C7: Cross-sheet | D7: 'FINMO'!D31 | E7: ='FINMO'!D31 | F7: ='FINMO'!D43 | G7: =E7-F7 | H7: 1 | I7: =IF(ABS(G7)<=H7,"OK","FAIL") | J7: Total assets must equal total liabilities and equity.
A8: Statement Coherence | B8: Cash Flow ties to Balance Sheet Q1 | C8: Cross-sheet | D8: 'FINMO'!D61 | E8: ='FINMO'!D61 | F8: ='FINMO'!D23 | G8: =E8-F8 | H8: 1 | I8: =IF(ABS(G8)<=H8,"OK","FAIL") | J8: Ending cash must tie to balance-sheet cash.
A9: Statement Coherence | B9: Balance Sheet balances Q20 | C9: Cross-sheet | D9: 'FINMO'!W31 | E9: ='FINMO'!W31 | F9: ='FINMO'!W43 | G9: =E9-F9 | H9: 1 | I9: =IF(ABS(G9)<=H9,"OK","FAIL") | J9: Total assets must equal total liabilities and equity.
A10: Statement Coherence | B10: Cash Flow ties to Balance Sheet Q20 | C10: Cross-sheet | D10: 'FINMO'!W61 | E10: ='FINMO'!W61 | F10: ='FINMO'!W23 | G10: =E10-F10 | H10: 1 | I10: =IF(ABS(G10)<=H10,"OK","FAIL") | J10: Ending cash must tie to balance-sheet cash.
A11: Schedule Bridge | B11: Revenue Drivers total feeds Model Inputs Revenue | C11: Cross-sheet | D11: 'Revenue Drivers'!C14:W14 | E11: =SUMPRODUCT(ABS('Revenue Drivers'!C14:W14-'Model Inputs'!C11:W11)) | F11: 0 | G11: =E11-F11 | H11: 1 | I11: =IF(ABS(G11)<=H11,"OK","FAIL") | J11: Changing Revenue Drivers should update Model Inputs and FINMO without creating a model failure.
A12: Schedule Bridge | B12: Payroll Schedule total feeds Model Inputs Payroll | C12: Cross-sheet | D12: 'Payroll Schedule'!D17:W17 | E12: =SUMPRODUCT(ABS('Payroll Schedule'!D17:W17-'Model Inputs'!D16:W16)) | F12: 0 | G12: =E12-F12 | H12: 1 | I12: =IF(ABS(G12)<=H12,"OK","FAIL") | J12: Changing payroll detail should update payroll summary, Model Inputs, and FINMO payroll.
A13: Schedule Bridge | B13: Debt repayment feeds Model Inputs | C13: Cross-sheet | D13: 'Debt Schedule'!C10:W10 | E13: =SUMPRODUCT(ABS('Debt Schedule'!C10:W10-'Model Inputs'!C43:W43)) | F13: 0 | G13: =E13-F13 | H13: 1 | I13: =IF(ABS(G13)<=H13,"OK","FAIL") | J13: Debt repayment must flow through the model from actual mechanically capped repayment.
A14: Schedule Bridge | B14: Capital lease additions feed CapEx schedule | C14: Cross-sheet | D14: 'Debt Schedule'!C21:W21 | E14: =SUMPRODUCT(ABS('Debt Schedule'!C21:W21-'CapEx Depreciation'!C9:W9)) | F14: 0 | G14: =E14-F14 | H14: 1 | I14: =IF(ABS(G14)<=H14,"OK","FAIL") | J14: Lease additions must affect PPE/depreciation through the CapEx schedule.
A15: Schedule Bridge | B15: Lease/rent feeds Model Inputs | C15: Cross-sheet | D15: 'Cash Equity Schedule'!C12:W12 | E15: =SUMPRODUCT(ABS('Cash Equity Schedule'!C12:W12-'Model Inputs'!C15:W15)) | F15: 0 | G15: =E15-F15 | H15: 1 | I15: =IF(ABS(G15)<=H15,"OK","FAIL") | J15: Operating lease/rent must flow through Model Inputs into FINMO.
A16: Schedule Coherence | B16: Payroll summary totals equal payroll detail by quarter | C16: Payroll Schedule | D16: A27:N86 | E16: =SUM(ABS('Payroll Schedule'!C15-SUMIFS('Payroll Schedule'!$G$27:$G$86,'Payroll Schedule'!$A$27:$A$86,0)),ABS('Payroll Schedule'!C16-SUMIFS('Payroll Schedule'!$H$27:$H$86,'Payroll Schedule'!$A$27:$A$86,0)),ABS('Payroll Schedule'!C17-SUMIFS('Payroll Schedule'!$M$27:$M$86,'Payroll Schedule'!$A$27:$A$86,0)),ABS('Payroll Schedule'!D15-SUMIFS('Payroll Schedule'!$G$27:$G$86,'Payroll Schedule'!$A$27:$A$86,1)),ABS('Payroll Schedule'!D16-SUMIFS('Payroll Schedule'!$H$27:$H$86,'Payroll Schedule'!$A$27:$A$86,1)),ABS('Payroll Schedule'!D17-SUMIFS('Payroll Schedule'!$M$27:$M$86,'Payroll Schedule'!$A$27:$A$86,1)),ABS('Payroll Schedule'!E15-SUMIFS('Payroll Schedule'!$G$27:$G$86,'Payroll Schedule'!$A$27:$A$86,2)),ABS('Payroll Schedule'!E16-SUMIFS('Payroll Schedule'!$H$27:$H$86,'Payroll Schedule'!$A$27:$A$86,2)),ABS('Payroll Schedule'!E17-SUMIFS('Payroll Schedule'!$M$27:$M$86,'Payroll Schedule'!$A$27:$A$86,2)),ABS('Payroll Schedule'!F15-SUMIFS('Payroll Schedule'!$G$27:$G$86,'Payroll Schedule'!$A$27:$A$86,3)),ABS('Payroll Schedule'!F16-SUMIFS('Payroll Schedule'!$H$27:$H$86,'Payroll Schedule'!$A$27:$A$86,3)),ABS('Payroll Schedule'!F17-SUMIFS('Payroll Schedule'!$M$27:$M$86,'Payroll Schedule'!$A$27:$A$86,3)),ABS('Payroll Schedule'!G15-SUMIFS('Payroll Schedule'!$G$27:$G$86,'Payroll Schedule'!$A$27:$A$86,4)),ABS('Payroll Schedule'!G16-SUMIFS('Payroll Schedule'!$H$27:$H$86,'Payroll Schedule'!$A$27:$A$86,4)),ABS('Payroll Schedule'!G17-SUMIFS('Payroll Schedule'!$M$27:$M$86,'Payroll Schedule'!$A$27:$A$86,4)),ABS('Payroll Schedule'!H15-SUMIFS('Payroll Schedule'!$G$27:$G$86,'Payroll Schedule'!$A$27:$A$86,5)),ABS('Payroll Schedule'!H16-SUMIFS('Payroll Schedule'!$H$27:$H$86,'Payroll Schedule'!$A$27:$A$86,5)),ABS('Payroll Schedule'!H17-SUMIFS('Payroll Schedule'!$M$27:$M$86,'Payroll Schedule'!$A$27:$A$86,5)),ABS('Payroll Schedule'!I15-SUMIFS('Payroll Schedule'!$G$27:$G$86,'Payroll Schedule'!$A$27:$A$86,6)),ABS('Payroll Schedule'!I16-SUMIFS('Payroll Schedule'!$H$27:$H$86,'Payroll Schedule'!$A$27:$A$86,6)),ABS('Payroll Schedule'!I17-SUMIFS('Payroll Schedule'!$M$27:$M$86,'Payroll Schedule'!$A$27:$A$86,6)),ABS('Payroll Schedule'!J15-SUMIFS('Payroll Schedule'!$G$27:$G$86,'Payroll Schedule'!$A$27:$A$86,7)),ABS('Payroll Schedule'!J16-SUMIFS('Payroll Schedule'!$H$27:$H$86,'Payroll Schedule'!$A$27:$A$86,7)),ABS('Payroll Schedule'!J17-SUMIFS('Payroll Schedule'!$M$27:$M$86,'Payroll Schedule'!$A$27:$A$86,7)),ABS('Payroll Schedule'!K15-SUMIFS('Payroll Schedule'!$G$27:$G$86,'Payroll Schedule'!$A$27:$A$86,8)),ABS('Payroll Schedule'!K16-SUMIFS('Payroll Schedule'!$H$27:$H$86,'Payroll Schedule'!$A$27:$A$86,8)),ABS('Payroll Schedule'!K17-SUMIFS('Payroll Schedule'!$M$27:$M$86,'Payroll Schedule'!$A$27:$A$86,8)),ABS('Payroll Schedule'!L15-SUMIFS('Payroll Schedule'!$G$27:$G$86,'Payroll Schedule'!$A$27:$A$86,9)),ABS('Payroll Schedule'!L16-SUMIFS('Payroll Schedule'!$H$27:$H$86,'Payroll Schedule'!$A$27:$A$86,9)),ABS('Payroll Schedule'!L17-SUMIFS('Payroll Schedule'!$M$27:$M$86,'Payroll Schedule'!$A$27:$A$86,9)),ABS('Payroll Schedule'!M15-SUMIFS('Payroll Schedule'!$G$27:$G$86,'Payroll Schedule'!$A$27:$A$86,10)),ABS('Payroll Schedule'!M16-SUMIFS('Payroll Schedule'!$H$27:$H$86,'Payroll Schedule'!$A$27:$A$86,10)),ABS('Payroll Schedule'!M17-SUMIFS('Payroll Schedule'!$M$27:$M$86,'Payroll Schedule'!$A$27:$A$86,10)),ABS('Payroll Schedule'!N15-SUMIFS('Payroll Schedule'!$G$27:$G$86,'Payroll Schedule'!$A$27:$A$86,11)),ABS('Payroll Schedule'!N16-SUMIFS('Payroll Schedule'!$H$27:$H$86,'Payroll Schedule'!$A$27:$A$86,11)),ABS('Payroll Schedule'!N17-SUMIFS('Payroll Schedule'!$M$27:$M$86,'Payroll Schedule'!$A$27:$A$86,11)),ABS('Payroll Schedule'!O15-SUMIFS('Payroll Schedule'!$G$27:$G$86,'Payroll Schedule'!$A$27:$A$86,12)),ABS('Payroll Schedule'!O16-SUMIFS('Payroll Schedule'!$H$27:$H$86,'Payroll Schedule'!$A$27:$A$86,12)),ABS('Payroll Schedule'!O17-SUMIFS('Payroll Schedule'!$M$27:$M$86,'Payroll Schedule'!$A$27:$A$86,12)),ABS('Payroll Schedule'!P15-SUMIFS('Payroll Schedule'!$G$27:$G$86,'Payroll Schedule'!$A$27:$A$86,13)),ABS('Payroll Schedule'!P16-SUMIFS('Payroll Schedule'!$H$27:$H$86,'Payroll Schedule'!$A$27:$A$86,13)),ABS('Payroll Schedule'!P17-SUMIFS('Payroll Schedule'!$M$27:$M$86,'Payroll Schedule'!$A$27:$A$86,13)),ABS('Payroll Schedule'!Q15-SUMIFS('Payroll Schedule'!$G$27:$G$86,'Payroll Schedule'!$A$27:$A$86,14)),ABS('Payroll Schedule'!Q16-SUMIFS('Payroll Schedule'!$H$27:$H$86,'Payroll Schedule'!$A$27:$A$86,14)),ABS('Payroll Schedule'!Q17-SUMIFS('Payroll Schedule'!$M$27:$M$86,'Payroll Schedule'!$A$27:$A$86,14)),ABS('Payroll Schedule'!R15-SUMIFS('Payroll Schedule'!$G$27:$G$86,'Payroll Schedule'!$A$27:$A$86,15)),ABS('Payroll Schedule'!R16-SUMIFS('Payroll Schedule'!$H$27:$H$86,'Payroll Schedule'!$A$27:$A$86,15)),ABS('Payroll Schedule'!R17-SUMIFS('Payroll Schedule'!$M$27:$M$86,'Payroll Schedule'!$A$27:$A$86,15)),ABS('Payroll Schedule'!S15-SUMIFS('Payroll Schedule'!$G$27:$G$86,'Payroll Schedule'!$A$27:$A$86,16)),ABS('Payroll Schedule'!S16-SUMIFS('Payroll Schedule'!$H$27:$H$86,'Payroll Schedule'!$A$27:$A$86,16)),ABS('Payroll Schedule'!S17-SUMIFS('Payroll Schedule'!$M$27:$M$86,'Payroll Schedule'!$A$27:$A$86,16)),ABS('Payroll Schedule'!T15-SUMIFS('Payroll Schedule'!$G$27:$G$86,'Payroll Schedule'!$A$27:$A$86,17)),ABS('Payroll Schedule'!T16-SUMIFS('Payroll Schedule'!$H$27:$H$86,'Payroll Schedule'!$A$27:$A$86,17)),ABS('Payroll Schedule'!T17-SUMIFS('Payroll Schedule'!$M$27:$M$86,'Payroll Schedule'!$A$27:$A$86,17)),ABS('Payroll Schedule'!U15-SUMIFS('Payroll Schedule'!$G$27:$G$86,'Payroll Schedule'!$A$27:$A$86,18)),ABS('Payroll Schedule'!U16-SUMIFS('Payroll Schedule'!$H$27:$H$86,'Payroll Schedule'!$A$27:$A$86,18)),ABS('Payroll Schedule'!U17-SUMIFS('Payroll Schedule'!$M$27:$M$86,'Payroll Schedule'!$A$27:$A$86,18)),ABS('Payroll Schedule'!V15-SUMIFS('Payroll Schedule'!$G$27:$G$86,'Payroll Schedule'!$A$27:$A$86,19)),ABS('Payroll Schedule'!V16-SUMIFS('Payroll Schedule'!$H$27:$H$86,'Payroll Schedule'!$A$27:$A$86,19)),ABS('Payroll Schedule'!V17-SUMIFS('Payroll Schedule'!$M$27:$M$86,'Payroll Schedule'!$A$27:$A$86,19)),ABS('Payroll Schedule'!W15-SUMIFS('Payroll Schedule'!$G$27:$G$86,'Payroll Schedule'!$A$27:$A$86,20)),ABS('Payroll Schedule'!W16-SUMIFS('Payroll Schedule'!$H$27:$H$86,'Payroll Schedule'!$A$27:$A$86,20)),ABS('Payroll Schedule'!W17-SUMIFS('Payroll Schedule'!$M$27:$M$86,'Payroll Schedule'!$A$27:$A$86,20))) | F16: 0 | G16: =E16-F16 | H16: 1 | I16: =IF(ABS(G16)<=H16,"OK","FAIL") | J16: If this fails, payroll summary is no longer tied to detail FTE/payroll rows.
A17: Schedule Coherence | B17: Payroll productivity metrics | C17: Payroll Schedule | D17: A16:W22 | E17: =SUM(ABS('Payroll Schedule'!C20-IFERROR('Payroll Schedule'!C18/'Payroll Schedule'!C16,0)),ABS('Payroll Schedule'!C21-IFERROR('Payroll Schedule'!C19/'Payroll Schedule'!C16,0)),ABS('Payroll Schedule'!C22-IFERROR('Payroll Schedule'!C17/'Payroll Schedule'!C18,0)),ABS('Payroll Schedule'!D20-IFERROR('Payroll Schedule'!D18/'Payroll Schedule'!D16,0)),ABS('Payroll Schedule'!D21-IFERROR('Payroll Schedule'!D19/'Payroll Schedule'!D16,0)),ABS('Payroll Schedule'!D22-IFERROR('Payroll Schedule'!D17/'Payroll Schedule'!D18,0)),ABS('Payroll Schedule'!E20-IFERROR('Payroll Schedule'!E18/'Payroll Schedule'!E16,0)),ABS('Payroll Schedule'!E21-IFERROR('Payroll Schedule'!E19/'Payroll Schedule'!E16,0)),ABS('Payroll Schedule'!E22-IFERROR('Payroll Schedule'!E17/'Payroll Schedule'!E18,0)),ABS('Payroll Schedule'!F20-IFERROR('Payroll Schedule'!F18/'Payroll Schedule'!F16,0)),ABS('Payroll Schedule'!F21-IFERROR('Payroll Schedule'!F19/'Payroll Schedule'!F16,0)),ABS('Payroll Schedule'!F22-IFERROR('Payroll Schedule'!F17/'Payroll Schedule'!F18,0)),ABS('Payroll Schedule'!G20-IFERROR('Payroll Schedule'!G18/'Payroll Schedule'!G16,0)),ABS('Payroll Schedule'!G21-IFERROR('Payroll Schedule'!G19/'Payroll Schedule'!G16,0)),ABS('Payroll Schedule'!G22-IFERROR('Payroll Schedule'!G17/'Payroll Schedule'!G18,0)),ABS('Payroll Schedule'!H20-IFERROR('Payroll Schedule'!H18/'Payroll Schedule'!H16,0)),ABS('Payroll Schedule'!H21-IFERROR('Payroll Schedule'!H19/'Payroll Schedule'!H16,0)),ABS('Payroll Schedule'!H22-IFERROR('Payroll Schedule'!H17/'Payroll Schedule'!H18,0)),ABS('Payroll Schedule'!I20-IFERROR('Payroll Schedule'!I18/'Payroll Schedule'!I16,0)),ABS('Payroll Schedule'!I21-IFERROR('Payroll Schedule'!I19/'Payroll Schedule'!I16,0)),ABS('Payroll Schedule'!I22-IFERROR('Payroll Schedule'!I17/'Payroll Schedule'!I18,0)),ABS('Payroll Schedule'!J20-IFERROR('Payroll Schedule'!J18/'Payroll Schedule'!J16,0)),ABS('Payroll Schedule'!J21-IFERROR('Payroll Schedule'!J19/'Payroll Schedule'!J16,0)),ABS('Payroll Schedule'!J22-IFERROR('Payroll Schedule'!J17/'Payroll Schedule'!J18,0)),ABS('Payroll Schedule'!K20-IFERROR('Payroll Schedule'!K18/'Payroll Schedule'!K16,0)),ABS('Payroll Schedule'!K21-IFERROR('Payroll Schedule'!K19/'Payroll Schedule'!K16,0)),ABS('Payroll Schedule'!K22-IFERROR('Payroll Schedule'!K17/'Payroll Schedule'!K18,0)),ABS('Payroll Schedule'!L20-IFERROR('Payroll Schedule'!L18/'Payroll Schedule'!L16,0)),ABS('Payroll Schedule'!L21-IFERROR('Payroll Schedule'!L19/'Payroll Schedule'!L16,0)),ABS('Payroll Schedule'!L22-IFERROR('Payroll Schedule'!L17/'Payroll Schedule'!L18,0)),ABS('Payroll Schedule'!M20-IFERROR('Payroll Schedule'!M18/'Payroll Schedule'!M16,0)),ABS('Payroll Schedule'!M21-IFERROR('Payroll Schedule'!M19/'Payroll Schedule'!M16,0)),ABS('Payroll Schedule'!M22-IFERROR('Payroll Schedule'!M17/'Payroll Schedule'!M18,0)),ABS('Payroll Schedule'!N20-IFERROR('Payroll Schedule'!N18/'Payroll Schedule'!N16,0)),ABS('Payroll Schedule'!N21-IFERROR('Payroll Schedule'!N19/'Payroll Schedule'!N16,0)),ABS('Payroll Schedule'!N22-IFERROR('Payroll Schedule'!N17/'Payroll Schedule'!N18,0)),ABS('Payroll Schedule'!O20-IFERROR('Payroll Schedule'!O18/'Payroll Schedule'!O16,0)),ABS('Payroll Schedule'!O21-IFERROR('Payroll Schedule'!O19/'Payroll Schedule'!O16,0)),ABS('Payroll Schedule'!O22-IFERROR('Payroll Schedule'!O17/'Payroll Schedule'!O18,0)),ABS('Payroll Schedule'!P20-IFERROR('Payroll Schedule'!P18/'Payroll Schedule'!P16,0)),ABS('Payroll Schedule'!P21-IFERROR('Payroll Schedule'!P19/'Payroll Schedule'!P16,0)),ABS('Payroll Schedule'!P22-IFERROR('Payroll Schedule'!P17/'Payroll Schedule'!P18,0)),ABS('Payroll Schedule'!Q20-IFERROR('Payroll Schedule'!Q18/'Payroll Schedule'!Q16,0)),ABS('Payroll Schedule'!Q21-IFERROR('Payroll Schedule'!Q19/'Payroll Schedule'!Q16,0)),ABS('Payroll Schedule'!Q22-IFERROR('Payroll Schedule'!Q17/'Payroll Schedule'!Q18,0)),ABS('Payroll Schedule'!R20-IFERROR('Payroll Schedule'!R18/'Payroll Schedule'!R16,0)),ABS('Payroll Schedule'!R21-IFERROR('Payroll Schedule'!R19/'Payroll Schedule'!R16,0)),ABS('Payroll Schedule'!R22-IFERROR('Payroll Schedule'!R17/'Payroll Schedule'!R18,0)),ABS('Payroll Schedule'!S20-IFERROR('Payroll Schedule'!S18/'Payroll Schedule'!S16,0)),ABS('Payroll Schedule'!S21-IFERROR('Payroll Schedule'!S19/'Payroll Schedule'!S16,0)),ABS('Payroll Schedule'!S22-IFERROR('Payroll Schedule'!S17/'Payroll Schedule'!S18,0)),ABS('Payroll Schedule'!T20-IFERROR('Payroll Schedule'!T18/'Payroll Schedule'!T16,0)),ABS('Payroll Schedule'!T21-IFERROR('Payroll Schedule'!T19/'Payroll Schedule'!T16,0)),ABS('Payroll Schedule'!T22-IFERROR('Payroll Schedule'!T17/'Payroll Schedule'!T18,0)),ABS('Payroll Schedule'!U20-IFERROR('Payroll Schedule'!U18/'Payroll Schedule'!U16,0)),ABS('Payroll Schedule'!U21-IFERROR('Payroll Schedule'!U19/'Payroll Schedule'!U16,0)),ABS('Payroll Schedule'!U22-IFERROR('Payroll Schedule'!U17/'Payroll Schedule'!U18,0)),ABS('Payroll Schedule'!V20-IFERROR('Payroll Schedule'!V18/'Payroll Schedule'!V16,0)),ABS('Payroll Schedule'!V21-IFERROR('Payroll Schedule'!V19/'Payroll Schedule'!V16,0)),ABS('Payroll Schedule'!V22-IFERROR('Payroll Schedule'!V17/'Payroll Schedule'!V18,0)),ABS('Payroll Schedule'!W20-IFERROR('Payroll Schedule'!W18/'Payroll Schedule'!W16,0)),ABS('Payroll Schedule'!W21-IFERROR('Payroll Schedule'!W19/'Payroll Schedule'!W16,0)),ABS('Payroll Schedule'!W22-IFERROR('Payroll Schedule'!W17/'Payroll Schedule'!W18,0))) | F17: 0 | G17: =E17-F17 | H17: 0.01 | I17: =IF(ABS(G17)<=H17,"OK","FAIL") | J17: Revenue per employee, units per employee, and payroll percent must stay tied to revenue/capacity and average FTE.
A18: Schedule Coherence | B18: Payroll detail FTE math | C18: Payroll Schedule | D18: E27:H86 | E18: =SUMPRODUCT(ABS('Payroll Schedule'!G27:G86-('Payroll Schedule'!E27:E86+'Payroll Schedule'!F27:F86)))+SUMPRODUCT(ABS('Payroll Schedule'!H27:H86-(('Payroll Schedule'!E27:E86+'Payroll Schedule'!G27:G86)/2))) | F18: 0 | G18: =E18-F18 | H18: 0.01 | I18: =IF(ABS(G18)<=H18,"OK","FAIL") | J18: Ending FTE must equal starting FTE plus hires; average FTE must be the average of starting and ending FTE.
A19: Schedule Coherence | B19: Payroll detail wage and tax math | C19: Payroll Schedule | D19: I27:M86 | E19: =SUMPRODUCT(ABS('Payroll Schedule'!K27:K86-('Payroll Schedule'!H27:H86*'Payroll Schedule'!I27:I86/4)))+SUMPRODUCT(ABS('Payroll Schedule'!L27:L86-('Payroll Schedule'!K27:K86*'Payroll Schedule'!J27:J86)))+SUMPRODUCT(ABS('Payroll Schedule'!M27:M86-('Payroll Schedule'!K27:K86+'Payroll Schedule'!L27:L86))) | F19: 0 | G19: =E19-F19 | H19: 1 | I19: =IF(ABS(G19)<=H19,"OK","FAIL") | J19: Payroll dollars must flow from average FTE, wage, benefits/taxes, and total payroll formulas.
A21: Line-Item Formula Logic Diagnostics
A22: Formula Logic | B22: Revenue calculation - lob_1_product_1 | C22: Revenue Drivers | D22: 'Revenue Drivers'!C11:W11 | E22: =SUMPRODUCT(ABS('Revenue Drivers'!C11:W11-('Revenue Drivers'!C8:W8*'Revenue Drivers'!C9:W9*'Revenue Drivers'!C10:W10))) | F22: 0 | G22: =E22-F22 | H22: 1 | I22: =IF(ABS(G22)<=H22,"OK","FAIL") | J22: Revenue rows must equal capacity x unit price x utilization.
A23: Formula Logic | B23: Revenue total equals all revenue products | C23: Revenue Drivers | D23: 'Revenue Drivers'!C14:W14 | E23: =SUMPRODUCT(ABS('Revenue Drivers'!C14:W14-('Revenue Drivers'!C11:W11))) | F23: 0 | G23: =E23-F23 | H23: 1 | I23: =IF(ABS(G23)<=H23,"OK","FAIL") | J23: Total revenue must stay tied to all revenue-product rows.
A24: Formula Logic | B24: Revenue total capacity equals all capacity products | C24: Revenue Drivers | D24: 'Revenue Drivers'!C13:W13 | E24: =SUMPRODUCT(ABS('Revenue Drivers'!C13:W13-('Revenue Drivers'!C8:W8))) | F24: 0 | G24: =E24-F24 | H24: 0.01 | I24: =IF(ABS(G24)<=H24,"OK","FAIL") | J24: Total capacity units must stay tied to all revenue-driver capacity rows.
A25: Formula Logic | B25: Debt opening balance continuity | C25: Debt Schedule | D25: 'Debt Schedule'!D7:W7 | E25: =SUMPRODUCT(ABS('Debt Schedule'!D7:W7-'Debt Schedule'!C11:V11)) | F25: 0 | G25: =E25-F25 | H25: 1 | I25: =IF(ABS(G25)<=H25,"OK","FAIL") | J25: Each quarter's opening debt must equal the prior quarter's closing debt.
A26: Formula Logic | B26: Actual debt repayment cap | C26: Debt Schedule | D26: 'Debt Schedule'!C10:W10 | E26: =SUMPRODUCT(--(('Debt Schedule'!C10:W10-'Debt Schedule'!C9:W9)>1))+SUMPRODUCT(--(('Debt Schedule'!C10:W10-('Debt Schedule'!C7:W7+'Debt Schedule'!C8:W8))>1)) | F26: 0 | G26: =E26-F26 | H26: 0 | I26: =IF(ABS(G26)<=H26,"OK","FAIL") | J26: Actual repayment must not exceed requested repayment or available debt balance.
A27: Formula Logic | B27: Closing debt formula | C27: Debt Schedule | D27: 'Debt Schedule'!C11:W11 | E27: =SUMPRODUCT(ABS('Debt Schedule'!C11:W11-('Debt Schedule'!C7:W7+'Debt Schedule'!C8:W8-'Debt Schedule'!C10:W10))) | F27: 0 | G27: =E27-F27 | H27: 1 | I27: =IF(ABS(G27)<=H27,"OK","FAIL") | J27: Closing debt must equal opening debt plus issuance less actual repayment, floored at zero.
A28: Formula Logic | B28: Interest expense formula | C28: Debt Schedule | D28: 'Debt Schedule'!C13:W13 | E28: =SUMPRODUCT(ABS('Debt Schedule'!C13:W13-((('Debt Schedule'!C7:W7+'Debt Schedule'!C11:W11)/2)*'Debt Schedule'!C12:W12))) | F28: 0 | G28: =E28-F28 | H28: 1 | I28: =IF(ABS(G28)<=H28,"OK","FAIL") | J28: Interest expense must equal average debt balance times interest rate.
A29: Formula Logic | B29: Debt service formula | C29: Debt Schedule | D29: 'Debt Schedule'!C14:W14 | E29: =SUMPRODUCT(ABS('Debt Schedule'!C14:W14-('Debt Schedule'!C13:W13+'Debt Schedule'!C10:W10))) | F29: 0 | G29: =E29-F29 | H29: 1 | I29: =IF(ABS(G29)<=H29,"OK","FAIL") | J29: Debt service must equal interest expense plus actual debt repayment.
A30: Formula Logic | B30: Lease opening balance continuity | C30: Debt Schedule | D30: 'Debt Schedule'!D18:W18 | E30: =SUMPRODUCT(ABS('Debt Schedule'!D18:W18-'Debt Schedule'!C23:V23)) | F30: 0 | G30: =E30-F30 | H30: 1 | I30: =IF(ABS(G30)<=H30,"OK","FAIL") | J30: Each quarter's opening lease balance must equal the prior quarter's closing lease balance.
A31: Formula Logic | B31: Lease principal repayment cap | C31: Debt Schedule | D31: 'Debt Schedule'!C20:W20 | E31: =SUMPRODUCT(--(('Debt Schedule'!C20:W20-'Debt Schedule'!C19:W19)>1))+SUMPRODUCT(--(('Debt Schedule'!C20:W20-('Debt Schedule'!C18:W18+'Debt Schedule'!C21:W21))>1)) | F31: 0 | G31: =E31-F31 | H31: 0 | I31: =IF(ABS(G31)<=H31,"OK","FAIL") | J31: Lease principal repayment must not exceed requested repayment or available lease balance.
A32: Formula Logic | B32: Lease closing balance formula | C32: Debt Schedule | D32: 'Debt Schedule'!C23:W23 | E32: =SUMPRODUCT(ABS('Debt Schedule'!C23:W23-('Debt Schedule'!C18:W18+'Debt Schedule'!C21:W21-'Debt Schedule'!C20:W20))) | F32: 0 | G32: =E32-F32 | H32: 1 | I32: =IF(ABS(G32)<=H32,"OK","FAIL") | J32: Lease closing balance must equal opening balance plus additions less principal repayment, floored at zero.
A33: Formula Logic | B33: PPE opening balance continuity | C33: CapEx Depreciation | D33: 'CapEx Depreciation'!D7:W7 | E33: =SUMPRODUCT(ABS('CapEx Depreciation'!D7:W7-'CapEx Depreciation'!C12:V12)) | F33: 0 | G33: =E33-F33 | H33: 1 | I33: =IF(ABS(G33)<=H33,"OK","FAIL") | J33: Each quarter's opening PPE must equal the prior quarter's closing PPE.
A34: Formula Logic | B34: Depreciation expense formula | C34: CapEx Depreciation | D34: 'CapEx Depreciation'!C11:W11 | E34: =SUMPRODUCT(ABS('CapEx Depreciation'!C11:W11-('CapEx Depreciation'!C7:W7*'CapEx Depreciation'!C10:W10))) | F34: 0 | G34: =E34-F34 | H34: 1 | I34: =IF(ABS(G34)<=H34,"OK","FAIL") | J34: Depreciation must equal opening PPE times rate, capped at opening PPE.
A35: Formula Logic | B35: Closing PPE formula | C35: CapEx Depreciation | D35: 'CapEx Depreciation'!C12:W12 | E35: =SUMPRODUCT(ABS('CapEx Depreciation'!C12:W12-('CapEx Depreciation'!C7:W7+'CapEx Depreciation'!C8:W8+'CapEx Depreciation'!C9:W9-'CapEx Depreciation'!C11:W11))) | F35: 0 | G35: =E35-F35 | H35: 1 | I35: =IF(ABS(G35)<=H35,"OK","FAIL") | J35: Closing PPE must include capex and lease additions and subtract depreciation.
A36: Formula Logic | B36: Accumulated depreciation continuity | C36: CapEx Depreciation | D36: 'CapEx Depreciation'!D13:W13 | E36: =SUMPRODUCT(ABS('CapEx Depreciation'!D13:W13-'CapEx Depreciation'!C14:V14)) | F36: 0 | G36: =E36-F36 | H36: 1 | I36: =IF(ABS(G36)<=H36,"OK","FAIL") | J36: Opening accumulated depreciation must equal the prior quarter's accumulated depreciation.
A37: Formula Logic | B37: Accumulated depreciation formula | C37: CapEx Depreciation | D37: 'CapEx Depreciation'!C14:W14 | E37: =SUMPRODUCT(ABS('CapEx Depreciation'!C14:W14-('CapEx Depreciation'!C13:W13-'CapEx Depreciation'!C11:W11))) | F37: 0 | G37: =E37-F37 | H37: 1 | I37: =IF(ABS(G37)<=H37,"OK","FAIL") | J37: Accumulated depreciation must roll forward by depreciation expense.
A39: Formula Manifest by Line Item
A40: Formula Manifest | B40: Revenue Drivers - Total Revenue | C40: Revenue Drivers | D40: 'Revenue Drivers'!C14:W14 | E40: =21 | F40: 21 | G40: =E40-F40 | H40: 0 | I40: =IF(G40=0,"OK","FAIL") | J40: This line is expected to be formula-driven across every period. Formula presence is verified at export; live edit integrity is covered by the logic and bridge checks above.
A41: Formula Manifest | B41: Revenue Drivers - Total Capacity Units | C41: Revenue Drivers | D41: 'Revenue Drivers'!C13:W13 | E41: =21 | F41: 21 | G41: =E41-F41 | H41: 0 | I41: =IF(G41=0,"OK","FAIL") | J41: This line is expected to be formula-driven across every period. Formula presence is verified at export; live edit integrity is covered by the logic and bridge checks above.
A42: Formula Manifest | B42: Revenue Drivers - Actual Revenue QoQ Growth | C42: Revenue Drivers | D42: 'Revenue Drivers'!C17:W17 | E42: =21 | F42: 21 | G42: =E42-F42 | H42: 0 | I42: =IF(G42=0,"OK","FAIL") | J42: This line is expected to be formula-driven across every period. Formula presence is verified at export; live edit integrity is covered by the logic and bridge checks above.
A43: Formula Manifest | B43: Payroll Schedule - Total Ending FTE | C43: Payroll Schedule | D43: 'Payroll Schedule'!C15:W15 | E43: =21 | F43: 21 | G43: =E43-F43 | H43: 0 | I43: =IF(G43=0,"OK","FAIL") | J43: This line is expected to be formula-driven across every period. Formula presence is verified at export; live edit integrity is covered by the logic and bridge checks above.
A44: Formula Manifest | B44: Payroll Schedule - Total Average FTE | C44: Payroll Schedule | D44: 'Payroll Schedule'!C16:W16 | E44: =21 | F44: 21 | G44: =E44-F44 | H44: 0 | I44: =IF(G44=0,"OK","FAIL") | J44: This line is expected to be formula-driven across every period. Formula presence is verified at export; live edit integrity is covered by the logic and bridge checks above.
A45: Formula Manifest | B45: Payroll Schedule - Total Payroll | C45: Payroll Schedule | D45: 'Payroll Schedule'!C17:W17 | E45: =21 | F45: 21 | G45: =E45-F45 | H45: 0 | I45: =IF(G45=0,"OK","FAIL") | J45: This line is expected to be formula-driven across every period. Formula presence is verified at export; live edit integrity is covered by the logic and bridge checks above.
A46: Formula Manifest | B46: Payroll Schedule - Total Revenue | C46: Payroll Schedule | D46: 'Payroll Schedule'!C18:W18 | E46: =21 | F46: 21 | G46: =E46-F46 | H46: 0 | I46: =IF(G46=0,"OK","FAIL") | J46: This line is expected to be formula-driven across every period. Formula presence is verified at export; live edit integrity is covered by the logic and bridge checks above.
A47: Formula Manifest | B47: Payroll Schedule - Total Capacity Units | C47: Payroll Schedule | D47: 'Payroll Schedule'!C19:W19 | E47: =21 | F47: 21 | G47: =E47-F47 | H47: 0 | I47: =IF(G47=0,"OK","FAIL") | J47: This line is expected to be formula-driven across every period. Formula presence is verified at export; live edit integrity is covered by the logic and bridge checks above.
A48: Formula Manifest | B48: Payroll Schedule - Revenue per Employee | C48: Payroll Schedule | D48: 'Payroll Schedule'!C20:W20 | E48: =21 | F48: 21 | G48: =E48-F48 | H48: 0 | I48: =IF(G48=0,"OK","FAIL") | J48: This line is expected to be formula-driven across every period. Formula presence is verified at export; live edit integrity is covered by the logic and bridge checks above.
A49: Formula Manifest | B49: Payroll Schedule - Units per Employee | C49: Payroll Schedule | D49: 'Payroll Schedule'!C21:W21 | E49: =21 | F49: 21 | G49: =E49-F49 | H49: 0 | I49: =IF(G49=0,"OK","FAIL") | J49: This line is expected to be formula-driven across every period. Formula presence is verified at export; live edit integrity is covered by the logic and bridge checks above.
A50: Formula Manifest | B50: Payroll Schedule - Payroll % of Revenue | C50: Payroll Schedule | D50: 'Payroll Schedule'!C22:W22 | E50: =21 | F50: 21 | G50: =E50-F50 | H50: 0 | I50: =IF(G50=0,"OK","FAIL") | J50: This line is expected to be formula-driven across every period. Formula presence is verified at export; live edit integrity is covered by the logic and bridge checks above.
A51: Formula Manifest | B51: CapEx Schedule - Lease Additions | C51: CapEx Depreciation | D51: 'CapEx Depreciation'!D9:W9 | E51: =20 | F51: 20 | G51: =E51-F51 | H51: 0 | I51: =IF(G51=0,"OK","FAIL") | J51: This line is expected to be formula-driven across every period. Formula presence is verified at export; live edit integrity is covered by the logic and bridge checks above.
A52: Formula Manifest | B52: CapEx Schedule - Closing PPE | C52: CapEx Depreciation | D52: 'CapEx Depreciation'!C12:W12 | E52: =21 | F52: 21 | G52: =E52-F52 | H52: 0 | I52: =IF(G52=0,"OK","FAIL") | J52: This line is expected to be formula-driven across every period. Formula presence is verified at export; live edit integrity is covered by the logic and bridge checks above.
A53: Formula Manifest | B53: Debt Schedule - Opening Debt | C53: Debt Schedule | D53: 'Debt Schedule'!D7:W7 | E53: =20 | F53: 20 | G53: =E53-F53 | H53: 0 | I53: =IF(G53=0,"OK","FAIL") | J53: This debt/lease line is expected to be formula-driven across every period. Formula presence is verified at export; live edit integrity is covered by the logic and bridge checks above.
A54: Formula Manifest | B54: Debt Schedule - Actual Debt Repayment | C54: Debt Schedule | D54: 'Debt Schedule'!C10:W10 | E54: =21 | F54: 21 | G54: =E54-F54 | H54: 0 | I54: =IF(G54=0,"OK","FAIL") | J54: This debt/lease line is expected to be formula-driven across every period. Formula presence is verified at export; live edit integrity is covered by the logic and bridge checks above.
A55: Formula Manifest | B55: Debt Schedule - Closing Debt | C55: Debt Schedule | D55: 'Debt Schedule'!C11:W11 | E55: =21 | F55: 21 | G55: =E55-F55 | H55: 0 | I55: =IF(G55=0,"OK","FAIL") | J55: This debt/lease line is expected to be formula-driven across every period. Formula presence is verified at export; live edit integrity is covered by the logic and bridge checks above.
A56: Formula Manifest | B56: Debt Schedule - Interest Expense | C56: Debt Schedule | D56: 'Debt Schedule'!C13:W13 | E56: =21 | F56: 21 | G56: =E56-F56 | H56: 0 | I56: =IF(G56=0,"OK","FAIL") | J56: This debt/lease line is expected to be formula-driven across every period. Formula presence is verified at export; live edit integrity is covered by the logic and bridge checks above.
A57: Formula Manifest | B57: Debt Schedule - Total Debt Service | C57: Debt Schedule | D57: 'Debt Schedule'!C14:W14 | E57: =21 | F57: 21 | G57: =E57-F57 | H57: 0 | I57: =IF(G57=0,"OK","FAIL") | J57: This debt/lease line is expected to be formula-driven across every period. Formula presence is verified at export; live edit integrity is covered by the logic and bridge checks above.
A58: Formula Manifest | B58: Debt Schedule - Lease Opening Balance | C58: Debt Schedule | D58: 'Debt Schedule'!D18:W18 | E58: =20 | F58: 20 | G58: =E58-F58 | H58: 0 | I58: =IF(G58=0,"OK","FAIL") | J58: This debt/lease line is expected to be formula-driven across every period. Formula presence is verified at export; live edit integrity is covered by the logic and bridge checks above.
A59: Formula Manifest | B59: Debt Schedule - Lease Principal Repayments | C59: Debt Schedule | D59: 'Debt Schedule'!C20:W20 | E59: =21 | F59: 21 | G59: =E59-F59 | H59: 0 | I59: =IF(G59=0,"OK","FAIL") | J59: This debt/lease line is expected to be formula-driven across every period. Formula presence is verified at export; live edit integrity is covered by the logic and bridge checks above.
A60: Formula Manifest | B60: Debt Schedule - Lease Closing Balance | C60: Debt Schedule | D60: 'Debt Schedule'!C23:W23 | E60: =21 | F60: 21 | G60: =E60-F60 | H60: 0 | I60: =IF(G60=0,"OK","FAIL") | J60: This debt/lease line is expected to be formula-driven across every period. Formula presence is verified at export; live edit integrity is covered by the logic and bridge checks above.
A61: Formula Manifest | B61: Payroll Detail - Ending FTE | C61: Payroll Schedule | D61: 'Payroll Schedule'!G27:G86 | E61: =60 | F61: 60 | G61: =E61-F61 | H61: 0 | I61: =IF(G61=0,"OK","FAIL") | J61: Payroll detail calculation columns must remain formulas so edits flow downstream. Formula presence is verified at export; live edit integrity is covered by the logic and bridge checks above.
A62: Formula Manifest | B62: Payroll Detail - Average FTE | C62: Payroll Schedule | D62: 'Payroll Schedule'!H27:H86 | E62: =60 | F62: 60 | G62: =E62-F62 | H62: 0 | I62: =IF(G62=0,"OK","FAIL") | J62: Payroll detail calculation columns must remain formulas so edits flow downstream. Formula presence is verified at export; live edit integrity is covered by the logic and bridge checks above.
A63: Formula Manifest | B63: Payroll Detail - Wage Cost | C63: Payroll Schedule | D63: 'Payroll Schedule'!K27:K86 | E63: =60 | F63: 60 | G63: =E63-F63 | H63: 0 | I63: =IF(G63=0,"OK","FAIL") | J63: Payroll detail calculation columns must remain formulas so edits flow downstream. Formula presence is verified at export; live edit integrity is covered by the logic and bridge checks above.
A64: Formula Manifest | B64: Payroll Detail - Taxes & Benefits | C64: Payroll Schedule | D64: 'Payroll Schedule'!L27:L86 | E64: =60 | F64: 60 | G64: =E64-F64 | H64: 0 | I64: =IF(G64=0,"OK","FAIL") | J64: Payroll detail calculation columns must remain formulas so edits flow downstream. Formula presence is verified at export; live edit integrity is covered by the logic and bridge checks above.
A65: Formula Manifest | B65: Payroll Detail - Total Payroll | C65: Payroll Schedule | D65: 'Payroll Schedule'!M27:M86 | E65: =60 | F65: 60 | G65: =E65-F65 | H65: 0 | I65: =IF(G65=0,"OK","FAIL") | J65: Payroll detail calculation columns must remain formulas so edits flow downstream. Formula presence is verified at export; live edit integrity is covered by the logic and bridge checks above.
A66: Formula Manifest | B66: Model Inputs - revenue::lob_1_product_1::Capacity | C66: Model Inputs | D66: 'Model Inputs'!C7:W7 | E66: =21 | F66: 21 | G66: =E66-F66 | H66: 0 | I66: =IF(G66=0,"OK","FAIL") | J66: Formula bridge rows in Model Inputs must stay linked to schedules. Formula presence is verified at export; live edit integrity is covered by the logic and bridge checks above.
A67: Formula Manifest | B67: Model Inputs - revenue::lob_1_product_1::Unit Price | C67: Model Inputs | D67: 'Model Inputs'!C8:W8 | E67: =21 | F67: 21 | G67: =E67-F67 | H67: 0 | I67: =IF(G67=0,"OK","FAIL") | J67: Formula bridge rows in Model Inputs must stay linked to schedules. Formula presence is verified at export; live edit integrity is covered by the logic and bridge checks above.
A68: Formula Manifest | B68: Model Inputs - revenue::lob_1_product_1::Utilization | C68: Model Inputs | D68: 'Model Inputs'!C9:W9 | E68: =21 | F68: 21 | G68: =E68-F68 | H68: 0 | I68: =IF(G68=0,"OK","FAIL") | J68: Formula bridge rows in Model Inputs must stay linked to schedules. Formula presence is verified at export; live edit integrity is covered by the logic and bridge checks above.
A69: Formula Manifest | B69: Model Inputs - revenue::lob_1_product_1::Revenue | C69: Model Inputs | D69: 'Model Inputs'!C10:W10 | E69: =21 | F69: 21 | G69: =E69-F69 | H69: 0 | I69: =IF(G69=0,"OK","FAIL") | J69: Formula bridge rows in Model Inputs must stay linked to schedules. Formula presence is verified at export; live edit integrity is covered by the logic and bridge checks above.
A70: Formula Manifest | B70: Model Inputs - is::Revenue | C70: Model Inputs | D70: 'Model Inputs'!C11:W11 | E70: =21 | F70: 21 | G70: =E70-F70 | H70: 0 | I70: =IF(G70=0,"OK","FAIL") | J70: Formula bridge rows in Model Inputs must stay linked to schedules. Formula presence is verified at export; live edit integrity is covered by the logic and bridge checks above.
A71: Formula Manifest | B71: Model Inputs - is::Lease | C71: Model Inputs | D71: 'Model Inputs'!C15:W15 | E71: =21 | F71: 21 | G71: =E71-F71 | H71: 0 | I71: =IF(G71=0,"OK","FAIL") | J71: Formula bridge rows in Model Inputs must stay linked to schedules. Formula presence is verified at export; live edit integrity is covered by the logic and bridge checks above.
A72: Formula Manifest | B72: Model Inputs - is::Payroll | C72: Model Inputs | D72: 'Model Inputs'!D16:W16 | E72: =20 | F72: 20 | G72: =E72-F72 | H72: 0 | I72: =IF(G72=0,"OK","FAIL") | J72: Formula bridge rows in Model Inputs must stay linked to schedules. Formula presence is verified at export; live edit integrity is covered by the logic and bridge checks above.
A73: Formula Manifest | B73: Model Inputs - is::Interest Rate | C73: Model Inputs | D73: 'Model Inputs'!C18:W18 | E73: =21 | F73: 21 | G73: =E73-F73 | H73: 0 | I73: =IF(G73=0,"OK","FAIL") | J73: Formula bridge rows in Model Inputs must stay linked to schedules. Formula presence is verified at export; live edit integrity is covered by the logic and bridge checks above.
A74: Formula Manifest | B74: Model Inputs - is::Interest Expense | C74: Model Inputs | D74: 'Model Inputs'!D19:W19 | E74: =20 | F74: 20 | G74: =E74-F74 | H74: 0 | I74: =IF(G74=0,"OK","FAIL") | J74: Formula bridge rows in Model Inputs must stay linked to schedules. Formula presence is verified at export; live edit integrity is covered by the logic and bridge checks above.
A75: Formula Manifest | B75: Model Inputs - is::Depreciation | C75: Model Inputs | D75: 'Model Inputs'!C20:W20 | E75: =21 | F75: 21 | G75: =E75-F75 | H75: 0 | I75: =IF(G75=0,"OK","FAIL") | J75: Formula bridge rows in Model Inputs must stay linked to schedules. Formula presence is verified at export; live edit integrity is covered by the logic and bridge checks above.
A76: Formula Manifest | B76: Model Inputs - is::Depreciation Expense | C76: Model Inputs | D76: 'Model Inputs'!C21:W21 | E76: =21 | F76: 21 | G76: =E76-F76 | H76: 0 | I76: =IF(G76=0,"OK","FAIL") | J76: Formula bridge rows in Model Inputs must stay linked to schedules. Formula presence is verified at export; live edit integrity is covered by the logic and bridge checks above.
A77: Formula Manifest | B77: Model Inputs - bs::Accounts Receivable Days | C77: Model Inputs | D77: 'Model Inputs'!C25:W25 | E77: =21 | F77: 21 | G77: =E77-F77 | H77: 0 | I77: =IF(G77=0,"OK","FAIL") | J77: Formula bridge rows in Model Inputs must stay linked to schedules. Formula presence is verified at export; live edit integrity is covered by the logic and bridge checks above.
A78: Formula Manifest | B78: Model Inputs - bs::Inventory Days | C78: Model Inputs | D78: 'Model Inputs'!C26:W26 | E78: =21 | F78: 21 | G78: =E78-F78 | H78: 0 | I78: =IF(G78=0,"OK","FAIL") | J78: Formula bridge rows in Model Inputs must stay linked to schedules. Formula presence is verified at export; live edit integrity is covered by the logic and bridge checks above.
A79: Formula Manifest | B79: Model Inputs - bs::Accounts Payable Days | C79: Model Inputs | D79: 'Model Inputs'!C27:W27 | E79: =21 | F79: 21 | G79: =E79-F79 | H79: 0 | I79: =IF(G79=0,"OK","FAIL") | J79: Formula bridge rows in Model Inputs must stay linked to schedules. Formula presence is verified at export; live edit integrity is covered by the logic and bridge checks above.
A80: Formula Manifest | B80: Model Inputs - bs::Prepaid Expenses (% of Revenue) | C80: Model Inputs | D80: 'Model Inputs'!C28:W28 | E80: =21 | F80: 21 | G80: =E80-F80 | H80: 0 | I80: =IF(G80=0,"OK","FAIL") | J80: Formula bridge rows in Model Inputs must stay linked to schedules. Formula presence is verified at export; live edit integrity is covered by the logic and bridge checks above.
A81: Formula Manifest | B81: Model Inputs - bs::Deferred Revenue (% of Revenue) | C81: Model Inputs | D81: 'Model Inputs'!C29:W29 | E81: =21 | F81: 21 | G81: =E81-F81 | H81: 0 | I81: =IF(G81=0,"OK","FAIL") | J81: Formula bridge rows in Model Inputs must stay linked to schedules. Formula presence is verified at export; live edit integrity is covered by the logic and bridge checks above.
A82: Formula Manifest | B82: Model Inputs - bs::Short Term Debt (% of LTD) | C82: Model Inputs | D82: 'Model Inputs'!C30:W30 | E82: =21 | F82: 21 | G82: =E82-F82 | H82: 0 | I82: =IF(G82=0,"OK","FAIL") | J82: Formula bridge rows in Model Inputs must stay linked to schedules. Formula presence is verified at export; live edit integrity is covered by the logic and bridge checks above.
A83: Formula Manifest | B83: Model Inputs - bs::Owner's Capital | C83: Model Inputs | D83: 'Model Inputs'!C31:W31 | E83: =21 | F83: 21 | G83: =E83-F83 | H83: 0 | I83: =IF(G83=0,"OK","FAIL") | J83: Formula bridge rows in Model Inputs must stay linked to schedules. Formula presence is verified at export; live edit integrity is covered by the logic and bridge checks above.
A84: Formula Manifest | B84: Model Inputs - bs::Other Equity | C84: Model Inputs | D84: 'Model Inputs'!C32:W32 | E84: =21 | F84: 21 | G84: =E84-F84 | H84: 0 | I84: =IF(G84=0,"OK","FAIL") | J84: Formula bridge rows in Model Inputs must stay linked to schedules. Formula presence is verified at export; live edit integrity is covered by the logic and bridge checks above.
A85: Formula Manifest | B85: Model Inputs - bs::Distributions | C85: Model Inputs | D85: 'Model Inputs'!C33:W33 | E85: =21 | F85: 21 | G85: =E85-F85 | H85: 0 | I85: =IF(G85=0,"OK","FAIL") | J85: Formula bridge rows in Model Inputs must stay linked to schedules. Formula presence is verified at export; live edit integrity is covered by the logic and bridge checks above.
A86: Formula Manifest | B86: Model Inputs - cash::Cash Opening Balance | C86: Model Inputs | D86: 'Model Inputs'!C36:W36 | E86: =21 | F86: 21 | G86: =E86-F86 | H86: 0 | I86: =IF(G86=0,"OK","FAIL") | J86: Formula bridge rows in Model Inputs must stay linked to schedules. Formula presence is verified at export; live edit integrity is covered by the logic and bridge checks above.
... A154: Formula Manifest | B154: FINMO - Cash Flow - Ending Cash | C154: FINMO | D154: 'FINMO'!C61:W61 | E154: =21 | F154: 21 | G154: =E154-F154 | H154: 0 | I154: =IF(G154=0,"OK","FAIL") | J154: FINMO statement lines must remain formula-driven. Formula presence is verified at export; live edit integrity is covered by the logic and bridge checks above.
A156: Formula Error Scans
A157: Formula Error Scan | B157: Revenue Drivers formula/error scan | C157: Revenue Drivers | D157: 'Revenue Drivers'!C7:W28 | E157: =SUMPRODUCT(--ISERROR('Revenue Drivers'!C7:W28)) | F157: 0 | G157: =E157-F157 | H157: 0 | I157: =IF(E157=0,"OK","FAIL") | J157: Counts Excel error values in the range.
A158: Formula Error Scan | B158: Payroll Schedule formula/error scan | C158: Payroll Schedule | D158: 'Payroll Schedule'!C15:W86 | E158: =SUMPRODUCT(--ISERROR('Payroll Schedule'!C15:W86)) | F158: 0 | G158: =E158-F158 | H158: 0 | I158: =IF(E158=0,"OK","FAIL") | J158: Counts Excel error values in the range.
A159: Formula Error Scan | B159: Debt Schedule formula/error scan | C159: Debt Schedule | D159: 'Debt Schedule'!C7:W26 | E159: =SUMPRODUCT(--ISERROR('Debt Schedule'!C7:W26)) | F159: 0 | G159: =E159-F159 | H159: 0 | I159: =IF(E159=0,"OK","FAIL") | J159: Counts Excel error values in the range.
A160: Formula Error Scan | B160: CapEx Depreciation formula/error scan | C160: CapEx Depreciation | D160: 'CapEx Depreciation'!C7:W14 | E160: =SUMPRODUCT(--ISERROR('CapEx Depreciation'!C7:W14)) | F160: 0 | G160: =E160-F160 | H160: 0 | I160: =IF(E160=0,"OK","FAIL") | J160: Counts Excel error values in the range.
A161: Formula Error Scan | B161: Cash Equity Schedule formula/error scan | C161: Cash Equity Schedule | D161: 'Cash Equity Schedule'!C7:W12 | E161: =SUMPRODUCT(--ISERROR('Cash Equity Schedule'!C7:W12)) | F161: 0 | G161: =E161-F161 | H161: 0 | I161: =IF(E161=0,"OK","FAIL") | J161: Counts Excel error values in the range.
A162: Formula Error Scan | B162: Model Inputs formula/error scan | C162: Model Inputs | D162: 'Model Inputs'!C7:W54 | E162: =SUMPRODUCT(--ISERROR('Model Inputs'!C7:W54)) | F162: 0 | G162: =E162-F162 | H162: 0 | I162: =IF(E162=0,"OK","FAIL") | J162: Counts Excel error values in the range.
A163: Formula Error Scan | B163: FINMO formula/error scan | C163: FINMO | D163: 'FINMO'!C8:W61 | E163: =SUMPRODUCT(--ISERROR('FINMO'!C8:W61)) | F163: 0 | G163: =E163-F163 | H163: 0 | I163: =IF(E163=0,"OK","FAIL") | J163: Counts Excel error values in the range.
A165: Persisted Baseline Reconciliation
A166: Persisted Baseline | B166: Revenue Q20 | C166: FINMO vs Audit Source | D166: 'FINMO'!W8 | E166: ='FINMO'!W8 | F166: ='Audit Source'!W7 | G166: =E166-F166 | H166: 1 | I166: =IF(ABS(G166)<=H166,"MATCH","CHANGED") | J166: CHANGED means assumptions were edited from the persisted run; it is informational and does not fail Model Status.
A167: Persisted Baseline | B167: Payroll Q20 | C167: FINMO vs Audit Source | D167: 'FINMO'!W14 | E167: ='FINMO'!W14 | F167: ='Audit Source'!W13 | G167: =E167-F167 | H167: 1 | I167: =IF(ABS(G167)<=H167,"MATCH","CHANGED") | J167: CHANGED means assumptions were edited from the persisted run; it is informational and does not fail Model Status.
A168: Persisted Baseline | B168: Net Income Q20 | C168: FINMO vs Audit Source | D168: 'FINMO'!W20 | E168: ='FINMO'!W20 | F168: ='Audit Source'!W19 | G168: =E168-F168 | H168: 1 | I168: =IF(ABS(G168)<=H168,"MATCH","CHANGED") | J168: CHANGED means assumptions were edited from the persisted run; it is informational and does not fail Model Status.
A169: Persisted Baseline | B169: Cash Q20 | C169: FINMO vs Audit Source | D169: 'FINMO'!W23 | E169: ='FINMO'!W23 | F169: ='Audit Source'!W23 | G169: =E169-F169 | H169: 1 | I169: =IF(ABS(G169)<=H169,"MATCH","CHANGED") | J169: CHANGED means assumptions were edited from the persisted run; it is informational and does not fail Model Status.
A170: Persisted Baseline | B170: Total Assets Q20 | C170: FINMO vs Audit Source | D170: 'FINMO'!W31 | E170: ='FINMO'!W31 | F170: ='Audit Source'!W29 | G170: =E170-F170 | H170: 1 | I170: =IF(ABS(G170)<=H170,"MATCH","CHANGED") | J170: CHANGED means assumptions were edited from the persisted run; it is informational and does not fail Model Status.
A171: Persisted Baseline | B171: Total Liabilities & Equity Q20 | C171: FINMO vs Audit Source | D171: 'FINMO'!W43 | E171: ='FINMO'!W43 | F171: ='Audit Source'!W41 | G171: =E171-F171 | H171: 1 | I171: =IF(ABS(G171)<=H171,"MATCH","CHANGED") | J171: CHANGED means assumptions were edited from the persisted run; it is informational and does not fail Model Status.
A172: Persisted Baseline | B172: Ending Cash Q20 | C172: FINMO vs Audit Source | D172: 'FINMO'!W61 | E172: ='FINMO'!W61 | F172: ='Audit Source'!W59 | G172: =E172-F172 | H172: 1 | I172: =IF(ABS(G172)<=H172,"MATCH","CHANGED") | J172: CHANGED means assumptions were edited from the persisted run; it is informational and does not fail Model Status.

Sheet Diagnostics
A1: Run Diagnostics
A3: Run Metadata
A4: Planning Mode | B4: rebalance
A5: Cash Strategy | B5: balanced
A6: Business Stage | B6: operating
A7: Business Name | B7: North Ridge Auto Care
A8: Business Start Date | B8: 8/5/2024
A9: NAICS-6 | B9: 811111
A10: Draft ID | B10: e83eb35e7b034a9bbb9bcea3842654e9
A11: Planning Run ID | B11: ac314a2946c54d31b97b20d57069132d
A13: Acceptance Gate
A14: Score | B14: 16/16
A15: Verdict | B15: PASSED
A17: GPT Exhaustion Handler
A18: Fired | B18: Yes
A19: Status | B19: landed_verified_tool_call
A20: Scope | B20: pnl_path
A21: Tool calls used | B21: 1
A22: Budget extension triggered | B22: False
A24: Realism Check Detail
A25: Metric Key | B25: Status
A26: advertising_percent_of_revenue | B26: ✓
A27: ap_days_dpo | B27: ✓
A28: ar_days_dso | B28: ✓
A29: capex_percent_of_revenue | B29: ✓
A30: cogs_percent_of_revenue | B30: ✓
A31: current_assets_minus_cash | B31: ✓
A32: current_liabilities_to_revenue | B32: ✓
A33: current_ratio | B33: ✓
A34: debt_to_assets | B34: ✓
A35: debt_to_equity | B35: ✓
A36: deferred_revenue_percent_of_revenue | B36: ✓
... A58: total_assets_to_revenue | B58: ✓
