Workbook

Sheet Revenue Drivers
A1: Revenue Drivers
A2: Source operating drivers. Model Inputs links to these rows.
C4: Stub | D4: Q1 | E4: Q2 | F4: Q3 | G4: Q4 | H4: Q5 | I4: Q6 | J4: Q7 | K4: Q8 | L4: Q9 | M4: Q10 | N4: Q11 | O4: Q12 | P4: Q13 | Q4: Q14 | R4: Q15 | S4: Q16 | T4: Q17 | U4: Q18 | V4: Q19 | W4: Q20 | X4: Y1 | Y4: Y2 | Z4: Y3 | AA4: Y4 | AB4: Y5
C5: 46162 | D5: 46295 | E5: 46387 | F5: 46477 | G5: 46568 | H5: 46660 | I5: 46752 | J5: 46843 | K5: 46934 | L5: 47026 | M5: 47118 | N5: 47208 | O5: 47299 | P5: 47391 | Q5: 47483 | R5: 47573 | S5: 47664 | T5: 47756 | U5: 47848 | V5: 47938 | W5: 48029 | X5: Annual | Y5: Annual | Z5: Annual | AA5: Annual | AB5: Annual
A6: Revenue Driver Source Rows
A7: Primary line of business / Individual IV session
A8: Primary line of business / Individual IV session - Capacity | B8: Source driver | C8: 260 | D8: 293.49069 | E8: 293.49069 | F8: 293.49069 | G8: 293.49069 | H8: 293.49069 | I8: 293.49069 | J8: 293.49069 | K8: 293.49069 | L8: 293.49069 | M8: 293.49069 | N8: 293.49069 | O8: 293.49069 | P8: 293.49069 | Q8: 293.49069 | R8: 293.49069 | S8: 293.49069 | T8: 293.49069 | U8: 293.49069 | V8: 293.49069 | W8: 308.16522
A9: Primary line of business / Individual IV session - Unit Price | B9: Source driver | C9: 150 | D9: 150 | E9: 154 | F9: 158 | G9: 162 | H9: 166 | I9: 170 | J9: 174 | K9: 178 | L9: 182 | M9: 186 | N9: 190 | O9: 192.22222 | P9: 194.44444 | Q9: 196.66667 | R9: 198.88889 | S9: 201.11111 | T9: 203.33333 | U9: 205.55556 | V9: 207.77778 | W9: 210
A10: Primary line of business / Individual IV session - Utilization | B10: Source driver | C10: 0.7 | D10: 0.7 | E10: 0.714 | F10: 0.728 | G10: 0.742 | H10: 0.756 | I10: 0.77 | J10: 0.784 | K10: 0.798 | L10: 0.812 | M10: 0.826 | N10: 0.84 | O10: 0.84 | P10: 0.84 | Q10: 0.84 | R10: 0.84 | S10: 0.84 | T10: 0.84 | U10: 0.84 | V10: 0.84 | W10: 0.84
A11: Primary line of business / Individual IV session - Revenue | B11: Capacity x Unit Price x Utilization | C11: =C8*C9*C10 | D11: =D8*D9*D10 | E11: =E8*E9*E10 | F11: =F8*F9*F10 | G11: =G8*G9*G10 | H11: =H8*H9*H10 | I11: =I8*I9*I10 | J11: =J8*J9*J10 | ... W11: =W8*W9*W10 | X11: =SUM(D11:G11) | Y11: =SUM(H11:K11) | Z11: =SUM(L11:O11) | AA11: =SUM(P11:S11) | AB11: =SUM(T11:W11)
A13: Primary line of business / Monthly IV membership
A14: Primary line of business / Monthly IV membership - Capacity | B14: Source driver | C14: 60 | D14: 67.728621 | E14: 67.728621 | F14: 67.728621 | G14: 67.728621 | H14: 67.728621 | I14: 67.728621 | J14: 67.728621 | K14: 67.728621 | L14: 67.728621 | M14: 67.728621 | N14: 67.728621 | O14: 67.728621 | P14: 67.728621 | Q14: 67.728621 | R14: 67.728621 | S14: 67.728621 | T14: 67.728621 | U14: 67.728621 | V14: 67.728621 | W14: 71.115052
A15: Primary line of business / Monthly IV membership - Unit Price | B15: Source driver | C15: 400 | D15: 150 | E15: 154 | F15: 158 | G15: 162 | H15: 166 | I15: 170 | J15: 174 | K15: 178 | L15: 182 | M15: 186 | N15: 190 | O15: 192.22222 | P15: 194.44444 | Q15: 196.66667 | R15: 198.88889 | S15: 201.11111 | T15: 203.33333 | U15: 205.55556 | V15: 207.77778 | W15: 210
A16: Primary line of business / Monthly IV membership - Utilization | B16: Source driver | C16: 0.5 | D16: 0.7 | E16: 0.714 | F16: 0.728 | G16: 0.742 | H16: 0.756 | I16: 0.77 | J16: 0.784 | K16: 0.798 | L16: 0.812 | M16: 0.826 | N16: 0.84 | O16: 0.84 | P16: 0.84 | Q16: 0.84 | R16: 0.84 | S16: 0.84 | T16: 0.84 | U16: 0.84 | V16: 0.84 | W16: 0.84
A17: Primary line of business / Monthly IV membership - Revenue | B17: Capacity x Unit Price x Utilization | C17: =C14*C15*C16 | D17: =D14*D15*D16 | E17: =E14*E15*E16 | F17: =F14*F15*F16 | G17: =G14*G15*G16 | H17: =H14*H15*H16 | I17: =I14*I15*I16 | J17: =J14*J15*J16 | ... W17: =W14*W15*W16 | X17: =SUM(D17:G17) | Y17: =SUM(H17:K17) | Z17: =SUM(L17:O17) | AA17: =SUM(P17:S17) | AB17: =SUM(T17:W17)
A19: Primary line of business / Retail wellness products
A20: Primary line of business / Retail wellness products - Capacity | B20: Source driver | C20: 260 | D20: 293.49069 | E20: 293.49069 | F20: 293.49069 | G20: 293.49069 | H20: 293.49069 | I20: 293.49069 | J20: 293.49069 | K20: 293.49069 | L20: 293.49069 | M20: 293.49069 | N20: 293.49069 | O20: 293.49069 | P20: 293.49069 | Q20: 293.49069 | R20: 293.49069 | S20: 293.49069 | T20: 293.49069 | U20: 293.49069 | V20: 293.49069 | W20: 308.16522
A21: Primary line of business / Retail wellness products - Unit Price | B21: Source driver | C21: 20 | D21: 150 | E21: 154 | F21: 158 | G21: 162 | H21: 166 | I21: 170 | J21: 174 | K21: 178 | L21: 182 | M21: 186 | N21: 190 | O21: 192.22222 | P21: 194.44444 | Q21: 196.66667 | R21: 198.88889 | S21: 201.11111 | T21: 203.33333 | U21: 205.55556 | V21: 207.77778 | W21: 210
A22: Primary line of business / Retail wellness products - Utilization | B22: Source driver | C22: 0 | D22: 0.7 | E22: 0.714 | F22: 0.728 | G22: 0.742 | H22: 0.756 | I22: 0.77 | J22: 0.784 | K22: 0.798 | L22: 0.812 | M22: 0.826 | N22: 0.84 | O22: 0.84 | P22: 0.84 | Q22: 0.84 | R22: 0.84 | S22: 0.84 | T22: 0.84 | U22: 0.84 | V22: 0.84 | W22: 0.84
A23: Primary line of business / Retail wellness products - Revenue | B23: Capacity x Unit Price x Utilization | C23: =C20*C21*C22 | D23: =D20*D21*D22 | E23: =E20*E21*E22 | F23: =F20*F21*F22 | G23: =G20*G21*G22 | H23: =H20*H21*H22 | I23: =I20*I21*I22 | J23: =J20*J21*J22 | ... W23: =W20*W21*W22 | X23: =SUM(D23:G23) | Y23: =SUM(H23:K23) | Z23: =SUM(L23:O23) | AA23: =SUM(P23:S23) | AB23: =SUM(T23:W23)
A25: Total Capacity Units | B25: All revenue driver capacity units | C25: =SUM(C8,C14,C20) | D25: =SUM(D8,D14,D20) | E25: =SUM(E8,E14,E20) | F25: =SUM(F8,F14,F20) | G25: =SUM(G8,G14,G20) | H25: =SUM(H8,H14,H20) | I25: =SUM(I8,I14,I20) | J25: =SUM(J8,J14,J20) | ... W25: =SUM(W8,W14,W20) | X25: =SUM(D25:G25) | Y25: =SUM(H25:K25) | Z25: =SUM(L25:O25) | AA25: =SUM(P25:S25) | AB25: =SUM(T25:W25)
A26: Total Revenue | B26: All revenue products | C26: =SUM(C11,C17,C23) | D26: =SUM(D11,D17,D23) | E26: =SUM(E11,E17,E23) | F26: =SUM(F11,F17,F23) | G26: =SUM(G11,G17,G23) | H26: =SUM(H11,H17,H23) | I26: =SUM(I11,I17,I23) | J26: =SUM(J11,J17,J23) | ... W26: =SUM(W11,W17,W23) | X26: =SUM(D26:G26) | Y26: =SUM(H26:K26) | Z26: =SUM(L26:O26) | AA26: =SUM(P26:S26) | AB26: =SUM(T26:W26)
A28: Stage Ramp Contract
A29: Actual Revenue QoQ Growth | B29: Total revenue growth from modeled revenue drivers | C29: =0 | D29: =IFERROR(D26/C26-1,0) | E29: =IFERROR(E26/D26-1,0) | F29: =IFERROR(F26/E26-1,0) | G29: =IFERROR(G26/F26-1,0) | H29: =IFERROR(H26/G26-1,0) | I29: =IFERROR(I26/H26-1,0) | J29: =IFERROR(J26/I26-1,0) | K29: =IFERROR(K26/J26-1,0) | ... W29: =IFERROR(W26/V26-1,0) | X29: =AVERAGE(D29:G29) | Y29: =AVERAGE(H29:K29) | Z29: =AVERAGE(L29:O29) | AA29: =AVERAGE(P29:S29) | AB29: =AVERAGE(T29:W29)
A30: Stage Ramp Revenue QoQ Target | B30: GPT-selected stage ramp contract | C30: 0 | D30: 0.02 | E30: 0.02 | F30: 0.02 | G30: 0.02 | H30: 0.02 | I30: 0.02 | J30: 0.02 | K30: 0.02 | L30: 0.02 | M30: 0.02 | N30: 0.02 | O30: 0.02 | P30: 0.02 | Q30: 0.02 | R30: 0.02 | S30: 0.02 | T30: 0.02 | U30: 0.02 | V30: 0.02 | W30: 0.02 | X30: =AVERAGE(D30:G30) | Y30: =AVERAGE(H30:K30) | Z30: =AVERAGE(L30:O30) | AA30: =AVERAGE(P30:S30) | AB30: =AVERAGE(T30:W30)
A31: Stage Ramp Revenue QoQ Max | B31: GPT-selected stage ramp contract | C31: 0 | D31: 0.07 | E31: 0.07 | F31: 0.07 | G31: 0.07 | H31: 0.07 | I31: 0.07 | J31: 0.07 | K31: 0.07 | L31: 0.07 | M31: 0.07 | N31: 0.07 | O31: 0.07 | P31: 0.07 | Q31: 0.07 | R31: 0.07 | S31: 0.07 | T31: 0.07 | U31: 0.07 | V31: 0.07 | W31: 0.07 | X31: =AVERAGE(D31:G31) | Y31: =AVERAGE(H31:K31) | Z31: =AVERAGE(L31:O31) | AA31: =AVERAGE(P31:S31) | AB31: =AVERAGE(T31:W31)
A32: Stage Ramp Revenue QoQ Spike Max | B32: GPT-selected stage ramp contract | C32: 0 | D32: 0.07 | E32: 0.07 | F32: 0.07 | G32: 0.07 | H32: 0.07 | I32: 0.07 | J32: 0.07 | K32: 0.07 | L32: 0.07 | M32: 0.07 | N32: 0.07 | O32: 0.07 | P32: 0.07 | Q32: 0.07 | R32: 0.07 | S32: 0.07 | T32: 0.07 | U32: 0.07 | V32: 0.07 | W32: 0.07 | X32: =AVERAGE(D32:G32) | Y32: =AVERAGE(H32:K32) | Z32: =AVERAGE(L32:O32) | AA32: =AVERAGE(P32:S32) | AB32: =AVERAGE(T32:W32)
A33: Stage Ramp Utilization Cap | B33: GPT-selected stage ramp contract | C33: 0 | D33: 0.65 | E33: 0.67 | F33: 0.69 | G33: 0.71 | H33: 0.73 | I33: 0.75 | J33: 0.77 | K33: 0.79 | L33: 0.81 | M33: 0.83 | N33: 0.85 | O33: 0.85 | P33: 0.85 | Q33: 0.85 | R33: 0.85 | S33: 0.85 | T33: 0.85 | U33: 0.85 | V33: 0.85 | W33: 0.85 | X33: =AVERAGE(D33:G33) | Y33: =AVERAGE(H33:K33) | Z33: =AVERAGE(L33:O33) | AA33: =AVERAGE(P33:S33) | AB33: =AVERAGE(T33:W33)
A34: Stage Ramp COGS % Revenue Target | B34: GPT-selected stage ramp contract | C34: 0 | D34: 0.47 | E34: 0.47 | F34: 0.47 | G34: 0.47 | H34: 0.47 | I34: 0.47 | J34: 0.47 | K34: 0.47 | L34: 0.47 | M34: 0.47 | N34: 0.47 | O34: 0.47 | P34: 0.47 | Q34: 0.47 | R34: 0.47 | S34: 0.47 | T34: 0.47 | U34: 0.47 | V34: 0.47 | W34: 0.47 | X34: =AVERAGE(D34:G34) | Y34: =AVERAGE(H34:K34) | Z34: =AVERAGE(L34:O34) | AA34: =AVERAGE(P34:S34) | AB34: =AVERAGE(T34:W34)
A35: Stage Ramp COGS % Revenue Max | B35: GPT-selected stage ramp contract | C35: 0 | D35: 0.69 | E35: 0.69 | F35: 0.69 | G35: 0.69 | H35: 0.69 | I35: 0.69 | J35: 0.69 | K35: 0.69 | L35: 0.69 | M35: 0.69 | N35: 0.69 | O35: 0.69 | P35: 0.69 | Q35: 0.69 | R35: 0.69 | S35: 0.69 | T35: 0.69 | U35: 0.69 | V35: 0.69 | W35: 0.69 | X35: =AVERAGE(D35:G35) | Y35: =AVERAGE(H35:K35) | Z35: =AVERAGE(L35:O35) | AA35: =AVERAGE(P35:S35) | AB35: =AVERAGE(T35:W35)
A36: Stage Ramp Marketing % Revenue Max | B36: GPT-selected stage ramp contract | C36: 0 | D36: 0.38 | E36: 0.38 | F36: 0.38 | G36: 0.38 | H36: 0.38 | I36: 0.38 | J36: 0.38 | K36: 0.38 | L36: 0.38 | M36: 0.38 | N36: 0.38 | O36: 0.38 | P36: 0.38 | Q36: 0.38 | R36: 0.38 | S36: 0.38 | T36: 0.38 | U36: 0.38 | V36: 0.38 | W36: 0.38 | X36: =AVERAGE(D36:G36) | Y36: =AVERAGE(H36:K36) | Z36: =AVERAGE(L36:O36) | AA36: =AVERAGE(P36:S36) | AB36: =AVERAGE(T36:W36)
A37: Stage Ramp R&D % Revenue Max | B37: GPT-selected stage ramp contract | C37: 0 | D37: 0.25 | E37: 0.25 | F37: 0.25 | G37: 0.25 | H37: 0.25 | I37: 0.25 | J37: 0.25 | K37: 0.25 | L37: 0.25 | M37: 0.25 | N37: 0.25 | O37: 0.25 | P37: 0.25 | Q37: 0.25 | R37: 0.25 | S37: 0.25 | T37: 0.25 | U37: 0.25 | V37: 0.25 | W37: 0.25 | X37: =AVERAGE(D37:G37) | Y37: =AVERAGE(H37:K37) | Z37: =AVERAGE(L37:O37) | AA37: =AVERAGE(P37:S37) | AB37: =AVERAGE(T37:W37)
A38: Stage Ramp G&A % Revenue Max | B38: GPT-selected stage ramp contract | C38: 0 | D38: 0.38 | E38: 0.38 | F38: 0.38 | G38: 0.38 | H38: 0.38 | I38: 0.38 | J38: 0.38 | K38: 0.38 | L38: 0.38 | M38: 0.38 | N38: 0.38 | O38: 0.38 | P38: 0.38 | Q38: 0.38 | R38: 0.38 | S38: 0.38 | T38: 0.38 | U38: 0.38 | V38: 0.38 | W38: 0.38 | X38: =AVERAGE(D38:G38) | Y38: =AVERAGE(H38:K38) | Z38: =AVERAGE(L38:O38) | AA38: =AVERAGE(P38:S38) | AB38: =AVERAGE(T38:W38)
A39: Stage Ramp Lease % Revenue Max | B39: GPT-selected stage ramp contract | C39: 0 | D39: 0.04 | E39: 0.04 | F39: 0.04 | G39: 0.04 | H39: 0.04 | I39: 0.04 | J39: 0.04 | K39: 0.04 | L39: 0.04 | M39: 0.04 | N39: 0.04 | O39: 0.04 | P39: 0.04 | Q39: 0.04 | R39: 0.04 | S39: 0.04 | T39: 0.04 | U39: 0.04 | V39: 0.04 | W39: 0.04 | X39: =AVERAGE(D39:G39) | Y39: =AVERAGE(H39:K39) | Z39: =AVERAGE(L39:O39) | AA39: =AVERAGE(P39:S39) | AB39: =AVERAGE(T39:W39)
A40: Stage Ramp Net Income Margin Floor | B40: GPT-selected stage ramp contract | C40: 0 | D40: 0 | E40: 0 | F40: 0 | G40: 0 | H40: 0.02 | I40: 0.02 | J40: 0.02 | K40: 0.02 | L40: 0.02 | M40: 0.02 | N40: 0.02 | O40: 0.02 | P40: 0.02 | Q40: 0.02 | R40: 0.02 | S40: 0.02 | T40: 0.02 | U40: 0.02 | V40: 0.02 | W40: 0.02 | X40: =AVERAGE(D40:G40) | Y40: =AVERAGE(H40:K40) | Z40: =AVERAGE(L40:O40) | AA40: =AVERAGE(P40:S40) | AB40: =AVERAGE(T40:W40)

Sheet Payroll Schedule
A1: Payroll Schedule
A2: OEWS-title, capacity/utilization-driven payroll source. Model Inputs links to Total Payroll.
C4: Stub | D4: Q1 | E4: Q2 | F4: Q3 | G4: Q4 | H4: Q5 | I4: Q6 | J4: Q7 | K4: Q8 | L4: Q9 | M4: Q10 | N4: Q11 | O4: Q12 | P4: Q13 | Q4: Q14 | R4: Q15 | S4: Q16 | T4: Q17 | U4: Q18 | V4: Q19 | W4: Q20 | X4: Y1 | Y4: Y2 | Z4: Y3 | AA4: Y4 | AB4: Y5
C5: 46162 | D5: 46295 | E5: 46387 | F5: 46477 | G5: 46568 | H5: 46660 | I5: 46752 | J5: 46843 | K5: 46934 | L5: 47026 | M5: 47118 | N5: 47208 | O5: 47299 | P5: 47391 | Q5: 47483 | R5: 47573 | S5: 47664 | T5: 47756 | U5: 47848 | V5: 47938 | W5: 48029 | X5: Annual | Y5: Annual | Z5: Annual | AA5: Annual | AB5: Annual
A6: Payroll Assumptions
A7: Capacity Labor Model | B7: labor_driven
A8: Labor Intensity Class | B8: high
A9: Wage Positioning Tier | B9: floor
A10: Wage Positioning Multiplier | B10: 1.05
A11: Capacity Units per Supporting FTE | B11: 654.71
A12: Target Payroll % of Revenue | B12: 0.4
A14: Quarter Summary
A15: Total Ending FTE | B15: Formula output from payroll detail | C15: =SUMIFS($G$27:$G$66,$A$27:$A$66,0) | D15: =SUMIFS($G$27:$G$66,$A$27:$A$66,1) | E15: =SUMIFS($G$27:$G$66,$A$27:$A$66,2) | F15: =SUMIFS($G$27:$G$66,$A$27:$A$66,3) | G15: =SUMIFS($G$27:$G$66,$A$27:$A$66,4) | H15: =SUMIFS($G$27:$G$66,$A$27:$A$66,5) | I15: =SUMIFS($G$27:$G$66,$A$27:$A$66,6) | J15: =SUMIFS($G$27:$G$66,$A$27:$A$66,7) | K15: =SUMIFS($G$27:$G$66,$A$27:$A$66,8) | L15: =SUMIFS($G$27:$G$66,$A$27:$A$66,9) | M15: =SUMIFS($G$27:$G$66,$A$27:$A$66,10) | N15: =SUMIFS($G$27:$G$66,$A$27:$A$66,11) | O15: =SUMIFS($G$27:$G$66,$A$27:$A$66,12) | P15: =SUMIFS($G$27:$G$66,$A$27:$A$66,13) | Q15: =SUMIFS($G$27:$G$66,$A$27:$A$66,14) | R15: =SUMIFS($G$27:$G$66,$A$27:$A$66,15) | S15: =SUMIFS($G$27:$G$66,$A$27:$A$66,16) | T15: =SUMIFS($G$27:$G$66,$A$27:$A$66,17) | U15: =SUMIFS($G$27:$G$66,$A$27:$A$66,18) | V15: =SUMIFS($G$27:$G$66,$A$27:$A$66,19) | W15: =SUMIFS($G$27:$G$66,$A$27:$A$66,20) | X15: =G15 | Y15: =K15 | Z15: =O15 | AA15: =S15 | AB15: =W15
A16: Total Average FTE | B16: Formula output from payroll detail | C16: =SUMIFS($H$27:$H$66,$A$27:$A$66,0) | D16: =SUMIFS($H$27:$H$66,$A$27:$A$66,1) | E16: =SUMIFS($H$27:$H$66,$A$27:$A$66,2) | F16: =SUMIFS($H$27:$H$66,$A$27:$A$66,3) | G16: =SUMIFS($H$27:$H$66,$A$27:$A$66,4) | H16: =SUMIFS($H$27:$H$66,$A$27:$A$66,5) | I16: =SUMIFS($H$27:$H$66,$A$27:$A$66,6) | J16: =SUMIFS($H$27:$H$66,$A$27:$A$66,7) | K16: =SUMIFS($H$27:$H$66,$A$27:$A$66,8) | L16: =SUMIFS($H$27:$H$66,$A$27:$A$66,9) | M16: =SUMIFS($H$27:$H$66,$A$27:$A$66,10) | N16: =SUMIFS($H$27:$H$66,$A$27:$A$66,11) | O16: =SUMIFS($H$27:$H$66,$A$27:$A$66,12) | P16: =SUMIFS($H$27:$H$66,$A$27:$A$66,13) | Q16: =SUMIFS($H$27:$H$66,$A$27:$A$66,14) | R16: =SUMIFS($H$27:$H$66,$A$27:$A$66,15) | S16: =SUMIFS($H$27:$H$66,$A$27:$A$66,16) | T16: =SUMIFS($H$27:$H$66,$A$27:$A$66,17) | U16: =SUMIFS($H$27:$H$66,$A$27:$A$66,18) | V16: =SUMIFS($H$27:$H$66,$A$27:$A$66,19) | W16: =SUMIFS($H$27:$H$66,$A$27:$A$66,20) | X16: =AVERAGE(D16:G16) | Y16: =AVERAGE(H16:K16) | Z16: =AVERAGE(L16:O16) | AA16: =AVERAGE(P16:S16) | AB16: =AVERAGE(T16:W16)
A17: Total Payroll | B17: Formula output from payroll detail | C17: =SUMIFS($M$27:$M$66,$A$27:$A$66,0) | D17: =SUMIFS($M$27:$M$66,$A$27:$A$66,1) | E17: =SUMIFS($M$27:$M$66,$A$27:$A$66,2) | F17: =SUMIFS($M$27:$M$66,$A$27:$A$66,3) | G17: =SUMIFS($M$27:$M$66,$A$27:$A$66,4) | H17: =SUMIFS($M$27:$M$66,$A$27:$A$66,5) | I17: =SUMIFS($M$27:$M$66,$A$27:$A$66,6) | J17: =SUMIFS($M$27:$M$66,$A$27:$A$66,7) | K17: =SUMIFS($M$27:$M$66,$A$27:$A$66,8) | L17: =SUMIFS($M$27:$M$66,$A$27:$A$66,9) | M17: =SUMIFS($M$27:$M$66,$A$27:$A$66,10) | N17: =SUMIFS($M$27:$M$66,$A$27:$A$66,11) | O17: =SUMIFS($M$27:$M$66,$A$27:$A$66,12) | P17: =SUMIFS($M$27:$M$66,$A$27:$A$66,13) | Q17: =SUMIFS($M$27:$M$66,$A$27:$A$66,14) | R17: =SUMIFS($M$27:$M$66,$A$27:$A$66,15) | S17: =SUMIFS($M$27:$M$66,$A$27:$A$66,16) | T17: =SUMIFS($M$27:$M$66,$A$27:$A$66,17) | U17: =SUMIFS($M$27:$M$66,$A$27:$A$66,18) | V17: =SUMIFS($M$27:$M$66,$A$27:$A$66,19) | W17: =SUMIFS($M$27:$M$66,$A$27:$A$66,20) | X17: =SUM(D17:G17) | Y17: =SUM(H17:K17) | Z17: =SUM(L17:O17) | AA17: =SUM(P17:S17) | AB17: =SUM(T17:W17)
A18: Total Revenue | B18: Linked from Revenue Drivers | C18: ='Revenue Drivers'!C26 | D18: ='Revenue Drivers'!D26 | E18: ='Revenue Drivers'!E26 | F18: ='Revenue Drivers'!F26 | G18: ='Revenue Drivers'!G26 | H18: ='Revenue Drivers'!H26 | I18: ='Revenue Drivers'!I26 | J18: ='Revenue Drivers'!J26 | ... W18: ='Revenue Drivers'!W26 | X18: =SUM(D18:G18) | Y18: =SUM(H18:K18) | Z18: =SUM(L18:O18) | AA18: =SUM(P18:S18) | AB18: =SUM(T18:W18)
A19: Total Capacity Units | B19: Linked from Revenue Drivers | C19: ='Revenue Drivers'!C25 | D19: ='Revenue Drivers'!D25 | E19: ='Revenue Drivers'!E25 | F19: ='Revenue Drivers'!F25 | G19: ='Revenue Drivers'!G25 | H19: ='Revenue Drivers'!H25 | I19: ='Revenue Drivers'!I25 | J19: ='Revenue Drivers'!J25 | ... W19: ='Revenue Drivers'!W25 | X19: =SUM(D19:G19) | Y19: =SUM(H19:K19) | Z19: =SUM(L19:O19) | AA19: =SUM(P19:S19) | AB19: =SUM(T19:W19)
A20: Revenue per Employee | B20: Python-built productivity formula | C20: =IFERROR(C18/C16,0) | D20: =IFERROR(D18/D16,0) | E20: =IFERROR(E18/E16,0) | F20: =IFERROR(F18/F16,0) | G20: =IFERROR(G18/G16,0) | H20: =IFERROR(H18/H16,0) | I20: =IFERROR(I18/I16,0) | J20: =IFERROR(J18/J16,0) | ... AB20: =IFERROR(AB18/AB16,0)
A21: Units per Employee | B21: Python-built productivity formula | C21: =IFERROR(C19/C16,0) | D21: =IFERROR(D19/D16,0) | E21: =IFERROR(E19/E16,0) | F21: =IFERROR(F19/F16,0) | G21: =IFERROR(G19/G16,0) | H21: =IFERROR(H19/H16,0) | I21: =IFERROR(I19/I16,0) | J21: =IFERROR(J19/J16,0) | ... AB21: =IFERROR(AB19/AB16,0)
A22: Payroll % of Revenue | B22: Python-built productivity formula | C22: =IFERROR(C17/C18,0) | D22: =IFERROR(D17/D18,0) | E22: =IFERROR(E17/E18,0) | F22: =IFERROR(F17/F18,0) | G22: =IFERROR(G17/G18,0) | H22: =IFERROR(H17/H18,0) | I22: =IFERROR(I17/I18,0) | J22: =IFERROR(J17/J18,0) | ... AB22: =IFERROR(AB17/AB18,0)
A25: Payroll Detail
A26: Quarter | B26: Staffing Class | C26: Title / Person | D26: OEWS Title | E26: Starting FTE | F26: Hires | G26: Ending FTE | H26: Average FTE | I26: Annual Wage | J26: Benefits % | K26: Wage Cost | L26: Taxes & Benefits | M26: Total Payroll | N26: Wage Source
A27: 1 | B27: key_person | C27: Founder and CEO | E27: 1 | F27: 0 | G27: =E27+F27 | H27: =(E27+G27)/2 | I27: 96750 | J27: 0.22 | K27: =H27*I27/4 | L27: =K27*J27 | M27: =K27+L27 | N27: oews_median
A28: 2 | B28: key_person | C28: Founder and CEO | E28: 1 | F28: 0 | G28: =E28+F28 | H28: =(E28+G28)/2 | I28: 96750 | J28: 0.22 | K28: =H28*I28/4 | L28: =K28*J28 | M28: =K28+L28 | N28: oews_median
A29: 3 | B29: key_person | C29: Founder and CEO | E29: 1 | F29: 0 | G29: =E29+F29 | H29: =(E29+G29)/2 | I29: 96750 | J29: 0.22 | K29: =H29*I29/4 | L29: =K29*J29 | M29: =K29+L29 | N29: oews_median
A30: 4 | B30: key_person | C30: Founder and CEO | E30: 1 | F30: 0 | G30: =E30+F30 | H30: =(E30+G30)/2 | I30: 96750 | J30: 0.22 | K30: =H30*I30/4 | L30: =K30*J30 | M30: =K30+L30 | N30: oews_median
A31: 5 | B31: key_person | C31: Founder and CEO | E31: 1 | F31: 0 | G31: =E31+F31 | H31: =(E31+G31)/2 | I31: 99652 | J31: 0.22 | K31: =H31*I31/4 | L31: =K31*J31 | M31: =K31+L31 | N31: oews_median
A32: 6 | B32: key_person | C32: Founder and CEO | E32: 1 | F32: 0 | G32: =E32+F32 | H32: =(E32+G32)/2 | I32: 99652 | J32: 0.22 | K32: =H32*I32/4 | L32: =K32*J32 | M32: =K32+L32 | N32: oews_median
A33: 7 | B33: key_person | C33: Founder and CEO | E33: 1 | F33: 0 | G33: =E33+F33 | H33: =(E33+G33)/2 | I33: 99652 | J33: 0.22 | K33: =H33*I33/4 | L33: =K33*J33 | M33: =K33+L33 | N33: oews_median
A34: 8 | B34: key_person | C34: Founder and CEO | E34: 1 | F34: 0 | G34: =E34+F34 | H34: =(E34+G34)/2 | I34: 99652 | J34: 0.22 | K34: =H34*I34/4 | L34: =K34*J34 | M34: =K34+L34 | N34: oews_median
A35: 9 | B35: key_person | C35: Founder and CEO | E35: 1 | F35: 0 | G35: =E35+F35 | H35: =(E35+G35)/2 | I35: 102642 | J35: 0.22 | K35: =H35*I35/4 | L35: =K35*J35 | M35: =K35+L35 | N35: oews_median
A36: 10 | B36: key_person | C36: Founder and CEO | E36: 1 | F36: 0 | G36: =E36+F36 | H36: =(E36+G36)/2 | I36: 102642 | J36: 0.22 | K36: =H36*I36/4 | L36: =K36*J36 | M36: =K36+L36 | N36: oews_median
A37: 11 | B37: key_person | C37: Founder and CEO | E37: 1 | F37: 0 | G37: =E37+F37 | H37: =(E37+G37)/2 | I37: 102642 | J37: 0.22 | K37: =H37*I37/4 | L37: =K37*J37 | M37: =K37+L37 | N37: oews_median
A38: 12 | B38: key_person | C38: Founder and CEO | E38: 1 | F38: 0 | G38: =E38+F38 | H38: =(E38+G38)/2 | I38: 102642 | J38: 0.22 | K38: =H38*I38/4 | L38: =K38*J38 | M38: =K38+L38 | N38: oews_median
... A46: 20 | B46: key_person | C46: Founder and CEO | E46: 1 | F46: 0 | G46: =E46+F46 | H46: =(E46+G46)/2 | I46: 108893 | J46: 0.22 | K46: =H46*I46/4 | L46: =K46*J46 | M46: =K46+L46 | N46: oews_median
A47: 1 | B47: supporting_staff | C47: Registered Nurses | D47: Registered Nurses | E47: 0 | F47: 0 | G47: =E47+F47 | H47: =(E47+G47)/2 | I47: 87392 | J47: 0.2 | K47: =H47*I47/4 | L47: =K47*J47 | M47: =K47+L47 | N47: oews_title_catalog:oews_median
A48: 2 | B48: supporting_staff | C48: Registered Nurses | D48: Registered Nurses | E48: 0 | F48: 0 | G48: =E48+F48 | H48: =(E48+G48)/2 | I48: 87392 | J48: 0.2 | K48: =H48*I48/4 | L48: =K48*J48 | M48: =K48+L48 | N48: oews_title_catalog:oews_median
A49: 3 | B49: supporting_staff | C49: Registered Nurses | D49: Registered Nurses | E49: 0 | F49: 0 | G49: =E49+F49 | H49: =(E49+G49)/2 | I49: 87392 | J49: 0.2 | K49: =H49*I49/4 | L49: =K49*J49 | M49: =K49+L49 | N49: oews_title_catalog:oews_median
A50: 4 | B50: supporting_staff | C50: Registered Nurses | D50: Registered Nurses | E50: 0 | F50: 0 | G50: =E50+F50 | H50: =(E50+G50)/2 | I50: 87392 | J50: 0.2 | K50: =H50*I50/4 | L50: =K50*J50 | M50: =K50+L50 | N50: oews_title_catalog:oews_median
A51: 5 | B51: supporting_staff | C51: Registered Nurses | D51: Registered Nurses | E51: 0 | F51: 0 | G51: =E51+F51 | H51: =(E51+G51)/2 | I51: 90013 | J51: 0.2 | K51: =H51*I51/4 | L51: =K51*J51 | M51: =K51+L51 | N51: oews_title_catalog:oews_median
A52: 6 | B52: supporting_staff | C52: Registered Nurses | D52: Registered Nurses | E52: 0 | F52: 0 | G52: =E52+F52 | H52: =(E52+G52)/2 | I52: 90013 | J52: 0.2 | K52: =H52*I52/4 | L52: =K52*J52 | M52: =K52+L52 | N52: oews_title_catalog:oews_median
A53: 7 | B53: supporting_staff | C53: Registered Nurses | D53: Registered Nurses | E53: 0 | F53: 0 | G53: =E53+F53 | H53: =(E53+G53)/2 | I53: 90013 | J53: 0.2 | K53: =H53*I53/4 | L53: =K53*J53 | M53: =K53+L53 | N53: oews_title_catalog:oews_median
A54: 8 | B54: supporting_staff | C54: Registered Nurses | D54: Registered Nurses | E54: 0 | F54: 0 | G54: =E54+F54 | H54: =(E54+G54)/2 | I54: 90013 | J54: 0.2 | K54: =H54*I54/4 | L54: =K54*J54 | M54: =K54+L54 | N54: oews_title_catalog:oews_median
A55: 9 | B55: supporting_staff | C55: Registered Nurses | D55: Registered Nurses | E55: 0 | F55: 0 | G55: =E55+F55 | H55: =(E55+G55)/2 | I55: 92714 | J55: 0.2 | K55: =H55*I55/4 | L55: =K55*J55 | M55: =K55+L55 | N55: oews_title_catalog:oews_median
A56: 10 | B56: supporting_staff | C56: Registered Nurses | D56: Registered Nurses | E56: 0 | F56: 0 | G56: =E56+F56 | H56: =(E56+G56)/2 | I56: 92714 | J56: 0.2 | K56: =H56*I56/4 | L56: =K56*J56 | M56: =K56+L56 | N56: oews_title_catalog:oews_median
A57: 11 | B57: supporting_staff | C57: Registered Nurses | D57: Registered Nurses | E57: 0 | F57: 0 | G57: =E57+F57 | H57: =(E57+G57)/2 | I57: 92714 | J57: 0.2 | K57: =H57*I57/4 | L57: =K57*J57 | M57: =K57+L57 | N57: oews_title_catalog:oews_median
A58: 12 | B58: supporting_staff | C58: Registered Nurses | D58: Registered Nurses | E58: 0 | F58: 0 | G58: =E58+F58 | H58: =(E58+G58)/2 | I58: 92714 | J58: 0.2 | K58: =H58*I58/4 | L58: =K58*J58 | M58: =K58+L58 | N58: oews_title_catalog:oews_median
... A66: 20 | B66: supporting_staff | C66: Registered Nurses | D66: Registered Nurses | E66: 0 | F66: 0.1 | G66: =E66+F66 | H66: =(E66+G66)/2 | I66: 98360 | J66: 0.2 | K66: =H66*I66/4 | L66: =K66*J66 | M66: =K66+L66 | N66: oews_title_catalog:oews_median

Sheet Debt Schedule
A1: Debt Schedule
A2: Debt, interest, and capital lease mechanics. Model Inputs links to calculated outputs.
C4: Stub | D4: Q1 | E4: Q2 | F4: Q3 | G4: Q4 | H4: Q5 | I4: Q6 | J4: Q7 | K4: Q8 | L4: Q9 | M4: Q10 | N4: Q11 | O4: Q12 | P4: Q13 | Q4: Q14 | R4: Q15 | S4: Q16 | T4: Q17 | U4: Q18 | V4: Q19 | W4: Q20 | X4: Y1 | Y4: Y2 | Z4: Y3 | AA4: Y4 | AB4: Y5
C5: 46162 | D5: 46295 | E5: 46387 | F5: 46477 | G5: 46568 | H5: 46660 | I5: 46752 | J5: 46843 | K5: 46934 | L5: 47026 | M5: 47118 | N5: 47208 | O5: 47299 | P5: 47391 | Q5: 47483 | R5: 47573 | S5: 47664 | T5: 47756 | U5: 47848 | V5: 47938 | W5: 48029 | X5: Annual | Y5: Annual | Z5: Annual | AA5: Annual | AB5: Annual
A6: Debt Amortization
A7: Opening Debt | B7: Calculated | C7: 0 | D7: =C11 | E7: =D11 | F7: =E11 | G7: =F11 | H7: =G11 | I7: =H11 | J7: =I11 | K7: =J11 | ... W7: =V11 | X7: =G7 | Y7: =K7 | Z7: =O7 | AA7: =S7 | AB7: =W7
A8: Debt Issuance | B8: Source borrowing | C8: 0 | D8: 0 | E8: 0 | F8: 0 | G8: 0 | H8: 0 | I8: 0 | J8: 0 | K8: 0 | L8: 0 | M8: 0 | N8: 0 | O8: 0 | P8: 0 | Q8: 0 | R8: 0 | S8: 0 | T8: 0 | U8: 0 | V8: 0 | W8: 0 | X8: =SUM(D8:G8) | Y8: =SUM(H8:K8) | Z8: =SUM(L8:O8) | AA8: =SUM(P8:S8) | AB8: =SUM(T8:W8)
A9: Requested Debt Repayment | B9: Source scheduled repayment | C9: 0 | D9: 0 | E9: 0 | F9: 0 | G9: 0 | H9: 0 | I9: 0 | J9: 0 | K9: 0 | L9: 0 | M9: 0 | N9: 0 | O9: 0 | P9: 0 | Q9: 0 | R9: 0 | S9: 0 | T9: 0 | U9: 0 | V9: 0 | W9: 0 | X9: =SUM(D9:G9) | Y9: =SUM(H9:K9) | Z9: =SUM(L9:O9) | AA9: =SUM(P9:S9) | AB9: =SUM(T9:W9)
A10: Actual Debt Repayment | B10: MIN(requested repayment, opening debt + issuance) | C10: =MIN(C9,C7+C8) | D10: =MIN(D9,D7+D8) | E10: =MIN(E9,E7+E8) | F10: =MIN(F9,F7+F8) | G10: =MIN(G9,G7+G8) | H10: =MIN(H9,H7+H8) | I10: =MIN(I9,I7+I8) | J10: =MIN(J9,J7+J8) | ... W10: =MIN(W9,W7+W8) | X10: =SUM(D10:G10) | Y10: =SUM(H10:K10) | Z10: =SUM(L10:O10) | AA10: =SUM(P10:S10) | AB10: =SUM(T10:W10)
A11: Closing Debt | B11: Calculated | C11: =MAX(0,C7+C8-C10) | D11: =MAX(0,D7+D8-D10) | E11: =MAX(0,E7+E8-E10) | F11: =MAX(0,F7+F8-F10) | G11: =MAX(0,G7+G8-G10) | H11: =MAX(0,H7+H8-H10) | I11: =MAX(0,I7+I8-I10) | J11: =MAX(0,J7+J8-J10) | ... W11: =MAX(0,W7+W8-W10) | X11: =G11 | Y11: =K11 | Z11: =O11 | AA11: =S11 | AB11: =W11
A12: Interest Rate | B12: Source rate | C12: 0 | D12: 0.024375 | E12: 0.024375 | F12: 0.024375 | G12: 0.024375 | H12: 0.024375 | I12: 0.024375 | J12: 0.024375 | K12: 0.024375 | L12: 0.024375 | M12: 0.024375 | N12: 0.024375 | O12: 0.024375 | P12: 0.024375 | Q12: 0.024375 | R12: 0.024375 | S12: 0.024375 | T12: 0.024375 | U12: 0.024375 | V12: 0.024375 | W12: 0.024375 | X12: =SUM(D12:G12) | Y12: =SUM(H12:K12) | Z12: =SUM(L12:O12) | AA12: =SUM(P12:S12) | AB12: =SUM(T12:W12)
A13: Interest Expense | B13: Average debt balance x rate | C13: =((C7+C11)/2)*C12 | D13: =((D7+D11)/2)*D12 | E13: =((E7+E11)/2)*E12 | F13: =((F7+F11)/2)*F12 | G13: =((G7+G11)/2)*G12 | H13: =((H7+H11)/2)*H12 | I13: =((I7+I11)/2)*I12 | J13: =((J7+J11)/2)*J12 | ... W13: =((W7+W11)/2)*W12 | X13: =SUM(D13:G13) | Y13: =SUM(H13:K13) | Z13: =SUM(L13:O13) | AA13: =SUM(P13:S13) | AB13: =SUM(T13:W13)
A14: Total Debt Service | B14: Interest + actual repayment | C14: =C13+C10 | D14: =D13+D10 | E14: =E13+E10 | F14: =F13+F10 | G14: =G13+G10 | H14: =H13+H10 | I14: =I13+I10 | J14: =J13+J10 | ... W14: =W13+W10 | X14: =SUM(D14:G14) | Y14: =SUM(H14:K14) | Z14: =SUM(L14:O14) | AA14: =SUM(P14:S14) | AB14: =SUM(T14:W14)
A17: Capital Lease Schedule
A18: Lease Opening Balance | B18: Capital leases | C18: 0 | D18: =C23 | E18: =D23 | F18: =E23 | G18: =F23 | H18: =G23 | I18: =H23 | J18: =I23 | K18: =J23 | ... W18: =V23 | X18: =G18 | Y18: =K18 | Z18: =O18 | AA18: =S18 | AB18: =W18
A19: Requested Lease Principal Repayments | B19: Capital leases | C19: 0 | D19: 0 | E19: 0 | F19: 0 | G19: 0 | H19: 0 | I19: 0 | J19: 0 | K19: 0 | L19: 0 | M19: 0 | N19: 0 | O19: 0 | P19: 0 | Q19: 0 | R19: 0 | S19: 0 | T19: 0 | U19: 0 | V19: 0 | W19: 0 | X19: =SUM(D19:G19) | Y19: =SUM(H19:K19) | Z19: =SUM(L19:O19) | AA19: =SUM(P19:S19) | AB19: =SUM(T19:W19)
A20: Lease Principal Repayments | B20: Capital leases | C20: =MIN(C19,C18+C21) | D20: =MIN(D19,D18+D21) | E20: =MIN(E19,E18+E21) | F20: =MIN(F19,F18+F21) | G20: =MIN(G19,G18+G21) | H20: =MIN(H19,H18+H21) | I20: =MIN(I19,I18+I21) | J20: =MIN(J19,J18+J21) | ... W20: =MIN(W19,W18+W21) | X20: =SUM(D20:G20) | Y20: =SUM(H20:K20) | Z20: =SUM(L20:O20) | AA20: =SUM(P20:S20) | AB20: =SUM(T20:W20)
A21: Lease Net Additions | B21: Capital leases | C21: 0 | D21: 0 | E21: 0 | F21: 0 | G21: 0 | H21: 0 | I21: 0 | J21: 0 | K21: 0 | L21: 0 | M21: 0 | N21: 0 | O21: 0 | P21: 0 | Q21: 0 | R21: 0 | S21: 0 | T21: 0 | U21: 0 | V21: 0 | W21: 0 | X21: =SUM(D21:G21) | Y21: =SUM(H21:K21) | Z21: =SUM(L21:O21) | AA21: =SUM(P21:S21) | AB21: =SUM(T21:W21)
A22: Lease Interest Expense | B22: Capital leases | C22: 0 | D22: =D18*D12 | E22: =E18*E12 | F22: =F18*F12 | G22: =G18*G12 | H22: =H18*H12 | I22: =I18*I12 | J22: =J18*J12 | K22: =K18*K12 | ... W22: =W18*W12 | X22: =SUM(D22:G22) | Y22: =SUM(H22:K22) | Z22: =SUM(L22:O22) | AA22: =SUM(P22:S22) | AB22: =SUM(T22:W22)
A23: Lease Closing Balance | B23: Capital leases | C23: =MAX(0,C18+C21-C20) | D23: =MAX(0,D18+D21-D20) | E23: =MAX(0,E18+E21-E20) | F23: =MAX(0,F18+F21-F20) | G23: =MAX(0,G18+G21-G20) | H23: =MAX(0,H18+H21-H20) | I23: =MAX(0,I18+I21-I20) | J23: =MAX(0,J18+J21-J20) | ... W23: =MAX(0,W18+W21-W20) | X23: =G23 | Y23: =K23 | Z23: =O23 | AA23: =S23 | AB23: =W23
A24: Right-of-Use Asset Opening | B24: Capital leases | C24: 0 | D24: =C26 | E24: =D26 | F24: =E26 | G24: =F26 | H24: =G26 | I24: =H26 | J24: =I26 | K24: =J26 | ... W24: =V26 | X24: =G24 | Y24: =K24 | Z24: =O24 | AA24: =S24 | AB24: =W24
A25: Lease Asset Depreciation | B25: Capital leases | C25: 0 | D25: =MIN((C18/20),D24) | E25: =MIN((C18/20),E24) | F25: =MIN((C18/20),F24) | G25: =MIN((C18/20),G24) | H25: =MIN((C18/20),H24) | I25: =MIN((C18/20),I24) | J25: =MIN((C18/20),J24) | K25: =MIN((C18/20),K24) | L25: =MIN((C18/20),L24) | M25: =MIN((C18/20),M24) | N25: =MIN((C18/20),N24) | O25: =MIN((C18/20),O24) | P25: =MIN((C18/20),P24) | Q25: =MIN((C18/20),Q24) | R25: =MIN((C18/20),R24) | S25: =MIN((C18/20),S24) | T25: =MIN((C18/20),T24) | U25: =MIN((C18/20),U24) | V25: =MIN((C18/20),V24) | W25: =MIN((C18/20),W24) | X25: =SUM(D25:G25) | Y25: =SUM(H25:K25) | Z25: =SUM(L25:O25) | AA25: =SUM(P25:S25) | AB25: =SUM(T25:W25)
A26: Right-of-Use Asset Closing | B26: Capital leases | C26: =MAX(0,C24-C25) | D26: =MAX(0,D24-D25) | E26: =MAX(0,E24-E25) | F26: =MAX(0,F24-F25) | G26: =MAX(0,G24-G25) | H26: =MAX(0,H24-H25) | I26: =MAX(0,I24-I25) | J26: =MAX(0,J24-J25) | ... W26: =MAX(0,W24-W25) | X26: =G26 | Y26: =K26 | Z26: =O26 | AA26: =S26 | AB26: =W26

Sheet CapEx Depreciation
A1: CapEx & Depreciation Schedule
A2: Capital expenditure and depreciation mechanics. Model Inputs links to calculated outputs.
C4: Stub | D4: Q1 | E4: Q2 | F4: Q3 | G4: Q4 | H4: Q5 | I4: Q6 | J4: Q7 | K4: Q8 | L4: Q9 | M4: Q10 | N4: Q11 | O4: Q12 | P4: Q13 | Q4: Q14 | R4: Q15 | S4: Q16 | T4: Q17 | U4: Q18 | V4: Q19 | W4: Q20 | X4: Y1 | Y4: Y2 | Z4: Y3 | AA4: Y4 | AB4: Y5
C5: 46162 | D5: 46295 | E5: 46387 | F5: 46477 | G5: 46568 | H5: 46660 | I5: 46752 | J5: 46843 | K5: 46934 | L5: 47026 | M5: 47118 | N5: 47208 | O5: 47299 | P5: 47391 | Q5: 47483 | R5: 47573 | S5: 47664 | T5: 47756 | U5: 47848 | V5: 47938 | W5: 48029 | X5: Annual | Y5: Annual | Z5: Annual | AA5: Annual | AB5: Annual
A6: PPE and Depreciation
A7: Opening PPE | B7: Calculated | C7: 12000 | D7: =C12 | E7: =D12 | F7: =E12 | G7: =F12 | H7: =G12 | I7: =H12 | J7: =I12 | K7: =J12 | ... W7: =V12 | X7: =G7 | Y7: =K7 | Z7: =O7 | AA7: =S7 | AB7: =W7
A8: Capital Expenditures | B8: Schedule source | C8: 0 | D8: 70.98 | E8: 71.378837 | F8: 71.758929 | G8: 72.120092 | H8: 72.462013 | I8: 72.784541 | J8: 73.087471 | K8: 73.370538 | L8: 73.633572 | M8: 73.876415 | N8: 74.098857 | O8: 74.300702 | P8: 74.481773 | Q8: 74.641835 | R8: 74.780818 | S8: 74.898448 | T8: 74.994692 | U8: 75.069312 | V8: 75.122161 | W8: 675.1531 | X8: =SUM(D8:G8) | Y8: =SUM(H8:K8) | Z8: =SUM(L8:O8) | AA8: =SUM(P8:S8) | AB8: =SUM(T8:W8)
A9: Lease Additions | B9: Schedule source | C9: 0 | D9: ='Debt Schedule'!D21 | E9: ='Debt Schedule'!E21 | F9: ='Debt Schedule'!F21 | G9: ='Debt Schedule'!G21 | H9: ='Debt Schedule'!H21 | I9: ='Debt Schedule'!I21 | J9: ='Debt Schedule'!J21 | K9: ='Debt Schedule'!K21 | ... W9: ='Debt Schedule'!W21 | X9: =SUM(D9:G9) | Y9: =SUM(H9:K9) | Z9: =SUM(L9:O9) | AA9: =SUM(P9:S9) | AB9: =SUM(T9:W9)
A10: Depreciation Rate | B10: Schedule source | C10: 0 | D10: 0.000296 | E10: 0.00059 | F10: 0.000882 | G10: 0.001174 | H10: 0.001464 | I10: 0.001753 | J10: 0.002042 | K10: 0.00233 | L10: 0.002617 | M10: 0.002904 | N10: 0.003191 | O10: 0.003478 | P10: 0.003766 | Q10: 0.004053 | R10: 0.004342 | S10: 0.00463 | T10: 0.00492 | U10: 0.005211 | V10: 0.005503 | W10: 0.008158 | X10: =SUM(D10:G10) | Y10: =SUM(H10:K10) | Z10: =SUM(L10:O10) | AA10: =SUM(P10:S10) | AB10: =SUM(T10:W10)
A11: Depreciation Expense | B11: Calculated | C11: =MIN(C7*C10,C7) | D11: =MIN(D7*D10,D7) | E11: =MIN(E7*E10,E7) | F11: =MIN(F7*F10,F7) | G11: =MIN(G7*G10,G7) | H11: =MIN(H7*H10,H7) | I11: =MIN(I7*I10,I7) | J11: =MIN(J7*J10,J7) | ... W11: =MIN(W7*W10,W7) | X11: =SUM(D11:G11) | Y11: =SUM(H11:K11) | Z11: =SUM(L11:O11) | AA11: =SUM(P11:S11) | AB11: =SUM(T11:W11)
A12: Closing PPE | B12: Calculated | C12: =MAX(0,C7+C8+C9-C11) | D12: =MAX(0,D7+D8+D9-D11) | E12: =MAX(0,E7+E8+E9-E11) | F12: =MAX(0,F7+F8+F9-F11) | G12: =MAX(0,G7+G8+G9-G11) | H12: =MAX(0,H7+H8+H9-H11) | I12: =MAX(0,I7+I8+I9-I11) | J12: =MAX(0,J7+J8+J9-J11) | ... W12: =MAX(0,W7+W8+W9-W11) | X12: =G12 | Y12: =K12 | Z12: =O12 | AA12: =S12 | AB12: =W12
A13: Opening Accumulated Depreciation | B13: Calculated | C13: 0 | D13: =C14 | E13: =D14 | F13: =E14 | G13: =F14 | H13: =G14 | I13: =H14 | J13: =I14 | K13: =J14 | ... W13: =V14 | X13: =G13 | Y13: =K13 | Z13: =O13 | AA13: =S13 | AB13: =W13
A14: Accumulated Depreciation | B14: Calculated | C14: =C13-C11 | D14: =D13-D11 | E14: =E13-E11 | F14: =F13-F11 | G14: =G13-G11 | H14: =H13-H11 | I14: =I13-I11 | J14: =J13-J11 | ... W14: =W13-W11 | X14: =G14 | Y14: =K14 | Z14: =O14 | AA14: =S14 | AB14: =W14

Sheet Working Capital
A1: Working Capital Schedule
A2: Working-capital drivers. Model Inputs links to these source rows.
C4: Stub | D4: Q1 | E4: Q2 | F4: Q3 | G4: Q4 | H4: Q5 | I4: Q6 | J4: Q7 | K4: Q8 | L4: Q9 | M4: Q10 | N4: Q11 | O4: Q12 | P4: Q13 | Q4: Q14 | R4: Q15 | S4: Q16 | T4: Q17 | U4: Q18 | V4: Q19 | W4: Q20 | X4: Y1 | Y4: Y2 | Z4: Y3 | AA4: Y4 | AB4: Y5
C5: 46162 | D5: 46295 | E5: 46387 | F5: 46477 | G5: 46568 | H5: 46660 | I5: 46752 | J5: 46843 | K5: 46934 | L5: 47026 | M5: 47118 | N5: 47208 | O5: 47299 | P5: 47391 | Q5: 47483 | R5: 47573 | S5: 47664 | T5: 47756 | U5: 47848 | V5: 47938 | W5: 48029 | X5: Annual | Y5: Annual | Z5: Annual | AA5: Annual | AB5: Annual
A6: Working Capital Drivers
A7: Accounts Receivable Days | B7: Working capital driver | C7: 0 | D7: 15 | E7: 15 | F7: 15 | G7: 15 | H7: 15 | I7: 15 | J7: 15 | K7: 15 | L7: 15 | M7: 15 | N7: 15 | O7: 15 | P7: 15 | Q7: 15 | R7: 15 | S7: 15 | T7: 15 | U7: 15 | V7: 15 | W7: 15
A8: Inventory Days | B8: Working capital driver | C8: 0 | D8: 10 | E8: 10 | F8: 10 | G8: 10 | H8: 10 | I8: 10 | J8: 10 | K8: 10 | L8: 10 | M8: 10 | N8: 10 | O8: 10 | P8: 10 | Q8: 10 | R8: 10 | S8: 10 | T8: 10 | U8: 10 | V8: 10 | W8: 10
A9: Accounts Payable Days | B9: Working capital driver | C9: 0 | D9: 30 | E9: 30 | F9: 30 | G9: 30 | H9: 30 | I9: 30 | J9: 30 | K9: 30 | L9: 30 | M9: 30 | N9: 30 | O9: 30 | P9: 30 | Q9: 30 | R9: 30 | S9: 30 | T9: 30 | U9: 30 | V9: 30 | W9: 30
A10: Prepaid Expenses (% of Revenue) | B10: Working capital driver | C10: 0 | D10: 0.05 | E10: 0.05 | F10: 0.05 | G10: 0.05 | H10: 0.05 | I10: 0.05 | J10: 0.05 | K10: 0.05 | L10: 0.05 | M10: 0.05 | N10: 0.05 | O10: 0.05 | P10: 0.05 | Q10: 0.05 | R10: 0.05 | S10: 0.05 | T10: 0.05 | U10: 0.05 | V10: 0.05 | W10: 0.05
A11: Deferred Revenue (% of Revenue) | B11: Working capital driver | C11: 0 | D11: 0 | E11: 0 | F11: 0 | G11: 0 | H11: 0 | I11: 0 | J11: 0 | K11: 0 | L11: 0 | M11: 0 | N11: 0 | O11: 0 | P11: 0 | Q11: 0 | R11: 0 | S11: 0 | T11: 0 | U11: 0 | V11: 0 | W11: 0
A12: Short Term Debt (% of LTD) | B12: Working capital driver | C12: 0 | D12: 0 | E12: 0 | F12: 0 | G12: 0 | H12: 0 | I12: 0 | J12: 0 | K12: 0 | L12: 0 | M12: 0 | N12: 0 | O12: 0 | P12: 0 | Q12: 0 | R12: 0 | S12: 0 | T12: 0 | U12: 0 | V12: 0 | W12: 0
A14: Opening Working Capital Seeds
A15: Cash Opening Balance | B15: Opening balance seed | C15: 10000 | D15: 0 | E15: 0 | F15: 0 | G15: 0 | H15: 0 | I15: 0 | J15: 0 | K15: 0 | L15: 0 | M15: 0 | N15: 0 | O15: 0 | P15: 0 | Q15: 0 | R15: 0 | S15: 0 | T15: 0 | U15: 0 | V15: 0 | W15: 0
A16: Accounts Receivable Opening Balance | B16: Opening balance seed | C16: 0 | D16: 0 | E16: 0 | F16: 0 | G16: 0 | H16: 0 | I16: 0 | J16: 0 | K16: 0 | L16: 0 | M16: 0 | N16: 0 | O16: 0 | P16: 0 | Q16: 0 | R16: 0 | S16: 0 | T16: 0 | U16: 0 | V16: 0 | W16: 0
A17: Inventory Opening Balance | B17: Opening balance seed | C17: 3000 | D17: 0 | E17: 0 | F17: 0 | G17: 0 | H17: 0 | I17: 0 | J17: 0 | K17: 0 | L17: 0 | M17: 0 | N17: 0 | O17: 0 | P17: 0 | Q17: 0 | R17: 0 | S17: 0 | T17: 0 | U17: 0 | V17: 0 | W17: 0
A18: Accounts Payable Opening Balance | B18: Opening balance seed | C18: 1200 | D18: 0 | E18: 0 | F18: 0 | G18: 0 | H18: 0 | I18: 0 | J18: 0 | K18: 0 | L18: 0 | M18: 0 | N18: 0 | O18: 0 | P18: 0 | Q18: 0 | R18: 0 | S18: 0 | T18: 0 | U18: 0 | V18: 0 | W18: 0
A19: Short Term Debt Opening Balance | B19: Opening balance seed | C19: 0 | D19: 0 | E19: 0 | F19: 0 | G19: 0 | H19: 0 | I19: 0 | J19: 0 | K19: 0 | L19: 0 | M19: 0 | N19: 0 | O19: 0 | P19: 0 | Q19: 0 | R19: 0 | S19: 0 | T19: 0 | U19: 0 | V19: 0 | W19: 0

Sheet Cash Equity Schedule
A1: Cash & Equity Schedule
A2: Equity, distributions, lease/rent, and opening cash seeds. Model Inputs links to these rows.
C4: Stub | D4: Q1 | E4: Q2 | F4: Q3 | G4: Q4 | H4: Q5 | I4: Q6 | J4: Q7 | K4: Q8 | L4: Q9 | M4: Q10 | N4: Q11 | O4: Q12 | P4: Q13 | Q4: Q14 | R4: Q15 | S4: Q16 | T4: Q17 | U4: Q18 | V4: Q19 | W4: Q20 | X4: Y1 | Y4: Y2 | Z4: Y3 | AA4: Y4 | AB4: Y5
C5: 46162 | D5: 46295 | E5: 46387 | F5: 46477 | G5: 46568 | H5: 46660 | I5: 46752 | J5: 46843 | K5: 46934 | L5: 47026 | M5: 47118 | N5: 47208 | O5: 47299 | P5: 47391 | Q5: 47483 | R5: 47573 | S5: 47664 | T5: 47756 | U5: 47848 | V5: 47938 | W5: 48029 | X5: Annual | Y5: Annual | Z5: Annual | AA5: Annual | AB5: Annual
A6: Equity and Distributions
A7: Owner's Capital | B7: Equity / distribution input | C7: 20000 | D7: 84858 | E7: 114346 | F7: 141217 | G7: 165562 | H7: 188001 | I7: 207086 | J7: 222769 | K7: 234867 | L7: 244170 | M7: 249196 | N7: 250013 | O7: 250013 | P7: 250013 | Q7: 250013 | R7: 250013 | S7: 250013 | T7: 250013 | U7: 250013 | V7: 250013 | W7: 250013
A8: Other Equity | B8: Equity / distribution input | C8: 0 | D8: 0 | E8: 0 | F8: 0 | G8: 0 | H8: 0 | I8: 0 | J8: 0 | K8: 0 | L8: 0 | M8: 0 | N8: 0 | O8: 0 | P8: 0 | Q8: 0 | R8: 0 | S8: 0 | T8: 0 | U8: 0 | V8: 0 | W8: 0
A9: Distributions | B9: Equity / distribution input | C9: 0 | D9: 0 | E9: 0 | F9: 0 | G9: 0 | H9: 0 | I9: 0 | J9: 0 | K9: 0 | L9: 0 | M9: 0 | N9: 0 | O9: 0 | P9: 0 | Q9: 0 | R9: 0 | S9: 135 | T9: 6481 | U9: 8197 | V9: 9534 | W9: 7611
A11: Operating Fixed Cash Items
A12: Lease | B12: Operating lease/rent input | C12: 3600 | D12: 3600 | E12: 3600 | F12: 3600 | G12: 3600 | H12: 3600 | I12: 3600 | J12: 3600 | K12: 3600 | L12: 3600 | M12: 3600 | N12: 3600 | O12: 3600 | P12: 3600 | Q12: 3600 | R12: 3600 | S12: 3600 | T12: 3600 | U12: 3600 | V12: 3600 | W12: 3600

Sheet Model Inputs
A1: Model Inputs
A2: Formula-driven bridge from schedules into FINMO. FINMO references this sheet only.
C4: Stub | D4: Q1 | E4: Q2 | F4: Q3 | G4: Q4 | H4: Q5 | I4: Q6 | J4: Q7 | K4: Q8 | L4: Q9 | M4: Q10 | N4: Q11 | O4: Q12 | P4: Q13 | Q4: Q14 | R4: Q15 | S4: Q16 | T4: Q17 | U4: Q18 | V4: Q19 | W4: Q20 | X4: Y1 | Y4: Y2 | Z4: Y3 | AA4: Y4 | AB4: Y5
C5: 46162 | D5: 46295 | E5: 46387 | F5: 46477 | G5: 46568 | H5: 46660 | I5: 46752 | J5: 46843 | K5: 46934 | L5: 47026 | M5: 47118 | N5: 47208 | O5: 47299 | P5: 47391 | Q5: 47483 | R5: 47573 | S5: 47664 | T5: 47756 | U5: 47848 | V5: 47938 | W5: 48029 | X5: Annual | Y5: Annual | Z5: Annual | AA5: Annual | AB5: Annual
A6: Income Statement Inputs
A7: Primary line of business / Individual IV session - Capacity | B7: Revenue Drivers schedule | C7: ='Revenue Drivers'!C8 | D7: ='Revenue Drivers'!D8 | E7: ='Revenue Drivers'!E8 | F7: ='Revenue Drivers'!F8 | G7: ='Revenue Drivers'!G8 | H7: ='Revenue Drivers'!H8 | I7: ='Revenue Drivers'!I8 | J7: ='Revenue Drivers'!J8 | ... W7: ='Revenue Drivers'!W8 | X7: =SUM(D7:G7) | Y7: =SUM(H7:K7) | Z7: =SUM(L7:O7) | AA7: =SUM(P7:S7) | AB7: =SUM(T7:W7)
A8: Primary line of business / Individual IV session - Unit Price | B8: Revenue Drivers schedule | C8: ='Revenue Drivers'!C9 | D8: ='Revenue Drivers'!D9 | E8: ='Revenue Drivers'!E9 | F8: ='Revenue Drivers'!F9 | G8: ='Revenue Drivers'!G9 | H8: ='Revenue Drivers'!H9 | I8: ='Revenue Drivers'!I9 | J8: ='Revenue Drivers'!J9 | ... W8: ='Revenue Drivers'!W9 | X8: =SUM(D8:G8) | Y8: =SUM(H8:K8) | Z8: =SUM(L8:O8) | AA8: =SUM(P8:S8) | AB8: =SUM(T8:W8)
A9: Primary line of business / Individual IV session - Utilization | B9: Revenue Drivers schedule | C9: ='Revenue Drivers'!C10 | D9: ='Revenue Drivers'!D10 | E9: ='Revenue Drivers'!E10 | F9: ='Revenue Drivers'!F10 | G9: ='Revenue Drivers'!G10 | H9: ='Revenue Drivers'!H10 | I9: ='Revenue Drivers'!I10 | J9: ='Revenue Drivers'!J10 | ... W9: ='Revenue Drivers'!W10 | X9: =SUM(D9:G9) | Y9: =SUM(H9:K9) | Z9: =SUM(L9:O9) | AA9: =SUM(P9:S9) | AB9: =SUM(T9:W9)
A10: Primary line of business / Individual IV session - Revenue | B10: Revenue Drivers schedule | C10: ='Revenue Drivers'!C11 | D10: ='Revenue Drivers'!D11 | E10: ='Revenue Drivers'!E11 | F10: ='Revenue Drivers'!F11 | G10: ='Revenue Drivers'!G11 | H10: ='Revenue Drivers'!H11 | I10: ='Revenue Drivers'!I11 | J10: ='Revenue Drivers'!J11 | ... W10: ='Revenue Drivers'!W11 | X10: =SUM(D10:G10) | Y10: =SUM(H10:K10) | Z10: =SUM(L10:O10) | AA10: =SUM(P10:S10) | AB10: =SUM(T10:W10)
A11: Primary line of business / Monthly IV membership - Capacity | B11: Revenue Drivers schedule | C11: ='Revenue Drivers'!C14 | D11: ='Revenue Drivers'!D14 | E11: ='Revenue Drivers'!E14 | F11: ='Revenue Drivers'!F14 | G11: ='Revenue Drivers'!G14 | H11: ='Revenue Drivers'!H14 | I11: ='Revenue Drivers'!I14 | J11: ='Revenue Drivers'!J14 | ... W11: ='Revenue Drivers'!W14 | X11: =SUM(D11:G11) | Y11: =SUM(H11:K11) | Z11: =SUM(L11:O11) | AA11: =SUM(P11:S11) | AB11: =SUM(T11:W11)
A12: Primary line of business / Monthly IV membership - Unit Price | B12: Revenue Drivers schedule | C12: ='Revenue Drivers'!C15 | D12: ='Revenue Drivers'!D15 | E12: ='Revenue Drivers'!E15 | F12: ='Revenue Drivers'!F15 | G12: ='Revenue Drivers'!G15 | H12: ='Revenue Drivers'!H15 | I12: ='Revenue Drivers'!I15 | J12: ='Revenue Drivers'!J15 | ... W12: ='Revenue Drivers'!W15 | X12: =SUM(D12:G12) | Y12: =SUM(H12:K12) | Z12: =SUM(L12:O12) | AA12: =SUM(P12:S12) | AB12: =SUM(T12:W12)
A13: Primary line of business / Monthly IV membership - Utilization | B13: Revenue Drivers schedule | C13: ='Revenue Drivers'!C16 | D13: ='Revenue Drivers'!D16 | E13: ='Revenue Drivers'!E16 | F13: ='Revenue Drivers'!F16 | G13: ='Revenue Drivers'!G16 | H13: ='Revenue Drivers'!H16 | I13: ='Revenue Drivers'!I16 | J13: ='Revenue Drivers'!J16 | ... W13: ='Revenue Drivers'!W16 | X13: =SUM(D13:G13) | Y13: =SUM(H13:K13) | Z13: =SUM(L13:O13) | AA13: =SUM(P13:S13) | AB13: =SUM(T13:W13)
A14: Primary line of business / Monthly IV membership - Revenue | B14: Revenue Drivers schedule | C14: ='Revenue Drivers'!C17 | D14: ='Revenue Drivers'!D17 | E14: ='Revenue Drivers'!E17 | F14: ='Revenue Drivers'!F17 | G14: ='Revenue Drivers'!G17 | H14: ='Revenue Drivers'!H17 | I14: ='Revenue Drivers'!I17 | J14: ='Revenue Drivers'!J17 | ... W14: ='Revenue Drivers'!W17 | X14: =SUM(D14:G14) | Y14: =SUM(H14:K14) | Z14: =SUM(L14:O14) | AA14: =SUM(P14:S14) | AB14: =SUM(T14:W14)
A15: Primary line of business / Retail wellness products - Capacity | B15: Revenue Drivers schedule | C15: ='Revenue Drivers'!C20 | D15: ='Revenue Drivers'!D20 | E15: ='Revenue Drivers'!E20 | F15: ='Revenue Drivers'!F20 | G15: ='Revenue Drivers'!G20 | H15: ='Revenue Drivers'!H20 | I15: ='Revenue Drivers'!I20 | J15: ='Revenue Drivers'!J20 | ... W15: ='Revenue Drivers'!W20 | X15: =SUM(D15:G15) | Y15: =SUM(H15:K15) | Z15: =SUM(L15:O15) | AA15: =SUM(P15:S15) | AB15: =SUM(T15:W15)
A16: Primary line of business / Retail wellness products - Unit Price | B16: Revenue Drivers schedule | C16: ='Revenue Drivers'!C21 | D16: ='Revenue Drivers'!D21 | E16: ='Revenue Drivers'!E21 | F16: ='Revenue Drivers'!F21 | G16: ='Revenue Drivers'!G21 | H16: ='Revenue Drivers'!H21 | I16: ='Revenue Drivers'!I21 | J16: ='Revenue Drivers'!J21 | ... W16: ='Revenue Drivers'!W21 | X16: =SUM(D16:G16) | Y16: =SUM(H16:K16) | Z16: =SUM(L16:O16) | AA16: =SUM(P16:S16) | AB16: =SUM(T16:W16)
A17: Primary line of business / Retail wellness products - Utilization | B17: Revenue Drivers schedule | C17: ='Revenue Drivers'!C22 | D17: ='Revenue Drivers'!D22 | E17: ='Revenue Drivers'!E22 | F17: ='Revenue Drivers'!F22 | G17: ='Revenue Drivers'!G22 | H17: ='Revenue Drivers'!H22 | I17: ='Revenue Drivers'!I22 | J17: ='Revenue Drivers'!J22 | ... W17: ='Revenue Drivers'!W22 | X17: =SUM(D17:G17) | Y17: =SUM(H17:K17) | Z17: =SUM(L17:O17) | AA17: =SUM(P17:S17) | AB17: =SUM(T17:W17)
A18: Primary line of business / Retail wellness products - Revenue | B18: Revenue Drivers schedule | C18: ='Revenue Drivers'!C23 | D18: ='Revenue Drivers'!D23 | E18: ='Revenue Drivers'!E23 | F18: ='Revenue Drivers'!F23 | G18: ='Revenue Drivers'!G23 | H18: ='Revenue Drivers'!H23 | I18: ='Revenue Drivers'!I23 | J18: ='Revenue Drivers'!J23 | ... W18: ='Revenue Drivers'!W23 | X18: =SUM(D18:G18) | Y18: =SUM(H18:K18) | Z18: =SUM(L18:O18) | AA18: =SUM(P18:S18) | AB18: =SUM(T18:W18)
A19: Revenue | B19: Revenue Drivers schedule | C19: ='Revenue Drivers'!C26 | D19: ='Revenue Drivers'!D26 | E19: ='Revenue Drivers'!E26 | F19: ='Revenue Drivers'!F26 | G19: ='Revenue Drivers'!G26 | H19: ='Revenue Drivers'!H26 | I19: ='Revenue Drivers'!I26 | J19: ='Revenue Drivers'!J26 | ... W19: ='Revenue Drivers'!W26 | X19: =SUM(D19:G19) | Y19: =SUM(H19:K19) | Z19: =SUM(L19:O19) | AA19: =SUM(P19:S19) | AB19: =SUM(T19:W19)
A20: Cost of Goods Sold | B20: Direct model driver | C20: 0.32 | D20: 0.48 | E20: 0.474 | F20: 0.468 | G20: 0.462 | H20: 0.456 | I20: 0.45 | J20: 0.444 | K20: 0.438 | L20: 0.432 | M20: 0.426 | N20: 0.42 | O20: 0.41777778 | P20: 0.41555556 | Q20: 0.41333333 | R20: 0.41111111 | S20: 0.40888889 | T20: 0.40666667 | U20: 0.40444444 | V20: 0.40222222 | W20: 0.4 | X20: =SUM(D20:G20) | Y20: =SUM(H20:K20) | Z20: =SUM(L20:O20) | AA20: =SUM(P20:S20) | AB20: =SUM(T20:W20)
A21: Marketing | B21: Direct model driver | C21: 0.22 | D21: 0.24 | E21: 0.228 | F21: 0.216 | G21: 0.204 | H21: 0.192 | I21: 0.18 | J21: 0.168 | K21: 0.156 | L21: 0.144 | M21: 0.132 | N21: 0.12 | O21: 0.11555556 | P21: 0.11111111 | Q21: 0.10666667 | R21: 0.10222222 | S21: 0.097777778 | T21: 0.093333333 | U21: 0.088888889 | V21: 0.084444444 | W21: 0.08 | X21: =SUM(D21:G21) | Y21: =SUM(H21:K21) | Z21: =SUM(L21:O21) | AA21: =SUM(P21:S21) | AB21: =SUM(T21:W21)
A22: Research & Development | B22: Direct model driver | C22: 0 | D22: 0 | E22: 0 | F22: 0 | G22: 0 | H22: 0 | I22: 0 | J22: 0 | K22: 0 | L22: 0 | M22: 0 | N22: 0 | O22: 0 | P22: 0 | Q22: 0 | R22: 0 | S22: 0 | T22: 0 | U22: 0 | V22: 0 | W22: 0 | X22: =SUM(D22:G22) | Y22: =SUM(H22:K22) | Z22: =SUM(L22:O22) | AA22: =SUM(P22:S22) | AB22: =SUM(T22:W22)
A23: Lease | B23: Cash Equity Schedule output | C23: ='Cash Equity Schedule'!C12 | D23: ='Cash Equity Schedule'!D12 | E23: ='Cash Equity Schedule'!E12 | F23: ='Cash Equity Schedule'!F12 | G23: ='Cash Equity Schedule'!G12 | H23: ='Cash Equity Schedule'!H12 | I23: ='Cash Equity Schedule'!I12 | J23: ='Cash Equity Schedule'!J12 | ... W23: ='Cash Equity Schedule'!W12 | X23: =SUM(D23:G23) | Y23: =SUM(H23:K23) | Z23: =SUM(L23:O23) | AA23: =SUM(P23:S23) | AB23: =SUM(T23:W23)
A24: Payroll | B24: Payroll Schedule output | C24: 27200 | D24: ='Payroll Schedule'!D17 | E24: ='Payroll Schedule'!E17 | F24: ='Payroll Schedule'!F17 | G24: ='Payroll Schedule'!G17 | H24: ='Payroll Schedule'!H17 | I24: ='Payroll Schedule'!I17 | J24: ='Payroll Schedule'!J17 | K24: ='Payroll Schedule'!K17 | ... W24: ='Payroll Schedule'!W17 | X24: =SUM(D24:G24) | Y24: =SUM(H24:K24) | Z24: =SUM(L24:O24) | AA24: =SUM(P24:S24) | AB24: =SUM(T24:W24)
A25: General & Administrative | B25: Direct model driver | C25: 0.005407 | D25: 0.24 | E25: 0.228 | F25: 0.216 | G25: 0.204 | H25: 0.192 | I25: 0.18 | J25: 0.168 | K25: 0.156 | L25: 0.144 | M25: 0.132 | N25: 0.12 | O25: 0.11555556 | P25: 0.11111111 | Q25: 0.10666667 | R25: 0.10222222 | S25: 0.097777778 | T25: 0.093333333 | U25: 0.088888889 | V25: 0.084444444 | W25: 0.08 | X25: =SUM(D25:G25) | Y25: =SUM(H25:K25) | Z25: =SUM(L25:O25) | AA25: =SUM(P25:S25) | AB25: =SUM(T25:W25)
A26: Interest Rate | B26: Debt Schedule output | C26: ='Debt Schedule'!C12 | D26: ='Debt Schedule'!D12 | E26: ='Debt Schedule'!E12 | F26: ='Debt Schedule'!F12 | G26: ='Debt Schedule'!G12 | H26: ='Debt Schedule'!H12 | I26: ='Debt Schedule'!I12 | J26: ='Debt Schedule'!J12 | ... W26: ='Debt Schedule'!W12 | X26: =SUM(D26:G26) | Y26: =SUM(H26:K26) | Z26: =SUM(L26:O26) | AA26: =SUM(P26:S26) | AB26: =SUM(T26:W26)
A27: Interest Expense | B27: Debt Schedule output | C27: 0 | D27: ='Debt Schedule'!D13 | E27: ='Debt Schedule'!E13 | F27: ='Debt Schedule'!F13 | G27: ='Debt Schedule'!G13 | H27: ='Debt Schedule'!H13 | I27: ='Debt Schedule'!I13 | J27: ='Debt Schedule'!J13 | K27: ='Debt Schedule'!K13 | ... W27: ='Debt Schedule'!W13 | X27: =SUM(D27:G27) | Y27: =SUM(H27:K27) | Z27: =SUM(L27:O27) | AA27: =SUM(P27:S27) | AB27: =SUM(T27:W27)
A28: Depreciation | B28: CapEx Depreciation output | C28: ='CapEx Depreciation'!C10 | D28: ='CapEx Depreciation'!D10 | E28: ='CapEx Depreciation'!E10 | F28: ='CapEx Depreciation'!F10 | G28: ='CapEx Depreciation'!G10 | H28: ='CapEx Depreciation'!H10 | I28: ='CapEx Depreciation'!I10 | J28: ='CapEx Depreciation'!J10 | ... W28: ='CapEx Depreciation'!W10 | X28: =SUM(D28:G28) | Y28: =SUM(H28:K28) | Z28: =SUM(L28:O28) | AA28: =SUM(P28:S28) | AB28: =SUM(T28:W28)
A29: Depreciation Expense | B29: CapEx Depreciation output | C29: ='CapEx Depreciation'!C11 | D29: ='CapEx Depreciation'!D11 | E29: ='CapEx Depreciation'!E11 | F29: ='CapEx Depreciation'!F11 | G29: ='CapEx Depreciation'!G11 | H29: ='CapEx Depreciation'!H11 | I29: ='CapEx Depreciation'!I11 | J29: ='CapEx Depreciation'!J11 | ... W29: ='CapEx Depreciation'!W11 | X29: =SUM(D29:G29) | Y29: =SUM(H29:K29) | Z29: =SUM(L29:O29) | AA29: =SUM(P29:S29) | AB29: =SUM(T29:W29)
A30: Taxes | B30: Direct model driver | C30: 0.189164 | D30: 0.189164 | E30: 0.189164 | F30: 0.189164 | G30: 0.189164 | H30: 0.189164 | I30: 0.189164 | J30: 0.189164 | K30: 0.189164 | L30: 0.189164 | M30: 0.189164 | N30: 0.189164 | O30: 0.189164 | P30: 0.189164 | Q30: 0.189164 | R30: 0.189164 | S30: 0.189164 | T30: 0.189164 | U30: 0.189164 | V30: 0.189164 | W30: 0.189164 | X30: =SUM(D30:G30) | Y30: =SUM(H30:K30) | Z30: =SUM(L30:O30) | AA30: =SUM(P30:S30) | AB30: =SUM(T30:W30)
A32: Balance Sheet Inputs
A33: Accounts Receivable Days | B33: Working Capital schedule | C33: ='Working Capital'!C7 | D33: ='Working Capital'!D7 | E33: ='Working Capital'!E7 | F33: ='Working Capital'!F7 | G33: ='Working Capital'!G7 | H33: ='Working Capital'!H7 | I33: ='Working Capital'!I7 | J33: ='Working Capital'!J7 | ... W33: ='Working Capital'!W7 | X33: =SUM(D33:G33) | Y33: =SUM(H33:K33) | Z33: =SUM(L33:O33) | AA33: =SUM(P33:S33) | AB33: =SUM(T33:W33)
A34: Inventory Days | B34: Working Capital schedule | C34: ='Working Capital'!C8 | D34: ='Working Capital'!D8 | E34: ='Working Capital'!E8 | F34: ='Working Capital'!F8 | G34: ='Working Capital'!G8 | H34: ='Working Capital'!H8 | I34: ='Working Capital'!I8 | J34: ='Working Capital'!J8 | ... W34: ='Working Capital'!W8 | X34: =SUM(D34:G34) | Y34: =SUM(H34:K34) | Z34: =SUM(L34:O34) | AA34: =SUM(P34:S34) | AB34: =SUM(T34:W34)
A35: Accounts Payable Days | B35: Working Capital schedule | C35: ='Working Capital'!C9 | D35: ='Working Capital'!D9 | E35: ='Working Capital'!E9 | F35: ='Working Capital'!F9 | G35: ='Working Capital'!G9 | H35: ='Working Capital'!H9 | I35: ='Working Capital'!I9 | J35: ='Working Capital'!J9 | ... W35: ='Working Capital'!W9 | X35: =SUM(D35:G35) | Y35: =SUM(H35:K35) | Z35: =SUM(L35:O35) | AA35: =SUM(P35:S35) | AB35: =SUM(T35:W35)
A36: Prepaid Expenses (% of Revenue) | B36: Working Capital schedule | C36: ='Working Capital'!C10 | D36: ='Working Capital'!D10 | E36: ='Working Capital'!E10 | F36: ='Working Capital'!F10 | G36: ='Working Capital'!G10 | H36: ='Working Capital'!H10 | I36: ='Working Capital'!I10 | J36: ='Working Capital'!J10 | ... W36: ='Working Capital'!W10 | X36: =SUM(D36:G36) | Y36: =SUM(H36:K36) | Z36: =SUM(L36:O36) | AA36: =SUM(P36:S36) | AB36: =SUM(T36:W36)
A37: Deferred Revenue (% of Revenue) | B37: Working Capital schedule | C37: ='Working Capital'!C11 | D37: ='Working Capital'!D11 | E37: ='Working Capital'!E11 | F37: ='Working Capital'!F11 | G37: ='Working Capital'!G11 | H37: ='Working Capital'!H11 | I37: ='Working Capital'!I11 | J37: ='Working Capital'!J11 | ... W37: ='Working Capital'!W11 | X37: =SUM(D37:G37) | Y37: =SUM(H37:K37) | Z37: =SUM(L37:O37) | AA37: =SUM(P37:S37) | AB37: =SUM(T37:W37)
A38: Short Term Debt (% of LTD) | B38: Working Capital schedule | C38: ='Working Capital'!C12 | D38: ='Working Capital'!D12 | E38: ='Working Capital'!E12 | F38: ='Working Capital'!F12 | G38: ='Working Capital'!G12 | H38: ='Working Capital'!H12 | I38: ='Working Capital'!I12 | J38: ='Working Capital'!J12 | ... W38: ='Working Capital'!W12 | X38: =SUM(D38:G38) | Y38: =SUM(H38:K38) | Z38: =SUM(L38:O38) | AA38: =SUM(P38:S38) | AB38: =SUM(T38:W38)
A39: Owner's Capital | B39: Cash Equity Schedule schedule | C39: ='Cash Equity Schedule'!C7 | D39: ='Cash Equity Schedule'!D7 | E39: ='Cash Equity Schedule'!E7 | F39: ='Cash Equity Schedule'!F7 | G39: ='Cash Equity Schedule'!G7 | H39: ='Cash Equity Schedule'!H7 | I39: ='Cash Equity Schedule'!I7 | J39: ='Cash Equity Schedule'!J7 | ... W39: ='Cash Equity Schedule'!W7 | X39: =G39 | Y39: =K39 | Z39: =O39 | AA39: =S39 | AB39: =W39
A40: Other Equity | B40: Cash Equity Schedule schedule | C40: ='Cash Equity Schedule'!C8 | D40: ='Cash Equity Schedule'!D8 | E40: ='Cash Equity Schedule'!E8 | F40: ='Cash Equity Schedule'!F8 | G40: ='Cash Equity Schedule'!G8 | H40: ='Cash Equity Schedule'!H8 | I40: ='Cash Equity Schedule'!I8 | J40: ='Cash Equity Schedule'!J8 | ... W40: ='Cash Equity Schedule'!W8 | X40: =G40 | Y40: =K40 | Z40: =O40 | AA40: =S40 | AB40: =W40
A41: Distributions | B41: Cash Equity Schedule schedule | C41: ='Cash Equity Schedule'!C9 | D41: ='Cash Equity Schedule'!D9 | E41: ='Cash Equity Schedule'!E9 | F41: ='Cash Equity Schedule'!F9 | G41: ='Cash Equity Schedule'!G9 | H41: ='Cash Equity Schedule'!H9 | I41: ='Cash Equity Schedule'!I9 | J41: ='Cash Equity Schedule'!J9 | ... W41: ='Cash Equity Schedule'!W9 | X41: =G41 | Y41: =K41 | Z41: =O41 | AA41: =S41 | AB41: =W41
A43: Cash Flow and Schedule Inputs
A44: Cash Opening Balance | B44: Working Capital schedule | C44: ='Working Capital'!C15 | D44: ='Working Capital'!D15 | E44: ='Working Capital'!E15 | F44: ='Working Capital'!F15 | G44: ='Working Capital'!G15 | H44: ='Working Capital'!H15 | I44: ='Working Capital'!I15 | J44: ='Working Capital'!J15 | ... W44: ='Working Capital'!W15 | X44: =G44 | Y44: =K44 | Z44: =O44 | AA44: =S44 | AB44: =W44
A45: Accounts Receivable Opening Balance | B45: Working Capital schedule | C45: ='Working Capital'!C16 | D45: ='Working Capital'!D16 | E45: ='Working Capital'!E16 | F45: ='Working Capital'!F16 | G45: ='Working Capital'!G16 | H45: ='Working Capital'!H16 | I45: ='Working Capital'!I16 | J45: ='Working Capital'!J16 | ... W45: ='Working Capital'!W16 | X45: =G45 | Y45: =K45 | Z45: =O45 | AA45: =S45 | AB45: =W45
A46: Inventory Opening Balance | B46: Working Capital schedule | C46: ='Working Capital'!C17 | D46: ='Working Capital'!D17 | E46: ='Working Capital'!E17 | F46: ='Working Capital'!F17 | G46: ='Working Capital'!G17 | H46: ='Working Capital'!H17 | I46: ='Working Capital'!I17 | J46: ='Working Capital'!J17 | ... W46: ='Working Capital'!W17 | X46: =G46 | Y46: =K46 | Z46: =O46 | AA46: =S46 | AB46: =W46
A47: Accounts Payable Opening Balance | B47: Working Capital schedule | C47: ='Working Capital'!C18 | D47: ='Working Capital'!D18 | E47: ='Working Capital'!E18 | F47: ='Working Capital'!F18 | G47: ='Working Capital'!G18 | H47: ='Working Capital'!H18 | I47: ='Working Capital'!I18 | J47: ='Working Capital'!J18 | ... W47: ='Working Capital'!W18 | X47: =G47 | Y47: =K47 | Z47: =O47 | AA47: =S47 | AB47: =W47
A48: Short Term Debt Opening Balance | B48: Working Capital schedule | C48: ='Working Capital'!C19 | D48: ='Working Capital'!D19 | E48: ='Working Capital'!E19 | F48: ='Working Capital'!F19 | G48: ='Working Capital'!G19 | H48: ='Working Capital'!H19 | I48: ='Working Capital'!I19 | J48: ='Working Capital'!J19 | ... W48: ='Working Capital'!W19 | X48: =G48 | Y48: =K48 | Z48: =O48 | AA48: =S48 | AB48: =W48
A49: Debt Opening Balance | B49: Debt Schedule schedule | C49: ='Debt Schedule'!C7 | D49: ='Debt Schedule'!D7 | E49: ='Debt Schedule'!E7 | F49: ='Debt Schedule'!F7 | G49: ='Debt Schedule'!G7 | H49: ='Debt Schedule'!H7 | I49: ='Debt Schedule'!I7 | J49: ='Debt Schedule'!J7 | ... W49: ='Debt Schedule'!W7 | X49: =G49 | Y49: =K49 | Z49: =O49 | AA49: =S49 | AB49: =W49
A50: Debt Issuance | B50: Debt Schedule schedule | C50: ='Debt Schedule'!C8 | D50: ='Debt Schedule'!D8 | E50: ='Debt Schedule'!E8 | F50: ='Debt Schedule'!F8 | G50: ='Debt Schedule'!G8 | H50: ='Debt Schedule'!H8 | I50: ='Debt Schedule'!I8 | J50: ='Debt Schedule'!J8 | ... W50: ='Debt Schedule'!W8 | X50: =SUM(D50:G50) | Y50: =SUM(H50:K50) | Z50: =SUM(L50:O50) | AA50: =SUM(P50:S50) | AB50: =SUM(T50:W50)
A51: Debt Repayment | B51: Debt Schedule schedule | C51: ='Debt Schedule'!C10 | D51: ='Debt Schedule'!D10 | E51: ='Debt Schedule'!E10 | F51: ='Debt Schedule'!F10 | G51: ='Debt Schedule'!G10 | H51: ='Debt Schedule'!H10 | I51: ='Debt Schedule'!I10 | J51: ='Debt Schedule'!J10 | ... W51: ='Debt Schedule'!W10 | X51: =SUM(D51:G51) | Y51: =SUM(H51:K51) | Z51: =SUM(L51:O51) | AA51: =SUM(P51:S51) | AB51: =SUM(T51:W51)
A52: Debt Closing Balance | B52: Debt Schedule schedule | C52: ='Debt Schedule'!C11 | D52: ='Debt Schedule'!D11 | E52: ='Debt Schedule'!E11 | F52: ='Debt Schedule'!F11 | G52: ='Debt Schedule'!G11 | H52: ='Debt Schedule'!H11 | I52: ='Debt Schedule'!I11 | J52: ='Debt Schedule'!J11 | ... W52: ='Debt Schedule'!W11 | X52: =G52 | Y52: =K52 | Z52: =O52 | AA52: =S52 | AB52: =W52
A53: Lease Opening Balance | B53: Debt Schedule schedule | C53: ='Debt Schedule'!C18 | D53: ='Debt Schedule'!D18 | E53: ='Debt Schedule'!E18 | F53: ='Debt Schedule'!F18 | G53: ='Debt Schedule'!G18 | H53: ='Debt Schedule'!H18 | I53: ='Debt Schedule'!I18 | J53: ='Debt Schedule'!J18 | ... W53: ='Debt Schedule'!W18 | X53: =G53 | Y53: =K53 | Z53: =O53 | AA53: =S53 | AB53: =W53
A54: Lease Principal Repayments | B54: Debt Schedule schedule | C54: ='Debt Schedule'!C20 | D54: ='Debt Schedule'!D20 | E54: ='Debt Schedule'!E20 | F54: ='Debt Schedule'!F20 | G54: ='Debt Schedule'!G20 | H54: ='Debt Schedule'!H20 | I54: ='Debt Schedule'!I20 | J54: ='Debt Schedule'!J20 | ... W54: ='Debt Schedule'!W20 | X54: =SUM(D54:G54) | Y54: =SUM(H54:K54) | Z54: =SUM(L54:O54) | AA54: =SUM(P54:S54) | AB54: =SUM(T54:W54)
A55: Lease Net Additions | B55: Debt Schedule schedule | C55: ='Debt Schedule'!C21 | D55: ='Debt Schedule'!D21 | E55: ='Debt Schedule'!E21 | F55: ='Debt Schedule'!F21 | G55: ='Debt Schedule'!G21 | H55: ='Debt Schedule'!H21 | I55: ='Debt Schedule'!I21 | J55: ='Debt Schedule'!J21 | ... W55: ='Debt Schedule'!W21 | X55: =SUM(D55:G55) | Y55: =SUM(H55:K55) | Z55: =SUM(L55:O55) | AA55: =SUM(P55:S55) | AB55: =SUM(T55:W55)
A56: Lease Interest Expense | B56: Debt Schedule schedule | C56: ='Debt Schedule'!C22 | D56: ='Debt Schedule'!D22 | E56: ='Debt Schedule'!E22 | F56: ='Debt Schedule'!F22 | G56: ='Debt Schedule'!G22 | H56: ='Debt Schedule'!H22 | I56: ='Debt Schedule'!I22 | J56: ='Debt Schedule'!J22 | ... W56: ='Debt Schedule'!W22 | X56: =SUM(D56:G56) | Y56: =SUM(H56:K56) | Z56: =SUM(L56:O56) | AA56: =SUM(P56:S56) | AB56: =SUM(T56:W56)
A57: Lease Closing Balance | B57: Debt Schedule schedule | C57: ='Debt Schedule'!C23 | D57: ='Debt Schedule'!D23 | E57: ='Debt Schedule'!E23 | F57: ='Debt Schedule'!F23 | G57: ='Debt Schedule'!G23 | H57: ='Debt Schedule'!H23 | I57: ='Debt Schedule'!I23 | J57: ='Debt Schedule'!J23 | ... W57: ='Debt Schedule'!W23 | X57: =G57 | Y57: =K57 | Z57: =O57 | AA57: =S57 | AB57: =W57
A58: Right-of-Use Asset | B58: Debt Schedule schedule | C58: ='Debt Schedule'!C26 | D58: ='Debt Schedule'!D26 | E58: ='Debt Schedule'!E26 | F58: ='Debt Schedule'!F26 | G58: ='Debt Schedule'!G26 | H58: ='Debt Schedule'!H26 | I58: ='Debt Schedule'!I26 | J58: ='Debt Schedule'!J26 | ... W58: ='Debt Schedule'!W26 | X58: =G58 | Y58: =K58 | Z58: =O58 | AA58: =S58 | AB58: =W58
A59: Lease Asset Depreciation | B59: Debt Schedule schedule | C59: ='Debt Schedule'!C25 | D59: ='Debt Schedule'!D25 | E59: ='Debt Schedule'!E25 | F59: ='Debt Schedule'!F25 | G59: ='Debt Schedule'!G25 | H59: ='Debt Schedule'!H25 | I59: ='Debt Schedule'!I25 | J59: ='Debt Schedule'!J25 | ... W59: ='Debt Schedule'!W25 | X59: =SUM(D59:G59) | Y59: =SUM(H59:K59) | Z59: =SUM(L59:O59) | AA59: =SUM(P59:S59) | AB59: =SUM(T59:W59)
A60: Capital Expenditures | B60: CapEx Depreciation schedule | C60: ='CapEx Depreciation'!C8 | D60: ='CapEx Depreciation'!D8 | E60: ='CapEx Depreciation'!E8 | F60: ='CapEx Depreciation'!F8 | G60: ='CapEx Depreciation'!G8 | H60: ='CapEx Depreciation'!H8 | I60: ='CapEx Depreciation'!I8 | J60: ='CapEx Depreciation'!J8 | ... W60: ='CapEx Depreciation'!W8 | X60: =SUM(D60:G60) | Y60: =SUM(H60:K60) | Z60: =SUM(L60:O60) | AA60: =SUM(P60:S60) | AB60: =SUM(T60:W60)
A61: PPE Closing Balance | B61: CapEx Depreciation schedule | C61: ='CapEx Depreciation'!C12 | D61: ='CapEx Depreciation'!D12 | E61: ='CapEx Depreciation'!E12 | F61: ='CapEx Depreciation'!F12 | G61: ='CapEx Depreciation'!G12 | H61: ='CapEx Depreciation'!H12 | I61: ='CapEx Depreciation'!I12 | J61: ='CapEx Depreciation'!J12 | ... W61: ='CapEx Depreciation'!W12 | X61: =G61 | Y61: =K61 | Z61: =O61 | AA61: =S61 | AB61: =W61
A62: Accumulated Depreciation | B62: CapEx Depreciation schedule | C62: ='CapEx Depreciation'!C14 | D62: ='CapEx Depreciation'!D14 | E62: ='CapEx Depreciation'!E14 | F62: ='CapEx Depreciation'!F14 | G62: ='CapEx Depreciation'!G14 | H62: ='CapEx Depreciation'!H14 | I62: ='CapEx Depreciation'!I14 | J62: ='CapEx Depreciation'!J14 | ... W62: ='CapEx Depreciation'!W14 | X62: =G62 | Y62: =K62 | Z62: =O62 | AA62: =S62 | AB62: =W62

Sheet FINMO
A1: FINMO
A2: Three-statement financial model. All formulas reference Model Inputs and in-sheet statement rows.
C4: Stub | D4: Q1 | E4: Q2 | F4: Q3 | G4: Q4 | H4: Q5 | I4: Q6 | J4: Q7 | K4: Q8 | L4: Q9 | M4: Q10 | N4: Q11 | O4: Q12 | P4: Q13 | Q4: Q14 | R4: Q15 | S4: Q16 | T4: Q17 | U4: Q18 | V4: Q19 | W4: Q20 | X4: Y1 | Y4: Y2 | Z4: Y3 | AA4: Y4 | AB4: Y5
C5: 46162 | D5: 46295 | E5: 46387 | F5: 46477 | G5: 46568 | H5: 46660 | I5: 46752 | J5: 46843 | K5: 46934 | L5: 47026 | M5: 47118 | N5: 47208 | O5: 47299 | P5: 47391 | Q5: 47483 | R5: 47573 | S5: 47664 | T5: 47756 | U5: 47848 | V5: 47938 | W5: 48029 | X5: Annual | Y5: Annual | Z5: Annual | AA5: Annual | AB5: Annual
A6: Days in Quarter | C6: 0 | D6: 92 | E6: 92 | F6: 90 | G6: 91 | H6: 92 | I6: 92 | J6: 91 | K6: 91 | L6: 92 | M6: 92 | N6: 90 | O6: 91 | P6: 92 | Q6: 92 | R6: 90 | S6: 91 | T6: 92 | U6: 92 | V6: 90 | W6: 91
A7: Income Statement
A8: Revenue | B8: Formula | C8: ='Model Inputs'!C19 | D8: ='Model Inputs'!D19 | E8: ='Model Inputs'!E19 | F8: ='Model Inputs'!F19 | G8: ='Model Inputs'!G19 | H8: ='Model Inputs'!H19 | I8: ='Model Inputs'!I19 | J8: ='Model Inputs'!J19 | ... W8: ='Model Inputs'!W19 | X8: =SUM(D8:G8) | Y8: =SUM(H8:K8) | Z8: =SUM(L8:O8) | AA8: =SUM(P8:S8) | AB8: =SUM(T8:W8)
A9: Cost of Goods Sold | B9: Formula | C9: =C8*'Model Inputs'!C20 | D9: =D8*'Model Inputs'!D20 | E9: =E8*'Model Inputs'!E20 | F9: =F8*'Model Inputs'!F20 | G9: =G8*'Model Inputs'!G20 | H9: =H8*'Model Inputs'!H20 | I9: =I8*'Model Inputs'!I20 | J9: =J8*'Model Inputs'!J20 | ... W9: =W8*'Model Inputs'!W20 | X9: =SUM(D9:G9) | Y9: =SUM(H9:K9) | Z9: =SUM(L9:O9) | AA9: =SUM(P9:S9) | AB9: =SUM(T9:W9)
A10: Gross Profit | B10: Formula | C10: =C8-C9 | D10: =D8-D9 | E10: =E8-E9 | F10: =F8-F9 | G10: =G8-G9 | H10: =H8-H9 | I10: =I8-I9 | J10: =J8-J9 | ... W10: =W8-W9 | X10: =SUM(D10:G10) | Y10: =SUM(H10:K10) | Z10: =SUM(L10:O10) | AA10: =SUM(P10:S10) | AB10: =SUM(T10:W10)
A11: Marketing | B11: Formula | C11: =C8*'Model Inputs'!C21 | D11: =D8*'Model Inputs'!D21 | E11: =E8*'Model Inputs'!E21 | F11: =F8*'Model Inputs'!F21 | G11: =G8*'Model Inputs'!G21 | H11: =H8*'Model Inputs'!H21 | I11: =I8*'Model Inputs'!I21 | J11: =J8*'Model Inputs'!J21 | ... W11: =W8*'Model Inputs'!W21 | X11: =SUM(D11:G11) | Y11: =SUM(H11:K11) | Z11: =SUM(L11:O11) | AA11: =SUM(P11:S11) | AB11: =SUM(T11:W11)
A12: Research & Development | B12: Formula | C12: =C8*'Model Inputs'!C22 | D12: =D8*'Model Inputs'!D22 | E12: =E8*'Model Inputs'!E22 | F12: =F8*'Model Inputs'!F22 | G12: =G8*'Model Inputs'!G22 | H12: =H8*'Model Inputs'!H22 | I12: =I8*'Model Inputs'!I22 | J12: =J8*'Model Inputs'!J22 | ... W12: =W8*'Model Inputs'!W22 | X12: =SUM(D12:G12) | Y12: =SUM(H12:K12) | Z12: =SUM(L12:O12) | AA12: =SUM(P12:S12) | AB12: =SUM(T12:W12)
A13: Lease/Rent | B13: Formula | C13: ='Model Inputs'!C23 | D13: ='Model Inputs'!D23 | E13: ='Model Inputs'!E23 | F13: ='Model Inputs'!F23 | G13: ='Model Inputs'!G23 | H13: ='Model Inputs'!H23 | I13: ='Model Inputs'!I23 | J13: ='Model Inputs'!J23 | ... W13: ='Model Inputs'!W23 | X13: =SUM(D13:G13) | Y13: =SUM(H13:K13) | Z13: =SUM(L13:O13) | AA13: =SUM(P13:S13) | AB13: =SUM(T13:W13)
A14: Payroll | B14: Formula | C14: ='Model Inputs'!C24 | D14: ='Model Inputs'!D24 | E14: ='Model Inputs'!E24 | F14: ='Model Inputs'!F24 | G14: ='Model Inputs'!G24 | H14: ='Model Inputs'!H24 | I14: ='Model Inputs'!I24 | J14: ='Model Inputs'!J24 | ... W14: ='Model Inputs'!W24 | X14: =SUM(D14:G14) | Y14: =SUM(H14:K14) | Z14: =SUM(L14:O14) | AA14: =SUM(P14:S14) | AB14: =SUM(T14:W14)
A15: General & Administrative | B15: Formula | C15: =C8*'Model Inputs'!C25 | D15: =D8*'Model Inputs'!D25 | E15: =E8*'Model Inputs'!E25 | F15: =F8*'Model Inputs'!F25 | G15: =G8*'Model Inputs'!G25 | H15: =H8*'Model Inputs'!H25 | I15: =I8*'Model Inputs'!I25 | J15: =J8*'Model Inputs'!J25 | ... W15: =W8*'Model Inputs'!W25 | X15: =SUM(D15:G15) | Y15: =SUM(H15:K15) | Z15: =SUM(L15:O15) | AA15: =SUM(P15:S15) | AB15: =SUM(T15:W15)
A16: EBITDA | B16: Formula | C16: =C10-SUM(C11:C15) | D16: =D10-SUM(D11:D15) | E16: =E10-SUM(E11:E15) | F16: =F10-SUM(F11:F15) | G16: =G10-SUM(G11:G15) | H16: =H10-SUM(H11:H15) | I16: =I10-SUM(I11:I15) | J16: =J10-SUM(J11:J15) | ... W16: =W10-SUM(W11:W15) | X16: =SUM(D16:G16) | Y16: =SUM(H16:K16) | Z16: =SUM(L16:O16) | AA16: =SUM(P16:S16) | AB16: =SUM(T16:W16)
A17: Interest | B17: Formula | C17: ='Model Inputs'!C27+'Model Inputs'!C56 | D17: ='Model Inputs'!D27+'Model Inputs'!D56 | E17: ='Model Inputs'!E27+'Model Inputs'!E56 | F17: ='Model Inputs'!F27+'Model Inputs'!F56 | G17: ='Model Inputs'!G27+'Model Inputs'!G56 | H17: ='Model Inputs'!H27+'Model Inputs'!H56 | I17: ='Model Inputs'!I27+'Model Inputs'!I56 | J17: ='Model Inputs'!J27+'Model Inputs'!J56 | ... W17: ='Model Inputs'!W27+'Model Inputs'!W56 | X17: =SUM(D17:G17) | Y17: =SUM(H17:K17) | Z17: =SUM(L17:O17) | AA17: =SUM(P17:S17) | AB17: =SUM(T17:W17)
A18: Depreciation | B18: Formula | C18: ='Model Inputs'!C29+'Model Inputs'!C59 | D18: ='Model Inputs'!D29+'Model Inputs'!D59 | E18: ='Model Inputs'!E29+'Model Inputs'!E59 | F18: ='Model Inputs'!F29+'Model Inputs'!F59 | G18: ='Model Inputs'!G29+'Model Inputs'!G59 | H18: ='Model Inputs'!H29+'Model Inputs'!H59 | I18: ='Model Inputs'!I29+'Model Inputs'!I59 | J18: ='Model Inputs'!J29+'Model Inputs'!J59 | ... W18: ='Model Inputs'!W29+'Model Inputs'!W59 | X18: =SUM(D18:G18) | Y18: =SUM(H18:K18) | Z18: =SUM(L18:O18) | AA18: =SUM(P18:S18) | AB18: =SUM(T18:W18)
A19: Taxes | B19: Formula | C19: =MAX(0,C16-C17-C18)*'Model Inputs'!C30 | D19: =MAX(0,D16-D17-D18)*'Model Inputs'!D30 | E19: =MAX(0,E16-E17-E18)*'Model Inputs'!E30 | F19: =MAX(0,F16-F17-F18)*'Model Inputs'!F30 | G19: =MAX(0,G16-G17-G18)*'Model Inputs'!G30 | H19: =MAX(0,H16-H17-H18)*'Model Inputs'!H30 | I19: =MAX(0,I16-I17-I18)*'Model Inputs'!I30 | J19: =MAX(0,J16-J17-J18)*'Model Inputs'!J30 | ... W19: =MAX(0,W16-W17-W18)*'Model Inputs'!W30 | X19: =SUM(D19:G19) | Y19: =SUM(H19:K19) | Z19: =SUM(L19:O19) | AA19: =SUM(P19:S19) | AB19: =SUM(T19:W19)
A20: Net Income | B20: Formula | C20: =C16-SUM(C17:C19) | D20: =D16-SUM(D17:D19) | E20: =E16-SUM(E17:E19) | F20: =F16-SUM(F17:F19) | G20: =G16-SUM(G17:G19) | H20: =H16-SUM(H17:H19) | I20: =I16-SUM(I17:I19) | J20: =J16-SUM(J17:J19) | ... W20: =W16-SUM(W17:W19) | X20: =SUM(D20:G20) | Y20: =SUM(H20:K20) | Z20: =SUM(L20:O20) | AA20: =SUM(P20:S20) | AB20: =SUM(T20:W20)
A22: Balance Sheet
A23: Cash | B23: Formula | C23: =C61 | D23: =D61 | E23: =E61 | F23: =F61 | G23: =G61 | H23: =H61 | I23: =I61 | J23: =J61 | ... W23: =W61 | X23: =G23 | Y23: =K23 | Z23: =O23 | AA23: =S23 | AB23: =W23
A24: Accounts Receivable | B24: Formula | C24: ='Model Inputs'!C45 | D24: =('Model Inputs'!D33/D6)*D8 | E24: =('Model Inputs'!E33/E6)*E8 | F24: =('Model Inputs'!F33/F6)*F8 | G24: =('Model Inputs'!G33/G6)*G8 | H24: =('Model Inputs'!H33/H6)*H8 | I24: =('Model Inputs'!I33/I6)*I8 | J24: =('Model Inputs'!J33/J6)*J8 | K24: =('Model Inputs'!K33/K6)*K8 | ... W24: =('Model Inputs'!W33/W6)*W8 | X24: =G24 | Y24: =K24 | Z24: =O24 | AA24: =S24 | AB24: =W24
A25: Inventory | B25: Formula | C25: ='Model Inputs'!C46 | D25: =('Model Inputs'!D34/D6)*D9 | E25: =('Model Inputs'!E34/E6)*E9 | F25: =('Model Inputs'!F34/F6)*F9 | G25: =('Model Inputs'!G34/G6)*G9 | H25: =('Model Inputs'!H34/H6)*H9 | I25: =('Model Inputs'!I34/I6)*I9 | J25: =('Model Inputs'!J34/J6)*J9 | K25: =('Model Inputs'!K34/K6)*K9 | ... W25: =('Model Inputs'!W34/W6)*W9 | X25: =G25 | Y25: =K25 | Z25: =O25 | AA25: =S25 | AB25: =W25
A26: Prepaid Expenses | B26: Formula | C26: =0 | D26: =D8*'Model Inputs'!D36 | E26: =E8*'Model Inputs'!E36 | F26: =F8*'Model Inputs'!F36 | G26: =G8*'Model Inputs'!G36 | H26: =H8*'Model Inputs'!H36 | I26: =I8*'Model Inputs'!I36 | J26: =J8*'Model Inputs'!J36 | K26: =K8*'Model Inputs'!K36 | ... W26: =W8*'Model Inputs'!W36 | X26: =G26 | Y26: =K26 | Z26: =O26 | AA26: =S26 | AB26: =W26
A27: Current Assets | B27: Formula | C27: =SUM(C23:C26) | D27: =SUM(D23:D26) | E27: =SUM(E23:E26) | F27: =SUM(F23:F26) | G27: =SUM(G23:G26) | H27: =SUM(H23:H26) | I27: =SUM(I23:I26) | J27: =SUM(J23:J26) | ... W27: =SUM(W23:W26) | X27: =G27 | Y27: =K27 | Z27: =O27 | AA27: =S27 | AB27: =W27
A28: PPE | B28: Formula | C28: ='Model Inputs'!C61 | D28: ='Model Inputs'!D61 | E28: ='Model Inputs'!E61 | F28: ='Model Inputs'!F61 | G28: ='Model Inputs'!G61 | H28: ='Model Inputs'!H61 | I28: ='Model Inputs'!I61 | J28: ='Model Inputs'!J61 | ... W28: ='Model Inputs'!W61 | X28: =G28 | Y28: =K28 | Z28: =O28 | AA28: =S28 | AB28: =W28
A29: Right-of-Use Asset (Capital Lease) | B29: Formula | C29: ='Model Inputs'!C58 | D29: ='Model Inputs'!D58 | E29: ='Model Inputs'!E58 | F29: ='Model Inputs'!F58 | G29: ='Model Inputs'!G58 | H29: ='Model Inputs'!H58 | I29: ='Model Inputs'!I58 | J29: ='Model Inputs'!J58 | ... W29: ='Model Inputs'!W58 | X29: =G29 | Y29: =K29 | Z29: =O29 | AA29: =S29 | AB29: =W29
A30: Accumulated Depreciation | B30: Formula | C30: ='Model Inputs'!C62 | D30: ='Model Inputs'!D62 | E30: ='Model Inputs'!E62 | F30: ='Model Inputs'!F62 | G30: ='Model Inputs'!G62 | H30: ='Model Inputs'!H62 | I30: ='Model Inputs'!I62 | J30: ='Model Inputs'!J62 | ... W30: ='Model Inputs'!W62 | X30: =G30 | Y30: =K30 | Z30: =O30 | AA30: =S30 | AB30: =W30
A31: Total Assets | B31: Formula | C31: =C27+C28+C29 | D31: =D27+D28+D29 | E31: =E27+E28+E29 | F31: =F27+F28+F29 | G31: =G27+G28+G29 | H31: =H27+H28+H29 | I31: =I27+I28+I29 | J31: =J27+J28+J29 | ... W31: =W27+W28+W29 | X31: =G31 | Y31: =K31 | Z31: =O31 | AA31: =S31 | AB31: =W31
A32: Accounts Payable | B32: Formula | C32: ='Model Inputs'!C47 | D32: =('Model Inputs'!D35/D6)*SUM(D11:D15) | E32: =('Model Inputs'!E35/E6)*SUM(E11:E15) | F32: =('Model Inputs'!F35/F6)*SUM(F11:F15) | G32: =('Model Inputs'!G35/G6)*SUM(G11:G15) | H32: =('Model Inputs'!H35/H6)*SUM(H11:H15) | I32: =('Model Inputs'!I35/I6)*SUM(I11:I15) | J32: =('Model Inputs'!J35/J6)*SUM(J11:J15) | K32: =('Model Inputs'!K35/K6)*SUM(K11:K15) | ... W32: =('Model Inputs'!W35/W6)*SUM(W11:W15) | X32: =G32 | Y32: =K32 | Z32: =O32 | AA32: =S32 | AB32: =W32
A33: Short Term Debt | B33: Formula | C33: ='Model Inputs'!C48 | D33: =SUM('Debt Schedule'!E10:H10) | E33: =SUM('Debt Schedule'!F10:I10) | F33: =SUM('Debt Schedule'!G10:J10) | G33: =SUM('Debt Schedule'!H10:K10) | H33: =SUM('Debt Schedule'!I10:L10) | I33: =SUM('Debt Schedule'!J10:M10) | J33: =SUM('Debt Schedule'!K10:N10) | K33: =SUM('Debt Schedule'!L10:O10) | ... S33: =SUM('Debt Schedule'!T10:W10) | T33: =SUM('Debt Schedule'!U10:W10) | U33: =SUM('Debt Schedule'!V10:W10) | V33: =SUM('Debt Schedule'!W10:W10) | W33: =0 | X33: =G33 | Y33: =K33 | Z33: =O33 | AA33: =S33 | AB33: =W33
A34: Deferred Revenue | B34: Formula | C34: =0 | D34: ='Model Inputs'!D37*D8 | E34: ='Model Inputs'!E37*E8 | F34: ='Model Inputs'!F37*F8 | G34: ='Model Inputs'!G37*G8 | H34: ='Model Inputs'!H37*H8 | I34: ='Model Inputs'!I37*I8 | J34: ='Model Inputs'!J37*J8 | K34: ='Model Inputs'!K37*K8 | ... W34: ='Model Inputs'!W37*W8 | X34: =G34 | Y34: =K34 | Z34: =O34 | AA34: =S34 | AB34: =W34
A35: Current Liabilities | B35: Formula | C35: =SUM(C32:C34) | D35: =SUM(D32:D34) | E35: =SUM(E32:E34) | F35: =SUM(F32:F34) | G35: =SUM(G32:G34) | H35: =SUM(H32:H34) | I35: =SUM(I32:I34) | J35: =SUM(J32:J34) | ... W35: =SUM(W32:W34) | X35: =G35 | Y35: =K35 | Z35: =O35 | AA35: =S35 | AB35: =W35
A36: Long Term Debt | B36: Formula | C36: =MAX(0,'Model Inputs'!C49-C33) | D36: =MAX(0,'Model Inputs'!D52-D33) | E36: =MAX(0,'Model Inputs'!E52-E33) | F36: =MAX(0,'Model Inputs'!F52-F33) | G36: =MAX(0,'Model Inputs'!G52-G33) | H36: =MAX(0,'Model Inputs'!H52-H33) | I36: =MAX(0,'Model Inputs'!I52-I33) | J36: =MAX(0,'Model Inputs'!J52-J33) | K36: =MAX(0,'Model Inputs'!K52-K33) | ... W36: =MAX(0,'Model Inputs'!W52-W33) | X36: =G36 | Y36: =K36 | Z36: =O36 | AA36: =S36 | AB36: =W36
A37: Capital Lease Obligation | B37: Formula | C37: ='Model Inputs'!C57 | D37: ='Model Inputs'!D57 | E37: ='Model Inputs'!E57 | F37: ='Model Inputs'!F57 | G37: ='Model Inputs'!G57 | H37: ='Model Inputs'!H57 | I37: ='Model Inputs'!I57 | J37: ='Model Inputs'!J57 | ... W37: ='Model Inputs'!W57 | X37: =G37 | Y37: =K37 | Z37: =O37 | AA37: =S37 | AB37: =W37
A38: Total Liabilities | B38: Formula | C38: =C35+C36+C37 | D38: =D35+D36+D37 | E38: =E35+E36+E37 | F38: =F35+F36+F37 | G38: =G35+G36+G37 | H38: =H35+H36+H37 | I38: =I35+I36+I37 | J38: =J35+J36+J37 | ... W38: =W35+W36+W37 | X38: =G38 | Y38: =K38 | Z38: =O38 | AA38: =S38 | AB38: =W38
A39: Owner's Capital | B39: Formula | C39: ='Model Inputs'!C39 | D39: ='Model Inputs'!D39 | E39: ='Model Inputs'!E39 | F39: ='Model Inputs'!F39 | G39: ='Model Inputs'!G39 | H39: ='Model Inputs'!H39 | I39: ='Model Inputs'!I39 | J39: ='Model Inputs'!J39 | ... W39: ='Model Inputs'!W39 | X39: =G39 | Y39: =K39 | Z39: =O39 | AA39: =S39 | AB39: =W39
A40: Retained Earnings | B40: Formula | C40: =C31-C38-C39-C41 | D40: =C40+D20-'Model Inputs'!D41 | E40: =D40+E20-'Model Inputs'!E41 | F40: =E40+F20-'Model Inputs'!F41 | G40: =F40+G20-'Model Inputs'!G41 | H40: =G40+H20-'Model Inputs'!H41 | I40: =H40+I20-'Model Inputs'!I41 | J40: =I40+J20-'Model Inputs'!J41 | K40: =J40+K20-'Model Inputs'!K41 | ... W40: =V40+W20-'Model Inputs'!W41 | X40: =G40 | Y40: =K40 | Z40: =O40 | AA40: =S40 | AB40: =W40
A41: Other Equity | B41: Formula | C41: ='Model Inputs'!C40 | D41: ='Model Inputs'!D40 | E41: ='Model Inputs'!E40 | F41: ='Model Inputs'!F40 | G41: ='Model Inputs'!G40 | H41: ='Model Inputs'!H40 | I41: ='Model Inputs'!I40 | J41: ='Model Inputs'!J40 | ... W41: ='Model Inputs'!W40 | X41: =G41 | Y41: =K41 | Z41: =O41 | AA41: =S41 | AB41: =W41
A42: Total Equity | B42: Formula | C42: =C39+C40+C41 | D42: =D39+D40+D41 | E42: =E39+E40+E41 | F42: =F39+F40+F41 | G42: =G39+G40+G41 | H42: =H39+H40+H41 | I42: =I39+I40+I41 | J42: =J39+J40+J41 | ... W42: =W39+W40+W41 | X42: =G42 | Y42: =K42 | Z42: =O42 | AA42: =S42 | AB42: =W42
A43: Total Liabilities & Equity | B43: Formula | C43: =C38+C42 | D43: =D38+D42 | E43: =E38+E42 | F43: =F38+F42 | G43: =G38+G42 | H43: =H38+H42 | I43: =I38+I42 | J43: =J38+J42 | ... W43: =W38+W42 | X43: =G43 | Y43: =K43 | Z43: =O43 | AA43: =S43 | AB43: =W43
A45: Cash Flow
A46: Beginning Cash | B46: Formula | C46: ='Model Inputs'!C44 | D46: =C61 | E46: =D61 | F46: =E61 | G46: =F61 | H46: =G61 | I46: =H61 | J46: =I61 | K46: =J61 | ... W46: =V61 | X46: =SUM(D46:G46) | Y46: =SUM(H46:K46) | Z46: =SUM(L46:O46) | AA46: =SUM(P46:S46) | AB46: =SUM(T46:W46)
A47: Net Income | B47: Formula | C47: =0 | D47: =D20 | E47: =E20 | F47: =F20 | G47: =G20 | H47: =H20 | I47: =I20 | J47: =J20 | K47: =K20 | ... W47: =W20 | X47: =SUM(D47:G47) | Y47: =SUM(H47:K47) | Z47: =SUM(L47:O47) | AA47: =SUM(P47:S47) | AB47: =SUM(T47:W47)
A48: Depreciation | B48: Formula | C48: =0 | D48: =D18 | E48: =E18 | F48: =F18 | G48: =G18 | H48: =H18 | I48: =I18 | J48: =J18 | K48: =K18 | ... W48: =W18 | X48: =SUM(D48:G48) | Y48: =SUM(H48:K48) | Z48: =SUM(L48:O48) | AA48: =SUM(P48:S48) | AB48: =SUM(T48:W48)
A49: Changes in Current Assets | B49: Formula | C49: =0 | D49: =-((D24+D25+D26)-(C24+C25+C26)) | E49: =-((E24+E25+E26)-(D24+D25+D26)) | F49: =-((F24+F25+F26)-(E24+E25+E26)) | G49: =-((G24+G25+G26)-(F24+F25+F26)) | H49: =-((H24+H25+H26)-(G24+G25+G26)) | I49: =-((I24+I25+I26)-(H24+H25+H26)) | J49: =-((J24+J25+J26)-(I24+I25+I26)) | K49: =-((K24+K25+K26)-(J24+J25+J26)) | ... W49: =-((W24+W25+W26)-(V24+V25+V26)) | X49: =SUM(D49:G49) | Y49: =SUM(H49:K49) | Z49: =SUM(L49:O49) | AA49: =SUM(P49:S49) | AB49: =SUM(T49:W49)
A50: Changes in Current Liabilities | B50: Formula | C50: =0 | D50: =(D32+D34)-(C32+C34) | E50: =(E32+E34)-(D32+D34) | F50: =(F32+F34)-(E32+E34) | G50: =(G32+G34)-(F32+F34) | H50: =(H32+H34)-(G32+G34) | I50: =(I32+I34)-(H32+H34) | J50: =(J32+J34)-(I32+I34) | K50: =(K32+K34)-(J32+J34) | ... W50: =(W32+W34)-(V32+V34) | X50: =SUM(D50:G50) | Y50: =SUM(H50:K50) | Z50: =SUM(L50:O50) | AA50: =SUM(P50:S50) | AB50: =SUM(T50:W50)
A51: Operating Cash Flow | B51: Formula | C51: =0 | D51: =SUM(D47:D50) | E51: =SUM(E47:E50) | F51: =SUM(F47:F50) | G51: =SUM(G47:G50) | H51: =SUM(H47:H50) | I51: =SUM(I47:I50) | J51: =SUM(J47:J50) | K51: =SUM(K47:K50) | ... W51: =SUM(W47:W50) | X51: =SUM(D51:G51) | Y51: =SUM(H51:K51) | Z51: =SUM(L51:O51) | AA51: =SUM(P51:S51) | AB51: =SUM(T51:W51)
A52: Capital Expenditures | B52: Formula | C52: ='Model Inputs'!C60 | D52: ='Model Inputs'!D60 | E52: ='Model Inputs'!E60 | F52: ='Model Inputs'!F60 | G52: ='Model Inputs'!G60 | H52: ='Model Inputs'!H60 | I52: ='Model Inputs'!I60 | J52: ='Model Inputs'!J60 | ... W52: ='Model Inputs'!W60 | X52: =SUM(D52:G52) | Y52: =SUM(H52:K52) | Z52: =SUM(L52:O52) | AA52: =SUM(P52:S52) | AB52: =SUM(T52:W52)
A53: Investing Cash Flow | B53: Formula | C53: =0 | D53: =-D52 | E53: =-E52 | F53: =-F52 | G53: =-G52 | H53: =-H52 | I53: =-I52 | J53: =-J52 | K53: =-K52 | ... W53: =-W52 | X53: =SUM(D53:G53) | Y53: =SUM(H53:K53) | Z53: =SUM(L53:O53) | AA53: =SUM(P53:S53) | AB53: =SUM(T53:W53)
A54: Debt Issuance (New Borrowing) | B54: Formula | C54: ='Model Inputs'!C50 | D54: ='Model Inputs'!D50 | E54: ='Model Inputs'!E50 | F54: ='Model Inputs'!F50 | G54: ='Model Inputs'!G50 | H54: ='Model Inputs'!H50 | I54: ='Model Inputs'!I50 | J54: ='Model Inputs'!J50 | ... W54: ='Model Inputs'!W50 | X54: =SUM(D54:G54) | Y54: =SUM(H54:K54) | Z54: =SUM(L54:O54) | AA54: =SUM(P54:S54) | AB54: =SUM(T54:W54)
A55: Debt Repayment | B55: Formula | C55: ='Model Inputs'!C51 | D55: ='Model Inputs'!D51 | E55: ='Model Inputs'!E51 | F55: ='Model Inputs'!F51 | G55: ='Model Inputs'!G51 | H55: ='Model Inputs'!H51 | I55: ='Model Inputs'!I51 | J55: ='Model Inputs'!J51 | ... W55: ='Model Inputs'!W51 | X55: =SUM(D55:G55) | Y55: =SUM(H55:K55) | Z55: =SUM(L55:O55) | AA55: =SUM(P55:S55) | AB55: =SUM(T55:W55)
A56: Equity | B56: Formula | C56: =0 | D56: =(D39-C39)+(D41-C41) | E56: =(E39-D39)+(E41-D41) | F56: =(F39-E39)+(F41-E41) | G56: =(G39-F39)+(G41-F41) | H56: =(H39-G39)+(H41-G41) | I56: =(I39-H39)+(I41-H41) | J56: =(J39-I39)+(J41-I41) | K56: =(K39-J39)+(K41-J41) | ... W56: =(W39-V39)+(W41-V41) | X56: =SUM(D56:G56) | Y56: =SUM(H56:K56) | Z56: =SUM(L56:O56) | AA56: =SUM(P56:S56) | AB56: =SUM(T56:W56)
A57: Distributions | B57: Formula | C57: ='Model Inputs'!C41 | D57: ='Model Inputs'!D41 | E57: ='Model Inputs'!E41 | F57: ='Model Inputs'!F41 | G57: ='Model Inputs'!G41 | H57: ='Model Inputs'!H41 | I57: ='Model Inputs'!I41 | J57: ='Model Inputs'!J41 | ... W57: ='Model Inputs'!W41 | X57: =SUM(D57:G57) | Y57: =SUM(H57:K57) | Z57: =SUM(L57:O57) | AA57: =SUM(P57:S57) | AB57: =SUM(T57:W57)
A58: Capital Lease Principal Payments | B58: Formula | C58: ='Model Inputs'!C54 | D58: ='Model Inputs'!D54 | E58: ='Model Inputs'!E54 | F58: ='Model Inputs'!F54 | G58: ='Model Inputs'!G54 | H58: ='Model Inputs'!H54 | I58: ='Model Inputs'!I54 | J58: ='Model Inputs'!J54 | ... W58: ='Model Inputs'!W54 | X58: =SUM(D58:G58) | Y58: =SUM(H58:K58) | Z58: =SUM(L58:O58) | AA58: =SUM(P58:S58) | AB58: =SUM(T58:W58)
A59: Financing Cash Flow | B59: Formula | C59: =0 | D59: =D54-D55+D56-D57-D58 | E59: =E54-E55+E56-E57-E58 | F59: =F54-F55+F56-F57-F58 | G59: =G54-G55+G56-G57-G58 | H59: =H54-H55+H56-H57-H58 | I59: =I54-I55+I56-I57-I58 | J59: =J54-J55+J56-J57-J58 | K59: =K54-K55+K56-K57-K58 | ... W59: =W54-W55+W56-W57-W58 | X59: =SUM(D59:G59) | Y59: =SUM(H59:K59) | Z59: =SUM(L59:O59) | AA59: =SUM(P59:S59) | AB59: =SUM(T59:W59)
A60: Net Cash Flow | B60: Formula | C60: =0 | D60: =D51+D53+D59 | E60: =E51+E53+E59 | F60: =F51+F53+F59 | G60: =G51+G53+G59 | H60: =H51+H53+H59 | I60: =I51+I53+I59 | J60: =J51+J53+J59 | K60: =K51+K53+K59 | ... W60: =W51+W53+W59 | X60: =SUM(D60:G60) | Y60: =SUM(H60:K60) | Z60: =SUM(L60:O60) | AA60: =SUM(P60:S60) | AB60: =SUM(T60:W60)
A61: Ending Cash | B61: Formula | C61: =C46+C60 | D61: =D46+D60 | E61: =E46+E60 | F61: =F46+F60 | G61: =G46+G60 | H61: =H46+H60 | I61: =I46+I60 | J61: =J46+J60 | ... W61: =W46+W60 | X61: =SUM(D61:G61) | Y61: =SUM(H61:K61) | Z61: =SUM(L61:O61) | AA61: =SUM(P61:S61) | AB61: =SUM(T61:W61)

Sheet Audit Source
A1: Audit Source
A2: Persisted system outputs used only for checks and audit tie-outs.
C4: Stub | D4: Q1 | E4: Q2 | F4: Q3 | G4: Q4 | H4: Q5 | I4: Q6 | J4: Q7 | K4: Q8 | L4: Q9 | M4: Q10 | N4: Q11 | O4: Q12 | P4: Q13 | Q4: Q14 | R4: Q15 | S4: Q16 | T4: Q17 | U4: Q18 | V4: Q19 | W4: Q20 | X4: Y1 | Y4: Y2 | Z4: Y3 | AA4: Y4 | AB4: Y5
C5: 46162 | D5: 46295 | E5: 46387 | F5: 46477 | G5: 46568 | H5: 46660 | I5: 46752 | J5: 46843 | K5: 46934 | L5: 47026 | M5: 47118 | N5: 47208 | O5: 47299 | P5: 47391 | Q5: 47483 | R5: 47573 | S5: 47664 | T5: 47756 | U5: 47848 | V5: 47938 | W5: 48029 | X5: Annual | Y5: Annual | Z5: Annual | AA5: Annual | AB5: Annual
A6: Income Statement
A7: Revenue | B7: Persisted FINMO | C7: 39300 | D7: 68744.55 | E7: 71989.293 | F7: 75307.363 | G7: 78698.761 | H7: 82163.486 | I7: 85701.539 | J7: 89312.919 | K7: 92997.627 | L7: 96755.663 | M7: 100587.03 | N7: 104491.72 | O7: 105713.84 | P7: 106935.97 | Q7: 108158.09 | R7: 109380.22 | S7: 110602.34 | T7: 111824.47 | U7: 113046.59 | V7: 114268.72 | W7: 121265.39
A8: Cost of Goods Sold | B8: Persisted FINMO | C8: 12576 | D8: 32997.384 | E8: 34122.925 | F8: 35243.846 | G8: 36358.828 | H8: 37466.55 | I8: 38565.693 | J8: 39654.936 | K8: 40732.961 | L8: 41798.446 | M8: 42850.073 | N8: 43886.521 | O8: 44164.894 | P8: 44437.835 | Q8: 44705.345 | R8: 44967.423 | S8: 45224.069 | T8: 45475.284 | U8: 45721.067 | V8: 45961.418 | W8: 48506.154
A9: Gross Profit | B9: Persisted FINMO | C9: 26724 | D9: 35747.166 | E9: 37866.368 | F9: 40063.517 | G9: 42339.933 | H9: 44696.937 | I9: 47135.847 | J9: 49657.983 | K9: 52264.667 | L9: 54957.216 | M9: 57736.953 | N9: 60605.195 | O9: 61548.948 | P9: 62498.132 | Q9: 63452.748 | R9: 64412.795 | S9: 65378.274 | T9: 66349.184 | U9: 67325.527 | V9: 68307.301 | W9: 72759.232
A10: Marketing | B10: Persisted FINMO | C10: 8646 | D10: 16498.692 | E10: 16413.559 | F10: 16266.39 | G10: 16054.547 | H10: 15775.389 | I10: 15426.277 | J10: 15004.57 | K10: 14507.63 | L10: 13932.815 | M10: 13277.487 | N10: 12539.006 | O10: 12215.822 | P10: 11881.774 | Q10: 11536.863 | R10: 11181.089 | S10: 10814.451 | T10: 10436.95 | U10: 10048.586 | V10: 9649.3585 | W10: 9701.2309
A11: Research & Development | B11: Persisted FINMO | C11: 0 | D11: 0 | E11: 0 | F11: 0 | G11: 0 | H11: 0 | I11: 0 | J11: 0 | K11: 0 | L11: 0 | M11: 0 | N11: 0 | O11: 0 | P11: 0 | Q11: 0 | R11: 0 | S11: 0 | T11: 0 | U11: 0 | V11: 0 | W11: 0
A12: Lease/Rent | B12: Persisted FINMO | C12: 3600 | D12: 3600 | E12: 3600 | F12: 3600 | G12: 3600 | H12: 3600 | I12: 3600 | J12: 3600 | K12: 3600 | L12: 3600 | M12: 3600 | N12: 3600 | O12: 3600 | P12: 3600 | Q12: 3600 | R12: 3600 | S12: 3600 | T12: 3600 | U12: 3600 | V12: 3600 | W12: 3600
A13: Payroll | B13: Persisted FINMO | C13: 27200 | D13: 29509 | E13: 29509 | F13: 29509 | G13: 29509 | H13: 30394 | I13: 30394 | J13: 30394 | K13: 30394 | L13: 31305 | M13: 31305 | N13: 31305 | O13: 31305 | P13: 32245 | Q13: 32245 | R13: 32245 | S13: 32245 | T13: 33212 | U13: 33212 | V13: 33212 | W13: 34688
A14: General & Administrative | B14: Persisted FINMO | C14: 212.4951 | D14: 16498.692 | E14: 16413.559 | F14: 16266.39 | G14: 16054.547 | H14: 15775.389 | I14: 15426.277 | J14: 15004.57 | K14: 14507.63 | L14: 13932.815 | M14: 13277.487 | N14: 12539.006 | O14: 12215.822 | P14: 11881.774 | Q14: 11536.863 | R14: 11181.089 | S14: 10814.451 | T14: 10436.95 | U14: 10048.586 | V14: 9649.3585 | W14: 9701.2309
A15: EBITDA | B15: Persisted FINMO | C15: -12934.495 | D15: -30359.218 | E15: -28069.749 | F15: -25578.264 | G15: -22878.161 | H15: -20847.842 | I15: -17710.708 | J15: -14345.158 | K15: -10744.593 | L15: -7813.4144 | M15: -3723.022 | N15: 622.18349 | O15: 2212.3043 | P15: 2889.5835 | Q15: 4534.0211 | R15: 6205.617 | S15: 7904.3711 | T15: 8663.2836 | U15: 10416.355 | V15: 12196.584 | W15: 15068.77
A16: Interest | B16: Persisted FINMO | C16: 0 | D16: 0 | E16: 0 | F16: 0 | G16: 0 | H16: 0 | I16: 0 | J16: 0 | K16: 0 | L16: 0 | M16: 0 | N16: 0 | O16: 0 | P16: 0 | Q16: 0 | R16: 0 | S16: 0 | T16: 0 | U16: 0 | V16: 0 | W16: 0
A17: Depreciation | B17: Persisted FINMO | C17: 0 | D17: 3.552 | E17: 7.119783 | F17: 10.700148 | G17: 14.314284 | H17: 17.934808 | I17: 21.570803 | J17: 25.231549 | K17: 28.901666 | L17: 32.578032 | M17: 36.27001 | N17: 39.974548 | O17: 43.688562 | P17: 47.421531 | Q17: 51.145115 | R17: 54.894051 | S17: 58.627187 | T17: 62.379355 | U17: 66.134605 | V17: 69.889645 | W17: 103.65158
A18: Taxes | B18: Persisted FINMO | C18: 0 | D18: 0 | E18: 0 | F18: 0 | G18: 0 | H18: 0 | I18: 0 | J18: 0 | K18: 0 | L18: 0 | M18: 0 | N18: 110.13297 | O18: 410.22403 | P18: 537.63472 | Q18: 847.99876 | R18: 1163.4954 | S18: 1484.1323 | T18: 1626.9815 | U18: 1957.889 | V18: 2293.934 | W18: 2830.8616
A19: Net Income | B19: Persisted FINMO | C19: -12934.495 | D19: -30362.77 | E19: -28076.869 | F19: -25588.964 | G19: -22892.475 | H19: -20865.777 | I19: -17732.278 | J19: -14370.389 | K19: -10773.495 | L19: -7845.9925 | M19: -3759.292 | N19: 472.07597 | O19: 1758.3917 | P19: 2304.5272 | Q19: 3634.8773 | R19: 4987.2276 | S19: 6361.6116 | T19: 6973.9228 | U19: 8392.3311 | V19: 9832.7603 | W19: 12134.257
A22: Balance Sheet
A23: Cash | B23: Persisted FINMO | C23: 10000 | D23: 49551.981 | E23: 50029.719 | F23: 50443.666 | G23: 50788.104 | H23: 51505.517 | I23: 51706.112 | J23: 51830.024 | K23: 51872.338 | L23: 52283.528 | M23: 52154.688 | N23: 51933.555 | O23: 53180.345 | P23: 55285.977 | Q23: 58382.972 | R23: 62746.303 | S23: 68466.168 | T23: 68774.166 | U23: 68420.2 | V23: 68048.435 | W23: 70798.083
A24: Accounts Receivable | B24: Persisted FINMO | C24: 0 | D24: 11208.351 | E24: 11737.385 | F24: 12551.227 | G24: 12972.323 | H24: 13396.221 | I24: 13973.077 | J24: 14721.91 | K24: 15329.279 | L24: 15775.38 | M24: 16400.059 | N24: 17415.286 | O24: 17425.358 | P24: 17435.212 | Q24: 17634.472 | R24: 18230.036 | S24: 18231.155 | T24: 18232.25 | U24: 18431.51 | V24: 19044.786 | W24: 19988.8
A25: Inventory | B25: Persisted FINMO | C25: 3000 | D25: 3586.6722 | E25: 3709.0136 | F25: 3915.9829 | G25: 3995.4756 | H25: 4072.4511 | I25: 4191.9231 | J25: 4357.6853 | K25: 4476.1495 | L25: 4543.3094 | M25: 4657.6166 | N25: 4876.2801 | O25: 4853.285 | P25: 4830.1995 | Q25: 4859.2766 | R25: 4996.3803 | S25: 4969.6779 | T25: 4942.9656 | U25: 4969.6812 | V25: 5106.8242 | W25: 5330.3466
A26: Current Assets | B26: Persisted FINMO | C26: 13000 | D26: 67784.232 | E26: 69075.582 | F26: 70676.245 | G26: 71690.841 | H26: 73082.363 | I26: 74156.189 | J26: 75375.265 | K26: 76327.648 | L26: 77440.001 | M26: 78241.714 | N26: 79449.707 | O26: 80744.68 | P26: 82898.187 | Q26: 86284.625 | R26: 91441.73 | S26: 97197.119 | T26: 97540.605 | U26: 97473.721 | V26: 97913.482 | W26: 102180.5
A27: PPE | B27: Persisted FINMO | C27: 12000 | D27: 12067.428 | E27: 12131.687 | F27: 12192.746 | G27: 12250.552 | H27: 12305.079 | I27: 12356.293 | J27: 12404.149 | K27: 12448.617 | L27: 12489.673 | M27: 12527.279 | N27: 12561.404 | O27: 12592.016 | P27: 12619.076 | Q27: 12642.573 | R27: 12662.46 | S27: 12678.731 | T27: 12691.346 | U27: 12700.281 | V27: 12705.513 | W27: 13277.015
A28: Accumulated Depreciation | B28: Persisted FINMO | C28: 0 | D28: -3.552 | E28: -10.671783 | F28: -21.371931 | G28: -35.686214 | H28: -53.621022 | I28: -75.191825 | J28: -100.42337 | K28: -129.32504 | L28: -161.90307 | M28: -198.17308 | N28: -238.14763 | O28: -281.83619 | P28: -329.25772 | Q28: -380.40284 | R28: -435.29689 | S28: -493.92408 | T28: -556.30343 | U28: -622.43804 | V28: -692.32768 | W28: -795.97926
A29: Total Assets | B29: Persisted FINMO | C29: 25000 | D29: 79851.66 | E29: 81207.269 | F29: 82868.991 | G29: 83941.392 | H29: 85387.442 | I29: 86512.482 | J29: 87779.413 | K29: 88776.266 | L29: 89929.674 | M29: 90768.994 | N29: 92011.111 | O29: 93336.696 | P29: 95517.263 | Q29: 98927.198 | R29: 104104.19 | S29: 109875.85 | T29: 110231.95 | U29: 110174 | V29: 110619 | W29: 115457.51
A30: Accounts Payable | B30: Persisted FINMO | C30: 1200 | D30: 21556.43 | E30: 21500.908 | F30: 21880.594 | G30: 21500.471 | H30: 21373.297 | I30: 21145.615 | J30: 21099.937 | K30: 20772.283 | L30: 20468.684 | M30: 20041.296 | N30: 19994.337 | O30: 19561.531 | P30: 19437.57 | Q30: 19212.628 | R30: 19402.393 | S30: 18947.44 | T30: 18810.62 | U30: 18557.339 | V30: 18703.572 | W30: 19018.834
A31: Prepaid Expenses (% of Revenue) | B31: Persisted FINMO | C31: 0 | D31: 3437.2275 | E31: 3599.4646 | F31: 3765.3682 | G31: 3934.938 | H31: 4108.1743 | I31: 4285.077 | J31: 4465.646 | K31: 4649.8814 | L31: 4837.7831 | M31: 5029.3513 | N31: 5224.5858 | O31: 5285.6921 | P31: 5346.7983 | Q31: 5407.9046 | R31: 5469.0109 | S31: 5530.1171 | T31: 5591.2234 | U31: 5652.3297 | V31: 5713.4359 | W31: 6063.2693
A32: Short Term Debt | B32: Persisted FINMO | C32: 0 | D32: 0 | E32: 0 | F32: 0 | G32: 0 | H32: 0 | I32: 0 | J32: 0 | K32: 0 | L32: 0 | M32: 0 | N32: 0 | O32: 0 | P32: 0 | Q32: 0 | R32: 0 | S32: 0 | T32: 0 | U32: 0 | V32: 0 | W32: 0
A33: Deferred Revenue (% of Revenue) | B33: Persisted FINMO | C33: 0 | D33: 0 | E33: 0 | F33: 0 | G33: 0 | H33: 0 | I33: 0 | J33: 0 | K33: 0 | L33: 0 | M33: 0 | N33: 0 | O33: 0 | P33: 0 | Q33: 0 | R33: 0 | S33: 0 | T33: 0 | U33: 0 | V33: 0 | W33: 0
A34: Current Liabilites | B34: Persisted FINMO | C34: 1200 | D34: 21556.43 | E34: 21500.908 | F34: 21880.594 | G34: 21500.471 | H34: 21373.297 | I34: 21145.615 | J34: 21099.937 | K34: 20772.283 | L34: 20468.684 | M34: 20041.296 | N34: 19994.337 | O34: 19561.531 | P34: 19437.57 | Q34: 19212.628 | R34: 19402.393 | S34: 18947.44 | T34: 18810.62 | U34: 18557.339 | V34: 18703.572 | W34: 19018.834
... A41: Total Liabilities & Equity | B41: Persisted FINMO | C41: 25000 | D41: 79851.66 | E41: 81207.269 | F41: 82868.991 | G41: 83941.392 | H41: 85387.442 | I41: 86512.482 | J41: 87779.413 | K41: 88776.266 | L41: 89929.674 | M41: 90768.994 | N41: 92011.111 | O41: 93336.696 | P41: 95517.263 | Q41: 98927.198 | R41: 104104.19 | S41: 109875.85 | T41: 110231.95 | U41: 110174 | V41: 110619 | W41: 115457.51
A44: Cash Flow
A45: Beginning Cash | B45: Persisted FINMO | C45: 10000 | D45: 10000 | E45: 49551.981 | F45: 50029.719 | G45: 50443.666 | H45: 50788.104 | I45: 51505.517 | J45: 51706.112 | K45: 51830.024 | L45: 51872.338 | M45: 52283.528 | N45: 52154.688 | O45: 51933.555 | P45: 53180.345 | Q45: 55285.977 | R45: 58382.972 | S45: 62746.303 | T45: 68466.168 | U45: 68774.166 | V45: 68420.2 | W45: 68048.435
A46: Net Income | B46: Persisted FINMO | C46: -12934.495 | D46: -30362.77 | E46: -28076.869 | F46: -25588.964 | G46: -22892.475 | H46: -20865.777 | I46: -17732.278 | J46: -14370.389 | K46: -10773.495 | L46: -7845.9925 | M46: -3759.292 | N46: 472.07597 | O46: 1758.3917 | P46: 2304.5272 | Q46: 3634.8773 | R46: 4987.2276 | S46: 6361.6116 | T46: 6973.9228 | U46: 8392.3311 | V46: 9832.7603 | W46: 12134.257
A47: Depreciatoin | B47: Persisted FINMO | C47: 0 | D47: 3.552 | E47: 7.119783 | F47: 10.700148 | G47: 14.314284 | H47: 17.934808 | I47: 21.570803 | J47: 25.231549 | K47: 28.901666 | L47: 32.578032 | M47: 36.27001 | N47: 39.974548 | O47: 43.688562 | P47: 47.421531 | Q47: 51.145115 | R47: 54.894051 | S47: 58.627187 | T47: 62.379355 | U47: 66.134605 | V47: 69.889645 | W47: 103.65158
A48: Changes in Current Assets | B48: Persisted FINMO | C48: 0 | D48: -15232.25 | E48: -813.61267 | F48: -1186.7153 | G48: -670.1586 | H48: -674.10912 | I48: -873.23113 | J48: -1095.164 | K48: -910.06906 | L48: -701.16218 | M48: -930.55413 | N48: -1429.1255 | O48: -48.18364 | P48: -47.874168 | Q48: -289.44308 | R48: -793.77464 | S48: -35.523012 | T48: -35.48877 | U48: -287.08148 | V48: -811.52596 | W48: -1517.3692
A49: Changes in Current Liabilites | B49: Persisted FINMO | C49: 0 | D49: 20356.43 | E49: -55.521685 | F49: 379.68573 | G49: -380.12292 | H49: -127.17329 | I49: -227.68195 | J49: -45.678886 | K49: -327.65314 | L49: -303.59945 | M49: -427.38786 | N49: -46.958834 | O49: -432.80652 | P49: -123.96073 | Q49: -224.94188 | R49: 189.76444 | S49: -454.95219 | T49: -136.82062 | U49: -253.28102 | V49: 146.23356 | W49: 315.26123
A50: Operating Cash Flow | B50: Persisted FINMO | C50: 0 | D50: -25235.039 | E50: -28938.884 | F50: -26385.293 | G50: -23928.443 | H50: -21649.125 | I50: -18811.621 | J50: -15486.001 | K50: -11982.315 | L50: -8818.176 | M50: -5080.964 | N50: -964.03378 | O50: 1321.0901 | P50: 2180.1138 | Q50: 3171.6374 | R50: 4438.1114 | S50: 5929.7636 | T50: 6863.9928 | U50: 7918.1032 | V50: 9237.3575 | W50: 11035.8
A51: Capital Expenditures | B51: Persisted FINMO | C51: 0 | D51: 70.98 | E51: 71.378837 | F51: 71.758929 | G51: 72.120092 | H51: 72.462013 | I51: 72.784541 | J51: 73.087471 | K51: 73.370538 | L51: 73.633572 | M51: 73.876415 | N51: 74.098857 | O51: 74.300702 | P51: 74.481773 | Q51: 74.641835 | R51: 74.780818 | S51: 74.898448 | T51: 74.994692 | U51: 75.069312 | V51: 75.122161 | W51: 675.1531
A52: Investing Cash Flow | B52: Persisted FINMO | C52: 0 | D52: -70.98 | E52: -71.378837 | F52: -71.758929 | G52: -72.120092 | H52: -72.462013 | I52: -72.784541 | J52: -73.087471 | K52: -73.370538 | L52: -73.633572 | M52: -73.876415 | N52: -74.098857 | O52: -74.300702 | P52: -74.481773 | Q52: -74.641835 | R52: -74.780818 | S52: -74.898448 | T52: -74.994692 | U52: -75.069312 | V52: -75.122161 | W52: -675.1531
A53: Debt Issuance (New Borrowing) | B53: Persisted FINMO | C53: 0 | D53: 0 | E53: 0 | F53: 0 | G53: 0 | H53: 0 | I53: 0 | J53: 0 | K53: 0 | L53: 0 | M53: 0 | N53: 0 | O53: 0 | P53: 0 | Q53: 0 | R53: 0 | S53: 0 | T53: 0 | U53: 0 | V53: 0 | W53: 0
A54: Debt Repayment | B54: Persisted FINMO | C54: 0 | D54: 0 | E54: 0 | F54: 0 | G54: 0 | H54: 0 | I54: 0 | J54: 0 | K54: 0 | L54: 0 | M54: 0 | N54: 0 | O54: 0 | P54: 0 | Q54: 0 | R54: 0 | S54: 0 | T54: 0 | U54: 0 | V54: 0 | W54: 0
A55: Equity | B55: Persisted FINMO | C55: 0 | D55: 64858 | E55: 29488 | F55: 26871 | G55: 24345 | H55: 22439 | I55: 19085 | J55: 15683 | K55: 12098 | L55: 9303 | M55: 5026 | N55: 817 | O55: 0 | P55: 0 | Q55: 0 | R55: 0 | S55: 0 | T55: 0 | U55: 0 | V55: 0 | W55: 0
A56: Distributions | B56: Persisted FINMO | C56: 0 | D56: 0 | E56: 0 | F56: 0 | G56: 0 | H56: 0 | I56: 0 | J56: 0 | K56: 0 | L56: 0 | M56: 0 | N56: 0 | O56: 0 | P56: 0 | Q56: 0 | R56: 0 | S56: 135 | T56: 6481 | U56: 8197 | V56: 9534 | W56: 7611
... A59: Ending Cash | B59: Persisted FINMO | C59: 10000 | D59: 49551.981 | E59: 50029.719 | F59: 50443.666 | G59: 50788.104 | H59: 51505.517 | I59: 51706.112 | J59: 51830.024 | K59: 51872.338 | L59: 52283.528 | M59: 52154.688 | N59: 51933.555 | O59: 53180.345 | P59: 55285.977 | Q59: 58382.972 | R59: 62746.303 | S59: 68466.168 | T59: 68774.166 | U59: 68420.2 | V59: 68048.435 | W59: 70798.083

Sheet Checks
A1: Checks
A2: Model Status | B2: =IF(COUNTIF(I7:I182,"FAIL")=0,"OK","FAIL")
A3: Rule | B3: Only real formula/coherence failures return FAIL. Baseline scenario changes show CHANGED.
A5: Category | B5: Line Item | C5: Sheet | D5: Range / Cell | E5: Actual | F5: Expected | G5: Difference | H5: Tolerance | I5: Status | J5: Notes
A6: Model Coherence Checks
A7: Statement Coherence | B7: Balance Sheet balances Q1 | C7: Cross-sheet | D7: 'FINMO'!D31 | E7: ='FINMO'!D31 | F7: ='FINMO'!D43 | G7: =E7-F7 | H7: 1 | I7: =IF(ABS(G7)<=H7,"OK","FAIL") | J7: Total assets must equal total liabilities and equity.
A8: Statement Coherence | B8: Cash Flow ties to Balance Sheet Q1 | C8: Cross-sheet | D8: 'FINMO'!D61 | E8: ='FINMO'!D61 | F8: ='FINMO'!D23 | G8: =E8-F8 | H8: 1 | I8: =IF(ABS(G8)<=H8,"OK","FAIL") | J8: Ending cash must tie to balance-sheet cash.
A9: Statement Coherence | B9: Balance Sheet balances Q20 | C9: Cross-sheet | D9: 'FINMO'!W31 | E9: ='FINMO'!W31 | F9: ='FINMO'!W43 | G9: =E9-F9 | H9: 1 | I9: =IF(ABS(G9)<=H9,"OK","FAIL") | J9: Total assets must equal total liabilities and equity.
A10: Statement Coherence | B10: Cash Flow ties to Balance Sheet Q20 | C10: Cross-sheet | D10: 'FINMO'!W61 | E10: ='FINMO'!W61 | F10: ='FINMO'!W23 | G10: =E10-F10 | H10: 1 | I10: =IF(ABS(G10)<=H10,"OK","FAIL") | J10: Ending cash must tie to balance-sheet cash.
A11: Schedule Bridge | B11: Revenue Drivers total feeds Model Inputs Revenue | C11: Cross-sheet | D11: 'Revenue Drivers'!C26:W26 | E11: =SUMPRODUCT(ABS('Revenue Drivers'!C26:W26-'Model Inputs'!C19:W19)) | F11: 0 | G11: =E11-F11 | H11: 1 | I11: =IF(ABS(G11)<=H11,"OK","FAIL") | J11: Changing Revenue Drivers should update Model Inputs and FINMO without creating a model failure.
A12: Schedule Bridge | B12: Payroll Schedule total feeds Model Inputs Payroll | C12: Cross-sheet | D12: 'Payroll Schedule'!D17:W17 | E12: =SUMPRODUCT(ABS('Payroll Schedule'!D17:W17-'Model Inputs'!D24:W24)) | F12: 0 | G12: =E12-F12 | H12: 1 | I12: =IF(ABS(G12)<=H12,"OK","FAIL") | J12: Changing payroll detail should update payroll summary, Model Inputs, and FINMO payroll.
A13: Schedule Bridge | B13: Debt repayment feeds Model Inputs | C13: Cross-sheet | D13: 'Debt Schedule'!C10:W10 | E13: =SUMPRODUCT(ABS('Debt Schedule'!C10:W10-'Model Inputs'!C51:W51)) | F13: 0 | G13: =E13-F13 | H13: 1 | I13: =IF(ABS(G13)<=H13,"OK","FAIL") | J13: Debt repayment must flow through the model from actual mechanically capped repayment.
A14: Schedule Bridge | B14: Capital lease additions feed CapEx schedule | C14: Cross-sheet | D14: 'Debt Schedule'!C21:W21 | E14: =SUMPRODUCT(ABS('Debt Schedule'!C21:W21-'CapEx Depreciation'!C9:W9)) | F14: 0 | G14: =E14-F14 | H14: 1 | I14: =IF(ABS(G14)<=H14,"OK","FAIL") | J14: Lease additions must affect PPE/depreciation through the CapEx schedule.
A15: Schedule Bridge | B15: Lease/rent feeds Model Inputs | C15: Cross-sheet | D15: 'Cash Equity Schedule'!C12:W12 | E15: =SUMPRODUCT(ABS('Cash Equity Schedule'!C12:W12-'Model Inputs'!C23:W23)) | F15: 0 | G15: =E15-F15 | H15: 1 | I15: =IF(ABS(G15)<=H15,"OK","FAIL") | J15: Operating lease/rent must flow through Model Inputs into FINMO.
A16: Schedule Coherence | B16: Payroll summary totals equal payroll detail by quarter | C16: Payroll Schedule | D16: A27:N66 | E16: =SUM(ABS('Payroll Schedule'!C15-SUMIFS('Payroll Schedule'!$G$27:$G$66,'Payroll Schedule'!$A$27:$A$66,0)),ABS('Payroll Schedule'!C16-SUMIFS('Payroll Schedule'!$H$27:$H$66,'Payroll Schedule'!$A$27:$A$66,0)),ABS('Payroll Schedule'!C17-SUMIFS('Payroll Schedule'!$M$27:$M$66,'Payroll Schedule'!$A$27:$A$66,0)),ABS('Payroll Schedule'!D15-SUMIFS('Payroll Schedule'!$G$27:$G$66,'Payroll Schedule'!$A$27:$A$66,1)),ABS('Payroll Schedule'!D16-SUMIFS('Payroll Schedule'!$H$27:$H$66,'Payroll Schedule'!$A$27:$A$66,1)),ABS('Payroll Schedule'!D17-SUMIFS('Payroll Schedule'!$M$27:$M$66,'Payroll Schedule'!$A$27:$A$66,1)),ABS('Payroll Schedule'!E15-SUMIFS('Payroll Schedule'!$G$27:$G$66,'Payroll Schedule'!$A$27:$A$66,2)),ABS('Payroll Schedule'!E16-SUMIFS('Payroll Schedule'!$H$27:$H$66,'Payroll Schedule'!$A$27:$A$66,2)),ABS('Payroll Schedule'!E17-SUMIFS('Payroll Schedule'!$M$27:$M$66,'Payroll Schedule'!$A$27:$A$66,2)),ABS('Payroll Schedule'!F15-SUMIFS('Payroll Schedule'!$G$27:$G$66,'Payroll Schedule'!$A$27:$A$66,3)),ABS('Payroll Schedule'!F16-SUMIFS('Payroll Schedule'!$H$27:$H$66,'Payroll Schedule'!$A$27:$A$66,3)),ABS('Payroll Schedule'!F17-SUMIFS('Payroll Schedule'!$M$27:$M$66,'Payroll Schedule'!$A$27:$A$66,3)),ABS('Payroll Schedule'!G15-SUMIFS('Payroll Schedule'!$G$27:$G$66,'Payroll Schedule'!$A$27:$A$66,4)),ABS('Payroll Schedule'!G16-SUMIFS('Payroll Schedule'!$H$27:$H$66,'Payroll Schedule'!$A$27:$A$66,4)),ABS('Payroll Schedule'!G17-SUMIFS('Payroll Schedule'!$M$27:$M$66,'Payroll Schedule'!$A$27:$A$66,4)),ABS('Payroll Schedule'!H15-SUMIFS('Payroll Schedule'!$G$27:$G$66,'Payroll Schedule'!$A$27:$A$66,5)),ABS('Payroll Schedule'!H16-SUMIFS('Payroll Schedule'!$H$27:$H$66,'Payroll Schedule'!$A$27:$A$66,5)),ABS('Payroll Schedule'!H17-SUMIFS('Payroll Schedule'!$M$27:$M$66,'Payroll Schedule'!$A$27:$A$66,5)),ABS('Payroll Schedule'!I15-SUMIFS('Payroll Schedule'!$G$27:$G$66,'Payroll Schedule'!$A$27:$A$66,6)),ABS('Payroll Schedule'!I16-SUMIFS('Payroll Schedule'!$H$27:$H$66,'Payroll Schedule'!$A$27:$A$66,6)),ABS('Payroll Schedule'!I17-SUMIFS('Payroll Schedule'!$M$27:$M$66,'Payroll Schedule'!$A$27:$A$66,6)),ABS('Payroll Schedule'!J15-SUMIFS('Payroll Schedule'!$G$27:$G$66,'Payroll Schedule'!$A$27:$A$66,7)),ABS('Payroll Schedule'!J16-SUMIFS('Payroll Schedule'!$H$27:$H$66,'Payroll Schedule'!$A$27:$A$66,7)),ABS('Payroll Schedule'!J17-SUMIFS('Payroll Schedule'!$M$27:$M$66,'Payroll Schedule'!$A$27:$A$66,7)),ABS('Payroll Schedule'!K15-SUMIFS('Payroll Schedule'!$G$27:$G$66,'Payroll Schedule'!$A$27:$A$66,8)),ABS('Payroll Schedule'!K16-SUMIFS('Payroll Schedule'!$H$27:$H$66,'Payroll Schedule'!$A$27:$A$66,8)),ABS('Payroll Schedule'!K17-SUMIFS('Payroll Schedule'!$M$27:$M$66,'Payroll Schedule'!$A$27:$A$66,8)),ABS('Payroll Schedule'!L15-SUMIFS('Payroll Schedule'!$G$27:$G$66,'Payroll Schedule'!$A$27:$A$66,9)),ABS('Payroll Schedule'!L16-SUMIFS('Payroll Schedule'!$H$27:$H$66,'Payroll Schedule'!$A$27:$A$66,9)),ABS('Payroll Schedule'!L17-SUMIFS('Payroll Schedule'!$M$27:$M$66,'Payroll Schedule'!$A$27:$A$66,9)),ABS('Payroll Schedule'!M15-SUMIFS('Payroll Schedule'!$G$27:$G$66,'Payroll Schedule'!$A$27:$A$66,10)),ABS('Payroll Schedule'!M16-SUMIFS('Payroll Schedule'!$H$27:$H$66,'Payroll Schedule'!$A$27:$A$66,10)),ABS('Payroll Schedule'!M17-SUMIFS('Payroll Schedule'!$M$27:$M$66,'Payroll Schedule'!$A$27:$A$66,10)),ABS('Payroll Schedule'!N15-SUMIFS('Payroll Schedule'!$G$27:$G$66,'Payroll Schedule'!$A$27:$A$66,11)),ABS('Payroll Schedule'!N16-SUMIFS('Payroll Schedule'!$H$27:$H$66,'Payroll Schedule'!$A$27:$A$66,11)),ABS('Payroll Schedule'!N17-SUMIFS('Payroll Schedule'!$M$27:$M$66,'Payroll Schedule'!$A$27:$A$66,11)),ABS('Payroll Schedule'!O15-SUMIFS('Payroll Schedule'!$G$27:$G$66,'Payroll Schedule'!$A$27:$A$66,12)),ABS('Payroll Schedule'!O16-SUMIFS('Payroll Schedule'!$H$27:$H$66,'Payroll Schedule'!$A$27:$A$66,12)),ABS('Payroll Schedule'!O17-SUMIFS('Payroll Schedule'!$M$27:$M$66,'Payroll Schedule'!$A$27:$A$66,12)),ABS('Payroll Schedule'!P15-SUMIFS('Payroll Schedule'!$G$27:$G$66,'Payroll Schedule'!$A$27:$A$66,13)),ABS('Payroll Schedule'!P16-SUMIFS('Payroll Schedule'!$H$27:$H$66,'Payroll Schedule'!$A$27:$A$66,13)),ABS('Payroll Schedule'!P17-SUMIFS('Payroll Schedule'!$M$27:$M$66,'Payroll Schedule'!$A$27:$A$66,13)),ABS('Payroll Schedule'!Q15-SUMIFS('Payroll Schedule'!$G$27:$G$66,'Payroll Schedule'!$A$27:$A$66,14)),ABS('Payroll Schedule'!Q16-SUMIFS('Payroll Schedule'!$H$27:$H$66,'Payroll Schedule'!$A$27:$A$66,14)),ABS('Payroll Schedule'!Q17-SUMIFS('Payroll Schedule'!$M$27:$M$66,'Payroll Schedule'!$A$27:$A$66,14)),ABS('Payroll Schedule'!R15-SUMIFS('Payroll Schedule'!$G$27:$G$66,'Payroll Schedule'!$A$27:$A$66,15)),ABS('Payroll Schedule'!R16-SUMIFS('Payroll Schedule'!$H$27:$H$66,'Payroll Schedule'!$A$27:$A$66,15)),ABS('Payroll Schedule'!R17-SUMIFS('Payroll Schedule'!$M$27:$M$66,'Payroll Schedule'!$A$27:$A$66,15)),ABS('Payroll Schedule'!S15-SUMIFS('Payroll Schedule'!$G$27:$G$66,'Payroll Schedule'!$A$27:$A$66,16)),ABS('Payroll Schedule'!S16-SUMIFS('Payroll Schedule'!$H$27:$H$66,'Payroll Schedule'!$A$27:$A$66,16)),ABS('Payroll Schedule'!S17-SUMIFS('Payroll Schedule'!$M$27:$M$66,'Payroll Schedule'!$A$27:$A$66,16)),ABS('Payroll Schedule'!T15-SUMIFS('Payroll Schedule'!$G$27:$G$66,'Payroll Schedule'!$A$27:$A$66,17)),ABS('Payroll Schedule'!T16-SUMIFS('Payroll Schedule'!$H$27:$H$66,'Payroll Schedule'!$A$27:$A$66,17)),ABS('Payroll Schedule'!T17-SUMIFS('Payroll Schedule'!$M$27:$M$66,'Payroll Schedule'!$A$27:$A$66,17)),ABS('Payroll Schedule'!U15-SUMIFS('Payroll Schedule'!$G$27:$G$66,'Payroll Schedule'!$A$27:$A$66,18)),ABS('Payroll Schedule'!U16-SUMIFS('Payroll Schedule'!$H$27:$H$66,'Payroll Schedule'!$A$27:$A$66,18)),ABS('Payroll Schedule'!U17-SUMIFS('Payroll Schedule'!$M$27:$M$66,'Payroll Schedule'!$A$27:$A$66,18)),ABS('Payroll Schedule'!V15-SUMIFS('Payroll Schedule'!$G$27:$G$66,'Payroll Schedule'!$A$27:$A$66,19)),ABS('Payroll Schedule'!V16-SUMIFS('Payroll Schedule'!$H$27:$H$66,'Payroll Schedule'!$A$27:$A$66,19)),ABS('Payroll Schedule'!V17-SUMIFS('Payroll Schedule'!$M$27:$M$66,'Payroll Schedule'!$A$27:$A$66,19)),ABS('Payroll Schedule'!W15-SUMIFS('Payroll Schedule'!$G$27:$G$66,'Payroll Schedule'!$A$27:$A$66,20)),ABS('Payroll Schedule'!W16-SUMIFS('Payroll Schedule'!$H$27:$H$66,'Payroll Schedule'!$A$27:$A$66,20)),ABS('Payroll Schedule'!W17-SUMIFS('Payroll Schedule'!$M$27:$M$66,'Payroll Schedule'!$A$27:$A$66,20))) | F16: 0 | G16: =E16-F16 | H16: 1 | I16: =IF(ABS(G16)<=H16,"OK","FAIL") | J16: If this fails, payroll summary is no longer tied to detail FTE/payroll rows.
A17: Schedule Coherence | B17: Payroll productivity metrics | C17: Payroll Schedule | D17: A16:W22 | E17: =SUM(ABS('Payroll Schedule'!C20-IFERROR('Payroll Schedule'!C18/'Payroll Schedule'!C16,0)),ABS('Payroll Schedule'!C21-IFERROR('Payroll Schedule'!C19/'Payroll Schedule'!C16,0)),ABS('Payroll Schedule'!C22-IFERROR('Payroll Schedule'!C17/'Payroll Schedule'!C18,0)),ABS('Payroll Schedule'!D20-IFERROR('Payroll Schedule'!D18/'Payroll Schedule'!D16,0)),ABS('Payroll Schedule'!D21-IFERROR('Payroll Schedule'!D19/'Payroll Schedule'!D16,0)),ABS('Payroll Schedule'!D22-IFERROR('Payroll Schedule'!D17/'Payroll Schedule'!D18,0)),ABS('Payroll Schedule'!E20-IFERROR('Payroll Schedule'!E18/'Payroll Schedule'!E16,0)),ABS('Payroll Schedule'!E21-IFERROR('Payroll Schedule'!E19/'Payroll Schedule'!E16,0)),ABS('Payroll Schedule'!E22-IFERROR('Payroll Schedule'!E17/'Payroll Schedule'!E18,0)),ABS('Payroll Schedule'!F20-IFERROR('Payroll Schedule'!F18/'Payroll Schedule'!F16,0)),ABS('Payroll Schedule'!F21-IFERROR('Payroll Schedule'!F19/'Payroll Schedule'!F16,0)),ABS('Payroll Schedule'!F22-IFERROR('Payroll Schedule'!F17/'Payroll Schedule'!F18,0)),ABS('Payroll Schedule'!G20-IFERROR('Payroll Schedule'!G18/'Payroll Schedule'!G16,0)),ABS('Payroll Schedule'!G21-IFERROR('Payroll Schedule'!G19/'Payroll Schedule'!G16,0)),ABS('Payroll Schedule'!G22-IFERROR('Payroll Schedule'!G17/'Payroll Schedule'!G18,0)),ABS('Payroll Schedule'!H20-IFERROR('Payroll Schedule'!H18/'Payroll Schedule'!H16,0)),ABS('Payroll Schedule'!H21-IFERROR('Payroll Schedule'!H19/'Payroll Schedule'!H16,0)),ABS('Payroll Schedule'!H22-IFERROR('Payroll Schedule'!H17/'Payroll Schedule'!H18,0)),ABS('Payroll Schedule'!I20-IFERROR('Payroll Schedule'!I18/'Payroll Schedule'!I16,0)),ABS('Payroll Schedule'!I21-IFERROR('Payroll Schedule'!I19/'Payroll Schedule'!I16,0)),ABS('Payroll Schedule'!I22-IFERROR('Payroll Schedule'!I17/'Payroll Schedule'!I18,0)),ABS('Payroll Schedule'!J20-IFERROR('Payroll Schedule'!J18/'Payroll Schedule'!J16,0)),ABS('Payroll Schedule'!J21-IFERROR('Payroll Schedule'!J19/'Payroll Schedule'!J16,0)),ABS('Payroll Schedule'!J22-IFERROR('Payroll Schedule'!J17/'Payroll Schedule'!J18,0)),ABS('Payroll Schedule'!K20-IFERROR('Payroll Schedule'!K18/'Payroll Schedule'!K16,0)),ABS('Payroll Schedule'!K21-IFERROR('Payroll Schedule'!K19/'Payroll Schedule'!K16,0)),ABS('Payroll Schedule'!K22-IFERROR('Payroll Schedule'!K17/'Payroll Schedule'!K18,0)),ABS('Payroll Schedule'!L20-IFERROR('Payroll Schedule'!L18/'Payroll Schedule'!L16,0)),ABS('Payroll Schedule'!L21-IFERROR('Payroll Schedule'!L19/'Payroll Schedule'!L16,0)),ABS('Payroll Schedule'!L22-IFERROR('Payroll Schedule'!L17/'Payroll Schedule'!L18,0)),ABS('Payroll Schedule'!M20-IFERROR('Payroll Schedule'!M18/'Payroll Schedule'!M16,0)),ABS('Payroll Schedule'!M21-IFERROR('Payroll Schedule'!M19/'Payroll Schedule'!M16,0)),ABS('Payroll Schedule'!M22-IFERROR('Payroll Schedule'!M17/'Payroll Schedule'!M18,0)),ABS('Payroll Schedule'!N20-IFERROR('Payroll Schedule'!N18/'Payroll Schedule'!N16,0)),ABS('Payroll Schedule'!N21-IFERROR('Payroll Schedule'!N19/'Payroll Schedule'!N16,0)),ABS('Payroll Schedule'!N22-IFERROR('Payroll Schedule'!N17/'Payroll Schedule'!N18,0)),ABS('Payroll Schedule'!O20-IFERROR('Payroll Schedule'!O18/'Payroll Schedule'!O16,0)),ABS('Payroll Schedule'!O21-IFERROR('Payroll Schedule'!O19/'Payroll Schedule'!O16,0)),ABS('Payroll Schedule'!O22-IFERROR('Payroll Schedule'!O17/'Payroll Schedule'!O18,0)),ABS('Payroll Schedule'!P20-IFERROR('Payroll Schedule'!P18/'Payroll Schedule'!P16,0)),ABS('Payroll Schedule'!P21-IFERROR('Payroll Schedule'!P19/'Payroll Schedule'!P16,0)),ABS('Payroll Schedule'!P22-IFERROR('Payroll Schedule'!P17/'Payroll Schedule'!P18,0)),ABS('Payroll Schedule'!Q20-IFERROR('Payroll Schedule'!Q18/'Payroll Schedule'!Q16,0)),ABS('Payroll Schedule'!Q21-IFERROR('Payroll Schedule'!Q19/'Payroll Schedule'!Q16,0)),ABS('Payroll Schedule'!Q22-IFERROR('Payroll Schedule'!Q17/'Payroll Schedule'!Q18,0)),ABS('Payroll Schedule'!R20-IFERROR('Payroll Schedule'!R18/'Payroll Schedule'!R16,0)),ABS('Payroll Schedule'!R21-IFERROR('Payroll Schedule'!R19/'Payroll Schedule'!R16,0)),ABS('Payroll Schedule'!R22-IFERROR('Payroll Schedule'!R17/'Payroll Schedule'!R18,0)),ABS('Payroll Schedule'!S20-IFERROR('Payroll Schedule'!S18/'Payroll Schedule'!S16,0)),ABS('Payroll Schedule'!S21-IFERROR('Payroll Schedule'!S19/'Payroll Schedule'!S16,0)),ABS('Payroll Schedule'!S22-IFERROR('Payroll Schedule'!S17/'Payroll Schedule'!S18,0)),ABS('Payroll Schedule'!T20-IFERROR('Payroll Schedule'!T18/'Payroll Schedule'!T16,0)),ABS('Payroll Schedule'!T21-IFERROR('Payroll Schedule'!T19/'Payroll Schedule'!T16,0)),ABS('Payroll Schedule'!T22-IFERROR('Payroll Schedule'!T17/'Payroll Schedule'!T18,0)),ABS('Payroll Schedule'!U20-IFERROR('Payroll Schedule'!U18/'Payroll Schedule'!U16,0)),ABS('Payroll Schedule'!U21-IFERROR('Payroll Schedule'!U19/'Payroll Schedule'!U16,0)),ABS('Payroll Schedule'!U22-IFERROR('Payroll Schedule'!U17/'Payroll Schedule'!U18,0)),ABS('Payroll Schedule'!V20-IFERROR('Payroll Schedule'!V18/'Payroll Schedule'!V16,0)),ABS('Payroll Schedule'!V21-IFERROR('Payroll Schedule'!V19/'Payroll Schedule'!V16,0)),ABS('Payroll Schedule'!V22-IFERROR('Payroll Schedule'!V17/'Payroll Schedule'!V18,0)),ABS('Payroll Schedule'!W20-IFERROR('Payroll Schedule'!W18/'Payroll Schedule'!W16,0)),ABS('Payroll Schedule'!W21-IFERROR('Payroll Schedule'!W19/'Payroll Schedule'!W16,0)),ABS('Payroll Schedule'!W22-IFERROR('Payroll Schedule'!W17/'Payroll Schedule'!W18,0))) | F17: 0 | G17: =E17-F17 | H17: 0.01 | I17: =IF(ABS(G17)<=H17,"OK","FAIL") | J17: Revenue per employee, units per employee, and payroll percent must stay tied to revenue/capacity and average FTE.
A18: Schedule Coherence | B18: Payroll detail FTE math | C18: Payroll Schedule | D18: E27:H66 | E18: =SUMPRODUCT(ABS('Payroll Schedule'!G27:G66-('Payroll Schedule'!E27:E66+'Payroll Schedule'!F27:F66)))+SUMPRODUCT(ABS('Payroll Schedule'!H27:H66-(('Payroll Schedule'!E27:E66+'Payroll Schedule'!G27:G66)/2))) | F18: 0 | G18: =E18-F18 | H18: 0.01 | I18: =IF(ABS(G18)<=H18,"OK","FAIL") | J18: Ending FTE must equal starting FTE plus hires; average FTE must be the average of starting and ending FTE.
A19: Schedule Coherence | B19: Payroll detail wage and tax math | C19: Payroll Schedule | D19: I27:M66 | E19: =SUMPRODUCT(ABS('Payroll Schedule'!K27:K66-('Payroll Schedule'!H27:H66*'Payroll Schedule'!I27:I66/4)))+SUMPRODUCT(ABS('Payroll Schedule'!L27:L66-('Payroll Schedule'!K27:K66*'Payroll Schedule'!J27:J66)))+SUMPRODUCT(ABS('Payroll Schedule'!M27:M66-('Payroll Schedule'!K27:K66+'Payroll Schedule'!L27:L66))) | F19: 0 | G19: =E19-F19 | H19: 1 | I19: =IF(ABS(G19)<=H19,"OK","FAIL") | J19: Payroll dollars must flow from average FTE, wage, benefits/taxes, and total payroll formulas.
A21: Line-Item Formula Logic Diagnostics
A22: Formula Logic | B22: Revenue calculation - lob_1_product_1 | C22: Revenue Drivers | D22: 'Revenue Drivers'!C11:W11 | E22: =SUMPRODUCT(ABS('Revenue Drivers'!C11:W11-('Revenue Drivers'!C8:W8*'Revenue Drivers'!C9:W9*'Revenue Drivers'!C10:W10))) | F22: 0 | G22: =E22-F22 | H22: 1 | I22: =IF(ABS(G22)<=H22,"OK","FAIL") | J22: Revenue rows must equal capacity x unit price x utilization.
A23: Formula Logic | B23: Revenue calculation - lob_1_product_2 | C23: Revenue Drivers | D23: 'Revenue Drivers'!C17:W17 | E23: =SUMPRODUCT(ABS('Revenue Drivers'!C17:W17-('Revenue Drivers'!C14:W14*'Revenue Drivers'!C15:W15*'Revenue Drivers'!C16:W16))) | F23: 0 | G23: =E23-F23 | H23: 1 | I23: =IF(ABS(G23)<=H23,"OK","FAIL") | J23: Revenue rows must equal capacity x unit price x utilization.
A24: Formula Logic | B24: Revenue calculation - lob_1_product_3 | C24: Revenue Drivers | D24: 'Revenue Drivers'!C23:W23 | E24: =SUMPRODUCT(ABS('Revenue Drivers'!C23:W23-('Revenue Drivers'!C20:W20*'Revenue Drivers'!C21:W21*'Revenue Drivers'!C22:W22))) | F24: 0 | G24: =E24-F24 | H24: 1 | I24: =IF(ABS(G24)<=H24,"OK","FAIL") | J24: Revenue rows must equal capacity x unit price x utilization.
A25: Formula Logic | B25: Revenue total equals all revenue products | C25: Revenue Drivers | D25: 'Revenue Drivers'!C26:W26 | E25: =SUMPRODUCT(ABS('Revenue Drivers'!C26:W26-('Revenue Drivers'!C11:W11+'Revenue Drivers'!C17:W17+'Revenue Drivers'!C23:W23))) | F25: 0 | G25: =E25-F25 | H25: 1 | I25: =IF(ABS(G25)<=H25,"OK","FAIL") | J25: Total revenue must stay tied to all revenue-product rows.
A26: Formula Logic | B26: Revenue total capacity equals all capacity products | C26: Revenue Drivers | D26: 'Revenue Drivers'!C25:W25 | E26: =SUMPRODUCT(ABS('Revenue Drivers'!C25:W25-('Revenue Drivers'!C8:W8+'Revenue Drivers'!C14:W14+'Revenue Drivers'!C20:W20))) | F26: 0 | G26: =E26-F26 | H26: 0.01 | I26: =IF(ABS(G26)<=H26,"OK","FAIL") | J26: Total capacity units must stay tied to all revenue-driver capacity rows.
A27: Formula Logic | B27: Debt opening balance continuity | C27: Debt Schedule | D27: 'Debt Schedule'!D7:W7 | E27: =SUMPRODUCT(ABS('Debt Schedule'!D7:W7-'Debt Schedule'!C11:V11)) | F27: 0 | G27: =E27-F27 | H27: 1 | I27: =IF(ABS(G27)<=H27,"OK","FAIL") | J27: Each quarter's opening debt must equal the prior quarter's closing debt.
A28: Formula Logic | B28: Actual debt repayment cap | C28: Debt Schedule | D28: 'Debt Schedule'!C10:W10 | E28: =SUMPRODUCT(--(('Debt Schedule'!C10:W10-'Debt Schedule'!C9:W9)>1))+SUMPRODUCT(--(('Debt Schedule'!C10:W10-('Debt Schedule'!C7:W7+'Debt Schedule'!C8:W8))>1)) | F28: 0 | G28: =E28-F28 | H28: 0 | I28: =IF(ABS(G28)<=H28,"OK","FAIL") | J28: Actual repayment must not exceed requested repayment or available debt balance.
A29: Formula Logic | B29: Closing debt formula | C29: Debt Schedule | D29: 'Debt Schedule'!C11:W11 | E29: =SUMPRODUCT(ABS('Debt Schedule'!C11:W11-('Debt Schedule'!C7:W7+'Debt Schedule'!C8:W8-'Debt Schedule'!C10:W10))) | F29: 0 | G29: =E29-F29 | H29: 1 | I29: =IF(ABS(G29)<=H29,"OK","FAIL") | J29: Closing debt must equal opening debt plus issuance less actual repayment, floored at zero.
A30: Formula Logic | B30: Interest expense formula | C30: Debt Schedule | D30: 'Debt Schedule'!C13:W13 | E30: =SUMPRODUCT(ABS('Debt Schedule'!C13:W13-((('Debt Schedule'!C7:W7+'Debt Schedule'!C11:W11)/2)*'Debt Schedule'!C12:W12))) | F30: 0 | G30: =E30-F30 | H30: 1 | I30: =IF(ABS(G30)<=H30,"OK","FAIL") | J30: Interest expense must equal average debt balance times interest rate.
A31: Formula Logic | B31: Debt service formula | C31: Debt Schedule | D31: 'Debt Schedule'!C14:W14 | E31: =SUMPRODUCT(ABS('Debt Schedule'!C14:W14-('Debt Schedule'!C13:W13+'Debt Schedule'!C10:W10))) | F31: 0 | G31: =E31-F31 | H31: 1 | I31: =IF(ABS(G31)<=H31,"OK","FAIL") | J31: Debt service must equal interest expense plus actual debt repayment.
A32: Formula Logic | B32: Lease opening balance continuity | C32: Debt Schedule | D32: 'Debt Schedule'!D18:W18 | E32: =SUMPRODUCT(ABS('Debt Schedule'!D18:W18-'Debt Schedule'!C23:V23)) | F32: 0 | G32: =E32-F32 | H32: 1 | I32: =IF(ABS(G32)<=H32,"OK","FAIL") | J32: Each quarter's opening lease balance must equal the prior quarter's closing lease balance.
A33: Formula Logic | B33: Lease principal repayment cap | C33: Debt Schedule | D33: 'Debt Schedule'!C20:W20 | E33: =SUMPRODUCT(--(('Debt Schedule'!C20:W20-'Debt Schedule'!C19:W19)>1))+SUMPRODUCT(--(('Debt Schedule'!C20:W20-('Debt Schedule'!C18:W18+'Debt Schedule'!C21:W21))>1)) | F33: 0 | G33: =E33-F33 | H33: 0 | I33: =IF(ABS(G33)<=H33,"OK","FAIL") | J33: Lease principal repayment must not exceed requested repayment or available lease balance.
A34: Formula Logic | B34: Lease closing balance formula | C34: Debt Schedule | D34: 'Debt Schedule'!C23:W23 | E34: =SUMPRODUCT(ABS('Debt Schedule'!C23:W23-('Debt Schedule'!C18:W18+'Debt Schedule'!C21:W21-'Debt Schedule'!C20:W20))) | F34: 0 | G34: =E34-F34 | H34: 1 | I34: =IF(ABS(G34)<=H34,"OK","FAIL") | J34: Lease closing balance must equal opening balance plus additions less principal repayment, floored at zero.
A35: Formula Logic | B35: PPE opening balance continuity | C35: CapEx Depreciation | D35: 'CapEx Depreciation'!D7:W7 | E35: =SUMPRODUCT(ABS('CapEx Depreciation'!D7:W7-'CapEx Depreciation'!C12:V12)) | F35: 0 | G35: =E35-F35 | H35: 1 | I35: =IF(ABS(G35)<=H35,"OK","FAIL") | J35: Each quarter's opening PPE must equal the prior quarter's closing PPE.
A36: Formula Logic | B36: Depreciation expense formula | C36: CapEx Depreciation | D36: 'CapEx Depreciation'!C11:W11 | E36: =SUMPRODUCT(ABS('CapEx Depreciation'!C11:W11-('CapEx Depreciation'!C7:W7*'CapEx Depreciation'!C10:W10))) | F36: 0 | G36: =E36-F36 | H36: 1 | I36: =IF(ABS(G36)<=H36,"OK","FAIL") | J36: Depreciation must equal opening PPE times rate, capped at opening PPE.
A37: Formula Logic | B37: Closing PPE formula | C37: CapEx Depreciation | D37: 'CapEx Depreciation'!C12:W12 | E37: =SUMPRODUCT(ABS('CapEx Depreciation'!C12:W12-('CapEx Depreciation'!C7:W7+'CapEx Depreciation'!C8:W8+'CapEx Depreciation'!C9:W9-'CapEx Depreciation'!C11:W11))) | F37: 0 | G37: =E37-F37 | H37: 1 | I37: =IF(ABS(G37)<=H37,"OK","FAIL") | J37: Closing PPE must include capex and lease additions and subtract depreciation.
A38: Formula Logic | B38: Accumulated depreciation continuity | C38: CapEx Depreciation | D38: 'CapEx Depreciation'!D13:W13 | E38: =SUMPRODUCT(ABS('CapEx Depreciation'!D13:W13-'CapEx Depreciation'!C14:V14)) | F38: 0 | G38: =E38-F38 | H38: 1 | I38: =IF(ABS(G38)<=H38,"OK","FAIL") | J38: Opening accumulated depreciation must equal the prior quarter's accumulated depreciation.
A39: Formula Logic | B39: Accumulated depreciation formula | C39: CapEx Depreciation | D39: 'CapEx Depreciation'!C14:W14 | E39: =SUMPRODUCT(ABS('CapEx Depreciation'!C14:W14-('CapEx Depreciation'!C13:W13-'CapEx Depreciation'!C11:W11))) | F39: 0 | G39: =E39-F39 | H39: 1 | I39: =IF(ABS(G39)<=H39,"OK","FAIL") | J39: Accumulated depreciation must roll forward by depreciation expense.
A41: Formula Manifest by Line Item
A42: Formula Manifest | B42: Revenue Drivers - Total Revenue | C42: Revenue Drivers | D42: 'Revenue Drivers'!C26:W26 | E42: =21 | F42: 21 | G42: =E42-F42 | H42: 0 | I42: =IF(G42=0,"OK","FAIL") | J42: This line is expected to be formula-driven across every period. Formula presence is verified at export; live edit integrity is covered by the logic and bridge checks above.
A43: Formula Manifest | B43: Revenue Drivers - Total Capacity Units | C43: Revenue Drivers | D43: 'Revenue Drivers'!C25:W25 | E43: =21 | F43: 21 | G43: =E43-F43 | H43: 0 | I43: =IF(G43=0,"OK","FAIL") | J43: This line is expected to be formula-driven across every period. Formula presence is verified at export; live edit integrity is covered by the logic and bridge checks above.
A44: Formula Manifest | B44: Revenue Drivers - Actual Revenue QoQ Growth | C44: Revenue Drivers | D44: 'Revenue Drivers'!C29:W29 | E44: =21 | F44: 21 | G44: =E44-F44 | H44: 0 | I44: =IF(G44=0,"OK","FAIL") | J44: This line is expected to be formula-driven across every period. Formula presence is verified at export; live edit integrity is covered by the logic and bridge checks above.
A45: Formula Manifest | B45: Payroll Schedule - Total Ending FTE | C45: Payroll Schedule | D45: 'Payroll Schedule'!C15:W15 | E45: =21 | F45: 21 | G45: =E45-F45 | H45: 0 | I45: =IF(G45=0,"OK","FAIL") | J45: This line is expected to be formula-driven across every period. Formula presence is verified at export; live edit integrity is covered by the logic and bridge checks above.
A46: Formula Manifest | B46: Payroll Schedule - Total Average FTE | C46: Payroll Schedule | D46: 'Payroll Schedule'!C16:W16 | E46: =21 | F46: 21 | G46: =E46-F46 | H46: 0 | I46: =IF(G46=0,"OK","FAIL") | J46: This line is expected to be formula-driven across every period. Formula presence is verified at export; live edit integrity is covered by the logic and bridge checks above.
A47: Formula Manifest | B47: Payroll Schedule - Total Payroll | C47: Payroll Schedule | D47: 'Payroll Schedule'!C17:W17 | E47: =21 | F47: 21 | G47: =E47-F47 | H47: 0 | I47: =IF(G47=0,"OK","FAIL") | J47: This line is expected to be formula-driven across every period. Formula presence is verified at export; live edit integrity is covered by the logic and bridge checks above.
A48: Formula Manifest | B48: Payroll Schedule - Total Revenue | C48: Payroll Schedule | D48: 'Payroll Schedule'!C18:W18 | E48: =21 | F48: 21 | G48: =E48-F48 | H48: 0 | I48: =IF(G48=0,"OK","FAIL") | J48: This line is expected to be formula-driven across every period. Formula presence is verified at export; live edit integrity is covered by the logic and bridge checks above.
A49: Formula Manifest | B49: Payroll Schedule - Total Capacity Units | C49: Payroll Schedule | D49: 'Payroll Schedule'!C19:W19 | E49: =21 | F49: 21 | G49: =E49-F49 | H49: 0 | I49: =IF(G49=0,"OK","FAIL") | J49: This line is expected to be formula-driven across every period. Formula presence is verified at export; live edit integrity is covered by the logic and bridge checks above.
A50: Formula Manifest | B50: Payroll Schedule - Revenue per Employee | C50: Payroll Schedule | D50: 'Payroll Schedule'!C20:W20 | E50: =21 | F50: 21 | G50: =E50-F50 | H50: 0 | I50: =IF(G50=0,"OK","FAIL") | J50: This line is expected to be formula-driven across every period. Formula presence is verified at export; live edit integrity is covered by the logic and bridge checks above.
A51: Formula Manifest | B51: Payroll Schedule - Units per Employee | C51: Payroll Schedule | D51: 'Payroll Schedule'!C21:W21 | E51: =21 | F51: 21 | G51: =E51-F51 | H51: 0 | I51: =IF(G51=0,"OK","FAIL") | J51: This line is expected to be formula-driven across every period. Formula presence is verified at export; live edit integrity is covered by the logic and bridge checks above.
A52: Formula Manifest | B52: Payroll Schedule - Payroll % of Revenue | C52: Payroll Schedule | D52: 'Payroll Schedule'!C22:W22 | E52: =21 | F52: 21 | G52: =E52-F52 | H52: 0 | I52: =IF(G52=0,"OK","FAIL") | J52: This line is expected to be formula-driven across every period. Formula presence is verified at export; live edit integrity is covered by the logic and bridge checks above.
A53: Formula Manifest | B53: CapEx Schedule - Lease Additions | C53: CapEx Depreciation | D53: 'CapEx Depreciation'!D9:W9 | E53: =20 | F53: 20 | G53: =E53-F53 | H53: 0 | I53: =IF(G53=0,"OK","FAIL") | J53: This line is expected to be formula-driven across every period. Formula presence is verified at export; live edit integrity is covered by the logic and bridge checks above.
A54: Formula Manifest | B54: CapEx Schedule - Closing PPE | C54: CapEx Depreciation | D54: 'CapEx Depreciation'!C12:W12 | E54: =21 | F54: 21 | G54: =E54-F54 | H54: 0 | I54: =IF(G54=0,"OK","FAIL") | J54: This line is expected to be formula-driven across every period. Formula presence is verified at export; live edit integrity is covered by the logic and bridge checks above.
A55: Formula Manifest | B55: Debt Schedule - Opening Debt | C55: Debt Schedule | D55: 'Debt Schedule'!D7:W7 | E55: =20 | F55: 20 | G55: =E55-F55 | H55: 0 | I55: =IF(G55=0,"OK","FAIL") | J55: This debt/lease line is expected to be formula-driven across every period. Formula presence is verified at export; live edit integrity is covered by the logic and bridge checks above.
A56: Formula Manifest | B56: Debt Schedule - Actual Debt Repayment | C56: Debt Schedule | D56: 'Debt Schedule'!C10:W10 | E56: =21 | F56: 21 | G56: =E56-F56 | H56: 0 | I56: =IF(G56=0,"OK","FAIL") | J56: This debt/lease line is expected to be formula-driven across every period. Formula presence is verified at export; live edit integrity is covered by the logic and bridge checks above.
A57: Formula Manifest | B57: Debt Schedule - Closing Debt | C57: Debt Schedule | D57: 'Debt Schedule'!C11:W11 | E57: =21 | F57: 21 | G57: =E57-F57 | H57: 0 | I57: =IF(G57=0,"OK","FAIL") | J57: This debt/lease line is expected to be formula-driven across every period. Formula presence is verified at export; live edit integrity is covered by the logic and bridge checks above.
A58: Formula Manifest | B58: Debt Schedule - Interest Expense | C58: Debt Schedule | D58: 'Debt Schedule'!C13:W13 | E58: =21 | F58: 21 | G58: =E58-F58 | H58: 0 | I58: =IF(G58=0,"OK","FAIL") | J58: This debt/lease line is expected to be formula-driven across every period. Formula presence is verified at export; live edit integrity is covered by the logic and bridge checks above.
A59: Formula Manifest | B59: Debt Schedule - Total Debt Service | C59: Debt Schedule | D59: 'Debt Schedule'!C14:W14 | E59: =21 | F59: 21 | G59: =E59-F59 | H59: 0 | I59: =IF(G59=0,"OK","FAIL") | J59: This debt/lease line is expected to be formula-driven across every period. Formula presence is verified at export; live edit integrity is covered by the logic and bridge checks above.
A60: Formula Manifest | B60: Debt Schedule - Lease Opening Balance | C60: Debt Schedule | D60: 'Debt Schedule'!D18:W18 | E60: =20 | F60: 20 | G60: =E60-F60 | H60: 0 | I60: =IF(G60=0,"OK","FAIL") | J60: This debt/lease line is expected to be formula-driven across every period. Formula presence is verified at export; live edit integrity is covered by the logic and bridge checks above.
A61: Formula Manifest | B61: Debt Schedule - Lease Principal Repayments | C61: Debt Schedule | D61: 'Debt Schedule'!C20:W20 | E61: =21 | F61: 21 | G61: =E61-F61 | H61: 0 | I61: =IF(G61=0,"OK","FAIL") | J61: This debt/lease line is expected to be formula-driven across every period. Formula presence is verified at export; live edit integrity is covered by the logic and bridge checks above.
A62: Formula Manifest | B62: Debt Schedule - Lease Closing Balance | C62: Debt Schedule | D62: 'Debt Schedule'!C23:W23 | E62: =21 | F62: 21 | G62: =E62-F62 | H62: 0 | I62: =IF(G62=0,"OK","FAIL") | J62: This debt/lease line is expected to be formula-driven across every period. Formula presence is verified at export; live edit integrity is covered by the logic and bridge checks above.
A63: Formula Manifest | B63: Payroll Detail - Ending FTE | C63: Payroll Schedule | D63: 'Payroll Schedule'!G27:G66 | E63: =40 | F63: 40 | G63: =E63-F63 | H63: 0 | I63: =IF(G63=0,"OK","FAIL") | J63: Payroll detail calculation columns must remain formulas so edits flow downstream. Formula presence is verified at export; live edit integrity is covered by the logic and bridge checks above.
A64: Formula Manifest | B64: Payroll Detail - Average FTE | C64: Payroll Schedule | D64: 'Payroll Schedule'!H27:H66 | E64: =40 | F64: 40 | G64: =E64-F64 | H64: 0 | I64: =IF(G64=0,"OK","FAIL") | J64: Payroll detail calculation columns must remain formulas so edits flow downstream. Formula presence is verified at export; live edit integrity is covered by the logic and bridge checks above.
A65: Formula Manifest | B65: Payroll Detail - Wage Cost | C65: Payroll Schedule | D65: 'Payroll Schedule'!K27:K66 | E65: =40 | F65: 40 | G65: =E65-F65 | H65: 0 | I65: =IF(G65=0,"OK","FAIL") | J65: Payroll detail calculation columns must remain formulas so edits flow downstream. Formula presence is verified at export; live edit integrity is covered by the logic and bridge checks above.
A66: Formula Manifest | B66: Payroll Detail - Taxes & Benefits | C66: Payroll Schedule | D66: 'Payroll Schedule'!L27:L66 | E66: =40 | F66: 40 | G66: =E66-F66 | H66: 0 | I66: =IF(G66=0,"OK","FAIL") | J66: Payroll detail calculation columns must remain formulas so edits flow downstream. Formula presence is verified at export; live edit integrity is covered by the logic and bridge checks above.
A67: Formula Manifest | B67: Payroll Detail - Total Payroll | C67: Payroll Schedule | D67: 'Payroll Schedule'!M27:M66 | E67: =40 | F67: 40 | G67: =E67-F67 | H67: 0 | I67: =IF(G67=0,"OK","FAIL") | J67: Payroll detail calculation columns must remain formulas so edits flow downstream. Formula presence is verified at export; live edit integrity is covered by the logic and bridge checks above.
A68: Formula Manifest | B68: Model Inputs - revenue::lob_1_product_1::Capacity | C68: Model Inputs | D68: 'Model Inputs'!C7:W7 | E68: =21 | F68: 21 | G68: =E68-F68 | H68: 0 | I68: =IF(G68=0,"OK","FAIL") | J68: Formula bridge rows in Model Inputs must stay linked to schedules. Formula presence is verified at export; live edit integrity is covered by the logic and bridge checks above.
A69: Formula Manifest | B69: Model Inputs - revenue::lob_1_product_1::Unit Price | C69: Model Inputs | D69: 'Model Inputs'!C8:W8 | E69: =21 | F69: 21 | G69: =E69-F69 | H69: 0 | I69: =IF(G69=0,"OK","FAIL") | J69: Formula bridge rows in Model Inputs must stay linked to schedules. Formula presence is verified at export; live edit integrity is covered by the logic and bridge checks above.
A70: Formula Manifest | B70: Model Inputs - revenue::lob_1_product_1::Utilization | C70: Model Inputs | D70: 'Model Inputs'!C9:W9 | E70: =21 | F70: 21 | G70: =E70-F70 | H70: 0 | I70: =IF(G70=0,"OK","FAIL") | J70: Formula bridge rows in Model Inputs must stay linked to schedules. Formula presence is verified at export; live edit integrity is covered by the logic and bridge checks above.
A71: Formula Manifest | B71: Model Inputs - revenue::lob_1_product_1::Revenue | C71: Model Inputs | D71: 'Model Inputs'!C10:W10 | E71: =21 | F71: 21 | G71: =E71-F71 | H71: 0 | I71: =IF(G71=0,"OK","FAIL") | J71: Formula bridge rows in Model Inputs must stay linked to schedules. Formula presence is verified at export; live edit integrity is covered by the logic and bridge checks above.
A72: Formula Manifest | B72: Model Inputs - revenue::lob_1_product_2::Capacity | C72: Model Inputs | D72: 'Model Inputs'!C11:W11 | E72: =21 | F72: 21 | G72: =E72-F72 | H72: 0 | I72: =IF(G72=0,"OK","FAIL") | J72: Formula bridge rows in Model Inputs must stay linked to schedules. Formula presence is verified at export; live edit integrity is covered by the logic and bridge checks above.
A73: Formula Manifest | B73: Model Inputs - revenue::lob_1_product_2::Unit Price | C73: Model Inputs | D73: 'Model Inputs'!C12:W12 | E73: =21 | F73: 21 | G73: =E73-F73 | H73: 0 | I73: =IF(G73=0,"OK","FAIL") | J73: Formula bridge rows in Model Inputs must stay linked to schedules. Formula presence is verified at export; live edit integrity is covered by the logic and bridge checks above.
A74: Formula Manifest | B74: Model Inputs - revenue::lob_1_product_2::Utilization | C74: Model Inputs | D74: 'Model Inputs'!C13:W13 | E74: =21 | F74: 21 | G74: =E74-F74 | H74: 0 | I74: =IF(G74=0,"OK","FAIL") | J74: Formula bridge rows in Model Inputs must stay linked to schedules. Formula presence is verified at export; live edit integrity is covered by the logic and bridge checks above.
A75: Formula Manifest | B75: Model Inputs - revenue::lob_1_product_2::Revenue | C75: Model Inputs | D75: 'Model Inputs'!C14:W14 | E75: =21 | F75: 21 | G75: =E75-F75 | H75: 0 | I75: =IF(G75=0,"OK","FAIL") | J75: Formula bridge rows in Model Inputs must stay linked to schedules. Formula presence is verified at export; live edit integrity is covered by the logic and bridge checks above.
A76: Formula Manifest | B76: Model Inputs - revenue::lob_1_product_3::Capacity | C76: Model Inputs | D76: 'Model Inputs'!C15:W15 | E76: =21 | F76: 21 | G76: =E76-F76 | H76: 0 | I76: =IF(G76=0,"OK","FAIL") | J76: Formula bridge rows in Model Inputs must stay linked to schedules. Formula presence is verified at export; live edit integrity is covered by the logic and bridge checks above.
A77: Formula Manifest | B77: Model Inputs - revenue::lob_1_product_3::Unit Price | C77: Model Inputs | D77: 'Model Inputs'!C16:W16 | E77: =21 | F77: 21 | G77: =E77-F77 | H77: 0 | I77: =IF(G77=0,"OK","FAIL") | J77: Formula bridge rows in Model Inputs must stay linked to schedules. Formula presence is verified at export; live edit integrity is covered by the logic and bridge checks above.
A78: Formula Manifest | B78: Model Inputs - revenue::lob_1_product_3::Utilization | C78: Model Inputs | D78: 'Model Inputs'!C17:W17 | E78: =21 | F78: 21 | G78: =E78-F78 | H78: 0 | I78: =IF(G78=0,"OK","FAIL") | J78: Formula bridge rows in Model Inputs must stay linked to schedules. Formula presence is verified at export; live edit integrity is covered by the logic and bridge checks above.
A79: Formula Manifest | B79: Model Inputs - revenue::lob_1_product_3::Revenue | C79: Model Inputs | D79: 'Model Inputs'!C18:W18 | E79: =21 | F79: 21 | G79: =E79-F79 | H79: 0 | I79: =IF(G79=0,"OK","FAIL") | J79: Formula bridge rows in Model Inputs must stay linked to schedules. Formula presence is verified at export; live edit integrity is covered by the logic and bridge checks above.
... A81: Formula Manifest | B81: Model Inputs - is::Lease | C81: Model Inputs | D81: 'Model Inputs'!C23:W23 | E81: =21 | F81: 21 | G81: =E81-F81 | H81: 0 | I81: =IF(G81=0,"OK","FAIL") | J81: Formula bridge rows in Model Inputs must stay linked to schedules. Formula presence is verified at export; live edit integrity is covered by the logic and bridge checks above.
A82: Formula Manifest | B82: Model Inputs - is::Payroll | C82: Model Inputs | D82: 'Model Inputs'!D24:W24 | E82: =20 | F82: 20 | G82: =E82-F82 | H82: 0 | I82: =IF(G82=0,"OK","FAIL") | J82: Formula bridge rows in Model Inputs must stay linked to schedules. Formula presence is verified at export; live edit integrity is covered by the logic and bridge checks above.
A83: Formula Manifest | B83: Model Inputs - is::Interest Rate | C83: Model Inputs | D83: 'Model Inputs'!C26:W26 | E83: =21 | F83: 21 | G83: =E83-F83 | H83: 0 | I83: =IF(G83=0,"OK","FAIL") | J83: Formula bridge rows in Model Inputs must stay linked to schedules. Formula presence is verified at export; live edit integrity is covered by the logic and bridge checks above.
A84: Formula Manifest | B84: Model Inputs - is::Interest Expense | C84: Model Inputs | D84: 'Model Inputs'!D27:W27 | E84: =20 | F84: 20 | G84: =E84-F84 | H84: 0 | I84: =IF(G84=0,"OK","FAIL") | J84: Formula bridge rows in Model Inputs must stay linked to schedules. Formula presence is verified at export; live edit integrity is covered by the logic and bridge checks above.
A85: Formula Manifest | B85: Model Inputs - is::Depreciation | C85: Model Inputs | D85: 'Model Inputs'!C28:W28 | E85: =21 | F85: 21 | G85: =E85-F85 | H85: 0 | I85: =IF(G85=0,"OK","FAIL") | J85: Formula bridge rows in Model Inputs must stay linked to schedules. Formula presence is verified at export; live edit integrity is covered by the logic and bridge checks above.
A86: Formula Manifest | B86: Model Inputs - is::Depreciation Expense | C86: Model Inputs | D86: 'Model Inputs'!C29:W29 | E86: =21 | F86: 21 | G86: =E86-F86 | H86: 0 | I86: =IF(G86=0,"OK","FAIL") | J86: Formula bridge rows in Model Inputs must stay linked to schedules. Formula presence is verified at export; live edit integrity is covered by the logic and bridge checks above.
A87: Formula Manifest | B87: Model Inputs - bs::Accounts Receivable Days | C87: Model Inputs | D87: 'Model Inputs'!C33:W33 | E87: =21 | F87: 21 | G87: =E87-F87 | H87: 0 | I87: =IF(G87=0,"OK","FAIL") | J87: Formula bridge rows in Model Inputs must stay linked to schedules. Formula presence is verified at export; live edit integrity is covered by the logic and bridge checks above.
A88: Formula Manifest | B88: Model Inputs - bs::Inventory Days | C88: Model Inputs | D88: 'Model Inputs'!C34:W34 | E88: =21 | F88: 21 | G88: =E88-F88 | H88: 0 | I88: =IF(G88=0,"OK","FAIL") | J88: Formula bridge rows in Model Inputs must stay linked to schedules. Formula presence is verified at export; live edit integrity is covered by the logic and bridge checks above.
A89: Formula Manifest | B89: Model Inputs - bs::Accounts Payable Days | C89: Model Inputs | D89: 'Model Inputs'!C35:W35 | E89: =21 | F89: 21 | G89: =E89-F89 | H89: 0 | I89: =IF(G89=0,"OK","FAIL") | J89: Formula bridge rows in Model Inputs must stay linked to schedules. Formula presence is verified at export; live edit integrity is covered by the logic and bridge checks above.
A90: Formula Manifest | B90: Model Inputs - bs::Prepaid Expenses (% of Revenue) | C90: Model Inputs | D90: 'Model Inputs'!C36:W36 | E90: =21 | F90: 21 | G90: =E90-F90 | H90: 0 | I90: =IF(G90=0,"OK","FAIL") | J90: Formula bridge rows in Model Inputs must stay linked to schedules. Formula presence is verified at export; live edit integrity is covered by the logic and bridge checks above.
A91: Formula Manifest | B91: Model Inputs - bs::Deferred Revenue (% of Revenue) | C91: Model Inputs | D91: 'Model Inputs'!C37:W37 | E91: =21 | F91: 21 | G91: =E91-F91 | H91: 0 | I91: =IF(G91=0,"OK","FAIL") | J91: Formula bridge rows in Model Inputs must stay linked to schedules. Formula presence is verified at export; live edit integrity is covered by the logic and bridge checks above.
A92: Formula Manifest | B92: Model Inputs - bs::Short Term Debt (% of LTD) | C92: Model Inputs | D92: 'Model Inputs'!C38:W38 | E92: =21 | F92: 21 | G92: =E92-F92 | H92: 0 | I92: =IF(G92=0,"OK","FAIL") | J92: Formula bridge rows in Model Inputs must stay linked to schedules. Formula presence is verified at export; live edit integrity is covered by the logic and bridge checks above.
A93: Formula Manifest | B93: Model Inputs - bs::Owner's Capital | C93: Model Inputs | D93: 'Model Inputs'!C39:W39 | E93: =21 | F93: 21 | G93: =E93-F93 | H93: 0 | I93: =IF(G93=0,"OK","FAIL") | J93: Formula bridge rows in Model Inputs must stay linked to schedules. Formula presence is verified at export; live edit integrity is covered by the logic and bridge checks above.
A94: Formula Manifest | B94: Model Inputs - bs::Other Equity | C94: Model Inputs | D94: 'Model Inputs'!C40:W40 | E94: =21 | F94: 21 | G94: =E94-F94 | H94: 0 | I94: =IF(G94=0,"OK","FAIL") | J94: Formula bridge rows in Model Inputs must stay linked to schedules. Formula presence is verified at export; live edit integrity is covered by the logic and bridge checks above.
A95: Formula Manifest | B95: Model Inputs - bs::Distributions | C95: Model Inputs | D95: 'Model Inputs'!C41:W41 | E95: =21 | F95: 21 | G95: =E95-F95 | H95: 0 | I95: =IF(G95=0,"OK","FAIL") | J95: Formula bridge rows in Model Inputs must stay linked to schedules. Formula presence is verified at export; live edit integrity is covered by the logic and bridge checks above.
A96: Formula Manifest | B96: Model Inputs - cash::Cash Opening Balance | C96: Model Inputs | D96: 'Model Inputs'!C44:W44 | E96: =21 | F96: 21 | G96: =E96-F96 | H96: 0 | I96: =IF(G96=0,"OK","FAIL") | J96: Formula bridge rows in Model Inputs must stay linked to schedules. Formula presence is verified at export; live edit integrity is covered by the logic and bridge checks above.
... A164: Formula Manifest | B164: FINMO - Cash Flow - Ending Cash | C164: FINMO | D164: 'FINMO'!C61:W61 | E164: =21 | F164: 21 | G164: =E164-F164 | H164: 0 | I164: =IF(G164=0,"OK","FAIL") | J164: FINMO statement lines must remain formula-driven. Formula presence is verified at export; live edit integrity is covered by the logic and bridge checks above.
A166: Formula Error Scans
A167: Formula Error Scan | B167: Revenue Drivers formula/error scan | C167: Revenue Drivers | D167: 'Revenue Drivers'!C7:W40 | E167: =SUMPRODUCT(--ISERROR('Revenue Drivers'!C7:W40)) | F167: 0 | G167: =E167-F167 | H167: 0 | I167: =IF(E167=0,"OK","FAIL") | J167: Counts Excel error values in the range.
A168: Formula Error Scan | B168: Payroll Schedule formula/error scan | C168: Payroll Schedule | D168: 'Payroll Schedule'!C15:W66 | E168: =SUMPRODUCT(--ISERROR('Payroll Schedule'!C15:W66)) | F168: 0 | G168: =E168-F168 | H168: 0 | I168: =IF(E168=0,"OK","FAIL") | J168: Counts Excel error values in the range.
A169: Formula Error Scan | B169: Debt Schedule formula/error scan | C169: Debt Schedule | D169: 'Debt Schedule'!C7:W26 | E169: =SUMPRODUCT(--ISERROR('Debt Schedule'!C7:W26)) | F169: 0 | G169: =E169-F169 | H169: 0 | I169: =IF(E169=0,"OK","FAIL") | J169: Counts Excel error values in the range.
A170: Formula Error Scan | B170: CapEx Depreciation formula/error scan | C170: CapEx Depreciation | D170: 'CapEx Depreciation'!C7:W14 | E170: =SUMPRODUCT(--ISERROR('CapEx Depreciation'!C7:W14)) | F170: 0 | G170: =E170-F170 | H170: 0 | I170: =IF(E170=0,"OK","FAIL") | J170: Counts Excel error values in the range.
A171: Formula Error Scan | B171: Cash Equity Schedule formula/error scan | C171: Cash Equity Schedule | D171: 'Cash Equity Schedule'!C7:W12 | E171: =SUMPRODUCT(--ISERROR('Cash Equity Schedule'!C7:W12)) | F171: 0 | G171: =E171-F171 | H171: 0 | I171: =IF(E171=0,"OK","FAIL") | J171: Counts Excel error values in the range.
A172: Formula Error Scan | B172: Model Inputs formula/error scan | C172: Model Inputs | D172: 'Model Inputs'!C7:W62 | E172: =SUMPRODUCT(--ISERROR('Model Inputs'!C7:W62)) | F172: 0 | G172: =E172-F172 | H172: 0 | I172: =IF(E172=0,"OK","FAIL") | J172: Counts Excel error values in the range.
...

Sheet Diagnostics
A1: Run Diagnostics
A3: Run Metadata
A4: Planning Mode | B4: turnaround
A5: Cash Strategy | B5: balanced
A6: Business Stage | B6: operating
A7: Business Name | B7: Revitalize Mobile IV Therapy
A8: Business Start Date | B8: 8/5/2024
A9: NAICS-6 | B9: 621999
A10: Draft ID | B10: 71ac5266acad4720badabbd6fd5715a9
A11: Planning Run ID | B11: ca04b735ff324c63bf66653b112f5682
A13: Acceptance Gate
A14: Score | B14: 16/16
A15: Verdict | B15: PASSED
A17: GPT Exhaustion Handler
A18: Fired | B18: Yes
A19: Status | B19: landed_verified_tool_call
A20: Scope | B20: pnl_path
A21: Tool calls used | B21: 2
A22: Budget extension triggered | B22: False
A24: Realism Check Detail
A25: Metric Key | B25: Status
A26: advertising_percent_of_revenue | B26: ✓
A27: ap_days_dpo | B27: ✓
A28: ar_days_dso | B28: ✓
A29: capex_percent_of_revenue | B29: ✓
A30: cogs_percent_of_revenue | B30: ✓
A31: current_assets_minus_cash | B31: ✓
A32: current_liabilities_to_revenue | B32: ✓
A33: current_ratio | B33: ✓
A34: debt_to_assets | B34: ✓
A35: debt_to_equity | B35: ✓
A36: deferred_revenue_percent_of_revenue | B36: ✓
... A58: total_assets_to_revenue | B58: ✓
