Workbook

Sheet Revenue Drivers
A1: Revenue Drivers
A2: Source operating drivers. Model Inputs links to these rows.
C4: Stub | D4: Q1 | E4: Q2 | F4: Q3 | G4: Q4 | H4: Q5 | I4: Q6 | J4: Q7 | K4: Q8 | L4: Q9 | M4: Q10 | N4: Q11 | O4: Q12 | P4: Q13 | Q4: Q14 | R4: Q15 | S4: Q16 | T4: Q17 | U4: Q18 | V4: Q19 | W4: Q20 | X4: Y1 | Y4: Y2 | Z4: Y3 | AA4: Y4 | AB4: Y5
C5: 46162 | D5: 46295 | E5: 46387 | F5: 46477 | G5: 46568 | H5: 46660 | I5: 46752 | J5: 46843 | K5: 46934 | L5: 47026 | M5: 47118 | N5: 47208 | O5: 47299 | P5: 47391 | Q5: 47483 | R5: 47573 | S5: 47664 | T5: 47756 | U5: 47848 | V5: 47938 | W5: 48029 | X5: Annual | Y5: Annual | Z5: Annual | AA5: Annual | AB5: Annual
A6: Revenue Driver Source Rows
A7: Corporate Legal Services / Corporate legal matter/engagement
A8: Corporate Legal Services / Corporate legal matter/engagement - Capacity | B8: Source driver | C8: 130 | D8: 57.266667 | E8: 57.266667 | F8: 57.266667 | G8: 57.266667 | H8: 57.266667 | I8: 57.266667 | J8: 57.266667 | K8: 57.266667 | L8: 57.266667 | M8: 57.266667 | N8: 57.266667 | O8: 57.266667 | P8: 57.266667 | Q8: 57.266667 | R8: 57.266667 | S8: 57.266667 | T8: 57.266667 | U8: 57.266667 | V8: 57.266667 | W8: 57.266667
A9: Corporate Legal Services / Corporate legal matter/engagement - Unit Price | B9: Source driver | C9: 12000 | D9: 3228.0648 | E9: 4687.3753 | F9: 5633.9904 | G9: 6458.0668 | H9: 7175.4669 | I9: 7800 | J9: 8343.6876 | K9: 8816.9952 | L9: 9229.0334 | M9: 9587.7335 | N9: 9900 | O9: 10171.844 | P9: 10408.498 | Q9: 10614.517 | R9: 10793.867 | S9: 10950 | T9: 11085.922 | U9: 11204.249 | V9: 11307.258 | W9: 11396.933
A10: Corporate Legal Services / Corporate legal matter/engagement - Utilization | B10: Source driver | C10: 0.7 | D10: 0.826081 | E10: 0.737694 | F10: 0.62412 | G10: 0.552413 | H10: 0.517806 | I10: 0.479663 | J10: 0.456714 | K10: 0.439438 | L10: 0.435679 | M10: 0.426566 | N10: 0.503357 | O10: 0.586577 | P10: 0.641591 | Q10: 0.671911 | R10: 0.686967 | S10: 0.694057 | T10: 0.697312 | U10: 0.698788 | V10: 0.699455 | W10: 0.699755
A11: Corporate Legal Services / Corporate legal matter/engagement - Revenue | B11: Capacity x Unit Price x Utilization | C11: =C8*C9*C10 -> 1092000 | D11: =D8*D9*D10 -> 152709.76 | E11: =E8*E9*E10 -> 198019.46 | F11: =F8*F9*F10 -> 201365.99 | G11: =G8*G9*G10 -> 204299.98 | H11: =H8*H9*H10 -> 212774.29 | I11: =I8*I9*I10 -> 214255.87 | J11: =J8*J9*J10 -> 218224.88 | ... W11: =W8*W9*W10 -> 456705.17 | X11: =SUM(D11:G11) -> 756395.19 | Y11: =SUM(H11:K11) -> 867136.05 | Z11: =SUM(L11:O11) -> 1091531.4 | AA11: =SUM(P11:S11) -> 1650709.6 | AB11: =SUM(T11:W11) -> 1800677.1
A13: Individual Legal Services / Family/estate legal matter
A14: Individual Legal Services / Family/estate legal matter - Capacity | B14: Source driver | C14: 104 | D14: 45.813333 | E14: 45.813333 | F14: 45.813333 | G14: 45.813333 | H14: 45.813333 | I14: 45.813333 | J14: 45.813333 | K14: 45.813333 | L14: 45.813333 | M14: 45.813333 | N14: 45.813333 | O14: 45.813333 | P14: 45.813333 | Q14: 45.813333 | R14: 45.813333 | S14: 45.813333 | T14: 45.813333 | U14: 45.813333 | V14: 45.813333 | W14: 45.813333
A15: Individual Legal Services / Family/estate legal matter - Unit Price | B15: Source driver | C15: 6000 | D15: 3228.0648 | E15: 2343.6876 | F15: 2816.9952 | G15: 3229.0334 | H15: 3587.7335 | I15: 3900 | J15: 4171.8438 | K15: 4408.4976 | L15: 4614.5167 | M15: 4793.8667 | N15: 4950 | O15: 5085.9219 | P15: 5204.2488 | Q15: 5307.2583 | R15: 5396.9334 | S15: 5475 | T15: 5542.961 | U15: 5602.1244 | V15: 5653.6292 | W15: 5698.4667
A16: Individual Legal Services / Family/estate legal matter - Utilization | B16: Source driver | C16: 0.7 | D16: 0.826081 | E16: 0.737694 | F16: 0.62412 | G16: 0.552413 | H16: 0.517806 | I16: 0.479663 | J16: 0.456714 | K16: 0.439438 | L16: 0.435679 | M16: 0.426566 | N16: 0.503357 | O16: 0.586577 | P16: 0.641591 | Q16: 0.671911 | R16: 0.686967 | S16: 0.694057 | T16: 0.697312 | U16: 0.698788 | V16: 0.699455 | W16: 0.699755
A17: Individual Legal Services / Family/estate legal matter - Revenue | B17: Capacity x Unit Price x Utilization | C17: =C14*C15*C16 -> 436800 | D17: =D14*D15*D16 -> 122167.8 | E17: =E14*E15*E16 -> 79207.785 | F17: =F14*F15*F16 -> 80546.393 | G17: =G14*G15*G16 -> 81719.992 | H17: =H14*H15*H16 -> 85109.715 | I17: =I14*I15*I16 -> 85702.347 | J17: =J14*J15*J16 -> 87289.952 | ... W17: =W14*W15*W16 -> 182682.07 | X17: =SUM(D17:G17) -> 363641.97 | Y17: =SUM(H17:K17) -> 346854.41 | Z17: =SUM(L17:O17) -> 436612.54 | AA17: =SUM(P17:S17) -> 660283.82 | AB17: =SUM(T17:W17) -> 720270.82
A19: Total Capacity Units | B19: All revenue driver capacity units | C19: =SUM(C8,C14) -> 234 | D19: =SUM(D8,D14) -> 103.08 | E19: =SUM(E8,E14) -> 103.08 | F19: =SUM(F8,F14) -> 103.08 | G19: =SUM(G8,G14) -> 103.08 | H19: =SUM(H8,H14) -> 103.08 | I19: =SUM(I8,I14) -> 103.08 | J19: =SUM(J8,J14) -> 103.08 | ... W19: =SUM(W8,W14) -> 103.08 | X19: =SUM(D19:G19) -> 412.32 | Y19: =SUM(H19:K19) -> 412.32 | Z19: =SUM(L19:O19) -> 412.32 | AA19: =SUM(P19:S19) -> 412.32 | AB19: =SUM(T19:W19) -> 412.32
A20: Total Revenue | B20: All revenue products | C20: =SUM(C11,C17) -> 1528800 | D20: =SUM(D11,D17) -> 274877.56 | E20: =SUM(E11,E17) -> 277227.25 | F20: =SUM(F11,F17) -> 281912.38 | G20: =SUM(G11,G17) -> 286019.97 | H20: =SUM(H11,H17) -> 297884.01 | I20: =SUM(I11,I17) -> 299958.22 | J20: =SUM(J11,J17) -> 305514.83 | ... W20: =SUM(W11,W17) -> 639387.23 | X20: =SUM(D20:G20) -> 1120037.2 | Y20: =SUM(H20:K20) -> 1213990.5 | Z20: =SUM(L20:O20) -> 1528143.9 | AA20: =SUM(P20:S20) -> 2310993.4 | AB20: =SUM(T20:W20) -> 2520947.9
A22: Stage Ramp Contract
A23: Actual Revenue QoQ Growth | B23: Total revenue growth from modeled revenue drivers | C23: =0 -> 0 | D23: =IFERROR(D20/C20-1,0) -> -0.82020044 | E23: =IFERROR(E20/D20-1,0) -> 0.0085481301 | F23: =IFERROR(F20/E20-1,0) -> 0.016899956 | G23: =IFERROR(G20/F20-1,0) -> 0.01457047 | H23: =IFERROR(H20/G20-1,0) -> 0.041479733 | I23: =IFERROR(I20/H20-1,0) -> 0.0069631497 | J23: =IFERROR(J20/I20-1,0) -> 0.018524639 | K23: =IFERROR(K20/J20-1,0) -> 0.016753914 | ... W23: =IFERROR(W20/V20-1,0) -> 0.008363055 | X23: =AVERAGE(D23:G23) -> -0.19504547 | Y23: =AVERAGE(H23:K23) -> 0.020930359 | Z23: =AVERAGE(L23:O23) -> 0.11767446 | AA23: =AVERAGE(P23:S23) -> 0.062960027 | AB23: =AVERAGE(T23:W23) -> 0.012123509
A24: Stage Ramp Revenue QoQ Target | B24: GPT-selected stage ramp contract | C24: 0 | D24: 0.5 | E24: 0.5 | F24: 0.5 | G24: 0.5 | H24: 0.5 | I24: 0.5 | J24: 0.5 | K24: 0.5 | L24: 0.5 | M24: 0.5 | N24: 0.5 | O24: 0.5 | P24: 0.5 | Q24: 0.5 | R24: 0.5 | S24: 0.5 | T24: 0.5 | U24: 0.5 | V24: 0.5 | W24: 0.5 | X24: =AVERAGE(D24:G24) -> 0.5 | Y24: =AVERAGE(H24:K24) -> 0.5 | Z24: =AVERAGE(L24:O24) -> 0.5 | AA24: =AVERAGE(P24:S24) -> 0.5 | AB24: =AVERAGE(T24:W24) -> 0.5
A25: Stage Ramp Revenue QoQ Max | B25: GPT-selected stage ramp contract | C25: 0 | D25: 0.75 | E25: 0.75 | F25: 0.75 | G25: 0.75 | H25: 0.75 | I25: 0.75 | J25: 0.75 | K25: 0.75 | L25: 0.75 | M25: 0.75 | N25: 0.75 | O25: 0.75 | P25: 0.75 | Q25: 0.75 | R25: 0.75 | S25: 0.75 | T25: 0.75 | U25: 0.75 | V25: 0.75 | W25: 0.75 | X25: =AVERAGE(D25:G25) -> 0.75 | Y25: =AVERAGE(H25:K25) -> 0.75 | Z25: =AVERAGE(L25:O25) -> 0.75 | AA25: =AVERAGE(P25:S25) -> 0.75 | AB25: =AVERAGE(T25:W25) -> 0.75
A26: Stage Ramp Revenue QoQ Spike Max | B26: GPT-selected stage ramp contract | C26: 0 | D26: 0.75 | E26: 0.75 | F26: 0.75 | G26: 0.75 | H26: 0.75 | I26: 0.75 | J26: 0.75 | K26: 0.75 | L26: 0.75 | M26: 0.75 | N26: 0.75 | O26: 0.75 | P26: 0.75 | Q26: 0.75 | R26: 0.75 | S26: 0.75 | T26: 0.75 | U26: 0.75 | V26: 0.75 | W26: 0.75 | X26: =AVERAGE(D26:G26) -> 0.75 | Y26: =AVERAGE(H26:K26) -> 0.75 | Z26: =AVERAGE(L26:O26) -> 0.75 | AA26: =AVERAGE(P26:S26) -> 0.75 | AB26: =AVERAGE(T26:W26) -> 0.75
A27: Stage Ramp Utilization Cap | B27: GPT-selected stage ramp contract | C27: 0 | D27: 0.25 | E27: 0.31 | F27: 0.37 | G27: 0.43 | H27: 0.49 | I27: 0.55 | J27: 0.61 | K27: 0.67 | L27: 0.73 | M27: 0.79 | N27: 0.85 | O27: 0.85 | P27: 0.85 | Q27: 0.85 | R27: 0.85 | S27: 0.85 | T27: 0.85 | U27: 0.85 | V27: 0.85 | W27: 0.85 | X27: =AVERAGE(D27:G27) -> 0.34 | Y27: =AVERAGE(H27:K27) -> 0.58 | Z27: =AVERAGE(L27:O27) -> 0.805 | AA27: =AVERAGE(P27:S27) -> 0.85 | AB27: =AVERAGE(T27:W27) -> 0.85
A28: Stage Ramp COGS % Revenue Target | B28: GPT-selected stage ramp contract | C28: 0 | D28: 0.48 | E28: 0.48 | F28: 0.48 | G28: 0.48 | H28: 0.48 | I28: 0.48 | J28: 0.48 | K28: 0.48 | L28: 0.48 | M28: 0.48 | N28: 0.48 | O28: 0.48 | P28: 0.48 | Q28: 0.48 | R28: 0.48 | S28: 0.48 | T28: 0.48 | U28: 0.48 | V28: 0.48 | W28: 0.48 | X28: =AVERAGE(D28:G28) -> 0.48 | Y28: =AVERAGE(H28:K28) -> 0.48 | Z28: =AVERAGE(L28:O28) -> 0.48 | AA28: =AVERAGE(P28:S28) -> 0.48 | AB28: =AVERAGE(T28:W28) -> 0.48
A29: Stage Ramp COGS % Revenue Max | B29: GPT-selected stage ramp contract | C29: 0 | D29: 0.71 | E29: 0.71 | F29: 0.71 | G29: 0.71 | H29: 0.71 | I29: 0.71 | J29: 0.71 | K29: 0.71 | L29: 0.71 | M29: 0.71 | N29: 0.71 | O29: 0.71 | P29: 0.71 | Q29: 0.71 | R29: 0.71 | S29: 0.71 | T29: 0.71 | U29: 0.71 | V29: 0.71 | W29: 0.71 | X29: =AVERAGE(D29:G29) -> 0.71 | Y29: =AVERAGE(H29:K29) -> 0.71 | Z29: =AVERAGE(L29:O29) -> 0.71 | AA29: =AVERAGE(P29:S29) -> 0.71 | AB29: =AVERAGE(T29:W29) -> 0.71
A30: Stage Ramp Marketing % Revenue Max | B30: GPT-selected stage ramp contract | C30: 0 | D30: 0.4 | E30: 0.4 | F30: 0.4 | G30: 0.4 | H30: 0.4 | I30: 0.4 | J30: 0.4 | K30: 0.4 | L30: 0.4 | M30: 0.4 | N30: 0.4 | O30: 0.4 | P30: 0.4 | Q30: 0.4 | R30: 0.4 | S30: 0.4 | T30: 0.4 | U30: 0.4 | V30: 0.4 | W30: 0.4 | X30: =AVERAGE(D30:G30) -> 0.4 | Y30: =AVERAGE(H30:K30) -> 0.4 | Z30: =AVERAGE(L30:O30) -> 0.4 | AA30: =AVERAGE(P30:S30) -> 0.4 | AB30: =AVERAGE(T30:W30) -> 0.4
A31: Stage Ramp R&D % Revenue Max | B31: GPT-selected stage ramp contract | C31: 0 | D31: 0.5 | E31: 0.5 | F31: 0.5 | G31: 0.5 | H31: 0.5 | I31: 0.5 | J31: 0.5 | K31: 0.5 | L31: 0.5 | M31: 0.5 | N31: 0.5 | O31: 0.5 | P31: 0.5 | Q31: 0.5 | R31: 0.5 | S31: 0.5 | T31: 0.5 | U31: 0.5 | V31: 0.5 | W31: 0.5 | X31: =AVERAGE(D31:G31) -> 0.5 | Y31: =AVERAGE(H31:K31) -> 0.5 | Z31: =AVERAGE(L31:O31) -> 0.5 | AA31: =AVERAGE(P31:S31) -> 0.5 | AB31: =AVERAGE(T31:W31) -> 0.5
A32: Stage Ramp G&A % Revenue Max | B32: GPT-selected stage ramp contract | C32: 0 | D32: 0.53 | E32: 0.53 | F32: 0.53 | G32: 0.53 | H32: 0.53 | I32: 0.53 | J32: 0.53 | K32: 0.53 | L32: 0.53 | M32: 0.53 | N32: 0.53 | O32: 0.53 | P32: 0.53 | Q32: 0.53 | R32: 0.53 | S32: 0.53 | T32: 0.53 | U32: 0.53 | V32: 0.53 | W32: 0.53 | X32: =AVERAGE(D32:G32) -> 0.53 | Y32: =AVERAGE(H32:K32) -> 0.53 | Z32: =AVERAGE(L32:O32) -> 0.53 | AA32: =AVERAGE(P32:S32) -> 0.53 | AB32: =AVERAGE(T32:W32) -> 0.53
A33: Stage Ramp Lease % Revenue Max | B33: GPT-selected stage ramp contract | C33: 0 | D33: 0.13 | E33: 0.13 | F33: 0.13 | G33: 0.13 | H33: 0.13 | I33: 0.13 | J33: 0.13 | K33: 0.13 | L33: 0.13 | M33: 0.13 | N33: 0.13 | O33: 0.13 | P33: 0.13 | Q33: 0.13 | R33: 0.13 | S33: 0.13 | T33: 0.13 | U33: 0.13 | V33: 0.13 | W33: 0.13 | X33: =AVERAGE(D33:G33) -> 0.13 | Y33: =AVERAGE(H33:K33) -> 0.13 | Z33: =AVERAGE(L33:O33) -> 0.13 | AA33: =AVERAGE(P33:S33) -> 0.13 | AB33: =AVERAGE(T33:W33) -> 0.13
A34: Stage Ramp Net Income Margin Floor | B34: GPT-selected stage ramp contract | C34: 0 | D34: -0.1 | E34: -0.1 | F34: -0.1 | G34: -0.1 | H34: 0 | I34: 0 | J34: 0 | K34: 0 | L34: 0 | M34: 0 | N34: 0.02 | O34: 0.03 | P34: 0.03 | Q34: 0.04 | R34: 0.04 | S34: 0.05 | T34: 0.05 | U34: 0.06 | V34: 0.06 | W34: 0.07 | X34: =AVERAGE(D34:G34) -> -0.1 | Y34: =AVERAGE(H34:K34) -> 0 | Z34: =AVERAGE(L34:O34) -> 0.0125 | AA34: =AVERAGE(P34:S34) -> 0.04 | AB34: =AVERAGE(T34:W34) -> 0.06

Sheet Payroll Schedule
A1: Payroll Schedule
A2: OEWS-title, capacity/utilization-driven payroll source. Model Inputs links to Total Payroll.
C4: Stub | D4: Q1 | E4: Q2 | F4: Q3 | G4: Q4 | H4: Q5 | I4: Q6 | J4: Q7 | K4: Q8 | L4: Q9 | M4: Q10 | N4: Q11 | O4: Q12 | P4: Q13 | Q4: Q14 | R4: Q15 | S4: Q16 | T4: Q17 | U4: Q18 | V4: Q19 | W4: Q20 | X4: Y1 | Y4: Y2 | Z4: Y3 | AA4: Y4 | AB4: Y5
C5: 46162 | D5: 46295 | E5: 46387 | F5: 46477 | G5: 46568 | H5: 46660 | I5: 46752 | J5: 46843 | K5: 46934 | L5: 47026 | M5: 47118 | N5: 47208 | O5: 47299 | P5: 47391 | Q5: 47483 | R5: 47573 | S5: 47664 | T5: 47756 | U5: 47848 | V5: 47938 | W5: 48029 | X5: Annual | Y5: Annual | Z5: Annual | AA5: Annual | AB5: Annual
A6: Payroll Assumptions
A7: Capacity Labor Model | B7: labor_driven
A8: Labor Intensity Class | B8: expert
A9: Wage Positioning Tier | B9: premium
A10: Wage Positioning Multiplier | B10: 1.5
A11: Capacity Units per Supporting FTE | B11: 34.36
A12: Target Payroll % of Revenue | B12: 0.45
A14: Quarter Summary
A15: Total Ending FTE | B15: Formula output from payroll detail | C15: =SUMIFS($G$27:$G$86,$A$27:$A$86,0) -> 0 | D15: =SUMIFS($G$27:$G$86,$A$27:$A$86,1) -> 3 | E15: =SUMIFS($G$27:$G$86,$A$27:$A$86,2) -> 3 | F15: =SUMIFS($G$27:$G$86,$A$27:$A$86,3) -> 3 | G15: =SUMIFS($G$27:$G$86,$A$27:$A$86,4) -> 3 | H15: =SUMIFS($G$27:$G$86,$A$27:$A$86,5) -> 3 | I15: =SUMIFS($G$27:$G$86,$A$27:$A$86,6) -> 3 | J15: =SUMIFS($G$27:$G$86,$A$27:$A$86,7) -> 3 | K15: =SUMIFS($G$27:$G$86,$A$27:$A$86,8) -> 3 | L15: =SUMIFS($G$27:$G$86,$A$27:$A$86,9) -> 3 | M15: =SUMIFS($G$27:$G$86,$A$27:$A$86,10) -> 3 | N15: =SUMIFS($G$27:$G$86,$A$27:$A$86,11) -> 3 | O15: =SUMIFS($G$27:$G$86,$A$27:$A$86,12) -> 3 | P15: =SUMIFS($G$27:$G$86,$A$27:$A$86,13) -> 3 | Q15: =SUMIFS($G$27:$G$86,$A$27:$A$86,14) -> 3 | R15: =SUMIFS($G$27:$G$86,$A$27:$A$86,15) -> 3 | S15: =SUMIFS($G$27:$G$86,$A$27:$A$86,16) -> 3 | T15: =SUMIFS($G$27:$G$86,$A$27:$A$86,17) -> 3 | U15: =SUMIFS($G$27:$G$86,$A$27:$A$86,18) -> 3 | V15: =SUMIFS($G$27:$G$86,$A$27:$A$86,19) -> 3 | W15: =SUMIFS($G$27:$G$86,$A$27:$A$86,20) -> 3 | X15: =G15 -> 3 | Y15: =K15 -> 3 | Z15: =O15 -> 3 | AA15: =S15 -> 3 | AB15: =W15 -> 3
A16: Total Average FTE | B16: Formula output from payroll detail | C16: =SUMIFS($H$27:$H$86,$A$27:$A$86,0) -> 0 | D16: =SUMIFS($H$27:$H$86,$A$27:$A$86,1) -> 3 | E16: =SUMIFS($H$27:$H$86,$A$27:$A$86,2) -> 3 | F16: =SUMIFS($H$27:$H$86,$A$27:$A$86,3) -> 3 | G16: =SUMIFS($H$27:$H$86,$A$27:$A$86,4) -> 3 | H16: =SUMIFS($H$27:$H$86,$A$27:$A$86,5) -> 3 | I16: =SUMIFS($H$27:$H$86,$A$27:$A$86,6) -> 3 | J16: =SUMIFS($H$27:$H$86,$A$27:$A$86,7) -> 3 | K16: =SUMIFS($H$27:$H$86,$A$27:$A$86,8) -> 3 | L16: =SUMIFS($H$27:$H$86,$A$27:$A$86,9) -> 3 | M16: =SUMIFS($H$27:$H$86,$A$27:$A$86,10) -> 3 | N16: =SUMIFS($H$27:$H$86,$A$27:$A$86,11) -> 3 | O16: =SUMIFS($H$27:$H$86,$A$27:$A$86,12) -> 3 | P16: =SUMIFS($H$27:$H$86,$A$27:$A$86,13) -> 3 | Q16: =SUMIFS($H$27:$H$86,$A$27:$A$86,14) -> 3 | R16: =SUMIFS($H$27:$H$86,$A$27:$A$86,15) -> 3 | S16: =SUMIFS($H$27:$H$86,$A$27:$A$86,16) -> 3 | T16: =SUMIFS($H$27:$H$86,$A$27:$A$86,17) -> 3 | U16: =SUMIFS($H$27:$H$86,$A$27:$A$86,18) -> 3 | V16: =SUMIFS($H$27:$H$86,$A$27:$A$86,19) -> 3 | W16: =SUMIFS($H$27:$H$86,$A$27:$A$86,20) -> 3 | X16: =AVERAGE(D16:G16) -> 3 | Y16: =AVERAGE(H16:K16) -> 3 | Z16: =AVERAGE(L16:O16) -> 3 | AA16: =AVERAGE(P16:S16) -> 3 | AB16: =AVERAGE(T16:W16) -> 3
A17: Total Payroll | B17: Formula output from payroll detail | C17: =SUMIFS($M$27:$M$86,$A$27:$A$86,0) -> 0 | D17: =SUMIFS($M$27:$M$86,$A$27:$A$86,1) -> 115547.95 | E17: =SUMIFS($M$27:$M$86,$A$27:$A$86,2) -> 115547.95 | F17: =SUMIFS($M$27:$M$86,$A$27:$A$86,3) -> 115547.95 | G17: =SUMIFS($M$27:$M$86,$A$27:$A$86,4) -> 115547.95 | H17: =SUMIFS($M$27:$M$86,$A$27:$A$86,5) -> 119014.33 | I17: =SUMIFS($M$27:$M$86,$A$27:$A$86,6) -> 119014.33 | J17: =SUMIFS($M$27:$M$86,$A$27:$A$86,7) -> 119014.33 | K17: =SUMIFS($M$27:$M$86,$A$27:$A$86,8) -> 119014.33 | L17: =SUMIFS($M$27:$M$86,$A$27:$A$86,9) -> 122584.71 | M17: =SUMIFS($M$27:$M$86,$A$27:$A$86,10) -> 122584.71 | N17: =SUMIFS($M$27:$M$86,$A$27:$A$86,11) -> 122584.71 | O17: =SUMIFS($M$27:$M$86,$A$27:$A$86,12) -> 122584.71 | P17: =SUMIFS($M$27:$M$86,$A$27:$A$86,13) -> 126262.76 | Q17: =SUMIFS($M$27:$M$86,$A$27:$A$86,14) -> 126262.76 | R17: =SUMIFS($M$27:$M$86,$A$27:$A$86,15) -> 126262.76 | S17: =SUMIFS($M$27:$M$86,$A$27:$A$86,16) -> 126262.76 | T17: =SUMIFS($M$27:$M$86,$A$27:$A$86,17) -> 130050.35 | U17: =SUMIFS($M$27:$M$86,$A$27:$A$86,18) -> 130050.35 | V17: =SUMIFS($M$27:$M$86,$A$27:$A$86,19) -> 130050.35 | W17: =SUMIFS($M$27:$M$86,$A$27:$A$86,20) -> 130050.35 | X17: =SUM(D17:G17) -> 462191.8 | Y17: =SUM(H17:K17) -> 476057.31 | Z17: =SUM(L17:O17) -> 490338.83 | AA17: =SUM(P17:S17) -> 505051.06 | AB17: =SUM(T17:W17) -> 520201.38
A18: Total Revenue | B18: Linked from Revenue Drivers | C18: ='Revenue Drivers'!C20 -> 1528800 | D18: ='Revenue Drivers'!D20 -> 274877.56 | E18: ='Revenue Drivers'!E20 -> 277227.25 | F18: ='Revenue Drivers'!F20 -> 281912.38 | G18: ='Revenue Drivers'!G20 -> 286019.97 | H18: ='Revenue Drivers'!H20 -> 297884.01 | I18: ='Revenue Drivers'!I20 -> 299958.22 | J18: ='Revenue Drivers'!J20 -> 305514.83 | ... W18: ='Revenue Drivers'!W20 -> 639387.23 | X18: =SUM(D18:G18) -> 1120037.2 | Y18: =SUM(H18:K18) -> 1213990.5 | Z18: =SUM(L18:O18) -> 1528143.9 | AA18: =SUM(P18:S18) -> 2310993.4 | AB18: =SUM(T18:W18) -> 2520947.9
A19: Total Capacity Units | B19: Linked from Revenue Drivers | C19: ='Revenue Drivers'!C19 -> 234 | D19: ='Revenue Drivers'!D19 -> 103.08 | E19: ='Revenue Drivers'!E19 -> 103.08 | F19: ='Revenue Drivers'!F19 -> 103.08 | G19: ='Revenue Drivers'!G19 -> 103.08 | H19: ='Revenue Drivers'!H19 -> 103.08 | I19: ='Revenue Drivers'!I19 -> 103.08 | J19: ='Revenue Drivers'!J19 -> 103.08 | ... W19: ='Revenue Drivers'!W19 -> 103.08 | X19: =SUM(D19:G19) -> 412.32 | Y19: =SUM(H19:K19) -> 412.32 | Z19: =SUM(L19:O19) -> 412.32 | AA19: =SUM(P19:S19) -> 412.32 | AB19: =SUM(T19:W19) -> 412.32
A20: Revenue per Employee | B20: Python-built productivity formula | C20: =IFERROR(C18/C16,0) -> 0 | D20: =IFERROR(D18/D16,0) -> 91625.854 | E20: =IFERROR(E18/E16,0) -> 92409.083 | F20: =IFERROR(F18/F16,0) -> 93970.793 | G20: =IFERROR(G18/G16,0) -> 95339.991 | H20: =IFERROR(H18/H16,0) -> 99294.669 | I20: =IFERROR(I18/I16,0) -> 99986.072 | J20: =IFERROR(J18/J16,0) -> 101838.28 | ... AB20: =IFERROR(AB18/AB16,0) -> 840315.96
A21: Units per Employee | B21: Python-built productivity formula | C21: =IFERROR(C19/C16,0) -> 0 | D21: =IFERROR(D19/D16,0) -> 34.36 | E21: =IFERROR(E19/E16,0) -> 34.36 | F21: =IFERROR(F19/F16,0) -> 34.36 | G21: =IFERROR(G19/G16,0) -> 34.36 | H21: =IFERROR(H19/H16,0) -> 34.36 | I21: =IFERROR(I19/I16,0) -> 34.36 | J21: =IFERROR(J19/J16,0) -> 34.36 | ... AB21: =IFERROR(AB19/AB16,0) -> 137.44
A22: Payroll % of Revenue | B22: Python-built productivity formula | C22: =IFERROR(C17/C18,0) -> 0 | D22: =IFERROR(D17/D18,0) -> 0.42036152 | E22: =IFERROR(E17/E18,0) -> 0.41679867 | F22: =IFERROR(F17/F18,0) -> 0.40987186 | G22: =IFERROR(G17/G18,0) -> 0.4039856 | H22: =IFERROR(H17/H18,0) -> 0.39953245 | I22: =IFERROR(I17/I18,0) -> 0.39676969 | J22: =IFERROR(J17/J18,0) -> 0.38955335 | ... AB22: =IFERROR(AB17/AB18,0) -> 0.2063515
A25: Payroll Detail
A26: Quarter | B26: Staffing Class | C26: Title / Person | D26: OEWS Title | E26: Starting FTE | F26: Hires | G26: Ending FTE | H26: Average FTE | I26: Annual Wage | J26: Benefits % | K26: Wage Cost | L26: Taxes & Benefits | M26: Total Payroll | N26: Wage Source
A27: 1 | B27: key_person | C27: Managing Partner | E27: 1 | F27: 0 | G27: =E27+F27 -> 1 | H27: =(E27+G27)/2 -> 1 | I27: 143470 | J27: 0.22 | K27: =H27*I27/4 -> 35867.5 | L27: =K27*J27 -> 7890.85 | M27: =K27+L27 -> 43758.35 | N27: oews_median
A28: 2 | B28: key_person | C28: Managing Partner | E28: 1 | F28: 0 | G28: =E28+F28 -> 1 | H28: =(E28+G28)/2 -> 1 | I28: 143470 | J28: 0.22 | K28: =H28*I28/4 -> 35867.5 | L28: =K28*J28 -> 7890.85 | M28: =K28+L28 -> 43758.35 | N28: oews_median
A29: 3 | B29: key_person | C29: Managing Partner | E29: 1 | F29: 0 | G29: =E29+F29 -> 1 | H29: =(E29+G29)/2 -> 1 | I29: 143470 | J29: 0.22 | K29: =H29*I29/4 -> 35867.5 | L29: =K29*J29 -> 7890.85 | M29: =K29+L29 -> 43758.35 | N29: oews_median
A30: 4 | B30: key_person | C30: Managing Partner | E30: 1 | F30: 0 | G30: =E30+F30 -> 1 | H30: =(E30+G30)/2 -> 1 | I30: 143470 | J30: 0.22 | K30: =H30*I30/4 -> 35867.5 | L30: =K30*J30 -> 7890.85 | M30: =K30+L30 -> 43758.35 | N30: oews_median
A31: 5 | B31: key_person | C31: Managing Partner | E31: 1 | F31: 0 | G31: =E31+F31 -> 1 | H31: =(E31+G31)/2 -> 1 | I31: 147774 | J31: 0.22 | K31: =H31*I31/4 -> 36943.5 | L31: =K31*J31 -> 8127.57 | M31: =K31+L31 -> 45071.07 | N31: oews_median
A32: 6 | B32: key_person | C32: Managing Partner | E32: 1 | F32: 0 | G32: =E32+F32 -> 1 | H32: =(E32+G32)/2 -> 1 | I32: 147774 | J32: 0.22 | K32: =H32*I32/4 -> 36943.5 | L32: =K32*J32 -> 8127.57 | M32: =K32+L32 -> 45071.07 | N32: oews_median
A33: 7 | B33: key_person | C33: Managing Partner | E33: 1 | F33: 0 | G33: =E33+F33 -> 1 | H33: =(E33+G33)/2 -> 1 | I33: 147774 | J33: 0.22 | K33: =H33*I33/4 -> 36943.5 | L33: =K33*J33 -> 8127.57 | M33: =K33+L33 -> 45071.07 | N33: oews_median
A34: 8 | B34: key_person | C34: Managing Partner | E34: 1 | F34: 0 | G34: =E34+F34 -> 1 | H34: =(E34+G34)/2 -> 1 | I34: 147774 | J34: 0.22 | K34: =H34*I34/4 -> 36943.5 | L34: =K34*J34 -> 8127.57 | M34: =K34+L34 -> 45071.07 | N34: oews_median
A35: 9 | B35: key_person | C35: Managing Partner | E35: 1 | F35: 0 | G35: =E35+F35 -> 1 | H35: =(E35+G35)/2 -> 1 | I35: 152207 | J35: 0.22 | K35: =H35*I35/4 -> 38051.75 | L35: =K35*J35 -> 8371.385 | M35: =K35+L35 -> 46423.135 | N35: oews_median
A36: 10 | B36: key_person | C36: Managing Partner | E36: 1 | F36: 0 | G36: =E36+F36 -> 1 | H36: =(E36+G36)/2 -> 1 | I36: 152207 | J36: 0.22 | K36: =H36*I36/4 -> 38051.75 | L36: =K36*J36 -> 8371.385 | M36: =K36+L36 -> 46423.135 | N36: oews_median
A37: 11 | B37: key_person | C37: Managing Partner | E37: 1 | F37: 0 | G37: =E37+F37 -> 1 | H37: =(E37+G37)/2 -> 1 | I37: 152207 | J37: 0.22 | K37: =H37*I37/4 -> 38051.75 | L37: =K37*J37 -> 8371.385 | M37: =K37+L37 -> 46423.135 | N37: oews_median
A38: 12 | B38: key_person | C38: Managing Partner | E38: 1 | F38: 0 | G38: =E38+F38 -> 1 | H38: =(E38+G38)/2 -> 1 | I38: 152207 | J38: 0.22 | K38: =H38*I38/4 -> 38051.75 | L38: =K38*J38 -> 8371.385 | M38: =K38+L38 -> 46423.135 | N38: oews_median
... A66: 20 | B66: key_person | C66: Partner | E66: 1 | F66: 0 | G66: =E66+F66 -> 1 | H66: =(E66+G66)/2 -> 1 | I66: 161477 | J66: 0.22 | K66: =H66*I66/4 -> 40369.25 | L66: =K66*J66 -> 8881.235 | M66: =K66+L66 -> 49250.485 | N66: oews_median
A67: 1 | B67: supporting_staff | C67: Paralegals and Legal Assistants | D67: Paralegals and Legal Assistants | E67: 1 | F67: 0 | G67: =E67+F67 -> 1 | H67: =(E67+G67)/2 -> 1 | I67: 89700 | J67: 0.25 | K67: =H67*I67/4 -> 22425 | L67: =K67*J67 -> 5606.25 | M67: =K67+L67 -> 28031.25 | N67: oews_title_catalog:oews_median
A68: 2 | B68: supporting_staff | C68: Paralegals and Legal Assistants | D68: Paralegals and Legal Assistants | E68: 1 | F68: 0 | G68: =E68+F68 -> 1 | H68: =(E68+G68)/2 -> 1 | I68: 89700 | J68: 0.25 | K68: =H68*I68/4 -> 22425 | L68: =K68*J68 -> 5606.25 | M68: =K68+L68 -> 28031.25 | N68: oews_title_catalog:oews_median
A69: 3 | B69: supporting_staff | C69: Paralegals and Legal Assistants | D69: Paralegals and Legal Assistants | E69: 1 | F69: 0 | G69: =E69+F69 -> 1 | H69: =(E69+G69)/2 -> 1 | I69: 89700 | J69: 0.25 | K69: =H69*I69/4 -> 22425 | L69: =K69*J69 -> 5606.25 | M69: =K69+L69 -> 28031.25 | N69: oews_title_catalog:oews_median
A70: 4 | B70: supporting_staff | C70: Paralegals and Legal Assistants | D70: Paralegals and Legal Assistants | E70: 1 | F70: 0 | G70: =E70+F70 -> 1 | H70: =(E70+G70)/2 -> 1 | I70: 89700 | J70: 0.25 | K70: =H70*I70/4 -> 22425 | L70: =K70*J70 -> 5606.25 | M70: =K70+L70 -> 28031.25 | N70: oews_title_catalog:oews_median
A71: 5 | B71: supporting_staff | C71: Paralegals and Legal Assistants | D71: Paralegals and Legal Assistants | E71: 1 | F71: 0 | G71: =E71+F71 -> 1 | H71: =(E71+G71)/2 -> 1 | I71: 92391 | J71: 0.25 | K71: =H71*I71/4 -> 23097.75 | L71: =K71*J71 -> 5774.4375 | M71: =K71+L71 -> 28872.188 | N71: oews_title_catalog:oews_median
A72: 6 | B72: supporting_staff | C72: Paralegals and Legal Assistants | D72: Paralegals and Legal Assistants | E72: 1 | F72: 0 | G72: =E72+F72 -> 1 | H72: =(E72+G72)/2 -> 1 | I72: 92391 | J72: 0.25 | K72: =H72*I72/4 -> 23097.75 | L72: =K72*J72 -> 5774.4375 | M72: =K72+L72 -> 28872.188 | N72: oews_title_catalog:oews_median
A73: 7 | B73: supporting_staff | C73: Paralegals and Legal Assistants | D73: Paralegals and Legal Assistants | E73: 1 | F73: 0 | G73: =E73+F73 -> 1 | H73: =(E73+G73)/2 -> 1 | I73: 92391 | J73: 0.25 | K73: =H73*I73/4 -> 23097.75 | L73: =K73*J73 -> 5774.4375 | M73: =K73+L73 -> 28872.188 | N73: oews_title_catalog:oews_median
A74: 8 | B74: supporting_staff | C74: Paralegals and Legal Assistants | D74: Paralegals and Legal Assistants | E74: 1 | F74: 0 | G74: =E74+F74 -> 1 | H74: =(E74+G74)/2 -> 1 | I74: 92391 | J74: 0.25 | K74: =H74*I74/4 -> 23097.75 | L74: =K74*J74 -> 5774.4375 | M74: =K74+L74 -> 28872.188 | N74: oews_title_catalog:oews_median
A75: 9 | B75: supporting_staff | C75: Paralegals and Legal Assistants | D75: Paralegals and Legal Assistants | E75: 1 | F75: 0 | G75: =E75+F75 -> 1 | H75: =(E75+G75)/2 -> 1 | I75: 95163 | J75: 0.25 | K75: =H75*I75/4 -> 23790.75 | L75: =K75*J75 -> 5947.6875 | M75: =K75+L75 -> 29738.438 | N75: oews_title_catalog:oews_median
A76: 10 | B76: supporting_staff | C76: Paralegals and Legal Assistants | D76: Paralegals and Legal Assistants | E76: 1 | F76: 0 | G76: =E76+F76 -> 1 | H76: =(E76+G76)/2 -> 1 | I76: 95163 | J76: 0.25 | K76: =H76*I76/4 -> 23790.75 | L76: =K76*J76 -> 5947.6875 | M76: =K76+L76 -> 29738.438 | N76: oews_title_catalog:oews_median
A77: 11 | B77: supporting_staff | C77: Paralegals and Legal Assistants | D77: Paralegals and Legal Assistants | E77: 1 | F77: 0 | G77: =E77+F77 -> 1 | H77: =(E77+G77)/2 -> 1 | I77: 95163 | J77: 0.25 | K77: =H77*I77/4 -> 23790.75 | L77: =K77*J77 -> 5947.6875 | M77: =K77+L77 -> 29738.438 | N77: oews_title_catalog:oews_median
A78: 12 | B78: supporting_staff | C78: Paralegals and Legal Assistants | D78: Paralegals and Legal Assistants | E78: 1 | F78: 0 | G78: =E78+F78 -> 1 | H78: =(E78+G78)/2 -> 1 | I78: 95163 | J78: 0.25 | K78: =H78*I78/4 -> 23790.75 | L78: =K78*J78 -> 5947.6875 | M78: =K78+L78 -> 29738.438 | N78: oews_title_catalog:oews_median
... A86: 20 | B86: supporting_staff | C86: Paralegals and Legal Assistants | D86: Paralegals and Legal Assistants | E86: 1 | F86: 0 | G86: =E86+F86 -> 1 | H86: =(E86+G86)/2 -> 1 | I86: 100958 | J86: 0.25 | K86: =H86*I86/4 -> 25239.5 | L86: =K86*J86 -> 6309.875 | M86: =K86+L86 -> 31549.375 | N86: oews_title_catalog:oews_median

Sheet Debt Schedule
A1: Debt Schedule
A2: Debt, interest, and capital lease mechanics. Model Inputs links to calculated outputs.
C4: Stub | D4: Q1 | E4: Q2 | F4: Q3 | G4: Q4 | H4: Q5 | I4: Q6 | J4: Q7 | K4: Q8 | L4: Q9 | M4: Q10 | N4: Q11 | O4: Q12 | P4: Q13 | Q4: Q14 | R4: Q15 | S4: Q16 | T4: Q17 | U4: Q18 | V4: Q19 | W4: Q20 | X4: Y1 | Y4: Y2 | Z4: Y3 | AA4: Y4 | AB4: Y5
C5: 46162 | D5: 46295 | E5: 46387 | F5: 46477 | G5: 46568 | H5: 46660 | I5: 46752 | J5: 46843 | K5: 46934 | L5: 47026 | M5: 47118 | N5: 47208 | O5: 47299 | P5: 47391 | Q5: 47483 | R5: 47573 | S5: 47664 | T5: 47756 | U5: 47848 | V5: 47938 | W5: 48029 | X5: Annual | Y5: Annual | Z5: Annual | AA5: Annual | AB5: Annual
A6: Debt Amortization
A7: Opening Debt | B7: Calculated | C7: 0 | D7: =C11 -> 0 | E7: =D11 -> 0 | F7: =E11 -> 0 | G7: =F11 -> 0 | H7: =G11 -> 0 | I7: =H11 -> 0 | J7: =I11 -> 0 | K7: =J11 -> 0 | ... W7: =V11 -> 0 | X7: =G7 -> 0 | Y7: =K7 -> 0 | Z7: =O7 -> 0 | AA7: =S7 -> 0 | AB7: =W7 -> 0
A8: Debt Issuance | B8: Source borrowing | C8: 0 | D8: 0 | E8: 0 | F8: 0 | G8: 0 | H8: 0 | I8: 0 | J8: 0 | K8: 0 | L8: 0 | M8: 0 | N8: 0 | O8: 0 | P8: 0 | Q8: 0 | R8: 0 | S8: 0 | T8: 0 | U8: 0 | V8: 0 | W8: 0 | X8: =SUM(D8:G8) -> 0 | Y8: =SUM(H8:K8) -> 0 | Z8: =SUM(L8:O8) -> 0 | AA8: =SUM(P8:S8) -> 0 | AB8: =SUM(T8:W8) -> 0
A9: Requested Debt Repayment | B9: Source scheduled repayment | C9: 0 | D9: 0 | E9: 0 | F9: 0 | G9: 0 | H9: 0 | I9: 0 | J9: 0 | K9: 0 | L9: 0 | M9: 0 | N9: 0 | O9: 0 | P9: 0 | Q9: 0 | R9: 0 | S9: 0 | T9: 0 | U9: 0 | V9: 0 | W9: 0 | X9: =SUM(D9:G9) -> 0 | Y9: =SUM(H9:K9) -> 0 | Z9: =SUM(L9:O9) -> 0 | AA9: =SUM(P9:S9) -> 0 | AB9: =SUM(T9:W9) -> 0
A10: Actual Debt Repayment | B10: MIN(requested repayment, opening debt + issuance) | C10: =MIN(C9,C7+C8) -> 0 | D10: =MIN(D9,D7+D8) -> 0 | E10: =MIN(E9,E7+E8) -> 0 | F10: =MIN(F9,F7+F8) -> 0 | G10: =MIN(G9,G7+G8) -> 0 | H10: =MIN(H9,H7+H8) -> 0 | I10: =MIN(I9,I7+I8) -> 0 | J10: =MIN(J9,J7+J8) -> 0 | ... W10: =MIN(W9,W7+W8) -> 0 | X10: =SUM(D10:G10) -> 0 | Y10: =SUM(H10:K10) -> 0 | Z10: =SUM(L10:O10) -> 0 | AA10: =SUM(P10:S10) -> 0 | AB10: =SUM(T10:W10) -> 0
A11: Closing Debt | B11: Calculated | C11: =MAX(0,C7+C8-C10) -> 0 | D11: =MAX(0,D7+D8-D10) -> 0 | E11: =MAX(0,E7+E8-E10) -> 0 | F11: =MAX(0,F7+F8-F10) -> 0 | G11: =MAX(0,G7+G8-G10) -> 0 | H11: =MAX(0,H7+H8-H10) -> 0 | I11: =MAX(0,I7+I8-I10) -> 0 | J11: =MAX(0,J7+J8-J10) -> 0 | ... W11: =MAX(0,W7+W8-W10) -> 0 | X11: =G11 -> 0 | Y11: =K11 -> 0 | Z11: =O11 -> 0 | AA11: =S11 -> 0 | AB11: =W11 -> 0
A12: Interest Rate | B12: Source rate | C12: 0 | D12: 0.023813 | E12: 0.023813 | F12: 0.023813 | G12: 0.023813 | H12: 0.023813 | I12: 0.023813 | J12: 0.023813 | K12: 0.023813 | L12: 0.023813 | M12: 0.023813 | N12: 0.023813 | O12: 0.023813 | P12: 0.023813 | Q12: 0.023813 | R12: 0.023813 | S12: 0.023813 | T12: 0.023813 | U12: 0.023813 | V12: 0.023813 | W12: 0.023813 | X12: =SUM(D12:G12) -> 0.095252 | Y12: =SUM(H12:K12) -> 0.095252 | Z12: =SUM(L12:O12) -> 0.095252 | AA12: =SUM(P12:S12) -> 0.095252 | AB12: =SUM(T12:W12) -> 0.095252
A13: Interest Expense | B13: Average debt balance x rate | C13: =((C7+C11)/2)*C12 -> 0 | D13: =((D7+D11)/2)*D12 -> 0 | E13: =((E7+E11)/2)*E12 -> 0 | F13: =((F7+F11)/2)*F12 -> 0 | G13: =((G7+G11)/2)*G12 -> 0 | H13: =((H7+H11)/2)*H12 -> 0 | I13: =((I7+I11)/2)*I12 -> 0 | J13: =((J7+J11)/2)*J12 -> 0 | ... W13: =((W7+W11)/2)*W12 -> 0 | X13: =SUM(D13:G13) -> 0 | Y13: =SUM(H13:K13) -> 0 | Z13: =SUM(L13:O13) -> 0 | AA13: =SUM(P13:S13) -> 0 | AB13: =SUM(T13:W13) -> 0
A14: Total Debt Service | B14: Interest + actual repayment | C14: =C13+C10 -> 0 | D14: =D13+D10 -> 0 | E14: =E13+E10 -> 0 | F14: =F13+F10 -> 0 | G14: =G13+G10 -> 0 | H14: =H13+H10 -> 0 | I14: =I13+I10 -> 0 | J14: =J13+J10 -> 0 | ... W14: =W13+W10 -> 0 | X14: =SUM(D14:G14) -> 0 | Y14: =SUM(H14:K14) -> 0 | Z14: =SUM(L14:O14) -> 0 | AA14: =SUM(P14:S14) -> 0 | AB14: =SUM(T14:W14) -> 0
A17: Capital Lease Schedule
A18: Lease Opening Balance | B18: Capital leases | C18: 0 | D18: =C23 -> 0 | E18: =D23 -> 0 | F18: =E23 -> 0 | G18: =F23 -> 0 | H18: =G23 -> 0 | I18: =H23 -> 0 | J18: =I23 -> 0 | K18: =J23 -> 0 | ... W18: =V23 -> 0 | X18: =G18 -> 0 | Y18: =K18 -> 0 | Z18: =O18 -> 0 | AA18: =S18 -> 0 | AB18: =W18 -> 0
A19: Requested Lease Principal Repayments | B19: Capital leases | C19: 0 | D19: 0 | E19: 0 | F19: 0 | G19: 0 | H19: 0 | I19: 0 | J19: 0 | K19: 0 | L19: 0 | M19: 0 | N19: 0 | O19: 0 | P19: 0 | Q19: 0 | R19: 0 | S19: 0 | T19: 0 | U19: 0 | V19: 0 | W19: 0 | X19: =SUM(D19:G19) -> 0 | Y19: =SUM(H19:K19) -> 0 | Z19: =SUM(L19:O19) -> 0 | AA19: =SUM(P19:S19) -> 0 | AB19: =SUM(T19:W19) -> 0
A20: Lease Principal Repayments | B20: Capital leases | C20: =MIN(C19,C18+C21) -> 0 | D20: =MIN(D19,D18+D21) -> 0 | E20: =MIN(E19,E18+E21) -> 0 | F20: =MIN(F19,F18+F21) -> 0 | G20: =MIN(G19,G18+G21) -> 0 | H20: =MIN(H19,H18+H21) -> 0 | I20: =MIN(I19,I18+I21) -> 0 | J20: =MIN(J19,J18+J21) -> 0 | ... W20: =MIN(W19,W18+W21) -> 0 | X20: =SUM(D20:G20) -> 0 | Y20: =SUM(H20:K20) -> 0 | Z20: =SUM(L20:O20) -> 0 | AA20: =SUM(P20:S20) -> 0 | AB20: =SUM(T20:W20) -> 0
A21: Lease Net Additions | B21: Capital leases | C21: 0 | D21: 0 | E21: 0 | F21: 0 | G21: 0 | H21: 0 | I21: 0 | J21: 0 | K21: 0 | L21: 0 | M21: 0 | N21: 0 | O21: 0 | P21: 0 | Q21: 0 | R21: 0 | S21: 0 | T21: 0 | U21: 0 | V21: 0 | W21: 0 | X21: =SUM(D21:G21) -> 0 | Y21: =SUM(H21:K21) -> 0 | Z21: =SUM(L21:O21) -> 0 | AA21: =SUM(P21:S21) -> 0 | AB21: =SUM(T21:W21) -> 0
A22: Lease Interest Expense | B22: Capital leases | C22: 0 | D22: =D18*D12 -> 0 | E22: =E18*E12 -> 0 | F22: =F18*F12 -> 0 | G22: =G18*G12 -> 0 | H22: =H18*H12 -> 0 | I22: =I18*I12 -> 0 | J22: =J18*J12 -> 0 | K22: =K18*K12 -> 0 | ... W22: =W18*W12 -> 0 | X22: =SUM(D22:G22) -> 0 | Y22: =SUM(H22:K22) -> 0 | Z22: =SUM(L22:O22) -> 0 | AA22: =SUM(P22:S22) -> 0 | AB22: =SUM(T22:W22) -> 0
A23: Lease Closing Balance | B23: Capital leases | C23: =MAX(0,C18+C21-C20) -> 0 | D23: =MAX(0,D18+D21-D20) -> 0 | E23: =MAX(0,E18+E21-E20) -> 0 | F23: =MAX(0,F18+F21-F20) -> 0 | G23: =MAX(0,G18+G21-G20) -> 0 | H23: =MAX(0,H18+H21-H20) -> 0 | I23: =MAX(0,I18+I21-I20) -> 0 | J23: =MAX(0,J18+J21-J20) -> 0 | ... W23: =MAX(0,W18+W21-W20) -> 0 | X23: =G23 -> 0 | Y23: =K23 -> 0 | Z23: =O23 -> 0 | AA23: =S23 -> 0 | AB23: =W23 -> 0
A24: Right-of-Use Asset Opening | B24: Capital leases | C24: 0 | D24: =C26 -> 0 | E24: =D26 -> 0 | F24: =E26 -> 0 | G24: =F26 -> 0 | H24: =G26 -> 0 | I24: =H26 -> 0 | J24: =I26 -> 0 | K24: =J26 -> 0 | ... W24: =V26 -> 0 | X24: =G24 -> 0 | Y24: =K24 -> 0 | Z24: =O24 -> 0 | AA24: =S24 -> 0 | AB24: =W24 -> 0
A25: Lease Asset Depreciation | B25: Capital leases | C25: 0 | D25: =MIN((C18/20),D24) -> 0 | E25: =MIN((C18/20),E24) -> 0 | F25: =MIN((C18/20),F24) -> 0 | G25: =MIN((C18/20),G24) -> 0 | H25: =MIN((C18/20),H24) -> 0 | I25: =MIN((C18/20),I24) -> 0 | J25: =MIN((C18/20),J24) -> 0 | K25: =MIN((C18/20),K24) -> 0 | L25: =MIN((C18/20),L24) -> 0 | M25: =MIN((C18/20),M24) -> 0 | N25: =MIN((C18/20),N24) -> 0 | O25: =MIN((C18/20),O24) -> 0 | P25: =MIN((C18/20),P24) -> 0 | Q25: =MIN((C18/20),Q24) -> 0 | R25: =MIN((C18/20),R24) -> 0 | S25: =MIN((C18/20),S24) -> 0 | T25: =MIN((C18/20),T24) -> 0 | U25: =MIN((C18/20),U24) -> 0 | V25: =MIN((C18/20),V24) -> 0 | W25: =MIN((C18/20),W24) -> 0 | X25: =SUM(D25:G25) -> 0 | Y25: =SUM(H25:K25) -> 0 | Z25: =SUM(L25:O25) -> 0 | AA25: =SUM(P25:S25) -> 0 | AB25: =SUM(T25:W25) -> 0
A26: Right-of-Use Asset Closing | B26: Capital leases | C26: =MAX(0,C24-C25) -> 0 | D26: =MAX(0,D24-D25) -> 0 | E26: =MAX(0,E24-E25) -> 0 | F26: =MAX(0,F24-F25) -> 0 | G26: =MAX(0,G24-G25) -> 0 | H26: =MAX(0,H24-H25) -> 0 | I26: =MAX(0,I24-I25) -> 0 | J26: =MAX(0,J24-J25) -> 0 | ... W26: =MAX(0,W24-W25) -> 0 | X26: =G26 -> 0 | Y26: =K26 -> 0 | Z26: =O26 -> 0 | AA26: =S26 -> 0 | AB26: =W26 -> 0

Sheet CapEx Depreciation
A1: CapEx & Depreciation Schedule
A2: Capital expenditure and depreciation mechanics. Model Inputs links to calculated outputs.
C4: Stub | D4: Q1 | E4: Q2 | F4: Q3 | G4: Q4 | H4: Q5 | I4: Q6 | J4: Q7 | K4: Q8 | L4: Q9 | M4: Q10 | N4: Q11 | O4: Q12 | P4: Q13 | Q4: Q14 | R4: Q15 | S4: Q16 | T4: Q17 | U4: Q18 | V4: Q19 | W4: Q20 | X4: Y1 | Y4: Y2 | Z4: Y3 | AA4: Y4 | AB4: Y5
C5: 46162 | D5: 46295 | E5: 46387 | F5: 46477 | G5: 46568 | H5: 46660 | I5: 46752 | J5: 46843 | K5: 46934 | L5: 47026 | M5: 47118 | N5: 47208 | O5: 47299 | P5: 47391 | Q5: 47483 | R5: 47573 | S5: 47664 | T5: 47756 | U5: 47848 | V5: 47938 | W5: 48029 | X5: Annual | Y5: Annual | Z5: Annual | AA5: Annual | AB5: Annual
A6: PPE and Depreciation
A7: Opening PPE | B7: Calculated | C7: 40000 | D7: =C12 -> 40000 | E7: =D12 -> 40190 | F7: =E12 -> 40370.895 | G7: =F12 -> 40542.593 | H7: =G12 -> 40705.047 | I7: =H12 -> 40858.138 | J7: =I12 -> 41001.755 | K7: =J12 -> 41135.831 | ... W7: =V12 -> 41973.955 | X7: =G7 -> 40542.593 | Y7: =K7 -> 41135.831 | Z7: =O7 -> 41575.259 | AA7: =S7 -> 41856.096 | AB7: =W7 -> 41973.955
A8: Capital Expenditures | B8: Schedule source | C8: 0 | D8: 200 | E8: 200.95 | F8: 201.85448 | G8: 202.71296 | H8: 203.52523 | I8: 204.29069 | J8: 205.00877 | K8: 205.67915 | L8: 206.30154 | M8: 206.87547 | N8: 207.40052 | O8: 207.87629 | P8: 208.30265 | Q8: 208.67905 | R8: 209.00501 | S8: 209.28048 | T8: 209.50504 | U8: 209.6783 | V8: 209.79991 | W8: 209.86977 | X8: =SUM(D8:G8) -> 805.51744 | Y8: =SUM(H8:K8) -> 818.50385 | Z8: =SUM(L8:O8) -> 828.45382 | AA8: =SUM(P8:S8) -> 835.26719 | AB8: =SUM(T8:W8) -> 838.85302
A9: Lease Additions | B9: Schedule source | C9: 0 | D9: ='Debt Schedule'!D21 -> 0 | E9: ='Debt Schedule'!E21 -> 0 | F9: ='Debt Schedule'!F21 -> 0 | G9: ='Debt Schedule'!G21 -> 0 | H9: ='Debt Schedule'!H21 -> 0 | I9: ='Debt Schedule'!I21 -> 0 | J9: ='Debt Schedule'!J21 -> 0 | K9: ='Debt Schedule'!K21 -> 0 | ... W9: ='Debt Schedule'!W21 -> 0 | X9: =SUM(D9:G9) -> 0 | Y9: =SUM(H9:K9) -> 0 | Z9: =SUM(L9:O9) -> 0 | AA9: =SUM(P9:S9) -> 0 | AB9: =SUM(T9:W9) -> 0
A10: Depreciation Rate | B10: Schedule source | C10: 0 | D10: 0.00025 | E10: 0.000499 | F10: 0.000747 | G10: 0.000993 | H10: 0.001239 | I10: 0.001485 | J10: 0.00173 | K10: 0.001974 | L10: 0.002218 | M10: 0.002462 | N10: 0.002706 | O10: 0.002949 | P10: 0.003193 | Q10: 0.003438 | R10: 0.003682 | S10: 0.003927 | T10: 0.004173 | U10: 0.00442 | V10: 0.004667 | W10: 0.004916 | X10: =SUM(D10:G10) -> 0.002489 | Y10: =SUM(H10:K10) -> 0.006428 | Z10: =SUM(L10:O10) -> 0.010335 | AA10: =SUM(P10:S10) -> 0.01424 | AB10: =SUM(T10:W10) -> 0.018176
A11: Depreciation Expense | B11: Calculated | C11: =MIN(C7*C10,C7) -> 0 | D11: =MIN(D7*D10,D7) -> 10 | E11: =MIN(E7*E10,E7) -> 20.05481 | F11: =MIN(F7*F10,F7) -> 30.157059 | G11: =MIN(G7*G10,G7) -> 40.258794 | H11: =MIN(H7*H10,H7) -> 50.433553 | I11: =MIN(I7*I10,I7) -> 60.674336 | J11: =MIN(J7*J10,J7) -> 70.933036 | ... W11: =MIN(W7*W10,W7) -> 206.34396 | X11: =SUM(D11:G11) -> 100.47066 | Y11: =SUM(H11:K11) -> 263.24305 | Z11: =SUM(L11:O11) -> 428.23144 | AA11: =SUM(P11:S11) -> 594.78996 | AB11: =SUM(T11:W11) -> 762.37971
A12: Closing PPE | B12: Calculated | C12: =MAX(0,C7+C8+C9-C11) -> 40000 | D12: =MAX(0,D7+D8+D9-D11) -> 40190 | E12: =MAX(0,E7+E8+E9-E11) -> 40370.895 | F12: =MAX(0,F7+F8+F9-F11) -> 40542.593 | G12: =MAX(0,G7+G8+G9-G11) -> 40705.047 | H12: =MAX(0,H7+H8+H9-H11) -> 40858.138 | I12: =MAX(0,I7+I8+I9-I11) -> 41001.755 | J12: =MAX(0,J7+J8+J9-J11) -> 41135.831 | ... W12: =MAX(0,W7+W8+W9-W11) -> 41977.48 | X12: =G12 -> 40705.047 | Y12: =K12 -> 41260.308 | Z12: =O12 -> 41660.53 | AA12: =S12 -> 41901.007 | AB12: =W12 -> 41977.48
A13: Opening Accumulated Depreciation | B13: Calculated | C13: 0 | D13: =C14 -> 0 | E13: =D14 -> -10 | F13: =E14 -> -30.05481 | G13: =F14 -> -60.211869 | H13: =G14 -> -100.47066 | I13: =H14 -> -150.90422 | J13: =I14 -> -211.57855 | K13: =J14 -> -282.51159 | ... W13: =V14 -> -1942.7709 | X13: =G13 -> -60.211869 | Y13: =K13 -> -282.51159 | Z13: =O13 -> -669.33972 | AA13: =S13 -> -1222.3662 | AB13: =W13 -> -1942.7709
A14: Accumulated Depreciation | B14: Calculated | C14: =C13-C11 -> 0 | D14: =D13-D11 -> -10 | E14: =E13-E11 -> -30.05481 | F14: =F13-F11 -> -60.211869 | G14: =G13-G11 -> -100.47066 | H14: =H13-H11 -> -150.90422 | I14: =I13-I11 -> -211.57855 | J14: =J13-J11 -> -282.51159 | ... W14: =W13-W11 -> -2149.1148 | X14: =G14 -> -100.47066 | Y14: =K14 -> -363.71372 | Z14: =O14 -> -791.94516 | AA14: =S14 -> -1386.7351 | AB14: =W14 -> -2149.1148

Sheet Working Capital
A1: Working Capital Schedule
A2: Working-capital drivers. Model Inputs links to these source rows.
C4: Stub | D4: Q1 | E4: Q2 | F4: Q3 | G4: Q4 | H4: Q5 | I4: Q6 | J4: Q7 | K4: Q8 | L4: Q9 | M4: Q10 | N4: Q11 | O4: Q12 | P4: Q13 | Q4: Q14 | R4: Q15 | S4: Q16 | T4: Q17 | U4: Q18 | V4: Q19 | W4: Q20 | X4: Y1 | Y4: Y2 | Z4: Y3 | AA4: Y4 | AB4: Y5
C5: 46162 | D5: 46295 | E5: 46387 | F5: 46477 | G5: 46568 | H5: 46660 | I5: 46752 | J5: 46843 | K5: 46934 | L5: 47026 | M5: 47118 | N5: 47208 | O5: 47299 | P5: 47391 | Q5: 47483 | R5: 47573 | S5: 47664 | T5: 47756 | U5: 47848 | V5: 47938 | W5: 48029 | X5: Annual | Y5: Annual | Z5: Annual | AA5: Annual | AB5: Annual
A6: Working Capital Drivers
A7: Accounts Receivable Days | B7: Working capital driver | C7: 0 | D7: 30 | E7: 40.918175 | F7: 40.918175 | G7: 40.918175 | H7: 40.918175 | I7: 40.918175 | J7: 40.918175 | K7: 40.918175 | L7: 40.918175 | M7: 40.918175 | N7: 40.918175 | O7: 40.918175 | P7: 40.918175 | Q7: 40.918175 | R7: 40.918175 | S7: 40.918175 | T7: 40.918175 | U7: 40.918175 | V7: 40.918175 | W7: 40.918175
A8: Inventory Days | B8: Working capital driver | C8: 0 | D8: 87.338516 | E8: 38.363792 | F8: 36.246985 | G8: 43.193839 | H8: 50.091365 | I8: 54.001195 | J8: 54.914438 | K8: 58.653383 | L8: 65.001325 | M8: 68.472739 | N8: 57.859672 | O8: 57.220096 | P8: 60.092872 | Q8: 61.160118 | R8: 58.232636 | S8: 62.555872 | T8: 67.389344 | U8: 69.496631 | V8: 67.333483 | W8: 71.66529
A9: Accounts Payable Days | B9: Working capital driver | C9: 0 | D9: 41.7 | E9: 45.544202 | F9: 43.522382 | G9: 43.306918 | H9: 44.763831 | I9: 44.676717 | J9: 43.861467 | K9: 45.768117 | L9: 54.123774 | M9: 59.769253 | N9: 72.201373 | O9: 78.849582 | P9: 82.052104 | Q9: 84.986986 | R9: 84.986986 | S9: 84.986986 | T9: 84.986986 | U9: 84.986986 | V9: 84.986986 | W9: 84.986986
A10: Prepaid Expenses (% of Revenue) | B10: Working capital driver | C10: 0 | D10: 0.02 | E10: 0.028269 | F10: 0.028269 | G10: 0.028269 | H10: 0.028269 | I10: 0.028269 | J10: 0.028269 | K10: 0.028673 | L10: 0.030024 | M10: 0.03108 | N10: 0.028269 | O10: 0.028269 | P10: 0.028269 | Q10: 0.028269 | R10: 0.028269 | S10: 0.028864 | T10: 0.030454 | U10: 0.031405 | V10: 0.031116 | W10: 0.032856
A11: Deferred Revenue (% of Revenue) | B11: Working capital driver | C11: 0 | D11: 0.15 | E11: 0.108048 | F11: 0.092136 | G11: 0.090163 | H11: 0.095003 | I11: 0.094688 | J11: 0.09191 | K11: 0.098403 | L11: 0.126861 | M11: 0.146088 | N11: 0.18843 | O11: 0.211072 | P11: 0.221979 | Q11: 0.231975 | R11: 0.231975 | S11: 0.231975 | T11: 0.231975 | U11: 0.231975 | V11: 0.231975 | W11: 0.231975
A12: Short Term Debt (% of LTD) | B12: Working capital driver | C12: 0 | D12: 0 | E12: 0 | F12: 0 | G12: 0 | H12: 0 | I12: 0 | J12: 0 | K12: 0 | L12: 0 | M12: 0 | N12: 0 | O12: 0 | P12: 0 | Q12: 0 | R12: 0 | S12: 0 | T12: 0 | U12: 0 | V12: 0 | W12: 0
A14: Opening Working Capital Seeds
A15: Cash Opening Balance | B15: Opening balance seed | C15: 80000 | D15: 0 | E15: 0 | F15: 0 | G15: 0 | H15: 0 | I15: 0 | J15: 0 | K15: 0 | L15: 0 | M15: 0 | N15: 0 | O15: 0 | P15: 0 | Q15: 0 | R15: 0 | S15: 0 | T15: 0 | U15: 0 | V15: 0 | W15: 0
A16: Accounts Receivable Opening Balance | B16: Opening balance seed | C16: 12000 | D16: 0 | E16: 0 | F16: 0 | G16: 0 | H16: 0 | I16: 0 | J16: 0 | K16: 0 | L16: 0 | M16: 0 | N16: 0 | O16: 0 | P16: 0 | Q16: 0 | R16: 0 | S16: 0 | T16: 0 | U16: 0 | V16: 0 | W16: 0
A17: Inventory Opening Balance | B17: Opening balance seed | C17: 0 | D17: 0 | E17: 0 | F17: 0 | G17: 0 | H17: 0 | I17: 0 | J17: 0 | K17: 0 | L17: 0 | M17: 0 | N17: 0 | O17: 0 | P17: 0 | Q17: 0 | R17: 0 | S17: 0 | T17: 0 | U17: 0 | V17: 0 | W17: 0
A18: Accounts Payable Opening Balance | B18: Opening balance seed | C18: 0 | D18: 0 | E18: 0 | F18: 0 | G18: 0 | H18: 0 | I18: 0 | J18: 0 | K18: 0 | L18: 0 | M18: 0 | N18: 0 | O18: 0 | P18: 0 | Q18: 0 | R18: 0 | S18: 0 | T18: 0 | U18: 0 | V18: 0 | W18: 0
A19: Short Term Debt Opening Balance | B19: Opening balance seed | C19: 0 | D19: 0 | E19: 0 | F19: 0 | G19: 0 | H19: 0 | I19: 0 | J19: 0 | K19: 0 | L19: 0 | M19: 0 | N19: 0 | O19: 0 | P19: 0 | Q19: 0 | R19: 0 | S19: 0 | T19: 0 | U19: 0 | V19: 0 | W19: 0

Sheet Cash Equity Schedule
A1: Cash & Equity Schedule
A2: Equity, distributions, lease/rent, and opening cash seeds. Model Inputs links to these rows.
C4: Stub | D4: Q1 | E4: Q2 | F4: Q3 | G4: Q4 | H4: Q5 | I4: Q6 | J4: Q7 | K4: Q8 | L4: Q9 | M4: Q10 | N4: Q11 | O4: Q12 | P4: Q13 | Q4: Q14 | R4: Q15 | S4: Q16 | T4: Q17 | U4: Q18 | V4: Q19 | W4: Q20 | X4: Y1 | Y4: Y2 | Z4: Y3 | AA4: Y4 | AB4: Y5
C5: 46162 | D5: 46295 | E5: 46387 | F5: 46477 | G5: 46568 | H5: 46660 | I5: 46752 | J5: 46843 | K5: 46934 | L5: 47026 | M5: 47118 | N5: 47208 | O5: 47299 | P5: 47391 | Q5: 47483 | R5: 47573 | S5: 47664 | T5: 47756 | U5: 47848 | V5: 47938 | W5: 48029 | X5: Annual | Y5: Annual | Z5: Annual | AA5: Annual | AB5: Annual
A6: Equity and Distributions
A7: Owner's Capital | B7: Equity / distribution input | C7: 100000 | D7: 157098 | E7: 162529 | F7: 170541 | G7: 173163 | H7: 173163 | I7: 173163 | J7: 173163 | K7: 173163 | L7: 173163 | M7: 173163 | N7: 173163 | O7: 173163 | P7: 173163 | Q7: 173163 | R7: 173163 | S7: 173163 | T7: 173163 | U7: 173163 | V7: 173163 | W7: 173163
A8: Other Equity | B8: Equity / distribution input | C8: 0 | D8: 0 | E8: 0 | F8: 0 | G8: 0 | H8: 0 | I8: 0 | J8: 0 | K8: 0 | L8: 0 | M8: 0 | N8: 0 | O8: 0 | P8: 0 | Q8: 0 | R8: 0 | S8: 0 | T8: 0 | U8: 0 | V8: 0 | W8: 0
A9: Distributions | B9: Equity / distribution input | C9: 0 | D9: 0 | E9: 0 | F9: 0 | G9: 0 | H9: 0 | I9: 0 | J9: 0 | K9: 0 | L9: 0 | M9: 27903 | N9: 20347 | O9: 0 | P9: 0 | Q9: 19113 | R9: 20352 | S9: 12743 | T9: 17757 | U9: 21932 | V9: 31847 | W9: 19557
A11: Operating Fixed Cash Items
A12: Lease | B12: Operating lease/rent input | C12: 12600 | D12: 12600 | E12: 12600 | F12: 12600 | G12: 12600 | H12: 12600 | I12: 12600 | J12: 12600 | K12: 12600 | L12: 12600 | M12: 12600 | N12: 12600 | O12: 12600 | P12: 12600 | Q12: 12600 | R12: 12600 | S12: 12600 | T12: 12600 | U12: 12600 | V12: 12600 | W12: 12600

Sheet Model Inputs
A1: Model Inputs
A2: Formula-driven bridge from schedules into FINMO. FINMO references this sheet only.
C4: Stub | D4: Q1 | E4: Q2 | F4: Q3 | G4: Q4 | H4: Q5 | I4: Q6 | J4: Q7 | K4: Q8 | L4: Q9 | M4: Q10 | N4: Q11 | O4: Q12 | P4: Q13 | Q4: Q14 | R4: Q15 | S4: Q16 | T4: Q17 | U4: Q18 | V4: Q19 | W4: Q20 | X4: Y1 | Y4: Y2 | Z4: Y3 | AA4: Y4 | AB4: Y5
C5: 46162 | D5: 46295 | E5: 46387 | F5: 46477 | G5: 46568 | H5: 46660 | I5: 46752 | J5: 46843 | K5: 46934 | L5: 47026 | M5: 47118 | N5: 47208 | O5: 47299 | P5: 47391 | Q5: 47483 | R5: 47573 | S5: 47664 | T5: 47756 | U5: 47848 | V5: 47938 | W5: 48029 | X5: Annual | Y5: Annual | Z5: Annual | AA5: Annual | AB5: Annual
A6: Income Statement Inputs
A7: Corporate Legal Services / Corporate legal matter/engagement - Capacity | B7: Revenue Drivers schedule | C7: ='Revenue Drivers'!C8 -> 130 | D7: ='Revenue Drivers'!D8 -> 57.266667 | E7: ='Revenue Drivers'!E8 -> 57.266667 | F7: ='Revenue Drivers'!F8 -> 57.266667 | G7: ='Revenue Drivers'!G8 -> 57.266667 | H7: ='Revenue Drivers'!H8 -> 57.266667 | I7: ='Revenue Drivers'!I8 -> 57.266667 | J7: ='Revenue Drivers'!J8 -> 57.266667 | ... W7: ='Revenue Drivers'!W8 -> 57.266667 | X7: =SUM(D7:G7) -> 229.06667 | Y7: =SUM(H7:K7) -> 229.06667 | Z7: =SUM(L7:O7) -> 229.06667 | AA7: =SUM(P7:S7) -> 229.06667 | AB7: =SUM(T7:W7) -> 229.06667
A8: Corporate Legal Services / Corporate legal matter/engagement - Unit Price | B8: Revenue Drivers schedule | C8: ='Revenue Drivers'!C9 -> 12000 | D8: ='Revenue Drivers'!D9 -> 3228.0648 | E8: ='Revenue Drivers'!E9 -> 4687.3753 | F8: ='Revenue Drivers'!F9 -> 5633.9904 | G8: ='Revenue Drivers'!G9 -> 6458.0668 | H8: ='Revenue Drivers'!H9 -> 7175.4669 | I8: ='Revenue Drivers'!I9 -> 7800 | J8: ='Revenue Drivers'!J9 -> 8343.6876 | ... W8: ='Revenue Drivers'!W9 -> 11396.933 | X8: =SUM(D8:G8) -> 20007.497 | Y8: =SUM(H8:K8) -> 32136.15 | Z8: =SUM(L8:O8) -> 38888.611 | AA8: =SUM(P8:S8) -> 42766.881 | AB8: =SUM(T8:W8) -> 44994.362
A9: Corporate Legal Services / Corporate legal matter/engagement - Utilization | B9: Revenue Drivers schedule | C9: ='Revenue Drivers'!C10 -> 0.7 | D9: ='Revenue Drivers'!D10 -> 0.826081 | E9: ='Revenue Drivers'!E10 -> 0.737694 | F9: ='Revenue Drivers'!F10 -> 0.62412 | G9: ='Revenue Drivers'!G10 -> 0.552413 | H9: ='Revenue Drivers'!H10 -> 0.517806 | I9: ='Revenue Drivers'!I10 -> 0.479663 | J9: ='Revenue Drivers'!J10 -> 0.456714 | ... W9: ='Revenue Drivers'!W10 -> 0.699755 | X9: =SUM(D9:G9) -> 2.740308 | Y9: =SUM(H9:K9) -> 1.893621 | Z9: =SUM(L9:O9) -> 1.952179 | AA9: =SUM(P9:S9) -> 2.694526 | AB9: =SUM(T9:W9) -> 2.79531
A10: Corporate Legal Services / Corporate legal matter/engagement - Revenue | B10: Revenue Drivers schedule | C10: ='Revenue Drivers'!C11 -> 1092000 | D10: ='Revenue Drivers'!D11 -> 152709.76 | E10: ='Revenue Drivers'!E11 -> 198019.46 | F10: ='Revenue Drivers'!F11 -> 201365.99 | G10: ='Revenue Drivers'!G11 -> 204299.98 | H10: ='Revenue Drivers'!H11 -> 212774.29 | I10: ='Revenue Drivers'!I11 -> 214255.87 | J10: ='Revenue Drivers'!J11 -> 218224.88 | ... W10: ='Revenue Drivers'!W11 -> 456705.17 | X10: =SUM(D10:G10) -> 756395.19 | Y10: =SUM(H10:K10) -> 867136.05 | Z10: =SUM(L10:O10) -> 1091531.4 | AA10: =SUM(P10:S10) -> 1650709.6 | AB10: =SUM(T10:W10) -> 1800677.1
A11: Individual Legal Services / Family/estate legal matter - Capacity | B11: Revenue Drivers schedule | C11: ='Revenue Drivers'!C14 -> 104 | D11: ='Revenue Drivers'!D14 -> 45.813333 | E11: ='Revenue Drivers'!E14 -> 45.813333 | F11: ='Revenue Drivers'!F14 -> 45.813333 | G11: ='Revenue Drivers'!G14 -> 45.813333 | H11: ='Revenue Drivers'!H14 -> 45.813333 | I11: ='Revenue Drivers'!I14 -> 45.813333 | J11: ='Revenue Drivers'!J14 -> 45.813333 | ... W11: ='Revenue Drivers'!W14 -> 45.813333 | X11: =SUM(D11:G11) -> 183.25333 | Y11: =SUM(H11:K11) -> 183.25333 | Z11: =SUM(L11:O11) -> 183.25333 | AA11: =SUM(P11:S11) -> 183.25333 | AB11: =SUM(T11:W11) -> 183.25333
A12: Individual Legal Services / Family/estate legal matter - Unit Price | B12: Revenue Drivers schedule | C12: ='Revenue Drivers'!C15 -> 6000 | D12: ='Revenue Drivers'!D15 -> 3228.0648 | E12: ='Revenue Drivers'!E15 -> 2343.6876 | F12: ='Revenue Drivers'!F15 -> 2816.9952 | G12: ='Revenue Drivers'!G15 -> 3229.0334 | H12: ='Revenue Drivers'!H15 -> 3587.7335 | I12: ='Revenue Drivers'!I15 -> 3900 | J12: ='Revenue Drivers'!J15 -> 4171.8438 | ... W12: ='Revenue Drivers'!W15 -> 5698.4667 | X12: =SUM(D12:G12) -> 11617.781 | Y12: =SUM(H12:K12) -> 16068.075 | Z12: =SUM(L12:O12) -> 19444.305 | AA12: =SUM(P12:S12) -> 21383.441 | AB12: =SUM(T12:W12) -> 22497.181
A13: Individual Legal Services / Family/estate legal matter - Utilization | B13: Revenue Drivers schedule | C13: ='Revenue Drivers'!C16 -> 0.7 | D13: ='Revenue Drivers'!D16 -> 0.826081 | E13: ='Revenue Drivers'!E16 -> 0.737694 | F13: ='Revenue Drivers'!F16 -> 0.62412 | G13: ='Revenue Drivers'!G16 -> 0.552413 | H13: ='Revenue Drivers'!H16 -> 0.517806 | I13: ='Revenue Drivers'!I16 -> 0.479663 | J13: ='Revenue Drivers'!J16 -> 0.456714 | ... W13: ='Revenue Drivers'!W16 -> 0.699755 | X13: =SUM(D13:G13) -> 2.740308 | Y13: =SUM(H13:K13) -> 1.893621 | Z13: =SUM(L13:O13) -> 1.952179 | AA13: =SUM(P13:S13) -> 2.694526 | AB13: =SUM(T13:W13) -> 2.79531
A14: Individual Legal Services / Family/estate legal matter - Revenue | B14: Revenue Drivers schedule | C14: ='Revenue Drivers'!C17 -> 436800 | D14: ='Revenue Drivers'!D17 -> 122167.8 | E14: ='Revenue Drivers'!E17 -> 79207.785 | F14: ='Revenue Drivers'!F17 -> 80546.393 | G14: ='Revenue Drivers'!G17 -> 81719.992 | H14: ='Revenue Drivers'!H17 -> 85109.715 | I14: ='Revenue Drivers'!I17 -> 85702.347 | J14: ='Revenue Drivers'!J17 -> 87289.952 | ... W14: ='Revenue Drivers'!W17 -> 182682.07 | X14: =SUM(D14:G14) -> 363641.97 | Y14: =SUM(H14:K14) -> 346854.41 | Z14: =SUM(L14:O14) -> 436612.54 | AA14: =SUM(P14:S14) -> 660283.82 | AB14: =SUM(T14:W14) -> 720270.82
A15: Revenue | B15: Revenue Drivers schedule | C15: ='Revenue Drivers'!C20 -> 1528800 | D15: ='Revenue Drivers'!D20 -> 274877.56 | E15: ='Revenue Drivers'!E20 -> 277227.25 | F15: ='Revenue Drivers'!F20 -> 281912.38 | G15: ='Revenue Drivers'!G20 -> 286019.97 | H15: ='Revenue Drivers'!H20 -> 297884.01 | I15: ='Revenue Drivers'!I20 -> 299958.22 | J15: ='Revenue Drivers'!J20 -> 305514.83 | ... W15: ='Revenue Drivers'!W20 -> 639387.23 | X15: =SUM(D15:G15) -> 1120037.2 | Y15: =SUM(H15:K15) -> 1213990.5 | Z15: =SUM(L15:O15) -> 1528143.9 | AA15: =SUM(P15:S15) -> 2310993.4 | AB15: =SUM(T15:W15) -> 2520947.9
A16: Cost of Goods Sold | B16: Direct model driver | C16: 0.16 | D16: 0.2160425 | E16: 0.2160425 | F16: 0.2160425 | G16: 0.2160425 | H16: 0.2160425 | I16: 0.2160425 | J16: 0.2160425 | K16: 0.2160425 | L16: 0.2160425 | M16: 0.2160425 | N16: 0.25195658 | O16: 0.28193058 | P16: 0.29441938 | Q16: 0.303294 | R16: 0.30827632 | S16: 0.31133082 | T16: 0.31011409 | U16: 0.31167919 | V16: 0.3129074 | W16: 0.31391029 | X16: =SUM(D16:G16) -> 0.86417 | Y16: =SUM(H16:K16) -> 0.86417 | Z16: =SUM(L16:O16) -> 0.96597216 | AA16: =SUM(P16:S16) -> 1.2173205 | AB16: =SUM(T16:W16) -> 1.248611
A17: Marketing | B17: Direct model driver | C17: 0.12 | D17: 0.15641125 | E17: 0.15641125 | F17: 0.15641125 | G17: 0.15641125 | H17: 0.15641125 | I17: 0.15641125 | J17: 0.15641125 | K17: 0.15641125 | L17: 0.15641125 | M17: 0.15641125 | N17: 0.1718625 | O17: 0.18475816 | P17: 0.1901312 | Q17: 0.19394931 | R17: 0.19609284 | S17: 0.19740698 | T17: 0.1968835 | U17: 0.19755685 | V17: 0.19808526 | W17: 0.19851674 | X17: =SUM(D17:G17) -> 0.625645 | Y17: =SUM(H17:K17) -> 0.625645 | Z17: =SUM(L17:O17) -> 0.66944316 | AA17: =SUM(P17:S17) -> 0.77758032 | AB17: =SUM(T17:W17) -> 0.79104235
A18: Research & Development | B18: Direct model driver | C18: 0 | D18: 0 | E18: 0 | F18: 0 | G18: 0 | H18: 0 | I18: 0 | J18: 0 | K18: 0 | L18: 0 | M18: 0 | N18: 0 | O18: 0 | P18: 0 | Q18: 0 | R18: 0 | S18: 0 | T18: 0 | U18: 0 | V18: 0 | W18: 0 | X18: =SUM(D18:G18) -> 0 | Y18: =SUM(H18:K18) -> 0 | Z18: =SUM(L18:O18) -> 0 | AA18: =SUM(P18:S18) -> 0 | AB18: =SUM(T18:W18) -> 0
A19: Lease | B19: Cash Equity Schedule output | C19: ='Cash Equity Schedule'!C12 -> 12600 | D19: ='Cash Equity Schedule'!D12 -> 12600 | E19: ='Cash Equity Schedule'!E12 -> 12600 | F19: ='Cash Equity Schedule'!F12 -> 12600 | G19: ='Cash Equity Schedule'!G12 -> 12600 | H19: ='Cash Equity Schedule'!H12 -> 12600 | I19: ='Cash Equity Schedule'!I12 -> 12600 | J19: ='Cash Equity Schedule'!J12 -> 12600 | ... W19: ='Cash Equity Schedule'!W12 -> 12600 | X19: =SUM(D19:G19) -> 50400 | Y19: =SUM(H19:K19) -> 50400 | Z19: =SUM(L19:O19) -> 50400 | AA19: =SUM(P19:S19) -> 50400 | AB19: =SUM(T19:W19) -> 50400
A20: Payroll | B20: Payroll Schedule output | C20: 134521.88 | D20: ='Payroll Schedule'!D17 -> 115547.95 | E20: ='Payroll Schedule'!E17 -> 115547.95 | F20: ='Payroll Schedule'!F17 -> 115547.95 | G20: ='Payroll Schedule'!G17 -> 115547.95 | H20: ='Payroll Schedule'!H17 -> 119014.33 | I20: ='Payroll Schedule'!I17 -> 119014.33 | J20: ='Payroll Schedule'!J17 -> 119014.33 | K20: ='Payroll Schedule'!K17 -> 119014.33 | ... W20: ='Payroll Schedule'!W17 -> 130050.35 | X20: =SUM(D20:G20) -> 462191.8 | Y20: =SUM(H20:K20) -> 476057.31 | Z20: =SUM(L20:O20) -> 490338.83 | AA20: =SUM(P20:S20) -> 505051.06 | AB20: =SUM(T20:W20) -> 520201.38
A21: General & Administrative | B21: Direct model driver | C21: 0.000458 | D21: 0.15641125 | E21: 0.15641125 | F21: 0.15641125 | G21: 0.15641125 | H21: 0.15641125 | I21: 0.15641125 | J21: 0.15641125 | K21: 0.15641125 | L21: 0.15641125 | M21: 0.15641125 | N21: 0.1718625 | O21: 0.18475816 | P21: 0.1901312 | Q21: 0.19394931 | R21: 0.19609284 | S21: 0.19740698 | T21: 0.1968835 | U21: 0.19755685 | V21: 0.19808526 | W21: 0.19851674 | X21: =SUM(D21:G21) -> 0.625645 | Y21: =SUM(H21:K21) -> 0.625645 | Z21: =SUM(L21:O21) -> 0.66944316 | AA21: =SUM(P21:S21) -> 0.77758032 | AB21: =SUM(T21:W21) -> 0.79104235
A22: Interest Rate | B22: Debt Schedule output | C22: ='Debt Schedule'!C12 -> 0 | D22: ='Debt Schedule'!D12 -> 0.023813 | E22: ='Debt Schedule'!E12 -> 0.023813 | F22: ='Debt Schedule'!F12 -> 0.023813 | G22: ='Debt Schedule'!G12 -> 0.023813 | H22: ='Debt Schedule'!H12 -> 0.023813 | I22: ='Debt Schedule'!I12 -> 0.023813 | J22: ='Debt Schedule'!J12 -> 0.023813 | ... W22: ='Debt Schedule'!W12 -> 0.023813 | X22: =SUM(D22:G22) -> 0.095252 | Y22: =SUM(H22:K22) -> 0.095252 | Z22: =SUM(L22:O22) -> 0.095252 | AA22: =SUM(P22:S22) -> 0.095252 | AB22: =SUM(T22:W22) -> 0.095252
A23: Interest Expense | B23: Debt Schedule output | C23: 0 | D23: ='Debt Schedule'!D13 -> 0 | E23: ='Debt Schedule'!E13 -> 0 | F23: ='Debt Schedule'!F13 -> 0 | G23: ='Debt Schedule'!G13 -> 0 | H23: ='Debt Schedule'!H13 -> 0 | I23: ='Debt Schedule'!I13 -> 0 | J23: ='Debt Schedule'!J13 -> 0 | K23: ='Debt Schedule'!K13 -> 0 | ... W23: ='Debt Schedule'!W13 -> 0 | X23: =SUM(D23:G23) -> 0 | Y23: =SUM(H23:K23) -> 0 | Z23: =SUM(L23:O23) -> 0 | AA23: =SUM(P23:S23) -> 0 | AB23: =SUM(T23:W23) -> 0
A24: Depreciation | B24: CapEx Depreciation output | C24: ='CapEx Depreciation'!C10 -> 0 | D24: ='CapEx Depreciation'!D10 -> 0.00025 | E24: ='CapEx Depreciation'!E10 -> 0.000499 | F24: ='CapEx Depreciation'!F10 -> 0.000747 | G24: ='CapEx Depreciation'!G10 -> 0.000993 | H24: ='CapEx Depreciation'!H10 -> 0.001239 | I24: ='CapEx Depreciation'!I10 -> 0.001485 | J24: ='CapEx Depreciation'!J10 -> 0.00173 | ... W24: ='CapEx Depreciation'!W10 -> 0.004916 | X24: =SUM(D24:G24) -> 0.002489 | Y24: =SUM(H24:K24) -> 0.006428 | Z24: =SUM(L24:O24) -> 0.010335 | AA24: =SUM(P24:S24) -> 0.01424 | AB24: =SUM(T24:W24) -> 0.018176
A25: Depreciation Expense | B25: CapEx Depreciation output | C25: ='CapEx Depreciation'!C11 -> 0 | D25: ='CapEx Depreciation'!D11 -> 10 | E25: ='CapEx Depreciation'!E11 -> 20.05481 | F25: ='CapEx Depreciation'!F11 -> 30.157059 | G25: ='CapEx Depreciation'!G11 -> 40.258794 | H25: ='CapEx Depreciation'!H11 -> 50.433553 | I25: ='CapEx Depreciation'!I11 -> 60.674336 | J25: ='CapEx Depreciation'!J11 -> 70.933036 | ... W25: ='CapEx Depreciation'!W11 -> 206.34396 | X25: =SUM(D25:G25) -> 100.47066 | Y25: =SUM(H25:K25) -> 263.24305 | Z25: =SUM(L25:O25) -> 428.23144 | AA25: =SUM(P25:S25) -> 594.78996 | AB25: =SUM(T25:W25) -> 762.37971
A26: Taxes | B26: Direct model driver | C26: 0.204976 | D26: 0.204976 | E26: 0.204976 | F26: 0.204976 | G26: 0.204976 | H26: 0.204976 | I26: 0.204976 | J26: 0.204976 | K26: 0.204976 | L26: 0.204976 | M26: 0.204976 | N26: 0.204976 | O26: 0.204976 | P26: 0.204976 | Q26: 0.204976 | R26: 0.204976 | S26: 0.204976 | T26: 0.204976 | U26: 0.204976 | V26: 0.204976 | W26: 0.204976 | X26: =SUM(D26:G26) -> 0.819904 | Y26: =SUM(H26:K26) -> 0.819904 | Z26: =SUM(L26:O26) -> 0.819904 | AA26: =SUM(P26:S26) -> 0.819904 | AB26: =SUM(T26:W26) -> 0.819904
A28: Balance Sheet Inputs
A29: Accounts Receivable Days | B29: Working Capital schedule | C29: ='Working Capital'!C7 -> 0 | D29: ='Working Capital'!D7 -> 30 | E29: ='Working Capital'!E7 -> 40.918175 | F29: ='Working Capital'!F7 -> 40.918175 | G29: ='Working Capital'!G7 -> 40.918175 | H29: ='Working Capital'!H7 -> 40.918175 | I29: ='Working Capital'!I7 -> 40.918175 | J29: ='Working Capital'!J7 -> 40.918175 | ... W29: ='Working Capital'!W7 -> 40.918175 | X29: =SUM(D29:G29) -> 152.75452 | Y29: =SUM(H29:K29) -> 163.6727 | Z29: =SUM(L29:O29) -> 163.6727 | AA29: =SUM(P29:S29) -> 163.6727 | AB29: =SUM(T29:W29) -> 163.6727
A30: Inventory Days | B30: Working Capital schedule | C30: ='Working Capital'!C8 -> 0 | D30: ='Working Capital'!D8 -> 87.338516 | E30: ='Working Capital'!E8 -> 38.363792 | F30: ='Working Capital'!F8 -> 36.246985 | G30: ='Working Capital'!G8 -> 43.193839 | H30: ='Working Capital'!H8 -> 50.091365 | I30: ='Working Capital'!I8 -> 54.001195 | J30: ='Working Capital'!J8 -> 54.914438 | ... W30: ='Working Capital'!W8 -> 71.66529 | X30: =SUM(D30:G30) -> 205.14313 | Y30: =SUM(H30:K30) -> 217.66038 | Z30: =SUM(L30:O30) -> 248.55383 | AA30: =SUM(P30:S30) -> 242.0415 | AB30: =SUM(T30:W30) -> 275.88475
A31: Accounts Payable Days | B31: Working Capital schedule | C31: ='Working Capital'!C9 -> 0 | D31: ='Working Capital'!D9 -> 41.7 | E31: ='Working Capital'!E9 -> 45.544202 | F31: ='Working Capital'!F9 -> 43.522382 | G31: ='Working Capital'!G9 -> 43.306918 | H31: ='Working Capital'!H9 -> 44.763831 | I31: ='Working Capital'!I9 -> 44.676717 | J31: ='Working Capital'!J9 -> 43.861467 | ... W31: ='Working Capital'!W9 -> 84.986986 | X31: =SUM(D31:G31) -> 174.0735 | Y31: =SUM(H31:K31) -> 179.07013 | Z31: =SUM(L31:O31) -> 264.94398 | AA31: =SUM(P31:S31) -> 337.01306 | AB31: =SUM(T31:W31) -> 339.94794
A32: Prepaid Expenses (% of Revenue) | B32: Working Capital schedule | C32: ='Working Capital'!C10 -> 0 | D32: ='Working Capital'!D10 -> 0.02 | E32: ='Working Capital'!E10 -> 0.028269 | F32: ='Working Capital'!F10 -> 0.028269 | G32: ='Working Capital'!G10 -> 0.028269 | H32: ='Working Capital'!H10 -> 0.028269 | I32: ='Working Capital'!I10 -> 0.028269 | J32: ='Working Capital'!J10 -> 0.028269 | ... W32: ='Working Capital'!W10 -> 0.032856 | X32: =SUM(D32:G32) -> 0.104807 | Y32: =SUM(H32:K32) -> 0.11348 | Z32: =SUM(L32:O32) -> 0.117642 | AA32: =SUM(P32:S32) -> 0.113671 | AB32: =SUM(T32:W32) -> 0.125831
A33: Deferred Revenue (% of Revenue) | B33: Working Capital schedule | C33: ='Working Capital'!C11 -> 0 | D33: ='Working Capital'!D11 -> 0.15 | E33: ='Working Capital'!E11 -> 0.108048 | F33: ='Working Capital'!F11 -> 0.092136 | G33: ='Working Capital'!G11 -> 0.090163 | H33: ='Working Capital'!H11 -> 0.095003 | I33: ='Working Capital'!I11 -> 0.094688 | J33: ='Working Capital'!J11 -> 0.09191 | ... W33: ='Working Capital'!W11 -> 0.231975 | X33: =SUM(D33:G33) -> 0.440347 | Y33: =SUM(H33:K33) -> 0.380004 | Z33: =SUM(L33:O33) -> 0.672451 | AA33: =SUM(P33:S33) -> 0.917904 | AB33: =SUM(T33:W33) -> 0.9279
A34: Short Term Debt (% of LTD) | B34: Working Capital schedule | C34: ='Working Capital'!C12 -> 0 | D34: ='Working Capital'!D12 -> 0 | E34: ='Working Capital'!E12 -> 0 | F34: ='Working Capital'!F12 -> 0 | G34: ='Working Capital'!G12 -> 0 | H34: ='Working Capital'!H12 -> 0 | I34: ='Working Capital'!I12 -> 0 | J34: ='Working Capital'!J12 -> 0 | ... W34: ='Working Capital'!W12 -> 0 | X34: =SUM(D34:G34) -> 0 | Y34: =SUM(H34:K34) -> 0 | Z34: =SUM(L34:O34) -> 0 | AA34: =SUM(P34:S34) -> 0 | AB34: =SUM(T34:W34) -> 0
A35: Owner's Capital | B35: Cash Equity Schedule schedule | C35: ='Cash Equity Schedule'!C7 -> 100000 | D35: ='Cash Equity Schedule'!D7 -> 157098 | E35: ='Cash Equity Schedule'!E7 -> 162529 | F35: ='Cash Equity Schedule'!F7 -> 170541 | G35: ='Cash Equity Schedule'!G7 -> 173163 | H35: ='Cash Equity Schedule'!H7 -> 173163 | I35: ='Cash Equity Schedule'!I7 -> 173163 | J35: ='Cash Equity Schedule'!J7 -> 173163 | ... W35: ='Cash Equity Schedule'!W7 -> 173163 | X35: =G35 -> 173163 | Y35: =K35 -> 173163 | Z35: =O35 -> 173163 | AA35: =S35 -> 173163 | AB35: =W35 -> 173163
A36: Other Equity | B36: Cash Equity Schedule schedule | C36: ='Cash Equity Schedule'!C8 -> 0 | D36: ='Cash Equity Schedule'!D8 -> 0 | E36: ='Cash Equity Schedule'!E8 -> 0 | F36: ='Cash Equity Schedule'!F8 -> 0 | G36: ='Cash Equity Schedule'!G8 -> 0 | H36: ='Cash Equity Schedule'!H8 -> 0 | I36: ='Cash Equity Schedule'!I8 -> 0 | J36: ='Cash Equity Schedule'!J8 -> 0 | ... W36: ='Cash Equity Schedule'!W8 -> 0 | X36: =G36 -> 0 | Y36: =K36 -> 0 | Z36: =O36 -> 0 | AA36: =S36 -> 0 | AB36: =W36 -> 0
A37: Distributions | B37: Cash Equity Schedule schedule | C37: ='Cash Equity Schedule'!C9 -> 0 | D37: ='Cash Equity Schedule'!D9 -> 0 | E37: ='Cash Equity Schedule'!E9 -> 0 | F37: ='Cash Equity Schedule'!F9 -> 0 | G37: ='Cash Equity Schedule'!G9 -> 0 | H37: ='Cash Equity Schedule'!H9 -> 0 | I37: ='Cash Equity Schedule'!I9 -> 0 | J37: ='Cash Equity Schedule'!J9 -> 0 | ... W37: ='Cash Equity Schedule'!W9 -> 19557 | X37: =G37 -> 0 | Y37: =K37 -> 0 | Z37: =O37 -> 0 | AA37: =S37 -> 12743 | AB37: =W37 -> 19557
A39: Cash Flow and Schedule Inputs
A40: Cash Opening Balance | B40: Working Capital schedule | C40: ='Working Capital'!C15 -> 80000 | D40: ='Working Capital'!D15 -> 0 | E40: ='Working Capital'!E15 -> 0 | F40: ='Working Capital'!F15 -> 0 | G40: ='Working Capital'!G15 -> 0 | H40: ='Working Capital'!H15 -> 0 | I40: ='Working Capital'!I15 -> 0 | J40: ='Working Capital'!J15 -> 0 | ... W40: ='Working Capital'!W15 -> 0 | X40: =G40 -> 0 | Y40: =K40 -> 0 | Z40: =O40 -> 0 | AA40: =S40 -> 0 | AB40: =W40 -> 0
A41: Accounts Receivable Opening Balance | B41: Working Capital schedule | C41: ='Working Capital'!C16 -> 12000 | D41: ='Working Capital'!D16 -> 0 | E41: ='Working Capital'!E16 -> 0 | F41: ='Working Capital'!F16 -> 0 | G41: ='Working Capital'!G16 -> 0 | H41: ='Working Capital'!H16 -> 0 | I41: ='Working Capital'!I16 -> 0 | J41: ='Working Capital'!J16 -> 0 | ... W41: ='Working Capital'!W16 -> 0 | X41: =G41 -> 0 | Y41: =K41 -> 0 | Z41: =O41 -> 0 | AA41: =S41 -> 0 | AB41: =W41 -> 0
A42: Inventory Opening Balance | B42: Working Capital schedule | C42: ='Working Capital'!C17 -> 0 | D42: ='Working Capital'!D17 -> 0 | E42: ='Working Capital'!E17 -> 0 | F42: ='Working Capital'!F17 -> 0 | G42: ='Working Capital'!G17 -> 0 | H42: ='Working Capital'!H17 -> 0 | I42: ='Working Capital'!I17 -> 0 | J42: ='Working Capital'!J17 -> 0 | ... W42: ='Working Capital'!W17 -> 0 | X42: =G42 -> 0 | Y42: =K42 -> 0 | Z42: =O42 -> 0 | AA42: =S42 -> 0 | AB42: =W42 -> 0
A43: Accounts Payable Opening Balance | B43: Working Capital schedule | C43: ='Working Capital'!C18 -> 0 | D43: ='Working Capital'!D18 -> 0 | E43: ='Working Capital'!E18 -> 0 | F43: ='Working Capital'!F18 -> 0 | G43: ='Working Capital'!G18 -> 0 | H43: ='Working Capital'!H18 -> 0 | I43: ='Working Capital'!I18 -> 0 | J43: ='Working Capital'!J18 -> 0 | ... W43: ='Working Capital'!W18 -> 0 | X43: =G43 -> 0 | Y43: =K43 -> 0 | Z43: =O43 -> 0 | AA43: =S43 -> 0 | AB43: =W43 -> 0
A44: Short Term Debt Opening Balance | B44: Working Capital schedule | C44: ='Working Capital'!C19 -> 0 | D44: ='Working Capital'!D19 -> 0 | E44: ='Working Capital'!E19 -> 0 | F44: ='Working Capital'!F19 -> 0 | G44: ='Working Capital'!G19 -> 0 | H44: ='Working Capital'!H19 -> 0 | I44: ='Working Capital'!I19 -> 0 | J44: ='Working Capital'!J19 -> 0 | ... W44: ='Working Capital'!W19 -> 0 | X44: =G44 -> 0 | Y44: =K44 -> 0 | Z44: =O44 -> 0 | AA44: =S44 -> 0 | AB44: =W44 -> 0
A45: Debt Opening Balance | B45: Debt Schedule schedule | C45: ='Debt Schedule'!C7 -> 0 | D45: ='Debt Schedule'!D7 -> 0 | E45: ='Debt Schedule'!E7 -> 0 | F45: ='Debt Schedule'!F7 -> 0 | G45: ='Debt Schedule'!G7 -> 0 | H45: ='Debt Schedule'!H7 -> 0 | I45: ='Debt Schedule'!I7 -> 0 | J45: ='Debt Schedule'!J7 -> 0 | ... W45: ='Debt Schedule'!W7 -> 0 | X45: =G45 -> 0 | Y45: =K45 -> 0 | Z45: =O45 -> 0 | AA45: =S45 -> 0 | AB45: =W45 -> 0
A46: Debt Issuance | B46: Debt Schedule schedule | C46: ='Debt Schedule'!C8 -> 0 | D46: ='Debt Schedule'!D8 -> 0 | E46: ='Debt Schedule'!E8 -> 0 | F46: ='Debt Schedule'!F8 -> 0 | G46: ='Debt Schedule'!G8 -> 0 | H46: ='Debt Schedule'!H8 -> 0 | I46: ='Debt Schedule'!I8 -> 0 | J46: ='Debt Schedule'!J8 -> 0 | ... W46: ='Debt Schedule'!W8 -> 0 | X46: =SUM(D46:G46) -> 0 | Y46: =SUM(H46:K46) -> 0 | Z46: =SUM(L46:O46) -> 0 | AA46: =SUM(P46:S46) -> 0 | AB46: =SUM(T46:W46) -> 0
A47: Debt Repayment | B47: Debt Schedule schedule | C47: ='Debt Schedule'!C10 -> 0 | D47: ='Debt Schedule'!D10 -> 0 | E47: ='Debt Schedule'!E10 -> 0 | F47: ='Debt Schedule'!F10 -> 0 | G47: ='Debt Schedule'!G10 -> 0 | H47: ='Debt Schedule'!H10 -> 0 | I47: ='Debt Schedule'!I10 -> 0 | J47: ='Debt Schedule'!J10 -> 0 | ... W47: ='Debt Schedule'!W10 -> 0 | X47: =SUM(D47:G47) -> 0 | Y47: =SUM(H47:K47) -> 0 | Z47: =SUM(L47:O47) -> 0 | AA47: =SUM(P47:S47) -> 0 | AB47: =SUM(T47:W47) -> 0
A48: Debt Closing Balance | B48: Debt Schedule schedule | C48: ='Debt Schedule'!C11 -> 0 | D48: ='Debt Schedule'!D11 -> 0 | E48: ='Debt Schedule'!E11 -> 0 | F48: ='Debt Schedule'!F11 -> 0 | G48: ='Debt Schedule'!G11 -> 0 | H48: ='Debt Schedule'!H11 -> 0 | I48: ='Debt Schedule'!I11 -> 0 | J48: ='Debt Schedule'!J11 -> 0 | ... W48: ='Debt Schedule'!W11 -> 0 | X48: =G48 -> 0 | Y48: =K48 -> 0 | Z48: =O48 -> 0 | AA48: =S48 -> 0 | AB48: =W48 -> 0
A49: Lease Opening Balance | B49: Debt Schedule schedule | C49: ='Debt Schedule'!C18 -> 0 | D49: ='Debt Schedule'!D18 -> 0 | E49: ='Debt Schedule'!E18 -> 0 | F49: ='Debt Schedule'!F18 -> 0 | G49: ='Debt Schedule'!G18 -> 0 | H49: ='Debt Schedule'!H18 -> 0 | I49: ='Debt Schedule'!I18 -> 0 | J49: ='Debt Schedule'!J18 -> 0 | ... W49: ='Debt Schedule'!W18 -> 0 | X49: =G49 -> 0 | Y49: =K49 -> 0 | Z49: =O49 -> 0 | AA49: =S49 -> 0 | AB49: =W49 -> 0
A50: Lease Principal Repayments | B50: Debt Schedule schedule | C50: ='Debt Schedule'!C20 -> 0 | D50: ='Debt Schedule'!D20 -> 0 | E50: ='Debt Schedule'!E20 -> 0 | F50: ='Debt Schedule'!F20 -> 0 | G50: ='Debt Schedule'!G20 -> 0 | H50: ='Debt Schedule'!H20 -> 0 | I50: ='Debt Schedule'!I20 -> 0 | J50: ='Debt Schedule'!J20 -> 0 | ... W50: ='Debt Schedule'!W20 -> 0 | X50: =SUM(D50:G50) -> 0 | Y50: =SUM(H50:K50) -> 0 | Z50: =SUM(L50:O50) -> 0 | AA50: =SUM(P50:S50) -> 0 | AB50: =SUM(T50:W50) -> 0
A51: Lease Net Additions | B51: Debt Schedule schedule | C51: ='Debt Schedule'!C21 -> 0 | D51: ='Debt Schedule'!D21 -> 0 | E51: ='Debt Schedule'!E21 -> 0 | F51: ='Debt Schedule'!F21 -> 0 | G51: ='Debt Schedule'!G21 -> 0 | H51: ='Debt Schedule'!H21 -> 0 | I51: ='Debt Schedule'!I21 -> 0 | J51: ='Debt Schedule'!J21 -> 0 | ... W51: ='Debt Schedule'!W21 -> 0 | X51: =SUM(D51:G51) -> 0 | Y51: =SUM(H51:K51) -> 0 | Z51: =SUM(L51:O51) -> 0 | AA51: =SUM(P51:S51) -> 0 | AB51: =SUM(T51:W51) -> 0
A52: Lease Interest Expense | B52: Debt Schedule schedule | C52: ='Debt Schedule'!C22 -> 0 | D52: ='Debt Schedule'!D22 -> 0 | E52: ='Debt Schedule'!E22 -> 0 | F52: ='Debt Schedule'!F22 -> 0 | G52: ='Debt Schedule'!G22 -> 0 | H52: ='Debt Schedule'!H22 -> 0 | I52: ='Debt Schedule'!I22 -> 0 | J52: ='Debt Schedule'!J22 -> 0 | ... W52: ='Debt Schedule'!W22 -> 0 | X52: =SUM(D52:G52) -> 0 | Y52: =SUM(H52:K52) -> 0 | Z52: =SUM(L52:O52) -> 0 | AA52: =SUM(P52:S52) -> 0 | AB52: =SUM(T52:W52) -> 0
A53: Lease Closing Balance | B53: Debt Schedule schedule | C53: ='Debt Schedule'!C23 -> 0 | D53: ='Debt Schedule'!D23 -> 0 | E53: ='Debt Schedule'!E23 -> 0 | F53: ='Debt Schedule'!F23 -> 0 | G53: ='Debt Schedule'!G23 -> 0 | H53: ='Debt Schedule'!H23 -> 0 | I53: ='Debt Schedule'!I23 -> 0 | J53: ='Debt Schedule'!J23 -> 0 | ... W53: ='Debt Schedule'!W23 -> 0 | X53: =G53 -> 0 | Y53: =K53 -> 0 | Z53: =O53 -> 0 | AA53: =S53 -> 0 | AB53: =W53 -> 0
A54: Right-of-Use Asset | B54: Debt Schedule schedule | C54: ='Debt Schedule'!C26 -> 0 | D54: ='Debt Schedule'!D26 -> 0 | E54: ='Debt Schedule'!E26 -> 0 | F54: ='Debt Schedule'!F26 -> 0 | G54: ='Debt Schedule'!G26 -> 0 | H54: ='Debt Schedule'!H26 -> 0 | I54: ='Debt Schedule'!I26 -> 0 | J54: ='Debt Schedule'!J26 -> 0 | ... W54: ='Debt Schedule'!W26 -> 0 | X54: =G54 -> 0 | Y54: =K54 -> 0 | Z54: =O54 -> 0 | AA54: =S54 -> 0 | AB54: =W54 -> 0
A55: Lease Asset Depreciation | B55: Debt Schedule schedule | C55: ='Debt Schedule'!C25 -> 0 | D55: ='Debt Schedule'!D25 -> 0 | E55: ='Debt Schedule'!E25 -> 0 | F55: ='Debt Schedule'!F25 -> 0 | G55: ='Debt Schedule'!G25 -> 0 | H55: ='Debt Schedule'!H25 -> 0 | I55: ='Debt Schedule'!I25 -> 0 | J55: ='Debt Schedule'!J25 -> 0 | ... W55: ='Debt Schedule'!W25 -> 0 | X55: =SUM(D55:G55) -> 0 | Y55: =SUM(H55:K55) -> 0 | Z55: =SUM(L55:O55) -> 0 | AA55: =SUM(P55:S55) -> 0 | AB55: =SUM(T55:W55) -> 0
A56: Capital Expenditures | B56: CapEx Depreciation schedule | C56: ='CapEx Depreciation'!C8 -> 0 | D56: ='CapEx Depreciation'!D8 -> 200 | E56: ='CapEx Depreciation'!E8 -> 200.95 | F56: ='CapEx Depreciation'!F8 -> 201.85448 | G56: ='CapEx Depreciation'!G8 -> 202.71296 | H56: ='CapEx Depreciation'!H8 -> 203.52523 | I56: ='CapEx Depreciation'!I8 -> 204.29069 | J56: ='CapEx Depreciation'!J8 -> 205.00877 | ... W56: ='CapEx Depreciation'!W8 -> 209.86977 | X56: =SUM(D56:G56) -> 805.51744 | Y56: =SUM(H56:K56) -> 818.50385 | Z56: =SUM(L56:O56) -> 828.45382 | AA56: =SUM(P56:S56) -> 835.26719 | AB56: =SUM(T56:W56) -> 838.85302
A57: PPE Closing Balance | B57: CapEx Depreciation schedule | C57: ='CapEx Depreciation'!C12 -> 40000 | D57: ='CapEx Depreciation'!D12 -> 40190 | E57: ='CapEx Depreciation'!E12 -> 40370.895 | F57: ='CapEx Depreciation'!F12 -> 40542.593 | G57: ='CapEx Depreciation'!G12 -> 40705.047 | H57: ='CapEx Depreciation'!H12 -> 40858.138 | I57: ='CapEx Depreciation'!I12 -> 41001.755 | J57: ='CapEx Depreciation'!J12 -> 41135.831 | ... W57: ='CapEx Depreciation'!W12 -> 41977.48 | X57: =G57 -> 40705.047 | Y57: =K57 -> 41260.308 | Z57: =O57 -> 41660.53 | AA57: =S57 -> 41901.007 | AB57: =W57 -> 41977.48
A58: Accumulated Depreciation | B58: CapEx Depreciation schedule | C58: ='CapEx Depreciation'!C14 -> 0 | D58: ='CapEx Depreciation'!D14 -> -10 | E58: ='CapEx Depreciation'!E14 -> -30.05481 | F58: ='CapEx Depreciation'!F14 -> -60.211869 | G58: ='CapEx Depreciation'!G14 -> -100.47066 | H58: ='CapEx Depreciation'!H14 -> -150.90422 | I58: ='CapEx Depreciation'!I14 -> -211.57855 | J58: ='CapEx Depreciation'!J14 -> -282.51159 | ... W58: ='CapEx Depreciation'!W14 -> -2149.1148 | X58: =G58 -> -100.47066 | Y58: =K58 -> -363.71372 | Z58: =O58 -> -791.94516 | AA58: =S58 -> -1386.7351 | AB58: =W58 -> -2149.1148

Sheet FINMO
A1: FINMO
A2: Three-statement financial model. All formulas reference Model Inputs and in-sheet statement rows.
C4: Stub | D4: Q1 | E4: Q2 | F4: Q3 | G4: Q4 | H4: Q5 | I4: Q6 | J4: Q7 | K4: Q8 | L4: Q9 | M4: Q10 | N4: Q11 | O4: Q12 | P4: Q13 | Q4: Q14 | R4: Q15 | S4: Q16 | T4: Q17 | U4: Q18 | V4: Q19 | W4: Q20 | X4: Y1 | Y4: Y2 | Z4: Y3 | AA4: Y4 | AB4: Y5
C5: 46162 | D5: 46295 | E5: 46387 | F5: 46477 | G5: 46568 | H5: 46660 | I5: 46752 | J5: 46843 | K5: 46934 | L5: 47026 | M5: 47118 | N5: 47208 | O5: 47299 | P5: 47391 | Q5: 47483 | R5: 47573 | S5: 47664 | T5: 47756 | U5: 47848 | V5: 47938 | W5: 48029 | X5: Annual | Y5: Annual | Z5: Annual | AA5: Annual | AB5: Annual
A6: Days in Quarter | C6: 0 | D6: 92 | E6: 92 | F6: 90 | G6: 91 | H6: 92 | I6: 92 | J6: 91 | K6: 91 | L6: 92 | M6: 92 | N6: 90 | O6: 91 | P6: 92 | Q6: 92 | R6: 90 | S6: 91 | T6: 92 | U6: 92 | V6: 90 | W6: 91
A7: Income Statement
A8: Revenue | B8: Formula | C8: ='Model Inputs'!C15 -> 1528800 | D8: ='Model Inputs'!D15 -> 274877.56 | E8: ='Model Inputs'!E15 -> 277227.25 | F8: ='Model Inputs'!F15 -> 281912.38 | G8: ='Model Inputs'!G15 -> 286019.97 | H8: ='Model Inputs'!H15 -> 297884.01 | I8: ='Model Inputs'!I15 -> 299958.22 | J8: ='Model Inputs'!J15 -> 305514.83 | ... W8: ='Model Inputs'!W15 -> 639387.23 | X8: =SUM(D8:G8) -> 1120037.2 | Y8: =SUM(H8:K8) -> 1213990.5 | Z8: =SUM(L8:O8) -> 1528143.9 | AA8: =SUM(P8:S8) -> 2310993.4 | AB8: =SUM(T8:W8) -> 2520947.9
A9: Cost of Goods Sold | B9: Formula | C9: =C8*'Model Inputs'!C16 -> 244608 | D9: =D8*'Model Inputs'!D16 -> 59385.235 | E9: =E8*'Model Inputs'!E16 -> 59892.868 | F9: =F8*'Model Inputs'!F16 -> 60905.055 | G9: =G8*'Model Inputs'!G16 -> 61792.47 | H9: =H8*'Model Inputs'!H16 -> 64355.605 | I9: =I8*'Model Inputs'!I16 -> 64803.723 | J9: =J8*'Model Inputs'!J16 -> 66004.189 | ... W9: =W8*'Model Inputs'!W16 -> 200710.23 | X9: =SUM(D9:G9) -> 241975.63 | Y9: =SUM(H9:K9) -> 262273.53 | Z9: =SUM(L9:O9) -> 376010.72 | AA9: =SUM(P9:S9) -> 704017.84 | AB9: =SUM(T9:W9) -> 786962.33
A10: Gross Profit | B10: Formula | C10: =C8-C9 -> 1284192 | D10: =D8-D9 -> 215492.33 | E10: =E8-E9 -> 217334.38 | F10: =F8-F9 -> 221007.32 | G10: =G8-G9 -> 224227.5 | H10: =H8-H9 -> 233528.4 | I10: =I8-I9 -> 235154.49 | J10: =J8-J9 -> 239510.65 | ... W10: =W8-W9 -> 438677 | X10: =SUM(D10:G10) -> 878061.53 | Y10: =SUM(H10:K10) -> 951716.93 | Z10: =SUM(L10:O10) -> 1152133.2 | AA10: =SUM(P10:S10) -> 1606975.6 | AB10: =SUM(T10:W10) -> 1733985.6
A11: Marketing | B11: Formula | C11: =C8*'Model Inputs'!C17 -> 183456 | D11: =D8*'Model Inputs'!D17 -> 42993.943 | E11: =E8*'Model Inputs'!E17 -> 43361.461 | F11: =F8*'Model Inputs'!F17 -> 44094.267 | G11: =G8*'Model Inputs'!G17 -> 44736.742 | H11: =H8*'Model Inputs'!H17 -> 46592.41 | I11: =I8*'Model Inputs'!I17 -> 46916.84 | J11: =J8*'Model Inputs'!J17 -> 47785.957 | ... W11: =W8*'Model Inputs'!W17 -> 126929.07 | X11: =SUM(D11:G11) -> 175186.41 | Y11: =SUM(H11:K11) -> 189881.77 | Z11: =SUM(L11:O11) -> 258752.04 | AA11: =SUM(P11:S11) -> 449552.46 | AB11: =SUM(T11:W11) -> 498562
A12: Research & Development | B12: Formula | C12: =C8*'Model Inputs'!C18 -> 0 | D12: =D8*'Model Inputs'!D18 -> 0 | E12: =E8*'Model Inputs'!E18 -> 0 | F12: =F8*'Model Inputs'!F18 -> 0 | G12: =G8*'Model Inputs'!G18 -> 0 | H12: =H8*'Model Inputs'!H18 -> 0 | I12: =I8*'Model Inputs'!I18 -> 0 | J12: =J8*'Model Inputs'!J18 -> 0 | ... W12: =W8*'Model Inputs'!W18 -> 0 | X12: =SUM(D12:G12) -> 0 | Y12: =SUM(H12:K12) -> 0 | Z12: =SUM(L12:O12) -> 0 | AA12: =SUM(P12:S12) -> 0 | AB12: =SUM(T12:W12) -> 0
A13: Lease/Rent | B13: Formula | C13: ='Model Inputs'!C19 -> 12600 | D13: ='Model Inputs'!D19 -> 12600 | E13: ='Model Inputs'!E19 -> 12600 | F13: ='Model Inputs'!F19 -> 12600 | G13: ='Model Inputs'!G19 -> 12600 | H13: ='Model Inputs'!H19 -> 12600 | I13: ='Model Inputs'!I19 -> 12600 | J13: ='Model Inputs'!J19 -> 12600 | ... W13: ='Model Inputs'!W19 -> 12600 | X13: =SUM(D13:G13) -> 50400 | Y13: =SUM(H13:K13) -> 50400 | Z13: =SUM(L13:O13) -> 50400 | AA13: =SUM(P13:S13) -> 50400 | AB13: =SUM(T13:W13) -> 50400
A14: Payroll | B14: Formula | C14: ='Model Inputs'!C20 -> 134521.88 | D14: ='Model Inputs'!D20 -> 115547.95 | E14: ='Model Inputs'!E20 -> 115547.95 | F14: ='Model Inputs'!F20 -> 115547.95 | G14: ='Model Inputs'!G20 -> 115547.95 | H14: ='Model Inputs'!H20 -> 119014.33 | I14: ='Model Inputs'!I20 -> 119014.33 | J14: ='Model Inputs'!J20 -> 119014.33 | ... W14: ='Model Inputs'!W20 -> 130050.35 | X14: =SUM(D14:G14) -> 462191.8 | Y14: =SUM(H14:K14) -> 476057.31 | Z14: =SUM(L14:O14) -> 490338.83 | AA14: =SUM(P14:S14) -> 505051.06 | AB14: =SUM(T14:W14) -> 520201.38
A15: General & Administrative | B15: Formula | C15: =C8*'Model Inputs'!C21 -> 700.1904 | D15: =D8*'Model Inputs'!D21 -> 42993.943 | E15: =E8*'Model Inputs'!E21 -> 43361.461 | F15: =F8*'Model Inputs'!F21 -> 44094.267 | G15: =G8*'Model Inputs'!G21 -> 44736.742 | H15: =H8*'Model Inputs'!H21 -> 46592.41 | I15: =I8*'Model Inputs'!I21 -> 46916.84 | J15: =J8*'Model Inputs'!J21 -> 47785.957 | ... W15: =W8*'Model Inputs'!W21 -> 126929.07 | X15: =SUM(D15:G15) -> 175186.41 | Y15: =SUM(H15:K15) -> 189881.77 | Z15: =SUM(L15:O15) -> 258752.04 | AA15: =SUM(P15:S15) -> 449552.46 | AB15: =SUM(T15:W15) -> 498562
A16: EBITDA | B16: Formula | C16: =C10-SUM(C11:C15) -> 952913.93 | D16: =D10-SUM(D11:D15) -> 1356.4896 | E16: =E10-SUM(E11:E15) -> 2463.5104 | F16: =F10-SUM(F11:F15) -> 4670.8383 | G16: =G10-SUM(G11:G15) -> 6606.0705 | H16: =H10-SUM(H11:H15) -> 8729.2537 | I16: =I10-SUM(I11:I15) -> 9706.4871 | J16: =J10-SUM(J11:J15) -> 12324.404 | ... W16: =W10-SUM(W11:W15) -> 42168.522 | X16: =SUM(D16:G16) -> 15096.909 | Y16: =SUM(H16:K16) -> 45496.086 | Z16: =SUM(L16:O16) -> 93890.274 | AA16: =SUM(P16:S16) -> 152419.58 | AB16: =SUM(T16:W16) -> 166260.18
A17: Interest | B17: Formula | C17: ='Model Inputs'!C23+'Model Inputs'!C52 -> 0 | D17: ='Model Inputs'!D23+'Model Inputs'!D52 -> 0 | E17: ='Model Inputs'!E23+'Model Inputs'!E52 -> 0 | F17: ='Model Inputs'!F23+'Model Inputs'!F52 -> 0 | G17: ='Model Inputs'!G23+'Model Inputs'!G52 -> 0 | H17: ='Model Inputs'!H23+'Model Inputs'!H52 -> 0 | I17: ='Model Inputs'!I23+'Model Inputs'!I52 -> 0 | J17: ='Model Inputs'!J23+'Model Inputs'!J52 -> 0 | ... W17: ='Model Inputs'!W23+'Model Inputs'!W52 -> 0 | X17: =SUM(D17:G17) -> 0 | Y17: =SUM(H17:K17) -> 0 | Z17: =SUM(L17:O17) -> 0 | AA17: =SUM(P17:S17) -> 0 | AB17: =SUM(T17:W17) -> 0
A18: Depreciation | B18: Formula | C18: ='Model Inputs'!C25+'Model Inputs'!C55 -> 0 | D18: ='Model Inputs'!D25+'Model Inputs'!D55 -> 10 | E18: ='Model Inputs'!E25+'Model Inputs'!E55 -> 20.05481 | F18: ='Model Inputs'!F25+'Model Inputs'!F55 -> 30.157059 | G18: ='Model Inputs'!G25+'Model Inputs'!G55 -> 40.258794 | H18: ='Model Inputs'!H25+'Model Inputs'!H55 -> 50.433553 | I18: ='Model Inputs'!I25+'Model Inputs'!I55 -> 60.674336 | J18: ='Model Inputs'!J25+'Model Inputs'!J55 -> 70.933036 | ... W18: ='Model Inputs'!W25+'Model Inputs'!W55 -> 206.34396 | X18: =SUM(D18:G18) -> 100.47066 | Y18: =SUM(H18:K18) -> 263.24305 | Z18: =SUM(L18:O18) -> 428.23144 | AA18: =SUM(P18:S18) -> 594.78996 | AB18: =SUM(T18:W18) -> 762.37971
A19: Taxes | B19: Formula | C19: =MAX(0,C16-C17-C18)*'Model Inputs'!C26 -> 195324.49 | D19: =MAX(0,D16-D17-D18)*'Model Inputs'!D26 -> 275.99805 | E19: =MAX(0,E16-E17-E18)*'Model Inputs'!E26 -> 500.84975 | F19: =MAX(0,F16-F17-F18)*'Model Inputs'!F26 -> 951.22829 | G19: =MAX(0,G16-G17-G18)*'Model Inputs'!G26 -> 1345.8338 | H19: =MAX(0,H16-H17-H18)*'Model Inputs'!H26 -> 1778.9498 | I19: =MAX(0,I16-I17-I18)*'Model Inputs'!I26 -> 1977.1601 | J19: =MAX(0,J16-J17-J18)*'Model Inputs'!J26 -> 2511.6675 | ... W19: =MAX(0,W16-W17-W18)*'Model Inputs'!W26 -> 8601.2394 | X19: =SUM(D19:G19) -> 3073.9099 | Y19: =SUM(H19:K19) -> 9271.6472 | Z19: =SUM(L19:O19) -> 19157.476 | AA19: =SUM(P19:S19) -> 31120.437 | AB19: =SUM(T19:W19) -> 33923.076
A20: Net Income | B20: Formula | C20: =C16-SUM(C17:C19) -> 757589.45 | D20: =D16-SUM(D17:D19) -> 1070.4915 | E20: =E16-SUM(E17:E19) -> 1942.6058 | F20: =F16-SUM(F17:F19) -> 3689.453 | G20: =G16-SUM(G17:G19) -> 5219.9779 | H20: =H16-SUM(H17:H19) -> 6899.8703 | I20: =I16-SUM(I17:I19) -> 7668.6526 | J20: =J16-SUM(J17:J19) -> 9741.8036 | ... W20: =W16-SUM(W17:W19) -> 33360.939 | X20: =SUM(D20:G20) -> 11922.528 | Y20: =SUM(H20:K20) -> 35961.196 | Z20: =SUM(L20:O20) -> 74304.567 | AA20: =SUM(P20:S20) -> 120704.35 | AB20: =SUM(T20:W20) -> 131574.72
A22: Balance Sheet
A23: Cash | B23: Formula | C23: =C61 -> 80000 | D23: =D61 -> 136761.7 | E23: =E61 -> 137383.46 | F23: =F61 -> 138622.68 | G23: =G61 -> 139710.26 | H23: =H61 -> 144857.78 | I23: =I61 -> 148608.43 | J23: =J61 -> 152000.32 | ... W23: =W61 -> 398158.27 | X23: =G23 -> 139710.26 | Y23: =K23 -> 165583.03 | Z23: =O23 -> 295285.19 | AA23: =S23 -> 379430.25 | AB23: =W23 -> 398158.27
A24: Accounts Receivable | B24: Formula | C24: ='Model Inputs'!C41 -> 12000 | D24: =('Model Inputs'!D29/D6)*D8 -> 89633.987 | E24: =('Model Inputs'!E29/E6)*E8 -> 123300.36 | F24: =('Model Inputs'!F29/F6)*F8 -> 128170.44 | G24: =('Model Inputs'!G29/G6)*G8 -> 128608.96 | H24: =('Model Inputs'!H29/H6)*H8 -> 132487.72 | I24: =('Model Inputs'!I29/I6)*I8 -> 133410.25 | J24: =('Model Inputs'!J29/J6)*J8 -> 137374.83 | K24: =('Model Inputs'!K29/K6)*K8 -> 139676.4 | ... W24: =('Model Inputs'!W29/W6)*W8 -> 287500.65 | X24: =G24 -> 128608.96 | Y24: =K24 -> 139676.4 | Z24: =O24 -> 215094.61 | AA24: =S24 -> 273976.97 | AB24: =W24 -> 287500.65
A25: Inventory | B25: Formula | C25: ='Model Inputs'!C42 -> 0 | D25: =('Model Inputs'!D30/D6)*D9 -> 56376.286 | E25: =('Model Inputs'!E30/E6)*E9 -> 24975.191 | F25: =('Model Inputs'!F30/F6)*F9 -> 24529.162 | G25: =('Model Inputs'!G30/G6)*G9 -> 29330.264 | H25: =('Model Inputs'!H30/H6)*H9 -> 35039.784 | I25: =('Model Inputs'!I30/I6)*I9 -> 38037.81 | J25: =('Model Inputs'!J30/J6)*J9 -> 39830.582 | K25: =('Model Inputs'!K30/K6)*K9 -> 43255.27 | ... W25: =('Model Inputs'!W30/W6)*W9 -> 158065.46 | X25: =G25 -> 29330.264 | Y25: =K25 -> 43255.27 | Z25: =O25 -> 84801.596 | AA25: =S25 -> 130403.13 | AB25: =W25 -> 158065.46
A26: Prepaid Expenses | B26: Formula | C26: =0 -> 0 | D26: =D8*'Model Inputs'!D32 -> 5497.5512 | E26: =E8*'Model Inputs'!E32 -> 7836.9371 | F26: =F8*'Model Inputs'!F32 -> 7969.381 | G26: =G8*'Model Inputs'!G32 -> 8085.4986 | H26: =H8*'Model Inputs'!H32 -> 8420.883 | I26: =I8*'Model Inputs'!I32 -> 8479.5188 | J26: =J8*'Model Inputs'!J32 -> 8636.5989 | K26: =K8*'Model Inputs'!K32 -> 8906.7916 | ... W26: =W8*'Model Inputs'!W32 -> 21007.707 | X26: =G26 -> 8085.4986 | Y26: =K26 -> 8906.7916 | Z26: =O26 -> 13522.753 | AA26: =S26 -> 17587.16 | AB26: =W26 -> 21007.707
A27: Current Assets | B27: Formula | C27: =SUM(C23:C26) -> 92000 | D27: =SUM(D23:D26) -> 288269.52 | E27: =SUM(E23:E26) -> 293495.95 | F27: =SUM(F23:F26) -> 299291.67 | G27: =SUM(G23:G26) -> 305734.98 | H27: =SUM(H23:H26) -> 320806.17 | I27: =SUM(I23:I26) -> 328536.01 | J27: =SUM(J23:J26) -> 337842.33 | ... W27: =SUM(W23:W26) -> 864732.09 | X27: =G27 -> 305734.98 | Y27: =K27 -> 357421.48 | Z27: =O27 -> 608704.14 | AA27: =S27 -> 801397.51 | AB27: =W27 -> 864732.09
A28: PPE | B28: Formula | C28: ='Model Inputs'!C57 -> 40000 | D28: ='Model Inputs'!D57 -> 40190 | E28: ='Model Inputs'!E57 -> 40370.895 | F28: ='Model Inputs'!F57 -> 40542.593 | G28: ='Model Inputs'!G57 -> 40705.047 | H28: ='Model Inputs'!H57 -> 40858.138 | I28: ='Model Inputs'!I57 -> 41001.755 | J28: ='Model Inputs'!J57 -> 41135.831 | ... W28: ='Model Inputs'!W57 -> 41977.48 | X28: =G28 -> 40705.047 | Y28: =K28 -> 41260.308 | Z28: =O28 -> 41660.53 | AA28: =S28 -> 41901.007 | AB28: =W28 -> 41977.48
A29: Right-of-Use Asset (Capital Lease) | B29: Formula | C29: ='Model Inputs'!C54 -> 0 | D29: ='Model Inputs'!D54 -> 0 | E29: ='Model Inputs'!E54 -> 0 | F29: ='Model Inputs'!F54 -> 0 | G29: ='Model Inputs'!G54 -> 0 | H29: ='Model Inputs'!H54 -> 0 | I29: ='Model Inputs'!I54 -> 0 | J29: ='Model Inputs'!J54 -> 0 | ... W29: ='Model Inputs'!W54 -> 0 | X29: =G29 -> 0 | Y29: =K29 -> 0 | Z29: =O29 -> 0 | AA29: =S29 -> 0 | AB29: =W29 -> 0
A30: Accumulated Depreciation | B30: Formula | C30: ='Model Inputs'!C58 -> 0 | D30: ='Model Inputs'!D58 -> -10 | E30: ='Model Inputs'!E58 -> -30.05481 | F30: ='Model Inputs'!F58 -> -60.211869 | G30: ='Model Inputs'!G58 -> -100.47066 | H30: ='Model Inputs'!H58 -> -150.90422 | I30: ='Model Inputs'!I58 -> -211.57855 | J30: ='Model Inputs'!J58 -> -282.51159 | ... W30: ='Model Inputs'!W58 -> -2149.1148 | X30: =G30 -> -100.47066 | Y30: =K30 -> -363.71372 | Z30: =O30 -> -791.94516 | AA30: =S30 -> -1386.7351 | AB30: =W30 -> -2149.1148
A31: Total Assets | B31: Formula | C31: =C27+C28+C29 -> 132000 | D31: =D27+D28+D29 -> 328459.52 | E31: =E27+E28+E29 -> 333866.84 | F31: =F27+F28+F29 -> 339834.26 | G31: =G27+G28+G29 -> 346440.03 | H31: =H27+H28+H29 -> 361664.31 | I31: =I27+I28+I29 -> 369537.76 | J31: =J27+J28+J29 -> 378978.16 | ... W31: =W27+W28+W29 -> 906709.57 | X31: =G31 -> 346440.03 | Y31: =K31 -> 398681.79 | Z31: =O31 -> 650364.67 | AA31: =S31 -> 843298.52 | AB31: =W31 -> 906709.57
A32: Accounts Payable | B32: Formula | C32: ='Model Inputs'!C43 -> 0 | D32: =('Model Inputs'!D31/D6)*SUM(D11:D15) -> 97059.395 | E32: =('Model Inputs'!E31/E6)*SUM(E11:E15) -> 106370.9 | F32: =('Model Inputs'!F31/F6)*SUM(F11:F15) -> 104616.43 | G32: =('Model Inputs'!G31/G6)*SUM(G11:G15) -> 103566.08 | H32: =('Model Inputs'!H31/H6)*SUM(H11:H15) -> 109379.03 | I32: =('Model Inputs'!I31/I6)*SUM(I11:I15) -> 109481.27 | J32: =('Model Inputs'!J31/J6)*SUM(J11:J15) -> 109502.44 | K32: =('Model Inputs'!K31/K6)*SUM(K11:K15) -> 115067.81 | ... W32: =('Model Inputs'!W31/W6)*SUM(W11:W15) -> 370308.36 | X32: =G32 -> 103566.08 | Y32: =K32 -> 115067.81 | Z32: =O32 -> 270295.03 | AA32: =S32 -> 354355.9 | AB32: =W32 -> 370308.36
A33: Short Term Debt | B33: Formula | C33: ='Model Inputs'!C44 -> 0 | D33: =SUM('Debt Schedule'!E10:H10) -> 0 | E33: =SUM('Debt Schedule'!F10:I10) -> 0 | F33: =SUM('Debt Schedule'!G10:J10) -> 0 | G33: =SUM('Debt Schedule'!H10:K10) -> 0 | H33: =SUM('Debt Schedule'!I10:L10) -> 0 | I33: =SUM('Debt Schedule'!J10:M10) -> 0 | J33: =SUM('Debt Schedule'!K10:N10) -> 0 | K33: =SUM('Debt Schedule'!L10:O10) -> 0 | ... S33: =SUM('Debt Schedule'!T10:W10) -> 0 | T33: =SUM('Debt Schedule'!U10:W10) -> 0 | U33: =SUM('Debt Schedule'!V10:W10) -> 0 | V33: =SUM('Debt Schedule'!W10:W10) -> 0 | W33: =0 -> 0 | X33: =G33 -> 0 | Y33: =K33 -> 0 | Z33: =O33 -> 0 | AA33: =S33 -> 0 | AB33: =W33 -> 0
A34: Deferred Revenue | B34: Formula | C34: =0 -> 0 | D34: ='Model Inputs'!D33*D8 -> 41231.634 | E34: ='Model Inputs'!E33*E8 -> 29953.85 | F34: ='Model Inputs'!F33*F8 -> 25974.279 | G34: ='Model Inputs'!G33*G8 -> 25788.419 | H34: ='Model Inputs'!H33*H8 -> 28299.874 | I34: ='Model Inputs'!I33*I8 -> 28402.444 | J34: ='Model Inputs'!J33*J8 -> 28079.868 | K34: ='Model Inputs'!K33*K8 -> 30567.259 | ... W34: ='Model Inputs'!W33*W8 -> 148321.85 | X34: =G34 -> 25788.419 | Y34: =K34 -> 30567.259 | Z34: =O34 -> 100968.35 | AA34: =S34 -> 141344.98 | AB34: =W34 -> 148321.85
A35: Current Liabilities | B35: Formula | C35: =SUM(C32:C34) -> 0 | D35: =SUM(D32:D34) -> 138291.03 | E35: =SUM(E32:E34) -> 136324.75 | F35: =SUM(F32:F34) -> 130590.71 | G35: =SUM(G32:G34) -> 129354.5 | H35: =SUM(H32:H34) -> 137678.91 | I35: =SUM(I32:I34) -> 137883.71 | J35: =SUM(J32:J34) -> 137582.31 | ... W35: =SUM(W32:W34) -> 518630.21 | X35: =G35 -> 129354.5 | Y35: =K35 -> 145635.07 | Z35: =O35 -> 371263.38 | AA35: =S35 -> 495700.88 | AB35: =W35 -> 518630.21
A36: Long Term Debt | B36: Formula | C36: =MAX(0,'Model Inputs'!C45-C33) -> 0 | D36: =MAX(0,'Model Inputs'!D48-D33) -> 0 | E36: =MAX(0,'Model Inputs'!E48-E33) -> 0 | F36: =MAX(0,'Model Inputs'!F48-F33) -> 0 | G36: =MAX(0,'Model Inputs'!G48-G33) -> 0 | H36: =MAX(0,'Model Inputs'!H48-H33) -> 0 | I36: =MAX(0,'Model Inputs'!I48-I33) -> 0 | J36: =MAX(0,'Model Inputs'!J48-J33) -> 0 | K36: =MAX(0,'Model Inputs'!K48-K33) -> 0 | ... W36: =MAX(0,'Model Inputs'!W48-W33) -> 0 | X36: =G36 -> 0 | Y36: =K36 -> 0 | Z36: =O36 -> 0 | AA36: =S36 -> 0 | AB36: =W36 -> 0
A37: Capital Lease Obligation | B37: Formula | C37: ='Model Inputs'!C53 -> 0 | D37: ='Model Inputs'!D53 -> 0 | E37: ='Model Inputs'!E53 -> 0 | F37: ='Model Inputs'!F53 -> 0 | G37: ='Model Inputs'!G53 -> 0 | H37: ='Model Inputs'!H53 -> 0 | I37: ='Model Inputs'!I53 -> 0 | J37: ='Model Inputs'!J53 -> 0 | ... W37: ='Model Inputs'!W53 -> 0 | X37: =G37 -> 0 | Y37: =K37 -> 0 | Z37: =O37 -> 0 | AA37: =S37 -> 0 | AB37: =W37 -> 0
A38: Total Liabilities | B38: Formula | C38: =C35+C36+C37 -> 0 | D38: =D35+D36+D37 -> 138291.03 | E38: =E35+E36+E37 -> 136324.75 | F38: =F35+F36+F37 -> 130590.71 | G38: =G35+G36+G37 -> 129354.5 | H38: =H35+H36+H37 -> 137678.91 | I38: =I35+I36+I37 -> 137883.71 | J38: =J35+J36+J37 -> 137582.31 | ... W38: =W35+W36+W37 -> 518630.21 | X38: =G38 -> 129354.5 | Y38: =K38 -> 145635.07 | Z38: =O38 -> 371263.38 | AA38: =S38 -> 495700.88 | AB38: =W38 -> 518630.21
A39: Owner's Capital | B39: Formula | C39: ='Model Inputs'!C35 -> 100000 | D39: ='Model Inputs'!D35 -> 157098 | E39: ='Model Inputs'!E35 -> 162529 | F39: ='Model Inputs'!F35 -> 170541 | G39: ='Model Inputs'!G35 -> 173163 | H39: ='Model Inputs'!H35 -> 173163 | I39: ='Model Inputs'!I35 -> 173163 | J39: ='Model Inputs'!J35 -> 173163 | ... W39: ='Model Inputs'!W35 -> 173163 | X39: =G39 -> 173163 | Y39: =K39 -> 173163 | Z39: =O39 -> 173163 | AA39: =S39 -> 173163 | AB39: =W39 -> 173163
A40: Retained Earnings | B40: Formula | C40: =C31-C38-C39-C41 -> 32000 | D40: =C40+D20-'Model Inputs'!D37 -> 33070.492 | E40: =D40+E20-'Model Inputs'!E37 -> 35013.097 | F40: =E40+F20-'Model Inputs'!F37 -> 38702.55 | G40: =F40+G20-'Model Inputs'!G37 -> 43922.528 | H40: =G40+H20-'Model Inputs'!H37 -> 50822.399 | I40: =H40+I20-'Model Inputs'!I37 -> 58491.051 | J40: =I40+J20-'Model Inputs'!J37 -> 68232.855 | K40: =J40+K20-'Model Inputs'!K37 -> 79883.724 | ... W40: =V40+W20-'Model Inputs'!W37 -> 214916.36 | X40: =G40 -> 43922.528 | Y40: =K40 -> 79883.724 | Z40: =O40 -> 105938.29 | AA40: =S40 -> 174434.64 | AB40: =W40 -> 214916.36
A41: Other Equity | B41: Formula | C41: ='Model Inputs'!C36 -> 0 | D41: ='Model Inputs'!D36 -> 0 | E41: ='Model Inputs'!E36 -> 0 | F41: ='Model Inputs'!F36 -> 0 | G41: ='Model Inputs'!G36 -> 0 | H41: ='Model Inputs'!H36 -> 0 | I41: ='Model Inputs'!I36 -> 0 | J41: ='Model Inputs'!J36 -> 0 | ... W41: ='Model Inputs'!W36 -> 0 | X41: =G41 -> 0 | Y41: =K41 -> 0 | Z41: =O41 -> 0 | AA41: =S41 -> 0 | AB41: =W41 -> 0
A42: Total Equity | B42: Formula | C42: =C39+C40+C41 -> 132000 | D42: =D39+D40+D41 -> 190168.49 | E42: =E39+E40+E41 -> 197542.1 | F42: =F39+F40+F41 -> 209243.55 | G42: =G39+G40+G41 -> 217085.53 | H42: =H39+H40+H41 -> 223985.4 | I42: =I39+I40+I41 -> 231654.05 | J42: =J39+J40+J41 -> 241395.85 | ... W42: =W39+W40+W41 -> 388079.36 | X42: =G42 -> 217085.53 | Y42: =K42 -> 253046.72 | Z42: =O42 -> 279101.29 | AA42: =S42 -> 347597.64 | AB42: =W42 -> 388079.36
A43: Total Liabilities & Equity | B43: Formula | C43: =C38+C42 -> 132000 | D43: =D38+D42 -> 328459.52 | E43: =E38+E42 -> 333866.84 | F43: =F38+F42 -> 339834.26 | G43: =G38+G42 -> 346440.03 | H43: =H38+H42 -> 361664.31 | I43: =I38+I42 -> 369537.76 | J43: =J38+J42 -> 378978.16 | ... W43: =W38+W42 -> 906709.57 | X43: =G43 -> 346440.03 | Y43: =K43 -> 398681.79 | Z43: =O43 -> 650364.67 | AA43: =S43 -> 843298.52 | AB43: =W43 -> 906709.57
A45: Cash Flow
A46: Beginning Cash | B46: Formula | C46: ='Model Inputs'!C40 -> 80000 | D46: =C61 -> 80000 | E46: =D61 -> 136761.7 | F46: =E61 -> 137383.46 | G46: =F61 -> 138622.68 | H46: =G61 -> 139710.26 | I46: =H61 -> 144857.78 | J46: =I61 -> 148608.43 | K46: =J61 -> 152000.32 | ... W46: =V61 -> 394856.73 | X46: =SUM(D46:G46) -> 492767.84 | Y46: =SUM(H46:K46) -> 585176.8 | Z46: =SUM(L46:O46) -> 822474.14 | AA46: =SUM(P46:S46) -> 1354934.4 | AB46: =SUM(T46:W46) -> 1551116.1
A47: Net Income | B47: Formula | C47: =0 -> 0 | D47: =D20 -> 1070.4915 | E47: =E20 -> 1942.6058 | F47: =F20 -> 3689.453 | G47: =G20 -> 5219.9779 | H47: =H20 -> 6899.8703 | I47: =I20 -> 7668.6526 | J47: =J20 -> 9741.8036 | K47: =K20 -> 11650.869 | ... W47: =W20 -> 33360.939 | X47: =SUM(D47:G47) -> 11922.528 | Y47: =SUM(H47:K47) -> 35961.196 | Z47: =SUM(L47:O47) -> 74304.567 | AA47: =SUM(P47:S47) -> 120704.35 | AB47: =SUM(T47:W47) -> 131574.72
A48: Depreciation | B48: Formula | C48: =0 -> 0 | D48: =D18 -> 10 | E48: =E18 -> 20.05481 | F48: =F18 -> 30.157059 | G48: =G18 -> 40.258794 | H48: =H18 -> 50.433553 | I48: =I18 -> 60.674336 | J48: =J18 -> 70.933036 | K48: =K18 -> 81.20213 | ... W48: =W18 -> 206.34396 | X48: =SUM(D48:G48) -> 100.47066 | Y48: =SUM(H48:K48) -> 263.24305 | Z48: =SUM(L48:O48) -> 428.23144 | AA48: =SUM(P48:S48) -> 594.78996 | AB48: =SUM(T48:W48) -> 762.37971
A49: Changes in Current Assets | B49: Formula | C49: =0 -> 0 | D49: =-((D24+D25+D26)-(C24+C25+C26)) -> -139507.82 | E49: =-((E24+E25+E26)-(D24+D25+D26)) -> -4604.6631 | F49: =-((F24+F25+F26)-(E24+E25+E26)) -> -4556.5004 | G49: =-((G24+G25+G26)-(F24+F25+F26)) -> -5355.7342 | H49: =-((H24+H25+H26)-(G24+G25+G26)) -> -9923.6607 | I49: =-((I24+I25+I26)-(H24+H25+H26)) -> -3979.1934 | J49: =-((J24+J25+J26)-(I24+I25+I26)) -> -5914.4333 | K49: =-((K24+K25+K26)-(J24+J25+J26)) -> -5996.4468 | ... W49: =-((W24+W25+W26)-(V24+V25+V26)) -> -10119.315 | X49: =SUM(D49:G49) -> -154024.72 | Y49: =SUM(H49:K49) -> -25813.734 | Z49: =SUM(L49:O49) -> -121580.5 | AA49: =SUM(P49:S49) -> -108548.31 | AB49: =SUM(T49:W49) -> -44606.554
A50: Changes in Current Liabilities | B50: Formula | C50: =0 -> 0 | D50: =(D32+D34)-(C32+C34) -> 138291.03 | E50: =(E32+E34)-(D32+D34) -> -1966.284 | F50: =(F32+F34)-(E32+E34) -> -5734.0315 | G50: =(G32+G34)-(F32+F34) -> -1236.2117 | H50: =(H32+H34)-(G32+G34) -> 8324.405 | I50: =(I32+I34)-(H32+H34) -> 204.80611 | J50: =(J32+J34)-(I32+I34) -> -301.40685 | K50: =(K32+K34)-(J32+J34) -> 8052.761 | ... W50: =(W32+W34)-(V32+V34) -> -379.55097 | X50: =SUM(D50:G50) -> 129354.5 | Y50: =SUM(H50:K50) -> 16280.565 | Z50: =SUM(L50:O50) -> 225628.31 | AA50: =SUM(P50:S50) -> 124437.5 | AB50: =SUM(T50:W50) -> 22929.334
A51: Operating Cash Flow | B51: Formula | C51: =0 -> 0 | D51: =SUM(D47:D50) -> -136.30389 | E51: =SUM(E47:E50) -> -4608.2865 | F51: =SUM(F47:F50) -> -6570.9218 | G51: =SUM(G47:G50) -> -1331.7093 | H51: =SUM(H47:H50) -> 5351.0482 | I51: =SUM(I47:I50) -> 3954.9396 | J51: =SUM(J47:J50) -> 3596.8965 | K51: =SUM(K47:K50) -> 13788.386 | ... W51: =SUM(W47:W50) -> 23068.416 | X51: =SUM(D51:G51) -> -12647.221 | Y51: =SUM(H51:K51) -> 26691.27 | Z51: =SUM(L51:O51) -> 178780.61 | AA51: =SUM(P51:S51) -> 137188.33 | AB51: =SUM(T51:W51) -> 110659.88
A52: Capital Expenditures | B52: Formula | C52: ='Model Inputs'!C56 -> 0 | D52: ='Model Inputs'!D56 -> 200 | E52: ='Model Inputs'!E56 -> 200.95 | F52: ='Model Inputs'!F56 -> 201.85448 | G52: ='Model Inputs'!G56 -> 202.71296 | H52: ='Model Inputs'!H56 -> 203.52523 | I52: ='Model Inputs'!I56 -> 204.29069 | J52: ='Model Inputs'!J56 -> 205.00877 | ... W52: ='Model Inputs'!W56 -> 209.86977 | X52: =SUM(D52:G52) -> 805.51744 | Y52: =SUM(H52:K52) -> 818.50385 | Z52: =SUM(L52:O52) -> 828.45382 | AA52: =SUM(P52:S52) -> 835.26719 | AB52: =SUM(T52:W52) -> 838.85302
A53: Investing Cash Flow | B53: Formula | C53: =0 -> 0 | D53: =-D52 -> -200 | E53: =-E52 -> -200.95 | F53: =-F52 -> -201.85448 | G53: =-G52 -> -202.71296 | H53: =-H52 -> -203.52523 | I53: =-I52 -> -204.29069 | J53: =-J52 -> -205.00877 | K53: =-K52 -> -205.67915 | ... W53: =-W52 -> -209.86977 | X53: =SUM(D53:G53) -> -805.51744 | Y53: =SUM(H53:K53) -> -818.50385 | Z53: =SUM(L53:O53) -> -828.45382 | AA53: =SUM(P53:S53) -> -835.26719 | AB53: =SUM(T53:W53) -> -838.85302
A54: Debt Issuance (New Borrowing) | B54: Formula | C54: ='Model Inputs'!C46 -> 0 | D54: ='Model Inputs'!D46 -> 0 | E54: ='Model Inputs'!E46 -> 0 | F54: ='Model Inputs'!F46 -> 0 | G54: ='Model Inputs'!G46 -> 0 | H54: ='Model Inputs'!H46 -> 0 | I54: ='Model Inputs'!I46 -> 0 | J54: ='Model Inputs'!J46 -> 0 | ... W54: ='Model Inputs'!W46 -> 0 | X54: =SUM(D54:G54) -> 0 | Y54: =SUM(H54:K54) -> 0 | Z54: =SUM(L54:O54) -> 0 | AA54: =SUM(P54:S54) -> 0 | AB54: =SUM(T54:W54) -> 0
A55: Debt Repayment | B55: Formula | C55: ='Model Inputs'!C47 -> 0 | D55: ='Model Inputs'!D47 -> 0 | E55: ='Model Inputs'!E47 -> 0 | F55: ='Model Inputs'!F47 -> 0 | G55: ='Model Inputs'!G47 -> 0 | H55: ='Model Inputs'!H47 -> 0 | I55: ='Model Inputs'!I47 -> 0 | J55: ='Model Inputs'!J47 -> 0 | ... W55: ='Model Inputs'!W47 -> 0 | X55: =SUM(D55:G55) -> 0 | Y55: =SUM(H55:K55) -> 0 | Z55: =SUM(L55:O55) -> 0 | AA55: =SUM(P55:S55) -> 0 | AB55: =SUM(T55:W55) -> 0
A56: Equity | B56: Formula | C56: =0 -> 0 | D56: =(D39-C39)+(D41-C41) -> 57098 | E56: =(E39-D39)+(E41-D41) -> 5431 | F56: =(F39-E39)+(F41-E41) -> 8012 | G56: =(G39-F39)+(G41-F41) -> 2622 | H56: =(H39-G39)+(H41-G41) -> 0 | I56: =(I39-H39)+(I41-H41) -> 0 | J56: =(J39-I39)+(J41-I41) -> 0 | K56: =(K39-J39)+(K41-J41) -> 0 | ... W56: =(W39-V39)+(W41-V41) -> 0 | X56: =SUM(D56:G56) -> 73163 | Y56: =SUM(H56:K56) -> 0 | Z56: =SUM(L56:O56) -> 0 | AA56: =SUM(P56:S56) -> 0 | AB56: =SUM(T56:W56) -> 0
A57: Distributions | B57: Formula | C57: ='Model Inputs'!C37 -> 0 | D57: ='Model Inputs'!D37 -> 0 | E57: ='Model Inputs'!E37 -> 0 | F57: ='Model Inputs'!F37 -> 0 | G57: ='Model Inputs'!G37 -> 0 | H57: ='Model Inputs'!H37 -> 0 | I57: ='Model Inputs'!I37 -> 0 | J57: ='Model Inputs'!J37 -> 0 | ... W57: ='Model Inputs'!W37 -> 19557 | X57: =SUM(D57:G57) -> 0 | Y57: =SUM(H57:K57) -> 0 | Z57: =SUM(L57:O57) -> 48250 | AA57: =SUM(P57:S57) -> 52208 | AB57: =SUM(T57:W57) -> 91093
A58: Capital Lease Principal Payments | B58: Formula | C58: ='Model Inputs'!C50 -> 0 | D58: ='Model Inputs'!D50 -> 0 | E58: ='Model Inputs'!E50 -> 0 | F58: ='Model Inputs'!F50 -> 0 | G58: ='Model Inputs'!G50 -> 0 | H58: ='Model Inputs'!H50 -> 0 | I58: ='Model Inputs'!I50 -> 0 | J58: ='Model Inputs'!J50 -> 0 | ... W58: ='Model Inputs'!W50 -> 0 | X58: =SUM(D58:G58) -> 0 | Y58: =SUM(H58:K58) -> 0 | Z58: =SUM(L58:O58) -> 0 | AA58: =SUM(P58:S58) -> 0 | AB58: =SUM(T58:W58) -> 0
A59: Financing Cash Flow | B59: Formula | C59: =0 -> 0 | D59: =D54-D55+D56-D57-D58 -> 57098 | E59: =E54-E55+E56-E57-E58 -> 5431 | F59: =F54-F55+F56-F57-F58 -> 8012 | G59: =G54-G55+G56-G57-G58 -> 2622 | H59: =H54-H55+H56-H57-H58 -> 0 | I59: =I54-I55+I56-I57-I58 -> 0 | J59: =J54-J55+J56-J57-J58 -> 0 | K59: =K54-K55+K56-K57-K58 -> 0 | ... W59: =W54-W55+W56-W57-W58 -> -19557 | X59: =SUM(D59:G59) -> 73163 | Y59: =SUM(H59:K59) -> 0 | Z59: =SUM(L59:O59) -> -48250 | AA59: =SUM(P59:S59) -> -52208 | AB59: =SUM(T59:W59) -> -91093
A60: Net Cash Flow | B60: Formula | C60: =0 -> 0 | D60: =D51+D53+D59 -> 56761.696 | E60: =E51+E53+E59 -> 621.76348 | F60: =F51+F53+F59 -> 1239.2237 | G60: =G51+G53+G59 -> 1087.5778 | H60: =H51+H53+H59 -> 5147.523 | I60: =I51+I53+I59 -> 3750.649 | J60: =J51+J53+J59 -> 3391.8877 | K60: =K51+K53+K59 -> 13582.706 | ... W60: =W51+W53+W59 -> 3301.5464 | X60: =SUM(D60:G60) -> 59710.261 | Y60: =SUM(H60:K60) -> 25872.766 | Z60: =SUM(L60:O60) -> 129702.16 | AA60: =SUM(P60:S60) -> 84145.06 | AB60: =SUM(T60:W60) -> 18728.026
A61: Ending Cash | B61: Formula | C61: =C46+C60 -> 80000 | D61: =D46+D60 -> 136761.7 | E61: =E46+E60 -> 137383.46 | F61: =F46+F60 -> 138622.68 | G61: =G46+G60 -> 139710.26 | H61: =H46+H60 -> 144857.78 | I61: =I46+I60 -> 148608.43 | J61: =J46+J60 -> 152000.32 | ... W61: =W46+W60 -> 398158.27 | X61: =SUM(D61:G61) -> 552478.1 | Y61: =SUM(H61:K61) -> 611049.57 | Z61: =SUM(L61:O61) -> 952176.3 | AA61: =SUM(P61:S61) -> 1439079.5 | AB61: =SUM(T61:W61) -> 1569844.1

Sheet Audit Source
A1: Audit Source
A2: Persisted system outputs used only for checks and audit tie-outs.
C4: Stub | D4: Q1 | E4: Q2 | F4: Q3 | G4: Q4 | H4: Q5 | I4: Q6 | J4: Q7 | K4: Q8 | L4: Q9 | M4: Q10 | N4: Q11 | O4: Q12 | P4: Q13 | Q4: Q14 | R4: Q15 | S4: Q16 | T4: Q17 | U4: Q18 | V4: Q19 | W4: Q20 | X4: Y1 | Y4: Y2 | Z4: Y3 | AA4: Y4 | AB4: Y5
C5: 46162 | D5: 46295 | E5: 46387 | F5: 46477 | G5: 46568 | H5: 46660 | I5: 46752 | J5: 46843 | K5: 46934 | L5: 47026 | M5: 47118 | N5: 47208 | O5: 47299 | P5: 47391 | Q5: 47483 | R5: 47573 | S5: 47664 | T5: 47756 | U5: 47848 | V5: 47938 | W5: 48029 | X5: Annual | Y5: Annual | Z5: Annual | AA5: Annual | AB5: Annual
A6: Income Statement
A7: Revenue | B7: Persisted FINMO | C7: 1528800 | D7: 274877.56 | E7: 277227.25 | F7: 281912.38 | G7: 286019.97 | H7: 297884.01 | I7: 299958.22 | J7: 305514.83 | K7: 310633.4 | L7: 322368.64 | M7: 327892.99 | N7: 399522.51 | O7: 478359.78 | P7: 535397.39 | Q7: 571797.06 | R7: 594487.69 | S7: 609311.25 | T7: 619767.64 | U7: 627708.67 | V7: 634084.35 | W7: 639387.23
A8: Cost of Goods Sold | B8: Persisted FINMO | C8: 244608 | D8: 59385.235 | E8: 59892.868 | F8: 60905.055 | G8: 61792.47 | H8: 64355.605 | I8: 64803.723 | J8: 66004.189 | K8: 67110.017 | L8: 69645.327 | M8: 70838.821 | N8: 100662.32 | O8: 134864.25 | P8: 157631.37 | Q8: 173422.61 | R8: 183266.48 | S8: 189697.37 | T8: 192198.68 | U8: 195643.73 | V8: 198409.69 | W8: 200710.23
A9: Gross Profit | B9: Persisted FINMO | C9: 1284192 | D9: 215492.33 | E9: 217334.38 | F9: 221007.32 | G9: 224227.5 | H9: 233528.4 | I9: 235154.49 | J9: 239510.65 | K9: 243523.39 | L9: 252723.31 | M9: 257054.17 | N9: 298860.18 | O9: 343495.53 | P9: 377766.02 | Q9: 398374.44 | R9: 411221.21 | S9: 419613.88 | T9: 427568.96 | U9: 432064.94 | V9: 435674.66 | W9: 438677
A10: Marketing | B10: Persisted FINMO | C10: 183456 | D10: 42993.943 | E10: 43361.461 | F10: 44094.267 | G10: 44736.742 | H10: 46592.41 | I10: 46916.84 | J10: 47785.957 | K10: 48586.559 | L10: 50422.082 | M10: 51286.152 | N10: 68662.937 | O10: 88380.872 | P10: 101795.75 | Q10: 110899.64 | R10: 116574.78 | S10: 120282.29 | T10: 122022.02 | U10: 124008.15 | V10: 125602.77 | W10: 126929.07
A11: Research & Development | B11: Persisted FINMO | C11: 0 | D11: 0 | E11: 0 | F11: 0 | G11: 0 | H11: 0 | I11: 0 | J11: 0 | K11: 0 | L11: 0 | M11: 0 | N11: 0 | O11: 0 | P11: 0 | Q11: 0 | R11: 0 | S11: 0 | T11: 0 | U11: 0 | V11: 0 | W11: 0
A12: Lease/Rent | B12: Persisted FINMO | C12: 12600 | D12: 12600 | E12: 12600 | F12: 12600 | G12: 12600 | H12: 12600 | I12: 12600 | J12: 12600 | K12: 12600 | L12: 12600 | M12: 12600 | N12: 12600 | O12: 12600 | P12: 12600 | Q12: 12600 | R12: 12600 | S12: 12600 | T12: 12600 | U12: 12600 | V12: 12600 | W12: 12600
A13: Payroll | B13: Persisted FINMO | C13: 134521.88 | D13: 115549 | E13: 115549 | F13: 115549 | G13: 115549 | H13: 119016 | I13: 119016 | J13: 119016 | K13: 119016 | L13: 122585 | M13: 122585 | N13: 122585 | O13: 122585 | P13: 126264 | Q13: 126264 | R13: 126264 | S13: 126264 | T13: 130050 | U13: 130050 | V13: 130050 | W13: 130050
A14: General & Administrative | B14: Persisted FINMO | C14: 700.1904 | D14: 42993.943 | E14: 43361.461 | F14: 44094.267 | G14: 44736.742 | H14: 46592.41 | I14: 46916.84 | J14: 47785.957 | K14: 48586.559 | L14: 50422.082 | M14: 51286.152 | N14: 68662.937 | O14: 88380.872 | P14: 101795.75 | Q14: 110899.64 | R14: 116574.78 | S14: 120282.29 | T14: 122022.02 | U14: 124008.15 | V14: 125602.77 | W14: 126929.07
A15: EBITDA | B15: Persisted FINMO | C15: 952913.93 | D15: 1355.4396 | E15: 2462.4604 | F15: 4669.7883 | G15: 6605.0205 | H15: 8727.5812 | I15: 9704.8146 | J15: 12322.732 | K15: 14734.269 | L15: 16694.149 | M15: 19296.863 | N15: 26349.308 | O15: 31548.784 | P15: 35310.529 | Q15: 37711.16 | R15: 39207.652 | S15: 40185.296 | T15: 40874.915 | U15: 41398.642 | V15: 41819.131 | W15: 42168.867
A16: Interest | B16: Persisted FINMO | C16: 0 | D16: 0 | E16: 0 | F16: 0 | G16: 0 | H16: 0 | I16: 0 | J16: 0 | K16: 0 | L16: 0 | M16: 0 | N16: 0 | O16: 0 | P16: 0 | Q16: 0 | R16: 0 | S16: 0 | T16: 0 | U16: 0 | V16: 0 | W16: 0
A17: Depreciation | B17: Persisted FINMO | C17: 0 | D17: 10 | E17: 20.05481 | F17: 30.157059 | G17: 40.258794 | H17: 50.433553 | I17: 60.674336 | J17: 70.933036 | K17: 81.20213 | L17: 91.515362 | M17: 101.86548 | N17: 112.24516 | O17: 122.60544 | P17: 133.02207 | Q17: 143.48772 | R17: 153.91129 | S17: 164.36889 | T17: 174.8529 | U17: 185.35561 | V17: 195.82724 | W17: 206.34396
A18: Taxes | B18: Persisted FINMO | C18: 195324.49 | D18: 275.78282 | E18: 500.63452 | F18: 951.01306 | G18: 1345.6186 | H18: 1778.607 | I18: 1976.8173 | J18: 2511.3247 | K18: 3003.527 | L18: 3403.1414 | M18: 3934.5138 | N18: 5377.9682 | O18: 6441.6124 | P18: 7210.5446 | Q18: 7700.4711 | R18: 8005.0796 | S18: 8203.3295 | T18: 8342.536 | U18: 8447.7346 | V18: 8531.7783 | W18: 8601.3101
A19: Net Income | B19: Persisted FINMO | C19: 757589.45 | D19: 1069.6568 | E19: 1941.771 | F19: 3688.6182 | G19: 5219.1431 | H19: 6898.5406 | I19: 7667.3229 | J19: 9740.4739 | K19: 11649.54 | L19: 13199.492 | M19: 15260.484 | N19: 20859.095 | O19: 24984.566 | P19: 27966.962 | Q19: 29867.201 | R19: 31048.661 | S19: 31817.597 | T19: 32357.526 | U19: 32765.552 | V19: 33091.526 | W19: 33361.213
A22: Balance Sheet
A23: Cash | B23: Persisted FINMO | C23: 80000 | D23: 136761.34 | E23: 137382.31 | F23: 138620.69 | G23: 139707.42 | H23: 144853.93 | I23: 148603.25 | J23: 151993.8 | K23: 165575.21 | L23: 202351.57 | M23: 205730.32 | N23: 248782.45 | O23: 295275.85 | P23: 333373.68 | Q23: 356058.25 | R23: 370186.03 | S23: 379417.89 | T23: 385928.43 | U23: 390873.81 | V23: 394843.71 | W23: 398145.53
A24: Accounts Receivable | B24: Persisted FINMO | C24: 12000 | D24: 89633.987 | E24: 123300.36 | F24: 128170.44 | G24: 128608.96 | H24: 132487.72 | I24: 133410.25 | J24: 137374.83 | K24: 139676.4 | L24: 143377.57 | M24: 145834.59 | N24: 181641.46 | O24: 215094.61 | P24: 238124.83 | Q24: 254314.04 | R24: 270281.68 | S24: 273976.97 | T24: 275649.57 | U24: 279181.45 | V24: 288284.16 | W24: 287500.65
A25: Inventory | B25: Persisted FINMO | C25: 0 | D25: 56376.286 | E25: 24975.191 | F25: 24529.162 | G25: 29330.264 | H25: 35039.784 | I25: 38037.81 | J25: 39830.582 | K25: 43255.27 | L25: 49206.94 | M25: 52723.131 | N25: 64714.323 | O25: 84801.596 | P25: 102962.19 | Q25: 115288.56 | R25: 118578.78 | S25: 130403.13 | T25: 140784.16 | U25: 147788.91 | V25: 148440.17 | W25: 158065.46
A26: Current Assets | B26: Persisted FINMO | C26: 92000 | D26: 288269.16 | E26: 293494.8 | F26: 299289.67 | G26: 305732.14 | H26: 320802.31 | I26: 328530.82 | J26: 337835.81 | K26: 357413.67 | L26: 404614.88 | M26: 414478.96 | N26: 506432.34 | O26: 608694.81 | P26: 689595.85 | Q26: 741824.98 | R26: 775852.06 | S26: 801385.15 | T26: 821236.56 | U26: 837557.36 | V26: 851298.21 | W26: 864719.35
A27: PPE | B27: Persisted FINMO | C27: 40000 | D27: 40190 | E27: 40370.895 | F27: 40542.593 | G27: 40705.047 | H27: 40858.138 | I27: 41001.755 | J27: 41135.831 | K27: 41260.308 | L27: 41375.094 | M27: 41480.104 | N27: 41575.259 | O27: 41660.53 | P27: 41735.811 | Q27: 41801.002 | R27: 41856.096 | S27: 41901.007 | T27: 41935.659 | U27: 41959.982 | V27: 41973.955 | W27: 41977.48
A28: Accumulated Depreciation | B28: Persisted FINMO | C28: 0 | D28: -10 | E28: -30.05481 | F28: -60.211869 | G28: -100.47066 | H28: -150.90422 | I28: -211.57855 | J28: -282.51159 | K28: -363.71372 | L28: -455.22908 | M28: -557.09456 | N28: -669.33972 | O28: -791.94516 | P28: -924.96723 | Q28: -1068.4549 | R28: -1222.3662 | S28: -1386.7351 | T28: -1561.588 | U28: -1746.9436 | V28: -1942.7709 | W28: -2149.1148
A29: Total Assets | B29: Persisted FINMO | C29: 132000 | D29: 328459.16 | E29: 333865.69 | F29: 339832.27 | G29: 346437.19 | H29: 361660.45 | I29: 369532.58 | J29: 378971.64 | K29: 398673.97 | L29: 445989.97 | M29: 455959.06 | N29: 548007.6 | O29: 650355.34 | P29: 731331.66 | Q29: 783625.98 | R29: 817708.16 | S29: 843286.15 | T29: 863172.22 | U29: 879517.34 | V29: 893272.16 | W29: 906696.83
A30: Accounts Payable | B30: Persisted FINMO | C30: 0 | D30: 97059.871 | E30: 106371.42 | F30: 104616.94 | G30: 103566.58 | H30: 109379.85 | I30: 109482.08 | J30: 109503.24 | K30: 115068.65 | L30: 138856.4 | M30: 154462.79 | N30: 218618.44 | O30: 270295.28 | P30: 305426.02 | Q30: 333170.49 | R30: 351292.35 | S30: 354357.05 | T30: 357216.97 | U30: 360886.42 | V30: 371917.72 | W30: 370308.03
A31: Prepaid Expenses (% of Revenue) | B31: Persisted FINMO | C31: 0 | D31: 5497.5512 | E31: 7836.9371 | F31: 7969.381 | G31: 8085.4986 | H31: 8420.883 | I31: 8479.5188 | J31: 8636.5989 | K31: 8906.7916 | L31: 9678.796 | M31: 10190.914 | N31: 11294.102 | O31: 13522.753 | P31: 15135.149 | Q31: 16164.131 | R31: 16805.573 | S31: 17587.16 | T31: 18874.404 | U31: 19713.191 | V31: 19730.169 | W31: 21007.707
A32: Short Term Debt | B32: Persisted FINMO | C32: 0 | D32: 0 | E32: 0 | F32: 0 | G32: 0 | H32: 0 | I32: 0 | J32: 0 | K32: 0 | L32: 0 | M32: 0 | N32: 0 | O32: 0 | P32: 0 | Q32: 0 | R32: 0 | S32: 0 | T32: 0 | U32: 0 | V32: 0 | W32: 0
A33: Deferred Revenue (% of Revenue) | B33: Persisted FINMO | C33: 0 | D33: 41231.634 | E33: 29953.85 | F33: 25974.279 | G33: 25788.419 | H33: 28299.874 | I33: 28402.444 | J33: 28079.868 | K33: 30567.259 | L33: 40896.008 | M33: 47901.231 | N33: 75282.026 | O33: 100968.35 | P33: 118846.98 | Q33: 132642.62 | R33: 137906.28 | S33: 141344.98 | T33: 143770.6 | U33: 145612.72 | V33: 147091.72 | W33: 148321.85
A34: Current Liabilites | B34: Persisted FINMO | C34: 0 | D34: 138291.51 | E34: 136325.27 | F34: 130591.22 | G34: 129355 | H34: 137679.72 | I34: 137884.53 | J34: 137583.11 | K34: 145635.91 | L34: 179752.41 | M34: 202364.02 | N34: 293900.46 | O34: 371263.63 | P34: 424273 | Q34: 465813.12 | R34: 489198.63 | S34: 495702.03 | T34: 500987.57 | U34: 506499.14 | V34: 519009.44 | W34: 518629.89
... A41: Total Liabilities & Equity | B41: Persisted FINMO | C41: 132000 | D41: 328459.16 | E41: 333865.69 | F41: 339832.27 | G41: 346437.19 | H41: 361660.45 | I41: 369532.58 | J41: 378971.64 | K41: 398673.97 | L41: 445989.97 | M41: 455959.06 | N41: 548007.6 | O41: 650355.34 | P41: 731331.66 | Q41: 783625.98 | R41: 817708.16 | S41: 843286.15 | T41: 863172.22 | U41: 879517.34 | V41: 893272.16 | W41: 906696.83
A44: Cash Flow
A45: Beginning Cash | B45: Persisted FINMO | C45: 80000 | D45: 80000 | E45: 136761.34 | F45: 137382.31 | G45: 138620.69 | H45: 139707.42 | I45: 144853.93 | J45: 148603.25 | K45: 151993.8 | L45: 165575.21 | M45: 202351.57 | N45: 205730.32 | O45: 248782.45 | P45: 295275.85 | Q45: 333373.68 | R45: 356058.25 | S45: 370186.03 | T45: 379417.89 | U45: 385928.43 | V45: 390873.81 | W45: 394843.71
A46: Net Income | B46: Persisted FINMO | C46: 757589.45 | D46: 1069.6568 | E46: 1941.771 | F46: 3688.6182 | G46: 5219.1431 | H46: 6898.5406 | I46: 7667.3229 | J46: 9740.4739 | K46: 11649.54 | L46: 13199.492 | M46: 15260.484 | N46: 20859.095 | O46: 24984.566 | P46: 27966.962 | Q46: 29867.201 | R46: 31048.661 | S46: 31817.597 | T46: 32357.526 | U46: 32765.552 | V46: 33091.526 | W46: 33361.213
A47: Depreciatoin | B47: Persisted FINMO | C47: 0 | D47: 10 | E47: 20.05481 | F47: 30.157059 | G47: 40.258794 | H47: 50.433553 | I47: 60.674336 | J47: 70.933036 | K47: 81.20213 | L47: 91.515362 | M47: 101.86548 | N47: 112.24516 | O47: 122.60544 | P47: 133.02207 | Q47: 143.48772 | R47: 153.91129 | S47: 164.36889 | T47: 174.8529 | U47: 185.35561 | V47: 195.82724 | W47: 206.34396
A48: Changes in Current Assets | B48: Persisted FINMO | C48: 0 | D48: -139507.82 | E48: -4604.6631 | F48: -4556.5004 | G48: -5355.7342 | H48: -9923.6607 | I48: -3979.1934 | J48: -5914.4333 | K48: -5996.4468 | L48: -10424.849 | M48: -6485.3341 | N48: -48901.249 | O48: -55769.065 | P48: -42803.216 | Q48: -29544.567 | R48: -19899.298 | S48: -16301.226 | T48: -13340.876 | U48: -11375.412 | V48: -9770.9507 | W48: -10119.315
A49: Changes in Current Liabilites | B49: Persisted FINMO | C49: 0 | D49: 138291.51 | E49: -1966.2401 | F49: -5734.0435 | G49: -1236.2197 | H49: 8324.7191 | I49: 204.80453 | J49: -301.4129 | K49: 8052.796 | L49: 34116.503 | M49: 22611.607 | N49: 91536.443 | O49: 77363.173 | P49: 53009.363 | Q49: 41540.121 | R49: 23385.514 | S49: 6503.3982 | T49: 5285.5409 | U49: 5511.5711 | V49: 12510.294 | W49: -379.54739
A50: Operating Cash Flow | B50: Persisted FINMO | C50: 0 | D50: -136.66274 | E50: -4609.0774 | F50: -6571.7686 | G50: -1332.5521 | H50: 5350.0326 | I50: 3953.6084 | J50: 3595.5607 | K50: 13787.091 | L50: 36982.661 | M50: 31488.623 | N50: 63606.534 | O50: 46701.279 | P50: 38306.131 | Q50: 42006.242 | R50: 34688.789 | S50: 22184.138 | T50: 24477.044 | U50: 27087.066 | V50: 36026.696 | W50: 23068.694
A51: Capital Expenditures | B51: Persisted FINMO | C51: 0 | D51: 200 | E51: 200.95 | F51: 201.85448 | G51: 202.71296 | H51: 203.52523 | I51: 204.29069 | J51: 205.00877 | K51: 205.67915 | L51: 206.30154 | M51: 206.87547 | N51: 207.40052 | O51: 207.87629 | P51: 208.30265 | Q51: 208.67905 | R51: 209.00501 | S51: 209.28048 | T51: 209.50504 | U51: 209.6783 | V51: 209.79991 | W51: 209.86977
A52: Investing Cash Flow | B52: Persisted FINMO | C52: 0 | D52: -200 | E52: -200.95 | F52: -201.85448 | G52: -202.71296 | H52: -203.52523 | I52: -204.29069 | J52: -205.00877 | K52: -205.67915 | L52: -206.30154 | M52: -206.87547 | N52: -207.40052 | O52: -207.87629 | P52: -208.30265 | Q52: -208.67905 | R52: -209.00501 | S52: -209.28048 | T52: -209.50504 | U52: -209.6783 | V52: -209.79991 | W52: -209.86977
A53: Debt Issuance (New Borrowing) | B53: Persisted FINMO | C53: 0 | D53: 0 | E53: 0 | F53: 0 | G53: 0 | H53: 0 | I53: 0 | J53: 0 | K53: 0 | L53: 0 | M53: 0 | N53: 0 | O53: 0 | P53: 0 | Q53: 0 | R53: 0 | S53: 0 | T53: 0 | U53: 0 | V53: 0 | W53: 0
A54: Debt Repayment | B54: Persisted FINMO | C54: 0 | D54: 0 | E54: 0 | F54: 0 | G54: 0 | H54: 0 | I54: 0 | J54: 0 | K54: 0 | L54: 0 | M54: 0 | N54: 0 | O54: 0 | P54: 0 | Q54: 0 | R54: 0 | S54: 0 | T54: 0 | U54: 0 | V54: 0 | W54: 0
A55: Equity | B55: Persisted FINMO | C55: 0 | D55: 57098 | E55: 5431 | F55: 8012 | G55: 2622 | H55: 0 | I55: 0 | J55: 0 | K55: 0 | L55: 0 | M55: 0 | N55: 0 | O55: 0 | P55: 0 | Q55: 0 | R55: 0 | S55: 0 | T55: 0 | U55: 0 | V55: 0 | W55: 0
A56: Distributions | B56: Persisted FINMO | C56: 0 | D56: 0 | E56: 0 | F56: 0 | G56: 0 | H56: 0 | I56: 0 | J56: 0 | K56: 0 | L56: 0 | M56: 27903 | N56: 20347 | O56: 0 | P56: 0 | Q56: 19113 | R56: 20352 | S56: 12743 | T56: 17757 | U56: 21932 | V56: 31847 | W56: 19557
... A59: Ending Cash | B59: Persisted FINMO | C59: 80000 | D59: 136761.34 | E59: 137382.31 | F59: 138620.69 | G59: 139707.42 | H59: 144853.93 | I59: 148603.25 | J59: 151993.8 | K59: 165575.21 | L59: 202351.57 | M59: 205730.32 | N59: 248782.45 | O59: 295275.85 | P59: 333373.68 | Q59: 356058.25 | R59: 370186.03 | S59: 379417.89 | T59: 385928.43 | U59: 390873.81 | V59: 394843.71 | W59: 398145.53

Sheet Checks
A1: Checks
A2: Model Status | B2: =IF(COUNTIF(I7:I177,"FAIL")=0,"OK","FAIL") -> OK
A3: Rule | B3: Only real formula/coherence failures return FAIL. Baseline scenario changes show CHANGED.
A5: Category | B5: Line Item | C5: Sheet | D5: Range / Cell | E5: Actual | F5: Expected | G5: Difference | H5: Tolerance | I5: Status | J5: Notes
A6: Model Coherence Checks
A7: Statement Coherence | B7: Balance Sheet balances Q1 | C7: Cross-sheet | D7: 'FINMO'!D31 | E7: =FINMO!D31 -> 328459.52 | F7: =FINMO!D43 -> 328459.52 | G7: =E7-F7 -> 0 | H7: 1 | I7: =IF(ABS(G7)<=H7,"OK","FAIL") -> OK | J7: Total assets must equal total liabilities and equity.
A8: Statement Coherence | B8: Cash Flow ties to Balance Sheet Q1 | C8: Cross-sheet | D8: 'FINMO'!D61 | E8: =FINMO!D61 -> 136761.7 | F8: =FINMO!D23 -> 136761.7 | G8: =E8-F8 -> 0 | H8: 1 | I8: =IF(ABS(G8)<=H8,"OK","FAIL") -> OK | J8: Ending cash must tie to balance-sheet cash.
A9: Statement Coherence | B9: Balance Sheet balances Q20 | C9: Cross-sheet | D9: 'FINMO'!W31 | E9: =FINMO!W31 -> 906709.57 | F9: =FINMO!W43 -> 906709.57 | G9: =E9-F9 -> 0 | H9: 1 | I9: =IF(ABS(G9)<=H9,"OK","FAIL") -> OK | J9: Total assets must equal total liabilities and equity.
A10: Statement Coherence | B10: Cash Flow ties to Balance Sheet Q20 | C10: Cross-sheet | D10: 'FINMO'!W61 | E10: =FINMO!W61 -> 398158.27 | F10: =FINMO!W23 -> 398158.27 | G10: =E10-F10 -> 0 | H10: 1 | I10: =IF(ABS(G10)<=H10,"OK","FAIL") -> OK | J10: Ending cash must tie to balance-sheet cash.
A11: Schedule Bridge | B11: Revenue Drivers total feeds Model Inputs Revenue | C11: Cross-sheet | D11: 'Revenue Drivers'!C20:W20 | E11: =SUMPRODUCT(ABS('Revenue Drivers'!C20:W20-'Model Inputs'!C15:W15)) -> 0 | F11: 0 | G11: =E11-F11 -> 0 | H11: 1 | I11: =IF(ABS(G11)<=H11,"OK","FAIL") -> OK | J11: Changing Revenue Drivers should update Model Inputs and FINMO without creating a model failure.
A12: Schedule Bridge | B12: Payroll Schedule total feeds Model Inputs Payroll | C12: Cross-sheet | D12: 'Payroll Schedule'!D17:W17 | E12: =SUMPRODUCT(ABS('Payroll Schedule'!D17:W17-'Model Inputs'!D20:W20)) -> 0 | F12: 0 | G12: =E12-F12 -> 0 | H12: 1 | I12: =IF(ABS(G12)<=H12,"OK","FAIL") -> OK | J12: Changing payroll detail should update payroll summary, Model Inputs, and FINMO payroll.
A13: Schedule Bridge | B13: Debt repayment feeds Model Inputs | C13: Cross-sheet | D13: 'Debt Schedule'!C10:W10 | E13: =SUMPRODUCT(ABS('Debt Schedule'!C10:W10-'Model Inputs'!C47:W47)) -> 0 | F13: 0 | G13: =E13-F13 -> 0 | H13: 1 | I13: =IF(ABS(G13)<=H13,"OK","FAIL") -> OK | J13: Debt repayment must flow through the model from actual mechanically capped repayment.
A14: Schedule Bridge | B14: Capital lease additions feed CapEx schedule | C14: Cross-sheet | D14: 'Debt Schedule'!C21:W21 | E14: =SUMPRODUCT(ABS('Debt Schedule'!C21:W21-'CapEx Depreciation'!C9:W9)) -> 0 | F14: 0 | G14: =E14-F14 -> 0 | H14: 1 | I14: =IF(ABS(G14)<=H14,"OK","FAIL") -> OK | J14: Lease additions must affect PPE/depreciation through the CapEx schedule.
A15: Schedule Bridge | B15: Lease/rent feeds Model Inputs | C15: Cross-sheet | D15: 'Cash Equity Schedule'!C12:W12 | E15: =SUMPRODUCT(ABS('Cash Equity Schedule'!C12:W12-'Model Inputs'!C19:W19)) -> 0 | F15: 0 | G15: =E15-F15 -> 0 | H15: 1 | I15: =IF(ABS(G15)<=H15,"OK","FAIL") -> OK | J15: Operating lease/rent must flow through Model Inputs into FINMO.
A16: Schedule Coherence | B16: Payroll summary totals equal payroll detail by quarter | C16: Payroll Schedule | D16: A27:N86 | E16: =SUM(ABS('Payroll Schedule'!C15-SUMIFS('Payroll Schedule'!$G$27:$G$86,'Payroll Schedule'!$A$27:$A$86,0)),ABS('Payroll Schedule'!C16-SUMIFS('Payroll Schedule'!$H$27:$H$86,'Payroll Schedule'!$A$27:$A$86,0)),ABS('Payroll Schedule'!C17-SUMIFS('Payroll Schedule'!$M$27:$M$86,'Payroll Schedule'!$A$27:$A$86,0)),ABS('Payroll Schedule'!D15-SUMIFS('Payroll Schedule'!$G$27:$G$86,'Payroll Schedule'!$A$27:$A$86,1)),ABS('Payroll Schedule'!D16-SUMIFS('Payroll Schedule'!$H$27:$H$86,'Payroll Schedule'!$A$27:$A$86,1)),ABS('Payroll Schedule'!D17-SUMIFS('Payroll Schedule'!$M$27:$M$86,'Payroll Schedule'!$A$27:$A$86,1)),ABS('Payroll Schedule'!E15-SUMIFS('Payroll Schedule'!$G$27:$G$86,'Payroll Schedule'!$A$27:$A$86,2)),ABS('Payroll Schedule'!E16-SUMIFS('Payroll Schedule'!$H$27:$H$86,'Payroll Schedule'!$A$27:$A$86,2)),ABS('Payroll Schedule'!E17-SUMIFS('Payroll Schedule'!$M$27:$M$86,'Payroll Schedule'!$A$27:$A$86,2)),ABS('Payroll Schedule'!F15-SUMIFS('Payroll Schedule'!$G$27:$G$86,'Payroll Schedule'!$A$27:$A$86,3)),ABS('Payroll Schedule'!F16-SUMIFS('Payroll Schedule'!$H$27:$H$86,'Payroll Schedule'!$A$27:$A$86,3)),ABS('Payroll Schedule'!F17-SUMIFS('Payroll Schedule'!$M$27:$M$86,'Payroll Schedule'!$A$27:$A$86,3)),ABS('Payroll Schedule'!G15-SUMIFS('Payroll Schedule'!$G$27:$G$86,'Payroll Schedule'!$A$27:$A$86,4)),ABS('Payroll Schedule'!G16-SUMIFS('Payroll Schedule'!$H$27:$H$86,'Payroll Schedule'!$A$27:$A$86,4)),ABS('Payroll Schedule'!G17-SUMIFS('Payroll Schedule'!$M$27:$M$86,'Payroll Schedule'!$A$27:$A$86,4)),ABS('Payroll Schedule'!H15-SUMIFS('Payroll Schedule'!$G$27:$G$86,'Payroll Schedule'!$A$27:$A$86,5)),ABS('Payroll Schedule'!H16-SUMIFS('Payroll Schedule'!$H$27:$H$86,'Payroll Schedule'!$A$27:$A$86,5)),ABS('Payroll Schedule'!H17-SUMIFS('Payroll Schedule'!$M$27:$M$86,'Payroll Schedule'!$A$27:$A$86,5)),ABS('Payroll Schedule'!I15-SUMIFS('Payroll Schedule'!$G$27:$G$86,'Payroll Schedule'!$A$27:$A$86,6)),ABS('Payroll Schedule'!I16-SUMIFS('Payroll Schedule'!$H$27:$H$86,'Payroll Schedule'!$A$27:$A$86,6)),ABS('Payroll Schedule'!I17-SUMIFS('Payroll Schedule'!$M$27:$M$86,'Payroll Schedule'!$A$27:$A$86,6)),ABS('Payroll Schedule'!J15-SUMIFS('Payroll Schedule'!$G$27:$G$86,'Payroll Schedule'!$A$27:$A$86,7)),ABS('Payroll Schedule'!J16-SUMIFS('Payroll Schedule'!$H$27:$H$86,'Payroll Schedule'!$A$27:$A$86,7)),ABS('Payroll Schedule'!J17-SUMIFS('Payroll Schedule'!$M$27:$M$86,'Payroll Schedule'!$A$27:$A$86,7)),ABS('Payroll Schedule'!K15-SUMIFS('Payroll Schedule'!$G$27:$G$86,'Payroll Schedule'!$A$27:$A$86,8)),ABS('Payroll Schedule'!K16-SUMIFS('Payroll Schedule'!$H$27:$H$86,'Payroll Schedule'!$A$27:$A$86,8)),ABS('Payroll Schedule'!K17-SUMIFS('Payroll Schedule'!$M$27:$M$86,'Payroll Schedule'!$A$27:$A$86,8)),ABS('Payroll Schedule'!L15-SUMIFS('Payroll Schedule'!$G$27:$G$86,'Payroll Schedule'!$A$27:$A$86,9)),ABS('Payroll Schedule'!L16-SUMIFS('Payroll Schedule'!$H$27:$H$86,'Payroll Schedule'!$A$27:$A$86,9)),ABS('Payroll Schedule'!L17-SUMIFS('Payroll Schedule'!$M$27:$M$86,'Payroll Schedule'!$A$27:$A$86,9)),ABS('Payroll Schedule'!M15-SUMIFS('Payroll Schedule'!$G$27:$G$86,'Payroll Schedule'!$A$27:$A$86,10)),ABS('Payroll Schedule'!M16-SUMIFS('Payroll Schedule'!$H$27:$H$86,'Payroll Schedule'!$A$27:$A$86,10)),ABS('Payroll Schedule'!M17-SUMIFS('Payroll Schedule'!$M$27:$M$86,'Payroll Schedule'!$A$27:$A$86,10)),ABS('Payroll Schedule'!N15-SUMIFS('Payroll Schedule'!$G$27:$G$86,'Payroll Schedule'!$A$27:$A$86,11)),ABS('Payroll Schedule'!N16-SUMIFS('Payroll Schedule'!$H$27:$H$86,'Payroll Schedule'!$A$27:$A$86,11)),ABS('Payroll Schedule'!N17-SUMIFS('Payroll Schedule'!$M$27:$M$86,'Payroll Schedule'!$A$27:$A$86,11)),ABS('Payroll Schedule'!O15-SUMIFS('Payroll Schedule'!$G$27:$G$86,'Payroll Schedule'!$A$27:$A$86,12)),ABS('Payroll Schedule'!O16-SUMIFS('Payroll Schedule'!$H$27:$H$86,'Payroll Schedule'!$A$27:$A$86,12)),ABS('Payroll Schedule'!O17-SUMIFS('Payroll Schedule'!$M$27:$M$86,'Payroll Schedule'!$A$27:$A$86,12)),ABS('Payroll Schedule'!P15-SUMIFS('Payroll Schedule'!$G$27:$G$86,'Payroll Schedule'!$A$27:$A$86,13)),ABS('Payroll Schedule'!P16-SUMIFS('Payroll Schedule'!$H$27:$H$86,'Payroll Schedule'!$A$27:$A$86,13)),ABS('Payroll Schedule'!P17-SUMIFS('Payroll Schedule'!$M$27:$M$86,'Payroll Schedule'!$A$27:$A$86,13)),ABS('Payroll Schedule'!Q15-SUMIFS('Payroll Schedule'!$G$27:$G$86,'Payroll Schedule'!$A$27:$A$86,14)),ABS('Payroll Schedule'!Q16-SUMIFS('Payroll Schedule'!$H$27:$H$86,'Payroll Schedule'!$A$27:$A$86,14)),ABS('Payroll Schedule'!Q17-SUMIFS('Payroll Schedule'!$M$27:$M$86,'Payroll Schedule'!$A$27:$A$86,14)),ABS('Payroll Schedule'!R15-SUMIFS('Payroll Schedule'!$G$27:$G$86,'Payroll Schedule'!$A$27:$A$86,15)),ABS('Payroll Schedule'!R16-SUMIFS('Payroll Schedule'!$H$27:$H$86,'Payroll Schedule'!$A$27:$A$86,15)),ABS('Payroll Schedule'!R17-SUMIFS('Payroll Schedule'!$M$27:$M$86,'Payroll Schedule'!$A$27:$A$86,15)),ABS('Payroll Schedule'!S15-SUMIFS('Payroll Schedule'!$G$27:$G$86,'Payroll Schedule'!$A$27:$A$86,16)),ABS('Payroll Schedule'!S16-SUMIFS('Payroll Schedule'!$H$27:$H$86,'Payroll Schedule'!$A$27:$A$86,16)),ABS('Payroll Schedule'!S17-SUMIFS('Payroll Schedule'!$M$27:$M$86,'Payroll Schedule'!$A$27:$A$86,16)),ABS('Payroll Schedule'!T15-SUMIFS('Payroll Schedule'!$G$27:$G$86,'Payroll Schedule'!$A$27:$A$86,17)),ABS('Payroll Schedule'!T16-SUMIFS('Payroll Schedule'!$H$27:$H$86,'Payroll Schedule'!$A$27:$A$86,17)),ABS('Payroll Schedule'!T17-SUMIFS('Payroll Schedule'!$M$27:$M$86,'Payroll Schedule'!$A$27:$A$86,17)),ABS('Payroll Schedule'!U15-SUMIFS('Payroll Schedule'!$G$27:$G$86,'Payroll Schedule'!$A$27:$A$86,18)),ABS('Payroll Schedule'!U16-SUMIFS('Payroll Schedule'!$H$27:$H$86,'Payroll Schedule'!$A$27:$A$86,18)),ABS('Payroll Schedule'!U17-SUMIFS('Payroll Schedule'!$M$27:$M$86,'Payroll Schedule'!$A$27:$A$86,18)),ABS('Payroll Schedule'!V15-SUMIFS('Payroll Schedule'!$G$27:$G$86,'Payroll Schedule'!$A$27:$A$86,19)),ABS('Payroll Schedule'!V16-SUMIFS('Payroll Schedule'!$H$27:$H$86,'Payroll Schedule'!$A$27:$A$86,19)),ABS('Payroll Schedule'!V17-SUMIFS('Payroll Schedule'!$M$27:$M$86,'Payroll Schedule'!$A$27:$A$86,19)),ABS('Payroll Schedule'!W15-SUMIFS('Payroll Schedule'!$G$27:$G$86,'Payroll Schedule'!$A$27:$A$86,20)),ABS('Payroll Schedule'!W16-SUMIFS('Payroll Schedule'!$H$27:$H$86,'Payroll Schedule'!$A$27:$A$86,20)),ABS('Payroll Schedule'!W17-SUMIFS('Payroll Schedule'!$M$27:$M$86,'Payroll Schedule'!$A$27:$A$86,20))) -> 0 | F16: 0 | G16: =E16-F16 -> 0 | H16: 1 | I16: =IF(ABS(G16)<=H16,"OK","FAIL") -> OK | J16: If this fails, payroll summary is no longer tied to detail FTE/payroll rows.
A17: Schedule Coherence | B17: Payroll productivity metrics | C17: Payroll Schedule | D17: A16:W22 | E17: =SUM(ABS('Payroll Schedule'!C20-IFERROR('Payroll Schedule'!C18/'Payroll Schedule'!C16,0)),ABS('Payroll Schedule'!C21-IFERROR('Payroll Schedule'!C19/'Payroll Schedule'!C16,0)),ABS('Payroll Schedule'!C22-IFERROR('Payroll Schedule'!C17/'Payroll Schedule'!C18,0)),ABS('Payroll Schedule'!D20-IFERROR('Payroll Schedule'!D18/'Payroll Schedule'!D16,0)),ABS('Payroll Schedule'!D21-IFERROR('Payroll Schedule'!D19/'Payroll Schedule'!D16,0)),ABS('Payroll Schedule'!D22-IFERROR('Payroll Schedule'!D17/'Payroll Schedule'!D18,0)),ABS('Payroll Schedule'!E20-IFERROR('Payroll Schedule'!E18/'Payroll Schedule'!E16,0)),ABS('Payroll Schedule'!E21-IFERROR('Payroll Schedule'!E19/'Payroll Schedule'!E16,0)),ABS('Payroll Schedule'!E22-IFERROR('Payroll Schedule'!E17/'Payroll Schedule'!E18,0)),ABS('Payroll Schedule'!F20-IFERROR('Payroll Schedule'!F18/'Payroll Schedule'!F16,0)),ABS('Payroll Schedule'!F21-IFERROR('Payroll Schedule'!F19/'Payroll Schedule'!F16,0)),ABS('Payroll Schedule'!F22-IFERROR('Payroll Schedule'!F17/'Payroll Schedule'!F18,0)),ABS('Payroll Schedule'!G20-IFERROR('Payroll Schedule'!G18/'Payroll Schedule'!G16,0)),ABS('Payroll Schedule'!G21-IFERROR('Payroll Schedule'!G19/'Payroll Schedule'!G16,0)),ABS('Payroll Schedule'!G22-IFERROR('Payroll Schedule'!G17/'Payroll Schedule'!G18,0)),ABS('Payroll Schedule'!H20-IFERROR('Payroll Schedule'!H18/'Payroll Schedule'!H16,0)),ABS('Payroll Schedule'!H21-IFERROR('Payroll Schedule'!H19/'Payroll Schedule'!H16,0)),ABS('Payroll Schedule'!H22-IFERROR('Payroll Schedule'!H17/'Payroll Schedule'!H18,0)),ABS('Payroll Schedule'!I20-IFERROR('Payroll Schedule'!I18/'Payroll Schedule'!I16,0)),ABS('Payroll Schedule'!I21-IFERROR('Payroll Schedule'!I19/'Payroll Schedule'!I16,0)),ABS('Payroll Schedule'!I22-IFERROR('Payroll Schedule'!I17/'Payroll Schedule'!I18,0)),ABS('Payroll Schedule'!J20-IFERROR('Payroll Schedule'!J18/'Payroll Schedule'!J16,0)),ABS('Payroll Schedule'!J21-IFERROR('Payroll Schedule'!J19/'Payroll Schedule'!J16,0)),ABS('Payroll Schedule'!J22-IFERROR('Payroll Schedule'!J17/'Payroll Schedule'!J18,0)),ABS('Payroll Schedule'!K20-IFERROR('Payroll Schedule'!K18/'Payroll Schedule'!K16,0)),ABS('Payroll Schedule'!K21-IFERROR('Payroll Schedule'!K19/'Payroll Schedule'!K16,0)),ABS('Payroll Schedule'!K22-IFERROR('Payroll Schedule'!K17/'Payroll Schedule'!K18,0)),ABS('Payroll Schedule'!L20-IFERROR('Payroll Schedule'!L18/'Payroll Schedule'!L16,0)),ABS('Payroll Schedule'!L21-IFERROR('Payroll Schedule'!L19/'Payroll Schedule'!L16,0)),ABS('Payroll Schedule'!L22-IFERROR('Payroll Schedule'!L17/'Payroll Schedule'!L18,0)),ABS('Payroll Schedule'!M20-IFERROR('Payroll Schedule'!M18/'Payroll Schedule'!M16,0)),ABS('Payroll Schedule'!M21-IFERROR('Payroll Schedule'!M19/'Payroll Schedule'!M16,0)),ABS('Payroll Schedule'!M22-IFERROR('Payroll Schedule'!M17/'Payroll Schedule'!M18,0)),ABS('Payroll Schedule'!N20-IFERROR('Payroll Schedule'!N18/'Payroll Schedule'!N16,0)),ABS('Payroll Schedule'!N21-IFERROR('Payroll Schedule'!N19/'Payroll Schedule'!N16,0)),ABS('Payroll Schedule'!N22-IFERROR('Payroll Schedule'!N17/'Payroll Schedule'!N18,0)),ABS('Payroll Schedule'!O20-IFERROR('Payroll Schedule'!O18/'Payroll Schedule'!O16,0)),ABS('Payroll Schedule'!O21-IFERROR('Payroll Schedule'!O19/'Payroll Schedule'!O16,0)),ABS('Payroll Schedule'!O22-IFERROR('Payroll Schedule'!O17/'Payroll Schedule'!O18,0)),ABS('Payroll Schedule'!P20-IFERROR('Payroll Schedule'!P18/'Payroll Schedule'!P16,0)),ABS('Payroll Schedule'!P21-IFERROR('Payroll Schedule'!P19/'Payroll Schedule'!P16,0)),ABS('Payroll Schedule'!P22-IFERROR('Payroll Schedule'!P17/'Payroll Schedule'!P18,0)),ABS('Payroll Schedule'!Q20-IFERROR('Payroll Schedule'!Q18/'Payroll Schedule'!Q16,0)),ABS('Payroll Schedule'!Q21-IFERROR('Payroll Schedule'!Q19/'Payroll Schedule'!Q16,0)),ABS('Payroll Schedule'!Q22-IFERROR('Payroll Schedule'!Q17/'Payroll Schedule'!Q18,0)),ABS('Payroll Schedule'!R20-IFERROR('Payroll Schedule'!R18/'Payroll Schedule'!R16,0)),ABS('Payroll Schedule'!R21-IFERROR('Payroll Schedule'!R19/'Payroll Schedule'!R16,0)),ABS('Payroll Schedule'!R22-IFERROR('Payroll Schedule'!R17/'Payroll Schedule'!R18,0)),ABS('Payroll Schedule'!S20-IFERROR('Payroll Schedule'!S18/'Payroll Schedule'!S16,0)),ABS('Payroll Schedule'!S21-IFERROR('Payroll Schedule'!S19/'Payroll Schedule'!S16,0)),ABS('Payroll Schedule'!S22-IFERROR('Payroll Schedule'!S17/'Payroll Schedule'!S18,0)),ABS('Payroll Schedule'!T20-IFERROR('Payroll Schedule'!T18/'Payroll Schedule'!T16,0)),ABS('Payroll Schedule'!T21-IFERROR('Payroll Schedule'!T19/'Payroll Schedule'!T16,0)),ABS('Payroll Schedule'!T22-IFERROR('Payroll Schedule'!T17/'Payroll Schedule'!T18,0)),ABS('Payroll Schedule'!U20-IFERROR('Payroll Schedule'!U18/'Payroll Schedule'!U16,0)),ABS('Payroll Schedule'!U21-IFERROR('Payroll Schedule'!U19/'Payroll Schedule'!U16,0)),ABS('Payroll Schedule'!U22-IFERROR('Payroll Schedule'!U17/'Payroll Schedule'!U18,0)),ABS('Payroll Schedule'!V20-IFERROR('Payroll Schedule'!V18/'Payroll Schedule'!V16,0)),ABS('Payroll Schedule'!V21-IFERROR('Payroll Schedule'!V19/'Payroll Schedule'!V16,0)),ABS('Payroll Schedule'!V22-IFERROR('Payroll Schedule'!V17/'Payroll Schedule'!V18,0)),ABS('Payroll Schedule'!W20-IFERROR('Payroll Schedule'!W18/'Payroll Schedule'!W16,0)),ABS('Payroll Schedule'!W21-IFERROR('Payroll Schedule'!W19/'Payroll Schedule'!W16,0)),ABS('Payroll Schedule'!W22-IFERROR('Payroll Schedule'!W17/'Payroll Schedule'!W18,0))) -> 0 | F17: 0 | G17: =E17-F17 -> 0 | H17: 0.01 | I17: =IF(ABS(G17)<=H17,"OK","FAIL") -> OK | J17: Revenue per employee, units per employee, and payroll percent must stay tied to revenue/capacity and average FTE.
A18: Schedule Coherence | B18: Payroll detail FTE math | C18: Payroll Schedule | D18: E27:H86 | E18: =SUMPRODUCT(ABS('Payroll Schedule'!G27:G86-('Payroll Schedule'!E27:E86+'Payroll Schedule'!F27:F86)))+SUMPRODUCT(ABS('Payroll Schedule'!H27:H86-(('Payroll Schedule'!E27:E86+'Payroll Schedule'!G27:G86)/2))) -> 0 | F18: 0 | G18: =E18-F18 -> 0 | H18: 0.01 | I18: =IF(ABS(G18)<=H18,"OK","FAIL") -> OK | J18: Ending FTE must equal starting FTE plus hires; average FTE must be the average of starting and ending FTE.
A19: Schedule Coherence | B19: Payroll detail wage and tax math | C19: Payroll Schedule | D19: I27:M86 | E19: =SUMPRODUCT(ABS('Payroll Schedule'!K27:K86-('Payroll Schedule'!H27:H86*'Payroll Schedule'!I27:I86/4)))+SUMPRODUCT(ABS('Payroll Schedule'!L27:L86-('Payroll Schedule'!K27:K86*'Payroll Schedule'!J27:J86)))+SUMPRODUCT(ABS('Payroll Schedule'!M27:M86-('Payroll Schedule'!K27:K86+'Payroll Schedule'!L27:L86))) -> 0 | F19: 0 | G19: =E19-F19 -> 0 | H19: 1 | I19: =IF(ABS(G19)<=H19,"OK","FAIL") -> OK | J19: Payroll dollars must flow from average FTE, wage, benefits/taxes, and total payroll formulas.
A21: Line-Item Formula Logic Diagnostics
A22: Formula Logic | B22: Revenue calculation - lob_1_product_1 | C22: Revenue Drivers | D22: 'Revenue Drivers'!C11:W11 | E22: =SUMPRODUCT(ABS('Revenue Drivers'!C11:W11-('Revenue Drivers'!C8:W8*'Revenue Drivers'!C9:W9*'Revenue Drivers'!C10:W10))) -> 0 | F22: 0 | G22: =E22-F22 -> 0 | H22: 1 | I22: =IF(ABS(G22)<=H22,"OK","FAIL") -> OK | J22: Revenue rows must equal capacity x unit price x utilization.
A23: Formula Logic | B23: Revenue calculation - lob_2_product_1 | C23: Revenue Drivers | D23: 'Revenue Drivers'!C17:W17 | E23: =SUMPRODUCT(ABS('Revenue Drivers'!C17:W17-('Revenue Drivers'!C14:W14*'Revenue Drivers'!C15:W15*'Revenue Drivers'!C16:W16))) -> 0 | F23: 0 | G23: =E23-F23 -> 0 | H23: 1 | I23: =IF(ABS(G23)<=H23,"OK","FAIL") -> OK | J23: Revenue rows must equal capacity x unit price x utilization.
A24: Formula Logic | B24: Revenue total equals all revenue products | C24: Revenue Drivers | D24: 'Revenue Drivers'!C20:W20 | E24: =SUMPRODUCT(ABS('Revenue Drivers'!C20:W20-('Revenue Drivers'!C11:W11+'Revenue Drivers'!C17:W17))) -> 0 | F24: 0 | G24: =E24-F24 -> 0 | H24: 1 | I24: =IF(ABS(G24)<=H24,"OK","FAIL") -> OK | J24: Total revenue must stay tied to all revenue-product rows.
A25: Formula Logic | B25: Revenue total capacity equals all capacity products | C25: Revenue Drivers | D25: 'Revenue Drivers'!C19:W19 | E25: =SUMPRODUCT(ABS('Revenue Drivers'!C19:W19-('Revenue Drivers'!C8:W8+'Revenue Drivers'!C14:W14))) -> 0 | F25: 0 | G25: =E25-F25 -> 0 | H25: 0.01 | I25: =IF(ABS(G25)<=H25,"OK","FAIL") -> OK | J25: Total capacity units must stay tied to all revenue-driver capacity rows.
A26: Formula Logic | B26: Debt opening balance continuity | C26: Debt Schedule | D26: 'Debt Schedule'!D7:W7 | E26: =SUMPRODUCT(ABS('Debt Schedule'!D7:W7-'Debt Schedule'!C11:V11)) -> 0 | F26: 0 | G26: =E26-F26 -> 0 | H26: 1 | I26: =IF(ABS(G26)<=H26,"OK","FAIL") -> OK | J26: Each quarter's opening debt must equal the prior quarter's closing debt.
A27: Formula Logic | B27: Actual debt repayment cap | C27: Debt Schedule | D27: 'Debt Schedule'!C10:W10 | E27: =SUMPRODUCT(--(('Debt Schedule'!C10:W10-'Debt Schedule'!C9:W9)>1))+SUMPRODUCT(--(('Debt Schedule'!C10:W10-('Debt Schedule'!C7:W7+'Debt Schedule'!C8:W8))>1)) -> 0 | F27: 0 | G27: =E27-F27 -> 0 | H27: 0 | I27: =IF(ABS(G27)<=H27,"OK","FAIL") -> OK | J27: Actual repayment must not exceed requested repayment or available debt balance.
A28: Formula Logic | B28: Closing debt formula | C28: Debt Schedule | D28: 'Debt Schedule'!C11:W11 | E28: =SUMPRODUCT(ABS('Debt Schedule'!C11:W11-('Debt Schedule'!C7:W7+'Debt Schedule'!C8:W8-'Debt Schedule'!C10:W10))) -> 0 | F28: 0 | G28: =E28-F28 -> 0 | H28: 1 | I28: =IF(ABS(G28)<=H28,"OK","FAIL") -> OK | J28: Closing debt must equal opening debt plus issuance less actual repayment, floored at zero.
A29: Formula Logic | B29: Interest expense formula | C29: Debt Schedule | D29: 'Debt Schedule'!C13:W13 | E29: =SUMPRODUCT(ABS('Debt Schedule'!C13:W13-((('Debt Schedule'!C7:W7+'Debt Schedule'!C11:W11)/2)*'Debt Schedule'!C12:W12))) -> 0 | F29: 0 | G29: =E29-F29 -> 0 | H29: 1 | I29: =IF(ABS(G29)<=H29,"OK","FAIL") -> OK | J29: Interest expense must equal average debt balance times interest rate.
A30: Formula Logic | B30: Debt service formula | C30: Debt Schedule | D30: 'Debt Schedule'!C14:W14 | E30: =SUMPRODUCT(ABS('Debt Schedule'!C14:W14-('Debt Schedule'!C13:W13+'Debt Schedule'!C10:W10))) -> 0 | F30: 0 | G30: =E30-F30 -> 0 | H30: 1 | I30: =IF(ABS(G30)<=H30,"OK","FAIL") -> OK | J30: Debt service must equal interest expense plus actual debt repayment.
A31: Formula Logic | B31: Lease opening balance continuity | C31: Debt Schedule | D31: 'Debt Schedule'!D18:W18 | E31: =SUMPRODUCT(ABS('Debt Schedule'!D18:W18-'Debt Schedule'!C23:V23)) -> 0 | F31: 0 | G31: =E31-F31 -> 0 | H31: 1 | I31: =IF(ABS(G31)<=H31,"OK","FAIL") -> OK | J31: Each quarter's opening lease balance must equal the prior quarter's closing lease balance.
A32: Formula Logic | B32: Lease principal repayment cap | C32: Debt Schedule | D32: 'Debt Schedule'!C20:W20 | E32: =SUMPRODUCT(--(('Debt Schedule'!C20:W20-'Debt Schedule'!C19:W19)>1))+SUMPRODUCT(--(('Debt Schedule'!C20:W20-('Debt Schedule'!C18:W18+'Debt Schedule'!C21:W21))>1)) -> 0 | F32: 0 | G32: =E32-F32 -> 0 | H32: 0 | I32: =IF(ABS(G32)<=H32,"OK","FAIL") -> OK | J32: Lease principal repayment must not exceed requested repayment or available lease balance.
A33: Formula Logic | B33: Lease closing balance formula | C33: Debt Schedule | D33: 'Debt Schedule'!C23:W23 | E33: =SUMPRODUCT(ABS('Debt Schedule'!C23:W23-('Debt Schedule'!C18:W18+'Debt Schedule'!C21:W21-'Debt Schedule'!C20:W20))) -> 0 | F33: 0 | G33: =E33-F33 -> 0 | H33: 1 | I33: =IF(ABS(G33)<=H33,"OK","FAIL") -> OK | J33: Lease closing balance must equal opening balance plus additions less principal repayment, floored at zero.
A34: Formula Logic | B34: PPE opening balance continuity | C34: CapEx Depreciation | D34: 'CapEx Depreciation'!D7:W7 | E34: =SUMPRODUCT(ABS('CapEx Depreciation'!D7:W7-'CapEx Depreciation'!C12:V12)) -> 0 | F34: 0 | G34: =E34-F34 -> 0 | H34: 1 | I34: =IF(ABS(G34)<=H34,"OK","FAIL") -> OK | J34: Each quarter's opening PPE must equal the prior quarter's closing PPE.
A35: Formula Logic | B35: Depreciation expense formula | C35: CapEx Depreciation | D35: 'CapEx Depreciation'!C11:W11 | E35: =SUMPRODUCT(ABS('CapEx Depreciation'!C11:W11-('CapEx Depreciation'!C7:W7*'CapEx Depreciation'!C10:W10))) -> 0 | F35: 0 | G35: =E35-F35 -> 0 | H35: 1 | I35: =IF(ABS(G35)<=H35,"OK","FAIL") -> OK | J35: Depreciation must equal opening PPE times rate, capped at opening PPE.
A36: Formula Logic | B36: Closing PPE formula | C36: CapEx Depreciation | D36: 'CapEx Depreciation'!C12:W12 | E36: =SUMPRODUCT(ABS('CapEx Depreciation'!C12:W12-('CapEx Depreciation'!C7:W7+'CapEx Depreciation'!C8:W8+'CapEx Depreciation'!C9:W9-'CapEx Depreciation'!C11:W11))) -> 0 | F36: 0 | G36: =E36-F36 -> 0 | H36: 1 | I36: =IF(ABS(G36)<=H36,"OK","FAIL") -> OK | J36: Closing PPE must include capex and lease additions and subtract depreciation.
A37: Formula Logic | B37: Accumulated depreciation continuity | C37: CapEx Depreciation | D37: 'CapEx Depreciation'!D13:W13 | E37: =SUMPRODUCT(ABS('CapEx Depreciation'!D13:W13-'CapEx Depreciation'!C14:V14)) -> 0 | F37: 0 | G37: =E37-F37 -> 0 | H37: 1 | I37: =IF(ABS(G37)<=H37,"OK","FAIL") -> OK | J37: Opening accumulated depreciation must equal the prior quarter's accumulated depreciation.
A38: Formula Logic | B38: Accumulated depreciation formula | C38: CapEx Depreciation | D38: 'CapEx Depreciation'!C14:W14 | E38: =SUMPRODUCT(ABS('CapEx Depreciation'!C14:W14-('CapEx Depreciation'!C13:W13-'CapEx Depreciation'!C11:W11))) -> 0 | F38: 0 | G38: =E38-F38 -> 0 | H38: 1 | I38: =IF(ABS(G38)<=H38,"OK","FAIL") -> OK | J38: Accumulated depreciation must roll forward by depreciation expense.
A40: Formula Manifest by Line Item
A41: Formula Manifest | B41: Revenue Drivers - Total Revenue | C41: Revenue Drivers | D41: 'Revenue Drivers'!C20:W20 | E41: =21 -> 21 | F41: 21 | G41: =E41-F41 -> 0 | H41: 0 | I41: =IF(G41=0,"OK","FAIL") -> OK | J41: This line is expected to be formula-driven across every period. Formula presence is verified at export; live edit integrity is covered by the logic and bridge checks above.
A42: Formula Manifest | B42: Revenue Drivers - Total Capacity Units | C42: Revenue Drivers | D42: 'Revenue Drivers'!C19:W19 | E42: =21 -> 21 | F42: 21 | G42: =E42-F42 -> 0 | H42: 0 | I42: =IF(G42=0,"OK","FAIL") -> OK | J42: This line is expected to be formula-driven across every period. Formula presence is verified at export; live edit integrity is covered by the logic and bridge checks above.
A43: Formula Manifest | B43: Revenue Drivers - Actual Revenue QoQ Growth | C43: Revenue Drivers | D43: 'Revenue Drivers'!C23:W23 | E43: =21 -> 21 | F43: 21 | G43: =E43-F43 -> 0 | H43: 0 | I43: =IF(G43=0,"OK","FAIL") -> OK | J43: This line is expected to be formula-driven across every period. Formula presence is verified at export; live edit integrity is covered by the logic and bridge checks above.
A44: Formula Manifest | B44: Payroll Schedule - Total Ending FTE | C44: Payroll Schedule | D44: 'Payroll Schedule'!C15:W15 | E44: =21 -> 21 | F44: 21 | G44: =E44-F44 -> 0 | H44: 0 | I44: =IF(G44=0,"OK","FAIL") -> OK | J44: This line is expected to be formula-driven across every period. Formula presence is verified at export; live edit integrity is covered by the logic and bridge checks above.
A45: Formula Manifest | B45: Payroll Schedule - Total Average FTE | C45: Payroll Schedule | D45: 'Payroll Schedule'!C16:W16 | E45: =21 -> 21 | F45: 21 | G45: =E45-F45 -> 0 | H45: 0 | I45: =IF(G45=0,"OK","FAIL") -> OK | J45: This line is expected to be formula-driven across every period. Formula presence is verified at export; live edit integrity is covered by the logic and bridge checks above.
A46: Formula Manifest | B46: Payroll Schedule - Total Payroll | C46: Payroll Schedule | D46: 'Payroll Schedule'!C17:W17 | E46: =21 -> 21 | F46: 21 | G46: =E46-F46 -> 0 | H46: 0 | I46: =IF(G46=0,"OK","FAIL") -> OK | J46: This line is expected to be formula-driven across every period. Formula presence is verified at export; live edit integrity is covered by the logic and bridge checks above.
A47: Formula Manifest | B47: Payroll Schedule - Total Revenue | C47: Payroll Schedule | D47: 'Payroll Schedule'!C18:W18 | E47: =21 -> 21 | F47: 21 | G47: =E47-F47 -> 0 | H47: 0 | I47: =IF(G47=0,"OK","FAIL") -> OK | J47: This line is expected to be formula-driven across every period. Formula presence is verified at export; live edit integrity is covered by the logic and bridge checks above.
A48: Formula Manifest | B48: Payroll Schedule - Total Capacity Units | C48: Payroll Schedule | D48: 'Payroll Schedule'!C19:W19 | E48: =21 -> 21 | F48: 21 | G48: =E48-F48 -> 0 | H48: 0 | I48: =IF(G48=0,"OK","FAIL") -> OK | J48: This line is expected to be formula-driven across every period. Formula presence is verified at export; live edit integrity is covered by the logic and bridge checks above.
A49: Formula Manifest | B49: Payroll Schedule - Revenue per Employee | C49: Payroll Schedule | D49: 'Payroll Schedule'!C20:W20 | E49: =21 -> 21 | F49: 21 | G49: =E49-F49 -> 0 | H49: 0 | I49: =IF(G49=0,"OK","FAIL") -> OK | J49: This line is expected to be formula-driven across every period. Formula presence is verified at export; live edit integrity is covered by the logic and bridge checks above.
A50: Formula Manifest | B50: Payroll Schedule - Units per Employee | C50: Payroll Schedule | D50: 'Payroll Schedule'!C21:W21 | E50: =21 -> 21 | F50: 21 | G50: =E50-F50 -> 0 | H50: 0 | I50: =IF(G50=0,"OK","FAIL") -> OK | J50: This line is expected to be formula-driven across every period. Formula presence is verified at export; live edit integrity is covered by the logic and bridge checks above.
A51: Formula Manifest | B51: Payroll Schedule - Payroll % of Revenue | C51: Payroll Schedule | D51: 'Payroll Schedule'!C22:W22 | E51: =21 -> 21 | F51: 21 | G51: =E51-F51 -> 0 | H51: 0 | I51: =IF(G51=0,"OK","FAIL") -> OK | J51: This line is expected to be formula-driven across every period. Formula presence is verified at export; live edit integrity is covered by the logic and bridge checks above.
A52: Formula Manifest | B52: CapEx Schedule - Lease Additions | C52: CapEx Depreciation | D52: 'CapEx Depreciation'!D9:W9 | E52: =20 -> 20 | F52: 20 | G52: =E52-F52 -> 0 | H52: 0 | I52: =IF(G52=0,"OK","FAIL") -> OK | J52: This line is expected to be formula-driven across every period. Formula presence is verified at export; live edit integrity is covered by the logic and bridge checks above.
A53: Formula Manifest | B53: CapEx Schedule - Closing PPE | C53: CapEx Depreciation | D53: 'CapEx Depreciation'!C12:W12 | E53: =21 -> 21 | F53: 21 | G53: =E53-F53 -> 0 | H53: 0 | I53: =IF(G53=0,"OK","FAIL") -> OK | J53: This line is expected to be formula-driven across every period. Formula presence is verified at export; live edit integrity is covered by the logic and bridge checks above.
A54: Formula Manifest | B54: Debt Schedule - Opening Debt | C54: Debt Schedule | D54: 'Debt Schedule'!D7:W7 | E54: =20 -> 20 | F54: 20 | G54: =E54-F54 -> 0 | H54: 0 | I54: =IF(G54=0,"OK","FAIL") -> OK | J54: This debt/lease line is expected to be formula-driven across every period. Formula presence is verified at export; live edit integrity is covered by the logic and bridge checks above.
A55: Formula Manifest | B55: Debt Schedule - Actual Debt Repayment | C55: Debt Schedule | D55: 'Debt Schedule'!C10:W10 | E55: =21 -> 21 | F55: 21 | G55: =E55-F55 -> 0 | H55: 0 | I55: =IF(G55=0,"OK","FAIL") -> OK | J55: This debt/lease line is expected to be formula-driven across every period. Formula presence is verified at export; live edit integrity is covered by the logic and bridge checks above.
A56: Formula Manifest | B56: Debt Schedule - Closing Debt | C56: Debt Schedule | D56: 'Debt Schedule'!C11:W11 | E56: =21 -> 21 | F56: 21 | G56: =E56-F56 -> 0 | H56: 0 | I56: =IF(G56=0,"OK","FAIL") -> OK | J56: This debt/lease line is expected to be formula-driven across every period. Formula presence is verified at export; live edit integrity is covered by the logic and bridge checks above.
A57: Formula Manifest | B57: Debt Schedule - Interest Expense | C57: Debt Schedule | D57: 'Debt Schedule'!C13:W13 | E57: =21 -> 21 | F57: 21 | G57: =E57-F57 -> 0 | H57: 0 | I57: =IF(G57=0,"OK","FAIL") -> OK | J57: This debt/lease line is expected to be formula-driven across every period. Formula presence is verified at export; live edit integrity is covered by the logic and bridge checks above.
A58: Formula Manifest | B58: Debt Schedule - Total Debt Service | C58: Debt Schedule | D58: 'Debt Schedule'!C14:W14 | E58: =21 -> 21 | F58: 21 | G58: =E58-F58 -> 0 | H58: 0 | I58: =IF(G58=0,"OK","FAIL") -> OK | J58: This debt/lease line is expected to be formula-driven across every period. Formula presence is verified at export; live edit integrity is covered by the logic and bridge checks above.
A59: Formula Manifest | B59: Debt Schedule - Lease Opening Balance | C59: Debt Schedule | D59: 'Debt Schedule'!D18:W18 | E59: =20 -> 20 | F59: 20 | G59: =E59-F59 -> 0 | H59: 0 | I59: =IF(G59=0,"OK","FAIL") -> OK | J59: This debt/lease line is expected to be formula-driven across every period. Formula presence is verified at export; live edit integrity is covered by the logic and bridge checks above.
A60: Formula Manifest | B60: Debt Schedule - Lease Principal Repayments | C60: Debt Schedule | D60: 'Debt Schedule'!C20:W20 | E60: =21 -> 21 | F60: 21 | G60: =E60-F60 -> 0 | H60: 0 | I60: =IF(G60=0,"OK","FAIL") -> OK | J60: This debt/lease line is expected to be formula-driven across every period. Formula presence is verified at export; live edit integrity is covered by the logic and bridge checks above.
A61: Formula Manifest | B61: Debt Schedule - Lease Closing Balance | C61: Debt Schedule | D61: 'Debt Schedule'!C23:W23 | E61: =21 -> 21 | F61: 21 | G61: =E61-F61 -> 0 | H61: 0 | I61: =IF(G61=0,"OK","FAIL") -> OK | J61: This debt/lease line is expected to be formula-driven across every period. Formula presence is verified at export; live edit integrity is covered by the logic and bridge checks above.
A62: Formula Manifest | B62: Payroll Detail - Ending FTE | C62: Payroll Schedule | D62: 'Payroll Schedule'!G27:G86 | E62: =60 -> 60 | F62: 60 | G62: =E62-F62 -> 0 | H62: 0 | I62: =IF(G62=0,"OK","FAIL") -> OK | J62: Payroll detail calculation columns must remain formulas so edits flow downstream. Formula presence is verified at export; live edit integrity is covered by the logic and bridge checks above.
A63: Formula Manifest | B63: Payroll Detail - Average FTE | C63: Payroll Schedule | D63: 'Payroll Schedule'!H27:H86 | E63: =60 -> 60 | F63: 60 | G63: =E63-F63 -> 0 | H63: 0 | I63: =IF(G63=0,"OK","FAIL") -> OK | J63: Payroll detail calculation columns must remain formulas so edits flow downstream. Formula presence is verified at export; live edit integrity is covered by the logic and bridge checks above.
A64: Formula Manifest | B64: Payroll Detail - Wage Cost | C64: Payroll Schedule | D64: 'Payroll Schedule'!K27:K86 | E64: =60 -> 60 | F64: 60 | G64: =E64-F64 -> 0 | H64: 0 | I64: =IF(G64=0,"OK","FAIL") -> OK | J64: Payroll detail calculation columns must remain formulas so edits flow downstream. Formula presence is verified at export; live edit integrity is covered by the logic and bridge checks above.
A65: Formula Manifest | B65: Payroll Detail - Taxes & Benefits | C65: Payroll Schedule | D65: 'Payroll Schedule'!L27:L86 | E65: =60 -> 60 | F65: 60 | G65: =E65-F65 -> 0 | H65: 0 | I65: =IF(G65=0,"OK","FAIL") -> OK | J65: Payroll detail calculation columns must remain formulas so edits flow downstream. Formula presence is verified at export; live edit integrity is covered by the logic and bridge checks above.
A66: Formula Manifest | B66: Payroll Detail - Total Payroll | C66: Payroll Schedule | D66: 'Payroll Schedule'!M27:M86 | E66: =60 -> 60 | F66: 60 | G66: =E66-F66 -> 0 | H66: 0 | I66: =IF(G66=0,"OK","FAIL") -> OK | J66: Payroll detail calculation columns must remain formulas so edits flow downstream. Formula presence is verified at export; live edit integrity is covered by the logic and bridge checks above.
A67: Formula Manifest | B67: Model Inputs - revenue::lob_1_product_1::Capacity | C67: Model Inputs | D67: 'Model Inputs'!C7:W7 | E67: =21 -> 21 | F67: 21 | G67: =E67-F67 -> 0 | H67: 0 | I67: =IF(G67=0,"OK","FAIL") -> OK | J67: Formula bridge rows in Model Inputs must stay linked to schedules. Formula presence is verified at export; live edit integrity is covered by the logic and bridge checks above.
A68: Formula Manifest | B68: Model Inputs - revenue::lob_1_product_1::Unit Price | C68: Model Inputs | D68: 'Model Inputs'!C8:W8 | E68: =21 -> 21 | F68: 21 | G68: =E68-F68 -> 0 | H68: 0 | I68: =IF(G68=0,"OK","FAIL") -> OK | J68: Formula bridge rows in Model Inputs must stay linked to schedules. Formula presence is verified at export; live edit integrity is covered by the logic and bridge checks above.
A69: Formula Manifest | B69: Model Inputs - revenue::lob_1_product_1::Utilization | C69: Model Inputs | D69: 'Model Inputs'!C9:W9 | E69: =21 -> 21 | F69: 21 | G69: =E69-F69 -> 0 | H69: 0 | I69: =IF(G69=0,"OK","FAIL") -> OK | J69: Formula bridge rows in Model Inputs must stay linked to schedules. Formula presence is verified at export; live edit integrity is covered by the logic and bridge checks above.
A70: Formula Manifest | B70: Model Inputs - revenue::lob_1_product_1::Revenue | C70: Model Inputs | D70: 'Model Inputs'!C10:W10 | E70: =21 -> 21 | F70: 21 | G70: =E70-F70 -> 0 | H70: 0 | I70: =IF(G70=0,"OK","FAIL") -> OK | J70: Formula bridge rows in Model Inputs must stay linked to schedules. Formula presence is verified at export; live edit integrity is covered by the logic and bridge checks above.
A71: Formula Manifest | B71: Model Inputs - revenue::lob_2_product_1::Capacity | C71: Model Inputs | D71: 'Model Inputs'!C11:W11 | E71: =21 -> 21 | F71: 21 | G71: =E71-F71 -> 0 | H71: 0 | I71: =IF(G71=0,"OK","FAIL") -> OK | J71: Formula bridge rows in Model Inputs must stay linked to schedules. Formula presence is verified at export; live edit integrity is covered by the logic and bridge checks above.
A72: Formula Manifest | B72: Model Inputs - revenue::lob_2_product_1::Unit Price | C72: Model Inputs | D72: 'Model Inputs'!C12:W12 | E72: =21 -> 21 | F72: 21 | G72: =E72-F72 -> 0 | H72: 0 | I72: =IF(G72=0,"OK","FAIL") -> OK | J72: Formula bridge rows in Model Inputs must stay linked to schedules. Formula presence is verified at export; live edit integrity is covered by the logic and bridge checks above.
A73: Formula Manifest | B73: Model Inputs - revenue::lob_2_product_1::Utilization | C73: Model Inputs | D73: 'Model Inputs'!C13:W13 | E73: =21 -> 21 | F73: 21 | G73: =E73-F73 -> 0 | H73: 0 | I73: =IF(G73=0,"OK","FAIL") -> OK | J73: Formula bridge rows in Model Inputs must stay linked to schedules. Formula presence is verified at export; live edit integrity is covered by the logic and bridge checks above.
A74: Formula Manifest | B74: Model Inputs - revenue::lob_2_product_1::Revenue | C74: Model Inputs | D74: 'Model Inputs'!C14:W14 | E74: =21 -> 21 | F74: 21 | G74: =E74-F74 -> 0 | H74: 0 | I74: =IF(G74=0,"OK","FAIL") -> OK | J74: Formula bridge rows in Model Inputs must stay linked to schedules. Formula presence is verified at export; live edit integrity is covered by the logic and bridge checks above.
A75: Formula Manifest | B75: Model Inputs - is::Revenue | C75: Model Inputs | D75: 'Model Inputs'!C15:W15 | E75: =21 -> 21 | F75: 21 | G75: =E75-F75 -> 0 | H75: 0 | I75: =IF(G75=0,"OK","FAIL") -> OK | J75: Formula bridge rows in Model Inputs must stay linked to schedules. Formula presence is verified at export; live edit integrity is covered by the logic and bridge checks above.
A76: Formula Manifest | B76: Model Inputs - is::Lease | C76: Model Inputs | D76: 'Model Inputs'!C19:W19 | E76: =21 -> 21 | F76: 21 | G76: =E76-F76 -> 0 | H76: 0 | I76: =IF(G76=0,"OK","FAIL") -> OK | J76: Formula bridge rows in Model Inputs must stay linked to schedules. Formula presence is verified at export; live edit integrity is covered by the logic and bridge checks above.
A77: Formula Manifest | B77: Model Inputs - is::Payroll | C77: Model Inputs | D77: 'Model Inputs'!D20:W20 | E77: =20 -> 20 | F77: 20 | G77: =E77-F77 -> 0 | H77: 0 | I77: =IF(G77=0,"OK","FAIL") -> OK | J77: Formula bridge rows in Model Inputs must stay linked to schedules. Formula presence is verified at export; live edit integrity is covered by the logic and bridge checks above.
A78: Formula Manifest | B78: Model Inputs - is::Interest Rate | C78: Model Inputs | D78: 'Model Inputs'!C22:W22 | E78: =21 -> 21 | F78: 21 | G78: =E78-F78 -> 0 | H78: 0 | I78: =IF(G78=0,"OK","FAIL") -> OK | J78: Formula bridge rows in Model Inputs must stay linked to schedules. Formula presence is verified at export; live edit integrity is covered by the logic and bridge checks above.
A79: Formula Manifest | B79: Model Inputs - is::Interest Expense | C79: Model Inputs | D79: 'Model Inputs'!D23:W23 | E79: =20 -> 20 | F79: 20 | G79: =E79-F79 -> 0 | H79: 0 | I79: =IF(G79=0,"OK","FAIL") -> OK | J79: Formula bridge rows in Model Inputs must stay linked to schedules. Formula presence is verified at export; live edit integrity is covered by the logic and bridge checks above.
A80: Formula Manifest | B80: Model Inputs - is::Depreciation | C80: Model Inputs | D80: 'Model Inputs'!C24:W24 | E80: =21 -> 21 | F80: 21 | G80: =E80-F80 -> 0 | H80: 0 | I80: =IF(G80=0,"OK","FAIL") -> OK | J80: Formula bridge rows in Model Inputs must stay linked to schedules. Formula presence is verified at export; live edit integrity is covered by the logic and bridge checks above.
A81: Formula Manifest | B81: Model Inputs - is::Depreciation Expense | C81: Model Inputs | D81: 'Model Inputs'!C25:W25 | E81: =21 -> 21 | F81: 21 | G81: =E81-F81 -> 0 | H81: 0 | I81: =IF(G81=0,"OK","FAIL") -> OK | J81: Formula bridge rows in Model Inputs must stay linked to schedules. Formula presence is verified at export; live edit integrity is covered by the logic and bridge checks above.
A82: Formula Manifest | B82: Model Inputs - bs::Accounts Receivable Days | C82: Model Inputs | D82: 'Model Inputs'!C29:W29 | E82: =21 -> 21 | F82: 21 | G82: =E82-F82 -> 0 | H82: 0 | I82: =IF(G82=0,"OK","FAIL") -> OK | J82: Formula bridge rows in Model Inputs must stay linked to schedules. Formula presence is verified at export; live edit integrity is covered by the logic and bridge checks above.
A83: Formula Manifest | B83: Model Inputs - bs::Inventory Days | C83: Model Inputs | D83: 'Model Inputs'!C30:W30 | E83: =21 -> 21 | F83: 21 | G83: =E83-F83 -> 0 | H83: 0 | I83: =IF(G83=0,"OK","FAIL") -> OK | J83: Formula bridge rows in Model Inputs must stay linked to schedules. Formula presence is verified at export; live edit integrity is covered by the logic and bridge checks above.
A84: Formula Manifest | B84: Model Inputs - bs::Accounts Payable Days | C84: Model Inputs | D84: 'Model Inputs'!C31:W31 | E84: =21 -> 21 | F84: 21 | G84: =E84-F84 -> 0 | H84: 0 | I84: =IF(G84=0,"OK","FAIL") -> OK | J84: Formula bridge rows in Model Inputs must stay linked to schedules. Formula presence is verified at export; live edit integrity is covered by the logic and bridge checks above.
A85: Formula Manifest | B85: Model Inputs - bs::Prepaid Expenses (% of Revenue) | C85: Model Inputs | D85: 'Model Inputs'!C32:W32 | E85: =21 -> 21 | F85: 21 | G85: =E85-F85 -> 0 | H85: 0 | I85: =IF(G85=0,"OK","FAIL") -> OK | J85: Formula bridge rows in Model Inputs must stay linked to schedules. Formula presence is verified at export; live edit integrity is covered by the logic and bridge checks above.
A86: Formula Manifest | B86: Model Inputs - bs::Deferred Revenue (% of Revenue) | C86: Model Inputs | D86: 'Model Inputs'!C33:W33 | E86: =21 -> 21 | F86: 21 | G86: =E86-F86 -> 0 | H86: 0 | I86: =IF(G86=0,"OK","FAIL") -> OK | J86: Formula bridge rows in Model Inputs must stay linked to schedules. Formula presence is verified at export; live edit integrity is covered by the logic and bridge checks above.
A87: Formula Manifest | B87: Model Inputs - bs::Short Term Debt (% of LTD) | C87: Model Inputs | D87: 'Model Inputs'!C34:W34 | E87: =21 -> 21 | F87: 21 | G87: =E87-F87 -> 0 | H87: 0 | I87: =IF(G87=0,"OK","FAIL") -> OK | J87: Formula bridge rows in Model Inputs must stay linked to schedules. Formula presence is verified at export; live edit integrity is covered by the logic and bridge checks above.
A88: Formula Manifest | B88: Model Inputs - bs::Owner's Capital | C88: Model Inputs | D88: 'Model Inputs'!C35:W35 | E88: =21 -> 21 | F88: 21 | G88: =E88-F88 -> 0 | H88: 0 | I88: =IF(G88=0,"OK","FAIL") -> OK | J88: Formula bridge rows in Model Inputs must stay linked to schedules. Formula presence is verified at export; live edit integrity is covered by the logic and bridge checks above.
A89: Formula Manifest | B89: Model Inputs - bs::Other Equity | C89: Model Inputs | D89: 'Model Inputs'!C36:W36 | E89: =21 -> 21 | F89: 21 | G89: =E89-F89 -> 0 | H89: 0 | I89: =IF(G89=0,"OK","FAIL") -> OK | J89: Formula bridge rows in Model Inputs must stay linked to schedules. Formula presence is verified at export; live edit integrity is covered by the logic and bridge checks above.
A90: Formula Manifest | B90: Model Inputs - bs::Distributions | C90: Model Inputs | D90: 'Model Inputs'!C37:W37 | E90: =21 -> 21 | F90: 21 | G90: =E90-F90 -> 0 | H90: 0 | I90: =IF(G90=0,"OK","FAIL") -> OK | J90: Formula bridge rows in Model Inputs must stay linked to schedules. Formula presence is verified at export; live edit integrity is covered by the logic and bridge checks above.
A91: Formula Manifest | B91: Model Inputs - cash::Cash Opening Balance | C91: Model Inputs | D91: 'Model Inputs'!C40:W40 | E91: =21 -> 21 | F91: 21 | G91: =E91-F91 -> 0 | H91: 0 | I91: =IF(G91=0,"OK","FAIL") -> OK | J91: Formula bridge rows in Model Inputs must stay linked to schedules. Formula presence is verified at export; live edit integrity is covered by the logic and bridge checks above.
... A159: Formula Manifest | B159: FINMO - Cash Flow - Ending Cash | C159: FINMO | D159: 'FINMO'!C61:W61 | E159: =21 -> 21 | F159: 21 | G159: =E159-F159 -> 0 | H159: 0 | I159: =IF(G159=0,"OK","FAIL") -> OK | J159: FINMO statement lines must remain formula-driven. Formula presence is verified at export; live edit integrity is covered by the logic and bridge checks above.
A161: Formula Error Scans
A162: Formula Error Scan | B162: Revenue Drivers formula/error scan | C162: Revenue Drivers | D162: 'Revenue Drivers'!C7:W34 | E162: =SUMPRODUCT(--ISERROR('Revenue Drivers'!C7:W34)) -> 0 | F162: 0 | G162: =E162-F162 -> 0 | H162: 0 | I162: =IF(E162=0,"OK","FAIL") -> OK | J162: Counts Excel error values in the range.
A163: Formula Error Scan | B163: Payroll Schedule formula/error scan | C163: Payroll Schedule | D163: 'Payroll Schedule'!C15:W86 | E163: =SUMPRODUCT(--ISERROR('Payroll Schedule'!C15:W86)) -> 0 | F163: 0 | G163: =E163-F163 -> 0 | H163: 0 | I163: =IF(E163=0,"OK","FAIL") -> OK | J163: Counts Excel error values in the range.
A164: Formula Error Scan | B164: Debt Schedule formula/error scan | C164: Debt Schedule | D164: 'Debt Schedule'!C7:W26 | E164: =SUMPRODUCT(--ISERROR('Debt Schedule'!C7:W26)) -> 0 | F164: 0 | G164: =E164-F164 -> 0 | H164: 0 | I164: =IF(E164=0,"OK","FAIL") -> OK | J164: Counts Excel error values in the range.
A165: Formula Error Scan | B165: CapEx Depreciation formula/error scan | C165: CapEx Depreciation | D165: 'CapEx Depreciation'!C7:W14 | E165: =SUMPRODUCT(--ISERROR('CapEx Depreciation'!C7:W14)) -> 0 | F165: 0 | G165: =E165-F165 -> 0 | H165: 0 | I165: =IF(E165=0,"OK","FAIL") -> OK | J165: Counts Excel error values in the range.
A166: Formula Error Scan | B166: Cash Equity Schedule formula/error scan | C166: Cash Equity Schedule | D166: 'Cash Equity Schedule'!C7:W12 | E166: =SUMPRODUCT(--ISERROR('Cash Equity Schedule'!C7:W12)) -> 0 | F166: 0 | G166: =E166-F166 -> 0 | H166: 0 | I166: =IF(E166=0,"OK","FAIL") -> OK | J166: Counts Excel error values in the range.
A167: Formula Error Scan | B167: Model Inputs formula/error scan | C167: Model Inputs | D167: 'Model Inputs'!C7:W58 | E167: =SUMPRODUCT(--ISERROR('Model Inputs'!C7:W58)) -> 0 | F167: 0 | G167: =E167-F167 -> 0 | H167: 0 | I167: =IF(E167=0,"OK","FAIL") -> OK | J167: Counts Excel error values in the range.
A168: Formula Error Scan | B168: FINMO formula/error scan | C168: FINMO | D168: 'FINMO'!C8:W61 | E168: =SUMPRODUCT(--ISERROR(FINMO!C8:W61)) -> 0 | F168: 0 | G168: =E168-F168 -> 0 | H168: 0 | I168: =IF(E168=0,"OK","FAIL") -> OK | J168: Counts Excel error values in the range.
A170: Persisted Baseline Reconciliation
A171: Persisted Baseline | B171: Revenue Q20 | C171: FINMO vs Audit Source | D171: 'FINMO'!W8 | E171: =FINMO!W8 -> 639387.23 | F171: ='Audit Source'!W7 -> 639387.23 | G171: =E171-F171 -> 3.0419324e-07 | H171: 1 | I171: =IF(ABS(G171)<=H171,"MATCH","CHANGED") -> MATCH | J171: CHANGED means assumptions were edited from the persisted run; it is informational and does not fail Model Status.
A172: Persisted Baseline | B172: Payroll Q20 | C172: FINMO vs Audit Source | D172: 'FINMO'!W14 | E172: =FINMO!W14 -> 130050.35 | F172: ='Audit Source'!W13 -> 130050 | G172: =E172-F172 -> 0.345 | H172: 1 | I172: =IF(ABS(G172)<=H172,"MATCH","CHANGED") -> MATCH | J172: CHANGED means assumptions were edited from the persisted run; it is informational and does not fail Model Status.
...

Sheet Diagnostics
A1: Run Diagnostics
A3: Run Metadata
A4: Planning Mode | B4: normalize
A5: Cash Strategy | B5: balanced
A6: Business Stage | B6: pre-revenue
A7: Business Name | B7: Anderson & Blake Legal Associates
A8: Business Start Date | B8: 06/19/2026
A9: NAICS-6 | B9: 541110
A10: Draft ID | B10: 770680284e484577917b00b9363c6175
A11: Planning Run ID | B11: 70125bba7ac443fba6733d496a014706
A13: Acceptance Gate
A14: Score | B14: 16/16
A15: Verdict | B15: PASSED
A17: GPT Exhaustion Handler
A18: Fired | B18: No (restoration loop landed deterministically)
A20: Realism Check Detail
A21: Metric Key | B21: Status
A22: advertising_percent_of_revenue | B22: ✓
A23: ap_days_dpo | B23: ✓
A24: ar_days_dso | B24: ✓
A25: capex_percent_of_revenue | B25: ✓
A26: cogs_percent_of_revenue | B26: ✓
A27: current_assets_minus_cash | B27: ✓
A28: current_liabilities_to_revenue | B28: ✓
A29: current_ratio | B29: ✓
A30: debt_to_assets | B30: ✓
A31: debt_to_equity | B31: ✓
A32: deferred_revenue_percent_of_revenue | B32: ✓
... A54: total_assets_to_revenue | B54: ✓
