Workbook

Sheet Revenue Drivers
A1: Revenue Drivers
A2: Source operating drivers. Model Inputs links to these rows.
C4: Stub | D4: Q1 | E4: Q2 | F4: Q3 | G4: Q4 | H4: Q5 | I4: Q6 | J4: Q7 | K4: Q8 | L4: Q9 | M4: Q10 | N4: Q11 | O4: Q12 | P4: Q13 | Q4: Q14 | R4: Q15 | S4: Q16 | T4: Q17 | U4: Q18 | V4: Q19 | W4: Q20 | X4: Y1 | Y4: Y2 | Z4: Y3 | AA4: Y4 | AB4: Y5
C5: 46162 | D5: 46295 | E5: 46387 | F5: 46477 | G5: 46568 | H5: 46660 | I5: 46752 | J5: 46843 | K5: 46934 | L5: 47026 | M5: 47118 | N5: 47208 | O5: 47299 | P5: 47391 | Q5: 47483 | R5: 47573 | S5: 47664 | T5: 47756 | U5: 47848 | V5: 47938 | W5: 48029 | X5: Annual | Y5: Annual | Z5: Annual | AA5: Annual | AB5: Annual
A6: Revenue Driver Source Rows
A7: Primary line of business / Billable home visit
A8: Primary line of business / Billable home visit - Capacity | B8: Source driver | C8: 1040 | D8: 2364.03 | E8: 2364.03 | F8: 2364.03 | G8: 2364.03 | H8: 2364.03 | I8: 2364.03 | J8: 2364.03 | K8: 2364.03 | L8: 2364.03 | M8: 2364.03 | N8: 2364.03 | O8: 2364.03 | P8: 2364.03 | Q8: 2364.03 | R8: 2364.03 | S8: 2364.03 | T8: 2364.03 | U8: 2364.03 | V8: 2364.03 | W8: 2364.03
A9: Primary line of business / Billable home visit - Unit Price | B9: Source driver | C9: 150 | D9: 150 | E9: 158 | F9: 166 | G9: 174 | H9: 182 | I9: 190 | J9: 198 | K9: 206 | L9: 214 | M9: 222 | N9: 230 | O9: 231.11111 | P9: 232.22222 | Q9: 233.33333 | R9: 234.44444 | S9: 235.55556 | T9: 236.66667 | U9: 237.77778 | V9: 238.88889 | W9: 240
A10: Primary line of business / Billable home visit - Utilization | B10: Source driver | C10: 0.75 | D10: 0.75 | E10: 0.759 | F10: 0.768 | G10: 0.777 | H10: 0.786 | I10: 0.795 | J10: 0.804 | K10: 0.813 | L10: 0.822 | M10: 0.831 | N10: 0.84 | O10: 0.84 | P10: 0.84 | Q10: 0.84 | R10: 0.84 | S10: 0.84 | T10: 0.84 | U10: 0.84 | V10: 0.84 | W10: 0.84
A11: Primary line of business / Billable home visit - Revenue | B11: Capacity x Unit Price x Utilization | C11: =C8*C9*C10 -> 117000 | D11: =D8*D9*D10 -> 265953.38 | E11: =E8*E9*E10 -> 283499.21 | F11: =F8*F9*F10 -> 301385.46 | G11: =G8*G9*G10 -> 319612.13 | H11: =H8*H9*H10 -> 338179.22 | I11: =I8*I9*I10 -> 357086.73 | J11: =J8*J9*J10 -> 376334.66 | ... W11: =W8*W9*W10 -> 476588.45 | X11: =SUM(D11:G11) -> 1170450.2 | Y11: =SUM(H11:K11) -> 1467523.6 | Z11: =SUM(L11:O11) -> 1767640.4 | AA11: =SUM(P11:S11) -> 1857812.4 | AB11: =SUM(T11:W11) -> 1893115.2
A13: Total Capacity Units | B13: All revenue driver capacity units | C13: =SUM(C8) -> 1040 | D13: =SUM(D8) -> 2364.03 | E13: =SUM(E8) -> 2364.03 | F13: =SUM(F8) -> 2364.03 | G13: =SUM(G8) -> 2364.03 | H13: =SUM(H8) -> 2364.03 | I13: =SUM(I8) -> 2364.03 | J13: =SUM(J8) -> 2364.03 | ... W13: =SUM(W8) -> 2364.03 | X13: =SUM(D13:G13) -> 9456.12 | Y13: =SUM(H13:K13) -> 9456.12 | Z13: =SUM(L13:O13) -> 9456.12 | AA13: =SUM(P13:S13) -> 9456.12 | AB13: =SUM(T13:W13) -> 9456.12
A14: Total Revenue | B14: All revenue products | C14: =SUM(C11) -> 117000 | D14: =SUM(D11) -> 265953.38 | E14: =SUM(E11) -> 283499.21 | F14: =SUM(F11) -> 301385.46 | G14: =SUM(G11) -> 319612.13 | H14: =SUM(H11) -> 338179.22 | I14: =SUM(I11) -> 357086.73 | J14: =SUM(J11) -> 376334.66 | ... W14: =SUM(W11) -> 476588.45 | X14: =SUM(D14:G14) -> 1170450.2 | Y14: =SUM(H14:K14) -> 1467523.6 | Z14: =SUM(L14:O14) -> 1767640.4 | AA14: =SUM(P14:S14) -> 1857812.4 | AB14: =SUM(T14:W14) -> 1893115.2
A16: Stage Ramp Contract
A17: Actual Revenue QoQ Growth | B17: Total revenue growth from modeled revenue drivers | C17: =0 -> 0 | D17: =IFERROR(D14/C14-1,0) -> 1.2731058 | E17: =IFERROR(E14/D14-1,0) -> 0.065973333 | F17: =IFERROR(F14/E14-1,0) -> 0.063091009 | G17: =IFERROR(G14/F14-1,0) -> 0.06047628 | H17: =IFERROR(H14/G14-1,0) -> 0.058092575 | I17: =IFERROR(I14/H14-1,0) -> 0.055909739 | J17: =IFERROR(J14/I14-1,0) -> 0.053902681 | K17: =IFERROR(K14/J14-1,0) -> 0.052050354 | ... W17: =IFERROR(W14/V14-1,0) -> 0.0046511623 | X17: =AVERAGE(D17:G17) -> 0.3656616 | Y17: =AVERAGE(H17:K17) -> 0.054988837 | Z17: =AVERAGE(L17:O17) -> 0.037790979 | AA17: =AVERAGE(P17:S17) -> 0.0047734062 | AB17: =AVERAGE(T17:W17) -> 0.0046839687
A18: Stage Ramp Revenue QoQ Target | B18: GPT-selected stage ramp contract | C18: 0 | D18: 0.5 | E18: 0.5 | F18: 0.5 | G18: 0.5 | H18: 0.5 | I18: 0.5 | J18: 0.5 | K18: 0.5 | L18: 0.5 | M18: 0.5 | N18: 0.5 | O18: 0.5 | P18: 0.5 | Q18: 0.5 | R18: 0.5 | S18: 0.5 | T18: 0.5 | U18: 0.5 | V18: 0.5 | W18: 0.5 | X18: =AVERAGE(D18:G18) -> 0.5 | Y18: =AVERAGE(H18:K18) -> 0.5 | Z18: =AVERAGE(L18:O18) -> 0.5 | AA18: =AVERAGE(P18:S18) -> 0.5 | AB18: =AVERAGE(T18:W18) -> 0.5
A19: Stage Ramp Revenue QoQ Max | B19: GPT-selected stage ramp contract | C19: 0 | D19: 0.75 | E19: 0.75 | F19: 0.75 | G19: 0.75 | H19: 0.75 | I19: 0.75 | J19: 0.75 | K19: 0.75 | L19: 0.75 | M19: 0.75 | N19: 0.75 | O19: 0.75 | P19: 0.75 | Q19: 0.75 | R19: 0.75 | S19: 0.75 | T19: 0.75 | U19: 0.75 | V19: 0.75 | W19: 0.75 | X19: =AVERAGE(D19:G19) -> 0.75 | Y19: =AVERAGE(H19:K19) -> 0.75 | Z19: =AVERAGE(L19:O19) -> 0.75 | AA19: =AVERAGE(P19:S19) -> 0.75 | AB19: =AVERAGE(T19:W19) -> 0.75
A20: Stage Ramp Revenue QoQ Spike Max | B20: GPT-selected stage ramp contract | C20: 0 | D20: 0.75 | E20: 0.75 | F20: 0.75 | G20: 0.75 | H20: 0.75 | I20: 0.75 | J20: 0.75 | K20: 0.75 | L20: 0.75 | M20: 0.75 | N20: 0.75 | O20: 0.75 | P20: 0.75 | Q20: 0.75 | R20: 0.75 | S20: 0.75 | T20: 0.75 | U20: 0.75 | V20: 0.75 | W20: 0.75 | X20: =AVERAGE(D20:G20) -> 0.75 | Y20: =AVERAGE(H20:K20) -> 0.75 | Z20: =AVERAGE(L20:O20) -> 0.75 | AA20: =AVERAGE(P20:S20) -> 0.75 | AB20: =AVERAGE(T20:W20) -> 0.75
A21: Stage Ramp Utilization Cap | B21: GPT-selected stage ramp contract | C21: 0 | D21: 0.25 | E21: 0.31 | F21: 0.37 | G21: 0.43 | H21: 0.49 | I21: 0.55 | J21: 0.61 | K21: 0.67 | L21: 0.73 | M21: 0.79 | N21: 0.85 | O21: 0.85 | P21: 0.85 | Q21: 0.85 | R21: 0.85 | S21: 0.85 | T21: 0.85 | U21: 0.85 | V21: 0.85 | W21: 0.85 | X21: =AVERAGE(D21:G21) -> 0.34 | Y21: =AVERAGE(H21:K21) -> 0.58 | Z21: =AVERAGE(L21:O21) -> 0.805 | AA21: =AVERAGE(P21:S21) -> 0.85 | AB21: =AVERAGE(T21:W21) -> 0.85
A22: Stage Ramp COGS % Revenue Target | B22: GPT-selected stage ramp contract | C22: 0 | D22: 0.69 | E22: 0.69 | F22: 0.69 | G22: 0.69 | H22: 0.69 | I22: 0.69 | J22: 0.69 | K22: 0.69 | L22: 0.69 | M22: 0.69 | N22: 0.69 | O22: 0.69 | P22: 0.69 | Q22: 0.69 | R22: 0.69 | S22: 0.69 | T22: 0.69 | U22: 0.69 | V22: 0.69 | W22: 0.69 | X22: =AVERAGE(D22:G22) -> 0.69 | Y22: =AVERAGE(H22:K22) -> 0.69 | Z22: =AVERAGE(L22:O22) -> 0.69 | AA22: =AVERAGE(P22:S22) -> 0.69 | AB22: =AVERAGE(T22:W22) -> 0.69
A23: Stage Ramp COGS % Revenue Max | B23: GPT-selected stage ramp contract | C23: 0 | D23: 0.75 | E23: 0.75 | F23: 0.75 | G23: 0.75 | H23: 0.75 | I23: 0.75 | J23: 0.75 | K23: 0.75 | L23: 0.75 | M23: 0.75 | N23: 0.75 | O23: 0.75 | P23: 0.75 | Q23: 0.75 | R23: 0.75 | S23: 0.75 | T23: 0.75 | U23: 0.75 | V23: 0.75 | W23: 0.75 | X23: =AVERAGE(D23:G23) -> 0.75 | Y23: =AVERAGE(H23:K23) -> 0.75 | Z23: =AVERAGE(L23:O23) -> 0.75 | AA23: =AVERAGE(P23:S23) -> 0.75 | AB23: =AVERAGE(T23:W23) -> 0.75
A24: Stage Ramp Marketing % Revenue Max | B24: GPT-selected stage ramp contract | C24: 0 | D24: 0.28 | E24: 0.28 | F24: 0.28 | G24: 0.28 | H24: 0.28 | I24: 0.28 | J24: 0.28 | K24: 0.28 | L24: 0.28 | M24: 0.28 | N24: 0.28 | O24: 0.28 | P24: 0.28 | Q24: 0.28 | R24: 0.28 | S24: 0.28 | T24: 0.28 | U24: 0.28 | V24: 0.28 | W24: 0.28 | X24: =AVERAGE(D24:G24) -> 0.28 | Y24: =AVERAGE(H24:K24) -> 0.28 | Z24: =AVERAGE(L24:O24) -> 0.28 | AA24: =AVERAGE(P24:S24) -> 0.28 | AB24: =AVERAGE(T24:W24) -> 0.28
A25: Stage Ramp R&D % Revenue Max | B25: GPT-selected stage ramp contract | C25: 0 | D25: 0.02 | E25: 0.02 | F25: 0.02 | G25: 0.02 | H25: 0.02 | I25: 0.02 | J25: 0.02 | K25: 0.02 | L25: 0.02 | M25: 0.02 | N25: 0.02 | O25: 0.02 | P25: 0.02 | Q25: 0.02 | R25: 0.02 | S25: 0.02 | T25: 0.02 | U25: 0.02 | V25: 0.02 | W25: 0.02 | X25: =AVERAGE(D25:G25) -> 0.02 | Y25: =AVERAGE(H25:K25) -> 0.02 | Z25: =AVERAGE(L25:O25) -> 0.02 | AA25: =AVERAGE(P25:S25) -> 0.02 | AB25: =AVERAGE(T25:W25) -> 0.02
A26: Stage Ramp G&A % Revenue Max | B26: GPT-selected stage ramp contract | C26: 0 | D26: 0.28 | E26: 0.28 | F26: 0.28 | G26: 0.28 | H26: 0.28 | I26: 0.28 | J26: 0.28 | K26: 0.28 | L26: 0.28 | M26: 0.28 | N26: 0.28 | O26: 0.28 | P26: 0.28 | Q26: 0.28 | R26: 0.28 | S26: 0.28 | T26: 0.28 | U26: 0.28 | V26: 0.28 | W26: 0.28 | X26: =AVERAGE(D26:G26) -> 0.28 | Y26: =AVERAGE(H26:K26) -> 0.28 | Z26: =AVERAGE(L26:O26) -> 0.28 | AA26: =AVERAGE(P26:S26) -> 0.28 | AB26: =AVERAGE(T26:W26) -> 0.28
A27: Stage Ramp Lease % Revenue Max | B27: GPT-selected stage ramp contract | C27: 0 | D27: 0.04 | E27: 0.04 | F27: 0.04 | G27: 0.04 | H27: 0.04 | I27: 0.04 | J27: 0.04 | K27: 0.04 | L27: 0.04 | M27: 0.04 | N27: 0.04 | O27: 0.04 | P27: 0.04 | Q27: 0.04 | R27: 0.04 | S27: 0.04 | T27: 0.04 | U27: 0.04 | V27: 0.04 | W27: 0.04 | X27: =AVERAGE(D27:G27) -> 0.04 | Y27: =AVERAGE(H27:K27) -> 0.04 | Z27: =AVERAGE(L27:O27) -> 0.04 | AA27: =AVERAGE(P27:S27) -> 0.04 | AB27: =AVERAGE(T27:W27) -> 0.04
A28: Stage Ramp Net Income Margin Floor | B28: GPT-selected stage ramp contract | C28: 0 | D28: -0.1 | E28: -0.1 | F28: -0.1 | G28: -0.1 | H28: -0.09 | I28: -0.07 | J28: -0.06 | K28: -0.05 | L28: -0.03 | M28: -0.02 | N28: 0 | O28: 0.01 | P28: 0.01 | Q28: 0.02 | R28: 0.02 | S28: 0.03 | T28: 0.03 | U28: 0.04 | V28: 0.04 | W28: 0.05 | X28: =AVERAGE(D28:G28) -> -0.1 | Y28: =AVERAGE(H28:K28) -> -0.0675 | Z28: =AVERAGE(L28:O28) -> -0.01 | AA28: =AVERAGE(P28:S28) -> 0.02 | AB28: =AVERAGE(T28:W28) -> 0.04

Sheet Payroll Schedule
A1: Payroll Schedule
A2: OEWS-title, capacity/utilization-driven payroll source. Model Inputs links to Total Payroll.
C4: Stub | D4: Q1 | E4: Q2 | F4: Q3 | G4: Q4 | H4: Q5 | I4: Q6 | J4: Q7 | K4: Q8 | L4: Q9 | M4: Q10 | N4: Q11 | O4: Q12 | P4: Q13 | Q4: Q14 | R4: Q15 | S4: Q16 | T4: Q17 | U4: Q18 | V4: Q19 | W4: Q20 | X4: Y1 | Y4: Y2 | Z4: Y3 | AA4: Y4 | AB4: Y5
C5: 46162 | D5: 46295 | E5: 46387 | F5: 46477 | G5: 46568 | H5: 46660 | I5: 46752 | J5: 46843 | K5: 46934 | L5: 47026 | M5: 47118 | N5: 47208 | O5: 47299 | P5: 47391 | Q5: 47483 | R5: 47573 | S5: 47664 | T5: 47756 | U5: 47848 | V5: 47938 | W5: 48029 | X5: Annual | Y5: Annual | Z5: Annual | AA5: Annual | AB5: Annual
A6: Payroll Assumptions
A7: Capacity Labor Model | B7: labor_driven
A8: Labor Intensity Class | B8: medium
A9: Wage Positioning Tier | B9: market
A10: Wage Positioning Multiplier | B10: 1.2
A11: Capacity Units per Supporting FTE | B11: 606.21
A12: Target Payroll % of Revenue | B12: 0.45
A14: Quarter Summary
A15: Total Ending FTE | B15: Formula output from payroll detail | C15: =SUMIFS($G$27:$G$86,$A$27:$A$86,0) -> 0 | D15: =SUMIFS($G$27:$G$86,$A$27:$A$86,1) -> 3 | E15: =SUMIFS($G$27:$G$86,$A$27:$A$86,2) -> 3 | F15: =SUMIFS($G$27:$G$86,$A$27:$A$86,3) -> 3 | G15: =SUMIFS($G$27:$G$86,$A$27:$A$86,4) -> 3 | H15: =SUMIFS($G$27:$G$86,$A$27:$A$86,5) -> 3 | I15: =SUMIFS($G$27:$G$86,$A$27:$A$86,6) -> 3 | J15: =SUMIFS($G$27:$G$86,$A$27:$A$86,7) -> 3 | K15: =SUMIFS($G$27:$G$86,$A$27:$A$86,8) -> 3 | L15: =SUMIFS($G$27:$G$86,$A$27:$A$86,9) -> 3 | M15: =SUMIFS($G$27:$G$86,$A$27:$A$86,10) -> 3 | N15: =SUMIFS($G$27:$G$86,$A$27:$A$86,11) -> 3 | O15: =SUMIFS($G$27:$G$86,$A$27:$A$86,12) -> 3 | P15: =SUMIFS($G$27:$G$86,$A$27:$A$86,13) -> 3 | Q15: =SUMIFS($G$27:$G$86,$A$27:$A$86,14) -> 3 | R15: =SUMIFS($G$27:$G$86,$A$27:$A$86,15) -> 3 | S15: =SUMIFS($G$27:$G$86,$A$27:$A$86,16) -> 3 | T15: =SUMIFS($G$27:$G$86,$A$27:$A$86,17) -> 3 | U15: =SUMIFS($G$27:$G$86,$A$27:$A$86,18) -> 3 | V15: =SUMIFS($G$27:$G$86,$A$27:$A$86,19) -> 3 | W15: =SUMIFS($G$27:$G$86,$A$27:$A$86,20) -> 3 | X15: =G15 -> 3 | Y15: =K15 -> 3 | Z15: =O15 -> 3 | AA15: =S15 -> 3 | AB15: =W15 -> 3
A16: Total Average FTE | B16: Formula output from payroll detail | C16: =SUMIFS($H$27:$H$86,$A$27:$A$86,0) -> 0 | D16: =SUMIFS($H$27:$H$86,$A$27:$A$86,1) -> 3 | E16: =SUMIFS($H$27:$H$86,$A$27:$A$86,2) -> 3 | F16: =SUMIFS($H$27:$H$86,$A$27:$A$86,3) -> 3 | G16: =SUMIFS($H$27:$H$86,$A$27:$A$86,4) -> 3 | H16: =SUMIFS($H$27:$H$86,$A$27:$A$86,5) -> 3 | I16: =SUMIFS($H$27:$H$86,$A$27:$A$86,6) -> 3 | J16: =SUMIFS($H$27:$H$86,$A$27:$A$86,7) -> 3 | K16: =SUMIFS($H$27:$H$86,$A$27:$A$86,8) -> 3 | L16: =SUMIFS($H$27:$H$86,$A$27:$A$86,9) -> 3 | M16: =SUMIFS($H$27:$H$86,$A$27:$A$86,10) -> 3 | N16: =SUMIFS($H$27:$H$86,$A$27:$A$86,11) -> 3 | O16: =SUMIFS($H$27:$H$86,$A$27:$A$86,12) -> 3 | P16: =SUMIFS($H$27:$H$86,$A$27:$A$86,13) -> 3 | Q16: =SUMIFS($H$27:$H$86,$A$27:$A$86,14) -> 3 | R16: =SUMIFS($H$27:$H$86,$A$27:$A$86,15) -> 3 | S16: =SUMIFS($H$27:$H$86,$A$27:$A$86,16) -> 3 | T16: =SUMIFS($H$27:$H$86,$A$27:$A$86,17) -> 3 | U16: =SUMIFS($H$27:$H$86,$A$27:$A$86,18) -> 3 | V16: =SUMIFS($H$27:$H$86,$A$27:$A$86,19) -> 3 | W16: =SUMIFS($H$27:$H$86,$A$27:$A$86,20) -> 3 | X16: =AVERAGE(D16:G16) -> 3 | Y16: =AVERAGE(H16:K16) -> 3 | Z16: =AVERAGE(L16:O16) -> 3 | AA16: =AVERAGE(P16:S16) -> 3 | AB16: =AVERAGE(T16:W16) -> 3
A17: Total Payroll | B17: Formula output from payroll detail | C17: =SUMIFS($M$27:$M$86,$A$27:$A$86,0) -> 0 | D17: =SUMIFS($M$27:$M$86,$A$27:$A$86,1) -> 106929.45 | E17: =SUMIFS($M$27:$M$86,$A$27:$A$86,2) -> 106929.45 | F17: =SUMIFS($M$27:$M$86,$A$27:$A$86,3) -> 106929.45 | G17: =SUMIFS($M$27:$M$86,$A$27:$A$86,4) -> 106929.45 | H17: =SUMIFS($M$27:$M$86,$A$27:$A$86,5) -> 110137.57 | I17: =SUMIFS($M$27:$M$86,$A$27:$A$86,6) -> 110137.57 | J17: =SUMIFS($M$27:$M$86,$A$27:$A$86,7) -> 110137.57 | K17: =SUMIFS($M$27:$M$86,$A$27:$A$86,8) -> 110137.57 | L17: =SUMIFS($M$27:$M$86,$A$27:$A$86,9) -> 113441.21 | M17: =SUMIFS($M$27:$M$86,$A$27:$A$86,10) -> 113441.21 | N17: =SUMIFS($M$27:$M$86,$A$27:$A$86,11) -> 113441.21 | O17: =SUMIFS($M$27:$M$86,$A$27:$A$86,12) -> 113441.21 | P17: =SUMIFS($M$27:$M$86,$A$27:$A$86,13) -> 116844.65 | Q17: =SUMIFS($M$27:$M$86,$A$27:$A$86,14) -> 116844.65 | R17: =SUMIFS($M$27:$M$86,$A$27:$A$86,15) -> 116844.65 | S17: =SUMIFS($M$27:$M$86,$A$27:$A$86,16) -> 116844.65 | T17: =SUMIFS($M$27:$M$86,$A$27:$A$86,17) -> 120350.07 | U17: =SUMIFS($M$27:$M$86,$A$27:$A$86,18) -> 120350.07 | V17: =SUMIFS($M$27:$M$86,$A$27:$A$86,19) -> 120350.07 | W17: =SUMIFS($M$27:$M$86,$A$27:$A$86,20) -> 120350.07 | X17: =SUM(D17:G17) -> 427717.8 | Y17: =SUM(H17:K17) -> 440550.3 | Z17: =SUM(L17:O17) -> 453764.83 | AA17: =SUM(P17:S17) -> 467378.62 | AB17: =SUM(T17:W17) -> 481400.27
A18: Total Revenue | B18: Linked from Revenue Drivers | C18: ='Revenue Drivers'!C14 -> 117000 | D18: ='Revenue Drivers'!D14 -> 265953.38 | E18: ='Revenue Drivers'!E14 -> 283499.21 | F18: ='Revenue Drivers'!F14 -> 301385.46 | G18: ='Revenue Drivers'!G14 -> 319612.13 | H18: ='Revenue Drivers'!H14 -> 338179.22 | I18: ='Revenue Drivers'!I14 -> 357086.73 | J18: ='Revenue Drivers'!J14 -> 376334.66 | ... W18: ='Revenue Drivers'!W14 -> 476588.45 | X18: =SUM(D18:G18) -> 1170450.2 | Y18: =SUM(H18:K18) -> 1467523.6 | Z18: =SUM(L18:O18) -> 1767640.4 | AA18: =SUM(P18:S18) -> 1857812.4 | AB18: =SUM(T18:W18) -> 1893115.2
A19: Total Capacity Units | B19: Linked from Revenue Drivers | C19: ='Revenue Drivers'!C13 -> 1040 | D19: ='Revenue Drivers'!D13 -> 2364.03 | E19: ='Revenue Drivers'!E13 -> 2364.03 | F19: ='Revenue Drivers'!F13 -> 2364.03 | G19: ='Revenue Drivers'!G13 -> 2364.03 | H19: ='Revenue Drivers'!H13 -> 2364.03 | I19: ='Revenue Drivers'!I13 -> 2364.03 | J19: ='Revenue Drivers'!J13 -> 2364.03 | ... W19: ='Revenue Drivers'!W13 -> 2364.03 | X19: =SUM(D19:G19) -> 9456.12 | Y19: =SUM(H19:K19) -> 9456.12 | Z19: =SUM(L19:O19) -> 9456.12 | AA19: =SUM(P19:S19) -> 9456.12 | AB19: =SUM(T19:W19) -> 9456.12
A20: Revenue per Employee | B20: Python-built productivity formula | C20: =IFERROR(C18/C16,0) -> 0 | D20: =IFERROR(D18/D16,0) -> 88651.125 | E20: =IFERROR(E18/E16,0) -> 94499.735 | F20: =IFERROR(F18/F16,0) -> 100461.82 | G20: =IFERROR(G18/G16,0) -> 106537.38 | H20: =IFERROR(H18/H16,0) -> 112726.41 | I20: =IFERROR(I18/I16,0) -> 119028.91 | J20: =IFERROR(J18/J16,0) -> 125444.89 | ... AB20: =IFERROR(AB18/AB16,0) -> 631038.41
A21: Units per Employee | B21: Python-built productivity formula | C21: =IFERROR(C19/C16,0) -> 0 | D21: =IFERROR(D19/D16,0) -> 788.01 | E21: =IFERROR(E19/E16,0) -> 788.01 | F21: =IFERROR(F19/F16,0) -> 788.01 | G21: =IFERROR(G19/G16,0) -> 788.01 | H21: =IFERROR(H19/H16,0) -> 788.01 | I21: =IFERROR(I19/I16,0) -> 788.01 | J21: =IFERROR(J19/J16,0) -> 788.01 | ... AB21: =IFERROR(AB19/AB16,0) -> 3152.04
A22: Payroll % of Revenue | B22: Python-built productivity formula | C22: =IFERROR(C17/C18,0) -> 0 | D22: =IFERROR(D17/D18,0) -> 0.40206089 | E22: =IFERROR(E17/E18,0) -> 0.37717725 | F22: =IFERROR(F17/F18,0) -> 0.354793 | G22: =IFERROR(G17/G18,0) -> 0.33456005 | H22: =IFERROR(H17/H18,0) -> 0.32567813 | I22: =IFERROR(I17/I18,0) -> 0.30843368 | J22: =IFERROR(J17/J18,0) -> 0.2926586 | ... AB22: =IFERROR(AB17/AB18,0) -> 0.25429
A25: Payroll Detail
A26: Quarter | B26: Staffing Class | C26: Title / Person | D26: OEWS Title | E26: Starting FTE | F26: Hires | G26: Ending FTE | H26: Average FTE | I26: Annual Wage | J26: Benefits % | K26: Wage Cost | L26: Taxes & Benefits | M26: Total Payroll | N26: Wage Source
A27: 1 | B27: key_person | C27: Chief Executive Officer (CEO) | E27: 1 | F27: 0 | G27: =E27+F27 -> 1 | H27: =(E27+G27)/2 -> 1 | I27: 149770 | J27: 0.22 | K27: =H27*I27/4 -> 37442.5 | L27: =K27*J27 -> 8237.35 | M27: =K27+L27 -> 45679.85 | N27: oews_median
A28: 2 | B28: key_person | C28: Chief Executive Officer (CEO) | E28: 1 | F28: 0 | G28: =E28+F28 -> 1 | H28: =(E28+G28)/2 -> 1 | I28: 149770 | J28: 0.22 | K28: =H28*I28/4 -> 37442.5 | L28: =K28*J28 -> 8237.35 | M28: =K28+L28 -> 45679.85 | N28: oews_median
A29: 3 | B29: key_person | C29: Chief Executive Officer (CEO) | E29: 1 | F29: 0 | G29: =E29+F29 -> 1 | H29: =(E29+G29)/2 -> 1 | I29: 149770 | J29: 0.22 | K29: =H29*I29/4 -> 37442.5 | L29: =K29*J29 -> 8237.35 | M29: =K29+L29 -> 45679.85 | N29: oews_median
A30: 4 | B30: key_person | C30: Chief Executive Officer (CEO) | E30: 1 | F30: 0 | G30: =E30+F30 -> 1 | H30: =(E30+G30)/2 -> 1 | I30: 149770 | J30: 0.22 | K30: =H30*I30/4 -> 37442.5 | L30: =K30*J30 -> 8237.35 | M30: =K30+L30 -> 45679.85 | N30: oews_median
A31: 5 | B31: key_person | C31: Chief Executive Officer (CEO) | E31: 1 | F31: 0 | G31: =E31+F31 -> 1 | H31: =(E31+G31)/2 -> 1 | I31: 154263 | J31: 0.22 | K31: =H31*I31/4 -> 38565.75 | L31: =K31*J31 -> 8484.465 | M31: =K31+L31 -> 47050.215 | N31: oews_median
A32: 6 | B32: key_person | C32: Chief Executive Officer (CEO) | E32: 1 | F32: 0 | G32: =E32+F32 -> 1 | H32: =(E32+G32)/2 -> 1 | I32: 154263 | J32: 0.22 | K32: =H32*I32/4 -> 38565.75 | L32: =K32*J32 -> 8484.465 | M32: =K32+L32 -> 47050.215 | N32: oews_median
A33: 7 | B33: key_person | C33: Chief Executive Officer (CEO) | E33: 1 | F33: 0 | G33: =E33+F33 -> 1 | H33: =(E33+G33)/2 -> 1 | I33: 154263 | J33: 0.22 | K33: =H33*I33/4 -> 38565.75 | L33: =K33*J33 -> 8484.465 | M33: =K33+L33 -> 47050.215 | N33: oews_median
A34: 8 | B34: key_person | C34: Chief Executive Officer (CEO) | E34: 1 | F34: 0 | G34: =E34+F34 -> 1 | H34: =(E34+G34)/2 -> 1 | I34: 154263 | J34: 0.22 | K34: =H34*I34/4 -> 38565.75 | L34: =K34*J34 -> 8484.465 | M34: =K34+L34 -> 47050.215 | N34: oews_median
A35: 9 | B35: key_person | C35: Chief Executive Officer (CEO) | E35: 1 | F35: 0 | G35: =E35+F35 -> 1 | H35: =(E35+G35)/2 -> 1 | I35: 158891 | J35: 0.22 | K35: =H35*I35/4 -> 39722.75 | L35: =K35*J35 -> 8739.005 | M35: =K35+L35 -> 48461.755 | N35: oews_median
A36: 10 | B36: key_person | C36: Chief Executive Officer (CEO) | E36: 1 | F36: 0 | G36: =E36+F36 -> 1 | H36: =(E36+G36)/2 -> 1 | I36: 158891 | J36: 0.22 | K36: =H36*I36/4 -> 39722.75 | L36: =K36*J36 -> 8739.005 | M36: =K36+L36 -> 48461.755 | N36: oews_median
A37: 11 | B37: key_person | C37: Chief Executive Officer (CEO) | E37: 1 | F37: 0 | G37: =E37+F37 -> 1 | H37: =(E37+G37)/2 -> 1 | I37: 158891 | J37: 0.22 | K37: =H37*I37/4 -> 39722.75 | L37: =K37*J37 -> 8739.005 | M37: =K37+L37 -> 48461.755 | N37: oews_median
A38: 12 | B38: key_person | C38: Chief Executive Officer (CEO) | E38: 1 | F38: 0 | G38: =E38+F38 -> 1 | H38: =(E38+G38)/2 -> 1 | I38: 158891 | J38: 0.22 | K38: =H38*I38/4 -> 39722.75 | L38: =K38*J38 -> 8739.005 | M38: =K38+L38 -> 48461.755 | N38: oews_median
... A66: 20 | B66: key_person | C66: Clinical Director | E66: 1 | F66: 0 | G66: =E66+F66 -> 1 | H66: =(E66+G66)/2 -> 1 | I66: 112799 | J66: 0.22 | K66: =H66*I66/4 -> 28199.75 | L66: =K66*J66 -> 6203.945 | M66: =K66+L66 -> 34403.695 | N66: oews_median
A67: 1 | B67: supporting_staff | C67: Registered Nurses | D67: Registered Nurses | E67: 1 | F67: 0 | G67: =E67+F67 -> 1 | H67: =(E67+G67)/2 -> 1 | I67: 98184 | J67: 0.25 | K67: =H67*I67/4 -> 24546 | L67: =K67*J67 -> 6136.5 | M67: =K67+L67 -> 30682.5 | N67: oews_title_catalog:oews_median
A68: 2 | B68: supporting_staff | C68: Registered Nurses | D68: Registered Nurses | E68: 1 | F68: 0 | G68: =E68+F68 -> 1 | H68: =(E68+G68)/2 -> 1 | I68: 98184 | J68: 0.25 | K68: =H68*I68/4 -> 24546 | L68: =K68*J68 -> 6136.5 | M68: =K68+L68 -> 30682.5 | N68: oews_title_catalog:oews_median
A69: 3 | B69: supporting_staff | C69: Registered Nurses | D69: Registered Nurses | E69: 1 | F69: 0 | G69: =E69+F69 -> 1 | H69: =(E69+G69)/2 -> 1 | I69: 98184 | J69: 0.25 | K69: =H69*I69/4 -> 24546 | L69: =K69*J69 -> 6136.5 | M69: =K69+L69 -> 30682.5 | N69: oews_title_catalog:oews_median
A70: 4 | B70: supporting_staff | C70: Registered Nurses | D70: Registered Nurses | E70: 1 | F70: 0 | G70: =E70+F70 -> 1 | H70: =(E70+G70)/2 -> 1 | I70: 98184 | J70: 0.25 | K70: =H70*I70/4 -> 24546 | L70: =K70*J70 -> 6136.5 | M70: =K70+L70 -> 30682.5 | N70: oews_title_catalog:oews_median
A71: 5 | B71: supporting_staff | C71: Registered Nurses | D71: Registered Nurses | E71: 1 | F71: 0 | G71: =E71+F71 -> 1 | H71: =(E71+G71)/2 -> 1 | I71: 101130 | J71: 0.25 | K71: =H71*I71/4 -> 25282.5 | L71: =K71*J71 -> 6320.625 | M71: =K71+L71 -> 31603.125 | N71: oews_title_catalog:oews_median
A72: 6 | B72: supporting_staff | C72: Registered Nurses | D72: Registered Nurses | E72: 1 | F72: 0 | G72: =E72+F72 -> 1 | H72: =(E72+G72)/2 -> 1 | I72: 101130 | J72: 0.25 | K72: =H72*I72/4 -> 25282.5 | L72: =K72*J72 -> 6320.625 | M72: =K72+L72 -> 31603.125 | N72: oews_title_catalog:oews_median
A73: 7 | B73: supporting_staff | C73: Registered Nurses | D73: Registered Nurses | E73: 1 | F73: 0 | G73: =E73+F73 -> 1 | H73: =(E73+G73)/2 -> 1 | I73: 101130 | J73: 0.25 | K73: =H73*I73/4 -> 25282.5 | L73: =K73*J73 -> 6320.625 | M73: =K73+L73 -> 31603.125 | N73: oews_title_catalog:oews_median
A74: 8 | B74: supporting_staff | C74: Registered Nurses | D74: Registered Nurses | E74: 1 | F74: 0 | G74: =E74+F74 -> 1 | H74: =(E74+G74)/2 -> 1 | I74: 101130 | J74: 0.25 | K74: =H74*I74/4 -> 25282.5 | L74: =K74*J74 -> 6320.625 | M74: =K74+L74 -> 31603.125 | N74: oews_title_catalog:oews_median
A75: 9 | B75: supporting_staff | C75: Registered Nurses | D75: Registered Nurses | E75: 1 | F75: 0 | G75: =E75+F75 -> 1 | H75: =(E75+G75)/2 -> 1 | I75: 104163 | J75: 0.25 | K75: =H75*I75/4 -> 26040.75 | L75: =K75*J75 -> 6510.1875 | M75: =K75+L75 -> 32550.938 | N75: oews_title_catalog:oews_median
A76: 10 | B76: supporting_staff | C76: Registered Nurses | D76: Registered Nurses | E76: 1 | F76: 0 | G76: =E76+F76 -> 1 | H76: =(E76+G76)/2 -> 1 | I76: 104163 | J76: 0.25 | K76: =H76*I76/4 -> 26040.75 | L76: =K76*J76 -> 6510.1875 | M76: =K76+L76 -> 32550.938 | N76: oews_title_catalog:oews_median
A77: 11 | B77: supporting_staff | C77: Registered Nurses | D77: Registered Nurses | E77: 1 | F77: 0 | G77: =E77+F77 -> 1 | H77: =(E77+G77)/2 -> 1 | I77: 104163 | J77: 0.25 | K77: =H77*I77/4 -> 26040.75 | L77: =K77*J77 -> 6510.1875 | M77: =K77+L77 -> 32550.938 | N77: oews_title_catalog:oews_median
A78: 12 | B78: supporting_staff | C78: Registered Nurses | D78: Registered Nurses | E78: 1 | F78: 0 | G78: =E78+F78 -> 1 | H78: =(E78+G78)/2 -> 1 | I78: 104163 | J78: 0.25 | K78: =H78*I78/4 -> 26040.75 | L78: =K78*J78 -> 6510.1875 | M78: =K78+L78 -> 32550.938 | N78: oews_title_catalog:oews_median
... A86: 20 | B86: supporting_staff | C86: Registered Nurses | D86: Registered Nurses | E86: 1 | F86: 0 | G86: =E86+F86 -> 1 | H86: =(E86+G86)/2 -> 1 | I86: 110507 | J86: 0.25 | K86: =H86*I86/4 -> 27626.75 | L86: =K86*J86 -> 6906.6875 | M86: =K86+L86 -> 34533.438 | N86: oews_title_catalog:oews_median

Sheet Debt Schedule
A1: Debt Schedule
A2: Debt, interest, and capital lease mechanics. Model Inputs links to calculated outputs.
C4: Stub | D4: Q1 | E4: Q2 | F4: Q3 | G4: Q4 | H4: Q5 | I4: Q6 | J4: Q7 | K4: Q8 | L4: Q9 | M4: Q10 | N4: Q11 | O4: Q12 | P4: Q13 | Q4: Q14 | R4: Q15 | S4: Q16 | T4: Q17 | U4: Q18 | V4: Q19 | W4: Q20 | X4: Y1 | Y4: Y2 | Z4: Y3 | AA4: Y4 | AB4: Y5
C5: 46162 | D5: 46295 | E5: 46387 | F5: 46477 | G5: 46568 | H5: 46660 | I5: 46752 | J5: 46843 | K5: 46934 | L5: 47026 | M5: 47118 | N5: 47208 | O5: 47299 | P5: 47391 | Q5: 47483 | R5: 47573 | S5: 47664 | T5: 47756 | U5: 47848 | V5: 47938 | W5: 48029 | X5: Annual | Y5: Annual | Z5: Annual | AA5: Annual | AB5: Annual
A6: Debt Amortization
A7: Opening Debt | B7: Calculated | C7: 30000 | D7: =C11 -> 30000 | E7: =D11 -> 28500 | F7: =E11 -> 27000 | G7: =F11 -> 25500 | H7: =G11 -> 24000 | I7: =H11 -> 22500 | J7: =I11 -> 21000 | K7: =J11 -> 19500 | ... W7: =V11 -> 1500 | X7: =G7 -> 25500 | Y7: =K7 -> 19500 | Z7: =O7 -> 13500 | AA7: =S7 -> 7500 | AB7: =W7 -> 1500
A8: Debt Issuance | B8: Source borrowing | C8: 0 | D8: 0 | E8: 0 | F8: 0 | G8: 0 | H8: 0 | I8: 0 | J8: 0 | K8: 0 | L8: 0 | M8: 0 | N8: 0 | O8: 0 | P8: 0 | Q8: 0 | R8: 0 | S8: 0 | T8: 0 | U8: 0 | V8: 0 | W8: 0 | X8: =SUM(D8:G8) -> 0 | Y8: =SUM(H8:K8) -> 0 | Z8: =SUM(L8:O8) -> 0 | AA8: =SUM(P8:S8) -> 0 | AB8: =SUM(T8:W8) -> 0
A9: Requested Debt Repayment | B9: Source scheduled repayment | C9: 0 | D9: 1500 | E9: 1500 | F9: 1500 | G9: 1500 | H9: 1500 | I9: 1500 | J9: 1500 | K9: 1500 | L9: 1500 | M9: 1500 | N9: 1500 | O9: 1500 | P9: 1500 | Q9: 1500 | R9: 1500 | S9: 1500 | T9: 1500 | U9: 1500 | V9: 1500 | W9: 1500 | X9: =SUM(D9:G9) -> 6000 | Y9: =SUM(H9:K9) -> 6000 | Z9: =SUM(L9:O9) -> 6000 | AA9: =SUM(P9:S9) -> 6000 | AB9: =SUM(T9:W9) -> 6000
A10: Actual Debt Repayment | B10: MIN(requested repayment, opening debt + issuance) | C10: =MIN(C9,C7+C8) -> 0 | D10: =MIN(D9,D7+D8) -> 1500 | E10: =MIN(E9,E7+E8) -> 1500 | F10: =MIN(F9,F7+F8) -> 1500 | G10: =MIN(G9,G7+G8) -> 1500 | H10: =MIN(H9,H7+H8) -> 1500 | I10: =MIN(I9,I7+I8) -> 1500 | J10: =MIN(J9,J7+J8) -> 1500 | ... W10: =MIN(W9,W7+W8) -> 1500 | X10: =SUM(D10:G10) -> 6000 | Y10: =SUM(H10:K10) -> 6000 | Z10: =SUM(L10:O10) -> 6000 | AA10: =SUM(P10:S10) -> 6000 | AB10: =SUM(T10:W10) -> 6000
A11: Closing Debt | B11: Calculated | C11: =MAX(0,C7+C8-C10) -> 30000 | D11: =MAX(0,D7+D8-D10) -> 28500 | E11: =MAX(0,E7+E8-E10) -> 27000 | F11: =MAX(0,F7+F8-F10) -> 25500 | G11: =MAX(0,G7+G8-G10) -> 24000 | H11: =MAX(0,H7+H8-H10) -> 22500 | I11: =MAX(0,I7+I8-I10) -> 21000 | J11: =MAX(0,J7+J8-J10) -> 19500 | ... W11: =MAX(0,W7+W8-W10) -> 0 | X11: =G11 -> 24000 | Y11: =K11 -> 18000 | Z11: =O11 -> 12000 | AA11: =S11 -> 6000 | AB11: =W11 -> 0
A12: Interest Rate | B12: Source rate | C12: 0.01 | D12: 0.025 | E12: 0.025 | F12: 0.025 | G12: 0.025 | H12: 0.025 | I12: 0.025 | J12: 0.025 | K12: 0.025 | L12: 0.025 | M12: 0.025 | N12: 0.025 | O12: 0.025 | P12: 0.025 | Q12: 0.025 | R12: 0.025 | S12: 0.025 | T12: 0.025 | U12: 0.025 | V12: 0.025 | W12: 0.025 | X12: =SUM(D12:G12) -> 0.1 | Y12: =SUM(H12:K12) -> 0.1 | Z12: =SUM(L12:O12) -> 0.1 | AA12: =SUM(P12:S12) -> 0.1 | AB12: =SUM(T12:W12) -> 0.1
A13: Interest Expense | B13: Average debt balance x rate | C13: =((C7+C11)/2)*C12 -> 300 | D13: =((D7+D11)/2)*D12 -> 731.25 | E13: =((E7+E11)/2)*E12 -> 693.75 | F13: =((F7+F11)/2)*F12 -> 656.25 | G13: =((G7+G11)/2)*G12 -> 618.75 | H13: =((H7+H11)/2)*H12 -> 581.25 | I13: =((I7+I11)/2)*I12 -> 543.75 | J13: =((J7+J11)/2)*J12 -> 506.25 | ... W13: =((W7+W11)/2)*W12 -> 18.75 | X13: =SUM(D13:G13) -> 2700 | Y13: =SUM(H13:K13) -> 2100 | Z13: =SUM(L13:O13) -> 1500 | AA13: =SUM(P13:S13) -> 900 | AB13: =SUM(T13:W13) -> 300
A14: Total Debt Service | B14: Interest + actual repayment | C14: =C13+C10 -> 300 | D14: =D13+D10 -> 2231.25 | E14: =E13+E10 -> 2193.75 | F14: =F13+F10 -> 2156.25 | G14: =G13+G10 -> 2118.75 | H14: =H13+H10 -> 2081.25 | I14: =I13+I10 -> 2043.75 | J14: =J13+J10 -> 2006.25 | ... W14: =W13+W10 -> 1518.75 | X14: =SUM(D14:G14) -> 8700 | Y14: =SUM(H14:K14) -> 8100 | Z14: =SUM(L14:O14) -> 7500 | AA14: =SUM(P14:S14) -> 6900 | AB14: =SUM(T14:W14) -> 6300
A17: Capital Lease Schedule
A18: Lease Opening Balance | B18: Capital leases | C18: 0 | D18: =C23 -> 0 | E18: =D23 -> 0 | F18: =E23 -> 0 | G18: =F23 -> 0 | H18: =G23 -> 0 | I18: =H23 -> 0 | J18: =I23 -> 0 | K18: =J23 -> 0 | ... W18: =V23 -> 0 | X18: =G18 -> 0 | Y18: =K18 -> 0 | Z18: =O18 -> 0 | AA18: =S18 -> 0 | AB18: =W18 -> 0
A19: Requested Lease Principal Repayments | B19: Capital leases | C19: 0 | D19: 2000 | E19: 2000 | F19: 2000 | G19: 2000 | H19: 2000 | I19: 2000 | J19: 2000 | K19: 2000 | L19: 2000 | M19: 2000 | N19: 2000 | O19: 2000 | P19: 2000 | Q19: 2000 | R19: 2000 | S19: 2000 | T19: 2000 | U19: 2000 | V19: 2000 | W19: 2000 | X19: =SUM(D19:G19) -> 8000 | Y19: =SUM(H19:K19) -> 8000 | Z19: =SUM(L19:O19) -> 8000 | AA19: =SUM(P19:S19) -> 8000 | AB19: =SUM(T19:W19) -> 8000
A20: Lease Principal Repayments | B20: Capital leases | C20: =MIN(C19,C18+C21) -> 0 | D20: =MIN(D19,D18+D21) -> 0 | E20: =MIN(E19,E18+E21) -> 0 | F20: =MIN(F19,F18+F21) -> 0 | G20: =MIN(G19,G18+G21) -> 0 | H20: =MIN(H19,H18+H21) -> 0 | I20: =MIN(I19,I18+I21) -> 0 | J20: =MIN(J19,J18+J21) -> 0 | ... W20: =MIN(W19,W18+W21) -> 0 | X20: =SUM(D20:G20) -> 0 | Y20: =SUM(H20:K20) -> 0 | Z20: =SUM(L20:O20) -> 0 | AA20: =SUM(P20:S20) -> 0 | AB20: =SUM(T20:W20) -> 0
A21: Lease Net Additions | B21: Capital leases | C21: 0 | D21: 0 | E21: 0 | F21: 0 | G21: 0 | H21: 0 | I21: 0 | J21: 0 | K21: 0 | L21: 0 | M21: 0 | N21: 0 | O21: 0 | P21: 0 | Q21: 0 | R21: 0 | S21: 0 | T21: 0 | U21: 0 | V21: 0 | W21: 0 | X21: =SUM(D21:G21) -> 0 | Y21: =SUM(H21:K21) -> 0 | Z21: =SUM(L21:O21) -> 0 | AA21: =SUM(P21:S21) -> 0 | AB21: =SUM(T21:W21) -> 0
A22: Lease Interest Expense | B22: Capital leases | C22: 0 | D22: =D18*D12 -> 0 | E22: =E18*E12 -> 0 | F22: =F18*F12 -> 0 | G22: =G18*G12 -> 0 | H22: =H18*H12 -> 0 | I22: =I18*I12 -> 0 | J22: =J18*J12 -> 0 | K22: =K18*K12 -> 0 | ... W22: =W18*W12 -> 0 | X22: =SUM(D22:G22) -> 0 | Y22: =SUM(H22:K22) -> 0 | Z22: =SUM(L22:O22) -> 0 | AA22: =SUM(P22:S22) -> 0 | AB22: =SUM(T22:W22) -> 0
A23: Lease Closing Balance | B23: Capital leases | C23: =MAX(0,C18+C21-C20) -> 0 | D23: =MAX(0,D18+D21-D20) -> 0 | E23: =MAX(0,E18+E21-E20) -> 0 | F23: =MAX(0,F18+F21-F20) -> 0 | G23: =MAX(0,G18+G21-G20) -> 0 | H23: =MAX(0,H18+H21-H20) -> 0 | I23: =MAX(0,I18+I21-I20) -> 0 | J23: =MAX(0,J18+J21-J20) -> 0 | ... W23: =MAX(0,W18+W21-W20) -> 0 | X23: =G23 -> 0 | Y23: =K23 -> 0 | Z23: =O23 -> 0 | AA23: =S23 -> 0 | AB23: =W23 -> 0
A24: Right-of-Use Asset Opening | B24: Capital leases | C24: 0 | D24: =C26 -> 0 | E24: =D26 -> 0 | F24: =E26 -> 0 | G24: =F26 -> 0 | H24: =G26 -> 0 | I24: =H26 -> 0 | J24: =I26 -> 0 | K24: =J26 -> 0 | ... W24: =V26 -> 0 | X24: =G24 -> 0 | Y24: =K24 -> 0 | Z24: =O24 -> 0 | AA24: =S24 -> 0 | AB24: =W24 -> 0
A25: Lease Asset Depreciation | B25: Capital leases | C25: 0 | D25: =MIN((C18/20),D24) -> 0 | E25: =MIN((C18/20),E24) -> 0 | F25: =MIN((C18/20),F24) -> 0 | G25: =MIN((C18/20),G24) -> 0 | H25: =MIN((C18/20),H24) -> 0 | I25: =MIN((C18/20),I24) -> 0 | J25: =MIN((C18/20),J24) -> 0 | K25: =MIN((C18/20),K24) -> 0 | L25: =MIN((C18/20),L24) -> 0 | M25: =MIN((C18/20),M24) -> 0 | N25: =MIN((C18/20),N24) -> 0 | O25: =MIN((C18/20),O24) -> 0 | P25: =MIN((C18/20),P24) -> 0 | Q25: =MIN((C18/20),Q24) -> 0 | R25: =MIN((C18/20),R24) -> 0 | S25: =MIN((C18/20),S24) -> 0 | T25: =MIN((C18/20),T24) -> 0 | U25: =MIN((C18/20),U24) -> 0 | V25: =MIN((C18/20),V24) -> 0 | W25: =MIN((C18/20),W24) -> 0 | X25: =SUM(D25:G25) -> 0 | Y25: =SUM(H25:K25) -> 0 | Z25: =SUM(L25:O25) -> 0 | AA25: =SUM(P25:S25) -> 0 | AB25: =SUM(T25:W25) -> 0
A26: Right-of-Use Asset Closing | B26: Capital leases | C26: =MAX(0,C24-C25) -> 0 | D26: =MAX(0,D24-D25) -> 0 | E26: =MAX(0,E24-E25) -> 0 | F26: =MAX(0,F24-F25) -> 0 | G26: =MAX(0,G24-G25) -> 0 | H26: =MAX(0,H24-H25) -> 0 | I26: =MAX(0,I24-I25) -> 0 | J26: =MAX(0,J24-J25) -> 0 | ... W26: =MAX(0,W24-W25) -> 0 | X26: =G26 -> 0 | Y26: =K26 -> 0 | Z26: =O26 -> 0 | AA26: =S26 -> 0 | AB26: =W26 -> 0

Sheet CapEx Depreciation
A1: CapEx & Depreciation Schedule
A2: Capital expenditure and depreciation mechanics. Model Inputs links to calculated outputs.
C4: Stub | D4: Q1 | E4: Q2 | F4: Q3 | G4: Q4 | H4: Q5 | I4: Q6 | J4: Q7 | K4: Q8 | L4: Q9 | M4: Q10 | N4: Q11 | O4: Q12 | P4: Q13 | Q4: Q14 | R4: Q15 | S4: Q16 | T4: Q17 | U4: Q18 | V4: Q19 | W4: Q20 | X4: Y1 | Y4: Y2 | Z4: Y3 | AA4: Y4 | AB4: Y5
C5: 46162 | D5: 46295 | E5: 46387 | F5: 46477 | G5: 46568 | H5: 46660 | I5: 46752 | J5: 46843 | K5: 46934 | L5: 47026 | M5: 47118 | N5: 47208 | O5: 47299 | P5: 47391 | Q5: 47483 | R5: 47573 | S5: 47664 | T5: 47756 | U5: 47848 | V5: 47938 | W5: 48029 | X5: Annual | Y5: Annual | Z5: Annual | AA5: Annual | AB5: Annual
A6: PPE and Depreciation
A7: Opening PPE | B7: Calculated | C7: 40000 | D7: =C12 -> 40000 | E7: =D12 -> 40190 | F7: =E12 -> 40370.895 | G7: =F12 -> 40542.593 | H7: =G12 -> 40705.047 | I7: =H12 -> 40858.138 | J7: =I12 -> 41001.755 | K7: =J12 -> 41135.831 | ... W7: =V12 -> 41973.955 | X7: =G7 -> 40542.593 | Y7: =K7 -> 41135.831 | Z7: =O7 -> 41575.259 | AA7: =S7 -> 41856.096 | AB7: =W7 -> 41973.955
A8: Capital Expenditures | B8: Schedule source | C8: 0 | D8: 200 | E8: 200.95 | F8: 201.85448 | G8: 202.71296 | H8: 203.52523 | I8: 204.29069 | J8: 205.00877 | K8: 205.67915 | L8: 206.30154 | M8: 206.87547 | N8: 207.40052 | O8: 207.87629 | P8: 208.30265 | Q8: 208.67905 | R8: 209.00501 | S8: 209.28048 | T8: 209.50504 | U8: 209.6783 | V8: 209.79991 | W8: 209.86977 | X8: =SUM(D8:G8) -> 805.51744 | Y8: =SUM(H8:K8) -> 818.50385 | Z8: =SUM(L8:O8) -> 828.45382 | AA8: =SUM(P8:S8) -> 835.26719 | AB8: =SUM(T8:W8) -> 838.85302
A9: Lease Additions | B9: Schedule source | C9: 0 | D9: ='Debt Schedule'!D21 -> 0 | E9: ='Debt Schedule'!E21 -> 0 | F9: ='Debt Schedule'!F21 -> 0 | G9: ='Debt Schedule'!G21 -> 0 | H9: ='Debt Schedule'!H21 -> 0 | I9: ='Debt Schedule'!I21 -> 0 | J9: ='Debt Schedule'!J21 -> 0 | K9: ='Debt Schedule'!K21 -> 0 | ... W9: ='Debt Schedule'!W21 -> 0 | X9: =SUM(D9:G9) -> 0 | Y9: =SUM(H9:K9) -> 0 | Z9: =SUM(L9:O9) -> 0 | AA9: =SUM(P9:S9) -> 0 | AB9: =SUM(T9:W9) -> 0
A10: Depreciation Rate | B10: Schedule source | C10: 0 | D10: 0.00025 | E10: 0.000499 | F10: 0.000747 | G10: 0.000993 | H10: 0.001239 | I10: 0.001485 | J10: 0.00173 | K10: 0.001974 | L10: 0.002218 | M10: 0.002462 | N10: 0.002706 | O10: 0.002949 | P10: 0.003193 | Q10: 0.003438 | R10: 0.003682 | S10: 0.003927 | T10: 0.004173 | U10: 0.00442 | V10: 0.004667 | W10: 0.004916 | X10: =SUM(D10:G10) -> 0.002489 | Y10: =SUM(H10:K10) -> 0.006428 | Z10: =SUM(L10:O10) -> 0.010335 | AA10: =SUM(P10:S10) -> 0.01424 | AB10: =SUM(T10:W10) -> 0.018176
A11: Depreciation Expense | B11: Calculated | C11: =MIN(C7*C10,C7) -> 0 | D11: =MIN(D7*D10,D7) -> 10 | E11: =MIN(E7*E10,E7) -> 20.05481 | F11: =MIN(F7*F10,F7) -> 30.157059 | G11: =MIN(G7*G10,G7) -> 40.258794 | H11: =MIN(H7*H10,H7) -> 50.433553 | I11: =MIN(I7*I10,I7) -> 60.674336 | J11: =MIN(J7*J10,J7) -> 70.933036 | ... W11: =MIN(W7*W10,W7) -> 206.34396 | X11: =SUM(D11:G11) -> 100.47066 | Y11: =SUM(H11:K11) -> 263.24305 | Z11: =SUM(L11:O11) -> 428.23144 | AA11: =SUM(P11:S11) -> 594.78996 | AB11: =SUM(T11:W11) -> 762.37971
A12: Closing PPE | B12: Calculated | C12: =MAX(0,C7+C8+C9-C11) -> 40000 | D12: =MAX(0,D7+D8+D9-D11) -> 40190 | E12: =MAX(0,E7+E8+E9-E11) -> 40370.895 | F12: =MAX(0,F7+F8+F9-F11) -> 40542.593 | G12: =MAX(0,G7+G8+G9-G11) -> 40705.047 | H12: =MAX(0,H7+H8+H9-H11) -> 40858.138 | I12: =MAX(0,I7+I8+I9-I11) -> 41001.755 | J12: =MAX(0,J7+J8+J9-J11) -> 41135.831 | ... W12: =MAX(0,W7+W8+W9-W11) -> 41977.48 | X12: =G12 -> 40705.047 | Y12: =K12 -> 41260.308 | Z12: =O12 -> 41660.53 | AA12: =S12 -> 41901.007 | AB12: =W12 -> 41977.48
A13: Opening Accumulated Depreciation | B13: Calculated | C13: 0 | D13: =C14 -> 0 | E13: =D14 -> -10 | F13: =E14 -> -30.05481 | G13: =F14 -> -60.211869 | H13: =G14 -> -100.47066 | I13: =H14 -> -150.90422 | J13: =I14 -> -211.57855 | K13: =J14 -> -282.51159 | ... W13: =V14 -> -1942.7709 | X13: =G13 -> -60.211869 | Y13: =K13 -> -282.51159 | Z13: =O13 -> -669.33972 | AA13: =S13 -> -1222.3662 | AB13: =W13 -> -1942.7709
A14: Accumulated Depreciation | B14: Calculated | C14: =C13-C11 -> 0 | D14: =D13-D11 -> -10 | E14: =E13-E11 -> -30.05481 | F14: =F13-F11 -> -60.211869 | G14: =G13-G11 -> -100.47066 | H14: =H13-H11 -> -150.90422 | I14: =I13-I11 -> -211.57855 | J14: =J13-J11 -> -282.51159 | ... W14: =W13-W11 -> -2149.1148 | X14: =G14 -> -100.47066 | Y14: =K14 -> -363.71372 | Z14: =O14 -> -791.94516 | AA14: =S14 -> -1386.7351 | AB14: =W14 -> -2149.1148

Sheet Working Capital
A1: Working Capital Schedule
A2: Working-capital drivers. Model Inputs links to these source rows.
C4: Stub | D4: Q1 | E4: Q2 | F4: Q3 | G4: Q4 | H4: Q5 | I4: Q6 | J4: Q7 | K4: Q8 | L4: Q9 | M4: Q10 | N4: Q11 | O4: Q12 | P4: Q13 | Q4: Q14 | R4: Q15 | S4: Q16 | T4: Q17 | U4: Q18 | V4: Q19 | W4: Q20 | X4: Y1 | Y4: Y2 | Z4: Y3 | AA4: Y4 | AB4: Y5
C5: 46162 | D5: 46295 | E5: 46387 | F5: 46477 | G5: 46568 | H5: 46660 | I5: 46752 | J5: 46843 | K5: 46934 | L5: 47026 | M5: 47118 | N5: 47208 | O5: 47299 | P5: 47391 | Q5: 47483 | R5: 47573 | S5: 47664 | T5: 47756 | U5: 47848 | V5: 47938 | W5: 48029 | X5: Annual | Y5: Annual | Z5: Annual | AA5: Annual | AB5: Annual
A6: Working Capital Drivers
A7: Accounts Receivable Days | B7: Working capital driver | C7: 0 | D7: 30 | E7: 30 | F7: 30 | G7: 30 | H7: 30 | I7: 30 | J7: 30 | K7: 30 | L7: 30 | M7: 30 | N7: 30 | O7: 30 | P7: 30 | Q7: 30 | R7: 30 | S7: 30 | T7: 30 | U7: 30 | V7: 30 | W7: 30
A8: Inventory Days | B8: Working capital driver | C8: 0 | D8: 0 | E8: 0 | F8: 0 | G8: 0 | H8: 0 | I8: 0 | J8: 0 | K8: 0 | L8: 0 | M8: 0 | N8: 0 | O8: 0 | P8: 0 | Q8: 0 | R8: 0 | S8: 0 | T8: 0 | U8: 0 | V8: 0 | W8: 0
A9: Accounts Payable Days | B9: Working capital driver | C9: 0 | D9: 30 | E9: 30 | F9: 30 | G9: 30 | H9: 30 | I9: 30 | J9: 30 | K9: 30 | L9: 30 | M9: 30 | N9: 30 | O9: 30 | P9: 30 | Q9: 30 | R9: 30 | S9: 30 | T9: 30 | U9: 30 | V9: 30 | W9: 30
A10: Prepaid Expenses (% of Revenue) | B10: Working capital driver | C10: 0 | D10: 5 | E10: 5 | F10: 5 | G10: 5 | H10: 5 | I10: 5 | J10: 5 | K10: 5 | L10: 5 | M10: 5 | N10: 5 | O10: 5 | P10: 5 | Q10: 5 | R10: 5 | S10: 5 | T10: 5 | U10: 5 | V10: 5 | W10: 5
A11: Deferred Revenue (% of Revenue) | B11: Working capital driver | C11: 0 | D11: 0 | E11: 0 | F11: 0 | G11: 0 | H11: 0 | I11: 0 | J11: 0 | K11: 0 | L11: 0 | M11: 0 | N11: 0 | O11: 0 | P11: 0 | Q11: 0 | R11: 0 | S11: 0 | T11: 0 | U11: 0 | V11: 0 | W11: 0
A12: Short Term Debt (% of LTD) | B12: Working capital driver | C12: 0 | D12: 0 | E12: 0 | F12: 0 | G12: 0 | H12: 0 | I12: 0 | J12: 0 | K12: 0 | L12: 0 | M12: 0 | N12: 0 | O12: 0 | P12: 0 | Q12: 0 | R12: 0 | S12: 0 | T12: 0 | U12: 0 | V12: 0 | W12: 0
A14: Opening Working Capital Seeds
A15: Cash Opening Balance | B15: Opening balance seed | C15: 12000 | D15: 0 | E15: 0 | F15: 0 | G15: 0 | H15: 0 | I15: 0 | J15: 0 | K15: 0 | L15: 0 | M15: 0 | N15: 0 | O15: 0 | P15: 0 | Q15: 0 | R15: 0 | S15: 0 | T15: 0 | U15: 0 | V15: 0 | W15: 0
A16: Accounts Receivable Opening Balance | B16: Opening balance seed | C16: 0 | D16: 0 | E16: 0 | F16: 0 | G16: 0 | H16: 0 | I16: 0 | J16: 0 | K16: 0 | L16: 0 | M16: 0 | N16: 0 | O16: 0 | P16: 0 | Q16: 0 | R16: 0 | S16: 0 | T16: 0 | U16: 0 | V16: 0 | W16: 0
A17: Inventory Opening Balance | B17: Opening balance seed | C17: 0 | D17: 0 | E17: 0 | F17: 0 | G17: 0 | H17: 0 | I17: 0 | J17: 0 | K17: 0 | L17: 0 | M17: 0 | N17: 0 | O17: 0 | P17: 0 | Q17: 0 | R17: 0 | S17: 0 | T17: 0 | U17: 0 | V17: 0 | W17: 0
A18: Accounts Payable Opening Balance | B18: Opening balance seed | C18: 4000 | D18: 0 | E18: 0 | F18: 0 | G18: 0 | H18: 0 | I18: 0 | J18: 0 | K18: 0 | L18: 0 | M18: 0 | N18: 0 | O18: 0 | P18: 0 | Q18: 0 | R18: 0 | S18: 0 | T18: 0 | U18: 0 | V18: 0 | W18: 0
A19: Short Term Debt Opening Balance | B19: Opening balance seed | C19: 0 | D19: 0 | E19: 0 | F19: 0 | G19: 0 | H19: 0 | I19: 0 | J19: 0 | K19: 0 | L19: 0 | M19: 0 | N19: 0 | O19: 0 | P19: 0 | Q19: 0 | R19: 0 | S19: 0 | T19: 0 | U19: 0 | V19: 0 | W19: 0

Sheet Cash Equity Schedule
A1: Cash & Equity Schedule
A2: Equity, distributions, lease/rent, and opening cash seeds. Model Inputs links to these rows.
C4: Stub | D4: Q1 | E4: Q2 | F4: Q3 | G4: Q4 | H4: Q5 | I4: Q6 | J4: Q7 | K4: Q8 | L4: Q9 | M4: Q10 | N4: Q11 | O4: Q12 | P4: Q13 | Q4: Q14 | R4: Q15 | S4: Q16 | T4: Q17 | U4: Q18 | V4: Q19 | W4: Q20 | X4: Y1 | Y4: Y2 | Z4: Y3 | AA4: Y4 | AB4: Y5
C5: 46162 | D5: 46295 | E5: 46387 | F5: 46477 | G5: 46568 | H5: 46660 | I5: 46752 | J5: 46843 | K5: 46934 | L5: 47026 | M5: 47118 | N5: 47208 | O5: 47299 | P5: 47391 | Q5: 47483 | R5: 47573 | S5: 47664 | T5: 47756 | U5: 47848 | V5: 47938 | W5: 48029 | X5: Annual | Y5: Annual | Z5: Annual | AA5: Annual | AB5: Annual
A6: Equity and Distributions
A7: Owner's Capital | B7: Equity / distribution input | C7: 45000 | D7: 46229083 | E7: 78731191 | F7: 110631979 | G7: 141884050 | H7: 172083847 | I7: 200913067 | J7: 228094164 | K7: 253394736 | L7: 276500513 | M7: 297047509 | N7: 314722680 | O7: 332761977 | P7: 350530836 | Q7: 368013828 | R7: 385201629 | S7: 402128145 | T7: 418770617 | U7: 435114802 | V7: 451152836 | W7: 466911700
A8: Other Equity | B8: Equity / distribution input | C8: 0 | D8: 0 | E8: 0 | F8: 0 | G8: 0 | H8: 0 | I8: 0 | J8: 0 | K8: 0 | L8: 0 | M8: 0 | N8: 0 | O8: 0 | P8: 0 | Q8: 0 | R8: 0 | S8: 0 | T8: 0 | U8: 0 | V8: 0 | W8: 0
A9: Distributions | B9: Equity / distribution input | C9: 0 | D9: 0 | E9: 0 | F9: 0 | G9: 0 | H9: 0 | I9: 0 | J9: 0 | K9: 0 | L9: 0 | M9: 0 | N9: 0 | O9: 0 | P9: 0 | Q9: 0 | R9: 0 | S9: 0 | T9: 0 | U9: 0 | V9: 0 | W9: 0
A11: Operating Fixed Cash Items
A12: Lease | B12: Operating lease/rent input | C12: 7500 | D12: 7500 | E12: 7500 | F12: 7500 | G12: 7500 | H12: 7500 | I12: 7500 | J12: 7500 | K12: 7500 | L12: 7500 | M12: 7500 | N12: 7500 | O12: 7500 | P12: 7500 | Q12: 7500 | R12: 7500 | S12: 7500 | T12: 7500 | U12: 7500 | V12: 7500 | W12: 7500

Sheet Model Inputs
A1: Model Inputs
A2: Formula-driven bridge from schedules into FINMO. FINMO references this sheet only.
C4: Stub | D4: Q1 | E4: Q2 | F4: Q3 | G4: Q4 | H4: Q5 | I4: Q6 | J4: Q7 | K4: Q8 | L4: Q9 | M4: Q10 | N4: Q11 | O4: Q12 | P4: Q13 | Q4: Q14 | R4: Q15 | S4: Q16 | T4: Q17 | U4: Q18 | V4: Q19 | W4: Q20 | X4: Y1 | Y4: Y2 | Z4: Y3 | AA4: Y4 | AB4: Y5
C5: 46162 | D5: 46295 | E5: 46387 | F5: 46477 | G5: 46568 | H5: 46660 | I5: 46752 | J5: 46843 | K5: 46934 | L5: 47026 | M5: 47118 | N5: 47208 | O5: 47299 | P5: 47391 | Q5: 47483 | R5: 47573 | S5: 47664 | T5: 47756 | U5: 47848 | V5: 47938 | W5: 48029 | X5: Annual | Y5: Annual | Z5: Annual | AA5: Annual | AB5: Annual
A6: Income Statement Inputs
A7: Primary line of business / Billable home visit - Capacity | B7: Revenue Drivers schedule | C7: ='Revenue Drivers'!C8 -> 1040 | D7: ='Revenue Drivers'!D8 -> 2364.03 | E7: ='Revenue Drivers'!E8 -> 2364.03 | F7: ='Revenue Drivers'!F8 -> 2364.03 | G7: ='Revenue Drivers'!G8 -> 2364.03 | H7: ='Revenue Drivers'!H8 -> 2364.03 | I7: ='Revenue Drivers'!I8 -> 2364.03 | J7: ='Revenue Drivers'!J8 -> 2364.03 | ... W7: ='Revenue Drivers'!W8 -> 2364.03 | X7: =SUM(D7:G7) -> 9456.12 | Y7: =SUM(H7:K7) -> 9456.12 | Z7: =SUM(L7:O7) -> 9456.12 | AA7: =SUM(P7:S7) -> 9456.12 | AB7: =SUM(T7:W7) -> 9456.12
A8: Primary line of business / Billable home visit - Unit Price | B8: Revenue Drivers schedule | C8: ='Revenue Drivers'!C9 -> 150 | D8: ='Revenue Drivers'!D9 -> 150 | E8: ='Revenue Drivers'!E9 -> 158 | F8: ='Revenue Drivers'!F9 -> 166 | G8: ='Revenue Drivers'!G9 -> 174 | H8: ='Revenue Drivers'!H9 -> 182 | I8: ='Revenue Drivers'!I9 -> 190 | J8: ='Revenue Drivers'!J9 -> 198 | ... W8: ='Revenue Drivers'!W9 -> 240 | X8: =SUM(D8:G8) -> 648 | Y8: =SUM(H8:K8) -> 776 | Z8: =SUM(L8:O8) -> 897.11111 | AA8: =SUM(P8:S8) -> 935.55556 | AB8: =SUM(T8:W8) -> 953.33333
A9: Primary line of business / Billable home visit - Utilization | B9: Revenue Drivers schedule | C9: ='Revenue Drivers'!C10 -> 0.75 | D9: ='Revenue Drivers'!D10 -> 0.75 | E9: ='Revenue Drivers'!E10 -> 0.759 | F9: ='Revenue Drivers'!F10 -> 0.768 | G9: ='Revenue Drivers'!G10 -> 0.777 | H9: ='Revenue Drivers'!H10 -> 0.786 | I9: ='Revenue Drivers'!I10 -> 0.795 | J9: ='Revenue Drivers'!J10 -> 0.804 | ... W9: ='Revenue Drivers'!W10 -> 0.84 | X9: =SUM(D9:G9) -> 3.054 | Y9: =SUM(H9:K9) -> 3.198 | Z9: =SUM(L9:O9) -> 3.333 | AA9: =SUM(P9:S9) -> 3.36 | AB9: =SUM(T9:W9) -> 3.36
A10: Primary line of business / Billable home visit - Revenue | B10: Revenue Drivers schedule | C10: ='Revenue Drivers'!C11 -> 117000 | D10: ='Revenue Drivers'!D11 -> 265953.38 | E10: ='Revenue Drivers'!E11 -> 283499.21 | F10: ='Revenue Drivers'!F11 -> 301385.46 | G10: ='Revenue Drivers'!G11 -> 319612.13 | H10: ='Revenue Drivers'!H11 -> 338179.22 | I10: ='Revenue Drivers'!I11 -> 357086.73 | J10: ='Revenue Drivers'!J11 -> 376334.66 | ... W10: ='Revenue Drivers'!W11 -> 476588.45 | X10: =SUM(D10:G10) -> 1170450.2 | Y10: =SUM(H10:K10) -> 1467523.6 | Z10: =SUM(L10:O10) -> 1767640.4 | AA10: =SUM(P10:S10) -> 1857812.4 | AB10: =SUM(T10:W10) -> 1893115.2
A11: Revenue | B11: Revenue Drivers schedule | C11: ='Revenue Drivers'!C14 -> 117000 | D11: ='Revenue Drivers'!D14 -> 265953.38 | E11: ='Revenue Drivers'!E14 -> 283499.21 | F11: ='Revenue Drivers'!F14 -> 301385.46 | G11: ='Revenue Drivers'!G14 -> 319612.13 | H11: ='Revenue Drivers'!H14 -> 338179.22 | I11: ='Revenue Drivers'!I14 -> 357086.73 | J11: ='Revenue Drivers'!J14 -> 376334.66 | ... W11: ='Revenue Drivers'!W14 -> 476588.45 | X11: =SUM(D11:G11) -> 1170450.2 | Y11: =SUM(H11:K11) -> 1467523.6 | Z11: =SUM(L11:O11) -> 1767640.4 | AA11: =SUM(P11:S11) -> 1857812.4 | AB11: =SUM(T11:W11) -> 1893115.2
A12: Cost of Goods Sold | B12: Direct model driver | C12: 0.675518 | D12: 75 | E12: 71 | F12: 67 | G12: 63 | H12: 59 | I12: 55 | J12: 51 | K12: 47 | L12: 43 | M12: 39 | N12: 35 | O12: 34.444444 | P12: 33.888889 | Q12: 33.333333 | R12: 32.777778 | S12: 32.222222 | T12: 31.666667 | U12: 31.111111 | V12: 30.555556 | W12: 30 | X12: =SUM(D12:G12) -> 276 | Y12: =SUM(H12:K12) -> 212 | Z12: =SUM(L12:O12) -> 151.44444 | AA12: =SUM(P12:S12) -> 132.22222 | AB12: =SUM(T12:W12) -> 123.33333
A13: Marketing | B13: Direct model driver | C13: 0.079412 | D13: 24 | E13: 21.9 | F13: 19.8 | G13: 17.7 | H13: 15.6 | I13: 13.5 | J13: 11.4 | K13: 9.3 | L13: 7.2 | M13: 5.1 | N13: 3 | O13: 2.8888889 | P13: 2.7777778 | Q13: 2.6666667 | R13: 2.5555556 | S13: 2.4444444 | T13: 2.3333333 | U13: 2.2222222 | V13: 2.1111111 | W13: 2 | X13: =SUM(D13:G13) -> 83.4 | Y13: =SUM(H13:K13) -> 49.8 | Z13: =SUM(L13:O13) -> 18.188889 | AA13: =SUM(P13:S13) -> 10.444444 | AB13: =SUM(T13:W13) -> 8.6666667
A14: Research & Development | B14: Direct model driver | C14: 0 | D14: 0 | E14: 0 | F14: 0 | G14: 0 | H14: 0 | I14: 0 | J14: 0 | K14: 0 | L14: 0 | M14: 0 | N14: 0 | O14: 0 | P14: 0 | Q14: 0 | R14: 0 | S14: 0 | T14: 0 | U14: 0 | V14: 0 | W14: 0 | X14: =SUM(D14:G14) -> 0 | Y14: =SUM(H14:K14) -> 0 | Z14: =SUM(L14:O14) -> 0 | AA14: =SUM(P14:S14) -> 0 | AB14: =SUM(T14:W14) -> 0
A15: Lease | B15: Cash Equity Schedule output | C15: ='Cash Equity Schedule'!C12 -> 7500 | D15: ='Cash Equity Schedule'!D12 -> 7500 | E15: ='Cash Equity Schedule'!E12 -> 7500 | F15: ='Cash Equity Schedule'!F12 -> 7500 | G15: ='Cash Equity Schedule'!G12 -> 7500 | H15: ='Cash Equity Schedule'!H12 -> 7500 | I15: ='Cash Equity Schedule'!I12 -> 7500 | J15: ='Cash Equity Schedule'!J12 -> 7500 | ... W15: ='Cash Equity Schedule'!W12 -> 7500 | X15: =SUM(D15:G15) -> 30000 | Y15: =SUM(H15:K15) -> 30000 | Z15: =SUM(L15:O15) -> 30000 | AA15: =SUM(P15:S15) -> 30000 | AB15: =SUM(T15:W15) -> 30000
A16: Payroll | B16: Payroll Schedule output | C16: 102356.25 | D16: ='Payroll Schedule'!D17 -> 106929.45 | E16: ='Payroll Schedule'!E17 -> 106929.45 | F16: ='Payroll Schedule'!F17 -> 106929.45 | G16: ='Payroll Schedule'!G17 -> 106929.45 | H16: ='Payroll Schedule'!H17 -> 110137.57 | I16: ='Payroll Schedule'!I17 -> 110137.57 | J16: ='Payroll Schedule'!J17 -> 110137.57 | K16: ='Payroll Schedule'!K17 -> 110137.57 | ... W16: ='Payroll Schedule'!W17 -> 120350.07 | X16: =SUM(D16:G16) -> 427717.8 | Y16: =SUM(H16:K16) -> 440550.3 | Z16: =SUM(L16:O16) -> 453764.83 | AA16: =SUM(P16:S16) -> 467378.62 | AB16: =SUM(T16:W16) -> 481400.27
A17: General & Administrative | B17: Direct model driver | C17: 0.002024 | D17: 24 | E17: 21.9 | F17: 19.8 | G17: 17.7 | H17: 15.6 | I17: 13.5 | J17: 11.4 | K17: 9.3 | L17: 7.2 | M17: 5.1 | N17: 3 | O17: 2.8888889 | P17: 2.7777778 | Q17: 2.6666667 | R17: 2.5555556 | S17: 2.4444444 | T17: 2.3333333 | U17: 2.2222222 | V17: 2.1111111 | W17: 2 | X17: =SUM(D17:G17) -> 83.4 | Y17: =SUM(H17:K17) -> 49.8 | Z17: =SUM(L17:O17) -> 18.188889 | AA17: =SUM(P17:S17) -> 10.444444 | AB17: =SUM(T17:W17) -> 8.6666667
A18: Interest Rate | B18: Debt Schedule output | C18: ='Debt Schedule'!C12 -> 0.01 | D18: ='Debt Schedule'!D12 -> 0.025 | E18: ='Debt Schedule'!E12 -> 0.025 | F18: ='Debt Schedule'!F12 -> 0.025 | G18: ='Debt Schedule'!G12 -> 0.025 | H18: ='Debt Schedule'!H12 -> 0.025 | I18: ='Debt Schedule'!I12 -> 0.025 | J18: ='Debt Schedule'!J12 -> 0.025 | ... W18: ='Debt Schedule'!W12 -> 0.025 | X18: =SUM(D18:G18) -> 0.1 | Y18: =SUM(H18:K18) -> 0.1 | Z18: =SUM(L18:O18) -> 0.1 | AA18: =SUM(P18:S18) -> 0.1 | AB18: =SUM(T18:W18) -> 0.1
A19: Interest Expense | B19: Debt Schedule output | C19: 0 | D19: ='Debt Schedule'!D13 -> 731.25 | E19: ='Debt Schedule'!E13 -> 693.75 | F19: ='Debt Schedule'!F13 -> 656.25 | G19: ='Debt Schedule'!G13 -> 618.75 | H19: ='Debt Schedule'!H13 -> 581.25 | I19: ='Debt Schedule'!I13 -> 543.75 | J19: ='Debt Schedule'!J13 -> 506.25 | K19: ='Debt Schedule'!K13 -> 468.75 | ... W19: ='Debt Schedule'!W13 -> 18.75 | X19: =SUM(D19:G19) -> 2700 | Y19: =SUM(H19:K19) -> 2100 | Z19: =SUM(L19:O19) -> 1500 | AA19: =SUM(P19:S19) -> 900 | AB19: =SUM(T19:W19) -> 300
A20: Depreciation | B20: CapEx Depreciation output | C20: ='CapEx Depreciation'!C10 -> 0 | D20: ='CapEx Depreciation'!D10 -> 0.00025 | E20: ='CapEx Depreciation'!E10 -> 0.000499 | F20: ='CapEx Depreciation'!F10 -> 0.000747 | G20: ='CapEx Depreciation'!G10 -> 0.000993 | H20: ='CapEx Depreciation'!H10 -> 0.001239 | I20: ='CapEx Depreciation'!I10 -> 0.001485 | J20: ='CapEx Depreciation'!J10 -> 0.00173 | ... W20: ='CapEx Depreciation'!W10 -> 0.004916 | X20: =SUM(D20:G20) -> 0.002489 | Y20: =SUM(H20:K20) -> 0.006428 | Z20: =SUM(L20:O20) -> 0.010335 | AA20: =SUM(P20:S20) -> 0.01424 | AB20: =SUM(T20:W20) -> 0.018176
A21: Depreciation Expense | B21: CapEx Depreciation output | C21: ='CapEx Depreciation'!C11 -> 0 | D21: ='CapEx Depreciation'!D11 -> 10 | E21: ='CapEx Depreciation'!E11 -> 20.05481 | F21: ='CapEx Depreciation'!F11 -> 30.157059 | G21: ='CapEx Depreciation'!G11 -> 40.258794 | H21: ='CapEx Depreciation'!H11 -> 50.433553 | I21: ='CapEx Depreciation'!I11 -> 60.674336 | J21: ='CapEx Depreciation'!J11 -> 70.933036 | ... W21: ='CapEx Depreciation'!W11 -> 206.34396 | X21: =SUM(D21:G21) -> 100.47066 | Y21: =SUM(H21:K21) -> 263.24305 | Z21: =SUM(L21:O21) -> 428.23144 | AA21: =SUM(P21:S21) -> 594.78996 | AB21: =SUM(T21:W21) -> 762.37971
A22: Taxes | B22: Direct model driver | C22: 0.237834 | D22: 0.237834 | E22: 0.237834 | F22: 0.237834 | G22: 0.237834 | H22: 0.237834 | I22: 0.237834 | J22: 0.237834 | K22: 0.237834 | L22: 0.237834 | M22: 0.237834 | N22: 0.237834 | O22: 0.237834 | P22: 0.237834 | Q22: 0.237834 | R22: 0.237834 | S22: 0.237834 | T22: 0.237834 | U22: 0.237834 | V22: 0.237834 | W22: 0.237834 | X22: =SUM(D22:G22) -> 0.951336 | Y22: =SUM(H22:K22) -> 0.951336 | Z22: =SUM(L22:O22) -> 0.951336 | AA22: =SUM(P22:S22) -> 0.951336 | AB22: =SUM(T22:W22) -> 0.951336
A24: Balance Sheet Inputs
A25: Accounts Receivable Days | B25: Working Capital schedule | C25: ='Working Capital'!C7 -> 0 | D25: ='Working Capital'!D7 -> 30 | E25: ='Working Capital'!E7 -> 30 | F25: ='Working Capital'!F7 -> 30 | G25: ='Working Capital'!G7 -> 30 | H25: ='Working Capital'!H7 -> 30 | I25: ='Working Capital'!I7 -> 30 | J25: ='Working Capital'!J7 -> 30 | ... W25: ='Working Capital'!W7 -> 30 | X25: =SUM(D25:G25) -> 120 | Y25: =SUM(H25:K25) -> 120 | Z25: =SUM(L25:O25) -> 120 | AA25: =SUM(P25:S25) -> 120 | AB25: =SUM(T25:W25) -> 120
A26: Inventory Days | B26: Working Capital schedule | C26: ='Working Capital'!C8 -> 0 | D26: ='Working Capital'!D8 -> 0 | E26: ='Working Capital'!E8 -> 0 | F26: ='Working Capital'!F8 -> 0 | G26: ='Working Capital'!G8 -> 0 | H26: ='Working Capital'!H8 -> 0 | I26: ='Working Capital'!I8 -> 0 | J26: ='Working Capital'!J8 -> 0 | ... W26: ='Working Capital'!W8 -> 0 | X26: =SUM(D26:G26) -> 0 | Y26: =SUM(H26:K26) -> 0 | Z26: =SUM(L26:O26) -> 0 | AA26: =SUM(P26:S26) -> 0 | AB26: =SUM(T26:W26) -> 0
A27: Accounts Payable Days | B27: Working Capital schedule | C27: ='Working Capital'!C9 -> 0 | D27: ='Working Capital'!D9 -> 30 | E27: ='Working Capital'!E9 -> 30 | F27: ='Working Capital'!F9 -> 30 | G27: ='Working Capital'!G9 -> 30 | H27: ='Working Capital'!H9 -> 30 | I27: ='Working Capital'!I9 -> 30 | J27: ='Working Capital'!J9 -> 30 | ... W27: ='Working Capital'!W9 -> 30 | X27: =SUM(D27:G27) -> 120 | Y27: =SUM(H27:K27) -> 120 | Z27: =SUM(L27:O27) -> 120 | AA27: =SUM(P27:S27) -> 120 | AB27: =SUM(T27:W27) -> 120
A28: Prepaid Expenses (% of Revenue) | B28: Working Capital schedule | C28: ='Working Capital'!C10 -> 0 | D28: ='Working Capital'!D10 -> 5 | E28: ='Working Capital'!E10 -> 5 | F28: ='Working Capital'!F10 -> 5 | G28: ='Working Capital'!G10 -> 5 | H28: ='Working Capital'!H10 -> 5 | I28: ='Working Capital'!I10 -> 5 | J28: ='Working Capital'!J10 -> 5 | ... W28: ='Working Capital'!W10 -> 5 | X28: =SUM(D28:G28) -> 20 | Y28: =SUM(H28:K28) -> 20 | Z28: =SUM(L28:O28) -> 20 | AA28: =SUM(P28:S28) -> 20 | AB28: =SUM(T28:W28) -> 20
A29: Deferred Revenue (% of Revenue) | B29: Working Capital schedule | C29: ='Working Capital'!C11 -> 0 | D29: ='Working Capital'!D11 -> 0 | E29: ='Working Capital'!E11 -> 0 | F29: ='Working Capital'!F11 -> 0 | G29: ='Working Capital'!G11 -> 0 | H29: ='Working Capital'!H11 -> 0 | I29: ='Working Capital'!I11 -> 0 | J29: ='Working Capital'!J11 -> 0 | ... W29: ='Working Capital'!W11 -> 0 | X29: =SUM(D29:G29) -> 0 | Y29: =SUM(H29:K29) -> 0 | Z29: =SUM(L29:O29) -> 0 | AA29: =SUM(P29:S29) -> 0 | AB29: =SUM(T29:W29) -> 0
A30: Short Term Debt (% of LTD) | B30: Working Capital schedule | C30: ='Working Capital'!C12 -> 0 | D30: ='Working Capital'!D12 -> 0 | E30: ='Working Capital'!E12 -> 0 | F30: ='Working Capital'!F12 -> 0 | G30: ='Working Capital'!G12 -> 0 | H30: ='Working Capital'!H12 -> 0 | I30: ='Working Capital'!I12 -> 0 | J30: ='Working Capital'!J12 -> 0 | ... W30: ='Working Capital'!W12 -> 0 | X30: =SUM(D30:G30) -> 0 | Y30: =SUM(H30:K30) -> 0 | Z30: =SUM(L30:O30) -> 0 | AA30: =SUM(P30:S30) -> 0 | AB30: =SUM(T30:W30) -> 0
A31: Owner's Capital | B31: Cash Equity Schedule schedule | C31: ='Cash Equity Schedule'!C7 -> 45000 | D31: ='Cash Equity Schedule'!D7 -> 46229083 | E31: ='Cash Equity Schedule'!E7 -> 78731191 | F31: ='Cash Equity Schedule'!F7 -> 110631979 | G31: ='Cash Equity Schedule'!G7 -> 141884050 | H31: ='Cash Equity Schedule'!H7 -> 172083847 | I31: ='Cash Equity Schedule'!I7 -> 200913067 | J31: ='Cash Equity Schedule'!J7 -> 228094164 | ... W31: ='Cash Equity Schedule'!W7 -> 466911700 | X31: =G31 -> 141884050 | Y31: =K31 -> 253394736 | Z31: =O31 -> 332761977 | AA31: =S31 -> 402128145 | AB31: =W31 -> 466911700
A32: Other Equity | B32: Cash Equity Schedule schedule | C32: ='Cash Equity Schedule'!C8 -> 0 | D32: ='Cash Equity Schedule'!D8 -> 0 | E32: ='Cash Equity Schedule'!E8 -> 0 | F32: ='Cash Equity Schedule'!F8 -> 0 | G32: ='Cash Equity Schedule'!G8 -> 0 | H32: ='Cash Equity Schedule'!H8 -> 0 | I32: ='Cash Equity Schedule'!I8 -> 0 | J32: ='Cash Equity Schedule'!J8 -> 0 | ... W32: ='Cash Equity Schedule'!W8 -> 0 | X32: =G32 -> 0 | Y32: =K32 -> 0 | Z32: =O32 -> 0 | AA32: =S32 -> 0 | AB32: =W32 -> 0
A33: Distributions | B33: Cash Equity Schedule schedule | C33: ='Cash Equity Schedule'!C9 -> 0 | D33: ='Cash Equity Schedule'!D9 -> 0 | E33: ='Cash Equity Schedule'!E9 -> 0 | F33: ='Cash Equity Schedule'!F9 -> 0 | G33: ='Cash Equity Schedule'!G9 -> 0 | H33: ='Cash Equity Schedule'!H9 -> 0 | I33: ='Cash Equity Schedule'!I9 -> 0 | J33: ='Cash Equity Schedule'!J9 -> 0 | ... W33: ='Cash Equity Schedule'!W9 -> 0 | X33: =G33 -> 0 | Y33: =K33 -> 0 | Z33: =O33 -> 0 | AA33: =S33 -> 0 | AB33: =W33 -> 0
A35: Cash Flow and Schedule Inputs
A36: Cash Opening Balance | B36: Working Capital schedule | C36: ='Working Capital'!C15 -> 12000 | D36: ='Working Capital'!D15 -> 0 | E36: ='Working Capital'!E15 -> 0 | F36: ='Working Capital'!F15 -> 0 | G36: ='Working Capital'!G15 -> 0 | H36: ='Working Capital'!H15 -> 0 | I36: ='Working Capital'!I15 -> 0 | J36: ='Working Capital'!J15 -> 0 | ... W36: ='Working Capital'!W15 -> 0 | X36: =G36 -> 0 | Y36: =K36 -> 0 | Z36: =O36 -> 0 | AA36: =S36 -> 0 | AB36: =W36 -> 0
A37: Accounts Receivable Opening Balance | B37: Working Capital schedule | C37: ='Working Capital'!C16 -> 0 | D37: ='Working Capital'!D16 -> 0 | E37: ='Working Capital'!E16 -> 0 | F37: ='Working Capital'!F16 -> 0 | G37: ='Working Capital'!G16 -> 0 | H37: ='Working Capital'!H16 -> 0 | I37: ='Working Capital'!I16 -> 0 | J37: ='Working Capital'!J16 -> 0 | ... W37: ='Working Capital'!W16 -> 0 | X37: =G37 -> 0 | Y37: =K37 -> 0 | Z37: =O37 -> 0 | AA37: =S37 -> 0 | AB37: =W37 -> 0
A38: Inventory Opening Balance | B38: Working Capital schedule | C38: ='Working Capital'!C17 -> 0 | D38: ='Working Capital'!D17 -> 0 | E38: ='Working Capital'!E17 -> 0 | F38: ='Working Capital'!F17 -> 0 | G38: ='Working Capital'!G17 -> 0 | H38: ='Working Capital'!H17 -> 0 | I38: ='Working Capital'!I17 -> 0 | J38: ='Working Capital'!J17 -> 0 | ... W38: ='Working Capital'!W17 -> 0 | X38: =G38 -> 0 | Y38: =K38 -> 0 | Z38: =O38 -> 0 | AA38: =S38 -> 0 | AB38: =W38 -> 0
A39: Accounts Payable Opening Balance | B39: Working Capital schedule | C39: ='Working Capital'!C18 -> 4000 | D39: ='Working Capital'!D18 -> 0 | E39: ='Working Capital'!E18 -> 0 | F39: ='Working Capital'!F18 -> 0 | G39: ='Working Capital'!G18 -> 0 | H39: ='Working Capital'!H18 -> 0 | I39: ='Working Capital'!I18 -> 0 | J39: ='Working Capital'!J18 -> 0 | ... W39: ='Working Capital'!W18 -> 0 | X39: =G39 -> 0 | Y39: =K39 -> 0 | Z39: =O39 -> 0 | AA39: =S39 -> 0 | AB39: =W39 -> 0
A40: Short Term Debt Opening Balance | B40: Working Capital schedule | C40: ='Working Capital'!C19 -> 0 | D40: ='Working Capital'!D19 -> 0 | E40: ='Working Capital'!E19 -> 0 | F40: ='Working Capital'!F19 -> 0 | G40: ='Working Capital'!G19 -> 0 | H40: ='Working Capital'!H19 -> 0 | I40: ='Working Capital'!I19 -> 0 | J40: ='Working Capital'!J19 -> 0 | ... W40: ='Working Capital'!W19 -> 0 | X40: =G40 -> 0 | Y40: =K40 -> 0 | Z40: =O40 -> 0 | AA40: =S40 -> 0 | AB40: =W40 -> 0
A41: Debt Opening Balance | B41: Debt Schedule schedule | C41: ='Debt Schedule'!C7 -> 30000 | D41: ='Debt Schedule'!D7 -> 30000 | E41: ='Debt Schedule'!E7 -> 28500 | F41: ='Debt Schedule'!F7 -> 27000 | G41: ='Debt Schedule'!G7 -> 25500 | H41: ='Debt Schedule'!H7 -> 24000 | I41: ='Debt Schedule'!I7 -> 22500 | J41: ='Debt Schedule'!J7 -> 21000 | ... W41: ='Debt Schedule'!W7 -> 1500 | X41: =G41 -> 25500 | Y41: =K41 -> 19500 | Z41: =O41 -> 13500 | AA41: =S41 -> 7500 | AB41: =W41 -> 1500
A42: Debt Issuance | B42: Debt Schedule schedule | C42: ='Debt Schedule'!C8 -> 0 | D42: ='Debt Schedule'!D8 -> 0 | E42: ='Debt Schedule'!E8 -> 0 | F42: ='Debt Schedule'!F8 -> 0 | G42: ='Debt Schedule'!G8 -> 0 | H42: ='Debt Schedule'!H8 -> 0 | I42: ='Debt Schedule'!I8 -> 0 | J42: ='Debt Schedule'!J8 -> 0 | ... W42: ='Debt Schedule'!W8 -> 0 | X42: =SUM(D42:G42) -> 0 | Y42: =SUM(H42:K42) -> 0 | Z42: =SUM(L42:O42) -> 0 | AA42: =SUM(P42:S42) -> 0 | AB42: =SUM(T42:W42) -> 0
A43: Debt Repayment | B43: Debt Schedule schedule | C43: ='Debt Schedule'!C10 -> 0 | D43: ='Debt Schedule'!D10 -> 1500 | E43: ='Debt Schedule'!E10 -> 1500 | F43: ='Debt Schedule'!F10 -> 1500 | G43: ='Debt Schedule'!G10 -> 1500 | H43: ='Debt Schedule'!H10 -> 1500 | I43: ='Debt Schedule'!I10 -> 1500 | J43: ='Debt Schedule'!J10 -> 1500 | ... W43: ='Debt Schedule'!W10 -> 1500 | X43: =SUM(D43:G43) -> 6000 | Y43: =SUM(H43:K43) -> 6000 | Z43: =SUM(L43:O43) -> 6000 | AA43: =SUM(P43:S43) -> 6000 | AB43: =SUM(T43:W43) -> 6000
A44: Debt Closing Balance | B44: Debt Schedule schedule | C44: ='Debt Schedule'!C11 -> 30000 | D44: ='Debt Schedule'!D11 -> 28500 | E44: ='Debt Schedule'!E11 -> 27000 | F44: ='Debt Schedule'!F11 -> 25500 | G44: ='Debt Schedule'!G11 -> 24000 | H44: ='Debt Schedule'!H11 -> 22500 | I44: ='Debt Schedule'!I11 -> 21000 | J44: ='Debt Schedule'!J11 -> 19500 | ... W44: ='Debt Schedule'!W11 -> 0 | X44: =G44 -> 24000 | Y44: =K44 -> 18000 | Z44: =O44 -> 12000 | AA44: =S44 -> 6000 | AB44: =W44 -> 0
A45: Lease Opening Balance | B45: Debt Schedule schedule | C45: ='Debt Schedule'!C18 -> 0 | D45: ='Debt Schedule'!D18 -> 0 | E45: ='Debt Schedule'!E18 -> 0 | F45: ='Debt Schedule'!F18 -> 0 | G45: ='Debt Schedule'!G18 -> 0 | H45: ='Debt Schedule'!H18 -> 0 | I45: ='Debt Schedule'!I18 -> 0 | J45: ='Debt Schedule'!J18 -> 0 | ... W45: ='Debt Schedule'!W18 -> 0 | X45: =G45 -> 0 | Y45: =K45 -> 0 | Z45: =O45 -> 0 | AA45: =S45 -> 0 | AB45: =W45 -> 0
A46: Lease Principal Repayments | B46: Debt Schedule schedule | C46: ='Debt Schedule'!C20 -> 0 | D46: ='Debt Schedule'!D20 -> 0 | E46: ='Debt Schedule'!E20 -> 0 | F46: ='Debt Schedule'!F20 -> 0 | G46: ='Debt Schedule'!G20 -> 0 | H46: ='Debt Schedule'!H20 -> 0 | I46: ='Debt Schedule'!I20 -> 0 | J46: ='Debt Schedule'!J20 -> 0 | ... W46: ='Debt Schedule'!W20 -> 0 | X46: =SUM(D46:G46) -> 0 | Y46: =SUM(H46:K46) -> 0 | Z46: =SUM(L46:O46) -> 0 | AA46: =SUM(P46:S46) -> 0 | AB46: =SUM(T46:W46) -> 0
A47: Lease Net Additions | B47: Debt Schedule schedule | C47: ='Debt Schedule'!C21 -> 0 | D47: ='Debt Schedule'!D21 -> 0 | E47: ='Debt Schedule'!E21 -> 0 | F47: ='Debt Schedule'!F21 -> 0 | G47: ='Debt Schedule'!G21 -> 0 | H47: ='Debt Schedule'!H21 -> 0 | I47: ='Debt Schedule'!I21 -> 0 | J47: ='Debt Schedule'!J21 -> 0 | ... W47: ='Debt Schedule'!W21 -> 0 | X47: =SUM(D47:G47) -> 0 | Y47: =SUM(H47:K47) -> 0 | Z47: =SUM(L47:O47) -> 0 | AA47: =SUM(P47:S47) -> 0 | AB47: =SUM(T47:W47) -> 0
A48: Lease Interest Expense | B48: Debt Schedule schedule | C48: ='Debt Schedule'!C22 -> 0 | D48: ='Debt Schedule'!D22 -> 0 | E48: ='Debt Schedule'!E22 -> 0 | F48: ='Debt Schedule'!F22 -> 0 | G48: ='Debt Schedule'!G22 -> 0 | H48: ='Debt Schedule'!H22 -> 0 | I48: ='Debt Schedule'!I22 -> 0 | J48: ='Debt Schedule'!J22 -> 0 | ... W48: ='Debt Schedule'!W22 -> 0 | X48: =SUM(D48:G48) -> 0 | Y48: =SUM(H48:K48) -> 0 | Z48: =SUM(L48:O48) -> 0 | AA48: =SUM(P48:S48) -> 0 | AB48: =SUM(T48:W48) -> 0
A49: Lease Closing Balance | B49: Debt Schedule schedule | C49: ='Debt Schedule'!C23 -> 0 | D49: ='Debt Schedule'!D23 -> 0 | E49: ='Debt Schedule'!E23 -> 0 | F49: ='Debt Schedule'!F23 -> 0 | G49: ='Debt Schedule'!G23 -> 0 | H49: ='Debt Schedule'!H23 -> 0 | I49: ='Debt Schedule'!I23 -> 0 | J49: ='Debt Schedule'!J23 -> 0 | ... W49: ='Debt Schedule'!W23 -> 0 | X49: =G49 -> 0 | Y49: =K49 -> 0 | Z49: =O49 -> 0 | AA49: =S49 -> 0 | AB49: =W49 -> 0
A50: Right-of-Use Asset | B50: Debt Schedule schedule | C50: ='Debt Schedule'!C26 -> 0 | D50: ='Debt Schedule'!D26 -> 0 | E50: ='Debt Schedule'!E26 -> 0 | F50: ='Debt Schedule'!F26 -> 0 | G50: ='Debt Schedule'!G26 -> 0 | H50: ='Debt Schedule'!H26 -> 0 | I50: ='Debt Schedule'!I26 -> 0 | J50: ='Debt Schedule'!J26 -> 0 | ... W50: ='Debt Schedule'!W26 -> 0 | X50: =G50 -> 0 | Y50: =K50 -> 0 | Z50: =O50 -> 0 | AA50: =S50 -> 0 | AB50: =W50 -> 0
A51: Lease Asset Depreciation | B51: Debt Schedule schedule | C51: ='Debt Schedule'!C25 -> 0 | D51: ='Debt Schedule'!D25 -> 0 | E51: ='Debt Schedule'!E25 -> 0 | F51: ='Debt Schedule'!F25 -> 0 | G51: ='Debt Schedule'!G25 -> 0 | H51: ='Debt Schedule'!H25 -> 0 | I51: ='Debt Schedule'!I25 -> 0 | J51: ='Debt Schedule'!J25 -> 0 | ... W51: ='Debt Schedule'!W25 -> 0 | X51: =SUM(D51:G51) -> 0 | Y51: =SUM(H51:K51) -> 0 | Z51: =SUM(L51:O51) -> 0 | AA51: =SUM(P51:S51) -> 0 | AB51: =SUM(T51:W51) -> 0
A52: Capital Expenditures | B52: CapEx Depreciation schedule | C52: ='CapEx Depreciation'!C8 -> 0 | D52: ='CapEx Depreciation'!D8 -> 200 | E52: ='CapEx Depreciation'!E8 -> 200.95 | F52: ='CapEx Depreciation'!F8 -> 201.85448 | G52: ='CapEx Depreciation'!G8 -> 202.71296 | H52: ='CapEx Depreciation'!H8 -> 203.52523 | I52: ='CapEx Depreciation'!I8 -> 204.29069 | J52: ='CapEx Depreciation'!J8 -> 205.00877 | ... W52: ='CapEx Depreciation'!W8 -> 209.86977 | X52: =SUM(D52:G52) -> 805.51744 | Y52: =SUM(H52:K52) -> 818.50385 | Z52: =SUM(L52:O52) -> 828.45382 | AA52: =SUM(P52:S52) -> 835.26719 | AB52: =SUM(T52:W52) -> 838.85302
A53: PPE Closing Balance | B53: CapEx Depreciation schedule | C53: ='CapEx Depreciation'!C12 -> 40000 | D53: ='CapEx Depreciation'!D12 -> 40190 | E53: ='CapEx Depreciation'!E12 -> 40370.895 | F53: ='CapEx Depreciation'!F12 -> 40542.593 | G53: ='CapEx Depreciation'!G12 -> 40705.047 | H53: ='CapEx Depreciation'!H12 -> 40858.138 | I53: ='CapEx Depreciation'!I12 -> 41001.755 | J53: ='CapEx Depreciation'!J12 -> 41135.831 | ... W53: ='CapEx Depreciation'!W12 -> 41977.48 | X53: =G53 -> 40705.047 | Y53: =K53 -> 41260.308 | Z53: =O53 -> 41660.53 | AA53: =S53 -> 41901.007 | AB53: =W53 -> 41977.48
A54: Accumulated Depreciation | B54: CapEx Depreciation schedule | C54: ='CapEx Depreciation'!C14 -> 0 | D54: ='CapEx Depreciation'!D14 -> -10 | E54: ='CapEx Depreciation'!E14 -> -30.05481 | F54: ='CapEx Depreciation'!F14 -> -60.211869 | G54: ='CapEx Depreciation'!G14 -> -100.47066 | H54: ='CapEx Depreciation'!H14 -> -150.90422 | I54: ='CapEx Depreciation'!I14 -> -211.57855 | J54: ='CapEx Depreciation'!J14 -> -282.51159 | ... W54: ='CapEx Depreciation'!W14 -> -2149.1148 | X54: =G54 -> -100.47066 | Y54: =K54 -> -363.71372 | Z54: =O54 -> -791.94516 | AA54: =S54 -> -1386.7351 | AB54: =W54 -> -2149.1148

Sheet FINMO
A1: FINMO
A2: Three-statement financial model. All formulas reference Model Inputs and in-sheet statement rows.
C4: Stub | D4: Q1 | E4: Q2 | F4: Q3 | G4: Q4 | H4: Q5 | I4: Q6 | J4: Q7 | K4: Q8 | L4: Q9 | M4: Q10 | N4: Q11 | O4: Q12 | P4: Q13 | Q4: Q14 | R4: Q15 | S4: Q16 | T4: Q17 | U4: Q18 | V4: Q19 | W4: Q20 | X4: Y1 | Y4: Y2 | Z4: Y3 | AA4: Y4 | AB4: Y5
C5: 46162 | D5: 46295 | E5: 46387 | F5: 46477 | G5: 46568 | H5: 46660 | I5: 46752 | J5: 46843 | K5: 46934 | L5: 47026 | M5: 47118 | N5: 47208 | O5: 47299 | P5: 47391 | Q5: 47483 | R5: 47573 | S5: 47664 | T5: 47756 | U5: 47848 | V5: 47938 | W5: 48029 | X5: Annual | Y5: Annual | Z5: Annual | AA5: Annual | AB5: Annual
A6: Days in Quarter | C6: 0 | D6: 92 | E6: 92 | F6: 90 | G6: 91 | H6: 92 | I6: 92 | J6: 91 | K6: 91 | L6: 92 | M6: 92 | N6: 90 | O6: 91 | P6: 92 | Q6: 92 | R6: 90 | S6: 91 | T6: 92 | U6: 92 | V6: 90 | W6: 91
A7: Income Statement
A8: Revenue | B8: Formula | C8: ='Model Inputs'!C11 -> 117000 | D8: ='Model Inputs'!D11 -> 265953.38 | E8: ='Model Inputs'!E11 -> 283499.21 | F8: ='Model Inputs'!F11 -> 301385.46 | G8: ='Model Inputs'!G11 -> 319612.13 | H8: ='Model Inputs'!H11 -> 338179.22 | I8: ='Model Inputs'!I11 -> 357086.73 | J8: ='Model Inputs'!J11 -> 376334.66 | ... W8: ='Model Inputs'!W11 -> 476588.45 | X8: =SUM(D8:G8) -> 1170450.2 | Y8: =SUM(H8:K8) -> 1467523.6 | Z8: =SUM(L8:O8) -> 1767640.4 | AA8: =SUM(P8:S8) -> 1857812.4 | AB8: =SUM(T8:W8) -> 1893115.2
A9: Cost of Goods Sold | B9: Formula | C9: =C8*'Model Inputs'!C12 -> 79035.606 | D9: =D8*'Model Inputs'!D12 -> 19946503 | E9: =E8*'Model Inputs'!E12 -> 20128444 | F9: =F8*'Model Inputs'!F12 -> 20192826 | G9: =G8*'Model Inputs'!G12 -> 20135564 | H9: =H8*'Model Inputs'!H12 -> 19952574 | I9: =I8*'Model Inputs'!I12 -> 19639770 | J9: =J8*'Model Inputs'!J12 -> 19193068 | ... W9: =W8*'Model Inputs'!W12 -> 14297653 | X9: =SUM(D9:G9) -> 80403336 | Y9: =SUM(H9:K9) -> 77393794 | Z9: =SUM(L9:O9) -> 66683747 | AA9: =SUM(P9:S9) -> 61404891 | AB9: =SUM(T9:W9) -> 58364924
A10: Gross Profit | B10: Formula | C10: =C8-C9 -> 37964.394 | D10: =D8-D9 -> -19680550 | E10: =E8-E9 -> -19844944 | F10: =F8-F9 -> -19891440 | G10: =G8-G9 -> -19815952 | H10: =H8-H9 -> -19614395 | I10: =I8-I9 -> -19282684 | J10: =J8-J9 -> -18816733 | ... W10: =W8-W9 -> -13821065 | X10: =SUM(D10:G10) -> -79232886 | Y10: =SUM(H10:K10) -> -75926270 | Z10: =SUM(L10:O10) -> -64916107 | AA10: =SUM(P10:S10) -> -59547079 | AB10: =SUM(T10:W10) -> -56471809
A11: Marketing | B11: Formula | C11: =C8*'Model Inputs'!C13 -> 9291.204 | D11: =D8*'Model Inputs'!D13 -> 6382881 | E11: =E8*'Model Inputs'!E13 -> 6208632.6 | F11: =F8*'Model Inputs'!F13 -> 5967432 | G11: =G8*'Model Inputs'!G13 -> 5657134.7 | H11: =H8*'Model Inputs'!H13 -> 5275595.8 | I11: =I8*'Model Inputs'!I13 -> 4820670.9 | J11: =J8*'Model Inputs'!J13 -> 4290215.2 | ... W11: =W8*'Model Inputs'!W13 -> 953176.9 | X11: =SUM(D11:G11) -> 24216080 | Y11: =SUM(H11:K11) -> 18068566 | Z11: =SUM(L11:O11) -> 7914359.7 | AA11: =SUM(P11:S11) -> 4849728.7 | AB11: =SUM(T11:W11) -> 4100523.9
A12: Research & Development | B12: Formula | C12: =C8*'Model Inputs'!C14 -> 0 | D12: =D8*'Model Inputs'!D14 -> 0 | E12: =E8*'Model Inputs'!E14 -> 0 | F12: =F8*'Model Inputs'!F14 -> 0 | G12: =G8*'Model Inputs'!G14 -> 0 | H12: =H8*'Model Inputs'!H14 -> 0 | I12: =I8*'Model Inputs'!I14 -> 0 | J12: =J8*'Model Inputs'!J14 -> 0 | ... W12: =W8*'Model Inputs'!W14 -> 0 | X12: =SUM(D12:G12) -> 0 | Y12: =SUM(H12:K12) -> 0 | Z12: =SUM(L12:O12) -> 0 | AA12: =SUM(P12:S12) -> 0 | AB12: =SUM(T12:W12) -> 0
A13: Lease/Rent | B13: Formula | C13: ='Model Inputs'!C15 -> 7500 | D13: ='Model Inputs'!D15 -> 7500 | E13: ='Model Inputs'!E15 -> 7500 | F13: ='Model Inputs'!F15 -> 7500 | G13: ='Model Inputs'!G15 -> 7500 | H13: ='Model Inputs'!H15 -> 7500 | I13: ='Model Inputs'!I15 -> 7500 | J13: ='Model Inputs'!J15 -> 7500 | ... W13: ='Model Inputs'!W15 -> 7500 | X13: =SUM(D13:G13) -> 30000 | Y13: =SUM(H13:K13) -> 30000 | Z13: =SUM(L13:O13) -> 30000 | AA13: =SUM(P13:S13) -> 30000 | AB13: =SUM(T13:W13) -> 30000
A14: Payroll | B14: Formula | C14: ='Model Inputs'!C16 -> 102356.25 | D14: ='Model Inputs'!D16 -> 106929.45 | E14: ='Model Inputs'!E16 -> 106929.45 | F14: ='Model Inputs'!F16 -> 106929.45 | G14: ='Model Inputs'!G16 -> 106929.45 | H14: ='Model Inputs'!H16 -> 110137.57 | I14: ='Model Inputs'!I16 -> 110137.57 | J14: ='Model Inputs'!J16 -> 110137.57 | ... W14: ='Model Inputs'!W16 -> 120350.07 | X14: =SUM(D14:G14) -> 427717.8 | Y14: =SUM(H14:K14) -> 440550.3 | Z14: =SUM(L14:O14) -> 453764.83 | AA14: =SUM(P14:S14) -> 467378.62 | AB14: =SUM(T14:W14) -> 481400.27
A15: General & Administrative | B15: Formula | C15: =C8*'Model Inputs'!C17 -> 236.808 | D15: =D8*'Model Inputs'!D17 -> 6382881 | E15: =E8*'Model Inputs'!E17 -> 6208632.6 | F15: =F8*'Model Inputs'!F17 -> 5967432 | G15: =G8*'Model Inputs'!G17 -> 5657134.7 | H15: =H8*'Model Inputs'!H17 -> 5275595.8 | I15: =I8*'Model Inputs'!I17 -> 4820670.9 | J15: =J8*'Model Inputs'!J17 -> 4290215.2 | ... W15: =W8*'Model Inputs'!W17 -> 953176.9 | X15: =SUM(D15:G15) -> 24216080 | Y15: =SUM(H15:K15) -> 18068566 | Z15: =SUM(L15:O15) -> 7914359.7 | AA15: =SUM(P15:S15) -> 4849728.7 | AB15: =SUM(T15:W15) -> 4100523.9
A16: EBITDA | B16: Formula | C16: =C10-SUM(C11:C15) -> -81419.868 | D16: =D10-SUM(D11:D15) -> -32560741 | E16: =E10-SUM(E11:E15) -> -32376639 | F16: =F10-SUM(F11:F15) -> -31940734 | G16: =G10-SUM(G11:G15) -> -31244651 | H16: =H10-SUM(H11:H15) -> -30283224 | I16: =I10-SUM(I11:I15) -> -29041663 | J16: =J10-SUM(J11:J15) -> -27514801 | ... W16: =W10-SUM(W11:W15) -> -15855269 | X16: =SUM(D16:G16) -> -1.2812276e+08 | Y16: =SUM(H16:K16) -> -1.1253395e+08 | Z16: =SUM(L16:O16) -> -81228591 | AA16: =SUM(P16:S16) -> -69743915 | AB16: =SUM(T16:W16) -> -65184257
A17: Interest | B17: Formula | C17: ='Model Inputs'!C19+'Model Inputs'!C48 -> 0 | D17: ='Model Inputs'!D19+'Model Inputs'!D48 -> 731.25 | E17: ='Model Inputs'!E19+'Model Inputs'!E48 -> 693.75 | F17: ='Model Inputs'!F19+'Model Inputs'!F48 -> 656.25 | G17: ='Model Inputs'!G19+'Model Inputs'!G48 -> 618.75 | H17: ='Model Inputs'!H19+'Model Inputs'!H48 -> 581.25 | I17: ='Model Inputs'!I19+'Model Inputs'!I48 -> 543.75 | J17: ='Model Inputs'!J19+'Model Inputs'!J48 -> 506.25 | ... W17: ='Model Inputs'!W19+'Model Inputs'!W48 -> 18.75 | X17: =SUM(D17:G17) -> 2700 | Y17: =SUM(H17:K17) -> 2100 | Z17: =SUM(L17:O17) -> 1500 | AA17: =SUM(P17:S17) -> 900 | AB17: =SUM(T17:W17) -> 300
A18: Depreciation | B18: Formula | C18: ='Model Inputs'!C21+'Model Inputs'!C51 -> 0 | D18: ='Model Inputs'!D21+'Model Inputs'!D51 -> 10 | E18: ='Model Inputs'!E21+'Model Inputs'!E51 -> 20.05481 | F18: ='Model Inputs'!F21+'Model Inputs'!F51 -> 30.157059 | G18: ='Model Inputs'!G21+'Model Inputs'!G51 -> 40.258794 | H18: ='Model Inputs'!H21+'Model Inputs'!H51 -> 50.433553 | I18: ='Model Inputs'!I21+'Model Inputs'!I51 -> 60.674336 | J18: ='Model Inputs'!J21+'Model Inputs'!J51 -> 70.933036 | ... W18: ='Model Inputs'!W21+'Model Inputs'!W51 -> 206.34396 | X18: =SUM(D18:G18) -> 100.47066 | Y18: =SUM(H18:K18) -> 263.24305 | Z18: =SUM(L18:O18) -> 428.23144 | AA18: =SUM(P18:S18) -> 594.78996 | AB18: =SUM(T18:W18) -> 762.37971
A19: Taxes | B19: Formula | C19: =MAX(0,C16-C17-C18)*'Model Inputs'!C22 -> 0 | D19: =MAX(0,D16-D17-D18)*'Model Inputs'!D22 -> 0 | E19: =MAX(0,E16-E17-E18)*'Model Inputs'!E22 -> 0 | F19: =MAX(0,F16-F17-F18)*'Model Inputs'!F22 -> 0 | G19: =MAX(0,G16-G17-G18)*'Model Inputs'!G22 -> 0 | H19: =MAX(0,H16-H17-H18)*'Model Inputs'!H22 -> 0 | I19: =MAX(0,I16-I17-I18)*'Model Inputs'!I22 -> 0 | J19: =MAX(0,J16-J17-J18)*'Model Inputs'!J22 -> 0 | ... W19: =MAX(0,W16-W17-W18)*'Model Inputs'!W22 -> 0 | X19: =SUM(D19:G19) -> 0 | Y19: =SUM(H19:K19) -> 0 | Z19: =SUM(L19:O19) -> 0 | AA19: =SUM(P19:S19) -> 0 | AB19: =SUM(T19:W19) -> 0
A20: Net Income | B20: Formula | C20: =C16-SUM(C17:C19) -> -81419.868 | D20: =D16-SUM(D17:D19) -> -32561482 | E20: =E16-SUM(E17:E19) -> -32377353 | F20: =F16-SUM(F17:F19) -> -31941420 | G20: =G16-SUM(G17:G19) -> -31245310 | H20: =H16-SUM(H17:H19) -> -30283856 | I20: =I16-SUM(I17:I19) -> -29042267 | J20: =J16-SUM(J17:J19) -> -27515378 | ... W20: =W16-SUM(W17:W19) -> -15855494 | X20: =SUM(D20:G20) -> -1.2812557e+08 | Y20: =SUM(H20:K20) -> -1.1253632e+08 | Z20: =SUM(L20:O20) -> -81230519 | AA20: =SUM(P20:S20) -> -69745410 | AB20: =SUM(T20:W20) -> -65185319
A22: Balance Sheet
A23: Cash | B23: Formula | C23: =C61 -> 12000 | D23: =D61 -> 16412482 | E23: =E61 -> 16328466 | F23: =F61 -> 16118723 | G23: =G61 -> 15779055 | H23: =H61 -> 15306862 | I23: =I61 -> 14694778 | J23: =J61 -> 13940217 | ... W23: =W61 -> 8150151.4 | X23: =G23 -> 15779055 | Y23: =K23 -> 13038985 | Z23: =O23 -> 9280970.2 | AA23: =S23 -> 8729309.4 | AB23: =W23 -> 8150151.4
A24: Accounts Receivable | B24: Formula | C24: ='Model Inputs'!C37 -> 0 | D24: =('Model Inputs'!D25/D6)*D8 -> 86723.927 | E24: =('Model Inputs'!E25/E6)*E8 -> 92445.393 | F24: =('Model Inputs'!F25/F6)*F8 -> 100461.82 | G24: =('Model Inputs'!G25/G6)*G8 -> 105366.64 | H24: =('Model Inputs'!H25/H6)*H8 -> 110275.83 | I24: =('Model Inputs'!I25/I6)*I8 -> 116441.33 | J24: =('Model Inputs'!J25/J6)*J8 -> 124066.37 | K24: =('Model Inputs'!K25/K6)*K8 -> 130524.07 | ... W24: =('Model Inputs'!W25/W6)*W8 -> 157117.07 | X24: =G24 -> 105366.64 | Y24: =K24 -> 130524.07 | Z24: =O24 -> 151297.92 | AA24: =S24 -> 154207.5 | AB24: =W24 -> 157117.07
A25: Inventory | B25: Formula | C25: ='Model Inputs'!C38 -> 0 | D25: =('Model Inputs'!D26/D6)*D9 -> 0 | E25: =('Model Inputs'!E26/E6)*E9 -> 0 | F25: =('Model Inputs'!F26/F6)*F9 -> 0 | G25: =('Model Inputs'!G26/G6)*G9 -> 0 | H25: =('Model Inputs'!H26/H6)*H9 -> 0 | I25: =('Model Inputs'!I26/I6)*I9 -> 0 | J25: =('Model Inputs'!J26/J6)*J9 -> 0 | K25: =('Model Inputs'!K26/K6)*K9 -> 0 | ... W25: =('Model Inputs'!W26/W6)*W9 -> 0 | X25: =G25 -> 0 | Y25: =K25 -> 0 | Z25: =O25 -> 0 | AA25: =S25 -> 0 | AB25: =W25 -> 0
A26: Prepaid Expenses | B26: Formula | C26: =0 -> 0 | D26: =D8*'Model Inputs'!D28 -> 1329766.9 | E26: =E8*'Model Inputs'!E28 -> 1417496 | F26: =F8*'Model Inputs'!F28 -> 1506927.3 | G26: =G8*'Model Inputs'!G28 -> 1598060.6 | H26: =H8*'Model Inputs'!H28 -> 1690896.1 | I26: =I8*'Model Inputs'!I28 -> 1785433.7 | J26: =J8*'Model Inputs'!J28 -> 1881673.3 | K26: =K8*'Model Inputs'!K28 -> 1979615.1 | ... W26: =W8*'Model Inputs'!W28 -> 2382942.2 | X26: =G26 -> 1598060.6 | Y26: =K26 -> 1979615.1 | Z26: =O26 -> 2294685.1 | AA26: =S26 -> 2338813.7 | AB26: =W26 -> 2382942.2
A27: Current Assets | B27: Formula | C27: =SUM(C23:C26) -> 12000 | D27: =SUM(D23:D26) -> 17828973 | E27: =SUM(E23:E26) -> 17838407 | F27: =SUM(F23:F26) -> 17726112 | G27: =SUM(G23:G26) -> 17482483 | H27: =SUM(H23:H26) -> 17108034 | I27: =SUM(I23:I26) -> 16596653 | J27: =SUM(J23:J26) -> 15945957 | ... W27: =SUM(W23:W26) -> 10690211 | X27: =G27 -> 17482483 | Y27: =K27 -> 15149124 | Z27: =O27 -> 11726953 | AA27: =S27 -> 11222331 | AB27: =W27 -> 10690211
A28: PPE | B28: Formula | C28: ='Model Inputs'!C53 -> 40000 | D28: ='Model Inputs'!D53 -> 40190 | E28: ='Model Inputs'!E53 -> 40370.895 | F28: ='Model Inputs'!F53 -> 40542.593 | G28: ='Model Inputs'!G53 -> 40705.047 | H28: ='Model Inputs'!H53 -> 40858.138 | I28: ='Model Inputs'!I53 -> 41001.755 | J28: ='Model Inputs'!J53 -> 41135.831 | ... W28: ='Model Inputs'!W53 -> 41977.48 | X28: =G28 -> 40705.047 | Y28: =K28 -> 41260.308 | Z28: =O28 -> 41660.53 | AA28: =S28 -> 41901.007 | AB28: =W28 -> 41977.48
A29: Right-of-Use Asset (Capital Lease) | B29: Formula | C29: ='Model Inputs'!C50 -> 0 | D29: ='Model Inputs'!D50 -> 0 | E29: ='Model Inputs'!E50 -> 0 | F29: ='Model Inputs'!F50 -> 0 | G29: ='Model Inputs'!G50 -> 0 | H29: ='Model Inputs'!H50 -> 0 | I29: ='Model Inputs'!I50 -> 0 | J29: ='Model Inputs'!J50 -> 0 | ... W29: ='Model Inputs'!W50 -> 0 | X29: =G29 -> 0 | Y29: =K29 -> 0 | Z29: =O29 -> 0 | AA29: =S29 -> 0 | AB29: =W29 -> 0
A30: Accumulated Depreciation | B30: Formula | C30: ='Model Inputs'!C54 -> 0 | D30: ='Model Inputs'!D54 -> -10 | E30: ='Model Inputs'!E54 -> -30.05481 | F30: ='Model Inputs'!F54 -> -60.211869 | G30: ='Model Inputs'!G54 -> -100.47066 | H30: ='Model Inputs'!H54 -> -150.90422 | I30: ='Model Inputs'!I54 -> -211.57855 | J30: ='Model Inputs'!J54 -> -282.51159 | ... W30: ='Model Inputs'!W54 -> -2149.1148 | X30: =G30 -> -100.47066 | Y30: =K30 -> -363.71372 | Z30: =O30 -> -791.94516 | AA30: =S30 -> -1386.7351 | AB30: =W30 -> -2149.1148
A31: Total Assets | B31: Formula | C31: =C27+C28+C29 -> 52000 | D31: =D27+D28+D29 -> 17869163 | E31: =E27+E28+E29 -> 17878778 | F31: =F27+F28+F29 -> 17766655 | G31: =G27+G28+G29 -> 17523188 | H31: =H27+H28+H29 -> 17148892 | I31: =I27+I28+I29 -> 16637655 | J31: =J27+J28+J29 -> 15987093 | ... W31: =W27+W28+W29 -> 10732188 | X31: =G31 -> 17523188 | Y31: =K31 -> 15190385 | Z31: =O31 -> 11768614 | AA31: =S31 -> 11264232 | AB31: =W31 -> 10732188
A32: Accounts Payable | B32: Formula | C32: ='Model Inputs'!C39 -> 4000 | D32: =('Model Inputs'!D27/D6)*SUM(D11:D15) -> 4200062.4 | E32: =('Model Inputs'!E27/E6)*SUM(E11:E15) -> 4086422.2 | F32: =('Model Inputs'!F27/F6)*SUM(F11:F15) -> 4016431.2 | G32: =('Model Inputs'!G27/G6)*SUM(G11:G15) -> 3767702.9 | H32: =('Model Inputs'!H27/H6)*SUM(H11:H15) -> 3478966.1 | I32: =('Model Inputs'!I27/I6)*SUM(I11:I15) -> 3182275.9 | J32: =('Model Inputs'!J27/J6)*SUM(J11:J15) -> 2867494.9 | K32: =('Model Inputs'!K27/K6)*SUM(K11:K15) -> 2466529.3 | ... W32: =('Model Inputs'!W27/W6)*SUM(W11:W15) -> 670616.66 | X32: =G32 -> 3767702.9 | Y32: =K32 -> 2466529.3 | Z32: =O32 -> 914036.49 | AA32: =S32 -> 794896.06 | AB32: =W32 -> 670616.66
A33: Short Term Debt | B33: Formula | C33: ='Model Inputs'!C40 -> 0 | D33: =SUM('Debt Schedule'!E10:H10) -> 6000 | E33: =SUM('Debt Schedule'!F10:I10) -> 6000 | F33: =SUM('Debt Schedule'!G10:J10) -> 6000 | G33: =SUM('Debt Schedule'!H10:K10) -> 6000 | H33: =SUM('Debt Schedule'!I10:L10) -> 6000 | I33: =SUM('Debt Schedule'!J10:M10) -> 6000 | J33: =SUM('Debt Schedule'!K10:N10) -> 6000 | K33: =SUM('Debt Schedule'!L10:O10) -> 6000 | ... S33: =SUM('Debt Schedule'!T10:W10) -> 6000 | T33: =SUM('Debt Schedule'!U10:W10) -> 4500 | U33: =SUM('Debt Schedule'!V10:W10) -> 3000 | V33: =SUM('Debt Schedule'!W10:W10) -> 1500 | W33: =0 -> 0 | X33: =G33 -> 6000 | Y33: =K33 -> 6000 | Z33: =O33 -> 6000 | AA33: =S33 -> 6000 | AB33: =W33 -> 0
A34: Deferred Revenue | B34: Formula | C34: =0 -> 0 | D34: ='Model Inputs'!D29*D8 -> 0 | E34: ='Model Inputs'!E29*E8 -> 0 | F34: ='Model Inputs'!F29*F8 -> 0 | G34: ='Model Inputs'!G29*G8 -> 0 | H34: ='Model Inputs'!H29*H8 -> 0 | I34: ='Model Inputs'!I29*I8 -> 0 | J34: ='Model Inputs'!J29*J8 -> 0 | K34: ='Model Inputs'!K29*K8 -> 0 | ... W34: ='Model Inputs'!W29*W8 -> 0 | X34: =G34 -> 0 | Y34: =K34 -> 0 | Z34: =O34 -> 0 | AA34: =S34 -> 0 | AB34: =W34 -> 0
A35: Current Liabilities | B35: Formula | C35: =SUM(C32:C34) -> 4000 | D35: =SUM(D32:D34) -> 4206062.4 | E35: =SUM(E32:E34) -> 4092422.2 | F35: =SUM(F32:F34) -> 4022431.2 | G35: =SUM(G32:G34) -> 3773702.9 | H35: =SUM(H32:H34) -> 3484966.1 | I35: =SUM(I32:I34) -> 3188275.9 | J35: =SUM(J32:J34) -> 2873494.9 | ... W35: =SUM(W32:W34) -> 670616.66 | X35: =G35 -> 3773702.9 | Y35: =K35 -> 2472529.3 | Z35: =O35 -> 920036.49 | AA35: =S35 -> 800896.06 | AB35: =W35 -> 670616.66
A36: Long Term Debt | B36: Formula | C36: =MAX(0,'Model Inputs'!C41-C33) -> 30000 | D36: =MAX(0,'Model Inputs'!D44-D33) -> 22500 | E36: =MAX(0,'Model Inputs'!E44-E33) -> 21000 | F36: =MAX(0,'Model Inputs'!F44-F33) -> 19500 | G36: =MAX(0,'Model Inputs'!G44-G33) -> 18000 | H36: =MAX(0,'Model Inputs'!H44-H33) -> 16500 | I36: =MAX(0,'Model Inputs'!I44-I33) -> 15000 | J36: =MAX(0,'Model Inputs'!J44-J33) -> 13500 | K36: =MAX(0,'Model Inputs'!K44-K33) -> 12000 | ... W36: =MAX(0,'Model Inputs'!W44-W33) -> 0 | X36: =G36 -> 18000 | Y36: =K36 -> 12000 | Z36: =O36 -> 6000 | AA36: =S36 -> 0 | AB36: =W36 -> 0
A37: Capital Lease Obligation | B37: Formula | C37: ='Model Inputs'!C49 -> 0 | D37: ='Model Inputs'!D49 -> 0 | E37: ='Model Inputs'!E49 -> 0 | F37: ='Model Inputs'!F49 -> 0 | G37: ='Model Inputs'!G49 -> 0 | H37: ='Model Inputs'!H49 -> 0 | I37: ='Model Inputs'!I49 -> 0 | J37: ='Model Inputs'!J49 -> 0 | ... W37: ='Model Inputs'!W49 -> 0 | X37: =G37 -> 0 | Y37: =K37 -> 0 | Z37: =O37 -> 0 | AA37: =S37 -> 0 | AB37: =W37 -> 0
A38: Total Liabilities | B38: Formula | C38: =C35+C36+C37 -> 34000 | D38: =D35+D36+D37 -> 4228562.4 | E38: =E35+E36+E37 -> 4113422.2 | F38: =F35+F36+F37 -> 4041931.2 | G38: =G35+G36+G37 -> 3791702.9 | H38: =H35+H36+H37 -> 3501466.1 | I38: =I35+I36+I37 -> 3203275.9 | J38: =J35+J36+J37 -> 2886994.9 | ... W38: =W35+W36+W37 -> 670616.66 | X38: =G38 -> 3791702.9 | Y38: =K38 -> 2484529.3 | Z38: =O38 -> 926036.49 | AA38: =S38 -> 800896.06 | AB38: =W38 -> 670616.66
A39: Owner's Capital | B39: Formula | C39: ='Model Inputs'!C31 -> 45000 | D39: ='Model Inputs'!D31 -> 46229083 | E39: ='Model Inputs'!E31 -> 78731191 | F39: ='Model Inputs'!F31 -> 110631979 | G39: ='Model Inputs'!G31 -> 141884050 | H39: ='Model Inputs'!H31 -> 172083847 | I39: ='Model Inputs'!I31 -> 200913067 | J39: ='Model Inputs'!J31 -> 228094164 | ... W39: ='Model Inputs'!W31 -> 466911700 | X39: =G39 -> 141884050 | Y39: =K39 -> 253394736 | Z39: =O39 -> 332761977 | AA39: =S39 -> 402128145 | AB39: =W39 -> 466911700
A40: Retained Earnings | B40: Formula | C40: =C31-C38-C39-C41 -> -27000 | D40: =C40+D20-'Model Inputs'!D33 -> -32588482 | E40: =D40+E20-'Model Inputs'!E33 -> -64965835 | F40: =E40+F20-'Model Inputs'!F33 -> -96907255 | G40: =F40+G20-'Model Inputs'!G33 -> -1.2815257e+08 | H40: =G40+H20-'Model Inputs'!H33 -> -1.5843642e+08 | I40: =H40+I20-'Model Inputs'!I33 -> -1.8747869e+08 | J40: =I40+J20-'Model Inputs'!J33 -> -2.1499407e+08 | K40: =J40+K20-'Model Inputs'!K33 -> -2.4068888e+08 | ... W40: =V40+W20-'Model Inputs'!W33 -> -4.5685013e+08 | X40: =G40 -> -1.2815257e+08 | Y40: =K40 -> -2.4068888e+08 | Z40: =O40 -> -3.219194e+08 | AA40: =S40 -> -3.9166481e+08 | AB40: =W40 -> -4.5685013e+08
A41: Other Equity | B41: Formula | C41: ='Model Inputs'!C32 -> 0 | D41: ='Model Inputs'!D32 -> 0 | E41: ='Model Inputs'!E32 -> 0 | F41: ='Model Inputs'!F32 -> 0 | G41: ='Model Inputs'!G32 -> 0 | H41: ='Model Inputs'!H32 -> 0 | I41: ='Model Inputs'!I32 -> 0 | J41: ='Model Inputs'!J32 -> 0 | ... W41: ='Model Inputs'!W32 -> 0 | X41: =G41 -> 0 | Y41: =K41 -> 0 | Z41: =O41 -> 0 | AA41: =S41 -> 0 | AB41: =W41 -> 0
A42: Total Equity | B42: Formula | C42: =C39+C40+C41 -> 18000 | D42: =D39+D40+D41 -> 13640601 | E42: =E39+E40+E41 -> 13765356 | F42: =F39+F40+F41 -> 13724724 | G42: =G39+G40+G41 -> 13731485 | H42: =H39+H40+H41 -> 13647426 | I42: =I39+I40+I41 -> 13434379 | J42: =J39+J40+J41 -> 13100098 | ... W42: =W39+W40+W41 -> 10061572 | X42: =G42 -> 13731485 | Y42: =K42 -> 12705855 | Z42: =O42 -> 10842577 | AA42: =S42 -> 10463336 | AB42: =W42 -> 10061572
A43: Total Liabilities & Equity | B43: Formula | C43: =C38+C42 -> 52000 | D43: =D38+D42 -> 17869163 | E43: =E38+E42 -> 17878778 | F43: =F38+F42 -> 17766655 | G43: =G38+G42 -> 17523188 | H43: =H38+H42 -> 17148892 | I43: =I38+I42 -> 16637655 | J43: =J38+J42 -> 15987093 | ... W43: =W38+W42 -> 10732188 | X43: =G43 -> 17523188 | Y43: =K43 -> 15190385 | Z43: =O43 -> 11768614 | AA43: =S43 -> 11264232 | AB43: =W43 -> 10732188
A45: Cash Flow
A46: Beginning Cash | B46: Formula | C46: ='Model Inputs'!C36 -> 12000 | D46: =C61 -> 12000 | E46: =D61 -> 16412482 | F46: =E61 -> 16328466 | G46: =F61 -> 16118723 | H46: =G61 -> 15779055 | I46: =H61 -> 15306862 | J46: =I61 -> 14694778 | K46: =J61 -> 13940217 | ... W46: =V61 -> 8297955.6 | X46: =SUM(D46:G46) -> 48871671 | Y46: =SUM(H46:K46) -> 59720913 | Z46: =SUM(L46:O46) -> 45223874 | AA46: =SUM(P46:S46) -> 36307513 | AB46: =SUM(T46:W46) -> 34059702
A47: Net Income | B47: Formula | C47: =0 -> 0 | D47: =D20 -> -32561482 | E47: =E20 -> -32377353 | F47: =F20 -> -31941420 | G47: =G20 -> -31245310 | H47: =H20 -> -30283856 | I47: =I20 -> -29042267 | J47: =J20 -> -27515378 | K47: =K20 -> -25694814 | ... W47: =W20 -> -15855494 | X47: =SUM(D47:G47) -> -1.2812557e+08 | Y47: =SUM(H47:K47) -> -1.1253632e+08 | Z47: =SUM(L47:O47) -> -81230519 | AA47: =SUM(P47:S47) -> -69745410 | AB47: =SUM(T47:W47) -> -65185319
A48: Depreciation | B48: Formula | C48: =0 -> 0 | D48: =D18 -> 10 | E48: =E18 -> 20.05481 | F48: =F18 -> 30.157059 | G48: =G18 -> 40.258794 | H48: =H18 -> 50.433553 | I48: =I18 -> 60.674336 | J48: =J18 -> 70.933036 | K48: =K18 -> 81.20213 | ... W48: =W18 -> 206.34396 | X48: =SUM(D48:G48) -> 100.47066 | Y48: =SUM(H48:K48) -> 263.24305 | Z48: =SUM(L48:O48) -> 428.23144 | AA48: =SUM(P48:S48) -> 594.78996 | AB48: =SUM(T48:W48) -> 762.37971
A49: Changes in Current Assets | B49: Formula | C49: =0 -> 0 | D49: =-((D24+D25+D26)-(C24+C25+C26)) -> -1416490.8 | E49: =-((E24+E25+E26)-(D24+D25+D26)) -> -93450.62 | F49: =-((F24+F25+F26)-(E24+E25+E26)) -> -97447.681 | G49: =-((G24+G25+G26)-(F24+F25+F26)) -> -96038.173 | H49: =-((H24+H25+H26)-(G24+G25+G26)) -> -97744.655 | I49: =-((I24+I25+I26)-(H24+H25+H26)) -> -100703.05 | J49: =-((J24+J25+J26)-(I24+I25+I26)) -> -103864.71 | K49: =-((K24+K25+K26)-(J24+J25+J26)) -> -104399.46 | ... W49: =-((W24+W25+W26)-(V24+V25+V26)) -> -10021.87 | X49: =SUM(D49:G49) -> -1703427.3 | Y49: =SUM(H49:K49) -> -406711.88 | Z49: =SUM(L49:O49) -> -335843.89 | AA49: =SUM(P49:S49) -> -47038.141 | AB49: =SUM(T49:W49) -> -47038.131
A50: Changes in Current Liabilities | B50: Formula | C50: =0 -> 0 | D50: =(D32+D34)-(C32+C34) -> 4196062.4 | E50: =(E32+E34)-(D32+D34) -> -113640.26 | F50: =(F32+F34)-(E32+E34) -> -69990.993 | G50: =(G32+G34)-(F32+F34) -> -248728.28 | H50: =(H32+H34)-(G32+G34) -> -288736.84 | I50: =(I32+I34)-(H32+H34) -> -296690.18 | J50: =(J32+J34)-(I32+I34) -> -314780.95 | K50: =(K32+K34)-(J32+J34) -> -400965.57 | ... W50: =(W32+W34)-(V32+V34) -> -39648.801 | X50: =SUM(D50:G50) -> 3763702.9 | Y50: =SUM(H50:K50) -> -1301173.5 | Z50: =SUM(L50:O50) -> -1552492.9 | AA50: =SUM(P50:S50) -> -119140.43 | AB50: =SUM(T50:W50) -> -124279.4
A51: Operating Cash Flow | B51: Formula | C51: =0 -> 0 | D51: =SUM(D47:D50) -> -29781901 | E51: =SUM(E47:E50) -> -32584424 | F51: =SUM(F47:F50) -> -32108829 | G51: =SUM(G47:G50) -> -31590036 | H51: =SUM(H47:H50) -> -30670287 | I51: =SUM(I47:I50) -> -29439600 | J51: =SUM(J47:J50) -> -27933953 | K51: =SUM(K47:K50) -> -26200098 | ... W51: =SUM(W47:W50) -> -15904958 | X51: =SUM(D51:G51) -> -1.2606519e+08 | Y51: =SUM(H51:K51) -> -1.1424394e+08 | Z51: =SUM(L51:O51) -> -83118428 | AA51: =SUM(P51:S51) -> -69910994 | AB51: =SUM(T51:W51) -> -65355874
A52: Capital Expenditures | B52: Formula | C52: ='Model Inputs'!C52 -> 0 | D52: ='Model Inputs'!D52 -> 200 | E52: ='Model Inputs'!E52 -> 200.95 | F52: ='Model Inputs'!F52 -> 201.85448 | G52: ='Model Inputs'!G52 -> 202.71296 | H52: ='Model Inputs'!H52 -> 203.52523 | I52: ='Model Inputs'!I52 -> 204.29069 | J52: ='Model Inputs'!J52 -> 205.00877 | ... W52: ='Model Inputs'!W52 -> 209.86977 | X52: =SUM(D52:G52) -> 805.51744 | Y52: =SUM(H52:K52) -> 818.50385 | Z52: =SUM(L52:O52) -> 828.45382 | AA52: =SUM(P52:S52) -> 835.26719 | AB52: =SUM(T52:W52) -> 838.85302
A53: Investing Cash Flow | B53: Formula | C53: =0 -> 0 | D53: =-D52 -> -200 | E53: =-E52 -> -200.95 | F53: =-F52 -> -201.85448 | G53: =-G52 -> -202.71296 | H53: =-H52 -> -203.52523 | I53: =-I52 -> -204.29069 | J53: =-J52 -> -205.00877 | K53: =-K52 -> -205.67915 | ... W53: =-W52 -> -209.86977 | X53: =SUM(D53:G53) -> -805.51744 | Y53: =SUM(H53:K53) -> -818.50385 | Z53: =SUM(L53:O53) -> -828.45382 | AA53: =SUM(P53:S53) -> -835.26719 | AB53: =SUM(T53:W53) -> -838.85302
A54: Debt Issuance (New Borrowing) | B54: Formula | C54: ='Model Inputs'!C42 -> 0 | D54: ='Model Inputs'!D42 -> 0 | E54: ='Model Inputs'!E42 -> 0 | F54: ='Model Inputs'!F42 -> 0 | G54: ='Model Inputs'!G42 -> 0 | H54: ='Model Inputs'!H42 -> 0 | I54: ='Model Inputs'!I42 -> 0 | J54: ='Model Inputs'!J42 -> 0 | ... W54: ='Model Inputs'!W42 -> 0 | X54: =SUM(D54:G54) -> 0 | Y54: =SUM(H54:K54) -> 0 | Z54: =SUM(L54:O54) -> 0 | AA54: =SUM(P54:S54) -> 0 | AB54: =SUM(T54:W54) -> 0
A55: Debt Repayment | B55: Formula | C55: ='Model Inputs'!C43 -> 0 | D55: ='Model Inputs'!D43 -> 1500 | E55: ='Model Inputs'!E43 -> 1500 | F55: ='Model Inputs'!F43 -> 1500 | G55: ='Model Inputs'!G43 -> 1500 | H55: ='Model Inputs'!H43 -> 1500 | I55: ='Model Inputs'!I43 -> 1500 | J55: ='Model Inputs'!J43 -> 1500 | ... W55: ='Model Inputs'!W43 -> 1500 | X55: =SUM(D55:G55) -> 6000 | Y55: =SUM(H55:K55) -> 6000 | Z55: =SUM(L55:O55) -> 6000 | AA55: =SUM(P55:S55) -> 6000 | AB55: =SUM(T55:W55) -> 6000
A56: Equity | B56: Formula | C56: =0 -> 0 | D56: =(D39-C39)+(D41-C41) -> 46184083 | E56: =(E39-D39)+(E41-D41) -> 32502108 | F56: =(F39-E39)+(F41-E41) -> 31900788 | G56: =(G39-F39)+(G41-F41) -> 31252071 | H56: =(H39-G39)+(H41-G41) -> 30199797 | I56: =(I39-H39)+(I41-H41) -> 28829220 | J56: =(J39-I39)+(J41-I41) -> 27181097 | K56: =(K39-J39)+(K41-J41) -> 25300572 | ... W56: =(W39-V39)+(W41-V41) -> 15758864 | X56: =SUM(D56:G56) -> 141839050 | Y56: =SUM(H56:K56) -> 111510686 | Z56: =SUM(L56:O56) -> 79367241 | AA56: =SUM(P56:S56) -> 69366168 | AB56: =SUM(T56:W56) -> 64783555
A57: Distributions | B57: Formula | C57: ='Model Inputs'!C33 -> 0 | D57: ='Model Inputs'!D33 -> 0 | E57: ='Model Inputs'!E33 -> 0 | F57: ='Model Inputs'!F33 -> 0 | G57: ='Model Inputs'!G33 -> 0 | H57: ='Model Inputs'!H33 -> 0 | I57: ='Model Inputs'!I33 -> 0 | J57: ='Model Inputs'!J33 -> 0 | ... W57: ='Model Inputs'!W33 -> 0 | X57: =SUM(D57:G57) -> 0 | Y57: =SUM(H57:K57) -> 0 | Z57: =SUM(L57:O57) -> 0 | AA57: =SUM(P57:S57) -> 0 | AB57: =SUM(T57:W57) -> 0
A58: Capital Lease Principal Payments | B58: Formula | C58: ='Model Inputs'!C46 -> 0 | D58: ='Model Inputs'!D46 -> 0 | E58: ='Model Inputs'!E46 -> 0 | F58: ='Model Inputs'!F46 -> 0 | G58: ='Model Inputs'!G46 -> 0 | H58: ='Model Inputs'!H46 -> 0 | I58: ='Model Inputs'!I46 -> 0 | J58: ='Model Inputs'!J46 -> 0 | ... W58: ='Model Inputs'!W46 -> 0 | X58: =SUM(D58:G58) -> 0 | Y58: =SUM(H58:K58) -> 0 | Z58: =SUM(L58:O58) -> 0 | AA58: =SUM(P58:S58) -> 0 | AB58: =SUM(T58:W58) -> 0
A59: Financing Cash Flow | B59: Formula | C59: =0 -> 0 | D59: =D54-D55+D56-D57-D58 -> 46182583 | E59: =E54-E55+E56-E57-E58 -> 32500608 | F59: =F54-F55+F56-F57-F58 -> 31899288 | G59: =G54-G55+G56-G57-G58 -> 31250571 | H59: =H54-H55+H56-H57-H58 -> 30198297 | I59: =I54-I55+I56-I57-I58 -> 28827720 | J59: =J54-J55+J56-J57-J58 -> 27179597 | K59: =K54-K55+K56-K57-K58 -> 25299072 | ... W59: =W54-W55+W56-W57-W58 -> 15757364 | X59: =SUM(D59:G59) -> 141833050 | Y59: =SUM(H59:K59) -> 111504686 | Z59: =SUM(L59:O59) -> 79361241 | AA59: =SUM(P59:S59) -> 69360168 | AB59: =SUM(T59:W59) -> 64777555
A60: Net Cash Flow | B60: Formula | C60: =0 -> 0 | D60: =D51+D53+D59 -> 16400482 | E60: =E51+E53+E59 -> -84016.632 | F60: =F51+F53+F59 -> -209742.45 | G60: =G51+G53+G59 -> -339667.63 | H60: =H51+H53+H59 -> -472193.23 | I60: =I51+I53+I59 -> -612084.1 | J60: =J51+J53+J59 -> -754561.02 | K60: =K51+K53+K59 -> -901231.89 | ... W60: =W51+W53+W59 -> -147804.14 | X60: =SUM(D60:G60) -> 15767055 | Y60: =SUM(H60:K60) -> -2740070.2 | Z60: =SUM(L60:O60) -> -3758015.1 | AA60: =SUM(P60:S60) -> -551660.77 | AB60: =SUM(T60:W60) -> -579157.97
A61: Ending Cash | B61: Formula | C61: =C46+C60 -> 12000 | D61: =D46+D60 -> 16412482 | E61: =E46+E60 -> 16328466 | F61: =F46+F60 -> 16118723 | G61: =G46+G60 -> 15779055 | H61: =H46+H60 -> 15306862 | I61: =I46+I60 -> 14694778 | J61: =J46+J60 -> 13940217 | ... W61: =W46+W60 -> 8150151.4 | X61: =SUM(D61:G61) -> 64638726 | Y61: =SUM(H61:K61) -> 56980843 | Z61: =SUM(L61:O61) -> 41465859 | AA61: =SUM(P61:S61) -> 35755852 | AB61: =SUM(T61:W61) -> 33480544

Sheet Audit Source
A1: Audit Source
A2: Persisted system outputs used only for checks and audit tie-outs.
C4: Stub | D4: Q1 | E4: Q2 | F4: Q3 | G4: Q4 | H4: Q5 | I4: Q6 | J4: Q7 | K4: Q8 | L4: Q9 | M4: Q10 | N4: Q11 | O4: Q12 | P4: Q13 | Q4: Q14 | R4: Q15 | S4: Q16 | T4: Q17 | U4: Q18 | V4: Q19 | W4: Q20 | X4: Y1 | Y4: Y2 | Z4: Y3 | AA4: Y4 | AB4: Y5
C5: 46162 | D5: 46295 | E5: 46387 | F5: 46477 | G5: 46568 | H5: 46660 | I5: 46752 | J5: 46843 | K5: 46934 | L5: 47026 | M5: 47118 | N5: 47208 | O5: 47299 | P5: 47391 | Q5: 47483 | R5: 47573 | S5: 47664 | T5: 47756 | U5: 47848 | V5: 47938 | W5: 48029 | X5: Annual | Y5: Annual | Z5: Annual | AA5: Annual | AB5: Annual
A6: Income Statement
A7: Revenue | B7: Persisted FINMO | C7: 117000 | D7: 265953.38 | E7: 283499.21 | F7: 301385.46 | G7: 319612.13 | H7: 338179.22 | I7: 357086.73 | J7: 376334.66 | K7: 395923.02 | L7: 415851.79 | M7: 436120.98 | N7: 456730.6 | O7: 458937.02 | P7: 461143.45 | Q7: 463349.88 | R7: 465556.31 | S7: 467762.74 | T7: 469969.16 | U7: 472175.59 | V7: 474382.02 | W7: 476588.45
A8: Cost of Goods Sold | B8: Persisted FINMO | C8: 79035.606 | D8: 19946503 | E8: 20128444 | F8: 20192826 | G8: 20135564 | H8: 19952574 | I8: 19639770 | J8: 19193068 | K8: 18608382 | L8: 17881627 | M8: 17008718 | N8: 15985571 | O8: 15807831 | P8: 15627639 | Q8: 15444996 | R8: 15259901 | S8: 15072355 | T8: 14882357 | U8: 14689907 | V8: 14495006 | W8: 14297653
A9: Gross Profit | B9: Persisted FINMO | C9: 37964.394 | D9: -19680550 | E9: -19844944 | F9: -19891440 | G9: -19815952 | H9: -19614395 | I9: -19282684 | J9: -18816733 | K9: -18212459 | L9: -17465775 | M9: -16572597 | N9: -15528840 | O9: -15348894 | P9: -15166496 | Q9: -14981646 | R9: -14794345 | S9: -14604592 | T9: -14412388 | U9: -14217732 | V9: -14020624 | W9: -13821065
A10: Marketing | B10: Persisted FINMO | C10: 9291.204 | D10: 6382881 | E10: 6208632.6 | F10: 5967432 | G10: 5657134.7 | H10: 5275595.8 | I10: 4820670.9 | J10: 4290215.2 | K10: 3682084.1 | L10: 2994132.9 | M10: 2224217 | N10: 1370191.8 | O10: 1325818.1 | P10: 1280954 | Q10: 1235599.7 | R10: 1189755 | S10: 1143420 | T10: 1096594.7 | U10: 1049279.1 | V10: 1001473.2 | W10: 953176.9
A11: Research & Development | B11: Persisted FINMO | C11: 0 | D11: 0 | E11: 0 | F11: 0 | G11: 0 | H11: 0 | I11: 0 | J11: 0 | K11: 0 | L11: 0 | M11: 0 | N11: 0 | O11: 0 | P11: 0 | Q11: 0 | R11: 0 | S11: 0 | T11: 0 | U11: 0 | V11: 0 | W11: 0
A12: Lease/Rent | B12: Persisted FINMO | C12: 7500 | D12: 7500 | E12: 7500 | F12: 7500 | G12: 7500 | H12: 7500 | I12: 7500 | J12: 7500 | K12: 7500 | L12: 7500 | M12: 7500 | N12: 7500 | O12: 7500 | P12: 7500 | Q12: 7500 | R12: 7500 | S12: 7500 | T12: 7500 | U12: 7500 | V12: 7500 | W12: 7500
A13: Payroll | B13: Persisted FINMO | C13: 102356.25 | D13: 106192 | E13: 106192 | F13: 106192 | G13: 106192 | H13: 109380 | I13: 109380 | J13: 109380 | K13: 109380 | L13: 112661 | M13: 112661 | N13: 112661 | O13: 112661 | P13: 116039 | Q13: 116039 | R13: 116039 | S13: 116039 | T13: 119522 | U13: 119522 | V13: 119522 | W13: 119522
A14: General & Administrative | B14: Persisted FINMO | C14: 236.808 | D14: 6382881 | E14: 6208632.6 | F14: 5967432 | G14: 5657134.7 | H14: 5275595.8 | I14: 4820670.9 | J14: 4290215.2 | K14: 3682084.1 | L14: 2994132.9 | M14: 2224217 | N14: 1370191.8 | O14: 1325818.1 | P14: 1280954 | Q14: 1235599.7 | R14: 1189755 | S14: 1143420 | T14: 1096594.7 | U14: 1049279.1 | V14: 1001473.2 | W14: 953176.9
A15: EBITDA | B15: Persisted FINMO | C15: -81419.868 | D15: -32560004 | E15: -32375902 | F15: -31939996 | G15: -31243913 | H15: -30282466 | I15: -29040905 | J15: -27514044 | K15: -25693507 | L15: -23574202 | M15: -21141192 | N15: -18389385 | O15: -18120691 | P15: -17851943 | Q15: -17576384 | R15: -17297394 | S15: -17014971 | T15: -16732599 | U15: -16443312 | V15: -16150592 | W15: -15854441
A16: Interest | B16: Persisted FINMO | C16: 300 | D16: 731.25 | E16: 693.75 | F16: 656.25 | G16: 618.75 | H16: 581.25 | I16: 543.75 | J16: 506.25 | K16: 468.75 | L16: 431.25 | M16: 393.75 | N16: 356.25 | O16: 318.75 | P16: 281.25 | Q16: 243.75 | R16: 206.25 | S16: 168.75 | T16: 131.25 | U16: 93.75 | V16: 56.25 | W16: 18.75
A17: Depreciation | B17: Persisted FINMO | C17: 0 | D17: 10 | E17: 20.05481 | F17: 30.157059 | G17: 40.258794 | H17: 50.433553 | I17: 60.674336 | J17: 70.933036 | K17: 81.20213 | L17: 91.515362 | M17: 101.86548 | N17: 112.24516 | O17: 122.60544 | P17: 133.02207 | Q17: 143.48772 | R17: 153.91129 | S17: 164.36889 | T17: 174.8529 | U17: 185.35561 | V17: 195.82724 | W17: 206.34396
A18: Taxes | B18: Persisted FINMO | C18: 0 | D18: 0 | E18: 0 | F18: 0 | G18: 0 | H18: 0 | I18: 0 | J18: 0 | K18: 0 | L18: 0 | M18: 0 | N18: 0 | O18: 0 | P18: 0 | Q18: 0 | R18: 0 | S18: 0 | T18: 0 | U18: 0 | V18: 0 | W18: 0
A19: Net Income | B19: Persisted FINMO | C19: -81719.868 | D19: -32560745 | E19: -32376615 | F19: -31940683 | G19: -31244572 | H19: -30283098 | I19: -29041510 | J19: -27514621 | K19: -25694057 | L19: -23574725 | M19: -21141688 | N19: -18389853 | O19: -18121132 | P19: -17852357 | Q19: -17576772 | R19: -17297754 | S19: -17015304 | T19: -16732905 | U19: -16443591 | V19: -16150845 | W19: -15854666
A22: Balance Sheet
A23: Cash | B23: Persisted FINMO | C23: 12000 | D23: 16412979 | E23: 16329700 | F23: 16120690 | G23: 15781762 | H23: 15310323 | I23: 14698996 | J23: 13945190 | K23: 13044716 | L23: 11995028 | M23: 10788657 | N23: 9423056.5 | O23: 9289813.9 | P23: 9156543.4 | Q23: 9019868 | R23: 8881474 | S23: 8741367.3 | T23: 8601284.2 | U23: 8457744.2 | V23: 8312487.3 | W23: 8165514.2
A24: Accounts Receivable | B24: Persisted FINMO | C24: 0 | D24: 86723.927 | E24: 92445.393 | F24: 100461.82 | G24: 105366.64 | H24: 110275.83 | I24: 116441.33 | J24: 124066.37 | K24: 130524.07 | L24: 135603.84 | M24: 142213.36 | N24: 152243.53 | O24: 151297.92 | P24: 150372.86 | Q24: 151092.35 | R24: 155185.44 | S24: 154207.5 | T24: 153250.81 | U24: 153970.3 | V24: 158127.34 | W24: 157117.07
A25: Inventory | B25: Persisted FINMO | C25: 0 | D25: 0 | E25: 0 | F25: 0 | G25: 0 | H25: 0 | I25: 0 | J25: 0 | K25: 0 | L25: 0 | M25: 0 | N25: 0 | O25: 0 | P25: 0 | Q25: 0 | R25: 0 | S25: 0 | T25: 0 | U25: 0 | V25: 0 | W25: 0
A26: Current Assets | B26: Persisted FINMO | C26: 12000 | D26: 17829470 | E26: 17839641 | F26: 17728079 | G26: 17485189 | H26: 17111495 | I26: 16600871 | J26: 15950930 | K26: 15154855 | L26: 14209891 | M26: 13111475 | N26: 11858953 | O26: 11735797 | P26: 11612634 | Q26: 11487710 | R26: 11364441 | S26: 11234389 | T26: 11104381 | U26: 10972592 | V26: 10842525 | W26: 10705574
A27: PPE | B27: Persisted FINMO | C27: 40000 | D27: 40190 | E27: 40370.895 | F27: 40542.593 | G27: 40705.047 | H27: 40858.138 | I27: 41001.755 | J27: 41135.831 | K27: 41260.308 | L27: 41375.094 | M27: 41480.104 | N27: 41575.259 | O27: 41660.53 | P27: 41735.811 | Q27: 41801.002 | R27: 41856.096 | S27: 41901.007 | T27: 41935.659 | U27: 41959.982 | V27: 41973.955 | W27: 41977.48
A28: Accumulated Depreciation | B28: Persisted FINMO | C28: 0 | D28: -10 | E28: -30.05481 | F28: -60.211869 | G28: -100.47066 | H28: -150.90422 | I28: -211.57855 | J28: -282.51159 | K28: -363.71372 | L28: -455.22908 | M28: -557.09456 | N28: -669.33972 | O28: -791.94516 | P28: -924.96723 | Q28: -1068.4549 | R28: -1222.3662 | S28: -1386.7351 | T28: -1561.588 | U28: -1746.9436 | V28: -1942.7709 | W28: -2149.1148
A29: Total Assets | B29: Persisted FINMO | C29: 52000 | D29: 17869660 | E29: 17880012 | F29: 17768621 | G29: 17525894 | H29: 17152353 | I29: 16641873 | J29: 15992065 | K29: 15196115 | L29: 14251266 | M29: 13152955 | N29: 11900528 | O29: 11777457 | P29: 11654369 | Q29: 11529511 | R29: 11406297 | S29: 11276290 | T29: 11146316 | U29: 11014552 | V29: 10884499 | W29: 10747551
A30: Accounts Payable | B30: Persisted FINMO | C30: 4000 | D30: 4199822 | E30: 4086181.7 | F30: 4016185.4 | G30: 3767459.8 | H30: 3478719 | I30: 3182028.8 | J30: 2867245.2 | K30: 2466279.6 | L30: 1991878.3 | M30: 1489759.2 | N30: 953514.86 | O30: 913779.28 | P30: 875689.26 | Q30: 846110.33 | R30: 834349.67 | S30: 794630.46 | T30: 756590.69 | U30: 725732.67 | V30: 709989.44 | W30: 670343.67
A31: Prepaid Expenses (% of Revenue) | B31: Persisted FINMO | C31: 0 | D31: 1329766.9 | E31: 1417496 | F31: 1506927.3 | G31: 1598060.6 | H31: 1690896.1 | I31: 1785433.7 | J31: 1881673.3 | K31: 1979615.1 | L31: 2079258.9 | M31: 2180604.9 | N31: 2283653 | O31: 2294685.1 | P31: 2305717.3 | Q31: 2316749.4 | R31: 2327781.5 | S31: 2338813.7 | T31: 2349845.8 | U31: 2360878 | V31: 2371910.1 | W31: 2382942.2
A32: Short Term Debt | B32: Persisted FINMO | C32: 0 | D32: 6000 | E32: 6000 | F32: 6000 | G32: 6000 | H32: 6000 | I32: 6000 | J32: 6000 | K32: 6000 | L32: 6000 | M32: 6000 | N32: 6000 | O32: 6000 | P32: 6000 | Q32: 6000 | R32: 6000 | S32: 6000 | T32: 4500 | U32: 3000 | V32: 1500 | W32: 0
A33: Deferred Revenue (% of Revenue) | B33: Persisted FINMO | C33: 0 | D33: 0 | E33: 0 | F33: 0 | G33: 0 | H33: 0 | I33: 0 | J33: 0 | K33: 0 | L33: 0 | M33: 0 | N33: 0 | O33: 0 | P33: 0 | Q33: 0 | R33: 0 | S33: 0 | T33: 0 | U33: 0 | V33: 0 | W33: 0
A34: Current Liabilites | B34: Persisted FINMO | C34: 4000 | D34: 4205822 | E34: 4092181.7 | F34: 4022185.4 | G34: 3773459.8 | H34: 3484719 | I34: 3188028.8 | J34: 2873245.2 | K34: 2472279.6 | L34: 1997878.3 | M34: 1495759.2 | N34: 959514.86 | O34: 919779.28 | P34: 881689.26 | Q34: 852110.33 | R34: 840349.67 | S34: 800630.46 | T34: 761090.69 | U34: 728732.67 | V34: 711489.44 | W34: 670343.67
... A41: Total Liabilities & Equity | B41: Persisted FINMO | C41: 52000 | D41: 17869660 | E41: 17880012 | F41: 17768621 | G41: 17525894 | H41: 17152353 | I41: 16641873 | J41: 15992065 | K41: 15196115 | L41: 14251266 | M41: 13152955 | N41: 11900528 | O41: 11777457 | P41: 11654369 | Q41: 11529511 | R41: 11406297 | S41: 11276290 | T41: 11146316 | U41: 11014552 | V41: 10884499 | W41: 10747551
A44: Cash Flow
A45: Beginning Cash | B45: Persisted FINMO | C45: 12000 | D45: 12000 | E45: 16412979 | F45: 16329700 | G45: 16120690 | H45: 15781762 | I45: 15310323 | J45: 14698996 | K45: 13945190 | L45: 13044716 | M45: 11995028 | N45: 10788657 | O45: 9423056.5 | P45: 9289813.9 | Q45: 9156543.4 | R45: 9019868 | S45: 8881474 | T45: 8741367.3 | U45: 8601284.2 | V45: 8457744.2 | W45: 8312487.3
A46: Net Income | B46: Persisted FINMO | C46: -81719.868 | D46: -32560745 | E46: -32376615 | F46: -31940683 | G46: -31244572 | H46: -30283098 | I46: -29041510 | J46: -27514621 | K46: -25694057 | L46: -23574725 | M46: -21141688 | N46: -18389853 | O46: -18121132 | P46: -17852357 | Q46: -17576772 | R46: -17297754 | S46: -17015304 | T46: -16732905 | U46: -16443591 | V46: -16150845 | W46: -15854666
A47: Depreciatoin | B47: Persisted FINMO | C47: 0 | D47: 10 | E47: 20.05481 | F47: 30.157059 | G47: 40.258794 | H47: 50.433553 | I47: 60.674336 | J47: 70.933036 | K47: 81.20213 | L47: 91.515362 | M47: 101.86548 | N47: 112.24516 | O47: 122.60544 | P47: 133.02207 | Q47: 143.48772 | R47: 153.91129 | S47: 164.36889 | T47: 174.8529 | U47: 185.35561 | V47: 195.82724 | W47: 206.34396
A48: Changes in Current Assets | B48: Persisted FINMO | C48: 0 | D48: -1416490.8 | E48: -93450.62 | F48: -97447.681 | G48: -96038.173 | H48: -97744.655 | I48: -100703.05 | J48: -103864.71 | K48: -104399.46 | L48: -104723.64 | M48: -107955.49 | N48: -113078.24 | O48: -10086.527 | P48: -10107.084 | Q48: -11751.626 | R48: -15125.223 | S48: -10054.209 | T48: -10075.458 | U48: -11751.626 | V48: -15189.177 | W48: -10021.87
A49: Changes in Current Liabilites | B49: Persisted FINMO | C49: 0 | D49: 4195822 | E49: -113640.26 | F49: -69996.337 | G49: -248725.58 | H49: -288740.76 | I49: -296690.18 | J49: -314783.67 | K49: -400965.57 | L49: -474401.3 | M49: -502119.05 | N49: -536244.39 | O49: -39735.583 | P49: -38090.016 | Q49: -29578.926 | R49: -11760.662 | S49: -39719.216 | T49: -38039.77 | U49: -30858.015 | V49: -15743.234 | W49: -39645.768
A50: Operating Cash Flow | B50: Persisted FINMO | C50: 0 | D50: -29781404 | E50: -32583686 | F50: -32108096 | G50: -31589296 | H50: -30669533 | I50: -29438842 | J50: -27933198 | K50: -26199341 | L50: -24153758 | M50: -21751661 | N50: -19039064 | O50: -18170832 | P50: -17900421 | Q50: -17617959 | R50: -17324486 | S50: -17064913 | T50: -16780846 | U50: -16486015 | V50: -16181581 | W50: -15904127
A51: Capital Expenditures | B51: Persisted FINMO | C51: 0 | D51: 200 | E51: 200.95 | F51: 201.85448 | G51: 202.71296 | H51: 203.52523 | I51: 204.29069 | J51: 205.00877 | K51: 205.67915 | L51: 206.30154 | M51: 206.87547 | N51: 207.40052 | O51: 207.87629 | P51: 208.30265 | Q51: 208.67905 | R51: 209.00501 | S51: 209.28048 | T51: 209.50504 | U51: 209.6783 | V51: 209.79991 | W51: 209.86977
A52: Investing Cash Flow | B52: Persisted FINMO | C52: 0 | D52: -200 | E52: -200.95 | F52: -201.85448 | G52: -202.71296 | H52: -203.52523 | I52: -204.29069 | J52: -205.00877 | K52: -205.67915 | L52: -206.30154 | M52: -206.87547 | N52: -207.40052 | O52: -207.87629 | P52: -208.30265 | Q52: -208.67905 | R52: -209.00501 | S52: -209.28048 | T52: -209.50504 | U52: -209.6783 | V52: -209.79991 | W52: -209.86977
A53: Debt Issuance (New Borrowing) | B53: Persisted FINMO | C53: 0 | D53: 0 | E53: 0 | F53: 0 | G53: 0 | H53: 0 | I53: 0 | J53: 0 | K53: 0 | L53: 0 | M53: 0 | N53: 0 | O53: 0 | P53: 0 | Q53: 0 | R53: 0 | S53: 0 | T53: 0 | U53: 0 | V53: 0 | W53: 0
A54: Debt Repayment | B54: Persisted FINMO | C54: 0 | D54: -1500 | E54: -1500 | F54: -1500 | G54: -1500 | H54: -1500 | I54: -1500 | J54: -1500 | K54: -1500 | L54: -1500 | M54: -1500 | N54: -1500 | O54: -1500 | P54: -1500 | Q54: -1500 | R54: -1500 | S54: -1500 | T54: -1500 | U54: -1500 | V54: -1500 | W54: -1500
A55: Equity | B55: Persisted FINMO | C55: 0 | D55: 46184083 | E55: 32502108 | F55: 31900788 | G55: 31252071 | H55: 30199797 | I55: 28829220 | J55: 27181097 | K55: 25300572 | L55: 23105777 | M55: 20546996 | N55: 17675171 | O55: 18039297 | P55: 17768859 | Q55: 17482992 | R55: 17187801 | S55: 16926516 | T55: 16642472 | U55: 16344185 | V55: 16038034 | W55: 15758864
A56: Distributions | B56: Persisted FINMO | C56: 0 | D56: 0 | E56: 0 | F56: 0 | G56: 0 | H56: 0 | I56: 0 | J56: 0 | K56: 0 | L56: 0 | M56: 0 | N56: 0 | O56: 0 | P56: 0 | Q56: 0 | R56: 0 | S56: 0 | T56: 0 | U56: 0 | V56: 0 | W56: 0
... A59: Ending Cash | B59: Persisted FINMO | C59: 12000 | D59: 16412979 | E59: 16329700 | F59: 16120690 | G59: 15781762 | H59: 15310323 | I59: 14698996 | J59: 13945190 | K59: 13044716 | L59: 11995028 | M59: 10788657 | N59: 9423056.5 | O59: 9289813.9 | P59: 9156543.4 | Q59: 9019868 | R59: 8881474 | S59: 8741367.3 | T59: 8601284.2 | U59: 8457744.2 | V59: 8312487.3 | W59: 8165514.2

Sheet Checks
A1: Checks
A2: Model Status | B2: =IF(COUNTIF(I7:I172,"FAIL")=0,"OK","FAIL") -> OK
A3: Rule | B3: Only real formula/coherence failures return FAIL. Baseline scenario changes show CHANGED.
A5: Category | B5: Line Item | C5: Sheet | D5: Range / Cell | E5: Actual | F5: Expected | G5: Difference | H5: Tolerance | I5: Status | J5: Notes
A6: Model Coherence Checks
A7: Statement Coherence | B7: Balance Sheet balances Q1 | C7: Cross-sheet | D7: 'FINMO'!D31 | E7: =FINMO!D31 -> 17869163 | F7: =FINMO!D43 -> 17869163 | G7: =E7-F7 -> 0 | H7: 1 | I7: =IF(ABS(G7)<=H7,"OK","FAIL") -> OK | J7: Total assets must equal total liabilities and equity.
A8: Statement Coherence | B8: Cash Flow ties to Balance Sheet Q1 | C8: Cross-sheet | D8: 'FINMO'!D61 | E8: =FINMO!D61 -> 16412482 | F8: =FINMO!D23 -> 16412482 | G8: =E8-F8 -> 0 | H8: 1 | I8: =IF(ABS(G8)<=H8,"OK","FAIL") -> OK | J8: Ending cash must tie to balance-sheet cash.
A9: Statement Coherence | B9: Balance Sheet balances Q20 | C9: Cross-sheet | D9: 'FINMO'!W31 | E9: =FINMO!W31 -> 10732188 | F9: =FINMO!W43 -> 10732188 | G9: =E9-F9 -> -1.0803342e-07 | H9: 1 | I9: =IF(ABS(G9)<=H9,"OK","FAIL") -> OK | J9: Total assets must equal total liabilities and equity.
A10: Statement Coherence | B10: Cash Flow ties to Balance Sheet Q20 | C10: Cross-sheet | D10: 'FINMO'!W61 | E10: =FINMO!W61 -> 8150151.4 | F10: =FINMO!W23 -> 8150151.4 | G10: =E10-F10 -> 0 | H10: 1 | I10: =IF(ABS(G10)<=H10,"OK","FAIL") -> OK | J10: Ending cash must tie to balance-sheet cash.
A11: Schedule Bridge | B11: Revenue Drivers total feeds Model Inputs Revenue | C11: Cross-sheet | D11: 'Revenue Drivers'!C14:W14 | E11: =SUMPRODUCT(ABS('Revenue Drivers'!C14:W14-'Model Inputs'!C11:W11)) -> 0 | F11: 0 | G11: =E11-F11 -> 0 | H11: 1 | I11: =IF(ABS(G11)<=H11,"OK","FAIL") -> OK | J11: Changing Revenue Drivers should update Model Inputs and FINMO without creating a model failure.
A12: Schedule Bridge | B12: Payroll Schedule total feeds Model Inputs Payroll | C12: Cross-sheet | D12: 'Payroll Schedule'!D17:W17 | E12: =SUMPRODUCT(ABS('Payroll Schedule'!D17:W17-'Model Inputs'!D16:W16)) -> 0 | F12: 0 | G12: =E12-F12 -> 0 | H12: 1 | I12: =IF(ABS(G12)<=H12,"OK","FAIL") -> OK | J12: Changing payroll detail should update payroll summary, Model Inputs, and FINMO payroll.
A13: Schedule Bridge | B13: Debt repayment feeds Model Inputs | C13: Cross-sheet | D13: 'Debt Schedule'!C10:W10 | E13: =SUMPRODUCT(ABS('Debt Schedule'!C10:W10-'Model Inputs'!C43:W43)) -> 0 | F13: 0 | G13: =E13-F13 -> 0 | H13: 1 | I13: =IF(ABS(G13)<=H13,"OK","FAIL") -> OK | J13: Debt repayment must flow through the model from actual mechanically capped repayment.
A14: Schedule Bridge | B14: Capital lease additions feed CapEx schedule | C14: Cross-sheet | D14: 'Debt Schedule'!C21:W21 | E14: =SUMPRODUCT(ABS('Debt Schedule'!C21:W21-'CapEx Depreciation'!C9:W9)) -> 0 | F14: 0 | G14: =E14-F14 -> 0 | H14: 1 | I14: =IF(ABS(G14)<=H14,"OK","FAIL") -> OK | J14: Lease additions must affect PPE/depreciation through the CapEx schedule.
A15: Schedule Bridge | B15: Lease/rent feeds Model Inputs | C15: Cross-sheet | D15: 'Cash Equity Schedule'!C12:W12 | E15: =SUMPRODUCT(ABS('Cash Equity Schedule'!C12:W12-'Model Inputs'!C15:W15)) -> 0 | F15: 0 | G15: =E15-F15 -> 0 | H15: 1 | I15: =IF(ABS(G15)<=H15,"OK","FAIL") -> OK | J15: Operating lease/rent must flow through Model Inputs into FINMO.
A16: Schedule Coherence | B16: Payroll summary totals equal payroll detail by quarter | C16: Payroll Schedule | D16: A27:N86 | E16: =SUM(ABS('Payroll Schedule'!C15-SUMIFS('Payroll Schedule'!$G$27:$G$86,'Payroll Schedule'!$A$27:$A$86,0)),ABS('Payroll Schedule'!C16-SUMIFS('Payroll Schedule'!$H$27:$H$86,'Payroll Schedule'!$A$27:$A$86,0)),ABS('Payroll Schedule'!C17-SUMIFS('Payroll Schedule'!$M$27:$M$86,'Payroll Schedule'!$A$27:$A$86,0)),ABS('Payroll Schedule'!D15-SUMIFS('Payroll Schedule'!$G$27:$G$86,'Payroll Schedule'!$A$27:$A$86,1)),ABS('Payroll Schedule'!D16-SUMIFS('Payroll Schedule'!$H$27:$H$86,'Payroll Schedule'!$A$27:$A$86,1)),ABS('Payroll Schedule'!D17-SUMIFS('Payroll Schedule'!$M$27:$M$86,'Payroll Schedule'!$A$27:$A$86,1)),ABS('Payroll Schedule'!E15-SUMIFS('Payroll Schedule'!$G$27:$G$86,'Payroll Schedule'!$A$27:$A$86,2)),ABS('Payroll Schedule'!E16-SUMIFS('Payroll Schedule'!$H$27:$H$86,'Payroll Schedule'!$A$27:$A$86,2)),ABS('Payroll Schedule'!E17-SUMIFS('Payroll Schedule'!$M$27:$M$86,'Payroll Schedule'!$A$27:$A$86,2)),ABS('Payroll Schedule'!F15-SUMIFS('Payroll Schedule'!$G$27:$G$86,'Payroll Schedule'!$A$27:$A$86,3)),ABS('Payroll Schedule'!F16-SUMIFS('Payroll Schedule'!$H$27:$H$86,'Payroll Schedule'!$A$27:$A$86,3)),ABS('Payroll Schedule'!F17-SUMIFS('Payroll Schedule'!$M$27:$M$86,'Payroll Schedule'!$A$27:$A$86,3)),ABS('Payroll Schedule'!G15-SUMIFS('Payroll Schedule'!$G$27:$G$86,'Payroll Schedule'!$A$27:$A$86,4)),ABS('Payroll Schedule'!G16-SUMIFS('Payroll Schedule'!$H$27:$H$86,'Payroll Schedule'!$A$27:$A$86,4)),ABS('Payroll Schedule'!G17-SUMIFS('Payroll Schedule'!$M$27:$M$86,'Payroll Schedule'!$A$27:$A$86,4)),ABS('Payroll Schedule'!H15-SUMIFS('Payroll Schedule'!$G$27:$G$86,'Payroll Schedule'!$A$27:$A$86,5)),ABS('Payroll Schedule'!H16-SUMIFS('Payroll Schedule'!$H$27:$H$86,'Payroll Schedule'!$A$27:$A$86,5)),ABS('Payroll Schedule'!H17-SUMIFS('Payroll Schedule'!$M$27:$M$86,'Payroll Schedule'!$A$27:$A$86,5)),ABS('Payroll Schedule'!I15-SUMIFS('Payroll Schedule'!$G$27:$G$86,'Payroll Schedule'!$A$27:$A$86,6)),ABS('Payroll Schedule'!I16-SUMIFS('Payroll Schedule'!$H$27:$H$86,'Payroll Schedule'!$A$27:$A$86,6)),ABS('Payroll Schedule'!I17-SUMIFS('Payroll Schedule'!$M$27:$M$86,'Payroll Schedule'!$A$27:$A$86,6)),ABS('Payroll Schedule'!J15-SUMIFS('Payroll Schedule'!$G$27:$G$86,'Payroll Schedule'!$A$27:$A$86,7)),ABS('Payroll Schedule'!J16-SUMIFS('Payroll Schedule'!$H$27:$H$86,'Payroll Schedule'!$A$27:$A$86,7)),ABS('Payroll Schedule'!J17-SUMIFS('Payroll Schedule'!$M$27:$M$86,'Payroll Schedule'!$A$27:$A$86,7)),ABS('Payroll Schedule'!K15-SUMIFS('Payroll Schedule'!$G$27:$G$86,'Payroll Schedule'!$A$27:$A$86,8)),ABS('Payroll Schedule'!K16-SUMIFS('Payroll Schedule'!$H$27:$H$86,'Payroll Schedule'!$A$27:$A$86,8)),ABS('Payroll Schedule'!K17-SUMIFS('Payroll Schedule'!$M$27:$M$86,'Payroll Schedule'!$A$27:$A$86,8)),ABS('Payroll Schedule'!L15-SUMIFS('Payroll Schedule'!$G$27:$G$86,'Payroll Schedule'!$A$27:$A$86,9)),ABS('Payroll Schedule'!L16-SUMIFS('Payroll Schedule'!$H$27:$H$86,'Payroll Schedule'!$A$27:$A$86,9)),ABS('Payroll Schedule'!L17-SUMIFS('Payroll Schedule'!$M$27:$M$86,'Payroll Schedule'!$A$27:$A$86,9)),ABS('Payroll Schedule'!M15-SUMIFS('Payroll Schedule'!$G$27:$G$86,'Payroll Schedule'!$A$27:$A$86,10)),ABS('Payroll Schedule'!M16-SUMIFS('Payroll Schedule'!$H$27:$H$86,'Payroll Schedule'!$A$27:$A$86,10)),ABS('Payroll Schedule'!M17-SUMIFS('Payroll Schedule'!$M$27:$M$86,'Payroll Schedule'!$A$27:$A$86,10)),ABS('Payroll Schedule'!N15-SUMIFS('Payroll Schedule'!$G$27:$G$86,'Payroll Schedule'!$A$27:$A$86,11)),ABS('Payroll Schedule'!N16-SUMIFS('Payroll Schedule'!$H$27:$H$86,'Payroll Schedule'!$A$27:$A$86,11)),ABS('Payroll Schedule'!N17-SUMIFS('Payroll Schedule'!$M$27:$M$86,'Payroll Schedule'!$A$27:$A$86,11)),ABS('Payroll Schedule'!O15-SUMIFS('Payroll Schedule'!$G$27:$G$86,'Payroll Schedule'!$A$27:$A$86,12)),ABS('Payroll Schedule'!O16-SUMIFS('Payroll Schedule'!$H$27:$H$86,'Payroll Schedule'!$A$27:$A$86,12)),ABS('Payroll Schedule'!O17-SUMIFS('Payroll Schedule'!$M$27:$M$86,'Payroll Schedule'!$A$27:$A$86,12)),ABS('Payroll Schedule'!P15-SUMIFS('Payroll Schedule'!$G$27:$G$86,'Payroll Schedule'!$A$27:$A$86,13)),ABS('Payroll Schedule'!P16-SUMIFS('Payroll Schedule'!$H$27:$H$86,'Payroll Schedule'!$A$27:$A$86,13)),ABS('Payroll Schedule'!P17-SUMIFS('Payroll Schedule'!$M$27:$M$86,'Payroll Schedule'!$A$27:$A$86,13)),ABS('Payroll Schedule'!Q15-SUMIFS('Payroll Schedule'!$G$27:$G$86,'Payroll Schedule'!$A$27:$A$86,14)),ABS('Payroll Schedule'!Q16-SUMIFS('Payroll Schedule'!$H$27:$H$86,'Payroll Schedule'!$A$27:$A$86,14)),ABS('Payroll Schedule'!Q17-SUMIFS('Payroll Schedule'!$M$27:$M$86,'Payroll Schedule'!$A$27:$A$86,14)),ABS('Payroll Schedule'!R15-SUMIFS('Payroll Schedule'!$G$27:$G$86,'Payroll Schedule'!$A$27:$A$86,15)),ABS('Payroll Schedule'!R16-SUMIFS('Payroll Schedule'!$H$27:$H$86,'Payroll Schedule'!$A$27:$A$86,15)),ABS('Payroll Schedule'!R17-SUMIFS('Payroll Schedule'!$M$27:$M$86,'Payroll Schedule'!$A$27:$A$86,15)),ABS('Payroll Schedule'!S15-SUMIFS('Payroll Schedule'!$G$27:$G$86,'Payroll Schedule'!$A$27:$A$86,16)),ABS('Payroll Schedule'!S16-SUMIFS('Payroll Schedule'!$H$27:$H$86,'Payroll Schedule'!$A$27:$A$86,16)),ABS('Payroll Schedule'!S17-SUMIFS('Payroll Schedule'!$M$27:$M$86,'Payroll Schedule'!$A$27:$A$86,16)),ABS('Payroll Schedule'!T15-SUMIFS('Payroll Schedule'!$G$27:$G$86,'Payroll Schedule'!$A$27:$A$86,17)),ABS('Payroll Schedule'!T16-SUMIFS('Payroll Schedule'!$H$27:$H$86,'Payroll Schedule'!$A$27:$A$86,17)),ABS('Payroll Schedule'!T17-SUMIFS('Payroll Schedule'!$M$27:$M$86,'Payroll Schedule'!$A$27:$A$86,17)),ABS('Payroll Schedule'!U15-SUMIFS('Payroll Schedule'!$G$27:$G$86,'Payroll Schedule'!$A$27:$A$86,18)),ABS('Payroll Schedule'!U16-SUMIFS('Payroll Schedule'!$H$27:$H$86,'Payroll Schedule'!$A$27:$A$86,18)),ABS('Payroll Schedule'!U17-SUMIFS('Payroll Schedule'!$M$27:$M$86,'Payroll Schedule'!$A$27:$A$86,18)),ABS('Payroll Schedule'!V15-SUMIFS('Payroll Schedule'!$G$27:$G$86,'Payroll Schedule'!$A$27:$A$86,19)),ABS('Payroll Schedule'!V16-SUMIFS('Payroll Schedule'!$H$27:$H$86,'Payroll Schedule'!$A$27:$A$86,19)),ABS('Payroll Schedule'!V17-SUMIFS('Payroll Schedule'!$M$27:$M$86,'Payroll Schedule'!$A$27:$A$86,19)),ABS('Payroll Schedule'!W15-SUMIFS('Payroll Schedule'!$G$27:$G$86,'Payroll Schedule'!$A$27:$A$86,20)),ABS('Payroll Schedule'!W16-SUMIFS('Payroll Schedule'!$H$27:$H$86,'Payroll Schedule'!$A$27:$A$86,20)),ABS('Payroll Schedule'!W17-SUMIFS('Payroll Schedule'!$M$27:$M$86,'Payroll Schedule'!$A$27:$A$86,20))) -> 0 | F16: 0 | G16: =E16-F16 -> 0 | H16: 1 | I16: =IF(ABS(G16)<=H16,"OK","FAIL") -> OK | J16: If this fails, payroll summary is no longer tied to detail FTE/payroll rows.
A17: Schedule Coherence | B17: Payroll productivity metrics | C17: Payroll Schedule | D17: A16:W22 | E17: =SUM(ABS('Payroll Schedule'!C20-IFERROR('Payroll Schedule'!C18/'Payroll Schedule'!C16,0)),ABS('Payroll Schedule'!C21-IFERROR('Payroll Schedule'!C19/'Payroll Schedule'!C16,0)),ABS('Payroll Schedule'!C22-IFERROR('Payroll Schedule'!C17/'Payroll Schedule'!C18,0)),ABS('Payroll Schedule'!D20-IFERROR('Payroll Schedule'!D18/'Payroll Schedule'!D16,0)),ABS('Payroll Schedule'!D21-IFERROR('Payroll Schedule'!D19/'Payroll Schedule'!D16,0)),ABS('Payroll Schedule'!D22-IFERROR('Payroll Schedule'!D17/'Payroll Schedule'!D18,0)),ABS('Payroll Schedule'!E20-IFERROR('Payroll Schedule'!E18/'Payroll Schedule'!E16,0)),ABS('Payroll Schedule'!E21-IFERROR('Payroll Schedule'!E19/'Payroll Schedule'!E16,0)),ABS('Payroll Schedule'!E22-IFERROR('Payroll Schedule'!E17/'Payroll Schedule'!E18,0)),ABS('Payroll Schedule'!F20-IFERROR('Payroll Schedule'!F18/'Payroll Schedule'!F16,0)),ABS('Payroll Schedule'!F21-IFERROR('Payroll Schedule'!F19/'Payroll Schedule'!F16,0)),ABS('Payroll Schedule'!F22-IFERROR('Payroll Schedule'!F17/'Payroll Schedule'!F18,0)),ABS('Payroll Schedule'!G20-IFERROR('Payroll Schedule'!G18/'Payroll Schedule'!G16,0)),ABS('Payroll Schedule'!G21-IFERROR('Payroll Schedule'!G19/'Payroll Schedule'!G16,0)),ABS('Payroll Schedule'!G22-IFERROR('Payroll Schedule'!G17/'Payroll Schedule'!G18,0)),ABS('Payroll Schedule'!H20-IFERROR('Payroll Schedule'!H18/'Payroll Schedule'!H16,0)),ABS('Payroll Schedule'!H21-IFERROR('Payroll Schedule'!H19/'Payroll Schedule'!H16,0)),ABS('Payroll Schedule'!H22-IFERROR('Payroll Schedule'!H17/'Payroll Schedule'!H18,0)),ABS('Payroll Schedule'!I20-IFERROR('Payroll Schedule'!I18/'Payroll Schedule'!I16,0)),ABS('Payroll Schedule'!I21-IFERROR('Payroll Schedule'!I19/'Payroll Schedule'!I16,0)),ABS('Payroll Schedule'!I22-IFERROR('Payroll Schedule'!I17/'Payroll Schedule'!I18,0)),ABS('Payroll Schedule'!J20-IFERROR('Payroll Schedule'!J18/'Payroll Schedule'!J16,0)),ABS('Payroll Schedule'!J21-IFERROR('Payroll Schedule'!J19/'Payroll Schedule'!J16,0)),ABS('Payroll Schedule'!J22-IFERROR('Payroll Schedule'!J17/'Payroll Schedule'!J18,0)),ABS('Payroll Schedule'!K20-IFERROR('Payroll Schedule'!K18/'Payroll Schedule'!K16,0)),ABS('Payroll Schedule'!K21-IFERROR('Payroll Schedule'!K19/'Payroll Schedule'!K16,0)),ABS('Payroll Schedule'!K22-IFERROR('Payroll Schedule'!K17/'Payroll Schedule'!K18,0)),ABS('Payroll Schedule'!L20-IFERROR('Payroll Schedule'!L18/'Payroll Schedule'!L16,0)),ABS('Payroll Schedule'!L21-IFERROR('Payroll Schedule'!L19/'Payroll Schedule'!L16,0)),ABS('Payroll Schedule'!L22-IFERROR('Payroll Schedule'!L17/'Payroll Schedule'!L18,0)),ABS('Payroll Schedule'!M20-IFERROR('Payroll Schedule'!M18/'Payroll Schedule'!M16,0)),ABS('Payroll Schedule'!M21-IFERROR('Payroll Schedule'!M19/'Payroll Schedule'!M16,0)),ABS('Payroll Schedule'!M22-IFERROR('Payroll Schedule'!M17/'Payroll Schedule'!M18,0)),ABS('Payroll Schedule'!N20-IFERROR('Payroll Schedule'!N18/'Payroll Schedule'!N16,0)),ABS('Payroll Schedule'!N21-IFERROR('Payroll Schedule'!N19/'Payroll Schedule'!N16,0)),ABS('Payroll Schedule'!N22-IFERROR('Payroll Schedule'!N17/'Payroll Schedule'!N18,0)),ABS('Payroll Schedule'!O20-IFERROR('Payroll Schedule'!O18/'Payroll Schedule'!O16,0)),ABS('Payroll Schedule'!O21-IFERROR('Payroll Schedule'!O19/'Payroll Schedule'!O16,0)),ABS('Payroll Schedule'!O22-IFERROR('Payroll Schedule'!O17/'Payroll Schedule'!O18,0)),ABS('Payroll Schedule'!P20-IFERROR('Payroll Schedule'!P18/'Payroll Schedule'!P16,0)),ABS('Payroll Schedule'!P21-IFERROR('Payroll Schedule'!P19/'Payroll Schedule'!P16,0)),ABS('Payroll Schedule'!P22-IFERROR('Payroll Schedule'!P17/'Payroll Schedule'!P18,0)),ABS('Payroll Schedule'!Q20-IFERROR('Payroll Schedule'!Q18/'Payroll Schedule'!Q16,0)),ABS('Payroll Schedule'!Q21-IFERROR('Payroll Schedule'!Q19/'Payroll Schedule'!Q16,0)),ABS('Payroll Schedule'!Q22-IFERROR('Payroll Schedule'!Q17/'Payroll Schedule'!Q18,0)),ABS('Payroll Schedule'!R20-IFERROR('Payroll Schedule'!R18/'Payroll Schedule'!R16,0)),ABS('Payroll Schedule'!R21-IFERROR('Payroll Schedule'!R19/'Payroll Schedule'!R16,0)),ABS('Payroll Schedule'!R22-IFERROR('Payroll Schedule'!R17/'Payroll Schedule'!R18,0)),ABS('Payroll Schedule'!S20-IFERROR('Payroll Schedule'!S18/'Payroll Schedule'!S16,0)),ABS('Payroll Schedule'!S21-IFERROR('Payroll Schedule'!S19/'Payroll Schedule'!S16,0)),ABS('Payroll Schedule'!S22-IFERROR('Payroll Schedule'!S17/'Payroll Schedule'!S18,0)),ABS('Payroll Schedule'!T20-IFERROR('Payroll Schedule'!T18/'Payroll Schedule'!T16,0)),ABS('Payroll Schedule'!T21-IFERROR('Payroll Schedule'!T19/'Payroll Schedule'!T16,0)),ABS('Payroll Schedule'!T22-IFERROR('Payroll Schedule'!T17/'Payroll Schedule'!T18,0)),ABS('Payroll Schedule'!U20-IFERROR('Payroll Schedule'!U18/'Payroll Schedule'!U16,0)),ABS('Payroll Schedule'!U21-IFERROR('Payroll Schedule'!U19/'Payroll Schedule'!U16,0)),ABS('Payroll Schedule'!U22-IFERROR('Payroll Schedule'!U17/'Payroll Schedule'!U18,0)),ABS('Payroll Schedule'!V20-IFERROR('Payroll Schedule'!V18/'Payroll Schedule'!V16,0)),ABS('Payroll Schedule'!V21-IFERROR('Payroll Schedule'!V19/'Payroll Schedule'!V16,0)),ABS('Payroll Schedule'!V22-IFERROR('Payroll Schedule'!V17/'Payroll Schedule'!V18,0)),ABS('Payroll Schedule'!W20-IFERROR('Payroll Schedule'!W18/'Payroll Schedule'!W16,0)),ABS('Payroll Schedule'!W21-IFERROR('Payroll Schedule'!W19/'Payroll Schedule'!W16,0)),ABS('Payroll Schedule'!W22-IFERROR('Payroll Schedule'!W17/'Payroll Schedule'!W18,0))) -> 0 | F17: 0 | G17: =E17-F17 -> 0 | H17: 0.01 | I17: =IF(ABS(G17)<=H17,"OK","FAIL") -> OK | J17: Revenue per employee, units per employee, and payroll percent must stay tied to revenue/capacity and average FTE.
A18: Schedule Coherence | B18: Payroll detail FTE math | C18: Payroll Schedule | D18: E27:H86 | E18: =SUMPRODUCT(ABS('Payroll Schedule'!G27:G86-('Payroll Schedule'!E27:E86+'Payroll Schedule'!F27:F86)))+SUMPRODUCT(ABS('Payroll Schedule'!H27:H86-(('Payroll Schedule'!E27:E86+'Payroll Schedule'!G27:G86)/2))) -> 0 | F18: 0 | G18: =E18-F18 -> 0 | H18: 0.01 | I18: =IF(ABS(G18)<=H18,"OK","FAIL") -> OK | J18: Ending FTE must equal starting FTE plus hires; average FTE must be the average of starting and ending FTE.
A19: Schedule Coherence | B19: Payroll detail wage and tax math | C19: Payroll Schedule | D19: I27:M86 | E19: =SUMPRODUCT(ABS('Payroll Schedule'!K27:K86-('Payroll Schedule'!H27:H86*'Payroll Schedule'!I27:I86/4)))+SUMPRODUCT(ABS('Payroll Schedule'!L27:L86-('Payroll Schedule'!K27:K86*'Payroll Schedule'!J27:J86)))+SUMPRODUCT(ABS('Payroll Schedule'!M27:M86-('Payroll Schedule'!K27:K86+'Payroll Schedule'!L27:L86))) -> 0 | F19: 0 | G19: =E19-F19 -> 0 | H19: 1 | I19: =IF(ABS(G19)<=H19,"OK","FAIL") -> OK | J19: Payroll dollars must flow from average FTE, wage, benefits/taxes, and total payroll formulas.
A21: Line-Item Formula Logic Diagnostics
A22: Formula Logic | B22: Revenue calculation - lob_1_product_1 | C22: Revenue Drivers | D22: 'Revenue Drivers'!C11:W11 | E22: =SUMPRODUCT(ABS('Revenue Drivers'!C11:W11-('Revenue Drivers'!C8:W8*'Revenue Drivers'!C9:W9*'Revenue Drivers'!C10:W10))) -> 0 | F22: 0 | G22: =E22-F22 -> 0 | H22: 1 | I22: =IF(ABS(G22)<=H22,"OK","FAIL") -> OK | J22: Revenue rows must equal capacity x unit price x utilization.
A23: Formula Logic | B23: Revenue total equals all revenue products | C23: Revenue Drivers | D23: 'Revenue Drivers'!C14:W14 | E23: =SUMPRODUCT(ABS('Revenue Drivers'!C14:W14-('Revenue Drivers'!C11:W11))) -> 0 | F23: 0 | G23: =E23-F23 -> 0 | H23: 1 | I23: =IF(ABS(G23)<=H23,"OK","FAIL") -> OK | J23: Total revenue must stay tied to all revenue-product rows.
A24: Formula Logic | B24: Revenue total capacity equals all capacity products | C24: Revenue Drivers | D24: 'Revenue Drivers'!C13:W13 | E24: =SUMPRODUCT(ABS('Revenue Drivers'!C13:W13-('Revenue Drivers'!C8:W8))) -> 0 | F24: 0 | G24: =E24-F24 -> 0 | H24: 0.01 | I24: =IF(ABS(G24)<=H24,"OK","FAIL") -> OK | J24: Total capacity units must stay tied to all revenue-driver capacity rows.
A25: Formula Logic | B25: Debt opening balance continuity | C25: Debt Schedule | D25: 'Debt Schedule'!D7:W7 | E25: =SUMPRODUCT(ABS('Debt Schedule'!D7:W7-'Debt Schedule'!C11:V11)) -> 0 | F25: 0 | G25: =E25-F25 -> 0 | H25: 1 | I25: =IF(ABS(G25)<=H25,"OK","FAIL") -> OK | J25: Each quarter's opening debt must equal the prior quarter's closing debt.
A26: Formula Logic | B26: Actual debt repayment cap | C26: Debt Schedule | D26: 'Debt Schedule'!C10:W10 | E26: =SUMPRODUCT(--(('Debt Schedule'!C10:W10-'Debt Schedule'!C9:W9)>1))+SUMPRODUCT(--(('Debt Schedule'!C10:W10-('Debt Schedule'!C7:W7+'Debt Schedule'!C8:W8))>1)) -> 0 | F26: 0 | G26: =E26-F26 -> 0 | H26: 0 | I26: =IF(ABS(G26)<=H26,"OK","FAIL") -> OK | J26: Actual repayment must not exceed requested repayment or available debt balance.
A27: Formula Logic | B27: Closing debt formula | C27: Debt Schedule | D27: 'Debt Schedule'!C11:W11 | E27: =SUMPRODUCT(ABS('Debt Schedule'!C11:W11-('Debt Schedule'!C7:W7+'Debt Schedule'!C8:W8-'Debt Schedule'!C10:W10))) -> 0 | F27: 0 | G27: =E27-F27 -> 0 | H27: 1 | I27: =IF(ABS(G27)<=H27,"OK","FAIL") -> OK | J27: Closing debt must equal opening debt plus issuance less actual repayment, floored at zero.
A28: Formula Logic | B28: Interest expense formula | C28: Debt Schedule | D28: 'Debt Schedule'!C13:W13 | E28: =SUMPRODUCT(ABS('Debt Schedule'!C13:W13-((('Debt Schedule'!C7:W7+'Debt Schedule'!C11:W11)/2)*'Debt Schedule'!C12:W12))) -> 0 | F28: 0 | G28: =E28-F28 -> 0 | H28: 1 | I28: =IF(ABS(G28)<=H28,"OK","FAIL") -> OK | J28: Interest expense must equal average debt balance times interest rate.
A29: Formula Logic | B29: Debt service formula | C29: Debt Schedule | D29: 'Debt Schedule'!C14:W14 | E29: =SUMPRODUCT(ABS('Debt Schedule'!C14:W14-('Debt Schedule'!C13:W13+'Debt Schedule'!C10:W10))) -> 0 | F29: 0 | G29: =E29-F29 -> 0 | H29: 1 | I29: =IF(ABS(G29)<=H29,"OK","FAIL") -> OK | J29: Debt service must equal interest expense plus actual debt repayment.
A30: Formula Logic | B30: Lease opening balance continuity | C30: Debt Schedule | D30: 'Debt Schedule'!D18:W18 | E30: =SUMPRODUCT(ABS('Debt Schedule'!D18:W18-'Debt Schedule'!C23:V23)) -> 0 | F30: 0 | G30: =E30-F30 -> 0 | H30: 1 | I30: =IF(ABS(G30)<=H30,"OK","FAIL") -> OK | J30: Each quarter's opening lease balance must equal the prior quarter's closing lease balance.
A31: Formula Logic | B31: Lease principal repayment cap | C31: Debt Schedule | D31: 'Debt Schedule'!C20:W20 | E31: =SUMPRODUCT(--(('Debt Schedule'!C20:W20-'Debt Schedule'!C19:W19)>1))+SUMPRODUCT(--(('Debt Schedule'!C20:W20-('Debt Schedule'!C18:W18+'Debt Schedule'!C21:W21))>1)) -> 0 | F31: 0 | G31: =E31-F31 -> 0 | H31: 0 | I31: =IF(ABS(G31)<=H31,"OK","FAIL") -> OK | J31: Lease principal repayment must not exceed requested repayment or available lease balance.
A32: Formula Logic | B32: Lease closing balance formula | C32: Debt Schedule | D32: 'Debt Schedule'!C23:W23 | E32: =SUMPRODUCT(ABS('Debt Schedule'!C23:W23-('Debt Schedule'!C18:W18+'Debt Schedule'!C21:W21-'Debt Schedule'!C20:W20))) -> 0 | F32: 0 | G32: =E32-F32 -> 0 | H32: 1 | I32: =IF(ABS(G32)<=H32,"OK","FAIL") -> OK | J32: Lease closing balance must equal opening balance plus additions less principal repayment, floored at zero.
A33: Formula Logic | B33: PPE opening balance continuity | C33: CapEx Depreciation | D33: 'CapEx Depreciation'!D7:W7 | E33: =SUMPRODUCT(ABS('CapEx Depreciation'!D7:W7-'CapEx Depreciation'!C12:V12)) -> 0 | F33: 0 | G33: =E33-F33 -> 0 | H33: 1 | I33: =IF(ABS(G33)<=H33,"OK","FAIL") -> OK | J33: Each quarter's opening PPE must equal the prior quarter's closing PPE.
A34: Formula Logic | B34: Depreciation expense formula | C34: CapEx Depreciation | D34: 'CapEx Depreciation'!C11:W11 | E34: =SUMPRODUCT(ABS('CapEx Depreciation'!C11:W11-('CapEx Depreciation'!C7:W7*'CapEx Depreciation'!C10:W10))) -> 0 | F34: 0 | G34: =E34-F34 -> 0 | H34: 1 | I34: =IF(ABS(G34)<=H34,"OK","FAIL") -> OK | J34: Depreciation must equal opening PPE times rate, capped at opening PPE.
A35: Formula Logic | B35: Closing PPE formula | C35: CapEx Depreciation | D35: 'CapEx Depreciation'!C12:W12 | E35: =SUMPRODUCT(ABS('CapEx Depreciation'!C12:W12-('CapEx Depreciation'!C7:W7+'CapEx Depreciation'!C8:W8+'CapEx Depreciation'!C9:W9-'CapEx Depreciation'!C11:W11))) -> 0 | F35: 0 | G35: =E35-F35 -> 0 | H35: 1 | I35: =IF(ABS(G35)<=H35,"OK","FAIL") -> OK | J35: Closing PPE must include capex and lease additions and subtract depreciation.
A36: Formula Logic | B36: Accumulated depreciation continuity | C36: CapEx Depreciation | D36: 'CapEx Depreciation'!D13:W13 | E36: =SUMPRODUCT(ABS('CapEx Depreciation'!D13:W13-'CapEx Depreciation'!C14:V14)) -> 0 | F36: 0 | G36: =E36-F36 -> 0 | H36: 1 | I36: =IF(ABS(G36)<=H36,"OK","FAIL") -> OK | J36: Opening accumulated depreciation must equal the prior quarter's accumulated depreciation.
A37: Formula Logic | B37: Accumulated depreciation formula | C37: CapEx Depreciation | D37: 'CapEx Depreciation'!C14:W14 | E37: =SUMPRODUCT(ABS('CapEx Depreciation'!C14:W14-('CapEx Depreciation'!C13:W13-'CapEx Depreciation'!C11:W11))) -> 0 | F37: 0 | G37: =E37-F37 -> 0 | H37: 1 | I37: =IF(ABS(G37)<=H37,"OK","FAIL") -> OK | J37: Accumulated depreciation must roll forward by depreciation expense.
A39: Formula Manifest by Line Item
A40: Formula Manifest | B40: Revenue Drivers - Total Revenue | C40: Revenue Drivers | D40: 'Revenue Drivers'!C14:W14 | E40: =21 -> 21 | F40: 21 | G40: =E40-F40 -> 0 | H40: 0 | I40: =IF(G40=0,"OK","FAIL") -> OK | J40: This line is expected to be formula-driven across every period. Formula presence is verified at export; live edit integrity is covered by the logic and bridge checks above.
A41: Formula Manifest | B41: Revenue Drivers - Total Capacity Units | C41: Revenue Drivers | D41: 'Revenue Drivers'!C13:W13 | E41: =21 -> 21 | F41: 21 | G41: =E41-F41 -> 0 | H41: 0 | I41: =IF(G41=0,"OK","FAIL") -> OK | J41: This line is expected to be formula-driven across every period. Formula presence is verified at export; live edit integrity is covered by the logic and bridge checks above.
A42: Formula Manifest | B42: Revenue Drivers - Actual Revenue QoQ Growth | C42: Revenue Drivers | D42: 'Revenue Drivers'!C17:W17 | E42: =21 -> 21 | F42: 21 | G42: =E42-F42 -> 0 | H42: 0 | I42: =IF(G42=0,"OK","FAIL") -> OK | J42: This line is expected to be formula-driven across every period. Formula presence is verified at export; live edit integrity is covered by the logic and bridge checks above.
A43: Formula Manifest | B43: Payroll Schedule - Total Ending FTE | C43: Payroll Schedule | D43: 'Payroll Schedule'!C15:W15 | E43: =21 -> 21 | F43: 21 | G43: =E43-F43 -> 0 | H43: 0 | I43: =IF(G43=0,"OK","FAIL") -> OK | J43: This line is expected to be formula-driven across every period. Formula presence is verified at export; live edit integrity is covered by the logic and bridge checks above.
A44: Formula Manifest | B44: Payroll Schedule - Total Average FTE | C44: Payroll Schedule | D44: 'Payroll Schedule'!C16:W16 | E44: =21 -> 21 | F44: 21 | G44: =E44-F44 -> 0 | H44: 0 | I44: =IF(G44=0,"OK","FAIL") -> OK | J44: This line is expected to be formula-driven across every period. Formula presence is verified at export; live edit integrity is covered by the logic and bridge checks above.
A45: Formula Manifest | B45: Payroll Schedule - Total Payroll | C45: Payroll Schedule | D45: 'Payroll Schedule'!C17:W17 | E45: =21 -> 21 | F45: 21 | G45: =E45-F45 -> 0 | H45: 0 | I45: =IF(G45=0,"OK","FAIL") -> OK | J45: This line is expected to be formula-driven across every period. Formula presence is verified at export; live edit integrity is covered by the logic and bridge checks above.
A46: Formula Manifest | B46: Payroll Schedule - Total Revenue | C46: Payroll Schedule | D46: 'Payroll Schedule'!C18:W18 | E46: =21 -> 21 | F46: 21 | G46: =E46-F46 -> 0 | H46: 0 | I46: =IF(G46=0,"OK","FAIL") -> OK | J46: This line is expected to be formula-driven across every period. Formula presence is verified at export; live edit integrity is covered by the logic and bridge checks above.
A47: Formula Manifest | B47: Payroll Schedule - Total Capacity Units | C47: Payroll Schedule | D47: 'Payroll Schedule'!C19:W19 | E47: =21 -> 21 | F47: 21 | G47: =E47-F47 -> 0 | H47: 0 | I47: =IF(G47=0,"OK","FAIL") -> OK | J47: This line is expected to be formula-driven across every period. Formula presence is verified at export; live edit integrity is covered by the logic and bridge checks above.
A48: Formula Manifest | B48: Payroll Schedule - Revenue per Employee | C48: Payroll Schedule | D48: 'Payroll Schedule'!C20:W20 | E48: =21 -> 21 | F48: 21 | G48: =E48-F48 -> 0 | H48: 0 | I48: =IF(G48=0,"OK","FAIL") -> OK | J48: This line is expected to be formula-driven across every period. Formula presence is verified at export; live edit integrity is covered by the logic and bridge checks above.
A49: Formula Manifest | B49: Payroll Schedule - Units per Employee | C49: Payroll Schedule | D49: 'Payroll Schedule'!C21:W21 | E49: =21 -> 21 | F49: 21 | G49: =E49-F49 -> 0 | H49: 0 | I49: =IF(G49=0,"OK","FAIL") -> OK | J49: This line is expected to be formula-driven across every period. Formula presence is verified at export; live edit integrity is covered by the logic and bridge checks above.
A50: Formula Manifest | B50: Payroll Schedule - Payroll % of Revenue | C50: Payroll Schedule | D50: 'Payroll Schedule'!C22:W22 | E50: =21 -> 21 | F50: 21 | G50: =E50-F50 -> 0 | H50: 0 | I50: =IF(G50=0,"OK","FAIL") -> OK | J50: This line is expected to be formula-driven across every period. Formula presence is verified at export; live edit integrity is covered by the logic and bridge checks above.
A51: Formula Manifest | B51: CapEx Schedule - Lease Additions | C51: CapEx Depreciation | D51: 'CapEx Depreciation'!D9:W9 | E51: =20 -> 20 | F51: 20 | G51: =E51-F51 -> 0 | H51: 0 | I51: =IF(G51=0,"OK","FAIL") -> OK | J51: This line is expected to be formula-driven across every period. Formula presence is verified at export; live edit integrity is covered by the logic and bridge checks above.
A52: Formula Manifest | B52: CapEx Schedule - Closing PPE | C52: CapEx Depreciation | D52: 'CapEx Depreciation'!C12:W12 | E52: =21 -> 21 | F52: 21 | G52: =E52-F52 -> 0 | H52: 0 | I52: =IF(G52=0,"OK","FAIL") -> OK | J52: This line is expected to be formula-driven across every period. Formula presence is verified at export; live edit integrity is covered by the logic and bridge checks above.
A53: Formula Manifest | B53: Debt Schedule - Opening Debt | C53: Debt Schedule | D53: 'Debt Schedule'!D7:W7 | E53: =20 -> 20 | F53: 20 | G53: =E53-F53 -> 0 | H53: 0 | I53: =IF(G53=0,"OK","FAIL") -> OK | J53: This debt/lease line is expected to be formula-driven across every period. Formula presence is verified at export; live edit integrity is covered by the logic and bridge checks above.
A54: Formula Manifest | B54: Debt Schedule - Actual Debt Repayment | C54: Debt Schedule | D54: 'Debt Schedule'!C10:W10 | E54: =21 -> 21 | F54: 21 | G54: =E54-F54 -> 0 | H54: 0 | I54: =IF(G54=0,"OK","FAIL") -> OK | J54: This debt/lease line is expected to be formula-driven across every period. Formula presence is verified at export; live edit integrity is covered by the logic and bridge checks above.
A55: Formula Manifest | B55: Debt Schedule - Closing Debt | C55: Debt Schedule | D55: 'Debt Schedule'!C11:W11 | E55: =21 -> 21 | F55: 21 | G55: =E55-F55 -> 0 | H55: 0 | I55: =IF(G55=0,"OK","FAIL") -> OK | J55: This debt/lease line is expected to be formula-driven across every period. Formula presence is verified at export; live edit integrity is covered by the logic and bridge checks above.
A56: Formula Manifest | B56: Debt Schedule - Interest Expense | C56: Debt Schedule | D56: 'Debt Schedule'!C13:W13 | E56: =21 -> 21 | F56: 21 | G56: =E56-F56 -> 0 | H56: 0 | I56: =IF(G56=0,"OK","FAIL") -> OK | J56: This debt/lease line is expected to be formula-driven across every period. Formula presence is verified at export; live edit integrity is covered by the logic and bridge checks above.
A57: Formula Manifest | B57: Debt Schedule - Total Debt Service | C57: Debt Schedule | D57: 'Debt Schedule'!C14:W14 | E57: =21 -> 21 | F57: 21 | G57: =E57-F57 -> 0 | H57: 0 | I57: =IF(G57=0,"OK","FAIL") -> OK | J57: This debt/lease line is expected to be formula-driven across every period. Formula presence is verified at export; live edit integrity is covered by the logic and bridge checks above.
A58: Formula Manifest | B58: Debt Schedule - Lease Opening Balance | C58: Debt Schedule | D58: 'Debt Schedule'!D18:W18 | E58: =20 -> 20 | F58: 20 | G58: =E58-F58 -> 0 | H58: 0 | I58: =IF(G58=0,"OK","FAIL") -> OK | J58: This debt/lease line is expected to be formula-driven across every period. Formula presence is verified at export; live edit integrity is covered by the logic and bridge checks above.
A59: Formula Manifest | B59: Debt Schedule - Lease Principal Repayments | C59: Debt Schedule | D59: 'Debt Schedule'!C20:W20 | E59: =21 -> 21 | F59: 21 | G59: =E59-F59 -> 0 | H59: 0 | I59: =IF(G59=0,"OK","FAIL") -> OK | J59: This debt/lease line is expected to be formula-driven across every period. Formula presence is verified at export; live edit integrity is covered by the logic and bridge checks above.
A60: Formula Manifest | B60: Debt Schedule - Lease Closing Balance | C60: Debt Schedule | D60: 'Debt Schedule'!C23:W23 | E60: =21 -> 21 | F60: 21 | G60: =E60-F60 -> 0 | H60: 0 | I60: =IF(G60=0,"OK","FAIL") -> OK | J60: This debt/lease line is expected to be formula-driven across every period. Formula presence is verified at export; live edit integrity is covered by the logic and bridge checks above.
A61: Formula Manifest | B61: Payroll Detail - Ending FTE | C61: Payroll Schedule | D61: 'Payroll Schedule'!G27:G86 | E61: =60 -> 60 | F61: 60 | G61: =E61-F61 -> 0 | H61: 0 | I61: =IF(G61=0,"OK","FAIL") -> OK | J61: Payroll detail calculation columns must remain formulas so edits flow downstream. Formula presence is verified at export; live edit integrity is covered by the logic and bridge checks above.
A62: Formula Manifest | B62: Payroll Detail - Average FTE | C62: Payroll Schedule | D62: 'Payroll Schedule'!H27:H86 | E62: =60 -> 60 | F62: 60 | G62: =E62-F62 -> 0 | H62: 0 | I62: =IF(G62=0,"OK","FAIL") -> OK | J62: Payroll detail calculation columns must remain formulas so edits flow downstream. Formula presence is verified at export; live edit integrity is covered by the logic and bridge checks above.
A63: Formula Manifest | B63: Payroll Detail - Wage Cost | C63: Payroll Schedule | D63: 'Payroll Schedule'!K27:K86 | E63: =60 -> 60 | F63: 60 | G63: =E63-F63 -> 0 | H63: 0 | I63: =IF(G63=0,"OK","FAIL") -> OK | J63: Payroll detail calculation columns must remain formulas so edits flow downstream. Formula presence is verified at export; live edit integrity is covered by the logic and bridge checks above.
A64: Formula Manifest | B64: Payroll Detail - Taxes & Benefits | C64: Payroll Schedule | D64: 'Payroll Schedule'!L27:L86 | E64: =60 -> 60 | F64: 60 | G64: =E64-F64 -> 0 | H64: 0 | I64: =IF(G64=0,"OK","FAIL") -> OK | J64: Payroll detail calculation columns must remain formulas so edits flow downstream. Formula presence is verified at export; live edit integrity is covered by the logic and bridge checks above.
A65: Formula Manifest | B65: Payroll Detail - Total Payroll | C65: Payroll Schedule | D65: 'Payroll Schedule'!M27:M86 | E65: =60 -> 60 | F65: 60 | G65: =E65-F65 -> 0 | H65: 0 | I65: =IF(G65=0,"OK","FAIL") -> OK | J65: Payroll detail calculation columns must remain formulas so edits flow downstream. Formula presence is verified at export; live edit integrity is covered by the logic and bridge checks above.
A66: Formula Manifest | B66: Model Inputs - revenue::lob_1_product_1::Capacity | C66: Model Inputs | D66: 'Model Inputs'!C7:W7 | E66: =21 -> 21 | F66: 21 | G66: =E66-F66 -> 0 | H66: 0 | I66: =IF(G66=0,"OK","FAIL") -> OK | J66: Formula bridge rows in Model Inputs must stay linked to schedules. Formula presence is verified at export; live edit integrity is covered by the logic and bridge checks above.
A67: Formula Manifest | B67: Model Inputs - revenue::lob_1_product_1::Unit Price | C67: Model Inputs | D67: 'Model Inputs'!C8:W8 | E67: =21 -> 21 | F67: 21 | G67: =E67-F67 -> 0 | H67: 0 | I67: =IF(G67=0,"OK","FAIL") -> OK | J67: Formula bridge rows in Model Inputs must stay linked to schedules. Formula presence is verified at export; live edit integrity is covered by the logic and bridge checks above.
A68: Formula Manifest | B68: Model Inputs - revenue::lob_1_product_1::Utilization | C68: Model Inputs | D68: 'Model Inputs'!C9:W9 | E68: =21 -> 21 | F68: 21 | G68: =E68-F68 -> 0 | H68: 0 | I68: =IF(G68=0,"OK","FAIL") -> OK | J68: Formula bridge rows in Model Inputs must stay linked to schedules. Formula presence is verified at export; live edit integrity is covered by the logic and bridge checks above.
A69: Formula Manifest | B69: Model Inputs - revenue::lob_1_product_1::Revenue | C69: Model Inputs | D69: 'Model Inputs'!C10:W10 | E69: =21 -> 21 | F69: 21 | G69: =E69-F69 -> 0 | H69: 0 | I69: =IF(G69=0,"OK","FAIL") -> OK | J69: Formula bridge rows in Model Inputs must stay linked to schedules. Formula presence is verified at export; live edit integrity is covered by the logic and bridge checks above.
A70: Formula Manifest | B70: Model Inputs - is::Revenue | C70: Model Inputs | D70: 'Model Inputs'!C11:W11 | E70: =21 -> 21 | F70: 21 | G70: =E70-F70 -> 0 | H70: 0 | I70: =IF(G70=0,"OK","FAIL") -> OK | J70: Formula bridge rows in Model Inputs must stay linked to schedules. Formula presence is verified at export; live edit integrity is covered by the logic and bridge checks above.
A71: Formula Manifest | B71: Model Inputs - is::Lease | C71: Model Inputs | D71: 'Model Inputs'!C15:W15 | E71: =21 -> 21 | F71: 21 | G71: =E71-F71 -> 0 | H71: 0 | I71: =IF(G71=0,"OK","FAIL") -> OK | J71: Formula bridge rows in Model Inputs must stay linked to schedules. Formula presence is verified at export; live edit integrity is covered by the logic and bridge checks above.
A72: Formula Manifest | B72: Model Inputs - is::Payroll | C72: Model Inputs | D72: 'Model Inputs'!D16:W16 | E72: =20 -> 20 | F72: 20 | G72: =E72-F72 -> 0 | H72: 0 | I72: =IF(G72=0,"OK","FAIL") -> OK | J72: Formula bridge rows in Model Inputs must stay linked to schedules. Formula presence is verified at export; live edit integrity is covered by the logic and bridge checks above.
A73: Formula Manifest | B73: Model Inputs - is::Interest Rate | C73: Model Inputs | D73: 'Model Inputs'!C18:W18 | E73: =21 -> 21 | F73: 21 | G73: =E73-F73 -> 0 | H73: 0 | I73: =IF(G73=0,"OK","FAIL") -> OK | J73: Formula bridge rows in Model Inputs must stay linked to schedules. Formula presence is verified at export; live edit integrity is covered by the logic and bridge checks above.
A74: Formula Manifest | B74: Model Inputs - is::Interest Expense | C74: Model Inputs | D74: 'Model Inputs'!D19:W19 | E74: =20 -> 20 | F74: 20 | G74: =E74-F74 -> 0 | H74: 0 | I74: =IF(G74=0,"OK","FAIL") -> OK | J74: Formula bridge rows in Model Inputs must stay linked to schedules. Formula presence is verified at export; live edit integrity is covered by the logic and bridge checks above.
A75: Formula Manifest | B75: Model Inputs - is::Depreciation | C75: Model Inputs | D75: 'Model Inputs'!C20:W20 | E75: =21 -> 21 | F75: 21 | G75: =E75-F75 -> 0 | H75: 0 | I75: =IF(G75=0,"OK","FAIL") -> OK | J75: Formula bridge rows in Model Inputs must stay linked to schedules. Formula presence is verified at export; live edit integrity is covered by the logic and bridge checks above.
A76: Formula Manifest | B76: Model Inputs - is::Depreciation Expense | C76: Model Inputs | D76: 'Model Inputs'!C21:W21 | E76: =21 -> 21 | F76: 21 | G76: =E76-F76 -> 0 | H76: 0 | I76: =IF(G76=0,"OK","FAIL") -> OK | J76: Formula bridge rows in Model Inputs must stay linked to schedules. Formula presence is verified at export; live edit integrity is covered by the logic and bridge checks above.
A77: Formula Manifest | B77: Model Inputs - bs::Accounts Receivable Days | C77: Model Inputs | D77: 'Model Inputs'!C25:W25 | E77: =21 -> 21 | F77: 21 | G77: =E77-F77 -> 0 | H77: 0 | I77: =IF(G77=0,"OK","FAIL") -> OK | J77: Formula bridge rows in Model Inputs must stay linked to schedules. Formula presence is verified at export; live edit integrity is covered by the logic and bridge checks above.
A78: Formula Manifest | B78: Model Inputs - bs::Inventory Days | C78: Model Inputs | D78: 'Model Inputs'!C26:W26 | E78: =21 -> 21 | F78: 21 | G78: =E78-F78 -> 0 | H78: 0 | I78: =IF(G78=0,"OK","FAIL") -> OK | J78: Formula bridge rows in Model Inputs must stay linked to schedules. Formula presence is verified at export; live edit integrity is covered by the logic and bridge checks above.
A79: Formula Manifest | B79: Model Inputs - bs::Accounts Payable Days | C79: Model Inputs | D79: 'Model Inputs'!C27:W27 | E79: =21 -> 21 | F79: 21 | G79: =E79-F79 -> 0 | H79: 0 | I79: =IF(G79=0,"OK","FAIL") -> OK | J79: Formula bridge rows in Model Inputs must stay linked to schedules. Formula presence is verified at export; live edit integrity is covered by the logic and bridge checks above.
A80: Formula Manifest | B80: Model Inputs - bs::Prepaid Expenses (% of Revenue) | C80: Model Inputs | D80: 'Model Inputs'!C28:W28 | E80: =21 -> 21 | F80: 21 | G80: =E80-F80 -> 0 | H80: 0 | I80: =IF(G80=0,"OK","FAIL") -> OK | J80: Formula bridge rows in Model Inputs must stay linked to schedules. Formula presence is verified at export; live edit integrity is covered by the logic and bridge checks above.
A81: Formula Manifest | B81: Model Inputs - bs::Deferred Revenue (% of Revenue) | C81: Model Inputs | D81: 'Model Inputs'!C29:W29 | E81: =21 -> 21 | F81: 21 | G81: =E81-F81 -> 0 | H81: 0 | I81: =IF(G81=0,"OK","FAIL") -> OK | J81: Formula bridge rows in Model Inputs must stay linked to schedules. Formula presence is verified at export; live edit integrity is covered by the logic and bridge checks above.
A82: Formula Manifest | B82: Model Inputs - bs::Short Term Debt (% of LTD) | C82: Model Inputs | D82: 'Model Inputs'!C30:W30 | E82: =21 -> 21 | F82: 21 | G82: =E82-F82 -> 0 | H82: 0 | I82: =IF(G82=0,"OK","FAIL") -> OK | J82: Formula bridge rows in Model Inputs must stay linked to schedules. Formula presence is verified at export; live edit integrity is covered by the logic and bridge checks above.
A83: Formula Manifest | B83: Model Inputs - bs::Owner's Capital | C83: Model Inputs | D83: 'Model Inputs'!C31:W31 | E83: =21 -> 21 | F83: 21 | G83: =E83-F83 -> 0 | H83: 0 | I83: =IF(G83=0,"OK","FAIL") -> OK | J83: Formula bridge rows in Model Inputs must stay linked to schedules. Formula presence is verified at export; live edit integrity is covered by the logic and bridge checks above.
A84: Formula Manifest | B84: Model Inputs - bs::Other Equity | C84: Model Inputs | D84: 'Model Inputs'!C32:W32 | E84: =21 -> 21 | F84: 21 | G84: =E84-F84 -> 0 | H84: 0 | I84: =IF(G84=0,"OK","FAIL") -> OK | J84: Formula bridge rows in Model Inputs must stay linked to schedules. Formula presence is verified at export; live edit integrity is covered by the logic and bridge checks above.
A85: Formula Manifest | B85: Model Inputs - bs::Distributions | C85: Model Inputs | D85: 'Model Inputs'!C33:W33 | E85: =21 -> 21 | F85: 21 | G85: =E85-F85 -> 0 | H85: 0 | I85: =IF(G85=0,"OK","FAIL") -> OK | J85: Formula bridge rows in Model Inputs must stay linked to schedules. Formula presence is verified at export; live edit integrity is covered by the logic and bridge checks above.
A86: Formula Manifest | B86: Model Inputs - cash::Cash Opening Balance | C86: Model Inputs | D86: 'Model Inputs'!C36:W36 | E86: =21 -> 21 | F86: 21 | G86: =E86-F86 -> 0 | H86: 0 | I86: =IF(G86=0,"OK","FAIL") -> OK | J86: Formula bridge rows in Model Inputs must stay linked to schedules. Formula presence is verified at export; live edit integrity is covered by the logic and bridge checks above.
... A154: Formula Manifest | B154: FINMO - Cash Flow - Ending Cash | C154: FINMO | D154: 'FINMO'!C61:W61 | E154: =21 -> 21 | F154: 21 | G154: =E154-F154 -> 0 | H154: 0 | I154: =IF(G154=0,"OK","FAIL") -> OK | J154: FINMO statement lines must remain formula-driven. Formula presence is verified at export; live edit integrity is covered by the logic and bridge checks above.
A156: Formula Error Scans
A157: Formula Error Scan | B157: Revenue Drivers formula/error scan | C157: Revenue Drivers | D157: 'Revenue Drivers'!C7:W28 | E157: =SUMPRODUCT(--ISERROR('Revenue Drivers'!C7:W28)) -> 0 | F157: 0 | G157: =E157-F157 -> 0 | H157: 0 | I157: =IF(E157=0,"OK","FAIL") -> OK | J157: Counts Excel error values in the range.
A158: Formula Error Scan | B158: Payroll Schedule formula/error scan | C158: Payroll Schedule | D158: 'Payroll Schedule'!C15:W86 | E158: =SUMPRODUCT(--ISERROR('Payroll Schedule'!C15:W86)) -> 0 | F158: 0 | G158: =E158-F158 -> 0 | H158: 0 | I158: =IF(E158=0,"OK","FAIL") -> OK | J158: Counts Excel error values in the range.
A159: Formula Error Scan | B159: Debt Schedule formula/error scan | C159: Debt Schedule | D159: 'Debt Schedule'!C7:W26 | E159: =SUMPRODUCT(--ISERROR('Debt Schedule'!C7:W26)) -> 0 | F159: 0 | G159: =E159-F159 -> 0 | H159: 0 | I159: =IF(E159=0,"OK","FAIL") -> OK | J159: Counts Excel error values in the range.
A160: Formula Error Scan | B160: CapEx Depreciation formula/error scan | C160: CapEx Depreciation | D160: 'CapEx Depreciation'!C7:W14 | E160: =SUMPRODUCT(--ISERROR('CapEx Depreciation'!C7:W14)) -> 0 | F160: 0 | G160: =E160-F160 -> 0 | H160: 0 | I160: =IF(E160=0,"OK","FAIL") -> OK | J160: Counts Excel error values in the range.
A161: Formula Error Scan | B161: Cash Equity Schedule formula/error scan | C161: Cash Equity Schedule | D161: 'Cash Equity Schedule'!C7:W12 | E161: =SUMPRODUCT(--ISERROR('Cash Equity Schedule'!C7:W12)) -> 0 | F161: 0 | G161: =E161-F161 -> 0 | H161: 0 | I161: =IF(E161=0,"OK","FAIL") -> OK | J161: Counts Excel error values in the range.
A162: Formula Error Scan | B162: Model Inputs formula/error scan | C162: Model Inputs | D162: 'Model Inputs'!C7:W54 | E162: =SUMPRODUCT(--ISERROR('Model Inputs'!C7:W54)) -> 0 | F162: 0 | G162: =E162-F162 -> 0 | H162: 0 | I162: =IF(E162=0,"OK","FAIL") -> OK | J162: Counts Excel error values in the range.
A163: Formula Error Scan | B163: FINMO formula/error scan | C163: FINMO | D163: 'FINMO'!C8:W61 | E163: =SUMPRODUCT(--ISERROR(FINMO!C8:W61)) -> 0 | F163: 0 | G163: =E163-F163 -> 0 | H163: 0 | I163: =IF(E163=0,"OK","FAIL") -> OK | J163: Counts Excel error values in the range.
A165: Persisted Baseline Reconciliation
A166: Persisted Baseline | B166: Revenue Q20 | C166: FINMO vs Audit Source | D166: 'FINMO'!W8 | E166: =FINMO!W8 -> 476588.45 | F166: ='Audit Source'!W7 -> 476588.45 | G166: =E166-F166 -> 0 | H166: 1 | I166: =IF(ABS(G166)<=H166,"MATCH","CHANGED") -> MATCH | J166: CHANGED means assumptions were edited from the persisted run; it is informational and does not fail Model Status.
A167: Persisted Baseline | B167: Payroll Q20 | C167: FINMO vs Audit Source | D167: 'FINMO'!W14 | E167: =FINMO!W14 -> 120350.07 | F167: ='Audit Source'!W13 -> 119522 | G167: =E167-F167 -> 828.0675 | H167: 1 | I167: =IF(ABS(G167)<=H167,"MATCH","CHANGED") -> CHANGED | J167: CHANGED means assumptions were edited from the persisted run; it is informational and does not fail Model Status.
A168: Persisted Baseline | B168: Net Income Q20 | C168: FINMO vs Audit Source | D168: 'FINMO'!W20 | E168: =FINMO!W20 -> -15855494 | F168: ='Audit Source'!W19 -> -15854666 | G168: =E168-F168 -> -828.0675 | H168: 1 | I168: =IF(ABS(G168)<=H168,"MATCH","CHANGED") -> CHANGED | J168: CHANGED means assumptions were edited from the persisted run; it is informational and does not fail Model Status.
A169: Persisted Baseline | B169: Cash Q20 | C169: FINMO vs Audit Source | D169: 'FINMO'!W23 | E169: =FINMO!W23 -> 8150151.4 | F169: ='Audit Source'!W23 -> 8165514.2 | G169: =E169-F169 -> -15362.831 | H169: 1 | I169: =IF(ABS(G169)<=H169,"MATCH","CHANGED") -> CHANGED | J169: CHANGED means assumptions were edited from the persisted run; it is informational and does not fail Model Status.
A170: Persisted Baseline | B170: Total Assets Q20 | C170: FINMO vs Audit Source | D170: 'FINMO'!W31 | E170: =FINMO!W31 -> 10732188 | F170: ='Audit Source'!W29 -> 10747551 | G170: =E170-F170 -> -15362.831 | H170: 1 | I170: =IF(ABS(G170)<=H170,"MATCH","CHANGED") -> CHANGED | J170: CHANGED means assumptions were edited from the persisted run; it is informational and does not fail Model Status.
A171: Persisted Baseline | B171: Total Liabilities & Equity Q20 | C171: FINMO vs Audit Source | D171: 'FINMO'!W43 | E171: =FINMO!W43 -> 10732188 | F171: ='Audit Source'!W41 -> 10747551 | G171: =E171-F171 -> -15362.831 | H171: 1 | I171: =IF(ABS(G171)<=H171,"MATCH","CHANGED") -> CHANGED | J171: CHANGED means assumptions were edited from the persisted run; it is informational and does not fail Model Status.
A172: Persisted Baseline | B172: Ending Cash Q20 | C172: FINMO vs Audit Source | D172: 'FINMO'!W61 | E172: =FINMO!W61 -> 8150151.4 | F172: ='Audit Source'!W59 -> 8165514.2 | G172: =E172-F172 -> -15362.831 | H172: 1 | I172: =IF(ABS(G172)<=H172,"MATCH","CHANGED") -> CHANGED | J172: CHANGED means assumptions were edited from the persisted run; it is informational and does not fail Model Status.

Sheet Diagnostics
A1: Run Diagnostics
A3: Run Metadata
A4: Planning Mode | B4: turnaround
A5: Cash Strategy | B5: balanced
A6: Business Stage | B6: pre-revenue
A7: Business Name | B7: CareFirst Home Health Services
A8: Business Start Date | B8: 06/19/2026
A9: NAICS-6 | B9: 621610
A10: Draft ID | B10: 0caeb5ad5d0843a6b4f0e52ba0cf7d5f
A11: Planning Run ID | B11: c029942f239d4bb784a8889a94a4049e
A13: Acceptance Gate
A14: Score | B14: 13/16
A15: Verdict | B15: FAILED
A17: GPT Exhaustion Handler
A18: Fired | B18: Yes
A19: Status | B19: landed_best_effort_no_all_pass
A20: Scope | B20: pnl_path
A21: Tool calls used | B21: 4
A22: Budget extension triggered | B22: False
A24: Realism Check Detail
A25: Metric Key | B25: Status
A26: advertising_percent_of_revenue | B26: ✓
A27: ap_days_dpo | B27: ✓
A28: ar_days_dso | B28: ✓
A29: capex_percent_of_revenue | B29: ✓
A30: cogs_percent_of_revenue | B30: ✓
A31: current_assets_minus_cash | B31: ✓
A32: current_liabilities_to_revenue | B32: ✓
A33: current_ratio | B33: ✓
A34: debt_to_assets | B34: ✓
A35: debt_to_equity | B35: ✓
A36: deferred_revenue_percent_of_revenue | B36: ✓
... A58: total_assets_to_revenue | B58: ✓
